Workbook
Name list: #REF!
Name list: #REF!
Name spec_values: [1]BOQ_Шаблон!$A$6:$A$275
Name МШП_СПИСОК: [2]НОРМИ_МК!$F$5:$R$5

Sheet Бюджет_Проекта
A1: Статья движения денежных средств | B1: ф1 | C1: ф2 | D1: Итого, грн | E1: Комментарии к бюджету объекта | H1: Матеріали | I1: =D101+D98 -> 705624.01
A2: ПОСТУПЛЕНИЯ | B2: =B3+B10 -> 1232000 | C2: =C3+C10 -> 0 | D2: =B2+C2 -> 1232000 | H2: Загальна сс, грн | I2: =D14-I1 -> 320996
A3: Операционная деятельность | B3: =SUM(B4:B9) -> 1232000 | C3: =SUM(C4:C9) -> 0 | D3: =B3+C3 -> 1232000 | H3: Налоговая нагрузка, 3%: | I3: =I4*3% -> 36960
A4: Поступление от Заказчика | B4: 1232000 | D4: =B4+C4 -> 1232000 | H4: КП: | I4: =B4 -> 1232000
A5: Прочие поступления | D5: =B5+C5 -> 0 | H5: Маржа, грн: за шт | I5: =I4-I3-I2-I1 -> 168419.99
A6: Возврат залоговой суммы | D6: =B6+C6 -> 0 | H6: Маржа, %: | I6: =I5/I4 -> 0.13670454
A7: Поступление от возврата денежных средств | D7: =B7+C7 -> 0 | H7: Количество в заказе, шт | I7: 1
A8: Поступление цех | D8: =B8+C8 -> 0 | H8: Итого маржа по заказу, грн | I8: =I7*I5 -> 168419.99 | K8: 157130.11
A9: Поступление за технику | D9: =B9+C9 -> 0
A10: Финансовая деятельность | B10: =SUM(B11:B13) -> 0 | C10: =SUM(C11:C13) -> 0 | D10: =B10+C10 -> 0
A11: Получение финансовой помощи | D11: =B11+C11 -> 0
A12: Поступление от Фин агента | C12: =B133 -> 0 | D12: =B12+C12 -> 0
A13: Кредитная линия | D13: =B13+C13 -> 0
A14: СПИСАНИЕ | B14: =B15+B128+B141 -> 832000.01 | C14: =C15+C128+C141 -> 194620 | D14: =B14+C14 -> 1026620
A15: Операционная деятельность | B15: =B16+B70+B93+B66 -> 802807.01 | C15: =C16+C70+C93+C66 -> 194620 | D15: =B15+C15 -> 997427.01
A16: Административные затраты | B16: =B17+B24+B29+B33+B41+B45+B49+B52+B58+B61+B21 -> 15000 | C16: =C17+C24+C29+C33+C41+C45+C49+C52+C58+C61+C21 -> 0 | D16: =B16+C16 -> 15000
A17: Аренда офиса | B17: =SUM(B18:B20) -> 0 | C17: =SUM(C18:C20) -> 0 | D17: =B17+C17 -> 0
A18: Аренда офиса | B18: =SUMIF('Проект СС'!$B:$B,$A18,'Проект СС'!$O:$O) -> 0 | D18: =B18+C18 -> 0
A19: Коммунальные платежи (офис) | B19: =SUMIF('Проект СС'!$B:$B,$A19,'Проект СС'!$O:$O) -> 0 | D19: =B19+C19 -> 0
A20: Охрана офиса и пожарная сигнализация | B20: =SUMIF('Проект СС'!$B:$B,$A20,'Проект СС'!$O:$O) -> 0 | D20: =B20+C20 -> 0
A21: Аренда квартиры | B21: =SUM(B22:B23) -> 0 | C21: =SUM(C22:C23) -> 0 | D21: =B21+C21 -> 0
A22: Аренда квартиры | B22: =SUMIF('Проект СС'!$B:$B,$A22,'Проект СС'!$O:$O) -> 0 | D22: =B22+C22 -> 0
A23: Коммунальные платежи | B23: =SUMIF('Проект СС'!$B:$B,$A23,'Проект СС'!$O:$O) -> 0 | D23: =B23+C23 -> 0
A24: Затраты на персонал | B24: =SUM(B25:B28) -> 0 | C24: =SUM(C25:C28) -> 0 | D24: =B24+C24 -> 0
A25: Затраты на обучение управленческого персонала | B25: =SUMIF('Проект СС'!$B:$B,$A25,'Проект СС'!$O:$O) -> 0 | D25: =B25+C25 -> 0
A26: Затраты по корпоративной культуре | B26: =SUMIF('Проект СС'!$B:$B,$A26,'Проект СС'!$O:$O) -> 0 | D26: =B26+C26 -> 0
A27: Материальная помощь | B27: =SUMIF('Проект СС'!$B:$B,$A27,'Проект СС'!$O:$O) -> 0 | D27: =B27+C27 -> 0
A28: Периодика | B28: =SUMIF('Проект СС'!$B:$B,$A28,'Проект СС'!$O:$O) -> 0 | D28: =B28+C28 -> 0
A29: Затраты на командировку | B29: =SUM(B30:B32) -> 5000 | C29: =SUM(C30:C32) -> 0 | D29: =B29+C29 -> 5000
A30: Проезд | B30: =SUMIF('Проект СС'!$B:$B,$A30,'Проект СС'!$O:$O) -> 0
A31: Проживание | B31: =SUMIF('Проект СС'!$B:$B,$A31,'Проект СС'!$O:$O) -> 5000 | D31: =B31+C31 -> 5000
A32: Суточные | B32: =SUMIF('Проект СС'!$B:$B,$A32,'Проект СС'!$O:$O) -> 0 | D32: =B32+C32 -> 0
A33: ЗП управленческого персонала с начислениями | B33: =SUM(B34:B40) -> 0 | C33: =SUM(C34:C40) -> 0 | D33: =B33+C33 -> 0
A34: Зарплата PM | C34: =SUMIF('Проект СС'!$B:$B,$A34,'Проект СС'!$O:$O) -> 0 | D34: =B34+C34 -> 0 | E34: 2 мес + 5 мес
A35: Удержание с зарплаты РМ | B35: =SUMIF('Проект СС'!$B:$B,$A35,'Проект СС'!$O:$O) -> 0 | D35: =B35+C35 -> 0
A36: Начисления на зарплату PM | B36: =SUMIF('Проект СС'!$B:$B,$A36,'Проект СС'!$O:$O) -> 0 | D36: =B36+C36 -> 0
A37: Зарплата управленческого персонала | B37: =SUMIF('Проект СС'!$B:$B,$A37,'Проект СС'!$O:$O) -> 0 | D37: =B37+C37 -> 0
A38: Удержание с админ зарплату | B38: =SUMIF('Проект СС'!$B:$B,$A38,'Проект СС'!$O:$O) -> 0 | D38: =B38+C38 -> 0
A39: Начисления на админ зарплату | B39: =SUMIF('Проект СС'!$B:$B,$A39,'Проект СС'!$O:$O) -> 0 | D39: =B39+C39 -> 0
A40: Премия админ персоналу | B40: =SUMIF('Проект СС'!$B:$B,$A40,'Проект СС'!$O:$O) -> 0 | D40: =B40+C40 -> 0
A41: Налоги и сборы | B41: =SUM(B42:B44) -> 0 | C41: =SUM(C42:C44) -> 0 | D41: =B41+C41 -> 0
A42: Налог на прибыль | B42: =SUMIF('Проект СС'!$B:$B,$A42,'Проект СС'!$O:$O) -> 0 | D42: =B42+C42 -> 0
A43: НДС | B43: =SUMIF('Проект СС'!$B:$B,$A43,'Проект СС'!$O:$O) -> 0 | D43: =B43+C43 -> 0
A44: Прочие налоги | B44: =SUMIF('Проект СС'!$B:$B,$A44,'Проект СС'!$O:$O) -> 0 | D44: =B44+C44 -> 0 | E44: 0.03
A45: Телекоммуникационные услуги | B45: =SUM(B46:B48) -> 0 | C45: =SUM(C46:C48) -> 0 | D45: =B45+C45 -> 0
A46: Интернет | B46: =SUMIF('Проект СС'!$B:$B,$A46,'Проект СС'!$O:$O) -> 0 | D46: =B46+C46 -> 0
A47: Мобильная связь | B47: =SUMIF('Проект СС'!$B:$B,$A47,'Проект СС'!$O:$O) -> 0 | D47: =B47+C47 -> 0
A48: Стационарный телефон | B48: =SUMIF('Проект СС'!$B:$B,$A48,'Проект СС'!$O:$O) -> 0 | D48: =B48+C48 -> 0
A49: Транспортные затраты | B49: =B50+B51 -> 10000 | C49: =C50+C51 -> 0 | D49: =B49+C49 -> 10000
A50: ГСМ (топливо) | B50: =SUMIF('Проект СС'!$B:$B,$A50,'Проект СС'!$O:$O) -> 10000 | D50: =B50+C50 -> 10000
A51: Такси | B51: =SUMIF('Проект СС'!$B:$B,$A51,'Проект СС'!$O:$O) -> 0 | D51: =B51+C51 -> 0
A52: Услуги | B52: =SUM(B53:B57) -> 0 | C52: =SUM(C53:C57) -> 0 | D52: =B52+C52 -> 0
A53: Аутсорсинг | B53: =SUMIF('Проект СС'!$B:$B,$A53,'Проект СС'!$O:$O) -> 0 | D53: =B53+C53 -> 0
A54: Представительские затраты | B54: =SUMIF('Проект СС'!$B:$B,$A54,'Проект СС'!$O:$O) -> 0 | D54: =B54+C54 -> 0
A55: Лицензия Медок | B55: =SUMIF('Проект СС'!$B:$B,$A55,'Проект СС'!$O:$O) -> 0 | D55: =B55+C55 -> 0
A56: Уборка помещений | B56: =SUMIF('Проект СС'!$B:$B,$A56,'Проект СС'!$O:$O) -> 0 | D56: =B56+C56 -> 0
A57: Прочие затраты | B57: =SUMIF('Проект СС'!$B:$B,$A57,'Проект СС'!$O:$O) -> 0 | D57: =B57+C57 -> 0
A58: Услуги банков | B58: =SUM(B59:B60) -> 0 | C58: =SUM(C59:C60) -> 0 | D58: =B58+C58 -> 0
A59: Комиссия банков и др.платежи по РКО | B59: =SUMIF('Проект СС'!$B:$B,$A59,'Проект СС'!$O:$O) -> 0 | D59: =B59+C59 -> 0
A60: Прочие услуги банка | B60: =SUMIF('Проект СС'!$B:$B,$A60,'Проект СС'!$O:$O) -> 0 | D60: =B60+C60 -> 0
A61: Юридические услуги | B61: =SUM(B62:B65) -> 0 | C61: =SUM(C62:C65) -> 0 | D61: =B61+C61 -> 0
A62: Нотариальные действия | B62: =SUMIF('Проект СС'!$B:$B,$A62,'Проект СС'!$O:$O) -> 0 | D62: =B62+C62 -> 0
A63: Тендер | B63: =SUMIF('Проект СС'!$B:$B,$A63,'Проект СС'!$O:$O) -> 0 | D63: =B63+C63 -> 0
A64: Штраф | B64: =SUMIF('Проект СС'!$B:$B,$A64,'Проект СС'!$O:$O) -> 0 | D64: =B64+C64 -> 0
A65: Прочие юр.услуги | B65: =SUMIF('Проект СС'!$B:$B,$A65,'Проект СС'!$O:$O) -> 0 | D65: =B65+C65 -> 0
A66: Маркетинговые затраты | B66: =B67 -> 0 | C66: =C67 -> 0 | D66: =B66+C66 -> 0
A67: Маркетинговые затраты | B67: =SUM(B68:B69) -> 0 | C67: =SUM(C68:C69) -> 0 | D67: =B67+C67 -> 0
A68: Реклама | B68: =SUMIF('Проект СС'!$B:$B,$A68,'Проект СС'!$O:$O) -> 0 | D68: =B68+C68 -> 0
A69: Прочие маркетинговые затраты | B69: =SUMIF('Проект СС'!$B:$B,$A69,'Проект СС'!$O:$O) -> 0 | D69: =B69+C69 -> 0
A70: Общепроизводственные затраты | B70: =B71+B76+B83+B86+B90 -> 0 | C70: =C71+C76+C83+C86+C90 -> 2800 | D70: =B70+C70 -> 2800
A71: ИТ расходы | B71: =SUM(B72:B75) -> 0 | C71: =SUM(C72:C75) -> 2800 | D71: =B71+C71 -> 2800
A72: Заправка картриджа | B72: =SUMIF('Проект СС'!$B:$B,$A72,'Проект СС'!$O:$O) -> 0 | C72: 2800 | D72: =B72+C72 -> 2800
A73: Обслуживание офисной техники | B73: =SUMIF('Проект СС'!$B:$B,$A73,'Проект СС'!$O:$O) -> 0 | D73: =B73+C73 -> 0
A74: ПО | B74: =SUMIF('Проект СС'!$B:$B,$A74,'Проект СС'!$O:$O) -> 0 | D74: =B74+C74 -> 0
A75: Расходный материал | B75: =SUMIF('Проект СС'!$B:$B,$A75,'Проект СС'!$O:$O) -> 0 | D75: =B75+C75 -> 0
A76: Общепроизводственные затраты | B76: =SUM(B77:B82) -> 0 | C76: =SUM(C77:C82) -> 0 | D76: =B76+C76 -> 0
A77: Благоустройство офиса | B77: =SUMIF('Проект СС'!$B:$B,$A77,'Проект СС'!$O:$O) -> 0 | D77: =B77+C77 -> 0
A78: Канцтовары | B78: =SUMIF('Проект СС'!$B:$B,$A78,'Проект СС'!$O:$O) -> 0 | D78: =B78+C78 -> 0
A79: Курьерские и почтовые | B79: =SUMIF('Проект СС'!$B:$B,$A79,'Проект СС'!$O:$O) -> 0 | D79: =B79+C79 -> 0
A80: Питьевая вода | B80: =SUMIF('Проект СС'!$B:$B,$A80,'Проект СС'!$O:$O) -> 0 | D80: =B80+C80 -> 0
A81: Спецодежда | B81: =SUMIF('Проект СС'!$B:$B,$A81,'Проект СС'!$O:$O) -> 0 | D81: =B81+C81 -> 0
A82: Юридический адрес | B82: =SUMIF('Проект СС'!$B:$B,$A82,'Проект СС'!$O:$O) -> 0 | D82: =B82+C82 -> 0
A83: Хозтовары и материалы | B83: =SUM(B84:B85) -> 0 | C83: =SUM(C84:C85) -> 0 | D83: =B83+C83 -> 0
A84: Бытовая химия | B84: =SUMIF('Проект СС'!$B:$B,$A84,'Проект СС'!$O:$O) -> 0 | D84: =B84+C84 -> 0
A85: Другие хозтовары | B85: =SUMIF('Проект СС'!$B:$B,$A85,'Проект СС'!$O:$O) -> 0 | D85: =B85+C85 -> 0 | E85: чай, кофе
A86: Охрана труда | B86: =SUM(B87:B89) -> 0 | C86: =SUM(C87:C89) -> 0 | D86: =SUM(D87:D89) -> 0
A87: Медосмотр | B87: =SUMIF('Проект СС'!$B:$B,$A87,'Проект СС'!$O:$O) -> 0 | D87: =B87+C87 -> 0
A88: Обучение производственного персонала | B88: =SUMIF('Проект СС'!$B:$B,$A88,'Проект СС'!$O:$O) -> 0 | D88: =B88+C88 -> 0
A89: Прочие затраты ОТ | B89: =SUMIF('Проект СС'!$B:$B,$A89,'Проект СС'!$O:$O) -> 0 | D89: =B89+C89 -> 0
A90: Разрешительная документация | B90: =SUM(B91:B92) -> 0 | C90: =SUM(C91:C92) -> 0 | D90: =B90+C90 -> 0
A91: Разрешительная документация | B91: =SUMIF('Проект СС'!$B:$B,$A91,'Проект СС'!$O:$O) -> 0 | D91: =B91+C91 -> 0
A92: Страхование | B92: =SUMIF('Проект СС'!$B:$B,$A92,'Проект СС'!$O:$O) -> 0 | D92: =B92+C92 -> 0
A93: Производственные затраты | B93: =B94+B105+B113+B117 -> 787807.01 | C93: =C94+C105+C113+C117 -> 191820 | D93: =B93+C93 -> 979627.01
A94: Производственные затраты и услуги | B94: =SUM(B95:B104) -> 762207.01 | C94: =SUM(C95:C104) -> 0 | D94: =B94+C94 -> 762207.01
A95: Вывоз мусора | B95: =SUMIF('Проект СС'!$B:$B,$A95,'Проект СС'!$O:$O) -> 0 | D95: =B95+C95 -> 0
A96: Залоговая сумма | B96: =SUMIF('Проект СС'!$B:$B,$A96,'Проект СС'!$O:$O) -> 0 | D96: =B96+C96 -> 0
A97: Запчасти для спецтехники | B97: =SUMIF('Проект СС'!$B:$B,$A97,'Проект СС'!$O:$O) -> 0 | D97: =B97+C97 -> 0
A98: МШП | B98: =SUMIF('Проект СС'!$B:$B,$A98,'Проект СС'!$O:$O) -> 0 | D98: =B98+C98 -> 0
A99: Прочие производственные затраты | B99: =SUMIF('Проект СС'!$B:$B,$A99,'Проект СС'!$O:$O) -> 2500 | D99: =B99+C99 -> 2500
A100: Ремонты | B100: =SUMIF('Проект СС'!$B:$B,$A100,'Проект СС'!$O:$O) -> 0 | D100: =B100+C100 -> 0
...

Sheet Анализ
A1: IRC 15 m2 | D1: Курс | E1: 43.5 | F1: Площадь | G1: 15
A3: Сумма по полю Всього, грн. з ПДВ | B3: Названия столбцов
A4: Названия строк | B4: Матеріал | C4: Робота | D4: Общий итог | E4: Материал $ | F4: Общий итог $ | G4: На 1 м2 $
A5: Дополнительная Комплектация | B5: 155087 | C5: 0 | D5: 155087 | E5: =B5/$E$1 -> 3565.2184 | F5: =D5/$E$1 -> 3565.2184 | G5: =F5/$G$1 -> 237.68123
A6: Каркас | B6: 151946.44 | C6: 0 | D6: 151946.44 | E6: =B6/$E$1 -> 3493.0215 | F6: =D6/$E$1 -> 3493.0215 | G6: =F6/$G$1 -> 232.8681
A7: Монтаж будинку | B7: 0 | C7: 0 | D7: 0 | E7: =B7/$E$1 -> 0 | F7: =D7/$E$1 -> 0 | G7: =F7/$G$1 -> 0
A8: Окна/двери | B8: 102799 | C8: 0 | D8: 102799 | E8: =B8/$E$1 -> 2363.1954 | F8: =D8/$E$1 -> 2363.1954 | G8: =F8/$G$1 -> 157.54636
A9: Отделка | B9: 163888.82 | C9: 0 | D9: 163888.82 | E9: =B9/$E$1 -> 3767.5591 | F9: =D9/$E$1 -> 3767.5591 | G9: =F9/$G$1 -> 251.17061
A10: Сантехника | B10: 39783.4 | C10: 0 | D10: 39783.4 | E10: =B10/$E$1 -> 914.56092 | F10: =D10/$E$1 -> 914.56092 | G10: =F10/$G$1 -> 60.970728
A11: Фасад | B11: 53172 | C11: 0 | D11: 53172 | E11: =B11/$E$1 -> 1222.3448 | F11: =D11/$E$1 -> 1222.3448 | G11: =F11/$G$1 -> 81.489655
A12: Электрика/Подогрев | B12: 38947.35 | C12: 0 | D12: 38947.35 | E12: =B12/$E$1 -> 895.34138 | F12: =D12/$E$1 -> 895.34138 | G12: =F12/$G$1 -> 59.689425
A13: Общий итог | B13: 705624.01 | C13: 0 | D13: 705624.01 | E13: =SUM(E5:E12) -> 16221.241 | F13: =SUM(F5:F12) -> 16221.241

Sheet Проект СС
A1: № | B1: Стаття в ДДС | C1: Робота/матеріал/додаткові | D1: Виробництво/Будівництво | E1: Тип робіт | F1: № з/п | G1: Найменування робіт/витрат/матеріалів | H1: Найменування робіт/витрат/матеріалів узагальнена | I1: Од. вим. | J1: Кіль- кість | K1: Вартість робіт за од.виміру, грн. з ПДВ | L1: Вартість матеріалів за од.виміру, грн. з ПДВ | M1: Вартість робіт за повний обсяг, грн. з ПДВ | N1: Вартість матеріалів за повний обсяг, грн. з ПДВ | O1: Всього, грн. з ПДВ
A2: І | F2: І | G2: Каркас | J2: =L3+L12 -> 0
A3: 1.1 | F3: 1.1 | G3: РОБОТА | L3: =SUM(L5:L11) -> 0
A4: 1.1.1 | B4: Зарплата производственного персонала | C4: Робота | D4: Виробництво/Будівництво | E4: Каркас | F4: 1.1.1 | G4: Приймання матеріалу | I4: чол/год | K4: 200 | M4: =J4*K4 -> 0 | N4: =J4*L4 -> 0 | O4: =N4+M4 -> 0
A5: 1.1.2 | B5: Зарплата производственного персонала | C5: Робота | D5: Виробництво/Будівництво | E5: Каркас | F5: 1.1.2 | G5: Обробка матеріалу (дерево) | I5: чол/год | J5: =96/7 -> 13.714286 | K5: 200 | M5: =J5*K5 -> 2742.8571 | N5: =J5*L5 -> 0 | O5: =N5+M5 -> 2742.8571
A6: 1.1.3 | B6: Зарплата производственного персонала | C6: Робота | D6: Виробництво/Будівництво | E6: Каркас | F6: 1.1.3 | G6: Нарізання деталей зігдно креслень | I6: чол/год | J6: =96/7 -> 13.714286 | K6: 200 | M6: =J6*K6 -> 2742.8571 | N6: =J6*L6 -> 0 | O6: =N6+M6 -> 2742.8571
A7: 1.1.4 | B7: Зарплата производственного персонала | C7: Робота | D7: Виробництво/Будівництво | E7: Каркас | F7: 1.1.4 | G7: Збирання деталей | I7: чол/год | J7: =96/7 -> 13.714286 | K7: 200 | M7: =J7*K7 -> 2742.8571 | N7: =J7*L7 -> 0 | O7: =N7+M7 -> 2742.8571
A8: 1.1.5 | B8: Зарплата производственного персонала | C8: Робота | D8: Виробництво/Будівництво | E8: Каркас | F8: 1.1.5 | G8: зварювання (дерево зєдання) | I8: чол/год | J8: =96/7 -> 13.714286 | K8: 200 | M8: =J8*K8 -> 2742.8571 | N8: =J8*L8 -> 0 | O8: =N8+M8 -> 2742.8571
A9: 1.1.6 | B9: Зарплата производственного персонала | C9: Робота | D9: Виробництво/Будівництво | E9: Каркас | F9: 1.1.6 | G9: Влаштування підшиви модуля | I9: чол/год | J9: =96/7 -> 13.714286 | K9: 200 | M9: =J9*K9 -> 2742.8571 | N9: =J9*L9 -> 0 | O9: =N9+M9 -> 2742.8571
A10: 1.1.7 | B10: Зарплата производственного персонала | C10: Робота | D10: Виробництво/Будівництво | E10: Каркас | F10: 1.1.7 | G10: Грунтування металокаркасу | I10: чол/год | J10: =96/7 -> 13.714286 | K10: 200 | M10: =J10*K10 -> 2742.8571 | N10: =J10*L10 -> 0 | O10: =N10+M10 -> 2742.8571
A11: 1.1.8 | B11: Зарплата производственного персонала | C11: Робота | D11: Виробництво/Будівництво | E11: Каркас | F11: 1.1.8 | G11: Фарубування металокаркасу | I11: чол/год | J11: =96/7 -> 13.714286 | K11: 200 | M11: =J11*K11 -> 2742.8571 | N11: =J11*L11 -> 0 | O11: =N11+M11 -> 2742.8571
A12: 1.2 | F12: 1.2 | G12: МАТЕРІАЛИ
A13: 1.2.1 | B13: Строительные материалы | C13: Матеріал | D13: Виробництво/Будівництво | E13: Каркас | F13: 1.2.1 | G13: Труба металева Ст3 100*100*3 | H13: Профільна труба | I13: м.п | J13: 50.2 | L13: 473 | M13: =J13*K13 -> 0 | N13: =J13*L13 -> 23744.6 | O13: =M13+N13 -> 23744.6
A14: 1.2.2 | B14: Строительные материалы | C14: Матеріал | D14: Виробництво/Будівництво | E14: Каркас | F14: 1.2.2 | G14: Труба металева Ст3 50*50*2 | H14: Профільна труба | I14: м.п. | J14: 175.2 | L14: 157 | M14: =J14*K14 -> 0 | N14: =J14*L14 -> 27506.4 | O14: =M14+N14 -> 27506.4
A15: 1.2.3 | B15: Строительные материалы | C15: Матеріал | D15: Виробництво/Будівництво | E15: Каркас | F15: 1.2.3 | G15: Труба металева Ст3 дв 40 *3,5 | H15: Профільна труба | I15: м.п | J15: 1.2 | L15: 151 | M15: =J15*K15 -> 0 | N15: =J15*L15 -> 181.2 | O15: =M15+N15 -> 181.2
A16: 1.2.4 | B16: Строительные материалы | C16: Матеріал | D16: Виробництво/Будівництво | E16: Каркас | F16: 1.2.4 | G16: Труба металева Ст3 дв 89 *3,5 | H16: Профільна труба | I16: м.п. | J16: 1 | L16: 339 | M16: =J16*K16 -> 0 | N16: =J16*L16 -> 339 | O16: =M16+N16 -> 339
A17: 1.2.5 | B17: Строительные материалы | C17: Матеріал | D17: Виробництво/Будівництво | E17: Каркас | F17: 1.2.5 | G17: Лист 4мм | H17: Лист ГК | I17: м.кв. | J17: 0.68 | L17: 1207 | M17: =J17*K17 -> 0 | N17: =J17*L17 -> 820.76 | O17: =M17+N17 -> 820.76
A18: 1.2.6 | B18: Строительные материалы | C18: Матеріал | D18: Виробництво/Будівництво | E18: Каркас | F18: 1.2.6 | G18: Лист 8мм | H18: Лист ГК | I18: м.кв. | J18: 1.215 | L18: 2487 | M18: =J18*K18 -> 0 | N18: =J18*L18 -> 3021.705 | O18: =M18+N18 -> 3021.705
A19: 1.2.7 | B19: Строительные материалы | C19: Матеріал | D19: Виробництво/Будівництво | E19: Каркас | F19: 1.2.7 | G19: Лист 14мм | H19: Лист ГК | I19: м.кв. | J19: 0.12 | L19: 4976 | M19: =J19*K19 -> 0 | N19: =J19*L19 -> 597.12 | O19: =M19+N19 -> 597.12
A20: 1.2.8 | B20: Строительные материалы | C20: Матеріал | D20: Виробництво/Будівництво | E20: Каркас | F20: 1.2.8 | G20: Гайка М48 | H20: Гайка | I20: шт | J20: 6 | L20: 1740 | M20: =J20*K20 -> 0 | N20: =J20*L20 -> 10440 | O20: =M20+N20 -> 10440
A21: 1.2.9 | B21: Строительные материалы | C21: Матеріал | D21: Виробництво/Будівництво | E21: Каркас | F21: 1.2.9 | G21: Шпилька М48 довжина 1000 мм | H21: Шпилька | I21: шт | J21: 3 | L21: 3600 | M21: =J21*K21 -> 0 | N21: =J21*L21 -> 10800 | O21: =M21+N21 -> 10800
A22: 1.2.10 | B22: Строительные материалы | C22: Матеріал | D22: Виробництво/Будівництво | E22: Каркас | F22: 1.2.10 | G22: Гайка М24 | H22: Гайка | I22: шт | J22: 14 | L22: 154 | M22: =J22*K22 -> 0 | N22: =J22*L22 -> 2156 | O22: =M22+N22 -> 2156
A23: 1.2.11 | B23: Строительные материалы | C23: Матеріал | D23: Виробництво/Будівництво | E23: Каркас | F23: 1.2.11 | G23: Болт М24х200 | H23: Болт | I23: шт | J23: 4 | L23: 168 | M23: =J23*K23 -> 0 | N23: =J23*L23 -> 672 | O23: =M23+N23 -> 672
A24: 1.2.12 | B24: Строительные материалы | C24: Матеріал | D24: Виробництво/Будівництво | E24: Каркас | F24: 1.2.12 | G24: Труба 40*40*3 | H24: Профільна труба | I24: м.п. | J24: 72 | L24: 165 | M24: =J24*K24 -> 0 | N24: =J24*L24 -> 11880 | O24: =M24+N24 -> 11880
... A51: 1.2.39 | B51: Строительные материалы | C51: Матеріал | D51: Виробництво/Будівництво | E51: Каркас | F51: 1.2.39 | G51: Гвинт з прес-шайбою 4,2*19 | H51: Гвинт | I51: шт | J51: 227 | L51: 0.93 | M51: =J51*K51 -> 0 | N51: =J51*L51 -> 211.11 | O51: =M51+N51 -> 211.11
A52: 1.2.40 | B52: Строительные материалы | C52: Матеріал | D52: Виробництво/Будівництво | E52: Каркас | F52: 1.2.40 | G52: Гвинт з прес-шайбою 4,2*16 | H52: Гвинт | I52: шт | J52: 60 | L52: 0.32 | M52: =J52*K52 -> 0 | N52: =J52*L52 -> 19.2 | O52: =M52+N52 -> 19.2 | P52: =SUM(N13:N52) -> 151946.44 | Q52: +
A53: ІІ | F53: ІІ | G53: Отделка | M53: =J53*K53 -> 0 | N53: =J53*L53 -> 0 | O53: =N53+M53 -> 0
A54: 2.1 | F54: 2.1 | G54: РОБОТА | M54: =J54*K54 -> 0 | N54: =J54*L54 -> 0 | O54: =N54+M54 -> 0
A55: 2.1.1 | B55: Зарплата производственного персонала | C55: Робота | D55: Виробництво/Будівництво | E55: Отделка | F55: 2.1.1 | G55: Утеплення та гідроізоляція підлоги | I55: чол/год | J55: =3*8 -> 24 | K55: 200 | M55: =J55*K55 -> 4800 | N55: =J55*L55 -> 0 | O55: =N55+M55 -> 4800
A56: 2.1.2 | B56: Зарплата производственного персонала | C56: Робота | D56: Виробництво/Будівництво | E56: Отделка | F56: 2.1.2 | G56: Монтаж брусу по каркасу | I56: чол/год | J56: =3*8 -> 24 | K56: 200 | M56: =J56*K56 -> 4800 | N56: =J56*L56 -> 0 | O56: =N56+M56 -> 4800
A57: 2.1.3 | B57: Зарплата производственного персонала | C57: Робота | D57: Виробництво/Будівництво | E57: Отделка | F57: 2.1.3 | G57: Пароізоляційна мембрана; | I57: чол/год | J57: =3*8*1 -> 24 | K57: 200 | M57: =J57*K57 -> 4800 | N57: =J57*L57 -> 0 | O57: =N57+M57 -> 4800
A58: 2.1.4 | B58: Зарплата производственного персонала | C58: Робота | D58: Виробництво/Будівництво | E58: Отделка | F58: 2.1.4 | G58: Укладання Настил підлоги | I58: чол/год | J58: =3*8*1 -> 24 | K58: 200 | M58: =J58*K58 -> 4800 | N58: =J58*L58 -> 0 | O58: =N58+M58 -> 4800
A59: 2.1.5 | B59: Зарплата производственного персонала | C59: Робота | D59: Виробництво/Будівництво | E59: Отделка | F59: 2.1.5 | G59: Гідроізоляційна та пароізоляція стін та стелі | I59: чол/год | J59: =3*8*1 -> 24 | K59: 200 | M59: =J59*K59 -> 4800 | N59: =J59*L59 -> 0 | O59: =N59+M59 -> 4800
A60: 2.1.6 | B60: Зарплата производственного персонала | C60: Робота | D60: Виробництво/Будівництво | E60: Отделка | F60: 2.1.6 | G60: Утеплення стеля та стіни | I60: чол/год | J60: =3*8*1 -> 24 | K60: 200 | M60: =J60*K60 -> 4800 | N60: =J60*L60 -> 0 | O60: =N60+M60 -> 4800
A61: 2.1.7 | B61: Зарплата производственного персонала | C61: Робота | D61: Виробництво/Будівництво | E61: Отделка | F61: 2.1.7 | G61: Монтаж фінішного оздоблення | I61: чол/год | J61: =3*8*2+12 -> 60 | K61: 200 | M61: =J61*K61 -> 12000 | N61: =J61*L61 -> 0 | O61: =N61+M61 -> 12000
A62: 2.2 | E62: Отделка | F62: 2.2 | G62: МАТЕРІАЛИ | M62: =J62*K62 -> 0 | N62: =J62*L62 -> 0 | O62: =N62+M62 -> 0
A63: 2.2.1 | B63: Строительные материалы | C63: Матеріал | D63: Виробництво/Будівництво | E63: Отделка | F63: 2.2.1 | G63: Вітробарєр | H63: Вітробарєр | I63: м2 | J63: 42 | L63: 29 | M63: =J63*K63 -> 0 | N63: =J63*L63 -> 1218 | O63: =M63+N63 -> 1218
A64: 2.2.2 | B64: Строительные материалы | C64: Матеріал | D64: Виробництво/Будівництво | E64: Отделка | F64: 2.2.2 | G64: Паро-гідро бар'єр | H64: Паробар'єр | I64: м2 | J64: 120 | L64: 13 | M64: =J64*K64 -> 0 | N64: =J64*L64 -> 1560 | O64: =M64+N64 -> 1560
A65: 2.2.3 | B65: Строительные материалы | C65: Матеріал | D65: Виробництво/Будівництво | E65: Отделка | F65: 2.2.3 | G65: Пінопласт товщина 50 мм | H65: Пінопласт | I65: м2 | J65: 44 | L65: 88 | M65: =J65*K65 -> 0 | N65: =J65*L65 -> 3872 | O65: =M65+N65 -> 3872
A66: 2.2.4 | B66: Строительные материалы | C66: Матеріал | D66: Виробництво/Будівництво | E66: Отделка | F66: 2.2.4 | G66: Мінеральна вата (100 мм) | H66: Мінеральна вата | I66: м2 | J66: 55 | L66: 176 | M66: =J66*K66 -> 0 | N66: =J66*L66 -> 9680 | O66: =M66+N66 -> 9680
A67: 2.2.5 | B67: Строительные материалы | C67: Матеріал | D67: Виробництво/Будівництво | E67: Отделка | F67: 2.2.5 | G67: Мінеральна вата (50 мм) | H67: Мінеральна вата | I67: м2 | J67: 171 | L67: 77 | M67: =J67*K67 -> 0 | N67: =J67*L67 -> 13167 | O67: =M67+N67 -> 13167
A68: 2.2.6 | B68: Строительные материалы | C68: Матеріал | D68: Виробництво/Будівництво | E68: Отделка | F68: 2.2.6 | G68: ЦСП панель 20 мм | H68: Плита ЦСП | I68: шт | J68: 5 | L68: 7700 | M68: =J68*K68 -> 0 | N68: =J68*L68 -> 38500 | O68: =M68+N68 -> 38500
A69: 2.2.7 | B69: Строительные материалы | C69: Матеріал | D69: Виробництво/Будівництво | E69: Отделка | F69: 2.2.7 | G69: Лінолеум комерційний на підлогу | H69: Лінолеум | I69: м2 | J69: 18 | L69: 515 | M69: =J69*K69 -> 0 | N69: =J69*L69 -> 9270 | O69: =M69+N69 -> 9270
A70: 2.2.8 | B70: Строительные материалы | C70: Матеріал | D70: Виробництво/Будівництво | E70: Отделка | F70: 2.2.8 | G70: Лінолеум на стіни | H70: Лінолеум | I70: м2 | J70: 80.1 | L70: 429 | M70: =J70*K70 -> 0 | N70: =J70*L70 -> 34362.9 | O70: =M70+N70 -> 34362.9
A71: 2.2.9 | B71: Строительные материалы | C71: Матеріал | D71: Виробництво/Будівництво | E71: Отделка | F71: 2.2.9 | G71: Клей для лінолеума | H71: Клей для лінолеума | I71: кг | J71: 26 | L71: 321.37 | M71: =J71*K71 -> 0 | N71: =J71*L71 -> 8355.62 | O71: =M71+N71 -> 8355.62
A72: 2.2.10 | B72: Строительные материалы | C72: Матеріал | D72: Виробництво/Будівництво | E72: Отделка | F72: 2.2.10 | G72: Плінтус | H72: Плінтус | I72: м.п | J72: 35 | L72: 132.58 | M72: =J72*K72 -> 0 | N72: =J72*L72 -> 4640.3 | O72: =M72+N72 -> 4640.3
A73: 2.2.11 | B73: Строительные материалы | C73: Матеріал | D73: Виробництво/Будівництво | E73: Отделка | F73: 2.2.11 | G73: ПВХ вагонка 8мм біла | H73: ПВХ вагонка | I73: м2 | J73: 18 | L73: 229 | M73: =J73*K73 -> 0 | N73: =J73*L73 -> 4122 | O73: =M73+N73 -> 4122
A74: 2.2.12 | B74: Строительные материалы | C74: Матеріал | D74: Виробництво/Будівництво | E74: Отделка | F74: 2.2.12 | G74: Меблевий кутик | H74: Кутик | I74: м.п | J74: 84 | L74: 75 | M74: =J74*K74 -> 0 | N74: =J74*L74 -> 6300 | O74: =M74+N74 -> 6300
... A82: 2.2.20 | B82: Строительные материалы | C82: Матеріал | D82: Виробництво/Будівництво | E82: Отделка | F82: 2.2.20 | G82: Кутики білі 50*50 мм | H82: Кутик | I82: шт | J82: 6 | L82: 103 | M82: =J82*K82 -> 0 | N82: =J82*L82 -> 618 | O82: =M82+N82 -> 618
A83: 2.2.21 | B83: Строительные материалы | C83: Матеріал | D83: Виробництво/Будівництво | E83: Отделка | F83: 2.2.21 | G83: Піна клей | H83: Піна клей | I83: шт | J83: 4 | L83: 293 | M83: =J83*K83 -> 0 | N83: =J83*L83 -> 1172 | O83: =M83+N83 -> 1172 | P83: =SUM(N63:N83) -> 163888.82 | Q83: +
A84: ІІІ | F84: ІІІ | G84: Фасад | H84: Фасад | M84: =J84*K84 -> 0 | N84: =J84*L84 -> 0 | O84: =N84+M84 -> 0
A85: 3.1 | F85: 3.1 | G85: РОБОТА | M85: =J85*K85 -> 0 | N85: =J85*L85 -> 0 | O85: =N85+M85 -> 0
A86: 3.1.1 | B86: Зарплата производственного персонала | C86: Робота | D86: Виробництво/Будівництво | E86: Фасад | F86: 3.1.1 | G86: монтаж обрешітки по каркасу | I86: чол/год | J86: =3*8*1 -> 24 | K86: 200 | M86: =J86*K86 -> 4800 | N86: =J86*L86 -> 0 | O86: =N86+M86 -> 4800
A87: 3.1.2 | B87: Зарплата производственного персонала | C87: Робота | D87: Виробництво/Будівництво | E87: Фасад | F87: 3.1.2 | G87: Гідроізоляційна плівка | I87: чол/год | J87: =3*8*0.5 -> 12 | K87: 200 | M87: =J87*K87 -> 2400 | N87: =J87*L87 -> 0 | O87: =N87+M87 -> 2400
A88: 3.1.3 | B88: Зарплата производственного персонала | C88: Робота | D88: Виробництво/Будівництво | E88: Фасад | F88: 3.1.3 | G88: монтаж фасаду та покрівлі | I88: чол/год | J88: =3*8*1.5 -> 36 | K88: 200 | M88: =J88*K88 -> 7200 | N88: =J88*L88 -> 0 | O88: =N88+M88 -> 7200
A89: 3.1 | E89: Фасад | F89: 3.1 | G89: МАТЕРІАЛИ | M89: =J89*K89 -> 0 | N89: =J89*L89 -> 0 | O89: =N89+M89 -> 0
A90: 3.1.1 | B90: Строительные материалы | C90: Матеріал | D90: Виробництво/Будівництво | E90: Фасад | F90: 3.1.1 | G90: Порфлист ПК 8 | H90: Профнастил | I90: м2 | J90: 16.5 | L90: 286 | M90: =J90*K90 -> 0 | N90: =J90*L90 -> 4719 | O90: =M90+N90 -> 4719
A91: 3.1.2 | B91: Строительные материалы | C91: Матеріал | D91: Виробництво/Будівництво | E91: Фасад | F91: 3.1.2 | G91: Порфлист ПК 20 Покрівля | H91: Профнастил | I91: м2 | J91: 21 | L91: 289 | M91: =J91*K91 -> 0 | N91: =J91*L91 -> 6069 | O91: =M91+N91 -> 6069
A92: 3.1.3 | B92: Строительные материалы | C92: Матеріал | D92: Виробництво/Будівництво | E92: Фасад | F92: 3.1.3 | G92: Порфлист ПК 10 Стіни | H92: Профнастил | I92: м2 | J92: 105 | L92: 281 | M92: =J92*K92 -> 0 | N92: =J92*L92 -> 29505 | O92: =M92+N92 -> 29505
A93: 3.1.4 | B93: Строительные материалы | C93: Матеріал | D93: Виробництво/Будівництво | E93: Фасад | F93: 3.1.4 | G93: Гладкий лист білий | H93: Гладкий лист метал | I93: м2 | J93: 23 | L93: 277 | M93: =J93*K93 -> 0 | N93: =J93*L93 -> 6371 | O93: =M93+N93 -> 6371
A94: 3.1.5 | B94: Строительные материалы | C94: Матеріал | D94: Виробництво/Будівництво | E94: Фасад | F94: 3.1.5 | G94: Ринва | H94: Ринва | I94: шт | J94: 3 | L94: 403 | M94: =J94*K94 -> 0 | N94: =J94*L94 -> 1209 | O94: =M94+N94 -> 1209 | Q94: +
A95: 3.1.6 | B95: Строительные материалы | C95: Матеріал | D95: Виробництво/Будівництво | E95: Фасад | F95: 3.1.6 | G95: труба | H95: Труба водостічна | I95: шт | J95: 2 | L95: 442 | M95: =J95*K95 -> 0 | N95: =J95*L95 -> 884 | O95: =M95+N95 -> 884
A96: 3.1.7 | B96: Строительные материалы | C96: Матеріал | D96: Виробництво/Будівництво | E96: Фасад | F96: 3.1.7 | G96: Злив лівий | H96: Злив лівий | I96: шт | J96: 2 | L96: 495 | M96: =J96*K96 -> 0 | N96: =J96*L96 -> 990 | O96: =M96+N96 -> 990
A97: 3.1.8 | B97: Строительные материалы | C97: Матеріал | D97: Виробництво/Будівництво | E97: Фасад | F97: 3.1.8 | G97: Злив правий | H97: Злив правий | I97: шт | J97: 1 | L97: 495 | M97: =J97*K97 -> 0 | N97: =J97*L97 -> 495 | O97: =M97+N97 -> 495
A98: 3.1.9 | B98: Строительные материалы | C98: Матеріал | D98: Виробництво/Будівництво | E98: Фасад | F98: 3.1.9 | G98: Відвід 45 | H98: Відвід | I98: шт | J98: 2 | L98: 196 | M98: =J98*K98 -> 0 | N98: =J98*L98 -> 392 | O98: =M98+N98 -> 392
A99: 3.1.10 | B99: Строительные материалы | C99: Матеріал | D99: Виробництво/Будівництво | E99: Фасад | F99: 3.1.10 | G99: кріплення ринви | H99: Держак ринви | I99: шт | J99: 8 | L99: 123 | M99: =J99*K99 -> 0 | N99: =J99*L99 -> 984 | O99: =M99+N99 -> 984
A100: 3.1.11 | B100: Строительные материалы | C100: Матеріал | D100: Виробництво/Будівництво | E100: Фасад | F100: 3.1.11 | G100: кріплення труби | H100: Комплект кріплення труб | I100: шт | J100: 4 | L100: 206 | M100: =J100*K100 -> 0 | N100: =J100*L100 -> 824 | O100: =M100+N100 -> 824
A101: 3.1.12 | B101: Строительные материалы | C101: Матеріал | D101: Виробництво/Будівництво | E101: Фасад | F101: 3.1.12 | G101: зєднувачі ринви | H101: З'єднувач ринви | I101: шт | J101: 2 | L101: 365 | M101: =J101*K101 -> 0 | N101: =J101*L101 -> 730 | O101: =M101+N101 -> 730 | P101: =SUM(N90:N101) -> 53172 | Q101: +
A102: IV | F102: IV | G102: Вікна/двері | H102: Вікна | M102: =J102*K102 -> 0 | N102: =J102*L102 -> 0 | O102: =N102+M102 -> 0
A103: 4.1 | F103: 4.1 | G103: РОБОТА | M103: =J103*K103 -> 0 | N103: =J103*L103 -> 0 | O103: =N103+M103 -> 0
A104: 4.1.1 | B104: Зарплата производственного персонала | C104: Робота | D104: Виробництво/Будівництво | E104: Окна/двери | F104: 4.1.1 | G104: монтаж вікон | I104: чол/год | J104: =1*8 -> 8 | K104: 200 | M104: =J104*K104 -> 1600 | N104: =J104*L104 -> 0 | O104: =N104+M104 -> 1600
A105: 4.1.2 | B105: Зарплата производственного персонала | C105: Робота | D105: Виробництво/Будівництво | E105: Окна/двери | F105: 4.1.2 | G105: монтаж вхідних дверей | I105: чол/год | J105: =2*4/2 -> 4 | K105: 200 | M105: =J105*K105 -> 800 | N105: =J105*L105 -> 0 | O105: =N105+M105 -> 800
A106: 4.1.3 | B106: Зарплата производственного персонала | C106: Робота | D106: Виробництво/Будівництво | E106: Окна/двери | F106: 4.1.3 | G106: монтаж мдф дверей | I106: чол/год | J106: 0 | K106: 200 | M106: =J106*K106 -> 0 | N106: =J106*L106 -> 0 | O106: =N106+M106 -> 0
A107: 4.1.4 | B107: Зарплата производственного персонала | C107: Робота | D107: Виробництво/Будівництво | E107: Окна/двери | F107: 4.1.4 | G107: монтаж металопластикових дврей | I107: чол/год | J107: =2*8*1 -> 16 | K107: 200 | M107: =J107*K107 -> 3200 | N107: =J107*L107 -> 0 | O107: =N107+M107 -> 3200
A108: 4.2 | F108: 4.2 | G108: МАТЕРІАЛИ | M108: =J108*K108 -> 0 | N108: =J108*L108 -> 0 | O108: =N108+M108 -> 0
A109: 4.2.1 | B109: Строительные материалы | C109: Матеріал | D109: Виробництво/Будівництво | E109: Окна/двери | F109: 4.2.1 | G109: Вікно металопластик 870*1140 | H109: Вікно металопластикове | I109: шт | J109: 3 | L109: 10240 | M109: =J109*K109 -> 0 | N109: =J109*L109 -> 30720 | O109: =M109+N109 -> 30720
A110: 4.2.2 | B110: Строительные материалы | C110: Матеріал | D110: Виробництво/Будівництво | E110: Окна/двери | F110: 4.2.2 | G110: Вхідні двері металеві | H110: Вхідні двері металеві | I110: шт | J110: 1 | L110: 31000 | M110: =J110*K110 -> 0 | N110: =J110*L110 -> 31000 | O110: =M110+N110 -> 31000
A111: 4.2.3 | B111: Строительные материалы | C111: Матеріал | D111: Виробництво/Будівництво | E111: Окна/двери | F111: 4.2.3 | G111: Двері внутрішні | H111: Внутрішні двері металопластикові | I111: шт | J111: 3 | L111: 12823 | M111: =J111*K111 -> 0 | N111: =J111*L111 -> 38469 | O111: =M111+N111 -> 38469
A112: 4.2.4 | B112: Строительные материалы | C112: Матеріал | D112: Виробництво/Будівництво | E112: Окна/двери | F112: 4.2.4 | G112: Підвіконик ПВХ | H112: Підвіконик ПВХ | I112: шт | J112: 3 | L112: 573 | M112: =J112*K112 -> 0 | N112: =J112*L112 -> 1719 | O112: =M112+N112 -> 1719
A113: 4.2.5 | B113: Строительные материалы | C113: Матеріал | D113: Виробництво/Будівництво | E113: Окна/двери | F113: 4.2.5 | G113: Піна монтажна | H113: мшп | I113: балон | J113: 3 | L113: 297 | M113: =J113*K113 -> 0 | N113: =J113*L113 -> 891 | O113: =M113+N113 -> 891 | P113: =SUM(N109:N113) -> 102799 | Q113: +
A114: V | F114: V | G114: Электрика/Подогрев | H114: Электрика | M114: =J114*K114 -> 0 | N114: =J114*L114 -> 0 | O114: =N114+M114 -> 0
A115: 5.1 | F115: 5.1 | G115: РОБОТА | M115: =J115*K115 -> 0 | N115: =J115*L115 -> 0 | O115: =N115+M115 -> 0
A116: 5.1.1 | B116: Зарплата производственного персонала | C116: Робота | D116: Виробництво/Будівництво | E116: Электрика/Подогрев | F116: 5.1.1 | G116: монтаж електрокабеля | I116: чол/год | J116: 0.334 | K116: 10000 | M116: =J116*K116 -> 3340 | N116: =J116*L116 -> 0 | O116: =N116+M116 -> 3340
A117: 5.1.2 | B117: Зарплата производственного персонала | C117: Робота | D117: Виробництво/Будівництво | E117: Электрика/Подогрев | F117: 5.1.2 | G117: монтаж електрофурнітури | I117: чол/год | J117: 0.334 | K117: 10000 | M117: =J117*K117 -> 3340 | N117: =J117*L117 -> 0 | O117: =N117+M117 -> 3340
A118: 5.1.3 | B118: Зарплата производственного персонала | C118: Робота | D118: Виробництво/Будівництво | E118: Электрика/Подогрев | F118: 5.1.3 | G118: монтаж електроприборів | I118: чол/год | J118: 0.334 | K118: 10000 | M118: =J118*K118 -> 3340 | N118: =J118*L118 -> 0 | O118: =N118+M118 -> 3340
A119: 5.2 | E119: Электрика/Подогрев | F119: 5.2 | G119: МАТЕРІАЛИ | M119: =J119*K119 -> 0 | N119: =J119*L119 -> 0 | O119: =N119+M119 -> 0
A120: 5.2.1 | B120: Строительные материалы | C120: Матеріал | D120: Виробництво/Будівництво | E120: Электрика/Подогрев | F120: 5.2.1 | G120: Щиток пластиковий | H120: Розподільчий щит | I120: шт | J120: 1 | L120: 928.01 | M120: =J120*K120 -> 0 | N120: =J120*L120 -> 928.01 | O120: =M120+N120 -> 928.01
A121: 5.2.2 | B121: Строительные материалы | C121: Матеріал | D121: Виробництво/Будівництво | E121: Электрика/Подогрев | F121: 5.2.2 | G121: ВВГнгд 3х4 кабель | H121: Кабель | I121: м.п | J121: 30 | L121: 75.27 | M121: =J121*K121 -> 0 | N121: =J121*L121 -> 2258.1 | O121: =M121+N121 -> 2258.1
A122: 5.2.3 | B122: Строительные материалы | C122: Матеріал | D122: Виробництво/Будівництво | E122: Электрика/Подогрев | F122: 5.2.3 | G122: ВВГнгд 3х2,5 | H122: Кабель | I122: м.п | J122: 60 | L122: 61 | M122: =J122*K122 -> 0 | N122: =J122*L122 -> 3660 | O122: =M122+N122 -> 3660
A123: 5.2.4 | B123: Строительные материалы | C123: Матеріал | D123: Виробництво/Будівництво | E123: Электрика/Подогрев | F123: 5.2.4 | G123: ВВГнгд 3х1,5 | H123: Кабель | I123: м.п | J123: 50 | L123: 55 | M123: =J123*K123 -> 0 | N123: =J123*L123 -> 2750 | O123: =M123+N123 -> 2750
A124: 5.2.5 | B124: Строительные материалы | C124: Матеріал | D124: Виробництво/Будівництво | E124: Электрика/Подогрев | F124: 5.2.5 | G124: Труба ПВХ гнучка 20мм | H124: Труба гофра | I124: м | J124: 50 | L124: 20 | M124: =J124*K124 -> 0 | N124: =J124*L124 -> 1000 | O124: =M124+N124 -> 1000
A125: 5.2.6 | B125: Строительные материалы | C125: Матеріал | D125: Виробництво/Будівництво | E125: Электрика/Подогрев | F125: 5.2.6 | G125: Модульний автомат 10А | H125: Вимикач | I125: шт | J125: 1 | L125: 124 | M125: =J125*K125 -> 0 | N125: =J125*L125 -> 124 | O125: =M125+N125 -> 124
A126: 5.2.7 | B126: Строительные материалы | C126: Матеріал | D126: Виробництво/Будівництво | E126: Электрика/Подогрев | F126: 5.2.7 | G126: Модульний автомат 16А | H126: Вимикач | I126: шт | J126: 3 | L126: 142.5 | M126: =J126*K126 -> 0 | N126: =J126*L126 -> 427.5 | O126: =M126+N126 -> 427.5
A127: 5.2.8 | B127: Строительные материалы | C127: Матеріал | D127: Виробництво/Будівництво | E127: Электрика/Подогрев | F127: 5.2.8 | G127: Модульний автомат 25А | H127: Вимикач | I127: шт | J127: 1 | L127: 137.65 | M127: =J127*K127 -> 0 | N127: =J127*L127 -> 137.65 | O127: =M127+N127 -> 137.65
A128: 5.2.9 | B128: Строительные материалы | C128: Матеріал | D128: Виробництво/Будівництво | E128: Электрика/Подогрев | F128: 5.2.9 | G128: Шина нульова | H128: Шина нульова на ізоляторі | I128: шт | J128: 1 | L128: 96 | M128: =J128*K128 -> 0 | N128: =J128*L128 -> 96 | O128: =M128+N128 -> 96
A129: 5.2.10 | B129: Строительные материалы | C129: Матеріал | D129: Виробництво/Будівництво | E129: Электрика/Подогрев | F129: 5.2.10 | G129: Розподільча коробка 100*100*45 | H129: Розподільча коробка | I129: шт | J129: 3 | L129: 107 | M129: =J129*K129 -> 0 | N129: =J129*L129 -> 321 | O129: =M129+N129 -> 321
A130: 5.2.11 | B130: Строительные материалы | C130: Матеріал | D130: Виробництво/Будівництво | E130: Электрика/Подогрев | F130: 5.2.11 | G130: Клема WGn-2 | H130: Клема з'єднувальна | I130: шт | J130: 8 | L130: 9.23 | M130: =J130*K130 -> 0 | N130: =J130*L130 -> 73.84 | O130: =M130+N130 -> 73.84
A131: 5.2.12 | B131: Строительные материалы | C131: Матеріал | D131: Виробництво/Будівництво | E131: Электрика/Подогрев | F131: 5.2.12 | G131: Клема WGn-3 | H131: Клема з'єднувальна | I131: шт | J131: 7 | L131: 12.36 | M131: =J131*K131 -> 0 | N131: =J131*L131 -> 86.52 | O131: =M131+N131 -> 86.52
... A152: 5.2.33 | B152: Строительные материалы | C152: Матеріал | D152: Виробництво/Будівництво | E152: Электрика/Подогрев | F152: 5.2.33 | G152: Ізоляційна стрічка | H152: Ізоляційна стрічка | I152: шт | J152: 2 | L152: 25 | M152: =J152*K152 -> 0 | N152: =J152*L152 -> 50 | O152: =M152+N152 -> 50
A153: 5.2.34 | B153: Строительные материалы | C153: Матеріал | D153: Виробництво/Будівництво | E153: Электрика/Подогрев | F153: 5.2.34 | G153: АВР | H153: АВР | I153: шт | J153: 1 | L153: 2760 | M153: =J153*K153 -> 0 | N153: =J153*L153 -> 2760 | O153: =M153+N153 -> 2760 | Q153: +
...

Sheet 30 м2
A1: № | B1: Стаття в ДДС | C1: Робота/матеріал/додаткові | D1: Виробництво/Будівництво | E1: Тип робіт | F1: № з/п | G1: Найменування робіт/витрат/матеріалів | I1: Од. вим. | J1: Кіль- кість | K1: Вартість робіт за од.виміру, грн. з ПДВ | L1: Вартість матеріалів за од.виміру, грн. з ПДВ | M1: Вартість робіт за повний обсяг, грн. з ПДВ | N1: Вартість матеріалів за повний обсяг, грн. з ПДВ | O1: Всього, грн. з ПДВ
A2: І | F2: І | G2: Каркас | J2: =L3+L12 -> 0
A3: 1.1 | F3: 1.1 | G3: РОБОТА | L3: =SUM(L5:L11) -> 0
A4: 1.1.1 | B4: Зарплата производственного персонала | C4: Робота | D4: Виробництво/Будівництво | E4: Каркас | F4: 1.1.1 | G4: Приймання матеріалу | I4: чол/год | K4: 200 | M4: =J4*K4 -> 0 | N4: =J4*L4 -> 0 | O4: =N4+M4 -> 0
A5: 1.1.2 | B5: Зарплата производственного персонала | C5: Робота | D5: Виробництво/Будівництво | E5: Каркас | F5: 1.1.2 | G5: Обробка матеріалу (дерево) | I5: чол/год | K5: 200 | M5: =J5*K5 -> 0 | N5: =J5*L5 -> 0 | O5: =N5+M5 -> 0
A6: 1.1.3 | B6: Зарплата производственного персонала | C6: Робота | D6: Виробництво/Будівництво | E6: Каркас | F6: 1.1.3 | G6: Нарізання деталей зігдно креслень | I6: чол/год | K6: 200 | M6: =J6*K6 -> 0 | N6: =J6*L6 -> 0 | O6: =N6+M6 -> 0
A7: 1.1.4 | B7: Зарплата производственного персонала | C7: Робота | D7: Виробництво/Будівництво | E7: Каркас | F7: 1.1.4 | G7: Збирання деталей | I7: чол/год | K7: 200 | M7: =J7*K7 -> 0 | N7: =J7*L7 -> 0 | O7: =N7+M7 -> 0
A8: 1.1.5 | B8: Зарплата производственного персонала | C8: Робота | D8: Виробництво/Будівництво | E8: Каркас | F8: 1.1.5 | G8: зварювання (дерево зєдання) | I8: чол/год | K8: 200 | M8: =J8*K8 -> 0 | N8: =J8*L8 -> 0 | O8: =N8+M8 -> 0
A9: 1.1.6 | B9: Зарплата производственного персонала | C9: Робота | D9: Виробництво/Будівництво | E9: Каркас | F9: 1.1.6 | G9: Влаштування підшиви модуля | I9: чол/год | K9: 200 | M9: =J9*K9 -> 0 | N9: =J9*L9 -> 0 | O9: =N9+M9 -> 0
A10: 1.1.7 | B10: Зарплата производственного персонала | C10: Робота | D10: Виробництво/Будівництво | E10: Каркас | F10: 1.1.7 | G10: Грунтування металокаркасу | I10: чол/год | K10: 200 | M10: =J10*K10 -> 0 | N10: =J10*L10 -> 0 | O10: =N10+M10 -> 0
A11: 1.1.8 | B11: Зарплата производственного персонала | C11: Робота | D11: Виробництво/Будівництво | E11: Каркас | F11: 1.1.8 | G11: Фарубування металокаркасу | I11: чол/год | K11: 200 | M11: =J11*K11 -> 0 | N11: =J11*L11 -> 0 | O11: =N11+M11 -> 0
A12: 1.2 | F12: 1.2 | G12: МАТЕРІАЛИ
A13: 1.2.1 | B13: Строительные материалы | C13: Матеріал | D13: Виробництво/Будівництво | E13: Каркас | F13: 1.2.1 | G13: Труба металева Ст3 100*100*3 | H13: Профільна труба | I13: м.п | J13: 80.4 | L13: 473 | M13: =J13*K13 -> 0 | N13: =J13*L13 -> 38029.2 | O13: =N13+M13 -> 38029.2
A14: 1.2.2 | B14: Строительные материалы | C14: Матеріал | D14: Виробництво/Будівництво | E14: Каркас | F14: 1.2.2 | G14: Труба металева Ст3 50*50*2 | H14: Профільна труба | I14: м.п. | J14: 240 | L14: 157 | M14: =J14*K14 -> 0 | N14: =J14*L14 -> 37680 | O14: =N14+M14 -> 37680
A15: 1.2.3 | B15: Строительные материалы | C15: Матеріал | D15: Виробництво/Будівництво | E15: Каркас | F15: 1.2.3 | G15: Труба металева Ст3 дв 40 *3,5 | H15: Профільна труба | I15: м.п | J15: 2.5 | L15: 151 | M15: =J15*K15 -> 0 | N15: =J15*L15 -> 377.5 | O15: =N15+M15 -> 377.5
A16: 1.2.4 | B16: Строительные материалы | C16: Матеріал | D16: Виробництво/Будівництво | E16: Каркас | F16: 1.2.4 | G16: Труба металева Ст3 дв 89 *3,5 | H16: Профільна труба | I16: м.п. | J16: 2 | L16: 339 | M16: =J16*K16 -> 0 | N16: =J16*L16 -> 678 | O16: =N16+M16 -> 678
A17: 1.2.5 | B17: Строительные материалы | C17: Матеріал | D17: Виробництво/Будівництво | E17: Каркас | F17: 1.2.5 | G17: Лист 4мм | H17: лист ГК | I17: м.кв. | J17: 1.02 | L17: 1207 | M17: =J17*K17 -> 0 | N17: =J17*L17 -> 1231.14 | O17: =N17+M17 -> 1231.14
A18: 1.2.6 | B18: Строительные материалы | C18: Матеріал | D18: Виробництво/Будівництво | E18: Каркас | F18: 1.2.6 | G18: Лист 8мм | H18: лист ГК | I18: м.кв. | J18: 1.215 | L18: 2487 | M18: =J18*K18 -> 0 | N18: =J18*L18 -> 3021.705 | O18: =N18+M18 -> 3021.705
A19: 1.2.7 | B19: Строительные материалы | C19: Матеріал | D19: Виробництво/Будівництво | E19: Каркас | F19: 1.2.7 | G19: Лист 14мм | H19: лист ГК | I19: м.кв. | J19: 0.24 | L19: 4976 | M19: =J19*K19 -> 0 | N19: =J19*L19 -> 1194.24 | O19: =N19+M19 -> 1194.24
A20: 1.2.8 | B20: Строительные материалы | C20: Матеріал | D20: Виробництво/Будівництво | E20: Каркас | F20: 1.2.8 | G20: Гайка М48 | H20: Гайка | I20: шт | J20: 11 | L20: 350 | M20: =J20*K20 -> 0 | N20: =J20*L20 -> 3850 | O20: =N20+M20 -> 3850
A21: 1.2.9 | B21: Строительные материалы | C21: Матеріал | D21: Виробництво/Будівництво | E21: Каркас | F21: 1.2.9 | G21: Шпилька М48 довжина 1000 мм | H21: Шпилька | I21: шт | J21: 5 | L21: 3600 | M21: =J21*K21 -> 0 | N21: =J21*L21 -> 18000 | O21: =N21+M21 -> 18000
A22: 1.2.10 | B22: Строительные материалы | C22: Матеріал | D22: Виробництво/Будівництво | E22: Каркас | F22: 1.2.10 | G22: Гайка М24 | H22: Гайка | I22: шт | J22: 28 | L22: 154 | M22: =J22*K22 -> 0 | N22: =J22*L22 -> 4312 | O22: =N22+M22 -> 4312
A23: 1.2.11 | B23: Строительные материалы | C23: Матеріал | D23: Виробництво/Будівництво | E23: Каркас | F23: 1.2.11 | G23: Болт М24х200 | H23: Болт | I23: шт | J23: 9 | L23: 168 | M23: =J23*K23 -> 0 | N23: =J23*L23 -> 1512 | O23: =N23+M23 -> 1512
A24: 1.2.12 | B24: Строительные материалы | C24: Матеріал | D24: Виробництво/Будівництво | E24: Каркас | F24: 1.2.12 | G24: Труба 40*40*3 | H24: Профільна труба | I24: м.п. | J24: 141 | L24: 165 | M24: =J24*K24 -> 0 | N24: =J24*L24 -> 23265 | O24: =N24+M24 -> 23265
... A52: 1.2.40 | B52: Строительные материалы | C52: Матеріал | D52: Виробництво/Будівництво | E52: Каркас | F52: 1.2.40 | G52: Гвинт з прес-шайбою 4,2*16 | H52: Гвинт | I52: шт | J52: 200 | L52: 0.32 | M52: =J52*K52 -> 0 | N52: =J52*L52 -> 64 | O52: =N52+M52 -> 64
A53: 1.2.41 | B53: Строительные материалы | C53: Матеріал | D53: Виробництво/Будівництво | E53: Каркас | F53: 1.2.41 | G53: Шуруп з пером 5,5*90 | H53: Саморіз | I53: шт | J53: 275 | L53: 1.03 | M53: =J53*K53 -> 0 | N53: =J53*L53 -> 283.25 | O53: =N53+M53 -> 283.25 | P53: =SUM(O13:O53) -> 236595.13 | Q53: +
A54: ІІ | F54: ІІ | G54: Отделка | M54: =J54*K54 -> 0 | N54: =J54*L54 -> 0 | O54: =N54+M54 -> 0
A55: 2.1 | F55: 2.1 | G55: РОБОТА | M55: =J55*K55 -> 0 | N55: =J55*L55 -> 0 | O55: =N55+M55 -> 0
A56: 2.1.1 | B56: Зарплата производственного персонала | C56: Робота | D56: Виробництво/Будівництво | E56: Отделка | F56: 2.1.1 | G56: Утеплення та гідроізоляція підлоги | I56: чол/год | K56: 200 | M56: =J56*K56 -> 0 | N56: =J56*L56 -> 0 | O56: =N56+M56 -> 0
A57: 2.1.2 | B57: Зарплата производственного персонала | C57: Робота | D57: Виробництво/Будівництво | E57: Отделка | F57: 2.1.2 | G57: Монтаж брусу по каркасу | I57: чол/год | K57: 200 | M57: =J57*K57 -> 0 | N57: =J57*L57 -> 0 | O57: =N57+M57 -> 0
A58: 2.1.3 | B58: Зарплата производственного персонала | C58: Робота | D58: Виробництво/Будівництво | E58: Отделка | F58: 2.1.3 | G58: Пароізоляційна мембрана; | I58: чол/год | K58: 200 | M58: =J58*K58 -> 0 | N58: =J58*L58 -> 0 | O58: =N58+M58 -> 0
A59: 2.1.4 | B59: Зарплата производственного персонала | C59: Робота | D59: Виробництво/Будівництво | E59: Отделка | F59: 2.1.4 | G59: Укладання Настил підлоги | I59: чол/год | K59: 200 | M59: =J59*K59 -> 0 | N59: =J59*L59 -> 0 | O59: =N59+M59 -> 0
A60: 2.1.5 | B60: Зарплата производственного персонала | C60: Робота | D60: Виробництво/Будівництво | E60: Отделка | F60: 2.1.5 | G60: Гідроізоляційна та пароізоляція стін та стелі | I60: чол/год | K60: 200 | M60: =J60*K60 -> 0 | N60: =J60*L60 -> 0 | O60: =N60+M60 -> 0
A61: 2.1.6 | B61: Зарплата производственного персонала | C61: Робота | D61: Виробництво/Будівництво | E61: Отделка | F61: 2.1.6 | G61: Утеплення стеля та стіни | I61: чол/год | K61: 200 | M61: =J61*K61 -> 0 | N61: =J61*L61 -> 0 | O61: =N61+M61 -> 0
A62: 2.1.7 | B62: Зарплата производственного персонала | C62: Робота | D62: Виробництво/Будівництво | E62: Отделка | F62: 2.1.7 | G62: Монтаж фінішного оздоблення | I62: чол/год | K62: 200 | M62: =J62*K62 -> 0 | N62: =J62*L62 -> 0 | O62: =N62+M62 -> 0
A63: 2.2 | E63: Отделка | F63: 2.2 | G63: МАТЕРІАЛИ | M63: =J63*K63 -> 0 | N63: =J63*L63 -> 0 | O63: =N63+M63 -> 0
A64: 2.2.1 | B64: Строительные материалы | C64: Матеріал | D64: Виробництво/Будівництво | E64: Отделка | F64: 2.2.1 | G64: Вітробарєр | H64: Мембрана | I64: м2 | J64: 82 | L64: 29 | M64: =J64*K64 -> 0 | N64: =J64*L64 -> 2378 | O64: =N64+M64 -> 2378
A65: 2.2.2 | B65: Строительные материалы | C65: Матеріал | D65: Виробництво/Будівництво | E65: Отделка | F65: 2.2.2 | G65: Паро-гідро бар'єр | H65: Мембрана | I65: м2 | J65: 210 | L65: 13 | M65: =J65*K65 -> 0 | N65: =J65*L65 -> 2730 | O65: =N65+M65 -> 2730
A66: 2.2.3 | B66: Строительные материалы | C66: Матеріал | D66: Виробництво/Будівництво | E66: Отделка | F66: 2.2.3 | G66: Пінопласт товщина 50 мм | H66: Пінопласт | I66: м2 | J66: 88 | L66: 112 | M66: =J66*K66 -> 0 | N66: =J66*L66 -> 9856 | O66: =N66+M66 -> 9856
A67: 2.2.4 | B67: Строительные материалы | C67: Матеріал | D67: Виробництво/Будівництво | E67: Отделка | F67: 2.2.4 | G67: Мінеральна вата (100 мм) | H67: мінеральна вата | I67: м2 | J67: 100 | L67: 180 | M67: =J67*K67 -> 0 | N67: =J67*L67 -> 18000 | O67: =N67+M67 -> 18000
A68: 2.2.5 | B68: Строительные материалы | C68: Матеріал | D68: Виробництво/Будівництво | E68: Отделка | F68: 2.2.5 | G68: Мінеральна вата (50 мм) | H68: мінеральна вата | I68: м2 | J68: 341 | L68: 90 | M68: =J68*K68 -> 0 | N68: =J68*L68 -> 30690 | O68: =N68+M68 -> 30690
A69: 2.2.6 | B69: Строительные материалы | C69: Матеріал | D69: Виробництво/Будівництво | E69: Отделка | F69: 2.2.6 | G69: ЦСП панель 20 мм | H69: Плита ЦСП | I69: шт | J69: 9 | L69: 7700 | M69: =J69*K69 -> 0 | N69: =J69*L69 -> 69300 | O69: =N69+M69 -> 69300
A70: 2.2.7 | B70: Строительные материалы | C70: Матеріал | D70: Виробництво/Будівництво | E70: Отделка | F70: 2.2.7 | G70: Лінолеум комерційний на підлогу | H70: Лінолеум | I70: м2 | J70: 36 | L70: 515 | M70: =J70*K70 -> 0 | N70: =J70*L70 -> 18540 | O70: =N70+M70 -> 18540
A71: 2.2.8 | B71: Строительные материалы | C71: Матеріал | D71: Виробництво/Будівництво | E71: Отделка | F71: 2.2.8 | G71: Лінолеум на стіни | H71: Лінолеум | I71: м2 | J71: 160 | L71: 429 | M71: =J71*K71 -> 0 | N71: =J71*L71 -> 68640 | O71: =N71+M71 -> 68640
A72: 2.2.9 | B72: Строительные материалы | C72: Матеріал | D72: Виробництво/Будівництво | E72: Отделка | F72: 2.2.9 | G72: Клей для лінолеума | H72: Клей для лінолеума | I72: кг | J72: 35 | L72: 540 | M72: =J72*K72 -> 0 | N72: =J72*L72 -> 18900 | O72: =N72+M72 -> 18900
A73: 2.2.10 | B73: Строительные материалы | C73: Матеріал | D73: Виробництво/Будівництво | E73: Отделка | F73: 2.2.10 | G73: Плінтус 100 | H73: Плінтус | I73: м.п | J73: 75 | L73: 132.58 | M73: =J73*K73 -> 0 | N73: =J73*L73 -> 9943.5 | O73: =N73+M73 -> 9943.5
A74: 2.2.11 | B74: Строительные материалы | C74: Матеріал | D74: Виробництво/Будівництво | E74: Отделка | F74: 2.2.11 | G74: ПВХ вагонка 8мм біла | H74: ПВХ вагонка | I74: м2 | J74: 36 | L74: 229 | M74: =J74*K74 -> 0 | N74: =J74*L74 -> 8244 | O74: =N74+M74 -> 8244
A75: 2.2.12 | B75: Строительные материалы | C75: Матеріал | D75: Виробництво/Будівництво | E75: Отделка | F75: 2.2.12 | G75: Меблевий кутик | H75: Кутик | I75: м.п | J75: 92 | L75: 139.26 | M75: =J75*K75 -> 0 | N75: =J75*L75 -> 12811.92 | O75: =N75+M75 -> 12811.92
... A83: 2.2.20 | B83: Строительные материалы | C83: Матеріал | D83: Виробництво/Будівництво | E83: Отделка | F83: 2.2.20 | G83: Кутики білі 50*50 мм | H83: Кутик | I83: шт | J83: 12 | L83: 103 | M83: =J83*K83 -> 0 | N83: =J83*L83 -> 1236 | O83: =N83+M83 -> 1236
A84: 2.2.21 | B84: Строительные материалы | C84: Матеріал | D84: Виробництво/Будівництво | E84: Отделка | F84: 2.2.21 | G84: Піна клей | H84: Піна клей | I84: шт | J84: 6 | L84: 293 | M84: =J84*K84 -> 0 | N84: =J84*L84 -> 1758 | O84: =N84+M84 -> 1758 | P84: =SUM(O64:O84) -> 325398.42 | Q84: +
A85: ІІІ | F85: ІІІ | G85: Фасад | M85: =J85*K85 -> 0 | N85: =J85*L85 -> 0 | O85: =N85+M85 -> 0
A86: 3.1 | F86: 3.1 | G86: РОБОТА | M86: =J86*K86 -> 0 | N86: =J86*L86 -> 0 | O86: =N86+M86 -> 0
A87: 3.1.1 | B87: Зарплата производственного персонала | C87: Робота | D87: Виробництво/Будівництво | E87: Фасад | F87: 3.1.1 | G87: монтаж обрешітки по каркасу | I87: чол/год | K87: 200 | M87: =J87*K87 -> 0 | N87: =J87*L87 -> 0 | O87: =N87+M87 -> 0
A88: 3.1.2 | B88: Зарплата производственного персонала | C88: Робота | D88: Виробництво/Будівництво | E88: Фасад | F88: 3.1.2 | G88: Гідроізоляційна плівка | I88: чол/год | K88: 200 | M88: =J88*K88 -> 0 | N88: =J88*L88 -> 0 | O88: =N88+M88 -> 0
A89: 3.1.3 | B89: Зарплата производственного персонала | C89: Робота | D89: Виробництво/Будівництво | E89: Фасад | F89: 3.1.3 | G89: монтаж фасаду та покрівлі | I89: чол/год | K89: 200 | M89: =J89*K89 -> 0 | N89: =J89*L89 -> 0 | O89: =N89+M89 -> 0
A90: 3.1 | E90: Фасад | F90: 3.1 | G90: МАТЕРІАЛИ | M90: =J90*K90 -> 0 | N90: =J90*L90 -> 0 | O90: =N90+M90 -> 0
A91: 3.1.1 | B91: Строительные материалы | C91: Матеріал | D91: Виробництво/Будівництво | E91: Фасад | F91: 3.1.1 | G91: Порфлист ПК 8 | H91: Профнастил | I91: м2 | J91: 33 | L91: 286 | M91: =J91*K91 -> 0 | N91: =J91*L91 -> 9438 | O91: =N91+M91 -> 9438
A92: 3.1.2 | B92: Строительные материалы | C92: Матеріал | D92: Виробництво/Будівництво | E92: Фасад | F92: 3.1.2 | G92: Порфлист ПК 20 Покрівля | H92: Профнастил | I92: м2 | J92: 43.2 | L92: 289 | M92: =J92*K92 -> 0 | N92: =J92*L92 -> 12484.8 | O92: =N92+M92 -> 12484.8
A93: 3.1.3 | B93: Строительные материалы | C93: Матеріал | D93: Виробництво/Будівництво | E93: Фасад | F93: 3.1.3 | G93: Порфлист ПК 10 Стіни | H93: Профнастил | I93: м2 | J93: 100 | L93: 281 | M93: =J93*K93 -> 0 | N93: =J93*L93 -> 28100 | O93: =N93+M93 -> 28100
A94: 3.1.4 | B94: Строительные материалы | C94: Матеріал | D94: Виробництво/Будівництво | E94: Фасад | F94: 3.1.4 | G94: Гладкий лист білий | H94: Гладкий лист метал | I94: м2 | J94: 44 | L94: 277 | M94: =J94*K94 -> 0 | N94: =J94*L94 -> 12188 | O94: =N94+M94 -> 12188
A95: 3.1.5 | B95: Строительные материалы | C95: Матеріал | D95: Виробництво/Будівництво | E95: Фасад | F95: 3.1.5 | G95: Ринва | H95: Ринва | I95: шт | J95: 6 | L95: 403 | M95: =J95*K95 -> 0 | N95: =J95*L95 -> 2418 | O95: =N95+M95 -> 2418 | Q95: +
A96: 3.1.6 | B96: Строительные материалы | C96: Матеріал | D96: Виробництво/Будівництво | E96: Фасад | F96: 3.1.6 | G96: труба | H96: Труба | I96: шт | J96: 4 | L96: 442 | M96: =J96*K96 -> 0 | N96: =J96*L96 -> 1768 | O96: =N96+M96 -> 1768
A97: 3.1.7 | B97: Строительные материалы | C97: Матеріал | D97: Виробництво/Будівництво | E97: Фасад | F97: 3.1.7 | G97: Злив лівий | H97: Злив лівий | I97: шт | J97: 2 | L97: 495 | M97: =J97*K97 -> 0 | N97: =J97*L97 -> 990 | O97: =N97+M97 -> 990
A98: 3.1.8 | B98: Строительные материалы | C98: Матеріал | D98: Виробництво/Будівництво | E98: Фасад | F98: 3.1.8 | G98: Злив правий | H98: Злив правий | I98: шт | J98: 2 | L98: 495 | M98: =J98*K98 -> 0 | N98: =J98*L98 -> 990 | O98: =N98+M98 -> 990
A99: 3.1.9 | B99: Строительные материалы | C99: Матеріал | D99: Виробництво/Будівництво | E99: Фасад | F99: 3.1.9 | G99: Відвід 45 | H99: Відвід | I99: шт | J99: 4 | L99: 196 | M99: =J99*K99 -> 0 | N99: =J99*L99 -> 784 | O99: =N99+M99 -> 784
A100: 3.1.10 | B100: Строительные материалы | C100: Матеріал | D100: Виробництво/Будівництво | E100: Фасад | F100: 3.1.10 | G100: кріплення ринви | H100: Кріплення | I100: шт | J100: 20 | L100: 123 | M100: =J100*K100 -> 0 | N100: =J100*L100 -> 2460 | O100: =N100+M100 -> 2460
A101: 3.1.11 | B101: Строительные материалы | C101: Матеріал | D101: Виробництво/Будівництво | E101: Фасад | F101: 3.1.11 | G101: кріплення труби | H101: Кріплення | I101: шт | J101: 8 | L101: 206 | M101: =J101*K101 -> 0 | N101: =J101*L101 -> 1648 | O101: =N101+M101 -> 1648
A102: 3.1.12 | B102: Строительные материалы | C102: Матеріал | D102: Виробництво/Будівництво | E102: Фасад | F102: 3.1.12 | G102: зєднувачі ринви | H102: З'єднувач | I102: шт | J102: 4 | L102: 365 | M102: =J102*K102 -> 0 | N102: =J102*L102 -> 1460 | O102: =N102+M102 -> 1460 | P102: =SUM(O91:O102) -> 74728.8 | Q102: +
A103: IV | F103: IV | G103: Вікна/двері | M103: =J103*K103 -> 0 | N103: =J103*L103 -> 0 | O103: =N103+M103 -> 0
A104: 4.1 | F104: 4.1 | G104: РОБОТА | M104: =J104*K104 -> 0 | N104: =J104*L104 -> 0 | O104: =N104+M104 -> 0
A105: 4.1.1 | B105: Зарплата производственного персонала | C105: Робота | D105: Виробництво/Будівництво | E105: Окна/двери | F105: 4.1.1 | G105: монтаж вікон | I105: чол/год | K105: 200 | M105: =J105*K105 -> 0 | N105: =J105*L105 -> 0 | O105: =N105+M105 -> 0
A106: 4.1.2 | B106: Зарплата производственного персонала | C106: Робота | D106: Виробництво/Будівництво | E106: Окна/двери | F106: 4.1.2 | G106: монтаж вхідних дверей | I106: чол/год | K106: 200 | M106: =J106*K106 -> 0 | N106: =J106*L106 -> 0 | O106: =N106+M106 -> 0
A107: 4.1.3 | B107: Зарплата производственного персонала | C107: Робота | D107: Виробництво/Будівництво | E107: Окна/двери | F107: 4.1.3 | G107: монтаж мдф дверей | I107: чол/год | K107: 200 | M107: =J107*K107 -> 0 | N107: =J107*L107 -> 0 | O107: =N107+M107 -> 0
A108: 4.1.4 | B108: Зарплата производственного персонала | C108: Робота | D108: Виробництво/Будівництво | E108: Окна/двери | F108: 4.1.4 | G108: монтаж металопластикових дврей | I108: чол/год | K108: 200 | M108: =J108*K108 -> 0 | N108: =J108*L108 -> 0 | O108: =N108+M108 -> 0
A109: 4.2 | F109: 4.2 | G109: МАТЕРІАЛИ | M109: =J109*K109 -> 0 | N109: =J109*L109 -> 0 | O109: =N109+M109 -> 0
A110: 4.2.1 | B110: Строительные материалы | C110: Матеріал | D110: Виробництво/Будівництво | E110: Окна/двери | F110: 4.2.1 | G110: Вікно металопластик 870*1140 | H110: Вікно металопластикове | I110: шт | J110: 6 | L110: 8500 | M110: =J110*K110 -> 0 | N110: =J110*L110 -> 51000 | O110: =N110+M110 -> 51000
A111: 4.2.2 | B111: Строительные материалы | C111: Матеріал | D111: Виробництво/Будівництво | E111: Окна/двери | F111: 4.2.2 | G111: Вхідні двері металеві | H111: Вхідні двері металеві | I111: шт | J111: 1 | L111: 25000 | M111: =J111*K111 -> 0 | N111: =J111*L111 -> 25000 | O111: =N111+M111 -> 25000
A112: 4.2.3 | B112: Строительные материалы | C112: Матеріал | D112: Виробництво/Будівництво | E112: Окна/двери | F112: 4.2.3 | G112: Двері внутрішні металопластикові | H112: Внутрішні двері металопластикові | I112: шт | J112: 3 | L112: 10000 | M112: =J112*K112 -> 0 | N112: =J112*L112 -> 30000 | O112: =N112+M112 -> 30000
A113: 4.2.4 | B113: Строительные материалы | C113: Матеріал | D113: Виробництво/Будівництво | E113: Окна/двери | F113: 4.2.4 | G113: Підвіконик ПВХ | H113: Підвіконня ПВХ | I113: шт | J113: 6 | L113: 573 | M113: =J113*K113 -> 0 | N113: =J113*L113 -> 3438 | O113: =N113+M113 -> 3438
A114: 4.2.5 | B114: Строительные материалы | C114: Матеріал | D114: Виробництво/Будівництво | E114: Окна/двери | F114: 4.2.5 | G114: Піна монтажна | H114: Піна | I114: балон | J114: 8 | L114: 297 | M114: =J114*K114 -> 0 | N114: =J114*L114 -> 2376 | O114: =N114+M114 -> 2376 | P114: =SUM(O110:O114) -> 111814 | Q114: +
A115: V | F115: V | G115: Электрика/Подогрев | M115: =J115*K115 -> 0 | N115: =J115*L115 -> 0 | O115: =N115+M115 -> 0
A116: 5.1 | F116: 5.1 | G116: РОБОТА | M116: =J116*K116 -> 0 | N116: =J116*L116 -> 0 | O116: =N116+M116 -> 0
A117: 5.1.1 | B117: Зарплата производственного персонала | C117: Робота | D117: Виробництво/Будівництво | E117: Электрика/Подогрев | F117: 5.1.1 | G117: монтаж електрокабеля | I117: чол/год | K117: 15000 | M117: =J117*K117 -> 0 | N117: =J117*L117 -> 0 | O117: =N117+M117 -> 0
A118: 5.1.2 | B118: Зарплата производственного персонала | C118: Робота | D118: Виробництво/Будівництво | E118: Электрика/Подогрев | F118: 5.1.2 | G118: монтаж електрофурнітури | I118: чол/год | K118: 15000 | M118: =J118*K118 -> 0 | N118: =J118*L118 -> 0 | O118: =N118+M118 -> 0
A119: 5.1.3 | B119: Зарплата производственного персонала | C119: Робота | D119: Виробництво/Будівництво | E119: Электрика/Подогрев | F119: 5.1.3 | G119: монтаж електроприборів | I119: чол/год | K119: 15000 | M119: =J119*K119 -> 0 | N119: =J119*L119 -> 0 | O119: =N119+M119 -> 0
A120: 5.2 | E120: Электрика/Подогрев | F120: 5.2 | G120: МАТЕРІАЛИ | M120: =J120*K120 -> 0 | N120: =J120*L120 -> 0 | O120: =N120+M120 -> 0
A121: 5.2.1 | B121: Строительные материалы | C121: Матеріал | D121: Виробництво/Будівництво | E121: Электрика/Подогрев | F121: 5.2.1 | G121: Щиток пластиковий зовнішній | H121: Розподільчий щит | I121: шт | J121: 2 | L121: 928 | M121: =J121*K121 -> 0 | N121: =J121*L121 -> 1856 | O121: =N121+M121 -> 1856
A122: 5.2.2 | B122: Строительные материалы | C122: Матеріал | D122: Виробництво/Будівництво | E122: Электрика/Подогрев | F122: 5.2.2 | G122: ВВГнгд 3х4 кабель | H122: Кабель | I122: м.п | J122: 50 | L122: 75.27 | M122: =J122*K122 -> 0 | N122: =J122*L122 -> 3763.5 | O122: =N122+M122 -> 3763.5
A123: 5.2.3 | B123: Строительные материалы | C123: Матеріал | D123: Виробництво/Будівництво | E123: Электрика/Подогрев | F123: 5.2.3 | G123: ВВГнгд 3х2,5 кабель | H123: Кабель | I123: м.п | J123: 120 | L123: 72 | M123: =J123*K123 -> 0 | N123: =J123*L123 -> 8640 | O123: =N123+M123 -> 8640
A124: 5.2.4 | B124: Строительные материалы | C124: Матеріал | D124: Виробництво/Будівництво | E124: Электрика/Подогрев | F124: 5.2.4 | G124: ВВГнгд 3х1,5 кабель | H124: Кабель | I124: м.п | J124: 83 | L124: 57 | M124: =J124*K124 -> 0 | N124: =J124*L124 -> 4731 | O124: =N124+M124 -> 4731
A125: 5.2.5 | B125: Строительные материалы | C125: Матеріал | D125: Виробництво/Будівництво | E125: Электрика/Подогрев | F125: 5.2.5 | G125: Труба ПВХ гнучка гофр. 20мм | H125: Труба гофра | I125: м | J125: 100 | L125: 20 | M125: =J125*K125 -> 0 | N125: =J125*L125 -> 2000 | O125: =N125+M125 -> 2000
A126: 5.2.6 | B126: Строительные материалы | C126: Матеріал | D126: Виробництво/Будівництво | E126: Электрика/Подогрев | F126: 5.2.6 | G126: Модульний автомат ... 10А | H126: Диференційний автомат | I126: шт | J126: 2 | L126: 131 | M126: =J126*K126 -> 0 | N126: =J126*L126 -> 262 | O126: =N126+M126 -> 262
A127: 5.2.7 | B127: Строительные материалы | C127: Матеріал | D127: Виробництво/Будівництво | E127: Электрика/Подогрев | F127: 5.2.7 | G127: Модульний автомат ... 16А | H127: Диференційний автомат | I127: шт | J127: 6 | L127: 142.5 | M127: =J127*K127 -> 0 | N127: =J127*L127 -> 855 | O127: =N127+M127 -> 855
A128: 5.2.8 | B128: Строительные материалы | C128: Матеріал | D128: Виробництво/Будівництво | E128: Электрика/Подогрев | F128: 5.2.8 | G128: Модульний автомат ... 25А | H128: Диференційний автомат | I128: шт | J128: 2 | L128: 137.65 | M128: =J128*K128 -> 0 | N128: =J128*L128 -> 275.3 | O128: =N128+M128 -> 275.3
A129: 5.2.9 | B129: Строительные материалы | C129: Матеріал | D129: Виробництво/Будівництво | E129: Электрика/Подогрев | F129: 5.2.9 | G129: Шина нульова | H129: Шина нульова на ізоляторі | I129: шт | J129: 2 | L129: 96 | M129: =J129*K129 -> 0 | N129: =J129*L129 -> 192 | O129: =N129+M129 -> 192
A130: 5.2.10 | B130: Строительные материалы | C130: Матеріал | D130: Виробництво/Будівництво | E130: Электрика/Подогрев | F130: 5.2.10 | G130: Розподільча коробка 100*100*45 | H130: Розподільча коробка | I130: шт | J130: 6 | L130: 107 | M130: =J130*K130 -> 0 | N130: =J130*L130 -> 642 | O130: =N130+M130 -> 642
A131: 5.2.11 | B131: Строительные материалы | C131: Матеріал | D131: Виробництво/Будівництво | E131: Электрика/Подогрев | F131: 5.2.11 | G131: Клема з'єднувальна WGn-2 | H131: Клема з'єднувальна | I131: шт | J131: 15 | L131: 9.23 | M131: =J131*K131 -> 0 | N131: =J131*L131 -> 138.45 | O131: =N131+M131 -> 138.45
A132: 5.2.12 | B132: Строительные материалы | C132: Матеріал | D132: Виробництво/Будівництво | E132: Электрика/Подогрев | F132: 5.2.12 | G132: Клема з'єднувальна WGn-3 | H132: Клема з'єднувальна | I132: шт | J132: 14 | L132: 12.36 | M132: =J132*K132 -> 0 | N132: =J132*L132 -> 173.04 | O132: =N132+M132 -> 173.04
... A154: 5.2.34 | B154: Строительные материалы | C154: Матеріал | D154: Виробництво/Будівництво | E154: Электрика/Подогрев | F154: 5.2.34 | G154: АВР | H154: АВР | I154: шт | J154: 1 | L154: 2760 | M154: =J154*K154 -> 0 | N154: =J154*L154 -> 2760 | O154: =N154+M154 -> 2760
A155: 5.2.35 | B155: Строительные материалы | C155: Матеріал | D155: Виробництво/Будівництво | E155: Электрика/Подогрев | F155: 5.2.35 | G155: Обігрівач керамічний | H155: Обігрівач | I155: шт | J155: 7 | L155: 2500 | M155: =J155*K155 -> 0 | N155: =J155*L155 -> 17500 | O155: =N155+M155 -> 17500 | P155: =SUM(O121:O155) -> 63656.19 | Q155: +
...

Sheet IRC 30 m2
G2: =VLOOKUP(#REF!,[3]СВОД!$B$4:$D$4,3,0) -> #REF!
A3: Найменування матеріалів | C3: Од. вим. | D3: Кількість | E3: Вартість матеріалів за од., грн. з ПДВ | F3: Разом вартість матеріалів, грн. з ПДВ | G3: Вартість 1 м.кв. грн
A4: 7 | C4: 8 | D4: 9 | E4: 10 | F4: 11
A5: Каркас
A6: Труба металева Ст3 100*100*3 | B6: Профільна труба | C6: м.п | D6: =100.4-20 -> 80.4 | E6: 473 | F6: =E6*D6 -> 38029.2
A7: Труба металева Ст3 50*50*2 | B7: Профільна труба | C7: м.п. | D7: =290-50 -> 240 | E7: 157 | F7: =E7*D7 -> 37680
A8: Труба металева Ст3 дв 40 *3,5 | B8: Профільна труба | C8: м.п | D8: 2.5 | E8: 151 | F8: =E8*D8 -> 377.5
A9: Труба металева Ст3 дв 89 *3,5 | B9: Профільна труба | C9: м.п. | D9: 2 | E9: 339 | F9: =E9*D9 -> 678
A10: Лист 4мм | B10: лист ГК | C10: м.кв. | D10: 1.02 | E10: 1207 | F10: =E10*D10 -> 1231.14
A11: Лист 8мм | B11: лист ГК | C11: м.кв. | D11: 1.215 | E11: 2487 | F11: =E11*D11 -> 3021.705
A12: Лист 14мм | B12: лист ГК | C12: м.кв. | D12: 0.24 | E12: 4976 | F12: =E12*D12 -> 1194.24
A13: Гайка М48 | B13: Гайка | C13: шт | D13: 11 | E13: 350 | F13: =E13*D13 -> 3850
A14: Шпилька М48 довжина 1000 мм | B14: Шпилька | C14: шт | D14: 5 | E14: 3600 | F14: =E14*D14 -> 18000
A15: Гайка М24 | B15: Гайка | C15: шт | D15: 28 | E15: 154 | F15: =E15*D15 -> 4312
A16: Болт М24х200 | B16: Болт | C16: шт | D16: 9 | E16: 168 | F16: =E16*D16 -> 1512
A17: Труба 40*40*3 | B17: Профільна труба | C17: м.п. | D17: 141 | E17: 165 | F17: =E17*D17 -> 23265
A18: кутик 32*32 *3 | B18: Кутики сталеві | C18: м.п. | D18: 10 | E18: 62 | F18: =E18*D18 -> 620
A19: пвл 406 1,25*2,5 | B19: МШП | C19: лист | D19: 2 | E19: 1799.27 | F19: =E19*D19 -> 3598.54
... A46: Шуруп з пером 5,5*90 | B46: Саморіз | C46: шт | D46: 275 | E46: 1.03 | F46: =E46*D46 -> 283.25
A47: Загальна сума | F47: =SUM(F6:F46) -> 236595.13
A48: Отделка
A49: Вітробарєр | B49: Мембрана | C49: м2 | D49: 82 | E49: 29 | F49: =E49*D49 -> 2378
A50: Паро-гідро бар'єр | B50: Мембрана | C50: м2 | D50: 210 | E50: 13 | F50: =E50*D50 -> 2730
A51: Пінопласт товщина 50 мм | B51: Пінопласт | C51: м2 | D51: 88 | E51: 112 | F51: =E51*D51 -> 9856
A52: Мінеральна вата (100 мм) | B52: мінеральна вата | C52: м2 | D52: 100 | E52: 180 | F52: =E52*D52 -> 18000
A53: Мінеральна вата (50 мм) | B53: мінеральна вата | C53: м2 | D53: 341 | E53: 90 | F53: =E53*D53 -> 30690
A54: ЦСП панель 20 мм | B54: Плита ЦСП | C54: шт | D54: 9 | E54: 7700 | F54: =E54*D54 -> 69300
A55: Лінолеум комерційний на підлогу | B55: Лінолеум | C55: м2 | D55: 36 | E55: 515 | F55: =E55*D55 -> 18540
A56: Лінолеум на стіни | B56: Лінолеум | C56: м2 | D56: 160 | E56: 429 | F56: =E56*D56 -> 68640
A57: Клей для лінолеума | B57: Клей для лінолеума | C57: кг | D57: 35 | E57: 540 | F57: =E57*D57 -> 18900
A58: Плінтус 100 | B58: Плінтус | C58: м.п | D58: 75 | E58: 132.58 | F58: =E58*D58 -> 9943.5
A59: ПВХ вагонка 8мм біла | B59: ПВХ вагонка | C59: м2 | D59: 36 | E59: 229 | F59: =E59*D59 -> 8244
A60: Меблевий кутик | B60: Кутики пластикові | C60: м.п | D60: 92 | E60: 139.26 | F60: =E60*D60 -> 12811.92
... A69: Піна клей | B69: Піна клей | C69: шт | D69: 6 | E69: 293 | F69: =E69*D69 -> 1758
A70: Загальна сума | F70: =SUM(F49:F69) -> 325398.42
A71: Фасад
A72: Порфлист ПК 8 | B72: Профнастил | C72: м2 | D72: 33 | E72: 286 | F72: =E72*D72 -> 9438
A73: Порфлист ПК 20 Покрівля | B73: Профнастил | C73: м2 | D73: 43.2 | E73: 289 | F73: =E73*D73 -> 12484.8
A74: Порфлист ПК 10 Стіни | B74: Профнастил | C74: м2 | D74: 100 | E74: 281 | F74: =E74*D74 -> 28100
A75: Гладкий лист білий | B75: Гладкий лист метал | C75: м2 | D75: 44 | E75: 277 | F75: =E75*D75 -> 12188
A76: Ринва | B76: Ринва | C76: шт | D76: 6 | E76: 403 | F76: =E76*D76 -> 2418
A77: труба | B77: Труба | C77: шт | D77: 4 | E77: 442 | F77: =E77*D77 -> 1768
A78: Злив лівий | B78: Злив | C78: шт | D78: 2 | E78: 495 | F78: =E78*D78 -> 990
A79: Злив правий | B79: Злив | C79: шт | D79: 2 | E79: 495 | F79: =E79*D79 -> 990
A80: Відвід 45 | B80: Відвід | C80: шт | D80: 4 | E80: 196 | F80: =E80*D80 -> 784
A81: кріплення ринви | B81: Кріплення | C81: шт | D81: 20 | E81: 123 | F81: =E81*D81 -> 2460
A82: кріплення труби | B82: Кріплення | C82: шт | D82: 8 | E82: 206 | F82: =E82*D82 -> 1648
A83: зєднувачі ринви | B83: З'єднувач | C83: шт | D83: 4 | E83: 365 | F83: =E83*D83 -> 1460
A84: Загальна сума | F84: =SUM(F72:F83) -> 74728.8
A85: Окна/двери
A86: Вікно металопластик 870*1140 | B86: Вікно металопластикове | C86: шт | D86: 6 | E86: 8500 | F86: =E86*D86 -> 51000
A87: Вхідні двері металеві | B87: Вхідні двері металеві | C87: шт | D87: 1 | E87: 25000 | F87: =E87*D87 -> 25000
A88: Двері внутрішні металопластикові | B88: Внутрішні двері металопластикові | C88: шт | D88: 3 | E88: 10000 | F88: =E88*D88 -> 30000
A89: Підвіконик ПВХ | B89: Підвіконик | C89: шт | D89: 6 | E89: 573 | F89: =E89*D89 -> 3438
A90: Піна монтажна | B90: Піна монтажна | C90: балон | D90: 8 | E90: 297 | F90: =E90*D90 -> 2376
A92: Загальна сума | F92: =SUM(F86:F91) -> 111814
A93: Электрика/Подогрев
A94: Щиток пластиковий зовнішній | B94: Розподільчий щит | C94: шт | D94: 2 | E94: 928 | F94: =E94*D94 -> 1856
A95: ВВГнгд 3х4 кабель | B95: Кабель | C95: м.п | D95: 50 | E95: 75.27 | F95: =E95*D95 -> 3763.5
A96: ВВГнгд 3х2,5 кабель | B96: Кабель | C96: м.п | D96: 120 | E96: 72 | F96: =E96*D96 -> 8640
A97: ВВГнгд 3х1,5 кабель | B97: Кабель | C97: м.п | D97: 83 | E97: 57 | F97: =E97*D97 -> 4731
A98: Труба ПВХ гнучка гофр. 20мм | B98: Труба гофра | C98: м | D98: 100 | E98: 20 | F98: =E98*D98 -> 2000
A99: Модульний автомат ... 10А | B99: Диференційний автомат | C99: шт | D99: 2 | E99: 131 | F99: =E99*D99 -> 262
A100: Модульний автомат ... 16А | B100: Диференційний автомат | C100: шт | D100: 6 | E100: 142.5 | F100: =E100*D100 -> 855
A101: Модульний автомат ... 25А | B101: Диференційний автомат | C101: шт | D101: 2 | E101: 137.65 | F101: =E101*D101 -> 275.3
A102: Шина нульова | B102: Шина | C102: шт | D102: 2 | E102: 96 | F102: =E102*D102 -> 192
A103: Розподільча коробка 100*100*45 | B103: Розподільча коробка | C103: шт | D103: 6 | E103: 107 | F103: =E103*D103 -> 642
A104: Клема з'єднувальна WGn-2 | B104: Клема | C104: шт | D104: 15 | E104: 9.23 | F104: =E104*D104 -> 138.45
A105: Клема з'єднувальна WGn-3 | B105: Клема | C105: шт | D105: 14 | E105: 12.36 | F105: =E105*D105 -> 173.04
... A128: Обігрівач керамічний | B128: Обігрівач | C128: шт | D128: 7 | E128: 2500 | F128: =E128*D128 -> 17500
A129: Загальна сума | F129: =SUM(F94:F128) -> 63656.19
A130: Сантехника
A131: Труба ПВХ д32 (500мм) | B131: Труба каналізаційна | C131: шт | D131: 1 | E131: 115 | F131: =E131*D131 -> 115
A132: Труба ПВХ д32 (1000мм) | B132: Труба каналізаційна | C132: шт | D132: 1 | E132: 201 | F132: =E132*D132 -> 201
A133: Труба ПВХ д110 (500мм) | B133: Труба каналізаційна | C133: шт | D133: 1 | E133: 305 | F133: =E133*D133 -> 305
A134: Труба ПВХ д110 (3000мм) | B134: Труба каналізаційна | C134: шт | D134: 1 | E134: 622 | F134: =E134*D134 -> 622
A135: Відвід ПВХ д110 45 | B135: Відвід | C135: шт | D135: 6 | E135: 260 | F135: =E135*D135 -> 1560
A136: Відвід ПВХ д32 87 | B136: Відвід | C136: шт | D136: 2 | E136: 98 | F136: =E136*D136 -> 196
A137: Сантехнічна редукція 50х32 | B137: Перехід | C137: шт | D137: 1 | E137: 87 | F137: =E137*D137 -> 87
A138: Перехід ексентричний 110х50 | B138: Перехід | C138: шт | D138: 1 | E138: 129 | F138: =E138*D138 -> 129
A139: Трійник д110 87 | B139: Трійник | C139: шт | D139: 1 | E139: 268 | F139: =E139*D139 -> 268
A140: Трійник д32 87 | B140: Трійник | C140: шт | D140: 1 | E140: 87 | F140: =E140*D140 -> 87
A141: Заглушка д110 | B141: Заглушка | C141: шт | D141: 1 | E141: 125 | F141: =E141*D141 -> 125
A142: Манжена для унітаза | B142: Манжета | C142: шт | D142: 1 | E142: 176.4 | F142: =E142*D142 -> 176.4
... A166: Кріплення умивальника | B166: Кріплення | C166: шт | D166: 1 | E166: 66 | F166: =E166*D166 -> 66
A167: Загальна сума | F167: =SUM(F131:F166) -> 46841.4
A168: Дополнительная Комплектация
A169: Вогнегасник (порошок 3 кг) | B169: Вогнегасник | C169: шт | D169: 2 | E169: 560 | F169: =E169*D169 -> 1120
A170: Протипожежна ковдра | B170: Протипожежна ковдра | C170: шт | D170: 1 | E170: 460 | F170: =E170*D170 -> 460
A171: Килимок всередині | B171: Килимок | C171: шт | D171: 1 | E171: 500 | F171: =E171*D171 -> 500
A172: Кондиціонер | B172: Кондиционер | C172: шт | D172: 1 | E172: 17000 | F172: =E172*D172 -> 17000
A173: Стільці для відвідувачів і персоналу | B173: Стілець | C173: шт | D173: 8 | E173: 1500 | F173: =E173*D173 -> 12000
A174: Сигналізація виявлення диму | B174: Сигналізація виявлення диму | C174: шт | D174: 4 | E174: 340 | F174: =E174*D174 -> 1360
A175: Дозатор рідкого мила | B175: Дозатор | C175: шт | D175: 1 | E175: 587 | F175: =E175*D175 -> 587
A176: Дозатор рушників | B176: Дозатор | C176: шт | D176: 1 | E176: 360 | F176: =E176*D176 -> 360
A177: Стіл офісний | B177: Стіл | C177: шт | D177: 1 | E177: 3460 | F177: =E177*D177 -> 3460
A178: Кушетка медична | B178: Кушетка | C178: шт | D178: 1 | E178: 6700 | F178: =E178*D178 -> 6700
A179: Вішалка для одягу стояча | B179: Вішалка | C179: шт | D179: 1 | E179: 1500 | F179: =E179*D179 -> 1500
A180: Столик для огляду/ сповивання | B180: Столик медичний | C180: шт | D180: 1 | E180: 7800 | F180: =E180*D180 -> 7800
... A188: Копмлпект септика | B188: Септик | C188: шт | D188: 1 | E188: 12000 | F188: =E188*D188 -> 12000
...

Sheet IRC 15 m2
G2: =VLOOKUP(#REF!,[3]СВОД!$B$4:$D$4,3,0) -> #REF!
A3: Найменування матеріалів | B3: Уніфікації | C3: Од. вим. | D3: Кількість | E3: Вартість матеріалів за од., грн. з ПДВ | F3: Разом вартість матеріалів, грн. з ПДВ | G3: Вартість 1 м.кв. грн
A4: 7 | C4: 8 | D4: 9 | E4: 10 | F4: 11
A5: Каркас
A6: Труба металева Ст3 100*100*3 | B6: Профільна труба | C6: м.п | D6: 50.2 | E6: 473 | F6: =E6*D6 -> 23744.6
A7: Труба металева Ст3 50*50*2 | B7: Профільна труба | C7: м.п. | D7: 175.2 | E7: 157 | F7: =E7*D7 -> 27506.4
A8: Труба металева Ст3 дв 40 *3,5 | B8: Профільна труба | C8: м.п | D8: 1.2 | E8: 151 | F8: =E8*D8 -> 181.2
A9: Труба металева Ст3 дв 89 *3,5 | B9: Профільна труба | C9: м.п. | D9: 1 | E9: 339 | F9: =E9*D9 -> 339
A10: Лист 4мм | B10: Лист ГК | C10: м.кв. | D10: 0.68 | E10: 1207 | F10: =E10*D10 -> 820.76
A11: Лист 8мм | B11: Лист ГК | C11: м.кв. | D11: 1.215 | E11: 2487 | F11: =E11*D11 -> 3021.705
A12: Лист 14мм | B12: Лист ГК | C12: м.кв. | D12: 0.12 | E12: 4976 | F12: =E12*D12 -> 597.12
A13: Гайка М48 | B13: Гайка | C13: шт | D13: 6 | E13: 1740 | F13: =E13*D13 -> 10440
A14: Шпилька М48 довжина 1000 мм | B14: Шпилька | C14: шт | D14: 3 | E14: 3600 | F14: =E14*D14 -> 10800
A15: Гайка М24 | B15: Гайка | C15: шт | D15: 14 | E15: 154 | F15: =E15*D15 -> 2156
A16: Болт М24х200 | B16: Болт | C16: шт | D16: 4 | E16: 168 | F16: =E16*D16 -> 672
A17: Труба 40*40*3 | B17: Профільна труба | C17: м.п. | D17: 72 | E17: 165 | F17: =E17*D17 -> 11880
... A46: Шуруп з пером 5,5*90 | B46: Саморіз | C46: шт | D46: 135 | E46: 1.03 | F46: =E46*D46 -> 139.05
A47: Загальна сума | F47: =SUM(F6:F46) -> 152085.49
A48: Отделка
A49: Вітробарєр | B49: Вітробарєр | C49: м2 | D49: 42 | E49: 29 | F49: =E49*D49 -> 1218
A50: Паро-гідро бар'єр | B50: Паробар'єр | C50: м2 | D50: 120 | E50: 13 | F50: =E50*D50 -> 1560
A51: Пінопласт товщина 50 мм | B51: Пінопласт | C51: м2 | D51: 44 | E51: 88 | F51: =E51*D51 -> 3872
A52: Мінеральна вата (100 мм) | B52: Мінеральна вата | C52: м2 | D52: 55 | E52: 176 | F52: =E52*D52 -> 9680
A53: Мінеральна вата (50 мм) | B53: Мінеральна вата | C53: м2 | D53: 171 | E53: 77 | F53: =E53*D53 -> 13167
A54: ЦСП панель 20 мм | B54: Плита ЦСП | C54: шт | D54: 5 | E54: 7700 | F54: =E54*D54 -> 38500
A55: Лінолеум комерційний на підлогу | B55: Лінолеум | C55: м2 | D55: 18 | E55: 515 | F55: =E55*D55 -> 9270
A56: Лінолеум на стіни | B56: Лінолеум | C56: м2 | D56: 80.1 | E56: 429 | F56: =E56*D56 -> 34362.9
A57: Клей для лінолеума | B57: Клей для лінолеума | C57: кг | D57: 26 | E57: 321.37 | F57: =E57*D57 -> 8355.62
A58: Плінтус | B58: Плінтус | C58: м.п | D58: 35 | E58: 132.58 | F58: =E58*D58 -> 4640.3
A59: ПВХ вагонка 8мм біла | B59: ПВХ вагонка | C59: м2 | D59: 18 | E59: 229 | F59: =E59*D59 -> 4122
A60: Меблевий кутик | B60: Кутик меблевий | C60: м.п | D60: 84 | E60: 75 | F60: =E60*D60 -> 6300
... A69: Піна клей | B69: Піна клей | C69: шт | D69: 4 | E69: 293 | F69: =E69*D69 -> 1172
A70: Загальна сума | F70: =SUM(F49:F69) -> 163888.82
A71: Фасад
A72: Порфлист ПК 8 | B72: Профнастил | C72: м2 | D72: 16.5 | E72: 286 | F72: =E72*D72 -> 4719
A73: Порфлист ПК 20 Покрівля | B73: Профнастил | C73: м2 | D73: 21 | E73: 289 | F73: =E73*D73 -> 6069
A74: Порфлист ПК 10 Стіни | B74: Профнастил | C74: м2 | D74: 105 | E74: 281 | F74: =E74*D74 -> 29505
A75: Гладкий лист білий | B75: Гладкий лист метал | C75: м2 | D75: 23 | E75: 277 | F75: =E75*D75 -> 6371
A76: Ринва | B76: Ринва | C76: шт | D76: 3 | E76: 403 | F76: =E76*D76 -> 1209
A77: труба | B77: Труба водостічна | C77: шт | D77: 2 | E77: 442 | F77: =E77*D77 -> 884
A78: Злив лівий | B78: Злив лівий | C78: шт | D78: 2 | E78: 495 | F78: =E78*D78 -> 990
A79: Злив правий | B79: Злив правий | C79: шт | D79: 1 | E79: 495 | F79: =E79*D79 -> 495
A80: Відвід 45 | B80: Відвід | C80: шт | D80: 2 | E80: 196 | F80: =E80*D80 -> 392
A81: кріплення ринви | B81: Кріплення ринви | C81: шт | D81: 8 | E81: 123 | F81: =E81*D81 -> 984
A82: кріплення труби | B82: Кріплення труби | C82: шт | D82: 4 | E82: 206 | F82: =E82*D82 -> 824
A83: зєднувачі ринви | B83: З'єднувач ринви | C83: шт | D83: 2 | E83: 365 | F83: =E83*D83 -> 730
A84: Загальна сума | F84: =SUM(F72:F83) -> 53172
A85: Окна/двери
A86: Вікно металопластик 870*1140 | B86: Вікно металопластикове | C86: шт | D86: 3 | E86: 10240 | F86: =E86*D86 -> 30720
A87: Вхідні двері металеві | B87: Вхідні двері металеві | C87: шт | D87: 1 | E87: 31000 | F87: =E87*D87 -> 31000
A88: Двері внутрішні | B88: Внутрішні двері металопластикові | C88: шт | D88: 3 | E88: 12823 | F88: =E88*D88 -> 38469
A89: Підвіконик ПВХ | B89: Підвіконик ПВХ | C89: шт | D89: 3 | E89: 573 | F89: =E89*D89 -> 1719
A90: Піна монтажна | B90: Піна монтажна | C90: балон | D90: 3 | E90: 297 | F90: =E90*D90 -> 891
A91: Загальна сума | F91: =SUM(F86:F90) -> 102799
A92: Электрика/Подогрев
A93: Щиток пластиковий | B93: Розподільчий щит | C93: шт | D93: 1 | E93: 928.01 | F93: =E93*D93 -> 928.01
A94: ВВГнгд 3х4 кабель | B94: Кабель | C94: м.п | D94: 30 | E94: 75.27 | F94: =E94*D94 -> 2258.1
A95: ВВГнгд 3х2,5 | B95: Кабель | C95: м.п | D95: 60 | E95: 61 | F95: =E95*D95 -> 3660
A96: ВВГнгд 3х1,5 | B96: Кабель | C96: м.п | D96: 50 | E96: 55 | F96: =E96*D96 -> 2750
A97: Труба ПВХ гнучка 20мм | B97: Труба гофрована | C97: м | D97: 50 | E97: 20 | F97: =E97*D97 -> 1000
A98: Модульний автомат 10А | B98: Автоматичний вимикач | C98: шт | D98: 1 | E98: 124 | F98: =E98*D98 -> 124
A99: Модульний автомат 16А | B99: Автоматичний вимикач | C99: шт | D99: 3 | E99: 142.5 | F99: =E99*D99 -> 427.5
A100: Модульний автомат 25А | B100: Автоматичний вимикач | C100: шт | D100: 1 | E100: 137.65 | F100: =E100*D100 -> 137.65
A101: Шина нульова | B101: Шина | C101: шт | D101: 1 | E101: 96 | F101: =E101*D101 -> 96
A102: Розподільча коробка 100*100*45 | B102: Розподільча коробка | C102: шт | D102: 3 | E102: 107 | F102: =E102*D102 -> 321
A103: Клема WGn-2 | B103: Клема | C103: шт | D103: 8 | E103: 9.23 | F103: =E103*D103 -> 73.84
A104: Клема WGn-3 | B104: Клема | C104: шт | D104: 7 | E104: 12.36 | F104: =E104*D104 -> 86.52
... A127: Обігрівач керамічний | B127: Обігрівач | C127: шт | D127: 4 | E127: 2500 | F127: =E127*D127 -> 10000
A128: Загальна сума | F128: =SUM(F93:F127) -> 38947.35
A129: Сантехника
A130: Труба ПВХ д32 (500мм) | B130: Труба каналізаційна | C130: шт | D130: 1 | E130: 115 | F130: =E130*D130 -> 115
A131: Труба ПВХ д32 (1000мм) | B131: Труба каналізаційна | C131: шт | D131: 1 | E131: 201 | F131: =E131*D131 -> 201
A132: Труба ПВХ д110 (500мм) | B132: Труба каналізаційна | C132: шт | D132: 1 | E132: 305 | F132: =E132*D132 -> 305
A133: Труба ПВХ д110 (3000мм) | B133: Труба каналізаційна | C133: шт | D133: 1 | E133: 622 | F133: =E133*D133 -> 622
A134: Відвід ПВХ д110 45 | B134: Відвід каналізаційний | C134: шт | D134: 3 | E134: 260 | F134: =E134*D134 -> 780
A135: Відвід ПВХ д32 87 | B135: Відвід каналізаційний | C135: шт | D135: 2 | E135: 98 | F135: =E135*D135 -> 196
A136: Сантехнічна редукція 50х32 | B136: Редукція | C136: шт | D136: 1 | E136: 87 | F136: =E136*D136 -> 87
A137: Перехід ексентричний 110х50 | B137: Перехід | C137: шт | D137: 1 | E137: 129 | F137: =E137*D137 -> 129
A138: Трійник д110 87 | B138: Трійник | C138: шт | D138: 1 | E138: 268 | F138: =E138*D138 -> 268
A139: Трійник д32 87 | B139: Трійник | C139: шт | D139: 1 | E139: 87 | F139: =E139*D139 -> 87
A140: Заглушка д110 | B140: Заглушка | C140: шт | D140: 1 | E140: 125 | F140: =E140*D140 -> 125
A141: Манжена для унітаза | B141: Манжета | C141: шт | D141: 1 | E141: 176.4 | F141: =E141*D141 -> 176.4
... A165: Кріплення умивальника | B165: Кріплення | C165: шт | D165: 1 | E165: 66 | F165: =E165*D165 -> 66
A166: Загальна сума | F166: =SUM(F130:F165) -> 39849.4
A167: Дополнительная Комплектация
A168: Вогнегасник (порошок 3 кг) | B168: Вогнегасник | C168: шт | D168: 1 | E168: 560 | F168: =E168*D168 -> 560
A169: Протипожежна ковдра | B169: Протипожежна ковдра | C169: шт | D169: 1 | E169: 460 | F169: =E169*D169 -> 460
A170: Килимок всередині | B170: Килимок | C170: шт | D170: 1 | E170: 500 | F170: =E170*D170 -> 500
A171: Кондиціонер | B171: Кондиціонер | C171: шт | D171: 1 | E171: 17000 | F171: =E171*D171 -> 17000
A172: Стільці для відвідувачів | B172: Стілець | C172: шт | D172: 3 | E172: 1500 | F172: =E172*D172 -> 4500
A173: Сигналізація виявлення диму | B173: Сигналізація виявлення диму | C173: шт | D173: 3 | E173: 340 | F173: =E173*D173 -> 1020
A174: Дозатор рідкого мила | B174: Дозатор рідкого мила | C174: шт | D174: 1 | E174: 587 | F174: =E174*D174 -> 587
A175: Дозатор рушників | B175: Дозатор рушників | C175: шт | D175: 1 | E175: 360 | F175: =E175*D175 -> 360
A176: Стіл офісний | B176: Стіл | C176: шт | D176: 1 | E176: 3460 | F176: =E176*D176 -> 3460
A177: Кушетка медична | B177: Кушетка медична | C177: шт | D177: 1 | E177: 6700 | F177: =E177*D177 -> 6700
A178: Вішалка для одягу стояча | B178: Вішалка для одягу | C178: шт | D178: 1 | E178: 1500 | F178: =E178*D178 -> 1500
A179: Столик для огляду/ сповивання | B179: Столик медичний | C179: шт | D179: 1 | E179: 7800 | F179: =E179*D179 -> 7800
... A187: Копмлпект септика | B187: Септик | C187: шт | D187: 1 | E187: 12000 | F187: =E187*D187 -> 12000
A188: Загальна сума | F188: =SUM(F168:F187) -> 155087
A189: Загальна вартість матеріалів грн з ПДВ | F189: =F188+F166+F128+F91+F84+F70+F47 -> 705829.06
...

Sheet Склади Стіл
A1: Склад | E1: Количество | F1: Сумма | G1: Количество для списания
A2: Рахунок | B2: Номенклатура код | C2: Номенклатура | D2: Единица | H2: Узагальнена назва | I2: ТИП
A3: СТІЛ _Червоний хрест | E3: 148.392 | F3: 306596.47
A4: 0221 | B4: 00-00016761 | C4: Водонагрівач 80л | D4: шт | E4: 2 | F4: 25520 | H4: Бойлер електричний | I4: Сантехніка
A5: 0221 | B5: 00-00017550 | C5: Двері вхідні 2050х860 металеві Л | D5: шт | E5: 2 | F5: 14866.6 | H5: Вхідні двері металеві | I5: вікна та двері
A6: 0221 | B6: 00-00017549 | C6: Двері вхідні 2050х860 металеві П | D6: шт | E6: 4 | F6: 29733.4 | H6: Вхідні двері металеві | I6: вікна та двері
A7: 0221 | B7: 00-00005567 | C7: Диспенсер туалетного папіру | D7: шт | E7: 2 | F7: 1308 | H7: Диспенсер для туалетного паперу | I7: Дополнительная Комплектация
A8: 0221 | B8: 00000006816 | C8: Дозатор для мила | D8: шт | E8: 2 | F8: 1374 | H8: Диспенсер рідкого мила | I8: Дополнительная Комплектация
A9: 0221 | B9: 00-00005396 | C9: Душова система | D9: шт | E9: 2 | F9: 8653.33 | H9: Змішувач для душу | I9: Сантехніка
A10: 0221 | B10: 00-00017539 | C10: Емаль ЕП-140 сіра, кг | D10: кг | E10: 50 | F10: 7291.5 | H10: фарба | I10: Каркас та конструкції
A11: 0221 | B11: 00000006819 | C11: Йоршик | D11: шт | E11: 2 | F11: 445 | H11: Йоршик | I11: Дополнительная Комплектация
A12: 0221 | B12: 00-00011895 | C12: Кріплення для телевізора | D12: шт | E12: 4 | F12: 4623.33 | H12: Кріплення для телевізора | I12: Дополнительная Комплектация
A13: 0221 | B13: 00-00017537 | C13: Кронштейн для мікрохвильвої печі | D13: шт | E13: 4 | F13: 2776.67 | H13: Кріплення для мікрохвильової печі | I13: Дополнительная Комплектация
A14: 0221 | B14: 00-00017255 | C14: Кутник 200х200х14 L=6 ст 1-3 сп/пс 5 | D14: т | E14: 2.02 | F14: 84587.5 | H14: Кутик | I14: Каркас та конструкції
A15: 0221 | B15: 00000012186 | C15: Кутник 63х63х5 L=6000 | D15: т | E15: 0.055 | F15: 1588.25 | H15: Кутик | I15: Каркас та конструкції
... A27: 0221 | B27: 00-00015078 | C27: Швелер 12 UPEAA | D27: т | E27: 0.265 | F27: 8338.53 | H27: Швелер | I27: Каркас та конструкції
A28: СТІЛ Виробничий склад | E28: 269.917 | F28: 54236.46
A29: 203 | B29: 00-00000320 | C29: Бензин А-95 | D29: л | E29: 14.2 | F29: 780.72
A30: 201 | B30: 00-00003742 | C30: Гіпсокартон KNAUF 12,5 мм х 1,2 х 2,5 м | D30: шт | E30: 1 | F30: 416 | H30: ГКЛ | I30: Отделка
A31: 201 | B31: 00-00006387 | C31: Добавка для фарби 1 л | D31: шт | E31: 2 | F31: 138 | H31: фарба | I31: Отделка
A32: 201 | B32: 00000010866 | C32: Емаль алкідна ПФ-115 М чорна 0,9 л | D32: шт | E32: 1 | F32: 118 | H32: фарба | I32: Каркас та конструкції
A33: 201 | B33: 00000020666 | C33: Емаль алкідна ПФ-115 червона 2,8 кг | D33: шт | E33: 1 | F33: 435 | H33: фарба | I33: Каркас та конструкції
A34: 201 | B34: 00000000102 | C34: З'єднувач PP-R D=20 mm. х1\2 Н сірий | D34: шт | E34: 3 | F34: 144.36 | H34: З'єднувач PP-R | I34: Сантехніка
A35: 201 | B35: 00000003426 | C35: Замок навісний | D35: шт | E35: 2 | F35: 386 | H35: мшп | I35: МШП
A36: 201 | B36: 00000002631 | C36: Кабель КГ 1х16 | D36: км | E36: 0.02 | F36: 1855.92 | H36: мшп | I36: МШП
A37: 201 | B37: 00-00010543 | C37: Кабель КГ 1х50 | D37: км | E37: 0.012 | F37: 3406.03 | H37: мшп | I37: МШП
A38: 221 | B38: 00-00012204 | C38: Колесо до візка *160 | D38: шт | E38: 4 | F38: 2024 | H38: мшп | I38: МШП
A39: 221 | B39: 00000007159 | C39: Круг алмазний відрізний 1A1RSS/C3-W 350х3,2/2,2*25,4 R160 Meteor Н15 | D39: шт | E39: 5 | F39: 808.35 | H39: мшп | I39: МШП
A40: 221 | B40: 00000017499 | C40: Круг відрізний по металу 125х1.6х22.2 мм прямий по металу | D40: шт | E40: 21 | F40: 384.3 | H40: Обрізні диски | I40: МШП
A41: 221 | B41: 00000017499 | C41: Круг відрізний по металу 125х1.6х22.2 мм прямий по металу | D41: шт | E41: 4 | F41: 730.4 | H41: Обрізні диски | I41: МШП
... A45: 201 | B45: 00-00009039 | C45: Накінечник DT-010 | D45: шт | E45: 8 | F45: 192 | H45: мшп | I45: МШП
A46: 221 | B46: 00000002101 | C46: Окуляри захисні | D46: шт | F46: 73.04 | H46: мшп | I46: МШП
A47: 221 | B47: 00-00015312 | C47: Олива для двохкратних двигунів | D47: шт | E47: 1 | F47: 159.2 | H47: мшп | I47: МШП
A48: 201 | B48: 00000020498 | C48: ПВС 3х2,5 дріт | D48: км | E48: 0.08 | F48: 3722.88 | H48: кабель | I48: Электрика/Подогрев
A49: 201 | B49: 00-00010574 | C49: Пісок (20кг) | D49: шт | E49: 20 | F49: 580 | H49: мшп | I49: МШП
A50: 201 | B50: 00-00010574 | C50: Пісок (20кг) | D50: шт | E50: 50 | F50: 1450 | H50: мшп | I50: МШП
A51: 201 | B51: 00-00010574 | C51: Пісок (20кг) | D51: шт | E51: 25 | F51: 725 | H51: мшп | I51: МШП
A52: 201 | B52: 00-00010574 | C52: Пісок (20кг) | D52: шт | E52: 18 | F52: 522 | H52: мшп | I52: МШП
A53: 221 | B53: 00000008993 | C53: Пістолет для підкачки коліс вантаж.авто | D53: шт | E53: 1 | F53: 275.8 | H53: мшп | I53: МШП
A54: 221 | B54: 00000020793 | C54: Прожектор світлодіодний LED 100 W FL12 чорний | D54: шт | E54: 10 | F54: 6513.1 | H54: Світильник | I54: Электрика/Подогрев
A55: 201 | B55: 00000000335 | C55: Профіль трапецієподібний ПП-20 матполіестр 7024*45 | D55: м2 | E55: 11.565 | F55: 2313.04 | H55: Профнастил | I55: фасад
A56: 201 | B56: 00-00000467 | C56: Профіль трапецієподібний ПП-45 РЕМА | D56: м2 | E56: 3.472 | F56: 694.41 | H56: Профнастил | I56: фасад
A57: 221 | B57: 00000010479 | C57: Рукавиці "Краги"зварювальні жовті | D57: пар | F57: -249.32 | H57: мшп | I57: МШП
A58: 201 | B58: 00-00003584 | C58: Труба 50х50х5 (6,05- 8940:2019 08кп/1-3пс) | D58: т | E58: 0.271 | F58: 9101.97 | H58: Профільна труба | I58: Каркас та конструкції
A59: 201 | B59: 00-00012758 | C59: Холодний асфальт | D59: шт | E59: 10 | F59: 2465.83 | H59: мшп | I59: МШП
A60: 201 | B60: 00-00010573 | C60: Цемент М-500 (25кг) | D60: шт | E60: 16 | F60: 2752 | H60: мшп | I60: МШП
A61: 201 | B61: 00-00010573 | C61: Цемент М-500 (25кг) | D61: шт | E61: 5 | F61: 860 | H61: мшп | I61: МШП
A62: 201 | B62: 00-00010573 | C62: Цемент М-500 (25кг) | D62: шт | E62: 5 | F62: 860 | H62: мшп | I62: МШП
A63: 201 | B63: 00000000416 | C63: Шайба збільшена DIN9021 10х29 (1уп=100шт) | D63: 100шт | F63: 89.44 | H63: шайба | I63: Каркас та конструкції
A64: 201 | B64: 00000000416 | C64: Шайба збільшена DIN9021 10х29 (1уп=100шт) | D64: 100шт | F64: 30.06 | H64: шайба | I64: Каркас та конструкції
A65: 201 | B65: 00000000416 | C65: Шайба збільшена DIN9021 10х29 (1уп=100шт) | D65: 100шт | F65: -33.82 | H65: шайба | I65: Каркас та конструкції
A66: СТІЛ Глобино | E66: 2251.278 | F66: 176248.03
A67: 201 | B67: 00-00000165 | C67: Грунт ГФ-021 червоно-коричневий | D67: кг | E67: 300 | F67: 17502 | H67: Грунт | I67: Каркас та конструкції
A68: 201 | B68: 00-00000165 | C68: Грунт ГФ-021 червоно-коричневий | D68: кг | E68: 300 | F68: 17502 | H68: Грунт | I68: Каркас та конструкції
A69: 201 | B69: 00-00000165 | C69: Грунт ГФ-021 червоно-коричневий | D69: кг | E69: 300 | F69: 18000 | H69: Грунт | I69: Каркас та конструкції
A70: 201 | B70: 00-00000165 | C70: Грунт ГФ-021 червоно-коричневий | D70: кг | E70: 251.778 | F70: 14688.73 | H70: Грунт | I70: Каркас та конструкції
A71: 201 | B71: 00-00000165 | C71: Грунт ГФ-021 червоно-коричневий | D71: кг | E71: 300 | F71: 17502 | H71: Грунт | I71: Каркас та конструкції
A72: 201 | B72: 00000014170 | C72: Грунт ГФ-021C червон.-коричн | D72: кг | E72: 250 | F72: 13335 | H72: Грунт | I72: Каркас та конструкції
A73: 201 | B73: 00000014170 | C73: Грунт ГФ-021C червон.-коричн | D73: кг | E73: 300 | F73: 17502 | H73: Грунт | I73: Каркас та конструкції
A74: 201 | B74: 00-00016511 | C74: Дошка 50*70 4,5 м | D74: м3 | E74: 3 | F74: 37500 | H74: Дошка | I74: Отделка
A75: 201 | B75: 00-00000166 | C75: Розчинник "White Spirit" | D75: л | E75: 50 | F75: 3283.5 | H75: Розчинник | I75: Каркас та конструкції
A76: 201 | B76: 00-00000166 | C76: Розчинник "White Spirit" | D76: л | E76: 50 | F76: 3283.5 | H76: Розчинник | I76: Каркас та конструкції
A77: 201 | B77: 00-00000166 | C77: Розчинник "White Spirit" | D77: л | E77: 42 | F77: 2827.86 | H77: Розчинник | I77: Каркас та конструкції
A78: 201 | B78: 00-00000166 | C78: Розчинник "White Spirit" | D78: л | E78: 43.5 | F78: 2856.64 | H78: Розчинник | I78: Каркас та конструкції
... A81: 201 | B81: 00-00000246 | C81: Шпилька ТМ оцинкована 20х1000 DIN975, (5шт) | D81: шт | E81: 5 | F81: 926.3 | H81: Шпилька | I81: Каркас та конструкції
A82: СТІЛ Глобино виробничий | E82: 800.832 | F82: 99401.72
A83: 201 | B83: 00000006540 | C83: Абразивний порошок (фр.0,63-2,0 мм) код 2621900000 | D83: т | E83: 2 | F83: 3265 | H83: мшп | I83: МШП
A84: 221 | B84: 00000003014 | C84: Біта РН 2*50 мм | D84: шт | E84: 1 | F84: 415.8 | H84: мшп | I84: МШП
A85: 201 | B85: 00-00015046 | C85: Брус 40*90*3 | D85: м3 | E85: 0.04 | F85: 328.2 | H85: Брус | I85: Отделка
A86: 201 | B86: 00000000570 | C86: Брус 50*50*300 | D86: куб | E86: 1.952 | F86: 16016.41 | H86: Брус | I86: Отделка
A87: 201 | B87: 00-00014841 | C87: Брус 50х70х2,25м | D87: куб | E87: 1.2 | F87: 15000 | H87: Брус | I87: Отделка
A88: 221 | B88: 00000021585 | C88: Вилка 16А каучук 2Р+Е чорна ІР44 | D88: шт | E88: 1 | F88: 36.7 | H88: Вилка переносна | I88: Электрика/Подогрев
A89: 221 | B89: 00-00000071 | C89: Відрізний диск Standard Inox 230x1,9мм арт.2608601514 | D89: шт | E89: 5 | F89: 237.5 | H89: мшп | I89: МШП
A90: 221 | B90: 00-00000071 | C90: Відрізний диск Standard Inox 230x1,9мм арт.2608601514 | D90: шт | E90: 5 | F90: 237.5 | H90: мшп | I90: МШП
A91: 221 | B91: 00-00000071 | C91: Відрізний диск Standard Inox 230x1,9мм арт.2608601514 | D91: шт | E91: 5 | F91: 237.5 | H91: мшп | I91: МШП
A92: 221 | B92: 00-00000071 | C92: Відрізний диск Standard Inox 230x1,9мм арт.2608601514 | D92: шт | E92: 5 | F92: 237.5 | H92: мшп | I92: МШП
A93: 221 | B93: 00000013492 | C93: Вставка для масок 110*90, затемнення DIN12/C6 | D93: шт | E93: 1 | F93: 12.5 | H93: мшп | I93: МШП
A94: 221 | B94: 00000000666 | C94: Газовий дифузор керамічний | D94: шт | E94: 2 | F94: 44 | H94: мшп | I94: МШП
A95: 201 | B95: 00-00000165 | C95: Грунт ГФ-021 червоно-коричневий | D95: кг | E95: -2.9 | H95: Грунт | I95: Каркас та конструкції
A96: 201 | B96: 00-00000165 | C96: Грунт ГФ-021 червоно-коричневий | D96: кг | F96: -169.19 | H96: Грунт | I96: Каркас та конструкції
A97: 201 | B97: 00-00000165 | C97: Грунт ГФ-021 червоно-коричневий | D97: кг | E97: 186.9 | F97: 10903.75 | H97: Грунт | I97: Каркас та конструкції
A98: 221 | B98: 00-00013078 | C98: Диск пелюстковий 125*22,23 G60 | D98: шт | E98: 1 | F98: 29.2 | H98: мшп | I98: МШП
A99: 221 | B99: 00-00013078 | C99: Диск пелюстковий 125*22,23 G60 | D99: шт | E99: 1 | F99: 29.2 | H99: мшп | I99: МШП
A100: 221 | B100: 00-00015255 | C100: Дріт 1,2 мм | D100: кг | E100: 25 | F100: 1625 | H100: Дріт | I100: МШП
A101: 221 | B101: 00-00015255 | C101: Дріт 1,2 мм | D101: кг | E101: 30 | F101: 1950 | H101: Дріт | I101: МШП
A102: 221 | B102: 00-00015255 | C102: Дріт 1,2 мм | D102: кг | E102: 15 | F102: 975 | H102: Дріт | I102: МШП
A103: 221 | B103: 00-00015255 | C103: Дріт 1,2 мм | D103: кг | E103: 15 | F103: 975 | H103: Дріт | I103: МШП
A104: 221 | B104: 00-00015255 | C104: Дріт 1,2 мм | D104: кг | E104: 45 | F104: 2925 | H104: Дріт | I104: МШП
A105: 221 | B105: 00000001670 | C105: Дріт 1,2 мм | D105: кг | E105: 10 | F105: 761.11 | H105: Дріт | I105: МШП
A106: 221 | B106: 00-00000206 | C106: Електроди Моноліт РЦ ф 3мм Уп/2.5кг (Тубус) | D106: кг | E106: 2.5 | F106: 281.25 | H106: Електроди | I106: МШП
A107: 221 | B107: 00-00000206 | C107: Електроди Моноліт РЦ ф 3мм Уп/2.5кг (Тубус) | D107: кг | E107: 5 | F107: 562.5 | H107: Електроди | I107: МШП
A108: 221 | B108: 00-00000206 | C108: Електроди Моноліт РЦ ф 3мм Уп/2.5кг (Тубус) | D108: кг | E108: 5 | F108: 562.5 | H108: Електроди | I108: МШП
... A163: 221 | B163: 00000013068 | C163: Редуктор пропановий БПО-5ДМ | D163: шт | E163: 1 | F163: 825 | H163: мшп | I163: МШП
A164: 201 | B164: 00-00000166 | C164: Розчинник "White Spirit" | D164: л | E164: -1 | H164: Розчинник | I164: Каркас та конструкції
A165: 201 | B165: 00-00000166 | C165: Розчинник "White Spirit" | D165: л | E165: 86.64 | F165: 5689.65 | H165: Розчинник | I165: Каркас та конструкції
A166: 201 | B166: 00-00000166 | C166: Розчинник "White Spirit" | D166: л | F166: -65.67 | H166: Розчинник | I166: Каркас та конструкції
A167: 221 | B167: 00000010479 | C167: Рукавиці "Краги"зварювальні жовті | D167: пар | E167: 1 | F167: 268.52 | H167: мшп | I167: МШП
A168: 221 | B168: 00000010479 | C168: Рукавиці "Краги"зварювальні жовті | D168: пар | E168: 1 | F168: 268.52 | H168: мшп | I168: МШП
A169: 221 | B169: 00000010479 | C169: Рукавиці "Краги"зварювальні жовті | D169: пар | E169: 2 | F169: 343.32 | H169: мшп | I169: МШП
A170: 221 | B170: 00000010479 | C170: Рукавиці "Краги"зварювальні жовті | D170: пар | E170: 3 | F170: 807.6 | H170: мшп | I170: МШП
...

Sheet Матеріали по СС
A1: №№ | B1: Назва згідно СС | C1: Узагальнена назва | D1: Од | E1: Тип
A2: 1 | B2: П’ЄДЕСТАЛ DECO 3922900000 | C2: П’ЄДЕСТАЛ | D2: шт | E2: Сантехніка
A3: 2 | B3: Болт кріплення для бойлера, М10х100мм ( 2шт) | C3: Болт кріплення М10х100мм | D3: шт | E3: Сантехніка
A4: 3 | B4: Гнучний шланг, 1 / 2" ВВ, довжина 30 см | C4: Гнучний шланг, 1 / 2" ВВ | D4: шт | E4: Сантехніка
A5: 4 | B5: Держак ринви | C5: Держак ринви | D5: шт | E5: фасад
A6: 5 | B6: Держак труби металевий | C6: Держак труби металевий | D6: шт | E6: фасад
A7: 6 | B7: Заглушка D=50 | C7: Заглушка | D7: шт | E7: Сантехніка
A8: 7 | B8: Залізо бетонна кришка з отвором Д1500 мм | C8: Залізо бетонна кришка Д 1500 мм | D8: шт | E8: Сантехніка
A9: 8 | B9: Залізо бетонне дно Д1500 мм | C9: Залізо бетонне дно Д 1500 мм | D9: шт | E9: Сантехніка
A10: 9 | B10: Залізо бетонне кільце Д1500 мм | C10: Залізо бетонне кільце Д 1500 мм | D10: шт | E10: Сантехніка
A11: 10 | B11: З'єднувач PP-R D=20 mm. х1\2 З | C11: З'єднувач PP-R D=20 mm. х1\2 З | D11: шт | E11: Сантехніка
A12: 11 | B12: З'єднувач ринви | C12: З'єднувач ринви | D12: шт | E12: фасад
A13: 12 | B13: Змішувач NICO, для умивальника, хром. | C13: Змішувач | D13: шт | E13: Сантехніка
... A315: 314 | B315: Злив правий | C315: Злив правий | D315: шт | E315: фасад
A316: 315 | B316: Інформаційний банер зовнішній - 2130х500мм | C316: Інформаційний банер | E316: Дополнительная Комплектация
A317: 316 | B317: Карниз кутовий 90*90 | C317: Карниз кутовий | D317: шт | E317: фасад
A318: 317 | B318: Керамічна плитка | C318: Керамічна плитка | D318: м² | E318: Отделка
A319: 318 | B319: Клей для лінолеума | C319: Клей для лінолеума | D319: кг | E319: Отделка
A320: 319 | B320: Клей для лінолеума | C320: Клей для лінолеума | D320: кг | E320: Отделка
A321: 320 | B321: Клей для ПВХ мембрани | C321: Клей для ПВХ мембрани | D321: кг | E321: Отделка
A322: 321 | B322: Клей монтажнй білий | C322: Клей монтажнй білий | D322: шт | E322: Отделка
A323: 322 | B323: Кляймер для фальш-бруса | C323: Кляймер для фальш-бруса | D323: шт | E323: Отделка
A324: 323 | B324: кріплення ринви | C324: кріплення | D324: шт | E324: фасад
A325: 324 | B325: кріплення труби | C325: кріплення | D325: шт | E325: фасад
A326: 325 | B326: Кут внутрішній | C326: Кут внутрішній | D326: шт | E326: фасад
A327: 326 | B327: Кут зовнішній | C327: Кут зовнішній | D327: шт | E327: фасад
A328: 327 | B328: Кутик 25х25х3 мм | C328: Кутики сталеві | D328: м.п | E328: Каркас та конструкції
... A334: 333 | B334: Кутики білі 50*50 мм 2,7м | C334: Кутик | D334: шт | E334: Отделка
A335: 334 | B335: Кутики, з'єднувачі, глушки | C335: з'єднувачі | E335: Отделка
A336: 335 | B336: Кутова планка внутрішня дерев'яна 15*15 (3м) | C336: Кутик | D336: м | E336: Отделка
A337: 337 | B337: Лак Паркетний | C337: Лак | D337: шт | E337: Отделка
A338: 338 | B338: Лак поліуретановий білий ТН 4701-902 | C338: Лак | D338: л | E338: Отделка
A339: 339 | B339: Ламінована ДСП плита 16мм (колір - білий); | C339: Плита ЛДСП | D339: м2 | E339: Отделка
A340: 340 | B340: ЛДСП 16 мм Swiss Krono U119 PE | C340: Плита ЛДСП | D340: м² | E340: Отделка
A341: 341 | B341: Лист 14мм | C341: лист ГК | D341: м.кв. | E341: Каркас та конструкції
A342: 342 | B342: лист 3 мм | C342: лист ГК | D342: м.кв. | E342: Каркас та конструкції
A343: 343 | B343: Лист 4 мм | C343: лист ГК | D343: тон | E343: Каркас та конструкції
A344: 344 | B344: Лист 4мм | C344: лист ГК | D344: м.кв. | E344: Каркас та конструкції
A345: 345 | B345: Лист 5 мм | C345: лист ГК | D345: м.кв. | E345: Каркас та конструкції
A346: 346 | B346: Лист 6мм | C346: лист ГК | D346: т | E346: Каркас та конструкції
A347: 347 | B347: Лист 8мм | C347: лист ГК | D347: м.кв. | E347: Каркас та конструкції
... A391: 391 | B391: Плита ЦСП 10 мм | C391: Плита OSB | D391: м² | E391: Отделка
A392: 392 | B392: Плитка керамічна | C392: Плитка керамічна | E392: Отделка
A393: 393 | B393: Плитка на стіни вінілова 200*600 | C393: Плитка вінілова | D393: шт | E393: Отделка
A394: 394 | B394: Плінтус | C394: Плінтус | D394: м.п | E394: Отделка
A395: 395 | B395: Плінтус 100 | C395: Плінтус | D395: м.п | E395: Отделка
A396: 396 | B396: Плінтус 2,5 м.п. | C396: Плінтус | D396: шт | E396: Отделка
A397: 397 | B397: Плінтус пластиковий | C397: Плінтус | D397: м | E397: Отделка
A398: 398 | B398: Полікарбонат покрівельний | C398: Полікарбонат | D398: м2 | E398: фасад
A399: 399 | B399: Порожок прижимний алюмінієвий в колір плит ЛДСП | C399: Порожок прижимний | D399: м | E399: Отделка
A400: 400 | B400: Порфлист ПК 10 Довжина 3100 мм Стіни РАЛ 9003 | C400: Профлист | D400: М.КВ. | E400: фасад
A401: 401 | B401: Порфлист ПК 10 довжина 2450 Стіни РАЛ 9003 | C401: Профлист | D401: М.КВ. | E401: фасад
A402: 402 | B402: Порфлист ПК 10 Стіни білий | C402: Профлист | D402: м2 | E402: фасад
A403: 403 | B403: Порфлист ПК 20 довжина 6070 мм Покрівля РАЛ 9003 | C403: Профлист | D403: М.КВ. | E403: фасад
A404: 404 | B404: Порфлист ПК 20 Покрівля білий | C404: Профлист | D404: м2 | E404: фасад
... A443: 443 | B443: Сендвіч панель одностороння ПВХ для укосів 10 мм | C443: Сендвіч палель | D443: м2 | E443: Отделка
A444: 444 | B444: Сітка металева | C444: Сітка металева | E444: Отделка
A445: 445 | B445: Сморіз по металу 4,2*65 з пером | C445: Саморіз | D445: шт | E445: фасад
A446: 446 | B446: Стінова сендвіч панель закритий замок зовнішня сторона металевий лист ПС20 - 0.45мм, з полімерним покриттям RAL7024 (графітовий сірий); внутрішня сторонаГладкий металевий лист 0.45мм, з полімерним покриттям RAL9003 (білий); мінеральна вата товщина 100 мм висота 2700 мм | C446: Сендвіч палель | D446: шт | E446: фасад
A447: 447 | B447: Страж (оброблення деревини) | C447: Страж (оброблення деревини) | D447: кг | E447: Каркас та конструкції
A448: 448 | B448: Стрічка К2 двостороння ширина 80 мм | C448: Стрічка К2 двостороння ширина 80 мм | D448: м.п | E448: фасад
A449: 449 | B449: Теплий відкос | C449: Теплий відкос | D449: лист | E449: Отделка
A450: 451 | B450: Труба 20*40*3 | C450: Профільна труба | D450: м.п. | E450: Каркас та конструкції
A451: 452 | B451: Труба 40*20*1,5 | C451: Профільна труба | D451: м.п. | E451: Каркас та конструкції
A452: 453 | B452: Труба 40*40*3 | C452: Профільна труба | D452: м.п. | E452: Каркас та конструкції
A453: 454 | B453: Труба 50*25*3 | C453: Профільна труба | D453: м.п. | E453: Каркас та конструкції
A454: 455 | B454: Труба 50*50*4 | C454: Профільна труба | D454: м.п. | E454: Каркас та конструкції
A455: 456 | B455: труба 75 мм | C455: труба | D455: шт | E455: Каркас та конструкції
A456: 457 | B456: Труба металева Ст3 100*100*3 | C456: Профільна труба | D456: м.п | E456: Каркас та конструкції
... A474: 475 | B474: ЦСП панель 20 мм 3,2*1,2 | C474: Плита ЦСП | D474: шт | E474: Отделка
A475: 476 | B475: Цсп плита 10 мм | C475: Плита ЦСП | E475: Отделка
A476: 477 | B476: шайба м12 | C476: Шайба | D476: шт | E476: Каркас та конструкції
A477: 478 | B477: Шайба М16 | C477: Шайба | D477: шт | E477: Каркас та конструкції
A478: 479 | B478: Шпилька М48 | C478: Шпилька | D478: м.п. | E478: Каркас та конструкції
A479: 480 | B479: Шпилька М48 довжина 1000 мм | C479: Шпилька | D479: шт | E479: Каркас та конструкції
A480: 481 | B480: Шторка для ванної PEVA Vanstore Green Point 180х200см (61008) | C480: Шторка | D480: шт | E480: Дополнительная Комплектация
A481: 482 | B481: Шуруп гартований з потаємною головкою 2.5*45 | C481: Шуруп | D481: шт | E481: Каркас та конструкції
A482: 483 | B482: Шуруп універсальний з пером по металу ЧАСТКОВА РІЗЬБА 5,5*90 | C482: Шуруп | D482: шт | E482: Каркас та конструкції
A483: 484 | B483: Шуруп універсальний цинк жов т0ий ЧАСТКОВА РІЗЬБА DIN 7997 5*70 | C483: Шуруп | D483: шт | E483: Каркас та конструкції
A484: 485 | B484: Шуруп універсальний цинк жовтий ПОВНА РІЗЬБА DIN 7997 4,5*45 | C484: Шуруп | D484: шт | E484: Каркас та конструкції
A485: 486 | B485: Біта PH1 MILWAUKEE | C485: Біта | D485: шт | E485: мшп
A486: 487 | B486: Біта PH2 MILWAUKEE | C486: Біта | D486: шт | E486: мшп
A487: 488 | B487: Біта PZ1 MILWAUKEE | C487: Біта | D487: шт | E487: мшп
... A492: 493 | B492: Болт замковий з грибовидною головкою 8х60 (1уп=25шт) повна різьба | C492: Болт | D492: шт | E492: Каркас та конструкції
A493: 494 | B493: Болты | C493: Болты | E493: Каркас та конструкції
A494: 495 | B494: Брус 70*70 | C494: Брус | D494: м3 | E494: Каркас та конструкції
A495: 496 | B495: Гайка DIN934 M 10/150шт | C495: Гайка | D495: шт | E495: Отделка
A496: 497 | B496: Гайка DIN934 M 12/100шт | C496: Гайка | D496: уп | E496: Отделка
A497: 498 | B497: Гайка DIN934 M 12/100шт збільшена | C497: Гайка | D497: шт | E497: Отделка
A498: 499 | B498: Гайка DIN934 M8/300шт. | C498: Гайка | D498: шт | E498: Отделка
A499: 500 | B499: Грунт ГФ 021 | C499: Грунт | D499: кг | E499: Каркас та конструкції
A500: 501 | B500: Диск відрізний Ø125х1 | C500: Обрізні диски | D500: шт | E500: мшп
A501: 502 | B501: Диск пильний (паркетка) | C501: Обрізні диски | D501: шт | E501: мшп
A502: 504 | B502: Дріт зварний 1 мм | C502: Дріт | D502: кг | E502: мшп
A503: 505 | B503: Електроди 3мм | C503: Електроди | D503: кг | E503: мшп
A504: 506 | B504: Електроди д3 мм | C504: Електроди | D504: кг. | E504: мшп
A505: 507 | B505: Зачисний диск пелюсток зерно 60 мікрон | C505: Зачисний диск | D505: шт | E505: мшп
... A570: 572 | B570: Порожек алюміній (оконтовка навколо решітки) | C570: Порожек алюміній | D570: м.п | E570: Отделка
A571: 574 | B571: Саморіз чорний 25 мм для дерева | C571: Саморіз | E571: Отделка
A572: 575 | B572: Силікон сантехнічний | C572: Силікон | D572: бал | E572: мшп
...
