Workbook
Name spec_values: [1]BOQ_Шаблон!$A$6:$A$275

Sheet Бюджет_Проекта
A1: Статья движения денежных средств | B1: ф1 | C1: ф2 | D1: Итого, грн | E1: Комментарии к бюджету объекта | H1: Матеріали | I1: =D101+D98 -> 3213611.4
A2: ПОСТУПЛЕНИЯ | B2: =B3+B10 -> 3838766 | C2: =C3+C10 -> 0 | D2: =B2+C2 -> 3838766 | H2: Загальна сс, грн | I2: =D14-I1 -> 1333865.5
A3: Операционная деятельность | B3: =SUM(B4:B9) -> 3838766 | C3: =SUM(C4:C9) -> 0 | D3: =B3+C3 -> 3838766 | H3: Налоговая нагрузка, 3%: | I3: =I4*3% -> 115162.98
A4: Поступление от Заказчика | B4: 3838766 | D4: =B4+C4 -> 3838766 | H4: КП: | I4: =B4 -> 3838766
A5: Прочие поступления | D5: =B5+C5 -> 0 | H5: Маржа, грн: за шт | I5: =I4-I3-I2-I1 -> -823873.9
A6: Возврат залоговой суммы | D6: =B6+C6 -> 0 | H6: Маржа, %: | I6: =I5/I4 -> -0.21461946
A7: Поступление от возврата денежных средств | D7: =B7+C7 -> 0 | H7: Количество в заказе, шт | I7: 1
A8: Поступление цех | D8: =B8+C8 -> 0 | H8: Итого маржа по заказу, грн | I8: =I7*I5 -> -823873.9
A9: Поступление за технику | D9: =B9+C9 -> 0
A10: Финансовая деятельность | B10: =SUM(B11:B13) -> 0 | C10: =SUM(C11:C13) -> 0 | D10: =B10+C10 -> 0
A11: Получение финансовой помощи | D11: =B11+C11 -> 0
A12: Поступление от Фин агента | C12: =B133 -> 0 | D12: =B12+C12 -> 0
A13: Кредитная линия | D13: =B13+C13 -> 0
A14: СПИСАНИЕ | B14: =B15+B128+B141 -> 3704526.9 | C14: =C15+C128+C141 -> 842950 | D14: =B14+C14 -> 4547476.9
A15: Операционная деятельность | B15: =B16+B70+B93+B66 -> 3578084.4 | C15: =C16+C70+C93+C66 -> 842950 | D15: =B15+C15 -> 4421034.4
A16: Административные затраты | B16: =B17+B24+B29+B33+B41+B45+B49+B52+B58+B61+B21 -> 59000 | C16: =C17+C24+C29+C33+C41+C45+C49+C52+C58+C61+C21 -> 0 | D16: =B16+C16 -> 59000
A17: Аренда офиса | B17: =SUM(B18:B20) -> 0 | C17: =SUM(C18:C20) -> 0 | D17: =B17+C17 -> 0
A18: Аренда офиса | B18: =SUMIF('Проект СС'!$B:$B,$A18,'Проект СС'!$O:$O) -> 0 | D18: =B18+C18 -> 0
A19: Коммунальные платежи (офис) | B19: =SUMIF('Проект СС'!$B:$B,$A19,'Проект СС'!$O:$O) -> 0 | D19: =B19+C19 -> 0
A20: Охрана офиса и пожарная сигнализация | B20: =SUMIF('Проект СС'!$B:$B,$A20,'Проект СС'!$O:$O) -> 0 | D20: =B20+C20 -> 0
A21: Аренда квартиры | B21: =SUM(B22:B23) -> 0 | C21: =SUM(C22:C23) -> 0 | D21: =B21+C21 -> 0
A22: Аренда квартиры | B22: =SUMIF('Проект СС'!$B:$B,$A22,'Проект СС'!$O:$O) -> 0 | D22: =B22+C22 -> 0
A23: Коммунальные платежи | B23: =SUMIF('Проект СС'!$B:$B,$A23,'Проект СС'!$O:$O) -> 0 | D23: =B23+C23 -> 0
A24: Затраты на персонал | B24: =SUM(B25:B28) -> 0 | C24: =SUM(C25:C28) -> 0 | D24: =B24+C24 -> 0
A25: Затраты на обучение управленческого персонала | B25: =SUMIF('Проект СС'!$B:$B,$A25,'Проект СС'!$O:$O) -> 0 | D25: =B25+C25 -> 0
A26: Затраты по корпоративной культуре | B26: =SUMIF('Проект СС'!$B:$B,$A26,'Проект СС'!$O:$O) -> 0 | D26: =B26+C26 -> 0
A27: Материальная помощь | B27: =SUMIF('Проект СС'!$B:$B,$A27,'Проект СС'!$O:$O) -> 0 | D27: =B27+C27 -> 0
A28: Периодика | B28: =SUMIF('Проект СС'!$B:$B,$A28,'Проект СС'!$O:$O) -> 0 | D28: =B28+C28 -> 0
A29: Затраты на командировку | B29: =SUM(B30:B32) -> 48000 | C29: =SUM(C30:C32) -> 0 | D29: =B29+C29 -> 48000
A30: Проезд | B30: =SUMIF('Проект СС'!$B:$B,$A30,'Проект СС'!$O:$O) -> 0
A31: Проживание | B31: =SUMIF('Проект СС'!$B:$B,$A31,'Проект СС'!$O:$O) -> 48000 | D31: =B31+C31 -> 48000
A32: Суточные | B32: =SUMIF('Проект СС'!$B:$B,$A32,'Проект СС'!$O:$O) -> 0 | D32: =B32+C32 -> 0
A33: ЗП управленческого персонала с начислениями | B33: =SUM(B34:B40) -> 0 | C33: =SUM(C34:C40) -> 0 | D33: =B33+C33 -> 0
A34: Зарплата PM | C34: =SUMIF('Проект СС'!$B:$B,$A34,'Проект СС'!$O:$O) -> 0 | D34: =B34+C34 -> 0 | E34: 2 мес + 5 мес
A35: Удержание с зарплаты РМ | B35: =SUMIF('Проект СС'!$B:$B,$A35,'Проект СС'!$O:$O) -> 0 | D35: =B35+C35 -> 0
A36: Начисления на зарплату PM | B36: =SUMIF('Проект СС'!$B:$B,$A36,'Проект СС'!$O:$O) -> 0 | D36: =B36+C36 -> 0
A37: Зарплата управленческого персонала | B37: =SUMIF('Проект СС'!$B:$B,$A37,'Проект СС'!$O:$O) -> 0 | D37: =B37+C37 -> 0
A38: Удержание с админ зарплату | B38: =SUMIF('Проект СС'!$B:$B,$A38,'Проект СС'!$O:$O) -> 0 | D38: =B38+C38 -> 0
A39: Начисления на админ зарплату | B39: =SUMIF('Проект СС'!$B:$B,$A39,'Проект СС'!$O:$O) -> 0 | D39: =B39+C39 -> 0
A40: Премия админ персоналу | B40: =SUMIF('Проект СС'!$B:$B,$A40,'Проект СС'!$O:$O) -> 0 | D40: =B40+C40 -> 0
A41: Налоги и сборы | B41: =SUM(B42:B44) -> 0 | C41: =SUM(C42:C44) -> 0 | D41: =B41+C41 -> 0
A42: Налог на прибыль | B42: =SUMIF('Проект СС'!$B:$B,$A42,'Проект СС'!$O:$O) -> 0 | D42: =B42+C42 -> 0
A43: НДС | B43: =SUMIF('Проект СС'!$B:$B,$A43,'Проект СС'!$O:$O) -> 0 | D43: =B43+C43 -> 0
A44: Прочие налоги | B44: =SUMIF('Проект СС'!$B:$B,$A44,'Проект СС'!$O:$O) -> 0 | D44: =B44+C44 -> 0 | E44: 0.03
A45: Телекоммуникационные услуги | B45: =SUM(B46:B48) -> 0 | C45: =SUM(C46:C48) -> 0 | D45: =B45+C45 -> 0
A46: Интернет | B46: =SUMIF('Проект СС'!$B:$B,$A46,'Проект СС'!$O:$O) -> 0 | D46: =B46+C46 -> 0
A47: Мобильная связь | B47: =SUMIF('Проект СС'!$B:$B,$A47,'Проект СС'!$O:$O) -> 0 | D47: =B47+C47 -> 0
A48: Стационарный телефон | B48: =SUMIF('Проект СС'!$B:$B,$A48,'Проект СС'!$O:$O) -> 0 | D48: =B48+C48 -> 0
A49: Транспортные затраты | B49: =B50+B51 -> 11000 | C49: =C50+C51 -> 0 | D49: =B49+C49 -> 11000
A50: ГСМ (топливо) | B50: =SUMIF('Проект СС'!$B:$B,$A50,'Проект СС'!$O:$O) -> 11000 | D50: =B50+C50 -> 11000
A51: Такси | B51: =SUMIF('Проект СС'!$B:$B,$A51,'Проект СС'!$O:$O) -> 0 | D51: =B51+C51 -> 0
A52: Услуги | B52: =SUM(B53:B57) -> 0 | C52: =SUM(C53:C57) -> 0 | D52: =B52+C52 -> 0
A53: Аутсорсинг | B53: =SUMIF('Проект СС'!$B:$B,$A53,'Проект СС'!$O:$O) -> 0 | D53: =B53+C53 -> 0
A54: Представительские затраты | B54: =SUMIF('Проект СС'!$B:$B,$A54,'Проект СС'!$O:$O) -> 0 | D54: =B54+C54 -> 0
A55: Лицензия Медок | B55: =SUMIF('Проект СС'!$B:$B,$A55,'Проект СС'!$O:$O) -> 0 | D55: =B55+C55 -> 0
A56: Уборка помещений | B56: =SUMIF('Проект СС'!$B:$B,$A56,'Проект СС'!$O:$O) -> 0 | D56: =B56+C56 -> 0
A57: Прочие затраты | B57: =SUMIF('Проект СС'!$B:$B,$A57,'Проект СС'!$O:$O) -> 0 | D57: =B57+C57 -> 0
A58: Услуги банков | B58: =SUM(B59:B60) -> 0 | C58: =SUM(C59:C60) -> 0 | D58: =B58+C58 -> 0
A59: Комиссия банков и др.платежи по РКО | B59: =SUMIF('Проект СС'!$B:$B,$A59,'Проект СС'!$O:$O) -> 0 | D59: =B59+C59 -> 0
A60: Прочие услуги банка | B60: =SUMIF('Проект СС'!$B:$B,$A60,'Проект СС'!$O:$O) -> 0 | D60: =B60+C60 -> 0
A61: Юридические услуги | B61: =SUM(B62:B65) -> 0 | C61: =SUM(C62:C65) -> 0 | D61: =B61+C61 -> 0
A62: Нотариальные действия | B62: =SUMIF('Проект СС'!$B:$B,$A62,'Проект СС'!$O:$O) -> 0 | D62: =B62+C62 -> 0
A63: Тендер | B63: =SUMIF('Проект СС'!$B:$B,$A63,'Проект СС'!$O:$O) -> 0 | D63: =B63+C63 -> 0
A64: Штраф | B64: =SUMIF('Проект СС'!$B:$B,$A64,'Проект СС'!$O:$O) -> 0 | D64: =B64+C64 -> 0
A65: Прочие юр.услуги | B65: =SUMIF('Проект СС'!$B:$B,$A65,'Проект СС'!$O:$O) -> 0 | D65: =B65+C65 -> 0
A66: Маркетинговые затраты | B66: =B67 -> 0 | C66: =C67 -> 0 | D66: =B66+C66 -> 0
A67: Маркетинговые затраты | B67: =SUM(B68:B69) -> 0 | C67: =SUM(C68:C69) -> 0 | D67: =B67+C67 -> 0
A68: Реклама | B68: =SUMIF('Проект СС'!$B:$B,$A68,'Проект СС'!$O:$O) -> 0 | D68: =B68+C68 -> 0
A69: Прочие маркетинговые затраты | B69: =SUMIF('Проект СС'!$B:$B,$A69,'Проект СС'!$O:$O) -> 0 | D69: =B69+C69 -> 0
A70: Общепроизводственные затраты | B70: =B71+B76+B83+B86+B90 -> 40793.003 | C70: =C71+C76+C83+C86+C90 -> 2800 | D70: =B70+C70 -> 43593.003
A71: ИТ расходы | B71: =SUM(B72:B75) -> 0 | C71: =SUM(C72:C75) -> 2800 | D71: =B71+C71 -> 2800
A72: Заправка картриджа | B72: =SUMIF('Проект СС'!$B:$B,$A72,'Проект СС'!$O:$O) -> 0 | C72: 2800 | D72: =B72+C72 -> 2800
A73: Обслуживание офисной техники | B73: =SUMIF('Проект СС'!$B:$B,$A73,'Проект СС'!$O:$O) -> 0 | D73: =B73+C73 -> 0
A74: ПО | B74: =SUMIF('Проект СС'!$B:$B,$A74,'Проект СС'!$O:$O) -> 0 | D74: =B74+C74 -> 0
A75: Расходный материал | B75: =SUMIF('Проект СС'!$B:$B,$A75,'Проект СС'!$O:$O) -> 0 | D75: =B75+C75 -> 0
A76: Общепроизводственные затраты | B76: =SUM(B77:B82) -> 0 | C76: =SUM(C77:C82) -> 0 | D76: =B76+C76 -> 0
A77: Благоустройство офиса | B77: =SUMIF('Проект СС'!$B:$B,$A77,'Проект СС'!$O:$O) -> 0 | D77: =B77+C77 -> 0
A78: Канцтовары | B78: =SUMIF('Проект СС'!$B:$B,$A78,'Проект СС'!$O:$O) -> 0 | D78: =B78+C78 -> 0
A79: Курьерские и почтовые | B79: =SUMIF('Проект СС'!$B:$B,$A79,'Проект СС'!$O:$O) -> 0 | D79: =B79+C79 -> 0
A80: Питьевая вода | B80: =SUMIF('Проект СС'!$B:$B,$A80,'Проект СС'!$O:$O) -> 0 | D80: =B80+C80 -> 0
A81: Спецодежда | B81: =SUMIF('Проект СС'!$B:$B,$A81,'Проект СС'!$O:$O) -> 0 | D81: =B81+C81 -> 0
A82: Юридический адрес | B82: =SUMIF('Проект СС'!$B:$B,$A82,'Проект СС'!$O:$O) -> 0 | D82: =B82+C82 -> 0
A83: Хозтовары и материалы | B83: =SUM(B84:B85) -> 0 | C83: =SUM(C84:C85) -> 0 | D83: =B83+C83 -> 0
A84: Бытовая химия | B84: =SUMIF('Проект СС'!$B:$B,$A84,'Проект СС'!$O:$O) -> 0 | D84: =B84+C84 -> 0
A85: Другие хозтовары | B85: =SUMIF('Проект СС'!$B:$B,$A85,'Проект СС'!$O:$O) -> 0 | D85: =B85+C85 -> 0 | E85: чай, кофе
A86: Охрана труда | B86: =SUM(B87:B89) -> 40793.003 | C86: =SUM(C87:C89) -> 0 | D86: =SUM(D87:D89) -> 40793.003
A87: Медосмотр | B87: =SUMIF('Проект СС'!$B:$B,$A87,'Проект СС'!$O:$O) -> 0 | D87: =B87+C87 -> 0
A88: Обучение производственного персонала | B88: =SUMIF('Проект СС'!$B:$B,$A88,'Проект СС'!$O:$O) -> 0 | D88: =B88+C88 -> 0
A89: Прочие затраты ОТ | B89: 40793.003 | D89: =B89+C89 -> 40793.003
A90: Разрешительная документация | B90: =SUM(B91:B92) -> 0 | C90: =SUM(C91:C92) -> 0 | D90: =B90+C90 -> 0
A91: Разрешительная документация | B91: =SUMIF('Проект СС'!$B:$B,$A91,'Проект СС'!$O:$O) -> 0 | D91: =B91+C91 -> 0
A92: Страхование | B92: =SUMIF('Проект СС'!$B:$B,$A92,'Проект СС'!$O:$O) -> 0 | D92: =B92+C92 -> 0
A93: Производственные затраты | B93: =B94+B105+B113+B117 -> 3478291.4 | C93: =C94+C105+C113+C117 -> 840150 | D93: =B93+C93 -> 4318441.4
A94: Производственные затраты и услуги | B94: =SUM(B95:B104) -> 3436691.4 | C94: =SUM(C95:C104) -> 0 | D94: =B94+C94 -> 3436691.4
A95: Вывоз мусора | B95: =SUMIF('Проект СС'!$B:$B,$A95,'Проект СС'!$O:$O) -> 0 | D95: =B95+C95 -> 0
A96: Залоговая сумма | B96: =SUMIF('Проект СС'!$B:$B,$A96,'Проект СС'!$O:$O) -> 0 | D96: =B96+C96 -> 0
A97: Запчасти для спецтехники | B97: =SUMIF('Проект СС'!$B:$B,$A97,'Проект СС'!$O:$O) -> 0 | D97: =B97+C97 -> 0
A98: МШП | B98: =SUMIF('Проект СС'!$B:$B,$A98,'Проект СС'!$O:$O) -> 5581.52 | D98: =B98+C98 -> 5581.52
A99: Прочие производственные затраты | B99: =SUMIF('Проект СС'!$B:$B,$A99,'Проект СС'!$O:$O) -> 0 | D99: =B99+C99 -> 0
A100: Ремонты | B100: =SUMIF('Проект СС'!$B:$B,$A100,'Проект СС'!$O:$O) -> 0 | D100: =B100+C100 -> 0
...

Sheet Анализ
A1: МД EMS мала | D1: Курс | E1: 43.5 | F1: Площадь | G1: =10*12 -> 120
A3: Сумма по полю Всього, грн. з ПДВ | B3: Названия столбцов
A4: Названия строк | B4: Матеріал | C4: Робота | D4: Общий итог | E4: Материал $ | F4: Общий итог $ | G4: На 1 м2 $
A5: Дополнительная Комплектация | B5: 323204 | C5: 0 | D5: 323204 | E5: =B5/$E$1 -> 7429.977 | F5: =D5/$E$1 -> 7429.977 | G5: =F5/$G$1 -> 61.916475
A6: Каркас | B6: 402079.36 | C6: 0 | D6: 402079.36 | E6: =B6/$E$1 -> 9243.2037 | F6: =D6/$E$1 -> 9243.2037 | G6: =F6/$G$1 -> 77.026697
A7: Монтаж будинку | C7: 0 | D7: 0 | E7: =B7/$E$1 -> 0 | F7: =D7/$E$1 -> 0 | G7: =F7/$G$1 -> 0
A8: Окна/двери | B8: 144953.03 | C8: 0 | D8: 144953.03 | E8: =B8/$E$1 -> 3332.2536 | F8: =D8/$E$1 -> 3332.2536 | G8: =F8/$G$1 -> 27.76878
A9: Отделка | B9: 665033.4 | C9: 0 | D9: 665033.4 | E9: =B9/$E$1 -> 15288.124 | F9: =D9/$E$1 -> 15288.124 | G9: =F9/$G$1 -> 127.40103
A10: Сантехника | B10: 97874 | C10: 0 | D10: 97874 | E10: =B10/$E$1 -> 2249.977 | F10: =D10/$E$1 -> 2249.977 | G10: =F10/$G$1 -> 18.749808
A11: Фасад | B11: 107743.56 | C11: 0 | D11: 107743.56 | E11: =B11/$E$1 -> 2476.8634 | F11: =D11/$E$1 -> 2476.8634 | G11: =F11/$G$1 -> 20.640529
A12: Электрика/Подогрев | B12: 136627.04 | C12: 0 | D12: 136627.04 | E12: =B12/$E$1 -> 3140.8515 | F12: =D12/$E$1 -> 3140.8515 | G12: =F12/$G$1 -> 26.173762
A13: Общий итог | B13: 1877514.4 | C13: 0 | D13: 1877514.4 | E13: =SUM(E5:E12) -> 43161.25 | F13: =SUM(F5:F12) -> 43161.25

Sheet Проект СС
A1: № | B1: Стаття в ДДС | C1: Робота/матеріал/додаткові | D1: Виробництво/Будівництво | E1: Тип робіт | F1: № з/п | G1: Найменування робіт/витрат/матеріалів | H1: Найменування робіт/витрат/матеріалів узагальнена | I1: Од. вим. | J1: Кіль- кість | K1: Вартість робіт за од.виміру, грн. з ПДВ | L1: Вартість матеріалів за од.виміру, грн. з ПДВ | M1: Вартість робіт за повний обсяг, грн. з ПДВ | N1: Вартість матеріалів за повний обсяг, грн. з ПДВ | O1: Всього, грн. з ПДВ
A2: І | F2: І | G2: Каркас | J2: =L3+L12 -> 0
A3: 1.1 | F3: 1.1 | G3: РОБОТА | L3: =SUM(L5:L11) -> 0
A4: 1.1.1 | B4: Зарплата производственного персонала | C4: Робота | D4: Виробництво/Будівництво | E4: Каркас | F4: 1.1.1 | G4: Приймання матеріалу | I4: чол/год | J4: =480/8 -> 60 | K4: 200 | M4: =J4*K4 -> 12000 | N4: =J4*L4 -> 0 | O4: =N4+M4 -> 12000
A5: 1.1.2 | B5: Зарплата производственного персонала | C5: Робота | D5: Виробництво/Будівництво | E5: Каркас | F5: 1.1.2 | G5: Обробка матеріалу (дерево) | I5: чол/год | J5: =480/8 -> 60 | K5: 200 | M5: =J5*K5 -> 12000 | N5: =J5*L5 -> 0 | O5: =N5+M5 -> 12000
A6: 1.1.3 | B6: Зарплата производственного персонала | C6: Робота | D6: Виробництво/Будівництво | E6: Каркас | F6: 1.1.3 | G6: Нарізання деталей зігдно креслень | I6: чол/год | J6: =480/8 -> 60 | K6: 200 | M6: =J6*K6 -> 12000 | N6: =J6*L6 -> 0 | O6: =N6+M6 -> 12000
A7: 1.1.4 | B7: Зарплата производственного персонала | C7: Робота | D7: Виробництво/Будівництво | E7: Каркас | F7: 1.1.4 | G7: Збирання деталей | I7: чол/год | J7: =480/8 -> 60 | K7: 200 | M7: =J7*K7 -> 12000 | N7: =J7*L7 -> 0 | O7: =N7+M7 -> 12000
A8: 1.1.5 | B8: Зарплата производственного персонала | C8: Робота | D8: Виробництво/Будівництво | E8: Каркас | F8: 1.1.5 | G8: зварювання (дерево зєдання) | I8: чол/год | J8: =480/8 -> 60 | K8: 200 | M8: =J8*K8 -> 12000 | N8: =J8*L8 -> 0 | O8: =N8+M8 -> 12000
A9: 1.1.6 | B9: Зарплата производственного персонала | C9: Робота | D9: Виробництво/Будівництво | E9: Каркас | F9: 1.1.6 | G9: Влаштування підшиви модуля | I9: чол/год | J9: =480/8 -> 60 | K9: 200 | M9: =J9*K9 -> 12000 | N9: =J9*L9 -> 0 | O9: =N9+M9 -> 12000
A10: 1.1.7 | B10: Зарплата производственного персонала | C10: Робота | D10: Виробництво/Будівництво | E10: Каркас | F10: 1.1.7 | G10: Грунтування металокаркасу | I10: чол/год | J10: =480/8 -> 60 | K10: 200 | M10: =J10*K10 -> 12000 | N10: =J10*L10 -> 0 | O10: =N10+M10 -> 12000
A11: 1.1.8 | B11: Зарплата производственного персонала | C11: Робота | D11: Виробництво/Будівництво | E11: Каркас | F11: 1.1.8 | G11: Фарубування металокаркасу | I11: чол/год | J11: =480/8 -> 60 | K11: 200 | M11: =J11*K11 -> 12000 | N11: =J11*L11 -> 0 | O11: =N11+M11 -> 12000
A12: 1.2 | F12: 1.2 | G12: МАТЕРІАЛИ
A13: 1.2.1 | B13: Строительные материалы | C13: Матеріал | D13: Виробництво/Будівництво | E13: Каркас | F13: 1.2.1 | G13: Труба металева Ст3 100*100*3 | H13: Профільна труба | I13: м.п | J13: 359 | L13: 441 | M13: =J13*K13 -> 0 | N13: =J13*L13 -> 158319 | O13: =N13+M13 -> 158319
A14: 1.2.2 | B14: Строительные материалы | C14: Матеріал | D14: Виробництво/Будівництво | E14: Каркас | F14: 1.2.2 | G14: Труба металева Ст3 50*50*2 | H14: Профільна труба | I14: м.п. | J14: 684 | L14: 156 | M14: =J14*K14 -> 0 | N14: =J14*L14 -> 106704 | O14: =N14+M14 -> 106704
A15: 1.2.3 | B15: Строительные материалы | C15: Матеріал | D15: Виробництво/Будівництво | E15: Каркас | F15: 1.2.3 | G15: Труба металева Ст3 50*25*2 | H15: Профільна труба | I15: м.п | J15: 384 | L15: 98 | M15: =J15*K15 -> 0 | N15: =J15*L15 -> 37632 | O15: =N15+M15 -> 37632
A16: 1.2.4 | B16: Строительные материалы | C16: Матеріал | D16: Виробництво/Будівництво | E16: Каркас | F16: 1.2.4 | G16: Лист 4мм | H16: лист ГК | I16: м2 | J16: 4.5 | L16: 1698 | M16: =J16*K16 -> 0 | N16: =J16*L16 -> 7641 | O16: =N16+M16 -> 7641
A17: 1.2.5 | B17: Строительные материалы | C17: Матеріал | D17: Виробництво/Будівництво | E17: Каркас | F17: 1.2.5 | G17: Лист 8мм | H17: лист ГК | I17: м2 | J17: 4.5 | L17: 3356 | M17: =J17*K17 -> 0 | N17: =J17*L17 -> 15102 | O17: =N17+M17 -> 15102
A18: 1.2.6 | B18: Строительные материалы | C18: Матеріал | D18: Виробництво/Будівництво | E18: Каркас | F18: 1.2.6 | G18: Лист 14мм | H18: лист ГК | I18: м.кв. | J18: 0.16 | L18: 6811 | M18: =J18*K18 -> 0 | N18: =J18*L18 -> 1089.76 | O18: =N18+M18 -> 1089.76
A19: 1.2.7 | B19: Строительные материалы | C19: Матеріал | D19: Виробництво/Будівництво | E19: Каркас | F19: 1.2.7 | G19: Шпилька М48 | H19: Шпилька | I19: м.п. | J19: 18 | L19: 1984 | M19: =J19*K19 -> 0 | N19: =J19*L19 -> 35712 | O19: =N19+M19 -> 35712
A20: 1.2.8 | B20: Строительные материалы | C20: Матеріал | D20: Виробництво/Будівництво | E20: Каркас | F20: 1.2.8 | G20: Гайка м 48 | H20: Гайка | I20: шт | J20: 36 | L20: 274 | M20: =J20*K20 -> 0 | N20: =J20*L20 -> 9864 | O20: =N20+M20 -> 9864
A21: 1.2.9 | B21: Строительные материалы | C21: Матеріал | D21: Виробництво/Будівництво | E21: Каркас | F21: 1.2.9 | G21: Болт м24*200 | H21: Болт | I21: шт | J21: 32 | L21: 145 | M21: =J21*K21 -> 0 | N21: =J21*L21 -> 4640 | O21: =N21+M21 -> 4640
A22: 1.2.10 | B22: Строительные материалы | C22: Матеріал | D22: Виробництво/Будівництво | E22: Каркас | F22: 1.2.10 | G22: Гайка м 24 | H22: Гайка | I22: шт | J22: 32 | L22: 154 | M22: =J22*K22 -> 0 | N22: =J22*L22 -> 4928 | O22: =N22+M22 -> 4928
A23: 1.2.11 | B23: Строительные материалы | C23: Матеріал | D23: Виробництво/Будівництво | E23: Каркас | F23: 1.2.11 | G23: Болт М16*90 | H23: Болт | I23: шт | J23: 52 | L23: 98 | M23: =J23*K23 -> 0 | N23: =J23*L23 -> 5096 | O23: =N23+M23 -> 5096
A24: 1.2.12 | B24: Строительные материалы | C24: Матеріал | D24: Виробництво/Будівництво | E24: Каркас | F24: 1.2.12 | G24: Гайка м 16 | H24: Гайка | I24: шт | J24: 52 | L24: 4.92 | M24: =J24*K24 -> 0 | N24: =J24*L24 -> 255.84 | O24: =N24+M24 -> 255.84
... A34: 1.2.22 | B34: МШП | C34: Матеріал | D34: Виробництво/Будівництво | E34: Каркас | F34: 1.2.22 | G34: Гайки м12 | H34: Гайка | I34: шт | J34: 38 | L34: 13.27 | M34: =J34*K34 -> 0 | N34: =J34*L34 -> 504.26 | O34: =N34+M34 -> 504.26
B35: Строительные материалы | C35: Матеріал | D35: Виробництво/Будівництво | E35: Каркас | F35: 1.2.23 | G35: шайба м12 | H35: Шайба | I35: шт | J35: 38 | L35: 9.215 | M35: =J35*K35 -> 0 | N35: =J35*L35 -> 350.17 | O35: =N35+M35 -> 350.17
B36: Строительные материалы | C36: Матеріал | D36: Виробництво/Будівництво | E36: Каркас | F36: 1.2.24 | G36: гровер м12 | H36: Гровер | I36: шт | J36: 40 | L36: 8.36 | M36: =J36*K36 -> 0 | N36: =J36*L36 -> 334.4 | O36: =N36+M36 -> 334.4
B37: Строительные материалы | C37: Матеріал | D37: Виробництво/Будівництво | E37: Каркас | F37: 1.2.25 | G37: Завіса 16мм | H37: Завіса | I37: шт | J37: 8 | L37: 136 | M37: =J37*K37 -> 0 | N37: =J37*L37 -> 1088 | O37: =N37+M37 -> 1088
B38: Строительные материалы | C38: Матеріал | D38: Виробництво/Будівництво | E38: Каркас | F38: 1.2.26 | G38: Завіса 20мм | H38: Завіса | I38: шт | J38: 4 | L38: 154 | M38: =J38*K38 -> 0 | N38: =J38*L38 -> 616 | O38: =N38+M38 -> 616
B39: Строительные материалы | C39: Матеріал | D39: Виробництво/Будівництво | E39: Каркас | F39: 1.2.27 | G39: Лист 5 мм | H39: лист ГК | I39: м.кв. | J39: 0.5 | L39: 1959.6 | M39: =J39*K39 -> 0 | N39: =J39*L39 -> 979.8 | O39: =N39+M39 -> 979.8
B40: Строительные материалы | C40: Матеріал | D40: Виробництво/Будівництво | E40: Каркас | F40: 1.2.28 | G40: Фарба 3 в 1 сіра | H40: Фарба | I40: кг | J40: 5 | L40: 216 | M40: =J40*K40 -> 0 | N40: =J40*L40 -> 1080 | O40: =N40+M40 -> 1080
B41: Строительные материалы | C41: Матеріал | D41: Виробництво/Будівництво | E41: Каркас | F41: 1.2.29 | G41: Розчинник | H41: Розчинник | I41: л | J41: 1 | L41: 96 | M41: =J41*K41 -> 0 | N41: =J41*L41 -> 96 | O41: =N41+M41 -> 96
B42: Строительные материалы | C42: Матеріал | D42: Виробництво/Будівництво | E42: Каркас | F42: 1.2.30 | G42: Труба 40*40*3 | H42: Профільна труба | I42: м.п | J42: 27.2 | L42: 132 | M42: =J42*K42 -> 0 | N42: =J42*L42 -> 3590.4 | O42: =N42+M42 -> 3590.4
B43: Строительные материалы | C43: Матеріал | D43: Виробництво/Будівництво | E43: Каркас | F43: 1.2.31 | G43: Труба 20*40*3 | H43: Профільна труба | I43: м.п. | J43: 53 | L43: 97 | M43: =J43*K43 -> 0 | N43: =J43*L43 -> 5141 | O43: =N43+M43 -> 5141
B44: Строительные материалы | C44: Матеріал | D44: Виробництво/Будівництво | E44: Каркас | F44: 1.2.32 | G44: Лист 4мм | H44: лист ГК | I44: т | J44: 0.013 | L44: 1698 | M44: =J44*K44 -> 0 | N44: =J44*L44 -> 22.074 | O44: =N44+M44 -> 22.074
B45: Строительные материалы | C45: Матеріал | D45: Виробництво/Будівництво | E45: Каркас | F45: 1.2.33 | G45: Лист 6мм | H45: лист ГК | I45: т | J45: 0.031 | L45: 2077 | M45: =J45*K45 -> 0 | N45: =J45*L45 -> 64.387 | O45: =N45+M45 -> 64.387
B46: Строительные материалы | C46: Матеріал | D46: Виробництво/Будівництво | E46: Каркас | F46: 1.2.34 | G46: Завіси 16 мм круглі | H46: Завіса | I46: шт | J46: 4 | L46: 136 | M46: =J46*K46 -> 0 | N46: =J46*L46 -> 544 | O46: =N46+M46 -> 544
B47: Строительные материалы | C47: Матеріал | D47: Виробництво/Будівництво | E47: Каркас | F47: 1.2.35 | G47: Фарба 3 в 1 | H47: Фарба | I47: кг | J47: 2.5 | L47: 216 | M47: =J47*K47 -> 0 | N47: =J47*L47 -> 540 | O47: =N47+M47 -> 540
B48: Строительные материалы | C48: Матеріал | D48: Виробництво/Будівництво | E48: Каркас | F48: 1.2.36 | G48: Розчинник | H48: #N/A | I48: л | J48: 1 | L48: 96 | M48: =J48*K48 -> 0 | N48: =J48*L48 -> 96 | O48: =N48+M48 -> 96
B49: Строительные материалы | C49: Матеріал | D49: Виробництво/Будівництво | E49: Каркас | F49: 1.2.37 | G49: Пінопласт 100мм | H49: Пінопласт | I49: м.кв. | J49: 9.6 | L49: 220 | M49: =J49*K49 -> 0 | N49: =J49*L49 -> 2112 | O49: =N49+M49 -> 2112
B50: Строительные материалы | C50: Матеріал | D50: Виробництво/Будівництво | E50: Каркас | F50: 1.2.38 | G50: Паробарьер | H50: Паробар'єр | I50: м.кв. | J50: 15 | L50: 13 | M50: =J50*K50 -> 0 | N50: =J50*L50 -> 195 | O50: =N50+M50 -> 195
B51: Строительные материалы | C51: Матеріал | D51: Виробництво/Будівництво | E51: Каркас | F51: 1.2.39 | G51: Профнастил ПК 10 | H51: Профнастил | I51: м.кв. | J51: 15 | L51: 267 | M51: =J51*K51 -> 0 | N51: =J51*L51 -> 4005 | O51: =N51+M51 -> 4005
B52: Строительные материалы | C52: Матеріал | D52: Виробництво/Будівництво | E52: Каркас | F52: 1.2.40 | G52: Гладкий лист | H52: Гладкий лист метал | I52: м.кв. | J52: 2.2 | L52: 211 | M52: =J52*K52 -> 0 | N52: =J52*L52 -> 464.2 | O52: =N52+M52 -> 464.2
B53: Строительные материалы | C53: Матеріал | D53: Виробництво/Будівництво | E53: Каркас | F53: 1.2.41 | G53: Труба 40*40*3 | H53: Профільна труба | I53: м.п | J53: 25.6 | L53: 174 | M53: =J53*K53 -> 0 | N53: =J53*L53 -> 4454.4 | O53: =N53+M53 -> 4454.4
B54: Строительные материалы | C54: Матеріал | D54: Виробництво/Будівництво | E54: Каркас | F54: 1.2.42 | G54: Труба 20*40*3 | H54: Профільна труба | I54: м.п. | J54: 30 | L54: 132 | M54: =J54*K54 -> 0 | N54: =J54*L54 -> 3960 | O54: =N54+M54 -> 3960
B55: Строительные материалы | C55: Матеріал | D55: Виробництво/Будівництво | E55: Каркас | F55: 1.2.43 | G55: Профнастил ПК 10 | H55: Профнастил | I55: м.кв. | J55: 7.2 | L55: 267 | M55: =J55*K55 -> 0 | N55: =J55*L55 -> 1922.4 | O55: =N55+M55 -> 1922.4
B56: Строительные материалы | C56: Матеріал | D56: Виробництво/Будівництво | E56: Каркас | F56: 1.2.44 | G56: лист 3 мм | H56: лист ГК | I56: м.кв. | J56: 0.7 | L56: 1221 | M56: =J56*K56 -> 0 | N56: =J56*L56 -> 854.7 | O56: =N56+M56 -> 854.7
B57: Строительные материалы | C57: Матеріал | D57: Виробництво/Будівництво | E57: Каркас | F57: 1.2.45 | G57: Інформаційний банер зовнішній - 2130х500мм | H57: Інформаційний банер | I57: шт | J57: 2 | L57: 5400 | M57: =J57*K57 -> 0 | N57: =J57*L57 -> 10800 | O57: =N57+M57 -> 10800 | Q57: +
A58: ІІ | F58: ІІ | G58: Отделка | M58: =J58*K58 -> 0 | N58: =J58*L58 -> 0 | O58: =N58+M58 -> 0
A59: 2.1 | F59: 2.1 | G59: РОБОТА | M59: =J59*K59 -> 0 | N59: =J59*L59 -> 0 | O59: =N59+M59 -> 0
A60: 2.1.1 | B60: Зарплата производственного персонала | C60: Робота | D60: Виробництво/Будівництво | E60: Отделка | F60: 2.1.1 | G60: Утеплення та гідроізоляція підлоги | I60: чол/год | J60: =1080/7 -> 154.28571 | K60: 200 | M60: =J60*K60 -> 30857.143 | N60: =J60*L60 -> 0 | O60: =N60+M60 -> 30857.143
A61: 2.1.2 | B61: Зарплата производственного персонала | C61: Робота | D61: Виробництво/Будівництво | E61: Отделка | F61: 2.1.2 | G61: Монтаж брусу по каркасу | I61: чол/год | J61: =1080/7 -> 154.28571 | K61: 200 | M61: =J61*K61 -> 30857.143 | N61: =J61*L61 -> 0 | O61: =N61+M61 -> 30857.143
A62: 2.1.3 | B62: Зарплата производственного персонала | C62: Робота | D62: Виробництво/Будівництво | E62: Отделка | F62: 2.1.3 | G62: Пароізоляційна мембрана; | I62: чол/год | J62: =1080/7 -> 154.28571 | K62: 200 | M62: =J62*K62 -> 30857.143 | N62: =J62*L62 -> 0 | O62: =N62+M62 -> 30857.143
A63: 2.1.4 | B63: Зарплата производственного персонала | C63: Робота | D63: Виробництво/Будівництво | E63: Отделка | F63: 2.1.4 | G63: Укладання Настил підлоги | I63: чол/год | J63: =1080/7 -> 154.28571 | K63: 200 | M63: =J63*K63 -> 30857.143 | N63: =J63*L63 -> 0 | O63: =N63+M63 -> 30857.143
A64: 2.1.5 | B64: Зарплата производственного персонала | C64: Робота | D64: Виробництво/Будівництво | E64: Отделка | F64: 2.1.5 | G64: Гідроізоляційна та пароізоляція стін та стелі | I64: чол/год | J64: =1080/7 -> 154.28571 | K64: 200 | M64: =J64*K64 -> 30857.143 | N64: =J64*L64 -> 0 | O64: =N64+M64 -> 30857.143
A65: 2.1.6 | B65: Зарплата производственного персонала | C65: Робота | D65: Виробництво/Будівництво | E65: Отделка | F65: 2.1.6 | G65: Утеплення стеля та стіни | I65: чол/год | J65: =1080/7 -> 154.28571 | K65: 200 | M65: =J65*K65 -> 30857.143 | N65: =J65*L65 -> 0 | O65: =N65+M65 -> 30857.143
A66: 2.1.7 | B66: Зарплата производственного персонала | C66: Робота | D66: Виробництво/Будівництво | E66: Отделка | F66: 2.1.7 | G66: Монтаж фінішного оздоблення | I66: чол/год | J66: =1080/7 -> 154.28571 | K66: 200 | M66: =J66*K66 -> 30857.143 | N66: =J66*L66 -> 0 | O66: =N66+M66 -> 30857.143
A67: 2.2 | E67: Отделка | F67: 2.2 | G67: МАТЕРІАЛИ | M67: =J67*K67 -> 0 | N67: =J67*L67 -> 0 | O67: =N67+M67 -> 0
A68: 2.2.1 | B68: Строительные материалы | C68: Матеріал | D68: Виробництво/Будівництво | E68: Отделка | F68: 2.2.1 | G68: Вітробарєр | H68: Мембрана | I68: м2 | J68: 400 | L68: 13 | M68: =J68*K68 -> 0 | N68: =J68*L68 -> 5200 | O68: =N68+M68 -> 5200
A69: 2.2.2 | B69: Строительные материалы | C69: Матеріал | D69: Виробництво/Будівництво | E69: Отделка | F69: 2.2.2 | G69: Шуруп універсальний цинк жовтий ПОВНА РІЗЬБА DIN 7997 4,5*45 | H69: Саморіз | I69: шт | J69: 5000 | L69: 0.47 | M69: =J69*K69 -> 0 | N69: =J69*L69 -> 2350 | O69: =N69+M69 -> 2350
A70: 2.2.3 | B70: Строительные материалы | C70: Матеріал | D70: Виробництво/Будівництво | E70: Отделка | F70: 2.2.3 | G70: Паро-гідро бар'єр | H70: Мембрана | I70: м2 | J70: 580 | L70: 13 | M70: =J70*K70 -> 0 | N70: =J70*L70 -> 7540 | O70: =N70+M70 -> 7540
A71: 2.2.4 | B71: Строительные материалы | C71: Матеріал | D71: Виробництво/Будівництво | E71: Отделка | F71: 2.2.4 | G71: Пінопласт 15 кг/м3 товщина 100 мм | H71: Пінопласт | I71: м2 | J71: 120 | L71: 220 | M71: =J71*K71 -> 0 | N71: =J71*L71 -> 26400 | O71: =N71+M71 -> 26400
A72: 2.2.5 | B72: Строительные материалы | C72: Матеріал | D72: Виробництво/Будівництво | E72: Отделка | F72: 2.2.5 | G72: Пінопласт 15 кг/м3 товщина 50 мм | H72: Пінопласт | I72: м2 | J72: 120 | L72: 118 | M72: =J72*K72 -> 0 | N72: =J72*L72 -> 14160 | O72: =N72+M72 -> 14160
A73: 2.2.6 | B73: Строительные материалы | C73: Матеріал | D73: Виробництво/Будівництво | E73: Отделка | F73: 2.2.6 | G73: Мінеральна вата щільність 35 кг/м3 (100 мм) | H73: мінеральна вата | I73: м2 | J73: 230 | L73: 181 | M73: =J73*K73 -> 0 | N73: =J73*L73 -> 41630 | O73: =N73+M73 -> 41630
A74: 2.2.7 | B74: Строительные материалы | C74: Матеріал | D74: Виробництво/Будівництво | E74: Отделка | F74: 2.2.7 | G74: Мінеральна вата щільність 35 кг/м3 (50 мм) | H74: мінеральна вата | I74: м2 | J74: 560 | L74: 90.5 | M74: =J74*K74 -> 0 | N74: =J74*L74 -> 50680 | O74: =N74+M74 -> 50680
A75: 2.2.8 | B75: Строительные материалы | C75: Матеріал | D75: Виробництво/Будівництво | E75: Отделка | F75: 2.2.8 | G75: ЦСП панель 20 мм 3,2*1,2 | H75: Плита ЦСП | I75: шт | J75: 36 | L75: 7700 | M75: =J75*K75 -> 0 | N75: =J75*L75 -> 277200 | O75: =N75+M75 -> 277200
A76: 2.2.9 | B76: Строительные материалы | C76: Матеріал | D76: Виробництво/Будівництво | E76: Отделка | F76: 2.2.9 | G76: Лінолеум сірий комерційний | H76: Лінолеум | I76: м2 | J76: 160 | L76: 478 | M76: =J76*K76 -> 0 | N76: =J76*L76 -> 76480 | O76: =N76+M76 -> 76480
A77: 2.2.10 | B77: Строительные материалы | C77: Матеріал | D77: Виробництво/Будівництво | E77: Отделка | F77: 2.2.10 | G77: Клей для лінолеума | H77: Клей для лінолеума | I77: кг | J77: 25 | L77: 393 | M77: =J77*K77 -> 0 | N77: =J77*L77 -> 9825 | O77: =N77+M77 -> 9825
A78: 2.2.11 | B78: Строительные материалы | C78: Матеріал | D78: Виробництво/Будівництво | E78: Отделка | F78: 2.2.11 | G78: Фарба 3 в 1 сіра | H78: Фарба | I78: кг | J78: 70 | L78: 216 | M78: =J78*K78 -> 0 | N78: =J78*L78 -> 15120 | O78: =N78+M78 -> 15120
A79: 2.2.12 | B79: Строительные материалы | C79: Матеріал | D79: Виробництво/Будівництво | E79: Отделка | F79: 2.2.12 | G79: Оцинкована решітка 1000х1000 | H79: Оцинкована решітка | I79: шт | J79: 1 | L79: 6340 | M79: =J79*K79 -> 0 | N79: =J79*L79 -> 6340 | O79: =N79+M79 -> 6340
... A88: 2.2.21 | B88: Строительные материалы | C88: Матеріал | D88: Виробництво/Будівництво | E88: Отделка | F88: 2.2.21 | G88: Брус 50*50 сосна стругана | H88: Брус | I88: м.п | J88: 1900 | L88: 57 | M88: =J88*K88 -> 0 | N88: =J88*L88 -> 108300 | O88: =N88+M88 -> 108300
B89: Строительные материалы | C89: Матеріал | D89: Виробництво/Будівництво | E89: Отделка | F89: 2.2.22 | G89: Дошка 20*100 | H89: Дошка | I89: м.п | J89: 302 | L89: 33 | M89: =J89*K89 -> 0 | N89: =J89*L89 -> 9966 | O89: =N89+M89 -> 9966
B90: Строительные материалы | C90: Матеріал | D90: Виробництво/Будівництво | E90: Отделка | F90: 2.2.23 | G90: Страж (оброблення деревини) | H90: Вогнезахист | I90: кг | J90: 15 | L90: 167 | M90: =J90*K90 -> 0 | N90: =J90*L90 -> 2505 | O90: =N90+M90 -> 2505
B91: Строительные материалы | C91: Матеріал | D91: Виробництво/Будівництво | E91: Отделка | F91: 2.2.24 | G91: ОСБ плита 10 мм 1250*2500 | H91: Плита ОСБ | I91: шт | J91: 202 | L91: 690 | M91: =J91*K91 -> 0 | N91: =J91*L91 -> 139380 | O91: =N91+M91 -> 139380
B92: Строительные материалы | C92: Матеріал | D92: Виробництво/Будівництво | E92: Отделка | F92: 2.2.25 | G92: Дверцята ревізійні пластикові DOMOVENT Л 100x100 | H92: Дверцята ревізійні | I92: шт | J92: 46 | L92: 51 | M92: =J92*K92 -> 0 | N92: =J92*L92 -> 2346 | O92: =N92+M92 -> 2346
B93: Строительные материалы | C93: Матеріал | D93: Виробництво/Будівництво | E93: Отделка | F93: 2.2.26 | G93: Герметик акриловий латексний білий | H93: Герметик | I93: шт | J93: 16 | L93: 146 | M93: =J93*K93 -> 0 | N93: =J93*L93 -> 2336 | O93: =N93+M93 -> 2336
B94: Строительные материалы | C94: Матеріал | D94: Виробництво/Будівництво | E94: Отделка | F94: 2.2.27 | G94: Клей монтажнй білий | H94: Клей | I94: шт | J94: 12 | L94: 204 | M94: =J94*K94 -> 0 | N94: =J94*L94 -> 2448 | O94: =N94+M94 -> 2448
B95: Строительные материалы | C95: Матеріал | D95: Виробництво/Будівництво | E95: Отделка | F95: 2.2.28 | G95: Теплий відкос | H95: Теплий відкос | I95: лист | J95: 5 | L95: 1670 | M95: =J95*K95 -> 0 | N95: =J95*L95 -> 8350 | O95: =N95+M95 -> 8350
B96: Строительные материалы | C96: Матеріал | D96: Виробництво/Будівництво | E96: Отделка | F96: 2.2.29 | G96: Лінолеум стіновий білий | H96: Лінолеум | I96: м2 | J96: 316 | L96: 456 | M96: =J96*K96 -> 0 | N96: =J96*L96 -> 144096 | O96: =N96+M96 -> 144096
B97: Строительные материалы | C97: Матеріал | D97: Виробництво/Будівництво | E97: Отделка | F97: 2.2.30 | G97: Кутики білі 30*30 мм 2,7м | H97: Кутики пластикові | I97: шт | J97: 36 | L97: 46 | M97: =J97*K97 -> 0 | N97: =J97*L97 -> 1656 | O97: =N97+M97 -> 1656
B98: Строительные материалы | C98: Матеріал | D98: Виробництво/Будівництво | E98: Отделка | F98: 2.2.31 | G98: Кутики білі 50*50 мм 2,7м | H98: Кутики пластикові | I98: шт | J98: 42 | L98: 57 | M98: =J98*K98 -> 0 | N98: =J98*L98 -> 2394 | O98: =N98+M98 -> 2394
B99: Строительные материалы | C99: Матеріал | D99: Виробництво/Будівництво | E99: Отделка | F99: 2.2.32 | G99: Піна клей | H99: Піна клей | I99: шт | J99: 10 | L99: 250 | M99: =J99*K99 -> 0 | N99: =J99*L99 -> 2500 | O99: =N99+M99 -> 2500
B100: Строительные материалы | C100: Матеріал | D100: Виробництво/Будівництво | E100: Отделка | F100: 2.2.33 | G100: ПВХ вагонка 8мм товщина 250 мм ширина без шовна біла | H100: ПВХ вагонка | I100: м2 | J100: 150 | L100: 246 | M100: =J100*K100 -> 0 | N100: =J100*L100 -> 36900 | O100: =N100+M100 -> 36900
B101: Строительные материалы | C101: Матеріал | D101: Виробництво/Будівництво | E101: Отделка | F101: 2.2.34 | G101: Лента К2 ширина 150 мм | H101: Лента | I101: м.п. | J101: 80 | L101: 43 | M101: =J101*K101 -> 0 | N101: =J101*L101 -> 3440 | O101: =N101+M101 -> 3440
B102: Строительные материалы | C102: Матеріал | D102: Виробництво/Будівництво | E102: Отделка | F102: 2.2.35 | G102: Плінтус на підлогу висота 100 мм | H102: Плінтус | I102: м.п | J102: 180 | L102: 72 | M102: =J102*K102 -> 0 | N102: =J102*L102 -> 12960 | O102: =N102+M102 -> 12960 | Q102: +
A103: ІІІ | F103: ІІІ | G103: Фасад | H103: Фасад | M103: =J103*K103 -> 0 | N103: =J103*L103 -> 0 | O103: =N103+M103 -> 0
A104: 3.1 | F104: 3.1 | G104: РОБОТА | M104: =J104*K104 -> 0 | N104: =J104*L104 -> 0 | O104: =N104+M104 -> 0
A105: 3.1.1 | B105: Зарплата производственного персонала | C105: Робота | D105: Виробництво/Будівництво | E105: Фасад | F105: 3.1.1 | G105: монтаж обрешітки по каркасу | I105: чол/год | J105: =3*8*1*8 -> 192 | K105: 200 | M105: =J105*K105 -> 38400 | N105: =J105*L105 -> 0 | O105: =N105+M105 -> 38400
A106: 3.1.2 | B106: Зарплата производственного персонала | C106: Робота | D106: Виробництво/Будівництво | E106: Фасад | F106: 3.1.2 | G106: Гідроізоляційна плівка | I106: чол/год | J106: =3*8*0.5*8 -> 96 | K106: 200 | M106: =J106*K106 -> 19200 | N106: =J106*L106 -> 0 | O106: =N106+M106 -> 19200
A107: 3.1.3 | B107: Зарплата производственного персонала | C107: Робота | D107: Виробництво/Будівництво | E107: Фасад | F107: 3.1.3 | G107: монтаж фасаду та покрівлі | I107: чол/год | J107: =3*8*2*8 -> 384 | K107: 200 | M107: =J107*K107 -> 76800 | N107: =J107*L107 -> 0 | O107: =N107+M107 -> 76800
A108: 3.1 | E108: Фасад | F108: 3.1 | G108: МАТЕРІАЛИ | M108: =J108*K108 -> 0 | N108: =J108*L108 -> 0 | O108: =N108+M108 -> 0
A109: 3.1.1 | B109: Строительные материалы | C109: Матеріал | D109: Виробництво/Будівництво | E109: Фасад | F109: 3.1.1 | G109: Порфлист ПК 20 довжина 6070 мм Покрівля РАЛ 9003 | H109: Профнастил | I109: м.кв. | J109: 145.68 | L109: 263 | M109: =J109*K109 -> 0 | N109: =J109*L109 -> 38313.84 | O109: =N109+M109 -> 38313.84
A110: 3.1.2 | B110: Строительные материалы | C110: Матеріал | D110: Виробництво/Будівництво | E110: Фасад | F110: 3.1.2 | G110: Порфлист ПК 10 довжина 2450 Стіни РАЛ 9003 | H110: Профнастил | I110: м.кв. | J110: 75 | L110: 261 | M110: =J110*K110 -> 0 | N110: =J110*L110 -> 19575 | O110: =N110+M110 -> 19575
A111: 3.1.3 | B111: Строительные материалы | C111: Матеріал | D111: Виробництво/Будівництво | E111: Фасад | F111: 3.1.3 | G111: Порфлист ПК 10 Довжина 3100 мм Стіни РАЛ 9003 | H111: Профнастил | I111: м.кв. | J111: 59.52 | L111: 261 | M111: =J111*K111 -> 0 | N111: =J111*L111 -> 15534.72 | O111: =N111+M111 -> 15534.72
F112: 3.1.4 | G112: Гладкий былий РАЛ 9003 довжина 2800 | H112: Гладкий лист метал | I112: м.кв. | J112: 73.5 | L112: 249 | M112: =J112*K112 -> 0 | N112: =J112*L112 -> 18301.5 | O112: =N112+M112 -> 18301.5
A113: 3.1.4 | B113: Строительные материалы | C113: Матеріал | D113: Виробництво/Будівництво | E113: Фасад | F113: 3.1.5 | G113: Порфлист ПК 8 довжина 2450мм (підшивка дна модуля) | H113: Профнастил | I113: м.кв. | J113: 132 | L113: 260 | M113: =J113*K113 -> 0 | N113: =J113*L113 -> 34320 | O113: =N113+M113 -> 34320 | Q113: +
A114: 3.1.7 | B114: МШП | C114: Матеріал | D114: Виробництво/Будівництво | E114: Фасад | F114: 3.1.6
A115: IV | F115: IV | G115: Вікна/двері | H115: Вікна | M115: =J115*K115 -> 0 | N115: =J115*L115 -> 0 | O115: =N115+M115 -> 0
A116: 4.1 | F116: 4.1 | G116: РОБОТА | M116: =J116*K116 -> 0 | N116: =J116*L116 -> 0 | O116: =N116+M116 -> 0
A117: 4.1.1 | B117: Зарплата производственного персонала | C117: Робота | D117: Виробництво/Будівництво | E117: Окна/двери | F117: 4.1.1 | G117: монтаж вікон | I117: чол/год | J117: =3*8*4 -> 96 | K117: 200 | M117: =J117*K117 -> 19200 | N117: =J117*L117 -> 0 | O117: =N117+M117 -> 19200
...

Sheet анализ виготовлення
A1: Найменування робіт | D1: Статус | E1: Факт виконання | F1: аналіз годин до закінчення, плановий
A2: Приймання матеріалу | B2: чол/год | C2: =480/8 -> 60 | D2: виконується | F2: 25
A3: Обробка матеріалу (дерево) | B3: чол/год | C3: =480/8 -> 60 | F3: 60
A4: Нарізання деталей зігдно креслень | B4: чол/год | C4: =480/8 -> 60 | D4: 1
A5: Збирання деталей | B5: чол/год | C5: =480/8 -> 60 | D5: 0.5 | F5: =30 -> 30
A6: зварювання (дерево зєдання) | B6: чол/год | C6: =480/8 -> 60 | D6: 0.5 | F6: =30 -> 30
A7: Влаштування підшиви модуля | B7: чол/год | C7: =480/8 -> 60 | D7: 0.5 | F7: =30 -> 30
A8: Грунтування металокаркасу | B8: чол/год | C8: =480/8 -> 60 | F8: =C8 -> 60
A9: Фарубування металокаркасу | B9: чол/год | C9: =480/8 -> 60 | F9: =C9 -> 60
A10: Утеплення та гідроізоляція підлоги | B10: чол/год | C10: =1080/7 -> 154.28571 | F10: =C10 -> 154.28571
A11: Монтаж брусу по каркасу | B11: чол/год | C11: =1080/7 -> 154.28571 | F11: =C11 -> 154.28571
A12: Пароізоляційна мембрана; | B12: чол/год | C12: =1080/7 -> 154.28571 | F12: =C12 -> 154.28571
A13: Укладання Настил підлоги | B13: чол/год | C13: =1080/7 -> 154.28571 | F13: =C13 -> 154.28571
A14: Гідроізоляційна та пароізоляція стін та стелі | B14: чол/год | C14: =1080/7 -> 154.28571 | F14: =C14 -> 154.28571
A15: Утеплення стеля та стіни | B15: чол/год | C15: =1080/7 -> 154.28571 | F15: =C15 -> 154.28571
A16: Монтаж фінішного оздоблення | B16: чол/год | C16: =1080/7 -> 154.28571 | F16: =C16 -> 154.28571
A17: монтаж обрешітки по каркасу | B17: чол/год | C17: =3*8*1*8 -> 192 | F17: =C17 -> 192
A18: Гідроізоляційна плівка | B18: чол/год | C18: =3*8*0.5*8 -> 96 | F18: =C18 -> 96
A19: монтаж фасаду та покрівлі | B19: чол/год | C19: =3*8*2*8 -> 384 | F19: =C19 -> 384
A20: монтаж вікон | B20: чол/год | C20: =3*8*4 -> 96 | F20: =C20 -> 96
A21: монтаж вхідних дверей | B21: чол/год | C21: =2*8*1 -> 16 | F21: =C21 -> 16
A22: монтаж мдф дверей | B22: чол/год | C22: 0 | F22: =C22 -> 0
A23: монтаж металопластикових дврей | B23: чол/год | C23: =3*8*4 -> 96 | F23: =C23 -> 96
A24: монтаж трубопроводів | B24: чол/год | C24: =100/4 -> 25 | F24: =C24 -> 25
A25: монтаж каналізаційних труб | B25: чол/год | C25: =100/4 -> 25 | F25: =C25 -> 25
A26: монтаж сантехнічних приборів | B26: чол/год | C26: =100/4 -> 25 | F26: =C26 -> 25
A27: підключення та перевірка сантехнічного обладнання | B27: чол/год | C27: =100/4 -> 25 | F27: =C27 -> 25
A28: табель | E28: 155 | F28: =C28 -> 0
A29: Загальна кількість, год | C29: =SUM(C2:C27) -> 2540 | E29: =SUM(E2:E28) -> 155 | F29: =SUM(F2:F28) -> 2355
