Workbook
Name Excel_BuiltIn_Print_Area_4: "#REF!"
Name Excel_BuiltIn_Print_Area_4_1: "#REF!"
Name Excel_BuiltIn_Print_Area_7: "#REF!"
Name Excel_BuiltIn_Print_Area_7_1: "#REF!"

Sheet расчет 2020
A2: 1. Расчет комиссии ФА: | C2: =AVERAGE(E4:E15) -> 0.1203793
C3: Всего | D3: в т.ч. комиссия | E3: удельный вес комиссии
B4: 1 | C4: =21734908.08+3039907.5 -> 24774816 | D4: 3039907.5 | E4: =D4/C4 -> 0.12270152
B5: 2 | C5: 2085216.7 | D5: 250168.02 | E5: =D5/C5 -> 0.11997219
B6: 3 | C6: 1619210.3 | D6: 187157.29 | E6: =D6/C6 -> 0.11558554
B7: 4 | C7: 6381759.2 | D7: 713762.83 | E7: =D7/C7 -> 0.11184421
B8: 5 | C8: 4404553.6 | D8: 504620.64 | E8: =D8/C8 -> 0.11456794
B9: 6 | C9: 5156496.2 | D9: 640953.8 | E9: =D9/C9 -> 0.12430026
B10: 7 | C10: 10920915 | D10: 1332106.5 | E10: =D10/C10 -> 0.12197756
B11: 8 | C11: 1984735.1 | D11: 252504.11 | E11: =D11/C11 -> 0.12722308
B12: 9 | C12: 3501909.8 | D12: 427337.8 | E12: =D12/C12 -> 0.12202993
B13: 10 | C13: 8418994.3 | D13: 1036294.3 | E13: =D13/C13 -> 0.12309003
B14: 11 | C14: 4529395.4 | D14: 544927.64 | E14: =D14/C14 -> 0.12030914
B15: 12 | C15: 3867500 | D15: 467775 | E15: =D15/C15 -> 0.12095023
A17: 2. | B17: Чистая прибыль: | C17: =#REF! -> #REF!
B18: Дивиденды выплачены | C18: =2051500+250000+246471 -> 2547971
B19: Покупка ОС | C19: =SUM(C21:C25) -> 23342228
B20: в т.ч.:
B21: офис | C21: =ОС!E41+88654.88+28990+12399.97+9971+18496.99 -> 262876.84
B22: техника | C22: =ОС!E39+806079.43+11600.04 -> 20594884
B23: производственные ОС | C23: =1348943.82+134648.07+ОС!E40+66223.6+41478.04+153811.68 -> 2167456.5
B24: ПК, ПО | C24: =242313.65+36673+600+37424 -> 317010.65
B26: фин.помощь,поплн.капит. | C26: =1840475+2243327+4623157-2186000 -> 6520959
C27: =C17-C18-C19+C26 -> #REF!
B29: не проведен:
B30: Пологи
B33: Приднепровский
C36: =SUM(C30:C35) -> 0
B38: резервный фонд (ф1 и Ф2 кроме ячейки согласно фиксов) | C38: =1300000+200000 -> 1500000
C40: =C27+C36-C38 -> #REF!
B41: тягач в январе | C41: -500000
C42: =C40+C41 -> #REF!

Sheet ОС
A8: Платежное поручение исходящее 9463 от 28.01.2020 0:00:00 | B8: РДК 250 | D8: -246 540,00 | E8: -246540 | F8: техника
A9: Платежное поручение исходящее 9502 от 31.01.2020 0:00:00 | B9: Гусиничные экскаватор | D9: -750 000,00 | E9: -750000 | F9: техника
A10: Расходный кассовый ордер N00017577 от 04.02.2020 12:00:04 | B10: покупка экскаватора JCB 220 34 400 $ | C10: -852 432,00 | E10: -852432 | F10: техника
A11: Расходный кассовый ордер N00016963 от 05.02.2020 15:05:30 | B11: Покупка гусенничного экскаватора (33 300 $) | C11: -833 215,00 | E11: -833215 | F11: техника
A12: Платежное поручение исходящее 9657 от 14.02.2020 0:00:00 | D12: -221 175,00 | E12: -221175 | F12: техника
A13: Платежное поручение исходящее 9816 от 18.02.2020 0:00:00 | B13: доплата за экскаватор 220 | D13: -108 395,00 | E13: -108395 | F13: техника
A14: Платежное поручение исходящее 000000513 от 31.03.2020 0:00:00 | D14: -562 600,00 | E14: -562600 | F14: техника
A15: Расходный кассовый ордер N00018123 от 31.03.2020 17:57:36 | B15: покупка экскаватора JCB 3Cх 16 650$ | C15: -466 200,00 | E15: -466200 | F15: техника
A16: Расходный кассовый ордер N00018408 от 17.04.2020 15:28:32 | B16: доплата за экскаватор 9000 $ 8350 - по курсу 28 грн - 233 800 + 300 по курсу 27,3 - 8 190 грн 350 по курсу 27,35 - 9572,5 | C16: -251 562,50 | E16: -251562.5 | F16: техника
A17: Платежное поручение исходящее 000001247 от 30.04.2020 11:19:10 | B17: покупка автокрана | D17: -2 062 500,00 | E17: -2062500 | F17: техника
A18: Расходный кассовый ордер N00018609 от 30.04.2020 11:23:57 | B18: Автокран 70 100$ курс 27 грн | C18: -1 892 700,00 | E18: -1892700 | F18: техника
A19: Платежное поручение исходящее 000001416 от 07.05.2020 12:50:04 | B19: Тахеометр -1 шт, штатив дер. с клипсами -1 шт , минипризма -1 шт, стикир для отбивки а-4 -1 шт | D19: -104 364,00 | E19: -104364 | F19: офис
A20: Платежное поручение исходящее 000001870 от 26.05.2020 0:00:00 | D20: -134 425,00 | E20: -134425 | F20: техника
A21: Платежное поручение исходящее 000002737 от 25.06.2020 0:00:00 | B21: Покупка нового автокрана | D21: -272 442,00 | E21: -272442 | F21: техника
A22: Платежное поручение исходящее 000002951 от 03.07.2020 0:00:00 | B22: самосвал | D22: -137 500,00 | E22: -137500 | F22: техника
A23: Расходный кассовый ордер N00019738 от 03.07.2020 17:29:02 | B23: покупка самосвала 25000$*27,05 | C23: -676 250,00 | E23: -676250 | F23: техника
A24: Расходный кассовый ордер N00019737 от 03.07.2020 17:29:43 | B24: покупка автокрана 54800$*27,05 | C24: -1 482 340,00 | E24: -1482340 | F24: техника
A25: Платежное поручение исходящее 000003272 от 14.07.2020 0:00:00 | B25: налоги за покупку камаза | D25: -2 205,88 | E25: -2205.88 | F25: техника
A26: Платежное поручение исходящее 000003274 от 14.07.2020 0:00:00 | B26: за покупку камаза | D26: -7 352,94 | E26: -7352.94 | F26: техника
A27: Платежное поручение исходящее 000003506 от 24.07.2020 10:52:58 | B27: автонавантажувач | D27: -1 210 170,00 | E27: -1210170 | F27: техника
A28: Платежное поручение исходящее 000004799 от 08.09.2020 13:24:04 | B28: Аванс телескоп 2 000 $ *27.77 | D28: -55 540,00 | E28: -55540 | F28: техника
A29: Платежное поручение исходящее 000005108 от 15.09.2020 15:52:23 | B29: Комплекс електродугової металізації КЕМ-1 (мод. 03-01) - 1 шт. | D29: -220 026,00 | E29: -220026 | F29: производственные ОС
A30: Платежное поручение исходящее 000005107 от 15.09.2020 15:52:31 | B30: Компресор А-1808 стаціонарний електричний гвинтовий - 1 шт; Система дистанційного керування - 1 шт; Повітряний рукав для дихання 9мм х 15мм, 40м - 1 шт; AirFlex-32 Повітряний рукав ID=32мм, бухта 40м - 0,125 шт; Фітинг Ду.32 DKR (1,1/4``-11) - 2 шт; Хомут для рукава 1.1/4" з захисними затискачами - 2 шт; Ресивер РВ 500.600-37 - 1 шт; Фильтр ФСВ -О-140 - 1 шт. | D30: -188 332,02 | E30: -188332.02 | F30: производственные ОС
A31: Платежное поручение исходящее 000005470 от 29.09.2020 11:30:56 | B31: кабеля для станка метализации и компрессора нового | D31: -13 993,25 | E31: -13993.25 | F31: производственные ОС
A32: Платежное поручение исходящее 000005610 от 30.09.2020 11:29:08 | B32: доплата телескоп 4 ( 46 100$ * 28.35) | D32: -1 306 935,00 | E32: -1306935 | F32: техника
A33: Платежное поручение исходящее 000005839 от 09.10.2020 9:37:38 | B33: Аванс XCMG 55 73 000 евро *33,36 + 0,65 % РКО | D33: -2 451 109,32 | E33: -2451109.3 | F33: техника
A34: Платежное поручение исходящее 000005905 от 09.10.2020 13:00:39 | B34: АВАНС 2000 дол. | D34: -56 520,00 | E34: -56520 | F34: техника
A35: Платежное поручение исходящее 000006053 от 15.10.2020 14:40:09 | B35: XCMG 55 = 69 500 евро *33,36+0,65 % РКО | D35: -2 333 590,38 | E35: -2333590.4 | F35: техника
A36: Платежное поручение исходящее 000006054 от 15.10.2020 14:45:16 | B36: Полная оплата 49 500 *28, 35 | D36: -1 403 505,00 | E36: -1403505 | F36: техника
E37: =SUM(E8:E36) -> -20303920
E39: =SUMIF($F$8:$F$36,F39,$E$8:$E$36)*-1 -> 19777205 | F39: техника
E40: =SUMIF($F$8:$F$36,F40,$E$8:$E$36)*-1 -> 422351.27 | F40: производственные ОС
E41: =SUMIF($F$8:$F$36,F41,$E$8:$E$36)*-1 -> 104364 | F41: офис
E42: =SUMIF($F$8:$F$36,F42,$E$8:$E$36)*-1 -> 0 | F42: Автомобіль Renauit Kangoo

Sheet PL_Сватово очередь 2
A2: PL Сватово очередь 2 | G2: Июнь 2020 | L2: Июль 2020 | Q2: Август 2020 | V2: Сентябрь 2020 | AA2: Октябрь 2020 | AF2: Ноябрь 2020 | AK2: Декабрь 2020 | AP2: Накопительный PL | AU2: Остаток PL январь 2020
A3: План итого
B4: Статья | C4: Сумма по Ф1, грн | D4: Сумма по Ф2, грн | E4: Сумма итого, грн | F4: % суммы затрат в общем объеме | G4: Сумма по Ф1, грн | H4: Сумма по Ф2, грн | I4: Сумма итого, грн | J4: % суммы затрат в общем объеме | K4: Комментарий | L4: Сумма по Ф1, грн | M4: Сумма по Ф2, грн | N4: Сумма итого, грн | O4: % суммы затрат в общем объеме | P4: Комментарий | Q4: Сумма по Ф1, грн | R4: Сумма по Ф2, грн | S4: Сумма итого, грн | T4: % суммы затрат в общем объеме | U4: Комментарий | V4: Сумма по Ф1, грн | W4: Сумма по Ф2, грн | X4: Сумма итого, грн | Y4: % суммы затрат в общем объеме | Z4: Комментарий | AA4: Сумма по Ф1, грн | AB4: Сумма по Ф2, грн | AC4: Сумма итого, грн | AD4: % суммы затрат в общем объеме | AE4: Комментарий | AF4: Сумма по Ф1, грн | AG4: Сумма по Ф2, грн | AH4: Сумма итого, грн | AI4: % суммы затрат в общем объеме | AJ4: Комментарий | AK4: Сумма по Ф1, грн | AL4: Сумма по Ф2, грн | AM4: Сумма итого, грн | AN4: % суммы затрат в общем объеме | AO4: Комментарий | AP4: Сумма по Ф1, грн | AQ4: Сумма по Ф2, грн | AR4: Сумма итого, грн | AS4: % суммы затрат в общем объеме | AT4: Комментарии | AU4: Сумма по Ф1, грн | AV4: Сумма по Ф2, грн | AW4: Сумма итого, грн | AX4: % суммы затрат в общем объеме | AY4: Комментарии
B5: Операционный доход | C5: =C6 -> 4590956 | D5: =D6 -> 0 | E5: =E6 -> 4590956 | G5: =G6 -> 0 | H5: =H6 -> 0 | I5: =I6 -> 0 | L5: =L6 -> 0 | M5: =M6 -> 0 | N5: =N6 -> 0 | Q5: =Q6 -> 0 | R5: =R6 -> 0 | S5: =S6 -> 0 | V5: =V6 -> 3025190.4 | W5: =W6 -> 0 | X5: =X6 -> 3025190.4 | AA5: =AA6 -> 1468296.4 | AB5: =AB6 -> 0 | AC5: =AC6 -> 1468296.4 | AF5: =AF6 -> 506097.41 | AG5: =AG6 -> 0 | AH5: =AH6 -> 506097.41 | AK5: =AK6 -> 0 | AL5: =AL6 -> 0 | AM5: =AM6 -> 0 | AP5: =AP6 -> 4999584.2 | AQ5: =AQ6 -> 0 | AR5: =AR6 -> 4999584.2 | AU5: =AU6 -> -408628.15 | AV5: =AV6 -> 0 | AW5: =AW6 -> -408628.15
A6: ='PL_Сватово очередь 2'!I6 -> 0 | B6: Выручка от продаж (товаров, работ, услуг) | C6: 4590956 | E6: =C6+D6 -> 4590956 | I6: =G6+H6 -> 0 | N6: =L6+M6 -> 0 | S6: =Q6+R6 -> 0 | V6: =524483.22+2500707.14 -> 3025190.4 | X6: =V6+W6 -> 3025190.4 | Z6: 2 Акта ( проведены бух учет в октябре) | AA6: =721198.33+254990+211690.21+280417.84 -> 1468296.4 | AC6: =AA6+AB6 -> 1468296.4 | AF6: =419194.7+86902.71 -> 506097.41 | AH6: =AF6+AG6 -> 506097.41 | AM6: =AK6+AL6 -> 0 | AP6: =G6+L6+Q6+V6+AA6+AF6+AK6 -> 4999584.2 | AQ6: =H6+M6+R6+W6+AB6+AG6+AL6 -> 0 | AR6: =AP6+AQ6 -> 4999584.2 | AU6: =C6-AP6 -> -408628.15 | AV6: =D6-AQ6 -> 0 | AW6: =AU6+AV6 -> -408628.15
B7: Доход от прочей операционной деятельности | E7: =C7+D7 -> 0 | I7: =G7+H7 -> 0 | N7: =L7+M7 -> 0 | S7: =Q7+R7 -> 0 | X7: =V7+W7 -> 0 | AC7: =AA7+AB7 -> 0 | AH7: =AF7+AG7 -> 0 | AM7: =AK7+AL7 -> 0 | AP7: =G7+L7+Q7+V7+AA7+AF7+AK7 -> 0 | AQ7: =H7+M7+R7+W7+AB7+AG7+AL7 -> 0 | AR7: =AP7+AQ7 -> 0 | AU7: =C7-AP7 -> 0 | AV7: =D7-AQ7 -> 0 | AW7: =AU7+AV7 -> 0
B8: Себестоимость проданой продукции (переменные производственные затраты) | C8: =SUM(C9:C31) -> 2057027 | D8: =SUM(D9:D31) -> 856715 | E8: =SUM(E9:E31) -> 2913742 | F8: =E8/$E$87 -> 0.91196428 | G8: =SUM(G9:G31) -> 44655 | H8: =SUM(H9:H31) -> 30403 | I8: =SUM(I9:I31) -> 75058 | J8: =I8/$I$87 -> 0.9450119 | L8: =SUM(L9:L31) -> 956216.47 | M8: =SUM(M9:M31) -> 43331.796 | N8: =SUM(N9:N31) -> 999548.27 | O8: =N8/$N$87 -> 0.98991612 | Q8: =SUM(Q9:Q31) -> 218190.11 | R8: =SUM(R9:R31) -> 30888 | S8: =SUM(S9:S31) -> 249078.11 | T8: =S8/$S$87 -> 0.9499065 | V8: =SUM(V9:V31) -> 1081138 | W8: =SUM(W9:W31) -> 458642 | X8: =SUM(X9:X31) -> 1539780 | Y8: =X8/$X$87 -> 0.95830793 | AA8: =SUM(AA9:AA31) -> 381045.94 | AB8: =SUM(AB9:AB31) -> 260754.52 | AC8: =SUM(AC9:AC31) -> 641800.46 | AD8: =AC8/$AC$87 -> 0.94336814 | AF8: =SUM(AF9:AF31) -> 38804.423 | AG8: =SUM(AG9:AG31) -> 180831.36 | AH8: =SUM(AH9:AH31) -> 219635.78 | AI8: =AH8/$AH$87 -> 0.8969512 | AK8: =SUM(AK9:AK31) -> 2054.406 | AL8: =SUM(AL9:AL31) -> 80000 | AM8: =SUM(AM9:AM31) -> 82054.406 | AN8: =AM8/$AM$87 -> 0.86833214 | AP8: =SUM(AP9:AP31) -> 2722104.4 | AQ8: =SUM(AQ9:AQ31) -> 1084850.7 | AR8: =SUM(AR9:AR31) -> 3806955.1 | AS8: =AR8/$AR$87 -> 0.95733641 | AU8: =SUM(AU9:AU31) -> -665077.39 | AV8: =SUM(AV9:AV31) -> -228135.68 | AW8: =SUM(AW9:AW31) -> -893213.06 | AX8: =AW8/$AW$87 -> 1.1257942
B9: ЗП производственного персонала | C9: 109480 | E9: =C9+D9 -> 109480 | F9: =E9/$E$87 -> 0.034265851 | G9: =4*3421.25 -> 13685 | I9: =G9+H9*1 -> 13685 | K9: 0,5 мес Сватовские | L9: 30791.25 | N9: =L9+M9*1 -> 30791.25 | O9: =N9/$N$87 -> 0.03049453 | Q9: =4*6842.5 -> 27370 | S9: =Q9+R9*1 -> 27370 | T9: =S9/$S$87 -> 0.10438067 | U9: бр Сватовские | V9: 27370 | X9: =V9+W9*1 -> 27370 | Y9: =X9/$X$87 -> 0.017034179 | Z9: 4 чел бр.Сватовские | AA9: =6842.5*4 -> 27370 | AC9: =AA9+AB9*1 -> 27370 | AD9: =AC9/$AC$87 -> 0.040230551 | AE9: бр.Сватовские | AF9: 6516.68 | AH9: =AF9+AG9*1 -> 6516.68 | AI9: =AH9/$AH$87 -> 0.026612895 | AM9: =AK9+AL9*1 -> 0 | AN9: =AM9/$AM$87 -> 0 | AP9: =G9+L9+Q9+V9+AA9+AF9+AK9 -> 133102.93 | AQ9: =H9+M9+R9+W9+AB9+AG9+AL9 -> 0 | AR9: =AP9+AQ9*1 -> 133102.93 | AS9: =AR9/$AR$87 -> 0.033471443 | AU9: =C9-AP9 -> -23622.93 | AV9: =D9-AQ9 -> 0 | AW9: =AU9+AV9*1 -> -23622.93 | AX9: =AW9/$AW$87 -> 0.029774035
B10: Удержание с зарплаты производственного персонала | C10: 26520 | E10: =C10+D10 -> 26520 | F10: =E10/$E$87 -> 0.0083004236 | G10: =4*8500*19.5% -> 6630 | I10: =G10+H10*1 -> 6630 | L10: 7458.75 | N10: =L10+M10*1 -> 7458.75 | O10: =N10/$N$87 -> 0.0073868737 | Q10: =8050*19.5%*4 -> 6279 | S10: =Q10+R10*1 -> 6279 | T10: =S10/$S$87 -> 0.023946155 | V10: 6630 | X10: =V10+W10*1 -> 6630 | Y10: =X10/$X$87 -> 0.0041262917 | AA10: =1658*4 -> 6632 | AC10: =AA10+AB10*1 -> 6632 | AD10: =AC10/$AC$87 -> 0.0097482285 | AF10: =AF9/0.805*0.195 -> 1578.5747 | AH10: =AF10+AG10*1 -> 1578.5747 | AI10: =AH10/$AH$87 -> 0.0064466018 | AM10: =AK10+AL10*1 -> 0 | AN10: =AM10/$AM$87 -> 0 | AP10: =G10+L10+Q10+V10+AA10+AF10+AK10 -> 35208.325 | AQ10: =H10+M10+R10+W10+AB10+AG10+AL10 -> 0 | AR10: =AP10+AQ10*1 -> 35208.325 | AS10: =AR10/$AR$87 -> 0.0088538505 | AU10: =C10-AP10 -> -8688.3247 | AV10: =D10-AQ10 -> 0 | AW10: =AU10+AV10*1 -> -8688.3247 | AX10: =AW10/$AW$87 -> 0.010950652
B11: Начисления на зарплату производственного персонала | C11: 29920 | E11: =C11+D11 -> 29920 | F11: =E11/$E$87 -> 0.0093645804 | G11: =4*8500*22% -> 7480 | I11: =G11+H11*1 -> 7480 | L11: 8415 | N11: =L11+M11*1 -> 8415 | O11: =N11/$N$87 -> 0.0083339088 | Q11: =8050*22%*4 -> 7084 | S11: =Q11+R11*1 -> 7084 | T11: =S11/$S$87 -> 0.027016174 | V11: 7480 | X11: =V11+W11*1 -> 7480 | Y11: =X11/$X$87 -> 0.0046553035 | AA11: =1870*2 -> 3740 | AC11: =AA11+AB11*1 -> 3740 | AD11: =AC11/$AC$87 -> 0.0054973424 | AF11: =AF9/0.805*0.22 -> 1780.956 | AH11: =AF11+AG11*1 -> 1780.956 | AI11: =AH11/$AH$87 -> 0.0072730893 | AJ11: бр.Сватовские, 1 половина ноября | AM11: =AK11+AL11*1 -> 0 | AN11: =AM11/$AM$87 -> 0 | AP11: =G11+L11+Q11+V11+AA11+AF11+AK11 -> 35979.956 | AQ11: =H11+M11+R11+W11+AB11+AG11+AL11 -> 0 | AR11: =AP11+AQ11*1 -> 35979.956 | AS11: =AR11/$AR$87 -> 0.0090478929 | AU11: =C11-AP11 -> -6059.956 | AV11: =D11-AQ11 -> 0 | AW11: =AU11+AV11*1 -> -6059.956 | AX11: =AW11/$AW$87 -> 0.0076378902
B12: Зарплата ИТР | C12: 28980 | D12: 91020 | E12: =C12+D12 -> 120000 | F12: =E12/$E$87 -> 0.037558478 | G12: 9660 | H12: 20340 | I12: =G12+H12*1 -> 30000 | J12: =I12/$I$87 -> 0.37771266 | K12: Терещенко | L12: 9660 | M12: 20340 | N12: =L12+M12*1 -> 30000 | O12: =N12/$N$87 -> 0.029710905 | P12: Терещенко А июль | Q12: 9660 | R12: 17340 | S12: =Q12+R12*1 -> 27000 | T12: =S12/$S$87 -> 0.10296961 | U12: Терещенко А за минусом штрафа 3 000 грн | V12: 9660 | W12: 19340 | X12: =V12+W12*1 -> 29000 | Y12: =X12/$X$87 -> 0.018048636 | Z12: Терещенко сентябрь за минусом штрафа 1 000 грн | AA12: 4830 | AB12: =20340/2 -> 10170 | AC12: =AA12+AB12*1 -> 15000 | AD12: =AC12/$AC$87 -> 0.022048165 | AE12: Терещенко | AH12: =AF12+AG12*1 -> 0 | AI12: =AH12/$AH$87 -> 0 | AM12: =AK12+AL12*1 -> 0 | AN12: =AM12/$AM$87 -> 0 | AP12: =G12+L12+Q12+V12+AA12+AF12+AK12 -> 43470 | AQ12: =H12+M12+R12+W12+AB12+AG12+AL12 -> 87530 | AR12: =AP12+AQ12*1 -> 131000 | AS12: =AR12/$AR$87 -> 0.032942619 | AU12: =C12-AP12 -> -14490 | AV12: =D12-AQ12 -> 3490 | AW12: =AU12+AV12*1 -> -11000 | AX12: =AW12/$AW$87 -> 0.013864258
B13: Удержание с зарплаты ИТР | C13: 9360 | E13: =C13+D13 -> 9360 | F13: =E13/$E$87 -> 0.0029295613 | G13: =12000*19.5% -> 2340 | I13: =G13+H13*1 -> 2340 | J13: =I13/$I$87 -> 0.029461588 | L13: 2340 | N13: =L13+M13*1 -> 2340 | O13: =N13/$N$87 -> 0.0023174506 | Q13: 2340 | S13: =Q13+R13*1 -> 2340 | T13: =S13/$S$87 -> 0.0089240327 | V13: 2340 | X13: =V13+W13*1 -> 2340 | Y13: =X13/$X$87 -> 0.0014563382 | AA13: 1170 | AC13: =AA13+AB13*1 -> 1170 | AD13: =AC13/$AC$87 -> 0.0017197568 | AH13: =AF13+AG13*1 -> 0 | AI13: =AH13/$AH$87 -> 0 | AM13: =AK13+AL13*1 -> 0 | AN13: =AM13/$AM$87 -> 0 | AP13: =G13+L13+Q13+V13+AA13+AF13+AK13 -> 10530 | AQ13: =H13+M13+R13+W13+AB13+AG13+AL13 -> 0 | AR13: =AP13+AQ13*1 -> 10530 | AS13: =AR13/$AR$87 -> 0.002647983 | AU13: =C13-AP13 -> -1170 | AV13: =D13-AQ13 -> 0 | AW13: =AU13+AV13*1 -> -1170 | AX13: =AW13/$AW$87 -> 0.0014746529
B14: Начисления на зарплату ИТР | C14: 10560 | E14: =C14+D14 -> 10560 | F14: =E14/$E$87 -> 0.003305146 | G14: =12000*22% -> 2640 | I14: =G14+H14*1 -> 2640 | J14: =I14/$I$87 -> 0.033238714 | L14: 2640 | N14: =L14+M14*1 -> 2640 | O14: =N14/$N$87 -> 0.0026145596 | Q14: 2640 | S14: =Q14+R14*1 -> 2640 | T14: =S14/$S$87 -> 0.010068139 | V14: 2640 | X14: =V14+W14*1 -> 2640 | Y14: =X14/$X$87 -> 0.0016430483 | AA14: 1320 | AC14: =AA14+AB14*1 -> 1320 | AD14: =AC14/$AC$87 -> 0.0019402385 | AH14: =AF14+AG14*1 -> 0 | AI14: =AH14/$AH$87 -> 0 | AM14: =AK14+AL14*1 -> 0 | AN14: =AM14/$AM$87 -> 0 | AP14: =G14+L14+Q14+V14+AA14+AF14+AK14 -> 11880 | AQ14: =H14+M14+R14+W14+AB14+AG14+AL14 -> 0 | AR14: =AP14+AQ14*1 -> 11880 | AS14: =AR14/$AR$87 -> 0.002987468 | AU14: =C14-AP14 -> -1320 | AV14: =D14-AQ14 -> 0 | AW14: =AU14+AV14*1 -> -1320 | AX14: =AW14/$AW$87 -> 0.0016637109
B15: ЗП подсобников | E15: =C15+D15 -> 0 | F15: =E15/$E$87 -> 0 | I15: =G15+H15*1 -> 0 | N15: =L15+M15*1 -> 0 | O15: =N15/$N$87 -> 0 | S15: =Q15+R15*1 -> 0 | T15: =S15/$S$87 -> 0 | X15: =V15+W15*1 -> 0 | Y15: =X15/$X$87 -> 0 | AC15: =AA15+AB15*1 -> 0 | AD15: =AC15/$AC$87 -> 0 | AG15: 1500 | AH15: =AF15+AG15*1 -> 1500 | AI15: =AH15/$AH$87 -> 0.0061257177 | AJ15: ЗП подсобников | AM15: =AK15+AL15*1 -> 0 | AN15: =AM15/$AM$87 -> 0 | AP15: =G15+L15+Q15+V15+AA15+AF15+AK15 -> 0 | AQ15: =H15+M15+R15+W15+AB15+AG15+AL15 -> 1500 | AR15: =AP15+AQ15*1 -> 1500 | AS15: =AR15/$AR$87 -> 0.00037720556 | AU15: =C15-AP15 -> 0 | AV15: =D15-AQ15 -> -1500 | AW15: =AU15+AV15*1 -> -1500 | AX15: =AW15/$AW$87 -> 0.0018905806
B16: Оплата за выполненные работы | D16: 623695 | E16: =C16+D16 -> 623695 | F16: =E16/$E$87 -> 0.19520862 | I16: =G16+H16*1 -> 0 | N16: =L16+M16*1 -> 0 | O16: =N16/$N$87 -> 0 | S16: =Q16+R16*1 -> 0 | T16: =S16/$S$87 -> 0 | W16: =9340+56250+36695+178352 -> 280637 | X16: =V16+W16*1 -> 280637 | Y16: =X16/$X$87 -> 0.17465914 | Z16: Сборная - 56 250 грн Харьковские - 9 340 грн Жук - 36 695 грн Сватовские - 178 352 грн | AB16: =47520+34695+28253.64+86385.5+15945+33625 -> 246424.14 | AC16: =AA16+AB16*1 -> 246424.14 | AD16: =AC16/$AC$87 -> 0.36221333 | AE16: 47520 - Чешко 34695 - Жук 164209,14 - Сватовские | AG16: =2992+15600+13739.36 -> 32331.36 | AH16: =AF16+AG16*1 -> 32331.36 | AI16: =AH16/$AH$87 -> 0.13203519 | AJ16: 2992 - Сватовские 15600 - Хрьковские 13739,36 - бр.Михальского | AM16: =AK16+AL16*1 -> 0 | AN16: =AM16/$AM$87 -> 0 | AP16: =G16+L16+Q16+V16+AA16+AF16+AK16 -> 0 | AQ16: =H16+M16+R16+W16+AB16+AG16+AL16 -> 559392.5 | AR16: =AP16+AQ16*1 -> 559392.5 | AS16: =AR16/$AR$87 -> 0.14067064 | AU16: =C16-AP16 -> 0 | AV16: =D16-AQ16 -> 64302.5 | AW16: =AU16+AV16*1 -> 64302.5 | AX16: =AW16/$AW$87 -> -0.081046039
B17: Премия производственного персонала | D17: 30000 | E17: =C17+D17 -> 30000 | F17: =E17/$E$87 -> 0.0093896194 | I17: =G17+H17*1 -> 0 | M17: 300 | N17: =L17+M17*1 -> 300 | O17: =N17/$N$87 -> 0.00029710905 | P17: Первый бетон бр.Жука 4 чел *75грн | S17: =Q17+R17*1 -> 0 | T17: =S17/$S$87 -> 0 | X17: =V17+W17*1 -> 0 | Y17: =X17/$X$87 -> 0 | AC17: =AA17+AB17*1 -> 0 | AD17: =AC17/$AC$87 -> 0 | AH17: =AF17+AG17*1 -> 0 | AI17: =AH17/$AH$87 -> 0 | AL17: =30000+50000 -> 80000 | AM17: =AK17+AL17*1 -> 80000 | AN17: =AM17/$AM$87 -> 0.8465916 | AP17: =G17+L17+Q17+V17+AA17+AF17+AK17 -> 0 | AQ17: =H17+M17+R17+W17+AB17+AG17+AL17 -> 80300 | AR17: =AP17+AQ17*1 -> 80300 | AS17: =AR17/$AR$87 -> 0.020193071 | AU17: =C17-AP17 -> 0 | AV17: =D17-AQ17 -> -50300 | AW17: =AU17+AV17*1 -> -50300 | AX17: =AW17/$AW$87 -> 0.063397469
B18: Услуги сторонних организаций | C18: 741860 | E18: =C18+D18 -> 741860 | F18: =E18/$E$87 -> 0.23219277 | I18: =G18+H18*1 -> 0 | L18: =48.79*14000 -> 683060 | M18: 3880 | N18: =L18+M18*1 -> 686940 | O18: =N18/$N$87 -> 0.6803203 | P18: Изготовление добора "цинк" для бункеров приема и кровли цеха грануляции - 3 400 грн+ изготовление доп стропов, услуги электрика Цех металлоконструкций - Цех грануляции лузги - 48,79*14000= 683 060грн | R18: 200 | S18: =Q18+R18*1 -> 200 | T18: =S18/$S$87 -> 0.00076273784 | U18: работа токаря -200,00 | W18: 150000 | X18: =V18+W18*1 -> 150000 | Y18: =X18/$X$87 -> 0.093355016 | Z18: выдал Воронцов А.В - аванс Вектор -150 000,00 | AC18: =AA18+AB18*1 -> 0 | AD18: =AC18/$AC$87 -> 0 | AG18: 147000 | AH18: =AF18+AG18*1 -> 147000 | AI18: =AH18/$AH$87 -> 0.60032034 | AJ18: ТОВ Вектор перевод Европочтой -147 000,00 | AM18: =AK18+AL18*1 -> 0 | AN18: =AM18/$AM$87 -> 0 | AP18: =G18+L18+Q18+V18+AA18+AF18+AK18 -> 683060 | AQ18: =H18+M18+R18+W18+AB18+AG18+AL18 -> 301080 | AR18: =AP18+AQ18*1 -> 984140 | AS18: =AR18/$AR$87 -> 0.24748205 | AU18: =C18-AP18 -> 58800 | AV18: =D18-AQ18 -> -301080 | AW18: =AU18+AV18*1 -> -242280 | AX18: =AW18/$AW$87 -> 0.30536658
B19: Аренда строительного оборудования | E19: =C19+D19 -> 0 | F19: =E19/$E$87 -> 0 | I19: =G19+H19*1 -> 0 | M19: 600 | N19: =L19+M19*1 -> 600 | O19: =N19/$N$87 -> 0.0005942181 | P19: аренда трамбовки | S19: =Q19+R19*1 -> 0 | T19: =S19/$S$87 -> 0 | X19: =V19+W19*1 -> 0 | Y19: =X19/$X$87 -> 0 | AC19: =AA19+AB19*1 -> 0 | AD19: =AC19/$AC$87 -> 0 | AH19: =AF19+AG19*1 -> 0 | AI19: =AH19/$AH$87 -> 0 | AM19: =AK19+AL19*1 -> 0 | AN19: =AM19/$AM$87 -> 0 | AP19: =G19+L19+Q19+V19+AA19+AF19+AK19 -> 0 | AQ19: =H19+M19+R19+W19+AB19+AG19+AL19 -> 600 | AR19: =AP19+AQ19*1 -> 600 | AS19: =AR19/$AR$87 -> 0.00015088222 | AU19: =C19-AP19 -> 0 | AV19: =D19-AQ19 -> -600 | AW19: =AU19+AV19*1 -> -600 | AX19: =AW19/$AW$87 -> 0.00075623224
B20: Аренда опалубки | E20: =C20+D20 -> 0 | F20: =E20/$E$87 -> 0 | I20: =G20+H20*1 -> 0 | N20: =L20+M20*1 -> 0 | O20: =N20/$N$87 -> 0 | S20: =Q20+R20*1 -> 0 | T20: =S20/$S$87 -> 0 | X20: =V20+W20*1 -> 0 | Y20: =X20/$X$87 -> 0 | AC20: =AA20+AB20*1 -> 0 | AD20: =AC20/$AC$87 -> 0 | AH20: =AF20+AG20*1 -> 0 | AI20: =AH20/$AH$87 -> 0 | AM20: =AK20+AL20*1 -> 0 | AN20: =AM20/$AM$87 -> 0 | AP20: =G20+L20+Q20+V20+AA20+AF20+AK20 -> 0 | AQ20: =H20+M20+R20+W20+AB20+AG20+AL20 -> 0 | AR20: =AP20+AQ20*1 -> 0 | AS20: =AR20/$AR$87 -> 0 | AU20: =C20-AP20 -> 0 | AV20: =D20-AQ20 -> 0 | AW20: =AU20+AV20*1 -> 0 | AX20: =AW20/$AW$87 -> 0
B21: Арена техники | C21: 269500 | E21: =C21+D21 -> 269500 | F21: =E21/$E$87 -> 0.084350081 | I21: =G21+H21*1 -> 0 | L21: =(285*459.49)+(4181.06*1.2)+(818*27.42) -> 158401.48 | M21: 1500 | N21: =L21+M21*1 -> 159901.48 | O21: =N21/$N$87 -> 0.15836059 | P21: Автокран ХСМG - (285*459,49)= 130 954,65 Автокран закрыто актами - 5 017,27 грн Перебазировка Автокран ХСМG = 818км*27,42 грн = 22 429,56 грн | Q21: =(339*459.49) -> 155767.11 | S21: =Q21+R21*1 -> 155767.11 | T21: =S21/$S$87 -> 0.59404735 | U21: Автокран XCMG - 155 767 ,11 | X21: =V21+W21*1 -> 0 | Y21: =X21/$X$87 -> 0 | AC21: =AA21+AB21*1 -> 0 | AD21: =AC21/$AC$87 -> 0 | AH21: =AF21+AG21*1 -> 0 | AI21: =AH21/$AH$87 -> 0 | AM21: =AK21+AL21*1 -> 0 | AN21: =AM21/$AM$87 -> 0 | AP21: =G21+L21+Q21+V21+AA21+AF21+AK21 -> 314168.59 | AQ21: =H21+M21+R21+W21+AB21+AG21+AL21 -> 1500 | AR21: =AP21+AQ21*1 -> 315668.59 | AS21: =AR21/$AR$87 -> 0.079381298 | AU21: =C21-AP21 -> -44668.592 | AV21: =D21-AQ21 -> -1500 | AW21: =AU21+AV21*1 -> -46168.592 | AX21: =AW21/$AW$87 -> 0.058190296
B22: Логистические затраты | C22: 58900 | E22: =C22+D22 -> 58900 | F22: =E22/$E$87 -> 0.018434953 | I22: =G22+H22*1 -> 0 | L22: =36166.66*1.2 -> 43399.992 | M22: 100 | N22: =L22+M22*1 -> 43499.992 | O22: =N22/$N$87 -> 0.043080804 | P22: ДХ Транс Украина - 43 399,99 грн | R22: 200 | S22: =Q22+R22*1 -> 200 | T22: =S22/$S$87 -> 0.00076273784 | U22: доставка мшп | X22: =V22+W22*1 -> 0 | Y22: =X22/$X$87 -> 0 | AA22: 14800 | AC22: =AA22+AB22*1 -> 14800 | AD22: =AC22/$AC$87 -> 0.021754189 | AE22: 14 800,00 - БЕЛЕС ТРАНС"ПП | AF22: =11500 -> 11500 | AH22: =AF22+AG22*1 -> 11500 | AI22: =AH22/$AH$87 -> 0.046963836 | AJ22: 11 500,00 - БЕЛЕС ТРАНС"ПП | AM22: =AK22+AL22*1 -> 0 | AN22: =AM22/$AM$87 -> 0 | AP22: =G22+L22+Q22+V22+AA22+AF22+AK22 -> 69699.992 | AQ22: =H22+M22+R22+W22+AB22+AG22+AL22 -> 300 | AR22: =AP22+AQ22*1 -> 69999.992 | AS22: =AR22/$AR$87 -> 0.017602924 | AU22: =C22-AP22 -> -10799.992 | AV22: =D22-AQ22 -> -300 | AW22: =AU22+AV22*1 -> -11099.992 | AX22: =AW22/$AW$87 -> 0.013990286
B23: МШП | C23: 57900 | E23: =C23+D23 -> 57900 | F23: =E23/$E$87 -> 0.018121965 | H23: 1524 | I23: =G23+H23*1 -> 1524 | M23: 3966 | N23: =L23+M23*1 -> 3966 | O23: =N23/$N$87 -> 0.0039277816 | R23: 1520 | S23: =Q23+R23*1 -> 1520 | T23: =S23/$S$87 -> 0.0057968076 | V23: =14274.39*1.2 -> 17129.268 | W23: 960 | X23: =V23+W23*1 -> 18089.268 | Y23: =X23/$X$87 -> 0.011258159 | Z23: согласно списания | AA23: =3959.69*1.2 -> 4751.628 | AB23: 1040 | AC23: =AA23+AB23*1 -> 5791.628 | AD23: =AC23/$AC$87 -> 0.0085129845 | AE23: ф2 - мшп + доставка Терещенко | AH23: =AF23+AG23*1 -> 0 | AI23: =AH23/$AH$87 -> 0 | AK23: =1198.98*1.2+615.63 -> 2054.406 | AM23: =AK23+AL23*1 -> 2054.406 | AN23: =AM23/$AM$87 -> 0.021740536 | AP23: =G23+L23+Q23+V23+AA23+AF23+AK23 -> 23935.302 | AQ23: =H23+M23+R23+W23+AB23+AG23+AL23 -> 9010 | AR23: =AP23+AQ23*1 -> 32945.302 | AS23: =AR23/$AR$87 -> 0.0082847673 | AU23: =C23-AP23 -> 33964.698 | AV23: =D23-AQ23 -> -9010 | AW23: =AU23+AV23*1 -> 24954.698 | AX23: =AW23/$AW$87 -> -0.031452578
B24: Строительные материалы | C24: 609407 | D24: 32000 | E24: =C24+D24 -> 641407 | F24: =E24/$E$87 -> 0.20075225 | H24: 400 | I24: =G24+H24*1 -> 400 | N24: =L24+M24*1 -> 0 | O24: =N24/$N$87 -> 0 | S24: =Q24+R24*1 -> 0 | T24: =S24/$S$87 -> 0 | V24: =(684058.3+243453.41-99070.06)*1.2 -> 994129.98 | X24: =V24+W24*1 -> 994129.98 | Y24: =X24/$X$87 -> 0.61871347 | Z24: в т ч металл для изготовления м/к цеха = 411 865,41 грн с НДС за минусом склада обмена 118 884,07 грн | AA24: =(90507.85+165264.62+5412.79)*1.2 -> 313422.31 | AC24: =AA24+AB24*1 -> 313422.31 | AD24: =AC24/$AC$87 -> 0.46069245 | AF24: =14523.51*1.2 -> 17428.212 | AH24: =AF24+AG24*1 -> 17428.212 | AI24: =AH24/$AH$87 -> 0.071173538 | AM24: =AK24+AL24*1 -> 0 | AN24: =AM24/$AM$87 -> 0 | AP24: =G24+L24+Q24+V24+AA24+AF24+AK24 -> 1324980.5 | AQ24: =H24+M24+R24+W24+AB24+AG24+AL24 -> 400 | AR24: =AP24+AQ24*1 -> 1325380.5 | AS24: =AR24/$AR$87 -> 0.33329393 | AU24: =C24-AP24 -> -715573.5 | AV24: =D24-AQ24 -> 31600 | AW24: =AU24+AV24*1 -> -683973.5 | AX24: =AW24/$AW$87 -> 0.86207135
B25: Ремонты | C25: 8000 | E25: =C25+D25 -> 8000 | F25: =E25/$E$87 -> 0.0025038985 | I25: =G25+H25*1 -> 0 | N25: =L25+M25*1 -> 0 | O25: =N25/$N$87 -> 0 | R25: 650 | S25: =Q25+R25*1 -> 650 | T25: =S25/$S$87 -> 0.002478898 | U25: ремонт лебедки -650,00 | V25: =4359.16*1.2 -> 5230.992 | W25: 400 | X25: =V25+W25*1 -> 5630.992 | Y25: =X25/$X$87 -> 0.0035045423 | Z25: Виктория Макс - ремонт инструмента ф2 -Ремонт отбойника -400,00 | AC25: =AA25+AB25*1 -> 0 | AD25: =AC25/$AC$87 -> 0 | AH25: =AF25+AG25*1 -> 0 | AI25: =AH25/$AH$87 -> 0 | AM25: =AK25+AL25*1 -> 0 | AN25: =AM25/$AM$87 -> 0 | AP25: =G25+L25+Q25+V25+AA25+AF25+AK25 -> 5230.992 | AQ25: =H25+M25+R25+W25+AB25+AG25+AL25 -> 1050 | AR25: =AP25+AQ25*1 -> 6280.992 | AS25: =AR25/$AR$87 -> 0.0015794834 | AU25: =C25-AP25 -> 2769.008 | AV25: =D25-AQ25 -> -1050 | AW25: =AU25+AV25*1 -> 1719.008 | AX25: =AW25/$AW$87 -> -0.0021666154
B26: Прочие производственные затраты | C26: 45040 | E26: =C26+D26 -> 45040 | F26: =E26/$E$87 -> 0.014096949 | I26: =G26+H26*1 -> 0 | M26: =950+(4.83*1.2) -> 955.796 | N26: =L26+M26*1 -> 955.796 | O26: =N26/$N$87 -> 0.00094658547 | P26: резиновые сапоги 4 пары=950 грн | R26: 120 | S26: =Q26+R26*1 -> 120 | T26: =S26/$S$87 -> 0.0004576427 | U26: лекарства для рабочего -120,00 | V26: =64.83*1.2 -> 77.796 | W26: 305 | X26: =V26+W26*1 -> 382.796 | Y26: =X26/$X$87 -> 0.00023823951 | Z26: карандаш строительный, прочие Бытовые покупки ( одеяло для Терещенко А) -305,00 | AB26: 500 | AC26: =AA26+AB26*1 -> 500 | AD26: =AC26/$AC$87 -> 0.00073493882 | AE26: заправка баллона газом | AH26: =AF26+AG26*1 -> 0 | AI26: =AH26/$AH$87 -> 0 | AM26: =AK26+AL26*1 -> 0 | AN26: =AM26/$AM$87 -> 0 | AP26: =G26+L26+Q26+V26+AA26+AF26+AK26 -> 77.796 | AQ26: =H26+M26+R26+W26+AB26+AG26+AL26 -> 1880.796 | AR26: =AP26+AQ26*1 -> 1958.592 | AS26: =AR26/$AR$87 -> 0.00049252786 | AU26: =C26-AP26 -> 44962.204 | AV26: =D26-AQ26 -> -1880.796 | AW26: =AU26+AV26*1 -> 43081.408 | AX26: =AW26/$AW$87 -> -0.054299249
B27: Командировочные производственного персонала | C27: 51600 | E27: =C27+D27 -> 51600 | F27: =E27/$E$87 -> 0.016150145 | G27: 2220 | I27: =G27+H27*1 -> 2220 | J27: =I27/$I$87 -> 0.027950737 | K27: 1820- Терещенко 400 -Гончаренко | L27: 10050 | M27: 2800 | N27: =L27+M27*1 -> 12850 | O27: =N27/$N$87 -> 0.012726171 | P27: бр Жуки, Сватовские, Терещенко | Q27: 7050 | R27: 200 | S27: =Q27+R27*1 -> 7250 | T27: =S27/$S$87 -> 0.027649247 | U27: Терещенко - 3 250 грн Бр Жук, Гончаренко | V27: =8710-260 -> 8450 | W27: 3000 | X27: =V27+W27*1 -> 11450 | Y27: =X27/$X$87 -> 0.0071260996 | Z27: ф1 - ИТР - 4 550 Гончаренко - 3 500 + 400грн Голубев ф2 - бр.Чешко 2 чел = 3000 | AA27: 3010 | AC27: =AA27+AB27*1 -> 3010 | AD27: =AC27/$AC$87 -> 0.0044243317 | AE27: Терещенко - 910грн Гончаренко - 2 100 | AH27: =AF27+AG27*1 -> 0 | AI27: =AH27/$AH$87 -> 0 | AM27: =AK27+AL27*1 -> 0 | AN27: =AM27/$AM$87 -> 0 | AP27: =G27+L27+Q27+V27+AA27+AF27+AK27 -> 30780 | AQ27: =H27+M27+R27+W27+AB27+AG27+AL27 -> 6000 | AR27: =AP27+AQ27*1 -> 36780 | AS27: =AR27/$AR$87 -> 0.0092490803 | AU27: =C27-AP27 -> 20820 | AV27: =D27-AQ27 -> -6000 | AW27: =AU27+AV27*1 -> 14820 | AX27: =AW27/$AW$87 -> -0.018678936
B28: Аренда квартиры с коммунальными платежами | D28: 16000 | E28: =C28+D28 -> 16000 | F28: =E28/$E$87 -> 0.005007797 | H28: =3500+ 1000 -> 4500 | I28: =G28+H28*1 -> 4500 | K28: Аренда квартиры | M28: =3500+500 -> 4000 | N28: =L28+M28*1 -> 4000 | O28: =N28/$N$87 -> 0.003961454 | P28: Терещенко | R28: =3500+800 -> 4300 | S28: =Q28+R28*1 -> 4300 | T28: =S28/$S$87 -> 0.016398864 | U28: аренда квартиры 3500 Терещенко + к/у 800 грн за август | W28: 3500 | X28: =V28+W28*1 -> 3500 | Y28: =X28/$X$87 -> 0.0021782837 | Z28: без к/у, квартира в счет посл месяца | AB28: 550 | AC28: =AA28+AB28*1 -> 550 | AD28: =AC28/$AC$87 -> 0.0008084327 | AE28: К/у Терещенко за октябрь -550,00 | AH28: =AF28+AG28*1 -> 0 | AI28: =AH28/$AH$87 -> 0 | AM28: =AK28+AL28*1 -> 0 | AN28: =AM28/$AM$87 -> 0 | AP28: =G28+L28+Q28+V28+AA28+AF28+AK28 -> 0 | AQ28: =H28+M28+R28+W28+AB28+AG28+AL28 -> 16850 | AR28: =AP28+AQ28*1 -> 16850 | AS28: =AR28/$AR$87 -> 0.0042372758 | AU28: =C28-AP28 -> 0 | AV28: =D28-AQ28 -> -850 | AW28: =AU28+AV28*1 -> -850 | AX28: =AW28/$AW$87 -> 0.001071329
B29: Транспортные затраты производственного персонала | D29: 14000 | E29: =C29+D29 -> 14000 | F29: =E29/$E$87 -> 0.0043818224 | H29: =969+770 -> 1739 | I29: =G29+H29*1 -> 1739 | J29: =I29/$I$87 -> 0.021894744 | K29: Терещенко на обьект Нежин-Киев-Сватово+ такси | M29: =800+2900 -> 3700 | N29: =L29+M29*1 -> 3700 | O29: =N29/$N$87 -> 0.0036643449 | P29: 2700 - приезд бриг жука 4 чел (563 гр. Поезд киев-сватово+ проезд нежин - киев бла-блакар, доставка людей с инструментом на объект на такси 2*50 5 чел) Такси -800 грн | R29: 6358 | S29: =Q29+R29*1 -> 6358 | T29: =S29/$S$87 -> 0.024247436 | U29: Уезд с обьекта 4чел бр.Жука -1 200,00 Приезд бр.на проф лист 3 чел (топливо) -750,00 приезд монтажников силоса 5 чел -2 100,00 Проезд Голубева И согласно билетам -957,50 Приезд на обьект Воликова -350,00 Приезд на обьект Чешко Сиряченко ( заправка топливо) -1 000,00 | W29: 500 | X29: =V29+W29*1 -> 500 | Y29: =X29/$X$87 -> 0.00031118339 | Z29: Чешко,Сиряченко уезд с обьекта (газ на машину) -500,00 | AB29: 2070.38 | AC29: =AA29+AB29*1 -> 2070.38 | AD29: =AC29/$AC$87 -> 0.0030432053 | AE29: Проезд Голубева по подотчету Киев-Сватово -810,38 Проезд Терещенко по городу ( магазины, рынок) -260,00 Проезд Терещенко Сватово-Киев- Кривой Рог -1 000,00 | AH29: =AF29+AG29*1 -> 0 | AI29: =AH29/$AH$87 -> 0 | AM29: =AK29+AL29*1 -> 0 | AN29: =AM29/$AM$87 -> 0 | AP29: =G29+L29+Q29+V29+AA29+AF29+AK29 -> 0 | AQ29: =H29+M29+R29+W29+AB29+AG29+AL29 -> 14367.38 | AR29: =AP29+AQ29*1 -> 14367.38 | AS29: =AR29/$AR$87 -> 0.0036129704 | AU29: =C29-AP29 -> 0 | AV29: =D29-AQ29 -> -367.38 | AW29: =AU29+AV29*1 -> -367.38 | AX29: =AW29/$AW$87 -> 0.000463041
B30: Разрешительная документация | E30: =C30+D30 -> 0 | F30: =E30/$E$87 -> 0 | I30: =G30+H30*1 -> 0 | N30: =L30+M30*1 -> 0 | O30: =N30/$N$87 -> 0 | S30: =Q30+R30*1 -> 0 | T30: =S30/$S$87 -> 0 | X30: =V30+W30*1 -> 0 | Y30: =X30/$X$87 -> 0 | AC30: =AA30+AB30*1 -> 0 | AD30: =AC30/$AC$87 -> 0 | AH30: =AF30+AG30*1 -> 0 | AI30: =AH30/$AH$87 -> 0 | AM30: =AK30+AL30*1 -> 0 | AN30: =AM30/$AM$87 -> 0 | AP30: =G30+L30+Q30+V30+AA30+AF30+AK30 -> 0 | AQ30: =H30+M30+R30+W30+AB30+AG30+AL30 -> 0 | AR30: =AP30+AQ30*1 -> 0 | AS30: =AR30/$AR$87 -> 0 | AU30: =C30-AP30 -> 0 | AV30: =D30-AQ30 -> 0 | AW30: =AU30+AV30*1 -> 0 | AX30: =AW30/$AW$87 -> 0
B31: Представительские затраты | D31: 50000 | E31: =C31+D31 -> 50000 | F31: =E31/$E$87 -> 0.015649366 | H31: 1900 | I31: =G31+H31*1 -> 1900 | K31: 600грн - налаживание отношений сэкскаваторщиками 600грн. - взятка трактаристу за неделю 700грн. - первый бетон бр.Сватовские (традиция) | M31: 1190 | N31: =L31+M31*1 -> 1190 | O31: =N31/$N$87 -> 0.0011785326 | P31: гостинец сватовским(рабочим) 390грн., налаживание отнош.с руководящими сотрудниками завода. | S31: =Q31+R31*1 -> 0 | T31: =S31/$S$87 -> 0 | X31: =V31+W31*1 -> 0 | Y31: =X31/$X$87 -> 0 | AC31: =AA31+AB31*1 -> 0 | AD31: =AC31/$AC$87 -> 0 | AH31: =AF31+AG31*1 -> 0 | AI31: =AH31/$AH$87 -> 0 | AM31: =AK31+AL31*1 -> 0 | AN31: =AM31/$AM$87 -> 0 | AP31: =G31+L31+Q31+V31+AA31+AF31+AK31 -> 0 | AQ31: =H31+M31+R31+W31+AB31+AG31+AL31 -> 3090 | AR31: =AP31+AQ31*1 -> 3090 | AS31: =AR31/$AR$87 -> 0.00077704345 | AU31: =C31-AP31 -> 0 | AV31: =D31-AQ31 -> 46910 | AW31: =AU31+AV31*1 -> 46910 | AX31: =AW31/$AW$87 -> -0.059124757
O32: =N32/$N$87 -> 0 | T32: =S32/$S$87 -> 0 | Y32: =X32/$X$87 -> 0 | AN32: =AM32/$AM$87 -> 0 | AP32: =G32 -> 0 | AQ32: =H32 -> 0
B33: Дополнительные расходы | C33: =C34 -> 0 | D33: =D34 -> 0 | E33: =E34 -> 0 | F33: =E33/$E$87 -> 0 | G33: =G34 -> 0 | H33: =H34 -> 0 | I33: =I34 -> 0 | L33: =L34 -> 0 | M33: =M34 -> 0 | N33: =N34 -> 0 | O33: =N33/$N$87 -> 0 | Q33: =Q34 -> 0 | R33: =R34 -> 0 | S33: =S34 -> 0 | T33: =S33/$S$87 -> 0 | V33: =V34 -> 0 | W33: =W34 -> 0 | X33: =X34 -> 0 | Y33: =X33/$X$87 -> 0 | AA33: =AA34 -> 0 | AB33: =AB34 -> 0 | AC33: =AC34 -> 0 | AD33: =AC33/$AC$87 -> 0 | AF33: =AF34 -> 0 | AG33: =AG34 -> 0 | AH33: =AH34 -> 0 | AI33: =AH33/$AC$87 -> 0 | AK33: =AK34 -> 0 | AL33: =AL34 -> 0 | AM33: =AM34 -> 0 | AN33: =AM33/$AM$87 -> 0 | AP33: =G33+L33+Q33+V33+AA33+AF33+AK33 -> 0 | AQ33: =H33+M33+R33+W33+AB33+AG33+AL33 -> 0 | AR33: =AR34 -> 0 | AU33: =AU34 -> 0 | AV33: =AV34 -> 0 | AW33: =AW34 -> 0
B34: Расход от ивест. Деятельности (ОС) | E34: =C34+D34 -> 0 | F34: =E34/$E$87 -> 0 | I34: =G34+H34*1 -> 0 | N34: =L34+M34*1 -> 0 | O34: =N34/$N$87 -> 0 | S34: =Q34+R34*1 -> 0 | T34: =S34/$S$87 -> 0 | X34: =V34+W34*1 -> 0 | Y34: =X34/$X$87 -> 0 | AC34: =AA34+AB34*1 -> 0 | AD34: =AC34/$AC$87 -> 0 | AH34: =AF34+AG34*1 -> 0 | AI34: =AH34/$AC$87 -> 0 | AM34: =AK34+AL34*1 -> 0 | AN34: =AM34/$AM$87 -> 0 | AP34: =G34+L34+Q34+V34+AA34+AF34+AK34 -> 0 | AQ34: =H34+M34+R34+W34+AB34+AG34+AL34 -> 0 | AR34: =AP34+AQ34*1 -> 0 | AS34: =AR34/$AR$87 -> 0 | AU34: =C34-AP34 -> 0 | AV34: =D34-AQ34 -> 0 | AW34: =AU34+AV34*1 -> 0 | AX34: =AW34/$E$87 -> 0
O35: =N35/$N$87 -> 0 | T35: =S35/$N$87 -> 0 | Y35: =X35/$N$87 -> 0 | AD35: =AC35/$N$87 -> 0 | AI35: =AH35/$N$87 -> 0 | AN35: =AM35/$AM$87 -> 0 | AP35: =G35 -> 0 | AQ35: =H35 -> 0
B36: Маржинальный доход, грн | C36: =(C5)-(C8) -> 2533929 | D36: =(D5)-(D8) -> -856715 | E36: =(E5)-(E8) -> 1677214 | G36: =(G5)-(G8) -> -44655 | H36: =(H5)-(H8) -> -30403 | I36: =(I5)-(I8) -> -75058 | L36: =(L5)-(L8) -> -956216.47 | M36: =(M5)-(M8) -> -43331.796 | N36: =(N5)-(N8) -> -999548.27 | Q36: =(Q5)-(Q8) -> -218190.11 | R36: =(R5)-(R8) -> -30888 | S36: =(S5)-(S8) -> -249078.11 | V36: =(V5)-(V8) -> 1944052.3 | W36: =(W5)-(W8) -> -458642 | X36: =(X5)-(X8) -> 1485410.3 | AA36: =(AA5)-(AA8) -> 1087250.4 | AB36: =(AB5)-(AB8) -> -260754.52 | AC36: =(AC5)-(AC8) -> 826495.92 | AF36: =(AF5)-(AF8) -> 467292.99 | AG36: =(AG5)-(AG8) -> -180831.36 | AH36: =(AH5)-(AH8) -> 286461.63 | AK36: =(AK5)-(AK8) -> -2054.406 | AL36: =(AL5)-(AL8) -> -80000 | AM36: =(AM5)-(AM8) -> -82054.406 | AN36: =AM36/$AM$87 -> -0.86833214 | AP36: =(AP5)-(AP8) -> 2277479.8 | AQ36: =(AQ5)-(AQ8) -> -1084850.7 | AR36: =(AR5)-(AR8) -> 1192629.1 | AU36: =(AU5)-(AU8) -> 256449.24 | AV36: =(AV5)-(AV8) -> 228135.68 | AW36: =(AW5)-(AW8) -> 484584.91
B37: Маржинальный доход, % | C37: =C36/(C5) -> 0.55193929 | D37: =D36/(D5) -> #DIV/0! | E37: =E36/(E5) -> 0.36533001 | G37: =G36/(G5) -> #DIV/0! | H37: =H36/(H5) -> #DIV/0! | I37: =I36/(I5) -> #DIV/0! | L37: =L36/(L5) -> #DIV/0! | M37: =M36/(M5) -> #DIV/0! | N37: =N36/(N5) -> #DIV/0! | Q37: =Q36/(Q5) -> #DIV/0! | R37: =R36/(R5) -> #DIV/0! | S37: =S36/(S5) -> #DIV/0! | T37: =S37/$S$87 -> #DIV/0! | V37: =V36/(V5) -> 0.64262149 | W37: =W36/(W5) -> #DIV/0! | X37: =X36/(X5) -> 0.49101384 | Y37: =X37/$S$87 -> 1.8725742e-06 | AA37: =AA36/(AA5) -> 0.74048432 | AB37: =AB36/(AB5) -> #DIV/0! | AC37: =AC36/(AC5) -> 0.56289448 | AD37: =AC37/$S$87 -> 2.1467046e-06 | AF37: =AF36/(AF5) -> 0.92332618 | AG37: =AG36/(AG5) -> #DIV/0! | AH37: =AH36/(AH5) -> 0.56602073 | AI37: =AH37/$AH$87 -> 2.3115222e-06 | AK37: =AK36/(AK5) -> #DIV/0! | AL37: =AL36/(AL5) -> #DIV/0! | AM37: =AM36/(AM5) -> #DIV/0! | AN37: =AM37/$AM$87 -> #DIV/0! | AP37: =AP36/(AP5) -> 0.45553384 | AQ37: =AQ36/(AQ5) -> #DIV/0! | AR37: =AR36/(AR5) -> 0.23854566 | AU37: =AU36/(AU5) -> -0.62758583 | AV37: =AV36/(AV5) -> #DIV/0! | AW37: =AW36/(AW5) -> -1.1858824
T38: =S38/$S$87 -> 0 | Y38: =X38/$S$87 -> 0 | AD38: =AC38/$S$87 -> 0 | AI38: =AH38/$S$87 -> 0 | AN38: =AM38/$AM$87 -> 0
B39: Общепроизводственные затраты | C39: =SUM(C40:C46) -> 4000 | D39: =SUM(D40:D46) -> 5600 | E39: =SUM(E40:E46) -> 9600 | F39: =E39/$E$87 -> 0.0030046782 | G39: =SUM(G40:G46) -> 0 | H39: =SUM(H40:H46) -> 100 | I39: =SUM(I40:I46) -> 100 | J39: =I39/$I$87 -> 0.0012590422 | L39: =SUM(L40:L46) -> 0 | M39: =SUM(M40:M46) -> 50 | N39: =SUM(N40:N46) -> 50 | O39: =N39/$I$87 -> 0.00062952111 | Q39: =SUM(Q40:Q46) -> 1817.5 | R39: =SUM(R40:R46) -> 0 | S39: =SUM(S40:S46) -> 1817.5 | T39: =S39/$S$87 -> 0.0069313801 | V39: =SUM(V40:V46) -> 2504.5 | W39: =SUM(W40:W46) -> 0 | X39: =SUM(X40:X46) -> 2504.5 | Y39: =X39/$X$87 -> 0.0015587176 | AA39: =SUM(AA40:AA46) -> 0 | AB39: =SUM(AB40:AB46) -> 0 | AC39: =SUM(AC40:AC46) -> 0 | AD39: =AC39/$AC$87 -> 0 | AF39: =SUM(AF40:AF46) -> 0 | AG39: =SUM(AG40:AG46) -> 0 | AH39: =SUM(AH40:AH46) -> 0 | AI39: =AH39/$AC$87 -> 0 | AK39: =SUM(AK40:AK46) -> 0 | AL39: =SUM(AL40:AL46) -> 0 | AM39: =SUM(AM40:AM46) -> 0 | AN39: =AM39/$AM$87 -> 0 | AP39: =SUM(AP40:AP46) -> 4322 | AQ39: =SUM(AQ40:AQ46) -> 150 | AR39: =SUM(AR40:AR46) -> 4472 | AS39: =AR39/$AR$87 -> 0.0011245755 | AU39: =SUM(AU40:AU46) -> -322 | AV39: =SUM(AV40:AV46) -> 5450 | AW39: =SUM(AW40:AW46) -> 5128
B40: Благоустройство офиса | E40: =C40+D40 -> 0 | F40: =E40/$E$87 -> 0 | I40: =G40+H40*1 -> 0 | N40: =L40+M40*1 -> 0 | O40: =N40/$N$87 -> 0 | S40: =Q40+R40*1 -> 0 | T40: =S40/$S$87 -> 0 | X40: =V40+W40*1 -> 0 | Y40: =X40/$X$87 -> 0 | AC40: =AA40+AB40*1 -> 0 | AD40: =AC40/$AC$87 -> 0 | AH40: =AF40+AG40*1 -> 0 | AI40: =AH40/$AC$87 -> 0 | AM40: =AK40+AL40*1 -> 0 | AN40: =AM40/$AM$87 -> 0 | AP40: =G40+L40+Q40+V40 -> 0 | AQ40: =H40+M40+R40+W40 -> 0 | AR40: =AP40+AQ40*1 -> 0 | AS40: =AR40/$AR$87 -> 0 | AU40: =C40-AP40 -> 0 | AV40: =D40-AQ40 -> 0 | AW40: =AU40+AV40*1 -> 0 | AX40: =AW40/$E$87 -> 0
B41: Хозтовары и материалы | D41: 1200 | E41: =C41+D41 -> 1200 | F41: =E41/$E$87 -> 0.00037558478 | I41: =G41+H41*1 -> 0 | N41: =L41+M41*1 -> 0 | O41: =N41/$N$87 -> 0 | S41: =Q41+R41*1 -> 0 | T41: =S41/$S$87 -> 0 | X41: =V41+W41*1 -> 0 | Y41: =X41/$X$87 -> 0 | AC41: =AA41+AB41*1 -> 0 | AD41: =AC41/$AC$87 -> 0 | AH41: =AF41+AG41*1 -> 0 | AI41: =AH41/$AC$87 -> 0 | AM41: =AK41+AL41*1 -> 0 | AN41: =AM41/$AM$87 -> 0 | AP41: =G41+L41+Q41+V41 -> 0 | AQ41: =H41+M41+R41+W41 -> 0 | AR41: =AP41+AQ41*1 -> 0 | AS41: =AR41/$AR$87 -> 0 | AU41: =C41-AP41 -> 0 | AV41: =D41-AQ41 -> 1200 | AW41: =AU41+AV41*1 -> 1200 | AX41: =AW41/$E$87 -> 0.00037558478
B42: ИТ расходы | D42: 1200 | E42: =C42+D42 -> 1200 | F42: =E42/$E$87 -> 0.00037558478 | I42: =G42+H42*1 -> 0 | N42: =L42+M42*1 -> 0 | O42: =N42/$N$87 -> 0 | S42: =Q42+R42*1 -> 0 | T42: =S42/$S$87 -> 0 | X42: =V42+W42*1 -> 0 | Y42: =X42/$X$87 -> 0 | AC42: =AA42+AB42*1 -> 0 | AD42: =AC42/$AC$87 -> 0 | AH42: =AF42+AG42*1 -> 0 | AI42: =AH42/$AC$87 -> 0 | AM42: =AK42+AL42*1 -> 0 | AN42: =AM42/$AM$87 -> 0 | AP42: =G42+L42+Q42+V42 -> 0 | AQ42: =H42+M42+R42+W42 -> 0 | AR42: =AP42+AQ42*1 -> 0 | AS42: =AR42/$AR$87 -> 0 | AU42: =C42-AP42 -> 0 | AV42: =D42-AQ42 -> 1200 | AW42: =AU42+AV42*1 -> 1200 | AX42: =AW42/$E$87 -> 0.00037558478
B43: Питьевая вода | C43: 4000 | E43: =C43+D43 -> 4000 | F43: =E43/$E$87 -> 0.0012519493 | I43: =G43+H43*1 -> 0 | N43: =L43+M43*1 -> 0 | O43: =N43/$N$87 -> 0 | S43: =Q43+R43*1 -> 0 | T43: =S43/$S$87 -> 0 | X43: =V43+W43*1 -> 0 | Y43: =X43/$X$87 -> 0 | AC43: =AA43+AB43*1 -> 0 | AD43: =AC43/$AC$87 -> 0 | AH43: =AF43+AG43*1 -> 0 | AI43: =AH43/$AC$87 -> 0 | AM43: =AK43+AL43*1 -> 0 | AN43: =AM43/$AM$87 -> 0 | AP43: =G43+L43+Q43+V43 -> 0 | AQ43: =H43+M43+R43+W43 -> 0 | AR43: =AP43+AQ43*1 -> 0 | AS43: =AR43/$AR$87 -> 0 | AU43: =C43-AP43 -> 4000 | AV43: =D43-AQ43 -> 0 | AW43: =AU43+AV43*1 -> 4000 | AX43: =AW43/$E$87 -> 0.0012519493
B44: Охрана офиса и пожарная сигнализация | E44: =C44+D44 -> 0 | F44: =E44/$E$87 -> 0 | I44: =G44+H44*1 -> 0 | N44: =L44+M44*1 -> 0 | O44: =N44/$N$87 -> 0 | S44: =Q44+R44*1 -> 0 | T44: =S44/$S$87 -> 0 | X44: =V44+W44*1 -> 0 | Y44: =X44/$X$87 -> 0 | AC44: =AA44+AB44*1 -> 0 | AD44: =AC44/$AC$87 -> 0 | AH44: =AF44+AG44*1 -> 0 | AI44: =AH44/$AC$87 -> 0 | AM44: =AK44+AL44*1 -> 0 | AN44: =AM44/$AM$87 -> 0 | AP44: =G44+L44+Q44+V44+AA44+AF44+AK44 -> 0 | AQ44: =H44+M44+R44+W44+AB44+AG44+AL44 -> 0 | AR44: =AP44+AQ44*1 -> 0 | AS44: =AR44/$AR$87 -> 0 | AU44: =C44-AP44 -> 0 | AV44: =D44-AQ44 -> 0 | AW44: =AU44+AV44*1 -> 0 | AX44: =AW44/$E$87 -> 0
B45: Курьерские и почтовые | D45: 1200 | E45: =C45+D45 -> 1200 | F45: =E45/$E$87 -> 0.00037558478 | H45: 100 | I45: =G45+H45*1 -> 100 | N45: =L45+M45*1 -> 0 | O45: =N45/$N$87 -> 0 | Q45: 1817.5 | S45: =Q45+R45*1 -> 1817.5 | T45: =S45/$S$87 -> 0.0069313801 | U45: Новая почта | V45: 2504.5 | X45: =V45+W45*1 -> 2504.5 | Y45: =X45/$X$87 -> 0.0015587176 | Z45: Новая почта -2 504,50 | AC45: =AA45+AB45*1 -> 0 | AD45: =AC45/$AC$87 -> 0 | AH45: =AF45+AG45*1 -> 0 | AI45: =AH45/$AC$87 -> 0 | AM45: =AK45+AL45*1 -> 0 | AN45: =AM45/$AM$87 -> 0 | AP45: =G45+L45+Q45+V45+AA45+AF45+AK45 -> 4322 | AQ45: =H45+M45+R45+W45+AB45+AG45+AL45 -> 100 | AR45: =AP45+AQ45*1 -> 4422 | AS45: =AR45/$AR$87 -> 0.001112002 | AU45: =C45-AP45 -> -4322 | AV45: =D45-AQ45 -> 1100 | AW45: =AU45+AV45*1 -> -3222 | AX45: =AW45/$E$87 -> -0.0010084451
B46: Канцтовары | D46: 2000 | E46: =C46+D46 -> 2000 | F46: =E46/$E$87 -> 0.00062597463 | I46: =G46+H46*1 -> 0 | J46: =I46/$I$87 -> 0 | M46: 50 | N46: =L46+M46*1 -> 50 | O46: =N46/$N$87 -> 4.9518175e-05 | S46: =Q46+R46*1 -> 0 | T46: =S46/$S$87 -> 0 | X46: =V46+W46*1 -> 0 | Y46: =X46/$X$87 -> 0 | AC46: =AA46+AB46*1 -> 0 | AD46: =AC46/$AC$87 -> 0 | AH46: =AF46+AG46*1 -> 0 | AI46: =AH46/$AC$87 -> 0 | AM46: =AK46+AL46*1 -> 0 | AN46: =AM46/$AM$87 -> 0 | AP46: =G46+L46+Q46+V46+AA46+AF46+AK46 -> 0 | AQ46: =H46+M46+R46+W46+AB46+AG46+AL46 -> 50 | AR46: =AP46+AQ46*1 -> 50 | AS46: =AR46/$AR$87 -> 1.2573519e-05 | AU46: =C46-AP46 -> 0 | AV46: =D46-AQ46 -> 1950 | AW46: =AU46+AV46*1 -> 1950 | AX46: =AW46/$E$87 -> 0.00061032526
O47: =N47/$N$87 -> 0 | T47: =S47/$S$87 -> 0 | Y47: =X47/$X$87 -> 0 | AD47: =AC47/$X$87 -> 0 | AI47: =AH47/$X$87 -> 0 | AN47: =AM47/$AM$87 -> 0 | AP47: =G47+L47+Q47 -> 0 | AQ47: =H47+M47+R47 -> 0 | AS47: =AR47/$AR$87 -> 0
B48: Маркетинговые затраты | E48: =SUM(E49:E50) -> 0 | F48: =E48/$E$87 -> 0 | G48: =SUM(G49:G50) -> 0 | H48: =SUM(H49:H50) -> 0 | I48: =SUM(I49:I50) -> 0 | L48: =SUM(L49:L50) -> 3053.8 | M48: =SUM(M49:M50) -> 0 | N48: =SUM(N49:N50) -> 3053.8 | O48: =N48/$N$87 -> 0.003024372 | Q48: =SUM(Q49:Q50) -> 0 | R48: =SUM(R49:R50) -> 0 | S48: =SUM(S49:S50) -> 0 | T48: =S48/$S$87 -> 0 | V48: =SUM(V49:V50) -> 0 | W48: =SUM(W49:W50) -> 0 | X48: =SUM(X49:X50) -> 0 | Y48: =X48/$X$87 -> 0 | AA48: =SUM(AA49:AA50) -> 0 | AB48: =SUM(AB49:AB50) -> 0 | AC48: =SUM(AC49:AC50) -> 0 | AD48: =AC48/$AC$87 -> 0 | AF48: =SUM(AF49:AF50) -> 0 | AG48: =SUM(AG49:AG50) -> 0 | AH48: =SUM(AH49:AH50) -> 0 | AI48: =AH48/$AC$87 -> 0 | AK48: =SUM(AK49:AK50) -> 1434.8 | AL48: =SUM(AL49:AL50) -> 0 | AM48: =SUM(AM49:AM50) -> 1434.8 | AN48: =AM48/$AM$87 -> 0.01518362 | AP48: =AP50+AP49 -> 4488.6 | AQ48: =AQ50+AQ49 -> 0 | AR48: =SUM(AR49:AR50) -> 4488.6 | AU48: =AU50+AU49 -> -4488.6 | AV48: =AV50+AV49 -> 0 | AW48: =SUM(AW49:AW50) -> -4488.6
B49: Реклама | E49: =C49+D49 -> 0 | F49: =E49/$E$87 -> 0 | I49: =G49+H49*1 -> 0 | N49: =L49+M49*1 -> 0 | O49: =N49/$N$87 -> 0 | S49: =Q49+R49*1 -> 0 | T49: =S49/$S$87 -> 0 | X49: =V49+W49*1 -> 0 | Y49: =X49/$X$87 -> 0 | AC49: =AA49+AB49*1 -> 0 | AD49: =AC49/$AC$87 -> 0 | AH49: =AF49+AG49*1 -> 0 | AI49: =AH49/$AC$87 -> 0 | AM49: =AK49+AL49*1 -> 0 | AN49: =AM49/$AM$87 -> 0 | AP49: =G49+L49+Q49+V49+AA49+AF49+AK49 -> 0 | AQ49: =H49+M49+R49+W49+AB49+AG49+AL49 -> 0 | AR49: =AP49+AQ49*1 -> 0 | AS49: =AR49/$AR$87 -> 0 | AU49: =C49-AP49 -> 0 | AV49: =D49-AQ49 -> 0 | AW49: =AU49+AV49*1 -> 0 | AX49: =AW49/$E$87 -> 0
B50: Прочие маркетинговые затраты | E50: =C50+D50 -> 0 | F50: =E50/$E$87 -> 0 | I50: =G50+H50*1 -> 0 | L50: 3053.8 | N50: =L50+M50*1 -> 3053.8 | O50: =N50/$N$87 -> 0.003024372 | P50: сувениры день строителя | S50: =Q50+R50*1 -> 0 | T50: =S50/$S$87 -> 0 | X50: =V50+W50*1 -> 0 | Y50: =X50/$X$87 -> 0 | AC50: =AA50+AB50*1 -> 0 | AD50: =AC50/$X$87 -> 0 | AH50: =AF50+AG50*1 -> 0 | AI50: =AH50/$X$87 -> 0 | AK50: 1434.8 | AM50: =AK50+AL50*1 -> 1434.8 | AN50: =AM50/$AM$87 -> 0.01518362 | AP50: =G50+L50+Q50+V50+AA50+AF50+AK50 -> 4488.6 | AQ50: =H50+M50+R50+W50 -> 0 | AR50: =AP50+AQ50*1 -> 4488.6 | AS50: =AR50/$AR$87 -> 0.0011287499 | AU50: =C50-AP50 -> -4488.6 | AV50: =D50-AQ50 -> 0 | AW50: =AU50+AV50*1 -> -4488.6 | AX50: =AW50/$E$87 -> -0.0014048749
O51: =N51/$N$87 -> 0 | T51: =S51/$S$87 -> 0 | Y51: =X51/$S$87 -> 0 | AD51: =AC51/$S$87 -> 0 | AI51: =AH51/$S$87 -> 0 | AN51: =AM51/$AM$87 -> 0 | AP51: =G51 -> 0 | AQ51: =H51 -> 0
B52: Административные затраты | C52: =SUM(C53:C69) -> 0 | D52: =SUM(D53:D69) -> 4000 | E52: =SUM(E53:E69) -> 4000 | F52: =E52/$E$87 -> 0.0012519493 | G52: =SUM(G53:G69) -> 0 | H52: =SUM(H53:H69) -> 95 | I52: =SUM(I53:I69) -> 95 | J52: =I52/$I$87 -> 0.0011960901 | L52: =SUM(L53:L69) -> 600 | M52: =SUM(M53:M69) -> 495 | N52: =SUM(N53:N69) -> 1095 | O52: =N52/$N$87 -> 0.001084448 | Q52: =SUM(Q53:Q69) -> 1000 | R52: =SUM(R53:R69) -> 5373 | S52: =SUM(S53:S69) -> 6373 | T52: =S52/$S$87 -> 0.024304641 | V52: =SUM(V53:V69) -> 260 | W52: =SUM(W53:W69) -> 1481 | X52: =SUM(X53:X69) -> 1741 | Y52: =X52/$X$87 -> 0.0010835406 | AA52: =SUM(AA53:AA69) -> 0 | AB52: =SUM(AB53:AB69) -> 1689.55 | AC52: =SUM(AC53:AC69) -> 1689.55 | AD52: =AC52/$AC$87 -> 0.0024834318 | AF52: =SUM(AF53:AF69) -> 0 | AG52: =SUM(AG53:AG69) -> 442 | AH52: =SUM(AH53:AH69) -> 442 | AI52: =AH52/$AH$87 -> 0.0018050448 | AK52: =SUM(AK53:AK69) -> 0 | AL52: =SUM(AL53:AL69) -> 0 | AM52: =SUM(AM53:AM69) -> 0 | AN52: =AM52/$AM$87 -> 0 | AP52: =SUM(AP53:AP69) -> 1860 | AQ52: =SUM(AQ53:AQ69) -> 9575.55 | AR52: =SUM(AR53:AR69) -> 11435.55 | AS52: =AR52/$AR$87 -> 0.002875702 | AU52: =SUM(AU53:AU69) -> -1860 | AV52: =SUM(AV53:AV69) -> -5575.55 | AW52: =SUM(AW53:AW69) -> -7435.55 | AX52: =AW52/$AW$87 -> 0.009371671
B53: ЗП управленческого персонала | E53: =C53+D53 -> 0 | F53: =E53/$E$87 -> 0 | I53: =G53+H53*1 -> 0 | J53: =I53/$I$87 -> 0 | N53: =L53+M53*1 -> 0 | O53: =N53/$N$87 -> 0 | S53: =Q53+R53*1 -> 0 | T53: =S53/$S$87 -> 0 | X53: =V53+W53*1 -> 0 | Y53: =X53/$X$87 -> 0 | AC53: =AA53+AB53*1 -> 0 | AD53: =AC53/$AC$87 -> 0 | AH53: =AF53+AG53*1 -> 0 | AI53: =AH53/$AC$87 -> 0 | AM53: =AK53+AL53*1 -> 0 | AN53: =AM53/$AM$87 -> 0 | AP53: =G53+L53 -> 0 | AQ53: =H53+M53 -> 0 | AR53: =AP53+AQ53*1 -> 0 | AS53: =AR53/$AR$87 -> 0 | AU53: =C53-AP53 -> 0 | AV53: =D53-AQ53 -> 0 | AW53: =AU53+AV53*1 -> 0 | AX53: =AW53/$AW$87 -> 0
B54: Начисления на управленчискую зарплату | E54: =C54+D54 -> 0 | F54: =E54/$E$87 -> 0 | I54: =G54+H54*1 -> 0 | J54: =I54/$I$87 -> 0 | N54: =L54+M54*1 -> 0 | O54: =N54/$N$87 -> 0 | S54: =Q54+R54*1 -> 0 | T54: =S54/$S$87 -> 0 | X54: =V54+W54*1 -> 0 | Y54: =X54/$X$87 -> 0 | AC54: =AA54+AB54*1 -> 0 | AD54: =AC54/$AC$87 -> 0 | AH54: =AF54+AG54*1 -> 0 | AI54: =AH54/$AC$87 -> 0 | AM54: =AK54+AL54*1 -> 0 | AN54: =AM54/$AM$87 -> 0 | AP54: =G54+L54 -> 0 | AQ54: =H54+M54 -> 0 | AR54: =AP54+AQ54*1 -> 0 | AS54: =AR54/$AR$87 -> 0 | AU54: =C54-AP54 -> 0 | AV54: =D54-AQ54 -> 0 | AW54: =AU54+AV54*1 -> 0 | AX54: =AW54/$AW$87 -> 0
B55: Удержание с зарплаты управленческого персонала | E55: =C55+D55 -> 0 | F55: =E55/$E$87 -> 0 | I55: =G55+H55*1 -> 0 | J55: =I55/$I$87 -> 0 | N55: =L55+M55*1 -> 0 | O55: =N55/$N$87 -> 0 | S55: =Q55+R55*1 -> 0 | T55: =S55/$S$87 -> 0 | X55: =V55+W55*1 -> 0 | Y55: =X55/$X$87 -> 0 | AC55: =AA55+AB55*1 -> 0 | AD55: =AC55/$AC$87 -> 0 | AH55: =AF55+AG55*1 -> 0 | AI55: =AH55/$AC$87 -> 0 | AM55: =AK55+AL55*1 -> 0 | AN55: =AM55/$AM$87 -> 0 | AP55: =G55+L55 -> 0 | AQ55: =H55+M55 -> 0 | AR55: =AP55+AQ55*1 -> 0 | AS55: =AR55/$AR$87 -> 0 | AU55: =C55-AP55 -> 0 | AV55: =D55-AQ55 -> 0 | AW55: =AU55+AV55*1 -> 0 | AX55: =AW55/$AW$87 -> 0
B56: ЗП РМ | E56: =C56+D56 -> 0 | F56: =E56/$E$87 -> 0 | I56: =G56+H56*1 -> 0 | J56: =I56/$I$87 -> 0 | N56: =L56+M56*1 -> 0 | O56: =N56/$N$87 -> 0 | S56: =Q56+R56*1 -> 0 | T56: =S56/$S$87 -> 0 | X56: =V56+W56*1 -> 0 | Y56: =X56/$X$87 -> 0 | AC56: =AA56+AB56*1 -> 0 | AD56: =AC56/$AC$87 -> 0 | AH56: =AF56+AG56*1 -> 0 | AI56: =AH56/$AC$87 -> 0 | AM56: =AK56+AL56*1 -> 0 | AN56: =AM56/$AM$87 -> 0 | AP56: =G56+L56 -> 0 | AQ56: =H56+M56 -> 0 | AR56: =AP56+AQ56*1 -> 0 | AS56: =AR56/$AR$87 -> 0 | AU56: =C56-AP56 -> 0 | AV56: =D56-AQ56 -> 0 | AW56: =AU56+AV56*1 -> 0 | AX56: =AW56/$AW$87 -> 0
B57: Удержание с зарплаты РМ | E57: =C57+D57 -> 0 | F57: =E57/$E$87 -> 0 | I57: =G57+H57*1 -> 0 | J57: =I57/$I$87 -> 0 | N57: =L57+M57*1 -> 0 | O57: =N57/$N$87 -> 0 | S57: =Q57+R57*1 -> 0 | T57: =S57/$S$87 -> 0 | X57: =V57+W57*1 -> 0 | Y57: =X57/$X$87 -> 0 | AC57: =AA57+AB57*1 -> 0 | AD57: =AC57/$AC$87 -> 0 | AH57: =AF57+AG57*1 -> 0 | AI57: =AH57/$AC$87 -> 0 | AM57: =AK57+AL57*1 -> 0 | AN57: =AM57/$AM$87 -> 0 | AP57: =G57+L57 -> 0 | AQ57: =H57+M57 -> 0 | AR57: =AP57+AQ57*1 -> 0 | AS57: =AR57/$AR$87 -> 0 | AU57: =C57-AP57 -> 0 | AV57: =D57-AQ57 -> 0 | AW57: =AU57+AV57*1 -> 0 | AX57: =AW57/$AW$87 -> 0
B58: Начисления на зарплату PM | E58: =C58+D58 -> 0 | F58: =E58/$E$87 -> 0 | I58: =G58+H58*1 -> 0 | J58: =I58/$I$87 -> 0 | N58: =L58+M58*1 -> 0 | O58: =N58/$N$87 -> 0 | S58: =Q58+R58*1 -> 0 | T58: =S58/$S$87 -> 0 | X58: =V58+W58*1 -> 0 | Y58: =X58/$X$87 -> 0 | AC58: =AA58+AB58*1 -> 0 | AD58: =AC58/$AC$87 -> 0 | AH58: =AF58+AG58*1 -> 0 | AI58: =AH58/$AC$87 -> 0 | AM58: =AK58+AL58*1 -> 0 | AN58: =AM58/$AM$87 -> 0 | AP58: =G58+L58 -> 0 | AQ58: =H58+M58 -> 0 | AR58: =AP58+AQ58*1 -> 0 | AS58: =AR58/$AR$87 -> 0 | AU58: =C58-AP58 -> 0 | AV58: =D58-AQ58 -> 0 | AW58: =AU58+AV58*1 -> 0 | AX58: =AW58/$AW$87 -> 0
B59: Премия управленческого персонала | E59: =C59+D59 -> 0 | F59: =E59/$E$87 -> 0 | I59: =G59+H59*1 -> 0 | J59: =I59/$I$87 -> 0 | N59: =L59+M59*1 -> 0 | O59: =N59/$N$87 -> 0 | S59: =Q59+R59*1 -> 0 | T59: =S59/$S$87 -> 0 | X59: =V59+W59*1 -> 0 | Y59: =X59/$X$87 -> 0 | AC59: =AA59+AB59*1 -> 0 | AD59: =AC59/$AC$87 -> 0 | AH59: =AF59+AG59*1 -> 0 | AI59: =AH59/$AC$87 -> 0 | AM59: =AK59+AL59*1 -> 0 | AN59: =AM59/$AM$87 -> 0 | AP59: =G59+L59 -> 0 | AQ59: =H59+M59 -> 0 | AR59: =AP59+AQ59*1 -> 0 | AS59: =AR59/$AR$87 -> 0 | AU59: =C59-AP59 -> 0 | AV59: =D59-AQ59 -> 0 | AW59: =AU59+AV59*1 -> 0 | AX59: =AW59/$AW$87 -> 0
B60: Телекомуникационные услуги | E60: =C60+D60 -> 0 | F60: =E60/$E$87 -> 0 | I60: =G60+H60*1 -> 0 | J60: =I60/$I$87 -> 0 | N60: =L60+M60*1 -> 0 | O60: =N60/$N$87 -> 0 | S60: =Q60+R60*1 -> 0 | T60: =S60/$S$87 -> 0 | X60: =V60+W60*1 -> 0 | Y60: =X60/$X$87 -> 0 | AC60: =AA60+AB60*1 -> 0 | AD60: =AC60/$AC$87 -> 0 | AH60: =AF60+AG60*1 -> 0 | AI60: =AH60/$AC$87 -> 0 | AM60: =AK60+AL60*1 -> 0 | AN60: =AM60/$AM$87 -> 0 | AP60: =G60+L60 -> 0 | AQ60: =H60+M60 -> 0 | AR60: =AP60+AQ60*1 -> 0 | AS60: =AR60/$AR$87 -> 0 | AU60: =C60-AP60 -> 0 | AV60: =D60-AQ60 -> 0 | AW60: =AU60+AV60*1 -> 0 | AX60: =AW60/$AW$87 -> 0
B61: Транспортные затраты управленческого персонала | E61: =C61+D61 -> 0 | F61: =E61/$E$87 -> 0 | I61: =G61+H61*1 -> 0 | J61: =I61/$I$87 -> 0 | N61: =L61+M61*1 -> 0 | O61: =N61/$N$87 -> 0 | S61: =Q61+R61*1 -> 0 | T61: =S61/$S$87 -> 0 | X61: =V61+W61*1 -> 0 | Y61: =X61/$X$87 -> 0 | AC61: =AA61+AB61*1 -> 0 | AD61: =AC61/$AC$87 -> 0 | AH61: =AF61+AG61*1 -> 0 | AI61: =AH61/$AC$87 -> 0 | AM61: =AK61+AL61*1 -> 0 | AN61: =AM61/$AM$87 -> 0 | AP61: =G61+L61 -> 0 | AQ61: =H61+M61 -> 0 | AR61: =AP61+AQ61*1 -> 0 | AS61: =AR61/$AR$87 -> 0 | AU61: =C61-AP61 -> 0 | AV61: =D61-AQ61 -> 0 | AW61: =AU61+AV61*1 -> 0 | AX61: =AW61/$AW$87 -> 0
B62: Аренда офиса с коммунальными платежами | E62: =C62+D62 -> 0 | F62: =E62/$E$87 -> 0 | I62: =G62+H62*1 -> 0 | N62: =L62+M62*1 -> 0 | O62: =N62/$N$87 -> 0 | S62: =Q62+R62*1 -> 0 | T62: =S62/$S$87 -> 0 | X62: =V62+W62*1 -> 0 | Y62: =X62/$X$87 -> 0 | AC62: =AA62+AB62*1 -> 0 | AD62: =AC62/$AC$87 -> 0 | AH62: =AF62+AG62*1 -> 0 | AI62: =AH62/$AC$87 -> 0 | AM62: =AK62+AL62*1 -> 0 | AN62: =AM62/$AM$87 -> 0 | AP62: =G62+L62 -> 0 | AQ62: =H62+M62 -> 0 | AR62: =AP62+AQ62*1 -> 0 | AS62: =AR62/$AR$87 -> 0 | AU62: =C62-AP62 -> 0 | AV62: =D62-AQ62 -> 0 | AW62: =AU62+AV62*1 -> 0 | AX62: =AW62/$AW$87 -> 0
B63: Затраты на коммандировки управленческого персонала | E63: =C63+D63 -> 0 | F63: =E63/$E$87 -> 0 | I63: =G63+H63*1 -> 0 | J63: =I63/$I$87 -> 0 | L63: 600 | N63: =L63+M63*1 -> 600 | O63: =N63/$N$87 -> 0.0005942181 | P63: директор - 600 грн | Q63: 1000 | S63: =Q63+R63*1 -> 1000 | T63: =S63/$S$87 -> 0.0038136892 | U63: директор- 600 грн Голубев И - 400 грн | V63: 260 | X63: =V63+W63*1 -> 260 | Y63: =X63/$X$87 -> 0.00016181536 | Z63: суточные Стариков | AC63: =AA63+AB63*1 -> 0 | AD63: =AC63/$AC$87 -> 0 | AH63: =AF63+AG63*1 -> 0 | AI63: =AH63/$AH$87 -> 0 | AM63: =AK63+AL63*1 -> 0 | AN63: =AM63/$AM$87 -> 0 | AP63: =G63+L63+Q63+V63+AA63+AF63+AK63 -> 1860 | AQ63: =H63+M63+R63+W63+AB63+AG63+AL63 -> 0 | AR63: =AP63+AQ63*1 -> 1860 | AS63: =AR63/$AR$87 -> 0.00046773489 | AU63: =C63-AP63 -> -1860 | AV63: =D63-AQ63 -> 0 | AW63: =AU63+AV63*1 -> -1860 | AX63: =AW63/$AW$87 -> 0.0023443199
B64: Юридические услуги | E64: =C64+D64 -> 0 | F64: =E64/$E$87 -> 0 | I64: =G64+H64*1 -> 0 | N64: =L64+M64*1 -> 0 | O64: =N64/$N$87 -> 0 | S64: =Q64+R64*1 -> 0 | T64: =S64/$S$87 -> 0 | X64: =V64+W64*1 -> 0 | Y64: =X64/$X$87 -> 0 | AC64: =AA64+AB64*1 -> 0 | AD64: =AC64/$AC$87 -> 0 | AH64: =AF64+AG64*1 -> 0 | AI64: =AH64/$AH$87 -> 0 | AM64: =AK64+AL64*1 -> 0 | AN64: =AM64/$AM$87 -> 0 | AP64: =G64+L64+Q64+V64+AA64+AF64+AK64 -> 0 | AQ64: =H64+M64+R64+W64+AB64+AG64+AL64 -> 0 | AR64: =AP64+AQ64*1 -> 0 | AS64: =AR64/$AR$87 -> 0 | AU64: =C64-AP64 -> 0 | AV64: =D64-AQ64 -> 0 | AW64: =AU64+AV64*1 -> 0 | AX64: =AW64/$AW$87 -> 0
B65: Услуги | E65: =C65+D65 -> 0 | F65: =E65/$E$87 -> 0 | I65: =G65+H65*1 -> 0 | N65: =L65+M65*1 -> 0 | O65: =N65/$N$87 -> 0 | S65: =Q65+R65*1 -> 0 | T65: =S65/$S$87 -> 0 | X65: =V65+W65*1 -> 0 | Y65: =X65/$X$87 -> 0 | AC65: =AA65+AB65*1 -> 0 | AD65: =AC65/$AC$87 -> 0 | AH65: =AF65+AG65*1 -> 0 | AI65: =AH65/$AH$87 -> 0 | AM65: =AK65+AL65*1 -> 0 | AN65: =AM65/$AM$87 -> 0 | AP65: =G65+L65+Q65+V65+AA65+AF65+AK65 -> 0 | AQ65: =H65+M65+R65+W65+AB65+AG65+AL65 -> 0 | AR65: =AP65+AQ65*1 -> 0 | AS65: =AR65/$AR$87 -> 0 | AU65: =C65-AP65 -> 0 | AV65: =D65-AQ65 -> 0 | AW65: =AU65+AV65*1 -> 0 | AX65: =AW65/$AW$87 -> 0
B66: Услуги банков | D66: 4000 | E66: =C66+D66 -> 4000 | F66: =E66/$E$87 -> 0.0012519493 | H66: 95 | I66: =G66+H66*1 -> 95 | M66: 495 | N66: =L66+M66*1 -> 495 | O66: =N66/$N$87 -> 0.00049022993 | R66: 1373 | S66: =Q66+R66*1 -> 1373 | T66: =S66/$S$87 -> 0.0052361953 | W66: 1481 | X66: =V66+W66*1 -> 1481 | Y66: =X66/$X$87 -> 0.00092172519 | Z66: РКО за переч.дс за акты -1 040,50 РКО за отправку пистолета для хим анкера на Сватово -230,00 | AB66: 1689.55 | AC66: =AA66+AB66*1 -> 1689.55 | AD66: =AC66/$AC$87 -> 0.0024834318 | AE66: РКО за перевод дс на карты | AG66: 442 | AH66: =AF66+AG66*1 -> 442 | AI66: =AH66/$AH$87 -> 0.0018050448 | AM66: =AK66+AL66*1 -> 0 | AN66: =AM66/$AM$87 -> 0 | AP66: =G66+L66+Q66+V66+AA66+AF66+AK66 -> 0 | AQ66: =H66+M66+R66+W66+AB66+AG66+AL66 -> 5575.55 | AR66: =AP66+AQ66*1 -> 5575.55 | AS66: =AR66/$AR$87 -> 0.0014020856 | AU66: =C66-AP66 -> 0 | AV66: =D66-AQ66 -> -1575.55 | AW66: =AU66+AV66*1 -> -1575.55 | AX66: =AW66/$AW$87 -> 0.0019858028
B67: Затраты на обучение персонала | E67: =C67+D67 -> 0 | F67: =E67/$E$87 -> 0 | I67: =G67+H67*1 -> 0 | J67: =I67/$I$87 -> 0 | N67: =L67+M67*1 -> 0 | O67: =N67/$N$87 -> 0 | S67: =Q67+R67*1 -> 0 | T67: =S67/$S$87 -> 0 | X67: =V67+W67*1 -> 0 | Y67: =X67/$X$87 -> 0 | AC67: =AA67+AB67*1 -> 0 | AD67: =AC67/$AC$87 -> 0 | AH67: =AF67+AG67*1 -> 0 | AI67: =AH67/$AH$87 -> 0 | AM67: =AK67+AL67*1 -> 0 | AN67: =AM67/$AH$87 -> 0 | AP67: =G67+L67+Q67+V67+AA67+AF67+AK67 -> 0 | AQ67: =H67+M67+R67+W67+AB67+AG67+AL67 -> 0 | AR67: =AP67+AQ67*1 -> 0 | AS67: =AR67/$AR$87 -> 0 | AU67: =C67-AP67 -> 0 | AV67: =D67-AQ67 -> 0 | AW67: =AU67+AV67*1 -> 0 | AX67: =AW67/$E$87 -> 0
B68: Затраты по корпоративной культуре | E68: =C68+D68 -> 0 | F68: =E68/$E$87 -> 0 | I68: =G68+H68*1 -> 0 | N68: =L68+M68*1 -> 0 | O68: =N68/$N$87 -> 0 | R68: 4000 | S68: =Q68+R68*1 -> 4000 | T68: =S68/$S$87 -> 0.015254757 | U68: День Строителя на обьекте -4 000,00 | X68: =V68+W68*1 -> 0 | Y68: =X68/$X$87 -> 0 | AC68: =AA68+AB68*1 -> 0 | AD68: =AC68/$AC$87 -> 0 | AH68: =AF68+AG68*1 -> 0 | AI68: =AH68/$AH$87 -> 0 | AM68: =AK68+AL68*1 -> 0 | AN68: =AM68/$AH$87 -> 0 | AP68: =G68+L68+Q68+V68+AA68+AF68+AK68 -> 0 | AQ68: =H68+M68+R68+W68+AB68+AG68+AL68 -> 4000 | AR68: =AP68+AQ68*1 -> 4000 | AS68: =AR68/$AR$87 -> 0.0010058815 | AU68: =C68-AP68 -> 0 | AV68: =D68-AQ68 -> -4000 | AW68: =AU68+AV68*1 -> -4000 | AX68: =AW68/$E$87 -> -0.0012519493
B69: Штраф | E69: =C69+D69 -> 0 | F69: =E69/$E$87 -> 0 | I69: =G69+H69*1 -> 0 | N69: =L69+M69*1 -> 0 | O69: =N69/$N$87 -> 0 | S69: =Q69+R69*1 -> 0 | T69: =S69/$S$87 -> 0 | X69: =V69+W69*1 -> 0 | Y69: =X69/$X$87 -> 0 | AC69: =AA69+AB69*1 -> 0 | AD69: =AC69/$AC$87 -> 0 | AH69: =AF69+AG69*1 -> 0 | AI69: =AH69/$AH$87 -> 0 | AM69: =AK69+AL69*1 -> 0 | AN69: =AM69/$AH$87 -> 0 | AP69: =G69+L69+Q69+V69+AA69+AF69+AK69 -> 0 | AQ69: =H69+M69+R69+W69+AB69+AG69+AL69 -> 0 | AR69: =AP69+AQ69*1 -> 0 | AS69: =AR69/$AR$87 -> 0 | AU69: =C69-AP69 -> 0 | AV69: =D69-AQ69 -> 0 | AW69: =AU69+AV69*1 -> 0 | AX69: =AW69/$E$87 -> 0
F70: =E70/$E$87 -> 0 | O70: =N70/$N$87 -> 0 | T70: =S70/$S$87 -> 0 | Y70: =X70/$S$87 -> 0 | AD70: =AC70/$S$87 -> 0 | AI70: =AH70/$AH$87 -> 0 | AN70: =AM70/$AH$87 -> 0 | AP70: =G70 -> 0 | AQ70: =H70 -> 0 | AS70: =AR70/$AR$87 -> 0 | AU70: =C70-AP70 -> 0 | AV70: =D70-AQ70 -> 0 | AX70: =AW70/$E$87 -> 0
B71: Налоги и сборы | C71: =C72 -> 137728.68 | D71: =D72 -> 0 | E71: =E72 -> 137728.68 | F71: =E71/$E$87 -> 0.04310733 | G71: =G72 -> 0 | H71: =H72 -> 0 | I71: =I72 -> 0 | L71: =L72 -> 0 | M71: =M72 -> 0 | N71: =N72 -> 0 | O71: =N71/$N$87 -> 0 | Q71: =Q72 -> 0 | R71: =R72 -> 0 | S71: =S72 -> 0 | T71: =S71/$S$87 -> 0 | V71: =V72 -> 0 | W71: =W72 -> 0 | X71: =X72 -> 0 | Y71: =X71/$X$87 -> 0 | AA71: =AA72 -> 0 | AB71: =AB72 -> 0 | AC71: =AC72 -> 0 | AD71: =AC71/$AC$87 -> 0 | AF71: =AF72 -> 0 | AG71: =AG72 -> 0 | AH71: =AH72 -> 0 | AI71: =AH71/$AC$87 -> 0 | AK71: =AK72 -> 0 | AL71: =AL72 -> 0 | AM71: =AM72 -> 0 | AN71: =AM71/$AC$87 -> 0 | AP71: =AP72 -> 0 | AQ71: =AQ72 -> 0 | AR71: =AR72 -> 0 | AU71: =C71-AP71 -> 137728.68 | AV71: =D71-AQ71 -> 0 | AW71: =AW72 -> 137728.68 | AX71: =AW71/$E$87 -> 0.04310733
B72: НДС/ Прочие налоги | C72: =C6*3% -> 137728.68 | E72: =C72+D72 -> 137728.68 | I72: =G72+H72*1 -> 0 | N72: =L72+M72*1 -> 0 | O72: =N72/$N$87 -> 0 | S72: =Q72+R72*1 -> 0 | T72: =S72/$S$87 -> 0 | X72: =V72+W72*1 -> 0 | Y72: =X72/$X$87 -> 0 | AC72: =AA72+AB72*1 -> 0 | AD72: =AC72/$AC$87 -> 0 | AH72: =AF72+AG72*1 -> 0 | AI72: =AH72/$AC$87 -> 0 | AM72: =AK72+AL72*1 -> 0 | AN72: =AM72/$AC$87 -> 0 | AP72: =AP6*0.03*0 -> 0 | AQ72: =H72+M72+R72+W72+AB72+AG72 -> 0 | AR72: =AP72+AQ72*1 -> 0 | AU72: =C72-AP72 -> 137728.68 | AV72: =D72-AQ72 -> 0 | AW72: =AU72+AV72*1 -> 137728.68
B73: Операционная прибыль, грн | C73: =C36-C39-C48-C52 -> 2529929 | D73: =D36-D39-D48-D52 -> -866315 | E73: =E36-E39-E48-E52 -> 1663614 | G73: =G36-G39-G48-G52 -> -44655 | H73: =H36-H39-H48-H52 -> -30598 | I73: =I36-I39-I48-I52 -> -75253 | L73: =L36-L39-L48-L52 -> -959870.27 | M73: =M36-M39-M48-M52 -> -43876.796 | N73: =N36-N39-N48-N52 -> -1003747.1 | Q73: =Q36-Q39-Q48-Q52 -> -221007.61 | R73: =R36-R39-R48-R52 -> -36261 | S73: =S36-S39-S48-S52 -> -257268.61 | V73: =V36-V39-V48-V52 -> 1941287.8 | W73: =W36-W39-W48-W52 -> -460123 | X73: =X36-X39-X48-X52 -> 1481164.8 | AA73: =AA36-AA39-AA48-AA52 -> 1087250.4 | AB73: =AB36-AB39-AB48-AB52 -> -262444.07 | AC73: =AC36-AC39-AC48-AC52 -> 824806.37 | AF73: =AF36-AF39-AF48-AF52 -> 467292.99 | AG73: =AG36-AG39-AG48-AG52 -> -181273.36 | AH73: =AH36-AH39-AH48-AH52 -> 286019.63 | AK73: =AK36-AK39-AK48-AK52 -> -3489.206 | AL73: =AL36-AL39-AL48-AL52 -> -80000 | AM73: =AM36-AM39-AM48-AM52 -> -83489.206 | AP73: =AP36-AP39-AP48-AP52 -> 2266809.2 | AQ73: =AQ36-AQ39-AQ48-AQ52 -> -1094576.2 | AR73: =AR36-AR39-AR48-AR52 -> 1172232.9 | AU73: =AU36-AU39-AU48-AU52 -> 263119.84 | AV73: =AV36-AV39-AV48-AV52 -> 228261.23 | AW73: =AW36-AW39-AW48-AW52 -> 491381.06
B74: Операционная прибыль, % | C74: =C73/C5 -> 0.55106801 | D74: =D73/D5 -> #DIV/0! | E74: =E73/E5 -> 0.36236766 | G74: =G73/G5 -> #DIV/0! | H74: =H73/H5 -> #DIV/0! | I74: =I73/I5 -> #DIV/0! | L74: =L73/L5 -> #DIV/0! | M74: =M73/M5 -> #DIV/0! | N74: =N73/N5 -> #DIV/0! | Q74: =Q73/Q5 -> #DIV/0! | R74: =R73/R5 -> #DIV/0! | S74: =S73/S5 -> #DIV/0! | V74: =V73/V5 -> 0.64170766 | W74: =W73/W5 -> #DIV/0! | X74: =X73/X5 -> 0.48961045 | AA74: =AA73/AA5 -> 0.74048432 | AB74: =AB73/AB5 -> #DIV/0! | AC74: =AC73/AC5 -> 0.56174379 | AF74: =AF73/AF5 -> 0.92332618 | AG74: =AG73/AG5 -> #DIV/0! | AH74: =AH73/AH5 -> 0.56514738 | AK74: =AK73/AK5 -> #DIV/0! | AL74: =AL73/AL5 -> #DIV/0! | AM74: =AM73/AM5 -> #DIV/0! | AP74: =AP73/AP5 -> 0.45339954 | AQ74: =AQ73/AQ5 -> #DIV/0! | AR74: =AR73/AR5 -> 0.23446609 | AU74: =AU73/AU5 -> -0.64391021 | AV74: =AV73/AV5 -> #DIV/0! | AW74: =AW73/AW5 -> -1.202514
B75: Финансовая деятельность | C75: =C76-C77 -> -129947 | D75: =D76-D77 -> 0 | E75: =E76-E77 -> -129947 | G75: =G76-G77 -> 0 | H75: =H76-H77 -> 0 | I75: =I76-I77 -> -4172.4545 | L75: =L76-L77 -> 0 | M75: =M76-M77 -> 0 | N75: =N76-N77 -> -5983.1995 | Q75: =Q76-Q77 -> 0 | R75: =R76-R77 -> 0 | S75: =S76-S77 -> -4944.6818 | V75: =V76-V77 -> 0 | W75: =W76-W77 -> 0 | X75: =X76-X77 -> -62744.045 | AA75: =AA76-AA77 -> 0 | AB75: =AB76-AB77 -> 0 | AC75: =AC76-AC77 -> -36838.73 | AF75: =AF76-AF77 -> 0 | AG75: =AG76-AG77 -> 0 | AH75: =AH76-AH77 -> -24791.483 | AK75: =AK76-AK77 -> 0 | AL75: =AL76-AL77 -> 0 | AM75: =AM76-AM77 -> -11007.361 | AP75: =AP76-AP77 -> 0 | AQ75: =AQ76-AQ77 -> 0 | AR75: =AR76-AR77 -> -149260.39 | AU75: =AU76-AU77 -> -129947 | AV75: =AV76-AV77 -> 0 | AW75: =AW76-AW77 -> 31126.531
B76: Финансовый доход | E76: =C76+D76*1.15 -> 0 | I76: =G76+H76*1.15 -> 0 | N76: =L76+M76*1.15 -> 0 | S76: =Q76+R76*1.15 -> 0 | X76: =V76+W76*1.15 -> 0 | Y76: =X76/$X$87 -> 0 | AC76: =AA76+AB76*1.15 -> 0 | AD76: =AC76/$X$87 -> 0 | AH76: =AF76+AG76*1.15 -> 0 | AI76: =AH76/$X$87 -> 0 | AM76: =AK76+AL76*1.15 -> 0 | AN76: =AM76/$X$87 -> 0 | AP76: =G76+L76+Q76+V76+AA76+AF76+AK76 -> 0 | AQ76: =H76+M76+R76+W76+AB76+AG76+AL76 -> 0 | AR76: =AP76+AQ76*1.15 -> 0 | AW76: =AU76+AV76*1.15 -> 0
B77: Финансовые расходы | C77: 129947 | E77: =C77+D77*1.15 -> 129947 | F77: =E77/$E$87 -> 0.040671762 | I77: =(H8+H39+H48+H52)/0.88*0.12 -> 4172.4545 | N77: =(M8+M39+M48+M52)/0.88*0.12 -> 5983.1995 | S77: =(R8+R39+R48+R52)/0.88*0.12 -> 4944.6818 | X77: =(W8+W39+W48+W52)/0.88*0.12 -> 62744.045 | Y77: =X77/$X$87 -> 0.039049809 | AC77: =(AB8+AB39+AB48+AB52)/(1-'расчет 2020'!E13)*'расчет 2020'!E13 -> 36838.73 | AD77: =AC77/$X$87 -> 0.022927202 | AH77: =(AG8+AG39+AG48+AG52)/(1-'расчет 2020'!E14)*'расчет 2020'!E14 -> 24791.483 | AI77: =AH77/$X$87 -> 0.015429395 | AM77: =(AL8+AL39+AL48+AL52)/(1-'расчет 2020'!E15)*'расчет 2020'!E15 -> 11007.361 | AN77: =AM77/$X$87 -> 0.0068506157 | AP77: =G77+L77+Q77+V77+AA77+AF77+AK77 -> 0 | AQ77: =H77+M77+R77+W77+AB77+AG77+AL77 -> 0 | AR77: =(AQ8+AQ39+AQ48+AQ52)/0.88*0.12 -> 149260.39 | AU77: =C77-AP77 -> 129947 | AV77: =D77-AQ77 -> 0 | AW77: =(AV8+AV39+AV48+AV52)/0.88*0.12 -> -31126.531 | AX77: =AW77/$E$87 -> -0.0097422093
AP78: =G78+L78+Q78 -> 0 | AQ78: =H78+M78+R78 -> 0
B79: Прибыль после вычета финансовых затрат | C79: =(C73+C76)-C77 -> 2399982 | D79: =(D73+D76)-D77 -> -866315 | E79: =(E73+E76)-E77 -> 1533667 | G79: =(G73+G76)-G77 -> -44655 | H79: =(H73+H76)-H77 -> -30598 | I79: =(I73+I76)-I77 -> -79425.455 | L79: =(L73+L76)-L77 -> -959870.27 | M79: =(M73+M76)-M77 -> -43876.796 | N79: =(N73+N76)-N77 -> -1009730.3 | Q79: =(Q73+Q76)-Q77 -> -221007.61 | R79: =(R73+R76)-R77 -> -36261 | S79: =(S73+S76)-S77 -> -262213.29 | V79: =(V73+V76)-V77 -> 1941287.8 | W79: =(W73+W76)-W77 -> -460123 | X79: =(X73+X76)-X77 -> 1418420.8 | AA79: =(AA73+AA76)-AA77 -> 1087250.4 | AB79: =(AB73+AB76)-AB77 -> -262444.07 | AC79: =(AC73+AC76)-AC77 -> 787967.64 | AF79: =(AF73+AF76)-AF77 -> 467292.99 | AG79: =(AG73+AG76)-AG77 -> -181273.36 | AH79: =(AH73+AH76)-AH77 -> 261228.14 | AK79: =(AK73+AK76)-AK77 -> -3489.206 | AL79: =(AL73+AL76)-AL77 -> -80000 | AM79: =(AM73+AM76)-AM77 -> -94496.567 | AP79: =(AP73+AP76)-AP77 -> 2266809.2 | AQ79: =(AQ73+AQ76)-AQ77 -> -1094576.2 | AR79: =(AR73+AR76)-AR77 -> 1022972.5 | AU79: =(AU73+AU76)-AU77 -> 133172.84 | AV79: =(AV73+AV76)-AV77 -> 228261.23 | AW79: =(AW73+AW76)-AW77 -> 522507.6
B80: Затраты на налог на прибыль | E80: =C80+D80 -> 0 | F80: =E80/$E$87 -> 0 | I80: =G80+H80 -> 0 | N80: =L80+M80 -> 0 | S80: =Q80+R80 -> 0 | X80: =V80+W80 -> 0 | Y80: =X80/$X$87 -> 0 | AC80: =AA80+AB80 -> 0 | AD80: =AC80/$X$87 -> 0 | AH80: =AF80+AG80 -> 0 | AI80: =AH80/$X$87 -> 0 | AM80: =AK80+AL80 -> 0 | AN80: =AM80/$X$87 -> 0 | AP80: =G80+L80+Q80+V80+AA80+AF80+AK80 -> 0 | AQ80: =H80+M80+R80+W80+AB80+AG80+AL80 -> 0 | AR80: =AP80+AQ80 -> 0 | AW80: =AU80+AV80 -> 0 | AX80: =AW80/$E$87 -> 0
B81: Прибыль до вычета налогов | C81: =(C79+C7)-C34 -> 2399982 | D81: =(D79+D7)-D34 -> -866315 | E81: =(E79+E7)-E34 -> 1533667 | G81: =(G79+G7)-G34 -> -44655 | H81: =(H79+H7)-H34 -> -30598 | I81: =(I79+I7)-I34 -> -79425.455 | L81: =(L79+L7)-L34 -> -959870.27 | M81: =(M79+M7)-M34 -> -43876.796 | N81: =(N79+N7)-N34 -> -1009730.3 | Q81: =(Q79+Q7)-Q34 -> -221007.61 | R81: =(R79+R7)-R34 -> -36261 | S81: =(S79+S7)-S34 -> -262213.29 | V81: =(V79+V7)-V34 -> 1941287.8 | W81: =(W79+W7)-W34 -> -460123 | X81: =(X79+X7)-X34 -> 1418420.8 | AA81: =(AA79+AA7)-AA34 -> 1087250.4 | AB81: =(AB79+AB7)-AB34 -> -262444.07 | AC81: =(AC79+AC7)-AC34 -> 787967.64 | AF81: =(AF79+AF7)-AF34 -> 467292.99 | AG81: =(AG79+AG7)-AG34 -> -181273.36 | AH81: =(AH79+AH7)-AH34 -> 261228.14 | AK81: =(AK79+AK7)-AK34 -> -3489.206 | AL81: =(AL79+AL7)-AL34 -> -80000 | AM81: =(AM79+AM7)-AM34 -> -94496.567 | AP81: =(AP79+AP7)-AP34 -> 2266809.2 | AQ81: =(AQ79+AQ7)-AQ34 -> -1094576.2 | AR81: =(AR79+AR7)-AR34 -> 1022972.5 | AU81: =(AU79+AU7)-AU34 -> 133172.84 | AV81: =(AV79+AV7)-AV34 -> 228261.23 | AW81: =(AW79+AW7)-AW34 -> 522507.6
B82: Чистый доход | C82: =C81-C71-C80 -> 2262253.3 | D82: =D81-D71-D80 -> -866315 | E82: =E81-E71-E80 -> 1395938.3 | G82: =G81-G71-G80 -> -44655 | H82: =H81-H71-H80 -> -30598 | I82: =I81-I71-I80 -> -79425.455 | L82: =L81-L71-L80 -> -959870.27 | M82: =M81-M71-M80 -> -43876.796 | N82: =N81-N71-N80 -> -1009730.3 | Q82: =Q81-Q71-Q80 -> -221007.61 | R82: =R81-R71-R80 -> -36261 | S82: =S81-S71-S80 -> -262213.29 | V82: =V81-V71-V80 -> 1941287.8 | W82: =W81-W71-W80 -> -460123 | X82: =X81-X71-X80 -> 1418420.8 | AA82: =AA81-AA71-AA80 -> 1087250.4 | AB82: =AB81-AB71-AB80 -> -262444.07 | AC82: =AC81-AC71-AC80 -> 787967.64 | AF82: =AF81-AF71-AF80 -> 467292.99 | AG82: =AG81-AG71-AG80 -> -181273.36 | AH82: =AH81-AH71-AH80 -> 261228.14 | AK82: =AK81-AK71-AK80 -> -3489.206 | AL82: =AL81-AL71-AL80 -> -80000 | AM82: =AM81-AM71-AM80 -> -94496.567 | AP82: =AP81-AP71-AP80 -> 2266809.2 | AQ82: =AQ81-AQ71-AQ80 -> -1094576.2 | AR82: =AR81-AR71-AR80 -> 1022972.5 | AU82: =AU81-AU71-AU80 -> -4555.8413 | AV82: =AV81-AV71-AV80 -> 228261.23 | AW82: =AW81-AW71-AW80 -> 384778.92
B83: Дивиденды | E83: =C83+D83 -> 0 | F83: =E83/$E$87 -> 0 | I83: =G83+H83 -> 0 | N83: =L83+M83 -> 0 | S83: =Q83+R83 -> 0 | X83: =V83+W83 -> 0 | Y83: =X83/$X$87 -> 0 | AC83: =AA83+AB83 -> 0 | AD83: =AC83/$X$87 -> 0 | AH83: =AF83+AG83 -> 0 | AI83: =AH83/$X$87 -> 0 | AM83: =AK83+AL83 -> 0 | AN83: =AM83/$X$87 -> 0 | AP83: =G83+L83+Q83+V83+AA83+AF83+AK83 -> 0 | AQ83: =H83+M83+R83+W83+AB83+AG83+AL83 -> 0 | AR83: =AP83+AQ83*1.15 -> 0 | AU83: =C83-AP83 -> 0 | AV83: =D83-AQ83 -> 0 | AW83: =AU83+AV83*1.15 -> 0 | AX83: =AW83/$E$87 -> 0
B84: Прибыль в распоряжении компании (нераспределенная прибыль), грн | C84: =C82-C83 -> 2262253.3 | D84: =D82-D83 -> -866315 | E84: =E82-E83 -> 1395938.3 | G84: =G82-G83 -> -44655 | H84: =H82-H83 -> -30598 | I84: =I82-I83 -> -79425.455 | L84: =L82-L83 -> -959870.27 | M84: =M82-M83 -> -43876.796 | N84: =N82-N83 -> -1009730.3 | Q84: =Q82-Q83 -> -221007.61 | R84: =R82-R83 -> -36261 | S84: =S82-S83 -> -262213.29 | V84: =V82-V83 -> 1941287.8 | W84: =W82-W83 -> -460123 | X84: =X82-X83 -> 1418420.8 | AA84: =AA82-AA83 -> 1087250.4 | AB84: =AB82-AB83 -> -262444.07 | AC84: =AC82-AC83 -> 787967.64 | AF84: =AF82-AF83 -> 467292.99 | AG84: =AG82-AG83 -> -181273.36 | AH84: =AH82-AH83 -> 261228.14 | AK84: =AK82-AK83 -> -3489.206 | AL84: =AL82-AL83 -> -80000 | AM84: =AM82-AM83 -> -94496.567 | AP84: =AP82-AP83 -> 2266809.2 | AQ84: =AQ82-AQ83 -> -1094576.2 | AR84: =AR82-AR83 -> 1022972.5 | AU84: =AU82-AU83 -> -4555.8413 | AV84: =AV82-AV83 -> 228261.23 | AW84: =AW82-AW83 -> 384778.92
B85: Рентабельность продукции, % | C85: =C84/C5 -> 0.49276301 | D85: =D84/D5 -> #DIV/0! | E85: =E84/E5 -> 0.30406267 | G85: =G84/G5 -> #DIV/0! | H85: =H84/H5 -> #DIV/0! | I85: =I84/I5 -> #DIV/0! | L85: =L84/L5 -> #DIV/0! | M85: =M84/M5 -> #DIV/0! | N85: =N84/N5 -> #DIV/0! | Q85: =Q84/Q5 -> #DIV/0! | R85: =R84/R5 -> #DIV/0! | S85: =S84/S5 -> #DIV/0! | V85: =V84/V5 -> 0.64170766 | W85: =W84/W5 -> #DIV/0! | X85: =X84/X5 -> 0.46886993 | AA85: =AA84/AA5 -> 0.74048432 | AB85: =AB84/AB5 -> #DIV/0! | AC85: =AC84/AC5 -> 0.53665435 | AF85: =AF84/AF5 -> 0.92332618 | AG85: =AG84/AG5 -> #DIV/0! | AH85: =AH84/AH5 -> 0.51616179 | AK85: =AK84/AK5 -> #DIV/0! | AL85: =AL84/AL5 -> #DIV/0! | AM85: =AM84/AM5 -> #DIV/0! | AP85: =AP84/AP5 -> 0.45339954 | AQ85: =AQ84/AQ5 -> #DIV/0! | AR85: =AR84/AR5 -> 0.20461153 | AU85: =AU84/AU5 -> 0.011149113 | AV85: =AV84/AV5 -> #DIV/0! | AW85: =AW84/AW5 -> -0.94163585
B87: Итого затрат | E87: =E8+E34+E39+E48+E52+E71+E77+E80+E83 -> 3195017.7 | I87: =I8+I34+I39+I48+I52+I71+I77+I80+I83 -> 79425.455 | N87: =N8+N34+N39+N48+N52+N71+N77+N80+N83 -> 1009730.3 | S87: =S8+S34+S39+S48+S52+S71+S77+S80+S83 -> 262213.29 | X87: =X8+X34+X39+X48+X52+X71+X77+X80+X83 -> 1606769.6 | AC87: =AC8+AC34+AC39+AC48+AC52+AC71+AC77+AC80+AC83 -> 680328.74 | AH87: =AH8+AH34+AH39+AH48+AH52+AH71+AH77+AH80+AH83 -> 244869.27 | AM87: =AM8+AM34+AM39+AM48+AM52+AM71+AM77+AM80+AM83 -> 94496.567 | AR87: =AR8+AR34+AR39+AR48+AR52+AR71+AR77+AR80+AR83 -> 3976611.6 | AW87: =AW8+AW34+AW39+AW48+AW52+AW71+AW77+AW80+AW83 -> -793407.07

Sheet расчет 2024
C1: СТРОИТЕЛЬСТВО | G1: ЛОГИСТИКА | K1: ПРОИЗВОДСТВО
A2: 1. Расчет комиссии ФА: | C2: =SUM(D4:D23)/SUM(C4:C23) -> 0.12232717 | G2: =SUM(H4:H23)/SUM(G4:G23) -> 0.11141855 | K2: =SUM(L4:L23)/SUM(K4:K23) -> 0.058979856
C3: Всего | D3: в т.ч. комиссия | E3: удельный вес комиссии | G3: Всего | H3: в т.ч. комиссия | I3: удельный вес комиссии | K3: Всего | L3: в т.ч. комиссия | M3: удельный вес комиссии
B4: 1 | C4: 2408426 | D4: 313095.38 | E4: =D4/C4 -> 0.13 | I4: =H4/G4 -> #DIV/0! | M4: =L4/K4 -> #DIV/0!
B5: 2 | C5: 3090864 | D5: 401812.32 | E5: =D5/C5 -> 0.13 | I5: =H5/G5 -> #DIV/0! | M5: =L5/K5 -> #DIV/0!
B6: 3 | C6: 0 | D6: 0 | E6: 0.13 | I6: 0.13 | M6: 0.13
B7: Август | C7: 5652236.7 | D7: 621432.22 | E7: =D7/C7 -> 0.10994448 | G7: 63036 | H7: 8825 | I7: =H7/G7 -> 0.13999937 | K7: =699476 -> 699476 | L7: 47451.54 | M7: =L7/K7 -> 0.067838696
B8: Сентябрь | C8: 10747681 | D8: 1359669.4 | E8: =D8/C8 -> 0.12650816 | G8: 100378.2 | H8: 14052.95 | I8: =H8/G8 -> 0.14000002 | K8: 1340996 | L8: 46250 | M8: =L8/K8 -> 0.03448929
B9: Октябрь | E9: =D9/C9 -> #DIV/0! | G9: 618288.79 | H9: 25433.85 | I9: =H9/G9 -> 0.041135874 | K9: 4151566 | L9: 195298.3 | M9: =L9/K9 -> 0.04704208
B10: Ноябрь | E10: =D10/C10 -> #DIV/0! | G10: 150445 | H10: 16548.95 | I10: =H10/G10 -> 0.11 | K10: 1312900 | L10: 59465 | M10: =L10/K10 -> 0.045292863
B11: Декабрь | C11: 3979360 | D11: 457626.4 | E11: =D11/C11 -> 0.115 | G11: 1267898 | H11: 147703.57 | I11: =H11/G11 -> 0.11649483 | K11: 4368550 | L11: 204187.5 | M11: =L11/K11 -> 0.046740337
B12: Январь 2023 | E12: =D12/C12 -> #DIV/0! | I12: =H12/G12 -> #DIV/0! | K12: 200000 | L12: 6000 | M12: =L12/K12 -> 0.03
B13: Февраль 2023 | C13: 2285664.8 | D13: 262851.45 | E13: =D13/C13 -> 0.115 | G13: 696620.59 | H13: 80111.37 | I13: =H13/G13 -> 0.115 | K13: 200000 | L13: 6000 | M13: =L13/K13 -> 0.03
B14: Март 2023 | C14: 4006508.2 | D14: 475748.45 | E14: =D14/C14 -> 0.11874391 | G14: =655733.71+139000 -> 794733.71 | H14: 75409.377 | I14: =H14/G14 -> 0.094886345 | K14: 4229000 | L14: 126870 | M14: =L14/K14 -> 0.03
B15: апрель 2023 | C15: 2850000 | D15: 342000 | E15: =D15/C15 -> 0.12 | G15: 429137.72 | H15: 49350.838 | I15: =H15/G15 -> 0.115 | K15: 1405340 | L15: 70267 | M15: =L15/K15 -> 0.05
B16: май 2023 | C16: 1889615.7 | D16: 223397.73 | E16: =D16/C16 -> 0.11822389 | I16: =H16/G16 -> #DIV/0! | K16: 2131701.4 | L16: 109432.72 | M16: =L16/K16 -> 0.051335858
B17: июнь 2023 | C17: 5146581 | D17: 637523 | E17: =D17/C17 -> 0.12387311 | G17: 401936 | H17: 52252 | I17: =H17/G17 -> 0.1300008 | K17: 1726170 | L17: 94939 | M17: =L17/K17 -> 0.054999797
B18: июль 2023 | C18: 1091840 | D18: 119011 | E18: =D18/C18 -> 0.1090004 | G18: 483950 | H18: 53235 | I18: =H18/G18 -> 0.11000103 | K18: 3202451 | L18: 167623 | M18: =L18/K18 -> 0.052342097
B19: август 2023 | C19: 9462589.4 | D19: 1103619.3 | E19: =D19/C19 -> 0.11662973 | G19: 299954 | H19: 32994.94 | I19: =H19/G19 -> 0.11 | K19: 1499970.2 | L19: 172496.57 | M19: =L19/K19 -> 0.115
B20: сентябрь 2023 | C20: 7762830 | D20: 918259 | E20: =D20/C20 -> 0.11828921 | G20: 543482 | H20: 70452 | I20: =H20/G20 -> 0.12963079 | K20: 1318783 | L20: 157961 | M20: =L20/K20 -> 0.11977786
B21: октябрь 2023 | C21: 4285951 | D21: 496273.3 | E21: =D21/C21 -> 0.11579071 | G21: 449304.76 | H21: 52029.49 | I21: =H21/G21 -> 0.1158 | K21: =1006651.19 -> 1006651.2 | L21: 116570.2 | M21: =L21/K21 -> 0.11579999
B22: Ноябрь 2023 | C22: 5646078 | D22: 718987 | E22: =D22/C22 -> 0.12734273 | G22: 123912 | H22: 17348 | I22: =H22/G22 -> 0.14000258 | M22: 0.1273
B23: Декабрь 2023 | C23: 9191143 | D23: 1273382 | E23: =D23/C23 -> 0.13854447 | G23: 628409 | H23: 89919 | I23: =H23/G23 -> 0.14308993 | K23: 1468605 | L23: 204046 | M23: =L23/K23 -> 0.13893865
B24: Январь 2024 | C24: 3135856 | D24: 394168 | E24: =D24/C24 -> 0.1256971 | G24: 120000 | H24: 16200 | I24: =H24/G24 -> 0.135 | K24: 1312728 | L24: 183782 | M24: =L24/K24 -> 0.14000006
B25: Февраль 2024 | C25: 4891736 | D25: 629847 | E25: =D25/C25 -> 0.12875736 | G25: 0 | H25: 0 | I25: =I24 -> 0.135 | K25: 442477 | L25: 57522 | M25: =L25/K25 -> 0.12999998
B26: Март 2024 | C26: 5338093 | D26: 672676.22 | E26: =D26/C26 -> 0.12601433 | G26: 120000 | H26: 15600 | I26: =H26/G26 -> 0.13 | K26: 319855 | L26: 41581 | M26: =L26/K26 -> 0.12999953
B27: Апрель 2024 | C27: 3575203.1 | D27: 464776.4 | E27: =D27/C27 -> 0.13 | G27: 0 | H27: 0 | I27: =I26 -> 0.13 | K27: 806365.59 | L27: 104827.53 | M27: =L27/K27 -> 0.13
B28: Май 2024 | C28: 5004914 | D28: 647658 | E28: =D28/C28 -> 0.12940442 | G28: 199968 | H28: 23996 | I28: =H28/G28 -> 0.1199992 | K28: 30053 | L28: 3907 | M28: =L28/K28 -> 0.13000366
B29: Июнь 2024 | C29: 1 | D29: 0.13 | E29: =D29/C29 -> 0.13 | G29: 1 | H29: 0.13 | I29: =H29/G29 -> 0.13 | K29: 1 | L29: 0.13 | M29: =L29/K29 -> 0.13
B32: Переходящяя Чистая прибыль за минусом CAPEX и Фин деятельности на 31.12.2021г. | C32: 15831480
B34: Прибыль по отчету | C34: 17670
C35: PnL | D35: инвестиции | E35: дивиденды | F35: Свободные ДС | G35: Резервный фонд | H35: ДС к распределению
B36: PnL по направлениям | C36: =C44 -> #REF! | D36: =SUM(D37:D41) -> 70760346 | E36: =SUM(E37:E41) -> 18204451 | F36: =SUM(F37:F41) -> #REF! | G36: =SUM(G37:G40) -> 7763333.3 | H36: =SUM(H37:H40) -> #REF!
B37: СТРОИТЕЛЬСТВО | C37: =53608622.52-1170745+#REF!+#REF!+#REF!+#REF!+#REF! -> #REF! | D37: =C46 -> 56679410 | E37: =C64 -> 12998874 | F37: =C37-D37-E37+(C40/3*2) -> #REF! | G37: =3000000+1000000/3*2+1500000+1000000/3*2 -> 5833333.3 | H37: =F37-G37 -> #REF!
B38: ЛОГИСТИКА+спецтехника | C38: =3620913.24+1403538-254470-1314185.2+#REF!+#REF!+#REF!+#REF!+#REF!+#REF!+#REF!+#REF!+#REF!+#REF! -> #REF! | D38: =C55 -> 2537197 | E38: =C65 -> 0 | F38: =C38-D38-E38 -> #REF! | H38: =F38-G38 -> #REF!
B39: ПРОИЗВОДСТВО | C39: =24034035.74+PL_Производство_СВОД!AD86+PL_Производство_СВОД!AI86+PL_Производство_СВОД!AN86+PL_Производство_СВОД!AS86+PL_Производство_СВОД!AX86 -> 22920002 | D39: =C58 -> 11543739 | E39: =C66 -> 5205576.9 | F39: =C39-D39-E39+(C40/3) -> #REF! | G39: =750000+1000000/3+500000+1000000/3+13333.3333333334 -> 1930000 | H39: =F39-G39 -> #REF!
B40: ЦО распределить Строительстов 2/ Производство 1 | C40: =-4674263.27+#REF!+#REF!+#REF!+#REF!+#REF! -> #REF!
C41: =C36-C37-C38-C39-C40 -> #REF!
B42: добавить вливания инвестора по направлениям
B44: операционная прибыль по компании 2022 - 2024г. | C44: =75253446.36+#REF! -> #REF! | D44: 44562 | E44: 44593 | F44: 44621 | G44: 44652 | H44: 44682 | I44: 44713 | J44: 44743 | K44: 44774 | L44: 44805 | M44: 44835 | N44: 44866 | O44: 44896 | P44: янв.23 | Q44: фев.23 | R44: март 23 | S44: апр.23 | T44: май 23 | U44: июн.23 | V44: июл.23 | W44: авг.23 | X44: сент.23 | Y44: окт.23 | Z44: 45231 | AA44: 45261 | AB44: 45292 | AC44: 45323 | AD44: 45352 | AE44: 45383 | AF44: 45413
B45: Покупка ОС (CAPEX) или инвестиции | C45: =C46+C55+C58 -> 70760346 | D45: =D46+D55+D58 -> 2050243.6 | E45: =E46+E55+E58 -> 4709675 | F45: =F46+F55+F58 -> 0 | G45: =G46+G55+G58 -> 0 | H45: =H46+H55+H58 -> 0 | I45: =I46+I55+I58 -> 8236445.2 | J45: =J46+J55+J58 -> 5137258 | ... AF45: =AF46+AF55+AF58 -> 0
B46: СТРОИТЕЛЬСТВО | C46: =SUM(D46:AF46) -> 56679410 | D46: =SUM(D47:D54) -> 2050243.6 | E46: =SUM(E47:E54) -> 4709675 | F46: =SUM(F47:F54) -> 0 | G46: =SUM(G47:G54) -> 0 | H46: =SUM(H47:H54) -> 0 | I46: =SUM(I47:I54) -> 8236445.2 | J46: =SUM(J47:J54) -> 5137258 | K46: =SUM(K47:K54) -> 9675 | ... AF46: =SUM(AF47:AF54) -> 0
B47: офис | C47: =SUM(D47:AF47) -> 10624 | E47: =10624 -> 10624
B48: И.П.С. | C48: =SUM(D48:AF48) -> 3436060 | U48: =1104300 -> 1104300 | V48: 2331760
B49: Подгорцы | C49: =SUM(D49:AF49) -> 34431488 | D49: =1751726.91+20160+8400+25849.15+24000+13558+2058+7975.54+7280+3543+5765+17374+10345+3522+1674 -> 1903230.6 | E49: =3801067+2470+43500+116044+58479+114777.36*1.2+1696.38 -> 4160989.2 | K49: 9675 | L49: 43500 | O49: 143467 | Q49: 11950 | S49: 185 | T49: 154918 | U49: 606394 | V49: 9010.24 | W49: 1068418.4 | X49: 2445758.7 | Y49: 7332813.3 | Z49: 3284317.1 | AA49: 2987534.9 | AB49: 3979772.5 | AC49: 4431677.1 | AD49: 1857877.3 | AE49: 0 | AF49: 0
B50: Лебедевка | C50: =SUM(D50:AF50) -> 3404440 | V50: =2300000+104440+1000000 -> 3404440
B51: техника | C51: =SUM(D51:AF51) -> 1765048 | D51: =61004 -> 61004 | E51: =61004 -> 61004 | I51: 244016 | J51: 61004 | AC51: 1338020
B52: капитальные инвестиции | C52: =SUM(D52:AF52) -> 13301771 | E52: 279000 | I52: =3174779.22+4817650 -> 7992429.2 | J52: 5030342
B53: производственные ОС | C53: =SUM(D53:AF53) -> 219491 | D53: 2609 | E53: =23310+147660 -> 170970 | J53: 45912
B54: ПК, ПО | C54: =SUM(D54:AF54) -> 110487.71 | D54: =83399.96 -> 83399.96 | E54: =20111.75+6976 -> 27087.75
B55: ЛОГИСТИКА | C55: =SUM(C56:C57) -> 2537197 | D55: =SUM(D56:D57) -> 0 | E55: =SUM(E56:E57) -> 0 | F55: =SUM(F56:F57) -> 0 | G55: =SUM(G56:G57) -> 0 | H55: =SUM(H56:H57) -> 0 | I55: =SUM(I56:I57) -> 0 | J55: =SUM(J56:J57) -> 0 | ... AF55: =SUM(AF56:AF57) -> 0
B56: техника | C56: =SUM(D56:AF56) -> 244016 | K56: 61004 | L56: 61004 | N56: 122008
B57: капитальные инвестиции | C57: =SUM(D57:AF57) -> 2293181 | N57: 1401096 | O57: =639485+210500*1.2 -> 892085
B58: ПРОИЗВОДСТВО | C58: =SUM(C59:C61) -> 11543739 | D58: =SUM(D60:D61) -> 0 | E58: =SUM(E60:E61) -> 0 | F58: =SUM(F60:F61) -> 0 | G58: =SUM(G60:G61) -> 0 | H58: =SUM(H60:H61) -> 0 | I58: =SUM(I60:I61) -> 0 | J58: =SUM(J60:J61) -> 0 | K58: =SUM(K60:K61) -> 0 | ... P58: =SUM(P60:P61) -> 0 | Q58: =SUM(Q59:Q61) -> 0 | R58: =SUM(R59:R61) -> 0 | S58: =SUM(S59:S61) -> 2755000 | T58: =SUM(T59:T61) -> 1578000 | U58: =SUM(U59:U61) -> 0 | V58: =SUM(V59:V61) -> 1390611 | W58: =SUM(W59:W61) -> 1449600 | X58: =SUM(X59:X61) -> 1590154 | ... AF58: =SUM(AF59:AF61) -> 0
B59: Лебедевка | C59: =SUM(D59:AF59) -> 973391 | V59: =590611+300000 -> 890611 | Z59: 41140 | AB59: 41140 | AC59: 500
B60: техника | C60: =SUM(D60:AF60) -> 2065475 | Z60: =1184000+544475 -> 1728475 | AA60: 296000 | AB60: 41000
B61: И.П.С. | C61: =SUM(D61:AF61) -> 8504873 | S61: =S73 -> 2755000 | T61: =738000+840000 -> 1578000 | V61: 500000 | W61: 1449600 | X61: =250154+1340000 -> 1590154 | Y61: =645119-1950000 -> -1304881 | Z61: 357000 | AA61: 1000000 | AB61: 580000
M62: =2802191/2 -> 1401095.5
B63: Дивиденды | C63: =SUM(C64:C66) -> 18204451 | D63: =SUM(D64:D66) -> 1000000 | E63: =SUM(E64:E66) -> 1000000 | F63: =SUM(F64:F66) -> 0 | G63: =SUM(G64:G66) -> 0 | H63: =SUM(H64:H66) -> 0 | I63: =SUM(I64:I66) -> 0 | J63: =SUM(J64:J66) -> 0 | ... AF63: =SUM(AF64:AF66) -> 2656.24
B64: СТРОИТЕЛЬСТВО | C64: =SUM(D64:AF64) -> 12998874 | D64: 1000000 | E64: 1000000 | K64: 200000 | M64: 4250000 | P64: 221400 | S64: =18000+21400 -> 39400 | U64: =38620+162026.62+3888639 -> 4089285.6 | V64: =300000+10400 -> 310400 | X64: =8815+20000+262229 -> 291044 | Y64: =27435.54+21399.75+1047723.44 -> 1096558.7 | Z64: =6121+424802.24 -> 430923.24 | AA64: =6549.54 -> 6549.54 | AB64: 9013 | AC64: =45547.66+2942.27 -> 48489.93 | AE64: 3154.11 | AF64: 2656.24
B65: ЛОГИСТИКА | C65: =SUM(D65:AF65) -> 0
B66: ПРОИЗВОДСТВО | C66: =SUM(D66:AF66) -> 5205576.9 | N66: 118053 | O66: =2733229 -> 2733229 | P66: 159192 | R66: 300000 | T66: 400000 | X66: 300000 | AA66: 599348.23 | AB66: 122387.35 | AC66: 73367.32 | AE66: 400000
B68: Дельта: | C68: =C44-C45-C63 -> #REF!
D69: 44562 | E69: 44593 | F69: 44621 | G69: 44652 | H69: 44682 | I69: 44713 | J69: 44743 | K69: 44774 | L69: 44805 | M69: 44835 | N69: 44866 | O69: 44896 | P69: янв.23 | Q69: фев.23 | R69: март 23 | S69: апр.23 | T69: май 23 | U69: июн.23 | V69: июл.23 | W69: авг.23
B70: Расшифровка Дивидендов | C70: =SUM(D70:W70) -> 20086033 | D70: 1000000 | E70: 1000000 | K70: 200000 | M70: 4250000 | N70: 118053 | O70: =49068+2733229 -> 2782297 | P70: =400737+21400 -> 422137 | Q70: 47560 | R70: 300000 | S70: =118000+21400+2655000 -> 2794400 | T70: =1578000+3888639+400000 -> 5866639 | U70: =38620+162026.62+1104300 -> 1304946.6
B71: СТРОИТЕЛЬСТВО | C71: =SUM(D71:W71) -> 9704385.5 | M71: 4250000 | P71: =200000+21400 -> 221400 | S71: =18000+21400 -> 39400 | T71: =781442+3107196.86 -> 3888638.9 | U71: =1104300+38620+162026.62 -> 1304946.6
B72: ЛОГИСТИКА | C72: =SUM(D72:W72) -> 138173 | O72: 49068 | P72: 41545 | Q72: 47560
B73: ПРОИЗВОДСТВО | C73: =SUM(D73:W73) -> 8043474 | N73: 118053 | O73: 2733229 | P73: 159192 | R73: 300000 | S73: =100000+2655000 -> 2755000 | T73: =400000+738000+840000 -> 1978000
S74: =S70-S71-S72-S73 -> 0 | T74: =T70-T71-T72-T73 -> 0.14 | U74: =U70-U71-U72-U73 -> 0
B76: Прибыль в распоряжении компании на 1.03.2024г. Минус Фин деятельность, Инвест деятельности | C76: =C68 -> #REF!
B78: Свободные ДС | C78: =C81+C99+C108 -> 33846220
B79: разница | C79: =C76-C78 -> #REF!
B81: р/с | C81: =SUM(C82:C98) -> 23321406
B82: ИБ ОТП | C82: 3244.61
B83: ИБ корпоративная карта | C83: 11032.13
B84: ИБ ОТП Депозит | C84: 4750000
B85: ИБ ТАС | C85: =21114224.42-C84 -> 16364224
B86: ИБ КА | C86: 476.59
B87: ДТ ОТП | C87: 0.06
B88: ДТ Приват | C88: 0
B89: ДТ КА | C89: 55.97
B90: И.П.С. | C90: 565561.94
B91: И.П.С. Трейд | C91: 12741.56
B92: ИТ | C92: 35230.14
B93: ИС грн. | C93: 472561.5
B94: ИС у.е. - 27 000 | C94: =27000*36.55 -> 986850
B95: ДД | C95: 0
B96: Кайлас | C96: 0
B97: Ассетс ВФ | C97: 27.98
B98: ФОП Воронцов | C98: 119399.25
B99: Кассы | C99: =SUM(C100:C107) -> 8401986.5
B100: Резерв | C100: 4985000
B101: Строительство | C101: 2364608.8
B102: Строительство подотчеты | C102: 200714.42
B103: Производство | C103: 159077
B104: Производство подотчеты | C104: 64969.13
B105: Логистика | C105: 173259.62
B106: Логистика подотчеты | C106: 9705.72
B107: ИПС | C107: 444651.88
B108: ДС в пути | C108: =2008695+87986+26146 -> 2122827

Sheet PL_Козин
A2: PL Козин | G2: 2019 | L2: Январь 2020 | Q2: Февраль 2020 | V2: Март 2020 | AA2: Накопительный PL январь-март 2020 | AF2: Остаток PL январь 2020
A3: План итого
B4: Статья | C4: Сумма по Ф1, грн | D4: Сумма по Ф2, грн | E4: Сумма итого, грн | F4: % суммы затрат в общем объеме | G4: Сумма по Ф1, грн | H4: Сумма по Ф2, грн | I4: Сумма итого, грн | J4: % суммы затрат в общем объеме | K4: Комментарий | L4: Сумма по Ф1, грн | M4: Сумма по Ф2, грн | N4: Сумма итого, грн | O4: % суммы затрат в общем объеме | P4: Комментарий | Q4: Сумма по Ф1, грн | R4: Сумма по Ф2, грн | S4: Сумма итого, грн | T4: % суммы затрат в общем объеме | U4: Комментарий | V4: Сумма по Ф1, грн | W4: Сумма по Ф2, грн | X4: Сумма итого, грн | Y4: % суммы затрат в общем объеме | Z4: Комментарий | AA4: Сумма по Ф1, грн | AB4: Сумма по Ф2, грн | AC4: Сумма итого, грн | AD4: % суммы затрат в общем объеме | AE4: Комментарии | AF4: Сумма по Ф1, грн | AG4: Сумма по Ф2, грн | AH4: Сумма итого, грн | AI4: % суммы затрат в общем объеме | AJ4: Комментарии
B5: Операционный доход | C5: =C6 -> 0 | D5: =D6 -> 4969127 | E5: =E6 -> 4969127 | G5: =G6 -> 0 | H5: =H6 -> 0 | I5: =I6 -> 0 | L5: =L6 -> 0 | M5: =M6 -> 1911138 | N5: =N6 -> 1911138 | Q5: =Q6 -> 0 | R5: =R6 -> 0 | S5: =S6 -> 0 | V5: =V6 -> 0 | W5: =W6 -> 2770509.3 | X5: =X6 -> 2770509.3 | AA5: =AA6 -> 0 | AB5: =AB6 -> 4681647.3 | AC5: =AC6 -> 4681647.3 | AF5: =AF6 -> 0 | AG5: =AG6 -> 287479.69 | AH5: =AH6 -> 287479.69
B6: Выручка от продаж (товаров, работ, услуг) | D6: 4969127 | E6: =C6+D6 -> 4969127 | I6: =G6+H6 -> 0 | M6: =1911138 -> 1911138 | N6: =L6+M6 -> 1911138 | P6: акт 1 | S6: =Q6+R6 -> 0 | W6: =3342509.28-572000 -> 2770509.3 | X6: =V6+W6 -> 2770509.3 | Z6: за минусом 572 000 грн не оплатили | AA6: =L6+Q6+V6+G6 -> 0 | AB6: =M6+R6+W6+H6 -> 4681647.3 | AC6: =AA6+AB6 -> 4681647.3 | AF6: =C6-AA6 -> 0 | AG6: =D6-AB6 -> 287479.69 | AH6: =AF6+AG6 -> 287479.69
B7: Доход от прочей операционной деятельности | E7: =C7+D7 -> 0 | I7: =G7+H7 -> 0 | N7: =L7+M7 -> 0 | S7: =Q7+R7 -> 0 | X7: =V7+W7 -> 0 | AC7: =AA7+AB7 -> 0 | AF7: =C7-AA7 -> 0 | AG7: =D7-AB7 -> 0 | AH7: =AF7+AG7 -> 0
B8: Себестоимость проданой продукции (переменные производственные затраты) | C8: =SUM(C9:C31) -> 975438 | D8: =SUM(D9:D31) -> 2243523 | E8: =SUM(E9:E31) -> 3218961 | F8: =E8/$E$87 -> 0.957426 | G8: =SUM(G9:G31) -> 0 | H8: =SUM(H9:H31) -> 480 | I8: =SUM(I9:I31) -> 480 | J8: =I8/$N$87 -> 0.0011248467 | L8: =SUM(L9:L31) -> 172736.6 | M8: =SUM(M9:M31) -> 163985.65 | N8: =SUM(N9:N31) -> 336722.25 | O8: =N8/$N$87 -> 0.7890852 | Q8: =SUM(Q9:Q31) -> 132386.06 | R8: =SUM(R9:R31) -> 33025 | S8: =SUM(S9:S31) -> 165411.06 | T8: =S8/$S$87 -> 0.71402739 | V8: =SUM(V9:V31) -> 209487.07 | W8: =SUM(W9:W31) -> 296819.5 | X8: =SUM(X9:X31) -> 506306.57 | Y8: =X8/$X$87 -> 0.82906417 | AA8: =SUM(AA9:AA31) -> 514609.72 | AB8: =SUM(AB9:AB31) -> 494310.15 | AC8: =SUM(AC9:AC31) -> 1008919.9 | AD8: =AC8/$AC$87 -> 0.79240227 | AF8: =SUM(AF9:AF31) -> 460828.28 | AG8: =SUM(AG9:AG31) -> 1749212.9 | AH8: =SUM(AH9:AH31) -> 2210041.1 | AI8: =AH8/$AH$87 -> 0.91677175
B9: ЗП производственного персонала | C9: 51842 | E9: =C9+D9 -> 51842 | F9: =E9/$E$87 -> 0.015419534 | I9: =G9+H9*1 -> 0 | J9: =I9/$N$87 -> 0 | L9: =5*3944.5 -> 19722.5 | N9: =L9+M9*1 -> 19722.5 | O9: =N9/$N$87 -> 0.046218309 | Q9: =5*6842.5 -> 34212.5 | S9: =Q9+R9*1 -> 34212.5 | T9: =S9/$S$87 -> 0.14768457 | U9: 5 чел бр Пономаренки | V9: =7*6842.5 -> 47897.5 | X9: =V9+W9*1 -> 47897.5 | Y9: =X9/$X$87 -> 0.078430942 | Z9: зп бр.Пономаренко 5чел - 34 212,5 зп бр.Перкатогот 2 чел - 13 685 | AA9: =L9+Q9+V9+G9 -> 101832.5 | AB9: =M9+R9+W9+H9 -> 0 | AC9: =AA9+AB9*1 -> 101832.5 | AD9: =AC9/$AC$87 -> 0.079978902 | AF9: =C9-AA9 -> -49990.5 | AG9: =D9-AB9 -> 0 | AH9: =AF9+AG9*1 -> -49990.5 | AI9: =AH9/$AH$87 -> -0.020737116
B10: Удержание с зарплаты производственного персонала | C10: 14168 | E10: =C10+D10 -> 14168 | F10: =E10/$E$87 -> 0.0042140341 | I10: =G10+H10*1 -> 0 | J10: =I10/$N$87 -> 0 | L10: =955.5*5 -> 4777.5 | N10: =L10+M10*1 -> 4777.5 | O10: =N10/$N$87 -> 0.01119574 | Q10: =1657.5*5 -> 8287.5 | S10: =Q10+R10*1 -> 8287.5 | T10: =S10/$S$87 -> 0.035774524 | V10: =(8500*19.5%)*7 -> 11602.5 | X10: =V10+W10*1 -> 11602.5 | Y10: =X10/$X$87 -> 0.0189988 | AA10: =L10+Q10+V10+G10 -> 24667.5 | AB10: =M10+R10+W10+H10 -> 0 | AC10: =AA10+AB10*1 -> 24667.5 | AD10: =AC10/$AC$87 -> 0.019373771 | AF10: =C10-AA10 -> -10499.5 | AG10: =D10-AB10 -> 0 | AH10: =AF10+AG10*1 -> -10499.5 | AI10: =AH10/$AH$87 -> -0.0043554144
B11: Начисления на зарплату производственного персонала | C11: 12558 | E11: =C11+D11 -> 12558 | F11: =E11/$E$87 -> 0.0037351666 | I11: =G11+H11*1 -> 0 | J11: =I11/$N$87 -> 0 | L11: =1078*5 -> 5390 | N11: =L11+M11*1 -> 5390 | O11: =N11/$N$87 -> 0.012631091 | Q11: =1870*5 -> 9350 | S11: =Q11+R11*1 -> 9350 | T11: =S11/$S$87 -> 0.040361002 | V11: =(8500*22%)*7 -> 13090 | X11: =V11+W11*1 -> 13090 | Y11: =X11/$X$87 -> 0.021434543 | AA11: =L11+Q11+V11+G11 -> 27830 | AB11: =M11+R11+W11+H11 -> 0 | AC11: =AA11+AB11*1 -> 27830 | AD11: =AC11/$AC$87 -> 0.021857588 | AF11: =C11-AA11 -> -15272 | AG11: =D11-AB11 -> 0 | AH11: =AF11+AG11*1 -> -15272 | AI11: =AH11/$AH$87 -> -0.0063351482
B12: Зарплата ИТР | E12: =C12+D12 -> 0 | F12: =E12/$E$87 -> 0 | I12: =G12+H12*1 -> 0 | J12: =I12/$N$87 -> 0 | N12: =L12+M12*1 -> 0 | O12: =N12/$N$87 -> 0 | S12: =Q12+R12*1 -> 0 | T12: =S12/$S$87 -> 0 | X12: =V12+W12*1 -> 0 | Y12: =X12/$X$87 -> 0 | AA12: =L12+Q12+V12+G12 -> 0 | AB12: =M12+R12+W12+H12 -> 0 | AC12: =AA12+AB12*1 -> 0 | AD12: =AC12/$AC$87 -> 0 | AF12: =C12-AA12 -> 0 | AG12: =D12-AB12 -> 0 | AH12: =AF12+AG12*1 -> 0 | AI12: =AH12/$AH$87 -> 0
B13: Удержание с зарплаты ИТР | E13: =C13+D13 -> 0 | F13: =E13/$E$87 -> 0 | I13: =G13+H13*1 -> 0 | J13: =I13/$N$87 -> 0 | N13: =L13+M13*1 -> 0 | O13: =N13/$N$87 -> 0 | S13: =Q13+R13*1 -> 0 | T13: =S13/$S$87 -> 0 | X13: =V13+W13*1 -> 0 | Y13: =X13/$X$87 -> 0 | AA13: =L13+Q13+V13+G13 -> 0 | AB13: =M13+R13+W13+H13 -> 0 | AC13: =AA13+AB13*1 -> 0 | AD13: =AC13/$AC$87 -> 0 | AF13: =C13-AA13 -> 0 | AG13: =D13-AB13 -> 0 | AH13: =AF13+AG13*1 -> 0 | AI13: =AH13/$AH$87 -> 0
B14: Начисления на зарплату ИТР | E14: =C14+D14 -> 0 | F14: =E14/$E$87 -> 0 | I14: =G14+H14*1 -> 0 | J14: =I14/$N$87 -> 0 | N14: =L14+M14*1 -> 0 | O14: =N14/$N$87 -> 0 | S14: =Q14+R14*1 -> 0 | T14: =S14/$S$87 -> 0 | X14: =V14+W14*1 -> 0 | Y14: =X14/$X$87 -> 0 | AA14: =L14+Q14+V14+G14 -> 0 | AB14: =M14+R14+W14+H14 -> 0 | AC14: =AA14+AB14*1 -> 0 | AD14: =AC14/$AC$87 -> 0 | AF14: =C14-AA14 -> 0 | AG14: =D14-AB14 -> 0 | AH14: =AF14+AG14*1 -> 0 | AI14: =AH14/$AH$87 -> 0
B15: ЗП подсобников | E15: =C15+D15 -> 0 | F15: =E15/$E$87 -> 0 | I15: =G15+H15*1 -> 0 | J15: =I15/$N$87 -> 0 | N15: =L15+M15*1 -> 0 | O15: =N15/$N$87 -> 0 | S15: =Q15+R15*1 -> 0 | T15: =S15/$S$87 -> 0 | X15: =V15+W15*1 -> 0 | Y15: =X15/$X$87 -> 0 | AA15: =L15+Q15+V15+G15 -> 0 | AB15: =M15+R15+W15+H15 -> 0 | AC15: =AA15+AB15*1 -> 0 | AD15: =AC15/$AC$87 -> 0 | AF15: =C15-AA15 -> 0 | AG15: =D15-AB15 -> 0 | AH15: =AF15+AG15*1 -> 0 | AI15: =AH15/$AH$87 -> 0
B16: Оплата за выполненные работы | D16: 1708693 | E16: =C16+D16 -> 1708693 | F16: =E16/$E$87 -> 0.5082221 | I16: =G16+H16*1 -> 0 | J16: =I16/$N$87 -> 0 | M16: =135000-L9 -> 115277.5 | N16: =L16+M16*1 -> 115277.5 | O16: =N16/$N$87 -> 0.27014482 | P16: за январь | S16: =Q16+R16*1 -> 0 | T16: =S16/$S$87 -> 0 | W16: 250552.5 | X16: =V16+W16*1 -> 250552.5 | Y16: =X16/$X$87 -> 0.41027337 | Z16: Перкатый Пономаренки | AA16: =L16+Q16+V16+G16 -> 0 | AB16: =M16+R16+W16+H16 -> 365830 | AC16: =AA16+AB16*1 -> 365830 | AD16: =AC16/$AC$87 -> 0.28732165 | AF16: =C16-AA16 -> 0 | AG16: =D16-AB16 -> 1342863 | AH16: =AF16+AG16*1 -> 1342863 | AI16: =AH16/$AH$87 -> 0.55704794
B17: Премия производственного персонала | E17: =C17+D17 -> 0 | F17: =E17/$E$87 -> 0 | I17: =G17+H17*1 -> 0 | J17: =I17/$N$87 -> 0 | N17: =L17+M17*1 -> 0 | O17: =N17/$N$87 -> 0 | S17: =Q17+R17*1 -> 0 | T17: =S17/$S$87 -> 0 | X17: =V17+W17*1 -> 0 | Y17: =X17/$X$87 -> 0 | AA17: =L17+Q17+V17+G17 -> 0 | AB17: =M17+R17+W17+H17 -> 0 | AC17: =AA17+AB17*1 -> 0 | AD17: =AC17/$AC$87 -> 0 | AF17: =C17-AA17 -> 0 | AG17: =D17-AB17 -> 0 | AH17: =AF17+AG17*1 -> 0 | AI17: =AH17/$AH$87 -> 0
B18: Услуги сторонних организаций | C18: 30000 | D18: 18830 | E18: =C18+D18 -> 48830 | F18: =E18/$E$87 -> 0.014523665 | I18: =G18+H18*1 -> 0 | J18: =I18/$N$87 -> 0 | L18: 15000 | M18: 18830 | N18: =L18+M18*1 -> 33830 | O18: =N18/$N$87 -> 0.079278256 | P18: Монтаж РДК -15 000 грн КМД - 18 830 грн | R18: 7455 | S18: =Q18+R18*1 -> 7455 | T18: =S18/$S$87 -> 0.032180884 | U18: КМД | V18: 21000 | X18: =V18+W18*1 -> 21000 | Y18: =X18/$X$87 -> 0.034386968 | Z18: Демонтаж РДК | AA18: =L18+Q18+V18+G18 -> 36000 | AB18: =M18+R18+W18+H18 -> 26285 | AC18: =AA18+AB18*1 -> 62285 | AD18: =AC18/$AC$87 -> 0.048918429 | AF18: =C18-AA18 -> -6000 | AG18: =D18-AB18 -> -7455 | AH18: =AF18+AG18*1 -> -13455 | AI18: =AH18/$AH$87 -> -0.0055814183
B19: Аренда строительного оборудования | E19: =C19+D19 -> 0 | F19: =E19/$E$87 -> 0 | I19: =G19+H19*1 -> 0 | J19: =I19/$N$87 -> 0 | N19: =L19+M19*1 -> 0 | O19: =N19/$N$87 -> 0 | S19: =Q19+R19*1 -> 0 | T19: =S19/$S$87 -> 0 | X19: =V19+W19*1 -> 0 | Y19: =X19/$X$87 -> 0 | AA19: =L19+Q19+V19+G19 -> 0 | AB19: =M19+R19+W19+H19 -> 0 | AC19: =AA19+AB19*1 -> 0 | AD19: =AC19/$AC$87 -> 0 | AF19: =C19-AA19 -> 0 | AG19: =D19-AB19 -> 0 | AH19: =AF19+AG19*1 -> 0 | AI19: =AH19/$AH$87 -> 0
B20: Аренда опалубки | E20: =C20+D20 -> 0 | F20: =E20/$E$87 -> 0 | I20: =G20+H20*1 -> 0 | J20: =I20/$N$87 -> 0 | N20: =L20+M20*1 -> 0 | O20: =N20/$N$87 -> 0 | S20: =Q20+R20*1 -> 0 | T20: =S20/$S$87 -> 0 | X20: =V20+W20*1 -> 0 | Y20: =X20/$X$87 -> 0 | AA20: =L20+Q20+V20+G20 -> 0 | AB20: =M20+R20+W20+H20 -> 0 | AC20: =AA20+AB20*1 -> 0 | AD20: =AC20/$AC$87 -> 0 | AF20: =C20-AA20 -> 0 | AG20: =D20-AB20 -> 0 | AH20: =AF20+AG20*1 -> 0 | AI20: =AH20/$AH$87 -> 0
B21: Арена техники | C21: 140000 | E21: =C21+D21 -> 140000 | F21: =E21/$E$87 -> 0.041640654 | I21: =G21+H21*1 -> 0 | J21: =I21/$N$87 -> 0 | L21: 48080.76 | N21: =L21+M21*1 -> 48080.76 | O21: =N21/$N$87 -> 0.11267392 | P21: РДК 250 (наш) = 105*264,18 грн= 27 739 грн+77 ч 8848 | Q21: 70536.06 | S21: =Q21+R21*1 -> 70536.06 | T21: =S21/$S$87 -> 0.30448193 | U21: РДК 158 ч*264,18+109 ч для 8848 | V21: 35664 | X21: =V21+W21*1 -> 35664 | Y21: =X21/$X$87 -> 0.058398896 | Z21: РДК 250 135ч =35 664 в т ч 8848-22ч | AA21: =L21+Q21+V21+G21 -> 154280.82 | AB21: =M21+R21+W21+H21 -> 0 | AC21: =AA21+AB21*1 -> 154280.82 | AD21: =AC21/$AC$87 -> 0.12117164 | AF21: =C21-AA21 -> -14280.82 | AG21: =D21-AB21 -> 0 | AH21: =AF21+AG21*1 -> -14280.82 | AI21: =AH21/$AH$87 -> -0.0059239858
B22: Логистические затраты | C22: 145600 | E22: =C22+D22 -> 145600 | F22: =E22/$E$87 -> 0.04330628 | I22: =G22+H22*1 -> 0 | J22: =I22/$N$87 -> 0 | L22: =(20833.35*1.2)+15000 -> 40000.02 | N22: =L22+M22*1 -> 40000.02 | O22: =N22/$N$87 -> 0.093737269 | P22: доставка металлоконструкций Альфабизнесгрупп 3 ходки + 15 000 грн перебазировка СБМУ | Q22: 10000 | S22: =Q22+R22*1 -> 10000 | T22: =S22/$S$87 -> 0.043166847 | U22: Доставка м/к Альфа-бизнес груп | V22: =8000*1.2 -> 9600 | X22: =V22+W22*1 -> 9600 | Y22: =X22/$X$87 -> 0.015719757 | Z22: Альфа бизнес групп | AA22: =L22+Q22+V22+G22 -> 59600.02 | AB22: =M22+R22+W22+H22 -> 0 | AC22: =AA22+AB22*1 -> 59600.02 | AD22: =AC22/$AC$87 -> 0.046809655 | AF22: =C22-AA22 -> 85999.98 | AG22: =D22-AB22 -> 0 | AH22: =AF22+AG22*1 -> 85999.98 | AI22: =AH22/$AH$87 -> 0.035674609
B23: МШП | C23: 302006 | E23: =C23+D23 -> 302006 | F23: =E23/$E$87 -> 0.089826623 | I23: =G23+H23*1 -> 0 | J23: =I23/$N$87 -> 0 | L23: =4769.8*1.2 -> 5723.76 | M23: 354.45 | N23: =L23+M23*1 -> 6078.21 | O23: =N23/$N$87 -> 0.014243863 | P23: списанные МШП | R23: 300 | S23: =Q23+R23*1 -> 300 | T23: =S23/$S$87 -> 0.0012950054 | V23: 11862.624 | W23: 163 | X23: =V23+W23*1 -> 12025.624 | Y23: =X23/$X$87 -> 0.019691654 | Z23: за минусом спецодежды механизатора -2 442,99 | AA23: =L23+Q23+V23+G23 -> 17586.384 | AB23: =M23+R23+W23+H23 -> 817.45 | AC23: =AA23+AB23*1 -> 18403.834 | AD23: =AC23/$AC$87 -> 0.014454309 | AF23: =C23-AA23 -> 284419.62 | AG23: =D23-AB23 -> -817.45 | AH23: =AF23+AG23*1 -> 283602.17 | AI23: =AH23/$AH$87 -> 0.11764417
B24: Строительные материалы | C24: 178192 | E24: =C24+D24 -> 178192 | F24: =E24/$E$87 -> 0.053000224 | I24: =G24+H24*1 -> 0 | J24: =I24/$N$87 -> 0 | L24: =28368.38*1.2 -> 34042.056 | N24: =L24+M24*1 -> 34042.056 | O24: =N24/$N$87 -> 0.079775194 | S24: =Q24+R24*1 -> 0 | T24: =S24/$S$87 -> 0 | V24: =((72535.75+4808)*1.2)-L24 -> 58770.444 | W24: 3503.7 | X24: =V24+W24*1 -> 62274.144 | Y24: =X24/$X$87 -> 0.10197233 | AA24: =L24+Q24+V24+G24 -> 92812.5 | AB24: =M24+R24+W24+H24 -> 3503.7 | AC24: =AA24+AB24*1 -> 96316.2 | AD24: =AC24/$AC$87 -> 0.075646419 | AF24: =C24-AA24 -> 85379.5 | AG24: =D24-AB24 -> -3503.7 | AH24: =AF24+AG24*1 -> 81875.8 | AI24: =AH24/$AH$87 -> 0.033963812
B25: Ремонты | C25: 6000 | E25: =C25+D25 -> 6000 | F25: =E25/$E$87 -> 0.0017845994 | I25: =G25+H25*1 -> 0 | J25: =I25/$N$87 -> 0 | N25: =L25+M25*1 -> 0 | O25: =N25/$N$87 -> 0 | S25: =Q25+R25*1 -> 0 | T25: =S25/$S$87 -> 0 | X25: =V25+W25*1 -> 0 | Y25: =X25/$X$87 -> 0 | AA25: =L25+Q25+V25+G25 -> 0 | AB25: =M25+R25+W25+H25 -> 0 | AC25: =AA25+AB25*1 -> 0 | AD25: =AC25/$AC$87 -> 0 | AF25: =C25-AA25 -> 6000 | AG25: =D25-AB25 -> 0 | AH25: =AF25+AG25*1 -> 6000 | AI25: =AH25/$AH$87 -> 0.0024889268
B26: Прочие производственные затраты | C26: 45272 | E26: =C26+D26 -> 45272 | F26: =E26/$E$87 -> 0.013465398 | H26: 180 | I26: =G26+H26*1 -> 180 | J26: =I26/$N$87 -> 0.0004218175 | K26: такси | M26: 1273.7 | N26: =L26+M26*1 -> 1273.7 | O26: =N26/$N$87 -> 0.0029848275 | P26: матрацы, кастрюли, аккумулятор для раций | R26: 870 | S26: =Q26+R26*1 -> 870 | T26: =S26/$S$87 -> 0.0037555157 | U26: 270 грн - распечатка КМД 600 грн - заправка баллонов пропаном | W26: =3684-R26-M26 -> 1540.3 | X26: =V26+W26*1 -> 1540.3 | Y26: =X26/$X$87 -> 0.0025222022 | Z26: заправка баллонов | AA26: =L26+Q26+V26+G26 -> 0 | AB26: =M26+R26+W26+H26 -> 3864 | AC26: =AA26+AB26*1 -> 3864 | AD26: =AC26/$AC$87 -> 0.0030347726 | AF26: =C26-AA26 -> 45272 | AG26: =D26-AB26 -> -3864 | AH26: =AF26+AG26*1 -> 41408 | AI26: =AH26/$AH$87 -> 0.017176913
B27: Командировочные производственного персонала | C27: 49800 | E27: =C27+D27 -> 49800 | F27: =E27/$E$87 -> 0.014812175 | H27: 300 | I27: =G27+H27*1 -> 300 | J27: =I27/$N$87 -> 0.00070302917 | M27: 10000 | N27: =L27+M27*1 -> 10000 | O27: =N27/$N$87 -> 0.023434306 | P27: Суточные бр Пономаренки - 10 000 грн | R27: 13700 | S27: =Q27+R27*1 -> 13700 | T27: =S27/$S$87 -> 0.05913858 | U27: Бр Пономаренки | W27: =40800-R27-M27-H27 -> 16800 | X27: =V27+W27*1 -> 16800 | Y27: =X27/$X$87 -> 0.027509574 | Z27: Суточные проезды | AA27: =L27+Q27+V27+G27 -> 0 | AB27: =M27+R27+W27+H27 -> 40800 | AC27: =AA27+AB27*1 -> 40800 | AD27: =AC27/$AC$87 -> 0.032044183 | AF27: =C27-AA27 -> 49800 | AG27: =D27-AB27 -> -40800 | AH27: =AF27+AG27*1 -> 9000 | AI27: =AH27/$AH$87 -> 0.0037333901
B28: Аренда квартиры с коммунальными платежами | E28: =C28+D28 -> 0 | F28: =E28/$E$87 -> 0 | I28: =G28+H28*1 -> 0 | J28: =I28/$N$87 -> 0 | M28: =13150 -> 13150 | N28: =L28+M28*1 -> 13150 | O28: =N28/$N$87 -> 0.030816112 | P28: Аренда квартиры бр Пономаренки 13 150 грн январь | R28: 7500 | S28: =Q28+R28*1 -> 7500 | T28: =S28/$S$87 -> 0.032375135 | U28: 7 500 грн - аренда квартиры Пономаренки февраль | W28: =36710-R28-M28 -> 16060 | X28: =V28+W28*1 -> 16060 | Y28: =X28/$X$87 -> 0.026297843 | Z28: долг аренда квартир Пономаренки | AA28: =L28+Q28+V28+G28 -> 0 | AB28: =M28+R28+W28+H28 -> 36710 | AC28: =AA28+AB28*1 -> 36710 | AD28: =AC28/$AC$87 -> 0.02883191 | AF28: =C28-AA28 -> 0 | AG28: =D28-AB28 -> -36710 | AH28: =AF28+AG28*1 -> -36710 | AI28: =AH28/$AH$87 -> -0.015228084
B29: Транспортные затраты производственного персонала | D29: 16000 | E29: =C29+D29 -> 16000 | F29: =E29/$E$87 -> 0.0047589318 | I29: =G29+H29*1 -> 0 | J29: =I29/$N$87 -> 0 | M29: =4800+300 -> 5100 | N29: =L29+M29*1 -> 5100 | O29: =N29/$N$87 -> 0.011951496 | P29: приезд на объект 5 чел по 500 грн - 2 500 грн Проезд на работу - 2 300 грн | R29: 3200 | S29: =Q29+R29*1 -> 3200 | T29: =S29/$S$87 -> 0.013813391 | U29: бр Пономаренки, Перкатого | W29: =16500-R29-M29 -> 8200 | X29: =V29+W29*1 -> 8200 | Y29: =X29/$X$87 -> 0.013427292 | AA29: =L29+Q29+V29+G29 -> 0 | AB29: =M29+R29+W29+H29 -> 16500 | AC29: =AA29+AB29*1 -> 16500 | AD29: =AC29/$AC$87 -> 0.012959044 | AF29: =C29-AA29 -> 0 | AG29: =D29-AB29 -> -500 | AH29: =AF29+AG29*1 -> -500 | AI29: =AH29/$AH$87 -> -0.00020741056
B30: Разрешительная документация | E30: =C30+D30 -> 0 | F30: =E30/$E$87 -> 0 | I30: =G30+H30*1 -> 0 | J30: =I30/$N$87 -> 0 | N30: =L30+M30*1 -> 0 | O30: =N30/$N$87 -> 0 | S30: =Q30+R30*1 -> 0 | T30: =S30/$N$87 -> 0 | X30: =V30+W30*1 -> 0 | Y30: =X30/$X$87 -> 0 | AA30: =L30+Q30+V30 -> 0 | AB30: =M30+R30+W30+H30 -> 0 | AC30: =AA30+AB30*1 -> 0 | AD30: =AC30/$AC$87 -> 0 | AF30: =C30-AA30 -> 0 | AG30: =D30-AB30 -> 0 | AH30: =AF30+AG30*1 -> 0 | AI30: =AH30/$AH$87 -> 0
B31: Представительские затраты | D31: 500000 | E31: =C31+D31 -> 500000 | F31: =E31/$E$87 -> 0.14871662 | I31: =G31+H31*1 -> 0 | J31: =I31/$N$87 -> 0 | N31: =L31+M31*1 -> 0 | O31: =N31/$N$87 -> 0 | S31: =Q31+R31*1 -> 0 | T31: =S31/$N$87 -> 0 | X31: =V31+W31*1 -> 0 | Y31: =X31/$X$87 -> 0 | AA31: =L31+Q31+V31 -> 0 | AB31: =M31+R31+W31+H31 -> 0 | AC31: =AA31+AB31*1 -> 0 | AD31: =AC31/$AC$87 -> 0 | AF31: =C31-AA31 -> 0 | AG31: =D31-AB31 -> 500000 | AH31: =AF31+AG31*1 -> 500000 | AI31: =AH31/$AH$87 -> 0.20741056
J32: =I32/$N$87 -> 0 | O32: =N32/$N$87 -> 0 | T32: =S32/$N$87 -> 0 | Y32: =X32/$X$87 -> 0 | AA32: =L32+Q32+V32 -> 0 | AB32: =M32+R32+W32+H32 -> 0
B33: Дополнительные расходы | C33: =C34 -> 0 | D33: =D34 -> 0 | E33: =E34 -> 0 | F33: =E33/$E$87 -> 0 | G33: =G34 -> 0 | H33: =H34 -> 0 | I33: =I34 -> 0 | J33: =I33/$N$87 -> 0 | L33: =L34 -> 0 | M33: =M34 -> 0 | N33: =N34 -> 0 | O33: =N33/$N$87 -> 0 | Q33: =Q34 -> 0 | R33: =R34 -> 0 | S33: =S34 -> 0 | T33: =S33/$N$87 -> 0 | V33: =V34 -> 0 | W33: =W34 -> 0 | X33: =X34 -> 0 | Y33: =X33/$X$87 -> 0 | AA33: =AA34 -> 0 | AB33: =AB34 -> 0 | AC33: =AC34 -> 0 | AF33: =AF34 -> 0 | AG33: =AG34 -> 0 | AH33: =AH34 -> 0
B34: Расход от ивест. Деятельности (ОС) | E34: =C34+D34 -> 0 | F34: =E34/$E$87 -> 0 | I34: =G34+H34*1 -> 0 | J34: =I34/$N$87 -> 0 | N34: =L34+M34*1 -> 0 | O34: =N34/$N$87 -> 0 | S34: =Q34+R34*1 -> 0 | T34: =S34/$N$87 -> 0 | X34: =V34+W34*1 -> 0 | Y34: =X34/$X$87 -> 0 | AA34: =L34+Q34+V34+G34 -> 0 | AB34: =M34+R34+W34+H34 -> 0 | AC34: =AA34+AB34*1 -> 0 | AD34: =AC34/$AC$87 -> 0 | AF34: =C34-AA34 -> 0 | AG34: =D34-AB34 -> 0 | AH34: =AF34+AG34*1 -> 0 | AI34: =AH34/$E$87 -> 0
J35: =I35/$N$87 -> 0 | O35: =N35/$N$87 -> 0 | T35: =S35/$N$87 -> 0 | Y35: =X35/$X$87 -> 0 | AA35: =L35+Q35+V35+G35 -> 0 | AB35: =M35+R35+W35+H35 -> 0
B36: Маржинальный доход, грн | C36: =(C5)-(C8) -> -975438 | D36: =(D5)-(D8) -> 2725604 | E36: =(E5)-(E8) -> 1750166 | G36: =(G5)-(G8) -> 0 | H36: =(H5)-(H8) -> -480 | I36: =(I5)-(I8) -> -480 | L36: =(L5)-(L8) -> -172736.6 | M36: =(M5)-(M8) -> 1747152.4 | N36: =(N5)-(N8) -> 1574415.8 | Q36: =(Q5)-(Q8) -> -132386.06 | R36: =(R5)-(R8) -> -33025 | S36: =(S5)-(S8) -> -165411.06 | V36: =(V5)-(V8) -> -209487.07 | W36: =(W5)-(W8) -> 2473689.8 | X36: =(X5)-(X8) -> 2264202.7 | Y36: =X36/$X$87 -> 3.7075745 | AA36: =(AA5)-(AA8) -> -514609.72 | AB36: =(AB5)-(AB8) -> 4187337.1 | AC36: =(AC5)-(AC8) -> 3672727.4 | AF36: =(AF5)-(AF8) -> -460828.28 | AG36: =(AG5)-(AG8) -> -1461733.2 | AH36: =(AH5)-(AH8) -> -1922561.4
B37: Маржинальный доход, % | C37: =C36/(C5) -> #DIV/0! | D37: =D36/(D5) -> 0.54850761 | E37: =E36/(E5) -> 0.35220794 | G37: =G36/(G5) -> #DIV/0! | H37: =H36/(H5) -> #DIV/0! | I37: =I36/(I5) -> #DIV/0! | L37: =L36/(L5) -> #DIV/0! | M37: =M36/(M5) -> 0.91419476 | N37: =N36/(N5) -> 0.82381061 | Q37: =Q36/(Q5) -> #DIV/0! | R37: =R36/(R5) -> #DIV/0! | S37: =S36/(S5) -> #DIV/0! | V37: =V36/(V5) -> #DIV/0! | W37: =W36/(W5) -> 0.89286464 | X37: =X36/(X5) -> 0.81725144 | Y37: =X37/$X$87 -> 1.3382285e-06 | AA37: =AA36/(AA5) -> #DIV/0! | AB37: =AB36/(AB5) -> 0.89441534 | AC37: =AC36/(AC5) -> 0.78449468 | AF37: =AF36/(AF5) -> #DIV/0! | AG37: =AG36/(AG5) -> -5.0846484 | AH37: =AH36/(AH5) -> -6.6876427
J38: =I38/$N$87 -> 0 | O38: =N38/$N$87 -> 0 | T38: =S38/$N$87 -> 0 | Y38: =X38/$X$87 -> 0 | AB38: =M38+R38+W38+H38 -> 0
B39: Общепроизводственные затраты | C39: =SUM(C40:C46) -> 0 | D39: =SUM(D40:D46) -> 3000 | E39: =SUM(E40:E46) -> 3000 | F39: =E39/$E$87 -> 0.00089229972 | G39: =SUM(G40:G46) -> 0 | H39: =SUM(H40:H46) -> 0 | I39: =SUM(I40:I46) -> 0 | J39: =I39/$N$87 -> 0 | L39: =SUM(L40:L46) -> 0 | M39: =SUM(M40:M46) -> 0 | N39: =SUM(N40:N46) -> 0 | O39: =N39/$N$87 -> 0 | Q39: =SUM(Q40:Q46) -> 414 | R39: =SUM(R40:R46) -> 0 | S39: =SUM(S40:S46) -> 414 | T39: =S39/$S$87 -> 0.0017871075 | V39: =SUM(V40:V46) -> 0 | W39: =SUM(W40:W46) -> 0 | X39: =SUM(X40:X46) -> 0 | Y39: =X39/$X$87 -> 0 | AA39: =SUM(AA40:AA46) -> 414 | AB39: =SUM(AB40:AB46) -> 0 | AC39: =SUM(AC40:AC46) -> 414 | AD39: =AC39/$AC$87 -> 0.0003251542 | AF39: =SUM(AF40:AF46) -> -414 | AG39: =SUM(AG40:AG46) -> 3000 | AH39: =SUM(AH40:AH46) -> 2586
B40: Благоустройство офиса | E40: =C40+D40 -> 0 | F40: =E40/$E$87 -> 0 | I40: =G40+H40*1 -> 0 | J40: =I40/$N$87 -> 0 | N40: =L40+M40*1 -> 0 | O40: =N40/$N$87 -> 0 | S40: =Q40+R40*1 -> 0 | T40: =S40/$S$87 -> 0 | X40: =V40+W40*1 -> 0 | Y40: =X40/$X$87 -> 0 | AA40: =L40 -> 0 | AB40: =M40+R40+W40+H40 -> 0 | AC40: =AA40+AB40*1 -> 0 | AD40: =AC40/$AC$87 -> 0 | AF40: =C40-AA40 -> 0 | AG40: =D40-AB40 -> 0 | AH40: =AF40+AG40*1 -> 0 | AI40: =AH40/$E$87 -> 0
B41: Хозтовары и материалы | E41: =C41+D41 -> 0 | F41: =E41/$E$87 -> 0 | I41: =G41+H41*1 -> 0 | J41: =I41/$N$87 -> 0 | N41: =L41+M41*1 -> 0 | O41: =N41/$N$87 -> 0 | S41: =Q41+R41*1 -> 0 | T41: =S41/$S$87 -> 0 | X41: =V41+W41*1 -> 0 | Y41: =X41/$X$87 -> 0 | AA41: =L41 -> 0 | AB41: =M41+R41+W41+H41 -> 0 | AC41: =AA41+AB41*1 -> 0 | AD41: =AC41/$AC$87 -> 0 | AF41: =C41-AA41 -> 0 | AG41: =D41-AB41 -> 0 | AH41: =AF41+AG41*1 -> 0 | AI41: =AH41/$E$87 -> 0
B42: ИТ расходы | E42: =C42+D42 -> 0 | F42: =E42/$E$87 -> 0 | I42: =G42+H42*1 -> 0 | J42: =I42/$N$87 -> 0 | N42: =L42+M42*1 -> 0 | O42: =N42/$N$87 -> 0 | S42: =Q42+R42*1 -> 0 | T42: =S42/$S$87 -> 0 | X42: =V42+W42*1 -> 0 | Y42: =X42/$X$87 -> 0 | AA42: =L42 -> 0 | AB42: =M42+R42+W42+H42 -> 0 | AC42: =AA42+AB42*1 -> 0 | AD42: =AC42/$AC$87 -> 0 | AF42: =C42-AA42 -> 0 | AG42: =D42-AB42 -> 0 | AH42: =AF42+AG42*1 -> 0 | AI42: =AH42/$E$87 -> 0
B43: Питьевая вода | D43: 2000 | E43: =C43+D43 -> 2000 | F43: =E43/$E$87 -> 0.00059486648 | I43: =G43+H43*1 -> 0 | J43: =I43/$N$87 -> 0 | N43: =L43+M43*1 -> 0 | O43: =N43/$N$87 -> 0 | S43: =Q43+R43*1 -> 0 | T43: =S43/$S$87 -> 0 | X43: =V43+W43*1 -> 0 | Y43: =X43/$X$87 -> 0 | AA43: =L43 -> 0 | AB43: =M43+R43+W43+H43 -> 0 | AC43: =AA43+AB43*1 -> 0 | AD43: =AC43/$AC$87 -> 0 | AF43: =C43-AA43 -> 0 | AG43: =D43-AB43 -> 2000 | AH43: =AF43+AG43*1 -> 2000 | AI43: =AH43/$E$87 -> 0.00059486648
B44: Охрана офиса и пожарная сигнализация | E44: =C44+D44 -> 0 | F44: =E44/$E$87 -> 0 | I44: =G44+H44*1 -> 0 | J44: =I44/$N$87 -> 0 | N44: =L44+M44*1 -> 0 | O44: =N44/$N$87 -> 0 | S44: =Q44+R44*1 -> 0 | T44: =S44/$S$87 -> 0 | X44: =V44+W44*1 -> 0 | Y44: =X44/$X$87 -> 0 | AA44: =L44 -> 0 | AB44: =M44+R44+W44+H44 -> 0 | AC44: =AA44+AB44*1 -> 0 | AD44: =AC44/$AC$87 -> 0 | AF44: =C44-AA44 -> 0 | AG44: =D44-AB44 -> 0 | AH44: =AF44+AG44*1 -> 0 | AI44: =AH44/$E$87 -> 0
B45: Курьерские и почтовые | D45: 1000 | E45: =C45+D45 -> 1000 | F45: =E45/$E$87 -> 0.00029743324 | I45: =G45+H45*1 -> 0 | J45: =I45/$N$87 -> 0 | N45: =L45+M45*1 -> 0 | O45: =N45/$N$87 -> 0 | S45: =Q45+R45*1 -> 0 | T45: =S45/$S$87 -> 0 | X45: =V45+W45*1 -> 0 | Y45: =X45/$X$87 -> 0 | AA45: =L45+Q45+V45+G45 -> 0 | AB45: =M45+R45+W45+H45 -> 0 | AC45: =AA45+AB45*1 -> 0 | AD45: =AC45/$AC$87 -> 0 | AF45: =C45-AA45 -> 0 | AG45: =D45-AB45 -> 1000 | AH45: =AF45+AG45*1 -> 1000 | AI45: =AH45/$E$87 -> 0.00029743324
B46: Канцтовары | E46: =C46+D46 -> 0 | F46: =E46/$E$87 -> 0 | I46: =G46+H46*1 -> 0 | J46: =I46/$N$87 -> 0 | N46: =L46+M46*1 -> 0 | O46: =N46/$N$87 -> 0 | Q46: 414 | S46: =Q46+R46*1 -> 414 | T46: =S46/$S$87 -> 0.0017871075 | X46: =V46+W46*1 -> 0 | Y46: =X46/$X$87 -> 0 | AA46: =L46+Q46+V46+G46 -> 414 | AB46: =M46+R46+W46+H46 -> 0 | AC46: =AA46+AB46*1 -> 414 | AD46: =AC46/$AC$87 -> 0.0003251542 | AF46: =C46-AA46 -> -414 | AG46: =D46-AB46 -> 0 | AH46: =AF46+AG46*1 -> -414 | AI46: =AH46/$E$87 -> -0.00012313736
J47: =I47/$N$87 -> 0 | O47: =N47/$N$87 -> 0 | T47: =S47/$N$87 -> 0 | Y47: =X47/$X$87 -> 0 | AA47: =L47+Q47+V47+G47 -> 0 | AB47: =M47+R47+W47+H47 -> 0 | AD47: =AC47/$AC$87 -> 0
B48: Маркетинговые затраты | C48: =SUM(C49:C50) -> 0 | D48: =SUM(D49:D50) -> 0 | E48: =SUM(E49:E50) -> 0 | F48: =E48/$E$87 -> 0 | G48: =SUM(G49:G50) -> 0 | H48: =SUM(H49:H50) -> 0 | I48: =SUM(I49:I50) -> 0 | J48: =I48/$N$87 -> 0 | L48: =SUM(L49:L50) -> 0 | M48: =SUM(M49:M50) -> 0 | N48: =SUM(N49:N50) -> 0 | O48: =N48/$N$87 -> 0 | Q48: =SUM(Q49:Q50) -> 0 | R48: =SUM(R49:R50) -> 0 | S48: =SUM(S49:S50) -> 0 | T48: =S48/$N$87 -> 0 | V48: =SUM(V49:V50) -> 0 | W48: =SUM(W49:W50) -> 0 | X48: =SUM(X49:X50) -> 0 | Y48: =X48/$X$87 -> 0 | AA48: =AA50+AA49 -> 0 | AB48: =AB50+AB49 -> 0 | AC48: =SUM(AC49:AC50) -> 0 | AF48: =AF50+AF49 -> 0 | AG48: =AG50+AG49 -> 0 | AH48: =SUM(AH49:AH50) -> 0
B49: Реклама | E49: =C49+D49 -> 0 | F49: =E49/$E$87 -> 0 | I49: =G49+H49*1 -> 0 | J49: =I49/$N$87 -> 0 | N49: =L49+M49*1 -> 0 | O49: =N49/$N$87 -> 0 | S49: =Q49+R49*1 -> 0 | T49: =S49/$N$87 -> 0 | X49: =V49+W49*1 -> 0 | Y49: =X49/$X$87 -> 0 | AA49: =L49 -> 0 | AB49: =M49+R49+W49+H49 -> 0 | AC49: =AA49+AB49*1 -> 0 | AD49: =AC49/$AC$87 -> 0 | AF49: =C49-AA49 -> 0 | AG49: =D49-AB49 -> 0 | AH49: =AF49+AG49*1 -> 0 | AI49: =AH49/$E$87 -> 0
B50: Прочие маркетинговые затраты | E50: =C50+D50 -> 0 | F50: =E50/$E$87 -> 0 | I50: =G50+H50*1 -> 0 | J50: =I50/$N$87 -> 0 | N50: =L50+M50*1 -> 0 | O50: =N50/$N$87 -> 0 | S50: =Q50+R50*1 -> 0 | T50: =S50/$N$87 -> 0 | X50: =V50+W50*1 -> 0 | Y50: =X50/$X$87 -> 0 | AA50: =L50 -> 0 | AB50: =M50 -> 0 | AC50: =AA50+AB50*1 -> 0 | AD50: =AC50/$AC$87 -> 0 | AF50: =C50-AA50 -> 0 | AG50: =D50-AB50 -> 0 | AH50: =AF50+AG50*1 -> 0 | AI50: =AH50/$E$87 -> 0
J51: =I51/$N$87 -> 0 | O51: =N51/$N$87 -> 0 | T51: =S51/$N$87 -> 0 | Y51: =X51/$X$87 -> 0
B52: Административные затраты | C52: =SUM(C53:C69) -> 26643 | D52: =SUM(D53:D69) -> 113495 | E52: =SUM(E53:E69) -> 140138 | F52: =E52/$E$87 -> 0.041681699 | G52: =SUM(G53:G69) -> 910 | H52: =SUM(H53:H69) -> 3035 | I52: =SUM(I53:I69) -> 3945 | J52: =I52/$N$87 -> 0.0092448336 | L52: =SUM(L53:L69) -> 12007.36 | M52: =SUM(M53:M69) -> 48303.8 | N52: =SUM(N53:N69) -> 60311.16 | O52: =N52/$N$87 -> 0.14133502 | Q52: =SUM(Q53:Q69) -> 20856.41 | R52: =SUM(R53:R69) -> 35617.46 | S52: =SUM(S53:S69) -> 56473.87 | T52: =S52/$S$87 -> 0.24377989 | V52: =SUM(V53:V69) -> 10842.32 | W52: =SUM(W53:W69) -> 46703.54 | X52: =SUM(X53:X69) -> 57545.86 | Y52: =X52/$X$87 -> 0.094229887 | AA52: =SUM(AA53:AA69) -> 44616.09 | AB52: =SUM(AB53:AB69) -> 133659.8 | AC52: =SUM(AC53:AC69) -> 178275.89 | AD52: =AC52/$AC$87 -> 0.14001728 | AF52: =SUM(AF53:AF69) -> -17973.09 | AG52: =SUM(AG53:AG69) -> -20164.8 | AH52: =SUM(AH53:AH69) -> -38137.89 | AI52: =AH52/$AH$87 -> -0.015820402
B53: ЗП управленческого персонала | C53: 5555 | D53: 28112 | E53: =C53+D53 -> 33667 | F53: =E53/$E$87 -> 0.010013685 | I53: =G53+H53*1 -> 0 | J53: =I53/$N$87 -> 0 | N53: =L53+M53*1 -> 0 | O53: =N53/$N$87 -> 0 | S53: =Q53+R53*1 -> 0 | T53: =S53/$S$87 -> 0 | X53: =V53+W53*1 -> 0 | Y53: =X53/$X$87 -> 0 | AA53: =L53 -> 0 | AB53: =M53+R53+W53+H53 -> 0 | AC53: =AA53+AB53*1 -> 0 | AD53: =AC53/$AC$87 -> 0 | AF53: =C53-AA53 -> 5555 | AG53: =D53-AB53 -> 28112 | AH53: =AF53+AG53*1 -> 33667 | AI53: =AH53/$AH$87 -> 0.013965783
B54: Начисления на управленчискую зарплату | C54: 1518 | E54: =C54+D54 -> 1518 | F54: =E54/$E$87 -> 0.00045150366 | I54: =G54+H54*1 -> 0 | J54: =I54/$N$87 -> 0 | N54: =L54+M54*1 -> 0 | O54: =N54/$N$87 -> 0 | S54: =Q54+R54*1 -> 0 | T54: =S54/$S$87 -> 0 | X54: =V54+W54*1 -> 0 | Y54: =X54/$X$87 -> 0 | AA54: =L54 -> 0 | AB54: =M54+R54+W54+H54 -> 0 | AC54: =AA54+AB54*1 -> 0 | AD54: =AC54/$AC$87 -> 0 | AF54: =C54-AA54 -> 1518 | AG54: =D54-AB54 -> 0 | AH54: =AF54+AG54*1 -> 1518 | AI54: =AH54/$AH$87 -> 0.00062969847
B55: Удержание с зарплаты управленческого персонала | C55: 1346 | E55: =C55+D55 -> 1346 | F55: =E55/$E$87 -> 0.00040034514 | I55: =G55+H55*1 -> 0 | J55: =I55/$N$87 -> 0 | N55: =L55+M55*1 -> 0 | O55: =N55/$N$87 -> 0 | S55: =Q55+R55*1 -> 0 | T55: =S55/$S$87 -> 0 | X55: =V55+W55*1 -> 0 | Y55: =X55/$X$87 -> 0 | AA55: =L55 -> 0 | AB55: =M55+R55+W55+H55 -> 0 | AC55: =AA55+AB55*1 -> 0 | AD55: =AC55/$AC$87 -> 0 | AF55: =C55-AA55 -> 1346 | AG55: =D55-AB55 -> 0 | AH55: =AF55+AG55*1 -> 1346 | AI55: =AH55/$AH$87 -> 0.00055834924
B56: ЗП РМ | C56: 7406 | D56: 67383 | E56: =C56+D56 -> 74789 | F56: =E56/$E$87 -> 0.022244735 | I56: =G56+H56*1 -> 0 | J56: =I56/$N$87 -> 0 | L56: 4347 | M56: 28288 | N56: =L56+M56*1 -> 32635 | O56: =N56/$N$87 -> 0.076477856 | P56: Стариков С | Q56: 10465 | R56: 22535 | S56: =Q56+R56*1 -> 33000 | T56: =S56/$S$87 -> 0.14245059 | U56: Стариков С февраль | V56: 5232.5 | W56: 11268 | X56: =V56+W56*1 -> 16500.5 | Y56: =X56/$X$87 -> 0.02701915 | Z56: Стариков март | AA56: =L56+Q56+V56+G56 -> 20044.5 | AB56: =M56+R56+W56+H56 -> 62091 | AC56: =AA56+AB56*1 -> 82135.5 | AD56: =AC56/$AC$87 -> 0.064508945 | AF56: =C56-AA56 -> -12638.5 | AG56: =D56-AB56 -> 5292 | AH56: =AF56+AG56*1 -> -7346.5 | AI56: =AH56/$AH$87 -> -0.0030474834
B57: Удержание с зарплаты РМ | C57: 2024 | E57: =C57+D57 -> 2024 | F57: =E57/$E$87 -> 0.00060200488 | I57: =G57+H57*1 -> 0 | J57: =I57/$N$87 -> 0 | L57: 1053 | N57: =L57+M57*1 -> 1053 | O57: =N57/$N$87 -> 0.0024676324 | Q57: 2535 | S57: =Q57+R57*1 -> 2535 | T57: =S57/$S$87 -> 0.010942796 | V57: 1267.5 | X57: =V57+W57*1 -> 1267.5 | Y57: =X57/$X$87 -> 0.0020754991 | AA57: =L57+Q57+V57+G57 -> 4855.5 | AB57: =M57+R57+W57+H57 -> 0 | AC57: =AA57+AB57*1 -> 4855.5 | AD57: =AC57/$AC$87 -> 0.0038134933 | AF57: =C57-AA57 -> -2831.5 | AG57: =D57-AB57 -> 0 | AH57: =AF57+AG57*1 -> -2831.5 | AI57: =AH57/$AH$87 -> -0.001174566
B58: Начисления на зарплату PM | C58: 1794 | E58: =C58+D58 -> 1794 | F58: =E58/$E$87 -> 0.00053359523 | I58: =G58+H58*1 -> 0 | J58: =I58/$N$87 -> 0 | L58: 1188 | N58: =L58+M58*1 -> 1188 | O58: =N58/$N$87 -> 0.0027839955 | Q58: 2860 | S58: =Q58+R58*1 -> 2860 | T58: =S58/$S$87 -> 0.012345718 | V58: 1430 | X58: =V58+W58*1 -> 1430 | Y58: =X58/$X$87 -> 0.0023415887 | AA58: =L58+Q58+V58+G58 -> 5478 | AB58: =M58+R58+W58+H58 -> 0 | AC58: =AA58+AB58*1 -> 5478 | AD58: =AC58/$AC$87 -> 0.0043024027 | AF58: =C58-AA58 -> -3684 | AG58: =D58-AB58 -> 0 | AH58: =AF58+AG58*1 -> -3684 | AI58: =AH58/$AH$87 -> -0.001528201
B59: Премия управленческого персонала | E59: =C59+D59 -> 0 | F59: =E59/$E$87 -> 0 | I59: =G59+H59*1 -> 0 | J59: =I59/$N$87 -> 0 | N59: =L59+M59*1 -> 0 | O59: =N59/$N$87 -> 0 | S59: =Q59+R59*1 -> 0 | T59: =S59/$S$87 -> 0 | X59: =V59+W59*1 -> 0 | Y59: =X59/$X$87 -> 0 | AA59: =L59+Q59+V59+G59 -> 0 | AB59: =M59+R59+W59+H59 -> 0 | AC59: =AA59+AB59*1 -> 0 | AD59: =AC59/$AC$87 -> 0 | AF59: =C59-AA59 -> 0 | AG59: =D59-AB59 -> 0 | AH59: =AF59+AG59*1 -> 0 | AI59: =AH59/$AH$87 -> 0
B60: Телекомуникационные услуги | E60: =C60+D60 -> 0 | F60: =E60/$E$87 -> 0 | I60: =G60+H60*1 -> 0 | J60: =I60/$N$87 -> 0 | N60: =L60+M60*1 -> 0 | O60: =N60/$N$87 -> 0 | S60: =Q60+R60*1 -> 0 | T60: =S60/$S$87 -> 0 | X60: =V60+W60*1 -> 0 | Y60: =X60/$X$87 -> 0 | AA60: =L60+Q60+V60+G60 -> 0 | AB60: =M60+R60+W60+H60 -> 0 | AC60: =AA60+AB60*1 -> 0 | AD60: =AC60/$AC$87 -> 0 | AF60: =C60-AA60 -> 0 | AG60: =D60-AB60 -> 0 | AH60: =AF60+AG60*1 -> 0 | AI60: =AH60/$AH$87 -> 0
B61: Транспортные затраты управленческого персонала | C61: 7000 | E61: =C61+D61 -> 7000 | F61: =E61/$E$87 -> 0.0020820327 | I61: =G61+H61*1 -> 0 | J61: =I61/$N$87 -> 0 | L61: 5419.36 | M61: 412.8 | N61: =L61+M61*1 -> 5832.16 | O61: =N61/$N$87 -> 0.013667262 | P61: Стариков С 20 л бензина, 360 л топливо | Q61: 4996.41 | S61: =Q61+R61*1 -> 4996.41 | T61: =S61/$S$87 -> 0.021567926 | U61: Стариков С | V61: 2912.32 | X61: =V61+W61*1 -> 2912.32 | Y61: =X61/$X$87 -> 0.0047688502 | Z61: Топливо Стариков | AA61: =L61+Q61+V61+G61 -> 13328.09 | AB61: =M61+R61+W61+H61 -> 412.8 | AC61: =AA61+AB61*1 -> 13740.89 | AD61: =AC61/$AC$87 -> 0.010792049 | AF61: =C61-AA61 -> -6328.09 | AG61: =D61-AB61 -> -412.8 | AH61: =AF61+AG61*1 -> -6740.89 | AI61: =AH61/$AH$87 -> -0.0027962636
B62: Аренда офиса с коммунальными платежами | E62: =C62+D62 -> 0 | F62: =E62/$E$87 -> 0 | I62: =G62+H62*1 -> 0 | J62: =I62/$N$87 -> 0 | N62: =L62+M62*1 -> 0 | O62: =N62/$N$87 -> 0 | S62: =Q62+R62*1 -> 0 | T62: =S62/$S$87 -> 0 | X62: =V62+W62*1 -> 0 | Y62: =X62/$X$87 -> 0 | AA62: =L62+Q62+V62+G62 -> 0 | AB62: =M62+R62+W62+H62 -> 0 | AC62: =AA62+AB62*1 -> 0 | AD62: =AC62/$AC$87 -> 0 | AF62: =C62-AA62 -> 0 | AG62: =D62-AB62 -> 0 | AH62: =AF62+AG62*1 -> 0 | AI62: =AH62/$AH$87 -> 0
B63: Затраты на коммандировки управленческого персонала | D63: 18000 | E63: =C63+D63 -> 18000 | F63: =E63/$E$87 -> 0.0053537983 | G63: 910 | H63: =1820+1205 -> 3025 | I63: =G63+H63*1 -> 3935 | J63: =I63/$N$87 -> 0.0092213993 | K63: суточные, проезд | M63: =1983+7500+4000+1250+4680+180 -> 19593 | N63: =L63+M63*1 -> 19593 | O63: =N63/$N$87 -> 0.045914835 | P63: Стариков С - 7 500 грн январь+ 1983 ком.услуги Гостинница 1250 грн Услуги риелтора - 4 000 грн Суточные Стариков С -4 680 грн | R63: =3120+7500+2325 -> 12945 | S63: =Q63+R63*1 -> 12945 | T63: =S63/$S$87 -> 0.055879483 | U63: Стариков С суточные - 3 120 грн аренда квартиры февраль - 7 500 грн + 2325 грн ком.услуги | W63: 8150 | X63: =V63+W63*1 -> 8150 | Y63: =X63/$X$87 -> 0.013345418 | AA63: =L63+Q63+V63+G63 -> 910 | AB63: =M63+R63+W63+H63 -> 43713 | AC63: =AA63+AB63*1 -> 44623 | AD63: =AC63/$AC$87 -> 0.035046754 | AF63: =C63-AA63 -> -910 | AG63: =D63-AB63 -> -25713 | AH63: =AF63+AG63*1 -> -26623 | AI63: =AH63/$AH$87 -> -0.011043783
B64: Юридические услуги | E64: =C64+D64 -> 0 | F64: =E64/$E$87 -> 0 | I64: =G64+H64*1 -> 0 | J64: =I64/$N$87 -> 0 | N64: =L64+M64*1 -> 0 | O64: =N64/$N$87 -> 0 | S64: =Q64+R64*1 -> 0 | T64: =S64/$S$87 -> 0 | X64: =V64+W64*1 -> 0 | Y64: =X64/$X$87 -> 0 | AA64: =L64+Q64+V64+G64 -> 0 | AB64: =M64+R64+W64+H64 -> 0 | AC64: =AA64+AB64*1 -> 0 | AD64: =AC64/$AC$87 -> 0 | AF64: =C64-AA64 -> 0 | AG64: =D64-AB64 -> 0 | AH64: =AF64+AG64*1 -> 0 | AI64: =AH64/$AH$87 -> 0
B65: Услуги | E65: =C65+D65 -> 0 | F65: =E65/$E$87 -> 0 | I65: =G65+H65*1 -> 0 | J65: =I65/$N$87 -> 0 | N65: =L65+M65*1 -> 0 | O65: =N65/$N$87 -> 0 | S65: =Q65+R65*1 -> 0 | T65: =S65/$S$87 -> 0 | X65: =V65+W65*1 -> 0 | Y65: =X65/$X$87 -> 0 | AA65: =L65+Q65+V65+G65 -> 0 | AB65: =M65+R65+W65+H65 -> 0 | AC65: =AA65+AB65*1 -> 0 | AD65: =AC65/$AC$87 -> 0 | AF65: =C65-AA65 -> 0 | AG65: =D65-AB65 -> 0 | AH65: =AF65+AG65*1 -> 0 | AI65: =AH65/$AH$87 -> 0
B66: Услуги банков | E66: =C66+D66 -> 0 | F66: =E66/$E$87 -> 0 | H66: 10 | I66: =G66+H66*1 -> 10 | J66: =I66/$N$87 -> 2.3434306e-05 | M66: 10 | N66: =L66+M66*1 -> 10 | O66: =N66/$N$87 -> 2.3434306e-05 | R66: 137.46 | S66: =Q66+R66*1 -> 137.46 | T66: =S66/$S$87 -> 0.00059337147 | W66: =38.54+27247 -> 27285.54 | X66: =V66+W66*1 -> 27285.54 | Y66: =X66/$X$87 -> 0.04467938 | AA66: =L66+Q66+V66+G66 -> 0 | AB66: =M66+R66+W66+H66 -> 27443 | AC66: =AA66+AB66*1 -> 27443 | AD66: =AC66/$AC$87 -> 0.02155364 | AF66: =C66-AA66 -> 0 | AG66: =D66-AB66 -> -27443 | AH66: =AF66+AG66*1 -> -27443 | AI66: =AH66/$AH$87 -> -0.011383936
B67: Затраты на обучение персонала | E67: =C67+D67 -> 0 | F67: =E67/$E$87 -> 0 | I67: =G67+H67*1 -> 0 | J67: =I67/$N$87 -> 0 | N67: =L67+M67*1 -> 0 | O67: =N67/$N$87 -> 0 | S67: =Q67+R67*1 -> 0 | T67: =S67/$N$87 -> 0 | X67: =V67+W67*1 -> 0 | Y67: =X67/$N$87 -> 0 | AA67: =L67 -> 0 | AB67: =M67+R67+W67+H67 -> 0 | AC67: =AA67+AB67*1 -> 0 | AD67: =AC67/$AC$87 -> 0 | AF67: =C67-AA67 -> 0 | AG67: =D67-AB67 -> 0 | AH67: =AF67+AG67*1 -> 0 | AI67: =AH67/$E$87 -> 0
B68: Затраты по корпоративной культуре | E68: =C68+D68 -> 0 | F68: =E68/$E$87 -> 0 | I68: =G68+H68*1 -> 0 | J68: =I68/$N$87 -> 0 | N68: =L68+M68*1 -> 0 | O68: =N68/$N$87 -> 0 | S68: =Q68+R68*1 -> 0 | T68: =S68/$N$87 -> 0 | X68: =V68+W68*1 -> 0 | Y68: =X68/$N$87 -> 0 | AA68: =L68 -> 0 | AB68: =M68+R68+W68+H68 -> 0 | AC68: =AA68+AB68*1 -> 0 | AD68: =AC68/$AC$87 -> 0 | AF68: =C68-AA68 -> 0 | AG68: =D68-AB68 -> 0 | AH68: =AF68+AG68*1 -> 0 | AI68: =AH68/$E$87 -> 0
B69: Штраф | E69: =C69+D69 -> 0 | F69: =E69/$E$87 -> 0 | I69: =G69+H69*1 -> 0 | J69: =I69/$N$87 -> 0 | N69: =L69+M69*1 -> 0 | O69: =N69/$N$87 -> 0 | S69: =Q69+R69*1 -> 0 | T69: =S69/$N$87 -> 0 | X69: =V69+W69*1 -> 0 | Y69: =X69/$N$87 -> 0 | AA69: =L69 -> 0 | AB69: =M69+R69+W69+H69 -> 0 | AC69: =AA69+AB69*1 -> 0 | AD69: =AC69/$AC$87 -> 0 | AF69: =C69-AA69 -> 0 | AG69: =D69-AB69 -> 0 | AH69: =AF69+AG69*1 -> 0 | AI69: =AH69/$E$87 -> 0
F70: =E70/$E$87 -> 0 | J70: =I70/$N$87 -> 0 | O70: =N70/$N$87 -> 0 | T70: =S70/$N$87 -> 0 | Y70: =X70/$N$87 -> 0 | AA70: =L70 -> 0 | AB70: =M70+R70+W70+H70 -> 0 | AD70: =AC70/$AC$87 -> 0 | AF70: =C70-AA70 -> 0 | AG70: =D70-AB70 -> 0 | AI70: =AH70/$E$87 -> 0
B71: Налоги и сборы | C71: =C72 -> 0 | D71: =D72 -> 0 | E71: =E72 -> 0 | F71: =E71/$E$87 -> 0 | G71: =G72 -> 0 | H71: =H72 -> 0 | I71: =I72 -> 0 | J71: =I71/$N$87 -> 0 | L71: =L72 -> 0 | M71: =M72 -> 0 | N71: =N72 -> 0 | O71: =N71/$N$87 -> 0 | Q71: =Q72 -> 0 | R71: =R72 -> 0 | S71: =S72 -> 0 | T71: =S71/$N$87 -> 0 | V71: =V72 -> 0 | W71: =W72 -> 0 | X71: =X72 -> 0 | Y71: =X71/$N$87 -> 0 | AA71: =AA72 -> 0 | AB71: =AB72 -> 0 | AC71: =AC72 -> 0 | AF71: =C71-AA71 -> 0 | AG71: =D71-AB71 -> 0 | AH71: =AH72 -> 0 | AI71: =AH71/$E$87 -> 0
B72: НДС/ Прочие налоги | E72: =C72+D72 -> 0 | I72: =G72+H72*1 -> 0 | J72: =I72/$N$87 -> 0 | N72: =L72+M72*1 -> 0 | O72: =N72/$N$87 -> 0 | S72: =Q72+R72*1 -> 0 | T72: =S72/$N$87 -> 0 | X72: =V72+W72*1 -> 0 | Y72: =X72/$N$87 -> 0 | AA72: =L72 -> 0 | AB72: =M72+R72+W72+H72 -> 0 | AC72: =AA72+AB72*1 -> 0 | AF72: =C72-AA72 -> 0 | AG72: =D72-AB72 -> 0 | AH72: =AF72+AG72*1 -> 0
B73: Операционная прибыль, грн | C73: =C36-C39-C48-C52 -> -1002081 | D73: =D36-D39-D48-D52 -> 2609109 | E73: =E36-E39-E48-E52 -> 1607028 | G73: =G36-G39-G48-G52 -> -910 | H73: =H36-H39-H48-H52 -> -3515 | I73: =I36-I39-I48-I52 -> -4425 | L73: =L36-L39-L48-L52 -> -184743.96 | M73: =M36-M39-M48-M52 -> 1698848.6 | N73: =N36-N39-N48-N52 -> 1514104.6 | Q73: =Q36-Q39-Q48-Q52 -> -153656.47 | R73: =R36-R39-R48-R52 -> -68642.46 | S73: =S36-S39-S48-S52 -> -222298.93 | V73: =V36-V39-V48-V52 -> -220329.39 | W73: =W36-W39-W48-W52 -> 2426986.2 | X73: =X36-X39-X48-X52 -> 2206656.9 | AA73: =AA36-AA39-AA48-AA52 -> -559639.81 | AB73: =AB36-AB39-AB48-AB52 -> 4053677.3 | AC73: =AC36-AC39-AC48-AC52 -> 3494037.5 | AF73: =AF36-AF39-AF48-AF52 -> -442441.19 | AG73: =AG36-AG39-AG48-AG52 -> -1444568.4 | AH73: =AH36-AH39-AH48-AH52 -> -1887009.5
B74: Операционная прибыль, % | C74: =C73/C5 -> #DIV/0! | D74: =D73/D5 -> 0.52506386 | E74: =E73/E5 -> 0.32340248 | G74: =G73/G5 -> #DIV/0! | H74: =H73/H5 -> #DIV/0! | I74: =I73/I5 -> #DIV/0! | L74: =L73/L5 -> #DIV/0! | M74: =M73/M5 -> 0.88891987 | N74: =N73/N5 -> 0.79225288 | Q74: =Q73/Q5 -> #DIV/0! | R74: =R73/R5 -> #DIV/0! | S74: =S73/S5 -> #DIV/0! | V74: =V73/V5 -> #DIV/0! | W74: =W73/W5 -> 0.87600726 | X74: =X73/X5 -> 0.79648058 | AA74: =AA73/AA5 -> #DIV/0! | AB74: =AB73/AB5 -> 0.8658656 | AC74: =AC73/AC5 -> 0.74632652 | AF74: =AF73/AF5 -> #DIV/0! | AG74: =AG73/AG5 -> -5.0249406 | AH74: =AH73/AH5 -> -6.5639752
B75: Финансовая деятельность | C75: =C76-C77 -> 0 | D75: =D76-D77 -> 0 | E75: =E76-E77 -> 0 | G75: =G76-G77 -> 0 | H75: =H76-H77 -> 0 | I75: =I76-I77 -> -479.31818 | J75: =I75/$N$87 -> -0.0011232489 | L75: =L76-L77 -> 0 | M75: =M76-M77 -> 0 | N75: =N76-N77 -> -29691.42 | O75: =N75/$N$87 -> -0.069579782 | Q75: =Q76-Q77 -> 0 | R75: =R76-R77 -> 0 | S75: =S76-S77 -> -9360.3355 | T75: =S75/$N$87 -> -0.021935296 | V75: =V76-V77 -> 0 | W75: =W76-W77 -> 0 | X75: =X76-X77 -> -46844.051 | Y75: =X75/$N$87 -> -0.10977578 | AA75: =AA76-AA77 -> 0 | AB75: =AB76-AB77 -> 0 | AC75: =AC76-AC77 -> -85632.266 | AF75: =AF76-AF77 -> 0 | AG75: =AG76-AG77 -> 0 | AH75: =AH76-AH77 -> -236188.37
B76: Финансовый доход | E76: =C76+D76*1.15 -> 0 | I76: =G76+H76*1 -> 0 | J76: =I76/$N$87 -> 0 | N76: =L76+M76*1 -> 0 | O76: =N76/$N$87 -> 0 | S76: =Q76+R76*1 -> 0 | T76: =S76/$N$87 -> 0 | X76: =V76+W76*1 -> 0 | Y76: =X76/$N$87 -> 0 | AC76: =AA76+AB76*1 -> 0 | AH76: =AF76+AG76*1 -> 0
B77: Финансовые расходы | E77: =C77+D77*1.15 -> 0 | F77: =E77/$E$87 -> 0 | I77: =(H8+H39+H48+H52)/0.88*0.12 -> 479.31818 | J77: =I77/$N$87 -> 0.0011232489 | N77: =(M8+M39+M48+M52)/(1-'расчет 2020'!E4)*'расчет 2020'!E4 -> 29691.42 | O77: =N77/$N$87 -> 0.069579782 | S77: =(R8+R39+R48+R52)/0.88*0.12 -> 9360.3355 | T77: =S77/$N$87 -> 0.021935296 | X77: =(W8+W39+W48+W52)/0.88*0.12 -> 46844.051 | Y77: =X77/$N$87 -> 0.10977578 | AA77: =L77 -> 0 | AB77: =M77 -> 0 | AC77: =(AB8+AB39+AB48+AB52)/0.88*0.12 -> 85632.266 | AF77: =C77-AA77 -> 0 | AG77: =D77-AB77 -> 0 | AH77: =(AG8+AG39+AG48+AG52)/0.88*0.12 -> 236188.37 | AI77: =AH77/$E$87 -> 0.070250272
J78: =I78/$N$87 -> 0 | O78: =N78/$N$87 -> 0 | T78: =S78/$N$87 -> 0 | Y78: =X78/$N$87 -> 0
B79: Прибыль после вычета финансовых затрат | C79: =(C73+C76)-C77 -> -1002081 | D79: =(D73+D76)-D77 -> 2609109 | E79: =(E73+E76)-E77 -> 1607028 | G79: =(G73+G76)-G77 -> -910 | H79: =(H73+H76)-H77 -> -3515 | I79: =(I73+I76)-I77 -> -4904.3182 | J79: =I79/$N$87 -> -0.011492929 | L79: =(L73+L76)-L77 -> -184743.96 | M79: =(M73+M76)-M77 -> 1698848.6 | N79: =(N73+N76)-N77 -> 1484413.2 | O79: =N79/$N$87 -> 3.4786192 | Q79: =(Q73+Q76)-Q77 -> -153656.47 | R79: =(R73+R76)-R77 -> -68642.46 | S79: =(S73+S76)-S77 -> -231659.27 | T79: =S79/$N$87 -> -0.5428774 | V79: =(V73+V76)-V77 -> -220329.39 | W79: =(W73+W76)-W77 -> 2426986.2 | X79: =(X73+X76)-X77 -> 2159812.8 | Y79: =X79/$N$87 -> 5.0613713 | AA79: =(AA73+AA76)-AA77 -> -559639.81 | AB79: =(AB73+AB76)-AB77 -> 4053677.3 | AC79: =(AC73+AC76)-AC77 -> 3408405.3 | AF79: =(AF73+AF76)-AF77 -> -442441.19 | AG79: =(AG73+AG76)-AG77 -> -1444568.4 | AH79: =(AH73+AH76)-AH77 -> -2123197.9
B80: Затраты на налог на прибыль | E80: =C80+D80 -> 0 | F80: =E80/$E$87 -> 0 | I80: =G80+H80 -> 0 | J80: =I80/$N$87 -> 0 | N80: =L80+M80 -> 0 | O80: =N80/$N$87 -> 0 | S80: =Q80+R80 -> 0 | T80: =S80/$N$87 -> 0 | X80: =V80+W80 -> 0 | Y80: =X80/$N$87 -> 0 | AC80: =AA80+AB80 -> 0 | AH80: =AF80+AG80 -> 0 | AI80: =AH80/$E$87 -> 0
B81: Прибыль до вычета налогов | C81: =(C79+C7)-C34 -> -1002081 | D81: =(D79+D7)-D34 -> 2609109 | E81: =(E79+E7)-E34 -> 1607028 | G81: =(G79+G7)-G34 -> -910 | H81: =(H79+H7)-H34 -> -3515 | I81: =(I79+I7)-I34 -> -4904.3182 | J81: =I81/$N$87 -> -0.011492929 | L81: =(L79+L7)-L34 -> -184743.96 | M81: =(M79+M7)-M34 -> 1698848.6 | N81: =(N79+N7)-N34 -> 1484413.2 | O81: =N81/$N$87 -> 3.4786192 | Q81: =(Q79+Q7)-Q34 -> -153656.47 | R81: =(R79+R7)-R34 -> -68642.46 | S81: =(S79+S7)-S34 -> -231659.27 | T81: =S81/$N$87 -> -0.5428774 | V81: =(V79+V7)-V34 -> -220329.39 | W81: =(W79+W7)-W34 -> 2426986.2 | X81: =(X79+X7)-X34 -> 2159812.8 | Y81: =X81/$N$87 -> 5.0613713 | AA81: =(AA79+AA7)-AA34 -> -559639.81 | AB81: =(AB79+AB7)-AB34 -> 4053677.3 | AC81: =(AC79+AC7)-AC34 -> 3408405.3 | AF81: =(AF79+AF7)-AF34 -> -442441.19 | AG81: =(AG79+AG7)-AG34 -> -1444568.4 | AH81: =(AH79+AH7)-AH34 -> -2123197.9
B82: Чистый доход | C82: =C81-C71-C80 -> -1002081 | D82: =D81-D71-D80 -> 2609109 | E82: =E81-E71-E80 -> 1607028 | G82: =G81-G71-G80 -> -910 | H82: =H81-H71-H80 -> -3515 | I82: =I81-I71-I80 -> -4904.3182 | J82: =I82/$N$87 -> -0.011492929 | L82: =L81-L71-L80 -> -184743.96 | M82: =M81-M71-M80 -> 1698848.6 | N82: =N81-N71-N80 -> 1484413.2 | O82: =N82/$N$87 -> 3.4786192 | Q82: =Q81-Q71-Q80 -> -153656.47 | R82: =R81-R71-R80 -> -68642.46 | S82: =S81-S71-S80 -> -231659.27 | T82: =S82/$N$87 -> -0.5428774 | V82: =V81-V71-V80 -> -220329.39 | W82: =W81-W71-W80 -> 2426986.2 | X82: =X81-X71-X80 -> 2159812.8 | Y82: =X82/$N$87 -> 5.0613713 | AA82: =AA81-AA71-AA80 -> -559639.81 | AB82: =AB81-AB71-AB80 -> 4053677.3 | AC82: =AC81-AC71-AC80 -> 3408405.3 | AF82: =AF81-AF71-AF80 -> -442441.19 | AG82: =AG81-AG71-AG80 -> -1444568.4 | AH82: =AH81-AH71-AH80 -> -2123197.9
B83: Дивиденды | E83: =C83+D83 -> 0 | F83: =E83/$E$87 -> 0 | I83: =G83+H83 -> 0 | J83: =I83/$N$87 -> 0 | N83: =L83+M83 -> 0 | O83: =N83/$N$87 -> 0 | S83: =Q83+R83 -> 0 | T83: =S83/$N$87 -> 0 | X83: =V83+W83 -> 0 | Y83: =X83/$N$87 -> 0 | AA83: =L83 -> 0 | AB83: =M83 -> 0 | AC83: =AA83+AB83*1.15 -> 0 | AF83: =C83-AA83 -> 0 | AG83: =D83-AB83 -> 0 | AH83: =AF83+AG83*1.15 -> 0 | AI83: =AH83/$E$87 -> 0
B84: Прибыль в распоряжении компании (нераспределенная прибыль), грн | C84: =C82-C83 -> -1002081 | D84: =D82-D83 -> 2609109 | E84: =E82-E83 -> 1607028 | G84: =G82-G83 -> -910 | H84: =H82-H83 -> -3515 | I84: =I82-I83 -> -4904.3182 | L84: =L82-L83 -> -184743.96 | M84: =M82-M83 -> 1698848.6 | N84: =N82-N83 -> 1484413.2 | Q84: =Q82-Q83 -> -153656.47 | R84: =R82-R83 -> -68642.46 | S84: =S82-S83 -> -231659.27 | V84: =V82-V83 -> -220329.39 | W84: =W82-W83 -> 2426986.2 | X84: =X82-X83 -> 2159812.8 | AA84: =AA82-AA83 -> -559639.81 | AB84: =AB82-AB83 -> 4053677.3 | AC84: =AC82-AC83 -> 3408405.3 | AF84: =AF82-AF83 -> -442441.19 | AG84: =AG82-AG83 -> -1444568.4 | AH84: =AH82-AH83 -> -2123197.9
B85: Рентабельность продукции, % | C85: =C84/C5 -> #DIV/0! | D85: =D84/D5 -> 0.52506386 | E85: =E84/E5 -> 0.32340248 | G85: =G84/G5 -> #DIV/0! | H85: =H84/H5 -> #DIV/0! | I85: =I84/I5 -> #DIV/0! | L85: =L84/L5 -> #DIV/0! | M85: =M84/M5 -> 0.88891987 | N85: =N84/N5 -> 0.7767169 | Q85: =Q84/Q5 -> #DIV/0! | R85: =R84/R5 -> #DIV/0! | S85: =S84/S5 -> #DIV/0! | V85: =V84/V5 -> #DIV/0! | W85: =W84/W5 -> 0.87600726 | X85: =X84/X5 -> 0.77957248 | AA85: =AA84/AA5 -> #DIV/0! | AB85: =AB84/AB5 -> 0.8658656 | AC85: =AC84/AC5 -> 0.72803546 | AF85: =AF84/AF5 -> #DIV/0! | AG85: =AG84/AG5 -> -5.0249406 | AH85: =AH84/AH5 -> -7.385558
B87: Итого затрат | E87: =E8+E34+E39+E48+E52+E71+E77+E80+E83 -> 3362099 | I87: =I8+I34+I39+I48+I52+I71+I77+I80+I83 -> 4904.3182 | N87: =N8+N34+N39+N48+N52+N71+N77+N80+N83 -> 426724.83 | S87: =S8+S34+S39+S48+S52+S71+S77+S80+S83 -> 231659.27 | X87: =X8+X34+X39+X48+X52+X71+X77+X80+X83 -> 610696.48 | AC87: =AC8+AC34+AC39+AC48+AC52+AC71+AC77+AC80+AC83 -> 1273242 | AH87: =AH8+AH34+AH39+AH48+AH52+AH71+AH77+AH80+AH83 -> 2410677.6

Sheet Лист1
A8: Заказчик | B8: Название заказа | C8: Ссылка | D8: Количество
A9: Номенклатура | B9: Примечание номенклатура
A10: Староконстантинов | B10: Галерея Староконстантинов- 3 | C10: Отгрузка продукции 000000039 от 02.11.2020 17:10:01 | D10: 9.08
A11: Галерея Староконстантинов - 3 | D11: 9.08
A12: Староконстантинов | B12: Галерея Староконстантинов- 4 | C12: Отгрузка продукции 000000040 от 05.11.2020 10:23:54 | D12: 7.535
A13: Галерея Староконстантинов - 4 | D13: 7.535
A14: Староконстантинов | B14: Галерея Староконстантинов- 5 | C14: Отгрузка продукции 000000042 от 10.11.2020 16:45:28 | D14: 0.716
A15: Галерея Староконстантинов - 5 | D15: 0.716
A16: Староконстантинов | B16: ЖД "Староконстантинов" - 10 | C16: Отгрузка продукции 000000046 от 24.11.2020 13:44:28 | D16: 19.255
A17: м/к Жд Староконстантинов - 10 | D17: 19.255
A18: Староконстантинов | B18: ЖД "Староконстантинов" - 11 | C18: Отгрузка продукции 000000048 от 28.11.2020 11:17:08 | D18: 20
A19: м/к Жд Староконстантинов - 11 | D19: 20
A20: Староконстантинов | B20: ЖД "Староконстантинов" - 12 | C20: Отгрузка продукции 000000049 от 01.12.2020 18:00:00 | D20: 20.705
A21: м/к Жд Староконстантинов - 12 | D21: 20.705
A22: Староконстантинов | B22: ЖД "Староконстантинов" - 13 | C22: Отгрузка продукции 000000050 от 07.12.2020 17:00:00 | D22: 18
A23: м/к Жд Староконстантинов - 13 | D23: 18
A24: Староконстантинов | B24: ЖД "Староконстантинов" - 14 | C24: Отгрузка продукции 000000051 от 09.12.2020 14:34:11 | D24: 15.72
A25: м/к Жд Староконстантинов - 14 | D25: 15.72
A26: Староконстантинов | B26: ЖД "Староконстантинов" - 15 | C26: Отгрузка продукции 000000052 от 11.12.2020 12:00:00 | D26: 18.7
A27: м/к Жд Староконстантинов - 15 | D27: 18.7
A28: Староконстантинов | B28: ЖД "Староконстантинов" - 16 | C28: Отгрузка продукции 000000053 от 17.12.2020 9:13:18 | D28: 14.62
A29: м/к Жд Староконстантинов - 16 | D29: 14.62
A30: Староконстантинов | B30: ЖД "Староконстантинов" - 17 | C30: Отгрузка продукции 000000054 от 21.12.2020 13:47:28 | D30: 21.975
A31: м/к Жд Староконстантинов - 17 | D31: 21.975
A32: Староконстантинов | B32: ЖД "Староконстантинов" - 18 | C32: Отгрузка продукции 000000055 от 25.12.2020 12:20:00 | D32: 18
A33: м/к Жд Староконстантинов - 18 | D33: 18
A34: Староконстантинов | B34: ЖД "Староконстантинов" - 6 | C34: Отгрузка продукции 000000037 от 05.11.2020 9:48:50 | D34: 7.35
A35: м/к Жд Староконстантинов - 6 | D35: 7.35
A36: Староконстантинов | B36: ЖД "Староконстантинов" - 7 | C36: Отгрузка продукции 000000041 от 10.11.2020 16:44:43 | D36: 15.79
A37: м/к Жд Староконстантинов - 7 | D37: 15.79
A38: Староконстантинов | B38: ЖД "Староконстантинов" - 8 | C38: Отгрузка продукции 000000043 от 14.11.2020 12:20:36 | D38: 18.06
A39: м/к Жд Староконстантинов - 8 | D39: 18.06
A40: Староконстантинов | B40: ЖД "Староконстантинов" - 9 | C40: Отгрузка продукции 000000045 от 18.11.2020 13:56:54 | D40: 15.92
A41: м/к Жд Староконстантинов - 9 | D41: 15.92
A42: Староконстантинов | B42: Инструменталка | C42: Отгрузка продукции 000000044 от 14.11.2020 12:21:53 | D42: 0.7
A43: Инструменталка 2000*2500мм | D43: 0.7
A44: Харьков | B44: Бытовка | C44: Отгрузка продукции 000000047 от 25.11.2020 12:00:00 | D44: 2
A45: Бытовка | D45: 2
A46: Итого | D46: 244.126

Sheet Цех ЗП
B3: Цех: | P3: галер | Q3: ЖД
B4: 1 | C4: 2 | D4: 3 | E4: 4 | F4: 5 | G4: 6 | H4: 7 | I4: 8 | J4: 9 | K4: 10 | L4: 11 | M4: 12 | P4: 10 | Q4: 10
B5: 3477 | C5: 3856 | D5: 3422 | E5: 3514 | F5: 3165 | G5: 2282 | H5: 5053 | I5: 4720 | J5: 4882 | K5: 5679 | P5: 1329 | Q5: 4307
A6: Скрипник Сергій | B6: 230 | C6: 283 | D6: 309 | E6: 256 | F6: 246 | G6: 165 | H6: 320 | I6: 235 | J6: 301 | K6: 301 | P6: 85 | Q6: 216
A7: Пономаренко Олександр | B7: 230 | C7: 288 | D7: 186 | E7: 281 | F7: 198 | G7: 165 | H7: 316 | I7: 277 | J7: 235 | K7: 312 | P7: 72 | Q7: 240
A8: Бутов Олександр | B8: 231 | C8: 279 | D8: 220 | E8: 281 | F8: 198 | G8: 165 | H8: 260 | I8: 286 | J8: 297 | K8: 295 | P8: 55 | Q8: 240
A9: остальные | B9: =B5-B6-B7-B8 -> 2786 | C9: =C5-C6-C7-C8 -> 3006 | D9: =D5-D6-D7-D8 -> 2707 | E9: =E5-E6-E7-E8 -> 2696 | F9: =F5-F6-F7-F8 -> 2523 | G9: =G5-G6-G7-G8 -> 1787 | H9: =H5-H6-H7-H8 -> 4157 | I9: =I5-I6-I7-I8 -> 3922 | ... M9: =M5-M6-M7-M8 -> 0 | P9: =P5-P6-P7-P8 -> 1117 | Q9: =Q5-Q6-Q7-Q8 -> 3611
A12: Скрипник Сергій | B12: =B6*100 -> 23000 | C12: =C6*100 -> 28300 | D12: =D6*100 -> 30900 | E12: =E6*100 -> 25600 | F12: =F6*100 -> 24600 | G12: =G6*100 -> 16500 | H12: =H6*100 -> 32000 | I12: =I6*100 -> 23500 | ... M12: =M6*100 -> 0 | P12: =P6*100 -> 8500 | Q12: =Q6*100 -> 21600
A13: Пономаренко Олександр | B13: =B7*110 -> 25300 | C13: =C7*110 -> 31680 | D13: =D7*110 -> 20460 | E13: =E7*110 -> 30910 | F13: =F7*110 -> 21780 | G13: =G7*110 -> 18150 | H13: =H7*110 -> 34760 | I13: =I7*110 -> 30470 | ... M13: =M7*110 -> 0 | P13: =P7*110 -> 7920 | Q13: =Q7*110 -> 26400
A14: Бутов Олександр | B14: =B8*95 -> 21945 | C14: =C8*95 -> 26505 | D14: =D8*95 -> 20900 | E14: =E8*95 -> 26695 | F14: =F8*95 -> 18810 | G14: =G8*95 -> 15675 | H14: =H8*95 -> 24700 | I14: =I8*95 -> 27170 | ... M14: =M8*95 -> 0 | P14: =P8*95 -> 5225 | Q14: =Q8*95 -> 22800
A15: остальные | B15: =B9*90 -> 250740 | C15: =C9*90 -> 270540 | D15: =D9*90 -> 243630 | E15: =E9*90 -> 242640 | F15: =F9*90 -> 227070 | G15: =G9*90 -> 160830 | H15: =H9*90 -> 374130 | I15: =I9*90 -> 352980 | ... M15: =M9*90 -> 0 | P15: =P9*90 -> 100530 | Q15: =Q9*90 -> 324990
B16: =SUM(B12:B15) -> 320985 | C16: =SUM(C12:C15) -> 357025 | D16: =SUM(D12:D15) -> 315890 | E16: =SUM(E12:E15) -> 325845 | F16: =SUM(F12:F15) -> 292260 | G16: =SUM(G12:G15) -> 211155 | H16: =SUM(H12:H15) -> 465590 | I16: =SUM(I12:I15) -> 434120 | ... M16: =SUM(M12:M15) -> 0 | N16: =SUM(B16:M16) -> 3693280 | P16: =SUM(P12:P15) -> 122175 | Q16: =SUM(Q12:Q15) -> 395790
N17: 365830 | O17: Козин
N18: 371026.37 | O18: ЗП + Козин
N19: =N16+N17-N18 -> 3688083.6 | O19: на 30.10.2020

Sheet PL_Пуща-Водица
A2: PL Пуща -Водица | G2: 2019 | L2: Январь 2020 | Q2: Февраль 2020 | V2: Март 2020 | AA2: Накопительный PL | AF2: Остаток PL январь 2020
A3: План итого
B4: Статья | C4: Сумма по Ф1, грн | D4: Сумма по Ф2, грн | E4: Сумма итого, грн | F4: % суммы затрат в общем объеме | G4: Сумма по Ф1, грн | H4: Сумма по Ф2, грн | I4: Сумма итого, грн | J4: % суммы затрат в общем объеме | K4: Комментарий | L4: Сумма по Ф1, грн | M4: Сумма по Ф2, грн | N4: Сумма итого, грн | O4: % суммы затрат в общем объеме | P4: Комментарий | Q4: Сумма по Ф1, грн | R4: Сумма по Ф2, грн | S4: Сумма итого, грн | T4: % суммы затрат в общем объеме | U4: Комментарий | V4: Сумма по Ф1, грн | W4: Сумма по Ф2, грн | X4: Сумма итого, грн | Y4: % суммы затрат в общем объеме | Z4: Комментарий | AA4: Сумма по Ф1, грн | AB4: Сумма по Ф2, грн | AC4: Сумма итого, грн | AD4: % суммы затрат в общем объеме | AE4: Комментарии | AF4: Сумма по Ф1, грн | AG4: Сумма по Ф2, грн | AH4: Сумма итого, грн | AI4: % суммы затрат в общем объеме | AJ4: Комментарии
B5: Операционный доход | C5: =C6 -> 3046281.3 | D5: =D6 -> 0 | E5: =E6 -> 3046281.3 | G5: =G6 -> 841617.06 | H5: =H6 -> 1210000 | I5: =I6 -> 2051617.1 | L5: =L6 -> 0 | M5: =M6 -> 0 | N5: =N6 -> 0 | Q5: =Q6 -> 1003963.3 | R5: =R6 -> 0 | S5: =S6 -> 1003963.3 | V5: =V6 -> 1811159.8 | W5: =W6 -> 0 | X5: =X6 -> 1811159.8 | AA5: =AA6 -> 3656740.1 | AB5: =AB6 -> 1210000 | AC5: =AC6 -> 4866740.1 | AF5: =AF6 -> -610458.81 | AG5: =AG6 -> -1210000 | AH5: =AH6 -> -1820458.8
B6: Выручка от продаж (товаров, работ, услуг) | C6: 3046281.3 | D6: 0 | E6: =C6+D6 -> 3046281.3 | G6: =2051617.06-H6 -> 841617.06 | H6: =1100000*1.1 -> 1210000 | I6: =G6+H6 -> 2051617.1 | N6: =L6+M6 -> 0 | P6: нет актов | Q6: =82210.91+504052.98+417699.4 -> 1003963.3 | S6: =Q6+R6 -> 1003963.3 | U6: Акт 6, 7,8 | V6: =404231.91+180701.72+1027339.15+132890.92+65996.06 -> 1811159.8 | X6: =V6+W6 -> 1811159.8 | Z6: Акты 9-13 | AA6: =G6+L6+Q6+V6 -> 3656740.1 | AB6: =H6+M6+R6+W6 -> 1210000 | AC6: =AA6+AB6 -> 4866740.1 | AF6: =C6-AA6 -> -610458.81 | AG6: =D6-AB6 -> -1210000 | AH6: =AF6+AG6 -> -1820458.8
B7: Доход от прочей операционной деятельности | E7: =C7+D7 -> 0 | I7: =G7+H7 -> 0 | N7: =L7+M7 -> 0 | S7: =Q7+R7 -> 0 | X7: =V7+W7 -> 0 | AC7: =AA7+AB7 -> 0 | AF7: =C7-AA7 -> 0 | AG7: =D7-AB7 -> 0 | AH7: =AF7+AG7 -> 0
B8: Себестоимость проданой продукции (переменные производственные затраты) | C8: =SUM(C9:C31) -> 1355548.2 | D8: =SUM(D9:D31) -> 916057.78 | E8: =SUM(E9:E31) -> 2271606 | F8: =E8/$E$87 -> 0.95730686 | G8: =SUM(G9:G31) -> 1187368.6 | H8: =SUM(H9:H31) -> 504589.58 | I8: =SUM(I9:I31) -> 1691958.2 | J8: =I8/$N$87 -> 8.2470017 | L8: =SUM(L9:L31) -> 107233.3 | M8: =SUM(M9:M31) -> 56982 | N8: =SUM(N9:N31) -> 164215.3 | O8: =N8/$N$87 -> 0.80042396 | Q8: =SUM(Q9:Q31) -> 467869.98 | R8: =SUM(R9:R31) -> 241020 | S8: =SUM(S9:S31) -> 708889.98 | T8: =S8/$S$87 -> 0.95499388 | V8: =SUM(V9:V31) -> 672023.03 | W8: =SUM(W9:W31) -> 239229.22 | X8: =SUM(X9:X31) -> 911252.25 | Y8: =X8/$X$87 -> 0.9313156 | AA8: =SUM(AA9:AA31) -> 2434494.9 | AB8: =SUM(AB9:AB31) -> 1041820.8 | AC8: =SUM(AC9:AC31) -> 3632588.8 | AD8: =AC8/$AC$87 -> 0.95053083 | AF8: =SUM(AF9:AF31) -> -1078946.7 | AG8: =SUM(AG9:AG31) -> -125763.02 | AH8: =SUM(AH9:AH31) -> -1223574.2 | AI8: =AH8/$AH$87 -> 0.93996399
B9: ЗП производственного персонала | C9: 68327 | D9: 0 | E9: =C9+D9 -> 68327 | F9: =E9/$E$87 -> 0.028794565 | G9: 64805 | H9: 0 | I9: =G9+H9 -> 64805 | J9: =I9/$N$87 -> 0.3158748 | L9: 47495 | N9: =L9+M9 -> 47495 | O9: =N9/$N$87 -> 0.23150179 | P9: 3 чел бр Перкатого 9 чел бр Жук | Q9: =(6842.5*9)+3079.12+(4392.5*2) -> 73446.62 | S9: =Q9+R9 -> 73446.62 | T9: =S9/$S$87 -> 0.098944934 | U9: 9 чел бр Жук 3 чел бр Перкатого | V9: 3550.51 | X9: =V9+W9 -> 3550.51 | Y9: =X9/$X$87 -> 0.0036286828 | Z9: Зп Перкатого | AA9: =G9+L9+Q9+V9 -> 189297.13 | AB9: =H9+M9+R9+W9 -> 0 | AC9: =AA9+AB9*1.15 -> 189297.13 | AD9: =AC9/$AC$87 -> 0.049532927 | AF9: =C9-AA9 -> -120970.13 | AG9: =D9-AB9 -> 0 | AH9: =AF9+AG9*1.15 -> -120970.13 | AI9: =AH9/$AH$87 -> 0.09293067
B10: Удержание с зарплаты производственного персонала | C10: 13377 | E10: =C10+D10 -> 13377 | F10: =E10/$E$87 -> 0.0056373745 | G10: 15700 | H10: 0 | I10: =G10+H10 -> 15700 | J10: =I10/$N$87 -> 0.076525489 | L10: 11505 | N10: =L10+M10 -> 11505 | O10: =N10/$N$87 -> 0.056078073 | Q10: =(1657.5*11)+745.88 -> 18978.38 | S10: =Q10+R10 -> 18978.38 | T10: =S10/$S$87 -> 0.025567066 | V10: 1657.5 | X10: =V10+W10 -> 1657.5 | Y10: =X10/$X$87 -> 0.0016939937 | AA10: =G10+L10+Q10+V10 -> 47840.88 | AB10: =H10+M10+R10+W10 -> 0 | AC10: =AA10+AB10*1.15 -> 47840.88 | AD10: =AC10/$AC$87 -> 0.012518409 | AF10: =C10-AA10 -> -34463.88 | AG10: =D10-AB10 -> 0 | AH10: =AF10+AG10*1.15 -> -34463.88 | AI10: =AH10/$AH$87 -> 0.026475556
B11: Начисления на зарплату производственного персонала | C11: 15092 | D11: 0 | E11: =C11+D11 -> 15092 | F11: =E11/$E$87 -> 0.0063601149 | G11: 17710 | H11: 0 | I11: =G11+H11 -> 17710 | J11: =I11/$N$87 -> 0.086322701 | L11: 12980 | N11: =L11+M11 -> 12980 | O11: =N11/$N$87 -> 0.06326757 | Q11: =(1870*11)+841.5 -> 21411.5 | S11: =Q11+R11 -> 21411.5 | T11: =S11/$S$87 -> 0.028844887 | V11: 1870 | X11: =V11+W11 -> 1870 | Y11: =X11/$X$87 -> 0.0019111724 | AA11: =G11+L11+Q11+V11 -> 53971.5 | AB11: =H11+M11+R11+W11 -> 0 | AC11: =AA11+AB11*1.15 -> 53971.5 | AD11: =AC11/$AC$87 -> 0.014122593 | AF11: =C11-AA11 -> -38879.5 | AG11: =D11-AB11 -> 0 | AH11: =AF11+AG11*1.15 -> -38879.5 | AI11: =AH11/$AH$87 -> 0.029867687
B12: Зарплата ИТР | C12: 9901.5 | D12: 61973.5 | E12: =C12+D12 -> 71875 | F12: =E12/$E$87 -> 0.030289773 | G12: 3703 | H12: 39044.5 | I12: =G12+H12 -> 42747.5 | J12: =I12/$N$87 -> 0.20836136 | L12: 4266.5 | M12: 20734 | N12: =L12+M12 -> 25000.5 | O12: =N12/$N$87 -> 0.12185831 | P12: Ширшов | Q12: 9660 | R12: 15340 | S12: =Q12+R12 -> 25000 | T12: =S12/$S$87 -> 0.033679199 | U12: Ширшов февраль | V12: 7532.44 | W12: 17463.04 | X12: =V12+W12 -> 24995.48 | Y12: =X12/$X$87 -> 0.025545814 | Z12: Зп Ширшова апрель | AA12: =G12+L12+Q12+V12 -> 25161.94 | AB12: =H12+M12+R12+W12 -> 92581.54 | AC12: =AA12+AB12*1.15 -> 131630.71 | AD12: =AC12/$AC$87 -> 0.034443493 | AF12: =C12-AA12 -> -15260.44 | AG12: =D12-AB12 -> -30608.04 | AH12: =AF12+AG12*1.15 -> -50459.686 | AI12: =AH12/$AH$87 -> 0.038763722
B13: Удержание с зарплаты ИТР | C13: 2706 | D13: 0 | E13: =C13+D13 -> 2706 | F13: =E13/$E$87 -> 0.0011403704 | G13: 897 | H13: 0 | I13: =G13+H13 -> 897 | J13: =I13/$N$87 -> 0.0043721888 | L13: 1033.5 | N13: =L13+M13 -> 1033.5 | O13: =N13/$N$87 -> 0.0050375218 | Q13: 1883.7 | S13: =Q13+R13 -> 1883.7 | T13: =S13/$S$87 -> 0.0025376603 | V13: 1824.6287 | X13: =V13+W13 -> 1824.6287 | Y13: =X13/$X$87 -> 0.0018648021 | AA13: =G13+L13+Q13+V13 -> 5638.8286 | AB13: =H13+M13+R13+W13 -> 0 | AC13: =AA13+AB13*1.15 -> 5638.8286 | AD13: =AC13/$AC$87 -> 0.0014754988 | AF13: =C13-AA13 -> -2932.8286 | AG13: =D13-AB13 -> 0 | AH13: =AF13+AG13*1.15 -> -2932.8286 | AI13: =AH13/$AH$87 -> 0.0022530333
B14: Начисления на зарплату ИТР | C14: 2398.5 | D14: 0 | E14: =C14+D14 -> 2398.5 | F14: =E14/$E$87 -> 0.0010107829 | G14: 1012 | H14: 0 | I14: =G14+H14 -> 1012 | J14: =I14/$N$87 -> 0.0049327258 | L14: 1166 | N14: =L14+M14 -> 1166 | O14: =N14/$N$87 -> 0.005683358 | Q14: 2640 | S14: =Q14+R14 -> 2640 | T14: =S14/$S$87 -> 0.0035565234 | V14: 2058.5554 | X14: =V14+W14 -> 2058.5554 | Y14: =X14/$X$87 -> 0.0021038793 | AA14: =G14+L14+Q14+V14 -> 6876.5554 | AB14: =H14+M14+R14+W14 -> 0 | AC14: =AA14+AB14*1.15 -> 6876.5554 | AD14: =AC14/$AC$87 -> 0.0017993718 | AF14: =C14-AA14 -> -4478.0554 | AG14: =D14-AB14 -> 0 | AH14: =AF14+AG14*1.15 -> -4478.0554 | AI14: =AH14/$AH$87 -> 0.0034400946
B15: ЗП подсобников | E15: =C15+D15 -> 0 | F15: =E15/$E$87 -> 0 | G15: 0 | H15: 0 | I15: =G15+H15 -> 0 | J15: =I15/$E$87 -> 0 | N15: =L15+M15 -> 0 | O15: =N15/$E$87 -> 0 | S15: =Q15+R15 -> 0 | T15: =S15/$S$87 -> 0 | X15: =V15+W15 -> 0 | Y15: =X15/$X$87 -> 0 | AA15: =G15+L15+Q15+V15 -> 0 | AB15: =H15+M15+R15+W15 -> 0 | AC15: =AA15+AB15*1.15 -> 0 | AD15: =AC15/$AC$87 -> 0 | AF15: =C15-AA15 -> 0 | AG15: =D15-AB15 -> 0 | AH15: =AF15+AG15*1.15 -> 0 | AI15: =AH15/$AH$87 -> 0
B16: Оплата за выполненные работы | D16: 634634.64 | E16: =C16+D16 -> 634634.64 | F16: =E16/$E$87 -> 0.26744959 | G16: 0 | H16: 360320 | I16: =G16+H16 -> 360320 | J16: =I16/$E$87 -> 0.15184711 | N16: =L16+M16 -> 0 | O16: =N16/$E$87 -> 0 | R16: =145166+47817 -> 192983 | S16: =Q16+R16 -> 192983 | T16: =S16/$S$87 -> 0.25998052 | U16: Бр Жук - 145 166 грн бр Перкатый - 47 817 грн | W16: 174796 | X16: =V16+W16 -> 174796 | Y16: =X16/$X$87 -> 0.17864454 | Z16: Зп бр.Перкатого= 134 472грн. зп бр.Жука= 35 324 грн. | AA16: =G16+L16+Q16+V16 -> 0 | AB16: =H16+M16+R16+W16 -> 728099 | AC16: =AA16+AB16*1.15 -> 837313.85 | AD16: =AC16/$AC$87 -> 0.21909791 | AF16: =C16-AA16 -> 0 | AG16: =D16-AB16 -> -93464.357 | AH16: =AF16+AG16*1.15 -> -107484.01 | AI16: =AH16/$AH$87 -> 0.082570476
B17: Премия производственного персонала | E17: =C17+D17 -> 0 | F17: =E17/$E$87 -> 0 | G17: 0 | H17: 0 | I17: =G17+H17 -> 0 | J17: =I17/$E$87 -> 0 | N17: =L17+M17 -> 0 | O17: =N17/$E$87 -> 0 | S17: =Q17+R17 -> 0 | T17: =S17/$S$87 -> 0 | W17: 12500 | X17: =V17+W17 -> 12500 | Y17: =X17/$X$87 -> 0.012775217 | Z17: бонусы Ширшов | AA17: =G17+L17+Q17+V17 -> 0 | AB17: =H17+M17+R17+W17 -> 12500 | AC17: =AA17+AB17*1.15 -> 14375 | AD17: =AC17/$AC$87 -> 0.0037614719 | AF17: =C17-AA17 -> 0 | AG17: =D17-AB17 -> -12500 | AH17: =AF17+AG17*1.15 -> -14375 | AI17: =AH17/$AH$87 -> 0.011043043
B18: Услуги сторонних организаций | E18: =C18+D18 -> 0 | F18: =E18/$E$87 -> 0 | G18: 0 | H18: 300 | I18: =G18+H18 -> 300 | J18: =I18/$E$87 -> 0.00012642688 | N18: =L18+M18 -> 0 | O18: =N18/$E$87 -> 0 | S18: =Q18+R18 -> 0 | T18: =S18/$S$87 -> 0 | X18: =V18+W18 -> 0 | Y18: =X18/$X$87 -> 0 | AA18: =G18+L18+Q18+V18 -> 0 | AB18: =H18+M18+R18+W18 -> 300 | AC18: =AA18+AB18*1.15 -> 345 | AD18: =AC18/$AC$87 -> 9.0275325e-05 | AF18: =C18-AA18 -> 0 | AG18: =D18-AB18 -> -300 | AH18: =AF18+AG18*1.15 -> -345 | AI18: =AH18/$AH$87 -> 0.00026503304
B19: Аренда строительного оборудования | C19: 2000 | D19: 0 | E19: =C19+D19 -> 2000 | F19: =E19/$E$87 -> 0.00084284586 | G19: =2640+850 -> 3490 | H19: 0 | I19: =G19+H19 -> 3490 | J19: =I19/$E$87 -> 0.001470766 | N19: =L19+M19 -> 0 | O19: =N19/$E$87 -> 0 | Q19: =1080*1.2 -> 1296 | S19: =Q19+R19 -> 1296 | T19: =S19/$S$87 -> 0.0017459297 | U19: Будпрокат - обогреватель - закрыто актами | V19: =150*1.2 -> 180 | X19: =V19+W19 -> 180 | Y19: =X19/$X$87 -> 0.00018396312 | Z19: Будпрокат , аренда вибратора | AA19: =G19+L19+Q19+V19 -> 4966 | AB19: =H19+M19+R19+W19 -> 0 | AC19: =AA19+AB19*1.15 -> 4966 | AD19: =AC19/$AC$87 -> 0.0012994413 | AF19: =C19-AA19 -> -2966 | AG19: =D19-AB19 -> 0 | AH19: =AF19+AG19*1.15 -> -2966 | AI19: =AH19/$AH$87 -> 0.0022785159
B20: Аренда опалубки | E20: =C20+D20 -> 0 | F20: =E20/$E$87 -> 0 | G20: 0 | H20: 0 | I20: =G20+H20 -> 0 | J20: =I20/$E$87 -> 0 | N20: =L20+M20 -> 0 | O20: =N20/$E$87 -> 0 | S20: =Q20+R20 -> 0 | T20: =S20/$S$87 -> 0 | X20: =V20+W20 -> 0 | Y20: =X20/$X$87 -> 0 | AA20: =G20+L20+Q20+V20 -> 0 | AB20: =H20+M20+R20+W20 -> 0 | AC20: =AA20+AB20*1.15 -> 0 | AD20: =AC20/$AC$87 -> 0 | AF20: =C20-AA20 -> 0 | AG20: =D20-AB20 -> 0 | AH20: =AF20+AG20*1.15 -> 0 | AI20: =AH20/$AH$87 -> 0
B21: Арена техники | C21: 194438.24 | D21: 0 | E21: =C21+D21 -> 194438.24 | F21: =E21/$E$87 -> 0.081940733 | G21: 151582.16 | H21: 0 | I21: =G21+H21 -> 151582.16 | J21: =I21/$E$87 -> 0.063880196 | N21: =L21+M21 -> 0 | O21: =N21/$E$87 -> 0 | Q21: =(35333.33*1.2)+73204 -> 115604 | S21: =Q21+R21 -> 115604 | T21: =S21/$S$87 -> 0.155738 | U21: 40 000 грн - самосвал Абу-закрыто актами 2 400 грн - автокран Акол- закрыто актами Экскаватор САТ 221 ч*331,24 грн = 73 204 грн | V21: =2649.92+ ((16333.34+18333.33+8250+2000)*1.2) -> 56549.924 | X21: =V21+W21 -> 56549.924 | Y21: =X21/$X$87 -> 0.057795003 | Z21: Экскаватор САТ наш 8ч= 2 649,92 АБУ самосвалы = 19 600 грн закрыто актами АБУ экскаваторы = 22 000 грн - закрыто актами Трест Буд - 9 900 грн - бетононасос Акол - 2 400 грн - автокран | AA21: =G21+L21+Q21+V21 -> 323736.08 | AB21: =H21+M21+R21+W21 -> 0 | AC21: =AA21+AB21*1.15 -> 323736.08 | AD21: =AC21/$AC$87 -> 0.084711245 | AF21: =C21-AA21 -> -129297.84 | AG21: =D21-AB21 -> 0 | AH21: =AF21+AG21*1.15 -> -129297.84 | AI21: =AH21/$AH$87 -> 0.099328112
B22: Логистические затраты | C22: 10000 | D22: 0 | E22: =C22+D22 -> 10000 | F22: =E22/$E$87 -> 0.0042142293 | G22: 24240 | H22: 3300 | I22: =G22+H22 -> 27540 | J22: =I22/$E$87 -> 0.011605987 | N22: =L22+M22 -> 0 | O22: =N22/$E$87 -> 0 | Q22: =500*1.2 -> 600 | S22: =Q22+R22 -> 600 | T22: =S22/$S$87 -> 0.00080830078 | U22: 600 гн Акол - перебазировка | V22: =(6833.34+2083.33)*1.2 -> 10700.004 | W22: 2100 | X22: =V22+W22 -> 12800.004 | Y22: =X22/$X$87 -> 0.013081826 | Z22: Транспортные Альфабизнесгрупп, акол закрыто актами ф2 перебазировка инструмента бр Перкатого согласовано с директором+ акт | AA22: =G22+L22+Q22+V22 -> 35540.004 | AB22: =H22+M22+R22+W22 -> 5400 | AC22: =AA22+AB22*1.15 -> 41750.004 | AD22: =AC22/$AC$87 -> 0.010924624 | AF22: =C22-AA22 -> -25540.004 | AG22: =D22-AB22 -> -5400 | AH22: =AF22+AG22*1.15 -> -31750.004 | AI22: =AH22/$AH$87 -> 0.024390725
B23: МШП | C23: 50000 | D23: 0 | E23: =C23+D23 -> 50000 | F23: =E23/$E$87 -> 0.021071147 | G23: 26408.592 | H23: 15324 | I23: =G23+H23 -> 41732.592 | J23: =I23/$E$87 -> 0.017587071 | N23: =L23+M23 -> 0 | O23: =N23/$E$87 -> 0 | P23: нет списаний | R23: 2290 | S23: =Q23+R23 -> 2290 | T23: =S23/$S$87 -> 0.0030850146 | V23: =34905.75*1.2 -> 41886.9 | W23: =993+260 -> 1253 | X23: =V23+W23 -> 43139.9 | Y23: =X23/$X$87 -> 0.044089726 | Z23: списанные МШП | AA23: =G23+L23+Q23+V23 -> 68295.492 | AB23: =H23+M23+R23+W23 -> 18867 | AC23: =AA23+AB23*1.15 -> 89992.542 | AD23: =AC23/$AC$87 -> 0.023548133 | AF23: =C23-AA23 -> -18295.492 | AG23: =D23-AB23 -> -18867 | AH23: =AF23+AG23*1.15 -> -39992.542 | AI23: =AH23/$AH$87 -> 0.030722739
B24: Строительные материалы | C24: 781652.62 | D24: 0 | E24: =C24+D24 -> 781652.62 | F24: =E24/$E$87 -> 0.32940634 | G24: 818952.48 | H24: 1880 | I24: =G24+H24 -> 820832.48 | J24: =I24/$E$87 -> 0.34591763 | N24: =L24+M24 -> 0 | O24: =N24/$E$87 -> 0 | P24: нет списаний | Q24: 187286.42 | S24: =Q24+R24 -> 187286.42 | T24: =S24/$S$87 -> 0.25230627 | U24: списаный материал | V24: =(416310.41+20360.05)*1.2 -> 524004.55 | W24: 208 | X24: =V24+W24 -> 524212.55 | Y24: =X24/$X$87 -> 0.53575432 | AA24: =G24+L24+Q24+V24 -> 1530243.5 | AB24: =H24+M24+R24+W24 -> 2088 | AC24: =AA24+AB24*1.15 -> 1532644.7 | AD24: =AC24/$AC$87 -> 0.40104346 | AF24: =C24-AA24 -> -748590.84 | AG24: =D24-AB24 -> -2088 | AH24: =AF24+AG24*1.15 -> -750992.04 | AI24: =AH24/$AH$87 -> 0.57692088
B25: Ремонты | C25: 20000 | D25: 0 | E25: =C25+D25 -> 20000 | F25: =E25/$E$87 -> 0.0084284586 | G25: 0.004 | H25: 0 | I25: =G25+H25 -> 0.004 | J25: =I25/$N$87 -> 1.949694e-08 | L25: 5900 | N25: =L25+M25 -> 5900 | O25: =N25/$N$87 -> 0.028757986 | P25: УШМ - 1920 грн Перфоратор - 2 660 грн Шуруповерт - 1 320 грн | Q25: =12737.22*1.2 -> 15284.664 | S25: =Q25+R25 -> 15284.664 | T25: =S25/$S$87 -> 0.02059101 | U25: Ремонт перфоратора Интерскоп - 1 265 грн Ремонт виброплиты - 14 019,66 грн | V25: =5773.35*1.2 -> 6928.02 | W25: 138 | X25: =V25+W25 -> 7066.02 | Y25: =X25/$X$87 -> 0.0072215949 | Z25: Сантел Украина закрыто актами (ремонт инструмента) | AA25: =G25+L25+Q25+V25 -> 28112.688 | AB25: =H25+M25+R25+W25 -> 138 | AC25: =AA25+AB25*1.15 -> 28271.388 | AD25: =AC25/$AC$87 -> 0.0073977065 | AF25: =C25-AA25 -> -8112.688 | AG25: =D25-AB25 -> -138 | AH25: =AF25+AG25*1.15 -> -8271.388 | AI25: =AH25/$AH$87 -> 0.0063541771
B26: Прочие производственные затраты | C26: =37431+50000 -> 87431 | D26: 10350 | E26: =C26+D26 -> 97781 | F26: =E26/$E$87 -> 0.041207156 | G26: 1238.4 | H26: 3051 | I26: =G26+H26 -> 4289.4 | J26: =I26/$N$87 -> 0.020907544 | M26: 3000 | N26: =L26+M26 -> 3000 | O26: =N26/$N$87 -> 0.014622705 | P26: амортизация авто Перкатого | R26: =1018 -> 1018 | S26: =Q26+R26 -> 1018 | T26: =S26/$S$87 -> 0.001371417 | U26: 943 грн - бензин и масло для трамбовки 75 грн - батарейки | W26: 1060 | X26: =V26+W26 -> 1060 | Y26: =X26/$X$87 -> 0.0010833384 | Z26: 20 л бензина,виброплащадка,трамбовка дороги =560грн грабли мет.черенки(по 5 шт)=500грн | AA26: =G26+L26+Q26+V26 -> 1238.4 | AB26: =H26+M26+R26+W26 -> 8129 | AC26: =AA26+AB26*1.15 -> 10586.75 | AD26: =AC26/$AC$87 -> 0.0027702095 | AF26: =C26-AA26 -> 86192.6 | AG26: =D26-AB26 -> 2221 | AH26: =AF26+AG26*1.15 -> 88746.75 | AI26: =AH26/$AH$87 -> -0.068176293
B27: Командировочные производственного персонала | C27: 0 | D27: 154368.56 | E27: =C27+D27 -> 154368.56 | F27: =E27/$E$87 -> 0.065054452 | G27: 3400 | H27: 58700 | I27: =G27+H27 -> 62100 | J27: =I27/$N$87 -> 0.30268999 | M27: 29600 | N27: =L27+M27 -> 29600 | O27: =N27/$N$87 -> 0.14427736 | P27: Суточные Жук, Перкатый - январь | R27: =900+22500 -> 23400 | S27: =Q27+R27 -> 23400 | T27: =S27/$S$87 -> 0.03152373 | U27: бр Жук, Перкатый | W27: 18400 | X27: =V27+W27 -> 18400 | Y27: =X27/$X$87 -> 0.018805119 | Z27: бр.Жука-9 900грн.,не планир бр.Перкатого- 7 600грн.,бр.Вектор- 900грн | AA27: =G27+L27+Q27+V27 -> 3400 | AB27: =H27+M27+R27+W27 -> 130100 | AC27: =AA27+AB27*1.15 -> 153015 | AD27: =AC27/$AC$87 -> 0.040039069 | AF27: =C27-AA27 -> -3400 | AG27: =D27-AB27 -> 24268.562 | AH27: =AF27+AG27*1.15 -> 24508.846 | AI27: =AH27/$AH$87 -> -0.018827982
B28: Аренда квартиры с коммунальными платежами | C28: 79640.119 | D28: 5750 | E28: =C28+D28 -> 85390.119 | F28: =E28/$E$87 -> 0.035985354 | G28: 38280 | H28: 6000 | I28: =G28+H28 -> 44280 | J28: =I28/$N$87 -> 0.21583112 | L28: 18180 | N28: =L28+M28 -> 18180 | O28: =N28/$N$87 -> 0.088613592 | P28: Проживание бригад - январь | Q28: =13500*1.2 -> 16200 | S28: =Q28+R28 -> 16200 | T28: =S28/$S$87 -> 0.021824121 | U28: Уют компени - за февраль - закрыто актами | V28: =8900*1.2 -> 10680 | X28: =V28+W28 -> 10680 | Y28: =X28/$X$87 -> 0.010915145 | Z28: Уют компани, закрыто актами | AA28: =G28+L28+Q28+V28 -> 83340 | AB28: =H28+M28+R28+W28 -> 6000 | AC28: =AA28+AB28*1.15 -> 90240 | AD28: =AC28/$AC$87 -> 0.023612885 | AF28: =C28-AA28 -> -3699.8809 | AG28: =D28-AB28 -> -250 | AH28: =AF28+AG28*1.15 -> -3987.3809 | AI28: =AH28/$AH$87 -> 0.0030631527
B29: Транспортные затраты производственного персонала | C29: =37168.75-C61 -> 18584.25 | D29: =44662.9698725352+575 -> 45237.97 | E29: =C29+D29 -> 63822.22 | F29: =E29/$E$87 -> 0.026896147 | G29: 15949.96 | H29: 16670.08 | I29: =G29+H29 -> 32620.04 | J29: =I29/$N$87 -> 0.15899774 | L29: =1968.3+2739 -> 4707.3 | M29: 3648 | N29: =L29+M29 -> 8355.3 | O29: =N29/$N$87 -> 0.040725695 | P29: Проезд на работу 16 грн/день - 3648 грн Перкатый 70 л - 1 968 грн Ширшов 100 л - 2 739 грн | Q29: =3578.7 -> 3578.7 | R29: 5989 | S29: =Q29+R29 -> 9567.7 | T29: =S29/$S$87 -> 0.012889299 | U29: Ширшов - 2 179,20 грн Перкатый - 1 399,5 грн ф2 - проезд на работу в т ч уезд с обїекта бр Перкатого - 1600 грн | V29: 2600 | W29: =10397.18+834+80 -> 11311.18 | X29: =V29+W29 -> 13911.18 | Y29: =X29/$X$87 -> 0.014217467 | Z29: ф2-30л бензина Перкатому проезд домой (согласовано с директором) Ширшов 40л=959,60 Перкатый 65л=1 640,35 приезд на обьект бр.Жука 9 чел (из-за не загруженности по работе согласовано с директором) - 4 470грн уезд с обьекта 9чел- 2374грн проезд на работу - -3 553,18 | AA29: =G29+L29+Q29+V29 -> 26835.96 | AB29: =H29+M29+R29+W29 -> 37618.26 | AC29: =AA29+AB29*1.15 -> 70096.959 | AD29: =AC29/$AC$87 -> 0.018342104 | AF29: =C29-AA29 -> -8251.71 | AG29: =D29-AB29 -> 7619.7099 | AH29: =AF29+AG29*1.15 -> 510.95635 | AI29: =AH29/$AH$87 -> -0.00039252265
B30: Разрешительная документация | E30: =C30+D30 -> 0 | F30: =E30/$E$87 -> 0 | G30: 0 | H30: 0 | I30: =G30+H30 -> 0 | J30: =I30/$E$87 -> 0 | N30: =L30+M30 -> 0 | O30: =N30/$E$87 -> 0 | S30: =Q30+R30 -> 0 | T30: =S30/$S$87 -> 0 | X30: =V30+W30 -> 0 | Y30: =X30/$X$87 -> 0 | AA30: =G30+L30+Q30+V30 -> 0 | AB30: =H30+M30+R30+W30 -> 0 | AC30: =AA30+AB30*1.15 -> 0 | AD30: =AC30/$AC$87 -> 0 | AF30: =C30-AA30 -> 0 | AG30: =D30-AB30 -> 0 | AH30: =AF30+AG30*1.15 -> 0 | AI30: =AH30/$AH$87 -> 0
B31: Представительские затраты | D31: 3743.1082 | E31: =C31+D31 -> 3743.1082 | F31: =E31/$E$87 -> 0.0015774316 | G31: 0 | H31: 0 | I31: =G31+H31 -> 0 | J31: =I31/$E$87 -> 0 | N31: =L31+M31 -> 0 | O31: =N31/$E$87 -> 0 | S31: =Q31+R31 -> 0 | T31: =S31/$S$87 -> 0 | X31: =V31+W31 -> 0 | Y31: =X31/$X$87 -> 0 | AA31: =G31+L31+Q31+V31 -> 0 | AB31: =H31+M31+R31+W31 -> 0 | AC31: =AA31+AB31*1.15 -> 0 | AD31: =AC31/$AC$87 -> 0 | AF31: =C31-AA31 -> 0 | AG31: =D31-AB31 -> 3743.1082 | AH31: =AF31+AG31*1.15 -> 4304.5744 | AI31: =AH31/$AH$87 -> -0.0033068245
Y32: =X32/$X$87 -> 0
B33: Дополнительные расходы | C33: =C34 -> 0 | D33: =D34 -> 0 | E33: =E34 -> 0 | F33: =E33/$E$87 -> 0 | G33: =G34 -> 0 | H33: =H34 -> 0 | I33: =I34 -> 0 | J33: =I33/$E$87 -> 0 | L33: =L34 -> 0 | M33: =M34 -> 0 | N33: =N34 -> 0 | O33: =N33/$E$87 -> 0 | Q33: =Q34 -> 0 | R33: =R34 -> 0 | S33: =S34 -> 0 | T33: =S33/$S$87 -> 0 | V33: =V34 -> 0 | W33: =W34 -> 0 | X33: =X34 -> 0 | Y33: =X33/$X$87 -> 0 | AA33: =AA34 -> 0 | AB33: =AB34 -> 0 | AC33: =AC34 -> 0 | AF33: =AF34 -> 0 | AG33: =AG34 -> 0 | AH33: =AH34 -> 0
B34: Расход от ивест. Деятельности (ОС) | E34: =C34+D34*1.15 -> 0 | F34: =E34/$E$87 -> 0 | I34: =G34+H34*1.15 -> 0 | J34: =I34/$E$87 -> 0 | N34: =L34+M34*1.15 -> 0 | O34: =N34/$E$87 -> 0 | S34: =Q34+R34*1.15 -> 0 | T34: =S34/$S$87 -> 0 | X34: =V34+W34*1.15 -> 0 | Y34: =X34/$X$87 -> 0 | AA34: =L34+Q34 -> 0 | AB34: =M34+R34 -> 0 | AC34: =AA34+AB34*1.15 -> 0 | AD34: =AC34/$AC$87 -> 0 | AF34: =C34-AA34 -> 0 | AG34: =D34-AB34 -> 0 | AH34: =AF34+AG34*1.15 -> 0 | AI34: =AH34/$E$87 -> 0
Y35: =X35/$X$87 -> 0
B36: Маржинальный доход, грн | C36: =(C5)-(C8) -> 1690733.1 | D36: =(D5)-(D8) -> -916057.78 | E36: =(E5)-(E8) -> 774675.29 | G36: =(G5)-(G8) -> -345751.53 | H36: =(H5)-(H8) -> 705410.42 | I36: =(I5)-(I8) -> 359658.89 | L36: =(L5)-(L8) -> -107233.3 | M36: =(M5)-(M8) -> -56982 | N36: =(N5)-(N8) -> -164215.3 | Q36: =(Q5)-(Q8) -> 536093.31 | R36: =(R5)-(R8) -> -241020 | S36: =(S5)-(S8) -> 295073.31 | V36: =(V5)-(V8) -> 1139136.7 | W36: =(W5)-(W8) -> -239229.22 | X36: =(X5)-(X8) -> 899907.51 | Y36: =X36/$X$87 -> 0.91972107 | AA36: =(AA5)-(AA8) -> 1222245.2 | AB36: =(AB5)-(AB8) -> 168179.2 | AC36: =(AC5)-(AC8) -> 1234151.3 | AF36: =(AF5)-(AF8) -> 468487.87 | AG36: =(AG5)-(AG8) -> -1084237 | AH36: =(AH5)-(AH8) -> -596884.66
B37: Маржинальный доход, % | C37: =C36/(C5) -> 0.55501541 | D37: =D36/(D5) -> #DIV/0! | E37: =E36/(E5) -> 0.25430195 | G37: =G36/(G5) -> -0.41081811 | H37: =H36/(H5) -> 0.58298382 | I37: =I36/(I5) -> 0.17530508 | L37: =L36/(L5) -> #DIV/0! | M37: =M36/(M5) -> #DIV/0! | N37: =N36/(N5) -> #DIV/0! | Q37: =Q36/(Q5) -> 0.533977 | R37: =R36/(R5) -> #DIV/0! | S37: =S36/(S5) -> 0.29390846 | V37: =V36/(V5) -> 0.6289543 | W37: =W36/(W5) -> #DIV/0! | X37: =X36/(X5) -> 0.4968681 | Y37: =X37/$X$87 -> 5.0780781e-07 | AA37: =AA36/(AA5) -> 0.33424448 | AB37: =AB36/(AB5) -> 0.13899107 | AC37: =AC36/(AC5) -> 0.2535889 | AF37: =AF36/(AF5) -> -0.76743568 | AG37: =AG36/(AG5) -> 0.89606362 | AH37: =AH36/(AH5) -> 0.32787595
Y38: =X38/$X$87 -> 0
B39: Общепроизводственные затраты | C39: =SUM(C40:C46) -> 3743.1082 | D39: =SUM(D40:D46) -> 0 | E39: =SUM(E40:E46) -> 3743.1082 | F39: =E39/$E$87 -> 0.0015774316 | G39: =SUM(G40:G46) -> 434.78 | H39: =SUM(H40:H46) -> 94 | I39: =SUM(I40:I46) -> 528.78 | J39: =I39/$E$87 -> 0.00022284002 | L39: =SUM(L40:L46) -> 0 | M39: =SUM(M40:M46) -> 0 | N39: =SUM(N40:N46) -> 0 | O39: =N39/$E$87 -> 0 | Q39: =SUM(Q40:Q46) -> 0 | R39: =SUM(R40:R46) -> 0 | S39: =SUM(S40:S46) -> 0 | T39: =S39/$S$87 -> 0 | V39: =SUM(V40:V46) -> 0 | W39: =SUM(W40:W46) -> 0 | X39: =SUM(X40:X46) -> 0 | Y39: =X39/$X$87 -> 0 | AA39: =SUM(AA40:AA46) -> 434.78 | AB39: =SUM(AB40:AB46) -> 94 | AC39: =SUM(AC40:AC46) -> 542.88 | AD39: =AC39/$AC$87 -> 0.00014205411 | AF39: =SUM(AF40:AF46) -> 3308.3282 | AG39: =SUM(AG40:AG46) -> -94 | AH39: =SUM(AH40:AH46) -> 3200.2282
B40: Благоустройство офиса | E40: =C40+D40*1.15 -> 0 | F40: =E40/$E$87 -> 0 | I40: =G40+H40*1.15 -> 0 | J40: =I40/$E$87 -> 0 | N40: =L40+M40*1.15 -> 0 | O40: =N40/$E$87 -> 0 | S40: =Q40+R40*1.15 -> 0 | T40: =S40/$S$87 -> 0 | X40: =V40+W40*1.15 -> 0 | Y40: =X40/$X$87 -> 0 | AA40: =L40 -> 0 | AB40: =M40 -> 0 | AC40: =AA40+AB40*1.15 -> 0 | AD40: =AC40/$AC$87 -> 0 | AF40: =C40-AA40 -> 0 | AG40: =D40-AB40 -> 0 | AH40: =AF40+AG40*1.15 -> 0 | AI40: =AH40/$E$87 -> 0
B41: Хозтовары и материалы | E41: =C41+D41*1.15 -> 0 | F41: =E41/$E$87 -> 0 | H41: 94 | I41: =G41+H41 -> 94 | J41: =I41/$E$87 -> 3.9613755e-05 | N41: =L41+M41 -> 0 | O41: =N41/$E$87 -> 0 | S41: =Q41+R41 -> 0 | T41: =S41/$S$87 -> 0 | X41: =V41+W41 -> 0 | Y41: =X41/$X$87 -> 0 | AA41: =G41+L41+Q41+V41 -> 0 | AB41: =H41+M41+R41+W41 -> 94 | AC41: =AA41+AB41*1.15 -> 108.1 | AD41: =AC41/$AC$87 -> 2.8286268e-05 | AF41: =C41-AA41 -> 0 | AG41: =D41-AB41 -> -94 | AH41: =AF41+AG41*1.15 -> -108.1 | AI41: =AH41/$E$87 -> -4.5555819e-05
B42: ИТ расходы | C42: 1871.5541 | E42: =C42+D42 -> 1871.5541 | F42: =E42/$E$87 -> 0.00078871582 | G42: 335 | I42: =G42+H42 -> 335 | J42: =I42/$E$87 -> 0.00014117668 | N42: =L42+M42 -> 0 | O42: =N42/$E$87 -> 0 | S42: =Q42+R42 -> 0 | T42: =S42/$S$87 -> 0 | X42: =V42+W42 -> 0 | Y42: =X42/$X$87 -> 0 | AA42: =G42+L42+Q42+V42 -> 335 | AB42: =H42+M42+R42+W42 -> 0 | AC42: =AA42+AB42*1.15 -> 335 | AD42: =AC42/$AC$87 -> 8.7658649e-05 | AF42: =C42-AA42 -> 1536.5541 | AG42: =D42-AB42 -> 0 | AH42: =AF42+AG42*1.15 -> 1536.5541 | AI42: =AH42/$E$87 -> 0.00064753913
B43: Питьевая вода | E43: =C43+D43 -> 0 | F43: =E43/$E$87 -> 0 | I43: =G43+H43 -> 0 | J43: =I43/$E$87 -> 0 | N43: =L43+M43 -> 0 | O43: =N43/$E$87 -> 0 | S43: =Q43+R43 -> 0 | T43: =S43/$S$87 -> 0 | X43: =V43+W43 -> 0 | Y43: =X43/$X$87 -> 0 | AA43: =G43+L43+Q43+V43 -> 0 | AB43: =H43+M43+R43+W43 -> 0 | AC43: =AA43+AB43*1.15 -> 0 | AD43: =AC43/$AC$87 -> 0 | AF43: =C43-AA43 -> 0 | AG43: =D43-AB43 -> 0 | AH43: =AF43+AG43*1.15 -> 0 | AI43: =AH43/$E$87 -> 0
B44: Охрана офиса и пожарная сигнализация | E44: =C44+D44 -> 0 | F44: =E44/$E$87 -> 0 | I44: =G44+H44 -> 0 | J44: =I44/$E$87 -> 0 | N44: =L44+M44 -> 0 | O44: =N44/$E$87 -> 0 | S44: =Q44+R44 -> 0 | T44: =S44/$S$87 -> 0 | X44: =V44+W44 -> 0 | Y44: =X44/$X$87 -> 0 | AA44: =G44+L44+Q44+V44 -> 0 | AB44: =H44+M44+R44+W44 -> 0 | AC44: =AA44+AB44*1.15 -> 0 | AD44: =AC44/$AC$87 -> 0 | AF44: =C44-AA44 -> 0 | AG44: =D44-AB44 -> 0 | AH44: =AF44+AG44*1.15 -> 0 | AI44: =AH44/$E$87 -> 0
B45: Курьерские и почтовые | E45: =C45+D45 -> 0 | F45: =E45/$E$87 -> 0 | I45: =G45+H45 -> 0 | J45: =I45/$E$87 -> 0 | N45: =L45+M45 -> 0 | O45: =N45/$E$87 -> 0 | S45: =Q45+R45 -> 0 | T45: =S45/$S$87 -> 0 | X45: =V45+W45 -> 0 | Y45: =X45/$X$87 -> 0 | AA45: =G45+L45+Q45+V45 -> 0 | AB45: =H45+M45+R45+W45 -> 0 | AC45: =AA45+AB45*1.15 -> 0 | AD45: =AC45/$AC$87 -> 0 | AF45: =C45-AA45 -> 0 | AG45: =D45-AB45 -> 0 | AH45: =AF45+AG45*1.15 -> 0 | AI45: =AH45/$E$87 -> 0
B46: Канцтовары | C46: 1871.5541 | E46: =C46+D46 -> 1871.5541 | F46: =E46/$E$87 -> 0.00078871582 | G46: 99.78 | I46: =G46+H46 -> 99.78 | J46: =I46/$E$87 -> 4.204958e-05 | N46: =L46+M46 -> 0 | O46: =N46/$E$87 -> 0 | S46: =Q46+R46 -> 0 | T46: =S46/$S$87 -> 0 | X46: =V46+W46 -> 0 | Y46: =X46/$X$87 -> 0 | AA46: =G46+L46+Q46+V46 -> 99.78 | AB46: =H46+M46+R46+W46 -> 0 | AC46: =AA46+AB46*1.15 -> 99.78 | AD46: =AC46/$AC$87 -> 2.6109194e-05 | AF46: =C46-AA46 -> 1771.7741 | AG46: =D46-AB46 -> 0 | AH46: =AF46+AG46*1.15 -> 1771.7741 | AI46: =AH46/$E$87 -> 0.00074666624
T47: =S47/$S$87 -> 0 | Y47: =X47/$X$87 -> 0 | AD47: =AC47/$AC$87 -> 0
B48: Маркетинговые затраты | C48: =SUM(C49:C50) -> 0 | D48: =SUM(D49:D50) -> 0 | E48: =SUM(E49:E50) -> 0 | F48: =E48/$E$87 -> 0 | G48: =SUM(G49:G50) -> 0 | H48: =SUM(H49:H50) -> 0 | I48: =SUM(I49:I50) -> 0 | J48: =I48/$E$87 -> 0 | L48: =SUM(L49:L50) -> 0 | M48: =SUM(M49:M50) -> 0 | N48: =SUM(N49:N50) -> 0 | O48: =N48/$E$87 -> 0 | Q48: =SUM(Q49:Q50) -> 0 | R48: =SUM(R49:R50) -> 0 | S48: =SUM(S49:S50) -> 0 | T48: =S48/$S$87 -> 0 | V48: =SUM(V49:V50) -> 0 | W48: =SUM(W49:W50) -> 0 | X48: =SUM(X49:X50) -> 0 | Y48: =X48/$X$87 -> 0 | AA48: =AA50+AA49 -> 0 | AB48: =AB50+AB49 -> 0 | AC48: =AC50+AC49 -> 0 | AF48: =AF50+AF49 -> 0 | AG48: =AG50+AG49 -> 0 | AH48: =AH50+AH49 -> 0
B49: Реклама | E49: =C49+D49*1.15 -> 0 | F49: =E49/$E$87 -> 0 | I49: =G49+H49*1.15 -> 0 | J49: =I49/$E$87 -> 0 | N49: =L49+M49*1.15 -> 0 | O49: =N49/$E$87 -> 0 | S49: =Q49+R49*1.15 -> 0 | T49: =S49/$E$87 -> 0 | X49: =V49+W49*1.15 -> 0 | Y49: =X49/$X$87 -> 0 | AA49: =L49+Q49+V49 -> 0 | AB49: =M49+R49+W49 -> 0 | AC49: =AA49+AB49*1.15 -> 0 | AD49: =AC49/$AC$87 -> 0 | AF49: =C49-AA49 -> 0 | AG49: =D49-AB49 -> 0 | AH49: =AF49+AG49*1.15 -> 0 | AI49: =AH49/$E$87 -> 0
B50: Прочие маркетинговые затраты | E50: =C50+D50*1.15 -> 0 | F50: =E50/$E$87 -> 0 | I50: =G50+H50*1.15 -> 0 | J50: =I50/$E$87 -> 0 | N50: =L50+M50*1.15 -> 0 | O50: =N50/$E$87 -> 0 | S50: =Q50+R50*1.15 -> 0 | T50: =S50/$E$87 -> 0 | X50: =V50+W50*1.15 -> 0 | Y50: =X50/$X$87 -> 0 | AA50: =L50+Q50+V50 -> 0 | AB50: =M50+R50+W50 -> 0 | AC50: =AA50+AB50*1.15 -> 0 | AD50: =AC50/$AC$87 -> 0 | AF50: =C50-AA50 -> 0 | AG50: =D50-AB50 -> 0 | AH50: =AF50+AG50*1.15 -> 0 | AI50: =AH50/$E$87 -> 0
Y51: =X51/$X$87 -> 0 | AA51: =L51+Q51+V51 -> 0 | AB51: =M51+R51+W51 -> 0
B52: Административные затраты | C52: =SUM(C53:C69) -> 33590.5 | D52: =SUM(D53:D69) -> 63973.5 | E52: =SUM(E53:E69) -> 97564 | F52: =E52/$E$87 -> 0.041115707 | G52: =SUM(G53:G69) -> 13302.36 | H52: =SUM(H53:H69) -> 32081.13 | I52: =SUM(I53:I69) -> 45383.49 | J52: =I52/$N$87 -> 0.22120979 | L52: =SUM(L53:L69) -> 9611.4 | M52: =SUM(M53:M69) -> 20497.23 | N52: =SUM(N53:N69) -> 30108.63 | O52: =N52/$N$87 -> 0.14675654 | Q52: =SUM(Q53:Q69) -> 17921 | R52: =SUM(R53:R69) -> 15486.95 | S52: =SUM(S53:S69) -> 33407.95 | T52: =S52/$S$87 -> 0.04500612 | V52: =SUM(V53:V69) -> 18817.98 | W52: =SUM(W53:W69) -> 14640 | X52: =SUM(X53:X69) -> 33457.98 | Y52: =X52/$X$87 -> 0.034194636 | AA52: =SUM(AA53:AA69) -> 59652.74 | AB52: =SUM(AB53:AB69) -> 82705.31 | AC52: =SUM(AC53:AC69) -> 154763.85 | AD52: =AC52/$AC$87 -> 0.040496685 | AF52: =SUM(AF53:AF69) -> -26062.24 | AG52: =SUM(AG53:AG69) -> -18731.81 | AH52: =SUM(AH53:AH69) -> -47603.822 | AI52: =AH52/$AH$87 -> 0.036569813
B53: ЗП управленческого персонала | E53: =C53+D53*1.15 -> 0 | F53: =E53/$E$87 -> 0 | I53: =G53+H53*1.15 -> 0 | J53: =I53/$N$87 -> 0 | N53: =L53+M53*1.15 -> 0 | O53: =N53/$N$87 -> 0 | S53: =Q53+R53*1.15 -> 0 | T53: =S53/$S$87 -> 0 | X53: =V53+W53*1.15 -> 0 | Y53: =X53/$X$87 -> 0 | AA53: =L53 -> 0 | AB53: =M53 -> 0 | AC53: =AA53+AB53*1.15 -> 0 | AD53: =AC53/$AC$87 -> 0 | AF53: =C53-AA53 -> 0 | AG53: =D53-AB53 -> 0 | AH53: =AF53+AG53*1.15 -> 0 | AI53: =AH53/$AH$87 -> 0
B54: Начисления на управленчискую зарплату | E54: =C54+D54*1.15 -> 0 | F54: =E54/$E$87 -> 0 | I54: =G54+H54*1.15 -> 0 | J54: =I54/$N$87 -> 0 | N54: =L54+M54*1.15 -> 0 | O54: =N54/$N$87 -> 0 | S54: =Q54+R54*1.15 -> 0 | T54: =S54/$S$87 -> 0 | X54: =V54+W54*1.15 -> 0 | Y54: =X54/$X$87 -> 0 | AA54: =L54 -> 0 | AB54: =M54 -> 0 | AC54: =AA54+AB54*1.15 -> 0 | AD54: =AC54/$AC$87 -> 0 | AF54: =C54-AA54 -> 0 | AG54: =D54-AB54 -> 0 | AH54: =AF54+AG54*1.15 -> 0 | AI54: =AH54/$AH$87 -> 0
B55: Удержание с зарплаты управленческого персонала | E55: =C55+D55*1.15 -> 0 | F55: =E55/$E$87 -> 0 | I55: =G55+H55*1.15 -> 0 | J55: =I55/$N$87 -> 0 | N55: =L55+M55*1.15 -> 0 | O55: =N55/$N$87 -> 0 | S55: =Q55+R55*1.15 -> 0 | T55: =S55/$S$87 -> 0 | X55: =V55+W55*1.15 -> 0 | Y55: =X55/$X$87 -> 0 | AA55: =L55 -> 0 | AB55: =M55 -> 0 | AC55: =AA55+AB55*1.15 -> 0 | AD55: =AC55/$AC$87 -> 0 | AF55: =C55-AA55 -> 0 | AG55: =D55-AB55 -> 0 | AH55: =AF55+AG55*1.15 -> 0 | AI55: =AH55/$AH$87 -> 0
B56: ЗП РМ | C56: 9901.5 | D56: 61973.5 | E56: =C56+D56 -> 71875 | F56: =E56/$E$87 -> 0.030289773 | G56: 5555 | H56: 31945.5 | I56: =G56+H56 -> 37500.5 | J56: =I56/$N$87 -> 0.18278625 | L56: 4552.75 | M56: 20447 | N56: =L56+M56 -> 24999.75 | O56: =N56/$N$87 -> 0.12185466 | P56: Бондарук П январь в т ч отпускные - 1541,30 грн | Q56: 10465 | R56: 14535 | S56: =Q56+R56 -> 25000 | T56: =S56/$S$87 -> 0.033679199 | U56: Бондарук П февраль | V56: 10465 | W56: 14335 | X56: =V56+W56 -> 24800 | Y56: =X56/$X$87 -> 0.02534603 | Z56: Бондарук П март | AA56: =G56+L56+Q56+V56 -> 31037.75 | AB56: =H56+M56+R56+W56 -> 81262.5 | AC56: =AA56+AB56*1.15 -> 124489.62 | AD56: =AC56/$AC$87 -> 0.032574902 | AF56: =C56-AA56 -> -21136.25 | AG56: =D56-AB56 -> -19289 | AH56: =AF56+AG56*1.15 -> -43318.6 | AI56: =AH56/$AH$87 -> 0.033277856
B57: Удержание с зарплаты РМ | C57: 2706 | D57: 0 | E57: =C57+D57 -> 2706 | F57: =E57/$E$87 -> 0.0011403704 | G57: 1346 | H57: 0 | I57: =G57+H57 -> 1346 | J57: =I57/$N$87 -> 0.0065607203 | L57: 1102.81 | N57: =L57+M57 -> 1102.81 | O57: =N57/$N$87 -> 0.0053753551 | Q57: 2535 | S57: =Q57+R57 -> 2535 | T57: =S57/$S$87 -> 0.0034150708 | V57: 2535 | X57: =V57+W57 -> 2535 | Y57: =X57/$X$87 -> 0.0025908139 | AA57: =G57+L57+Q57+V57 -> 7518.81 | AB57: =H57+M57+R57+W57 -> 0 | AC57: =AA57+AB57*1.15 -> 7518.81 | AD57: =AC57/$AC$87 -> 0.001967429 | AF57: =C57-AA57 -> -4812.81 | AG57: =D57-AB57 -> 0 | AH57: =AF57+AG57*1.15 -> -4812.81 | AI57: =AH57/$AH$87 -> 0.003697257
B58: Начисления на зарплату PM | C58: 2398.5 | D58: 0 | E58: =C58+D58 -> 2398.5 | F58: =E58/$E$87 -> 0.0010107829 | G58: 1518 | H58: 0 | I58: =G58+H58 -> 1518 | J58: =I58/$N$87 -> 0.0073990887 | L58: 1244.23 | N58: =L58+M58 -> 1244.23 | O58: =N58/$N$87 -> 0.0060646694 | Q58: 2860 | S58: =Q58+R58 -> 2860 | T58: =S58/$S$87 -> 0.0038529004 | V58: 2860 | X58: =V58+W58 -> 2860 | Y58: =X58/$X$87 -> 0.0029229696 | AA58: =G58+L58+Q58+V58 -> 8482.23 | AB58: =H58+M58+R58+W58 -> 0 | AC58: =AA58+AB58*1.15 -> 8482.23 | AD58: =AC58/$AC$87 -> 0.0022195248 | AF58: =C58-AA58 -> -6083.73 | AG58: =D58-AB58 -> 0 | AH58: =AF58+AG58*1.15 -> -6083.73 | AI58: =AH58/$AH$87 -> 0.0046735926
B59: Премия управленческого персонала | E59: =C59+D59 -> 0 | F59: =E59/$E$87 -> 0 | G59: 0 | H59: 0 | I59: =G59+H59 -> 0 | J59: =I59/$N$87 -> 0 | N59: =L59+M59 -> 0 | O59: =N59/$N$87 -> 0 | S59: =Q59+R59 -> 0 | T59: =S59/$S$87 -> 0 | X59: =V59+W59 -> 0 | Y59: =X59/$X$87 -> 0 | AA59: =G59+L59+Q59+V59 -> 0 | AB59: =H59+M59+R59+W59 -> 0 | AC59: =AA59+AB59*1.15 -> 0 | AD59: =AC59/$AC$87 -> 0 | AF59: =C59-AA59 -> 0 | AG59: =D59-AB59 -> 0 | AH59: =AF59+AG59*1.15 -> 0 | AI59: =AH59/$AH$87 -> 0
B60: Телекомуникационные услуги | E60: =C60+D60 -> 0 | F60: =E60/$E$87 -> 0 | G60: 0 | H60: 0 | I60: =G60+H60 -> 0 | J60: =I60/$N$87 -> 0 | N60: =L60+M60 -> 0 | O60: =N60/$N$87 -> 0 | S60: =Q60+R60 -> 0 | T60: =S60/$S$87 -> 0 | X60: =V60+W60 -> 0 | Y60: =X60/$X$87 -> 0 | AA60: =G60+L60+Q60+V60 -> 0 | AB60: =H60+M60+R60+W60 -> 0 | AC60: =AA60+AB60*1.15 -> 0 | AD60: =AC60/$AC$87 -> 0 | AF60: =C60-AA60 -> 0 | AG60: =D60-AB60 -> 0 | AH60: =AF60+AG60*1.15 -> 0 | AI60: =AH60/$AH$87 -> 0
B61: Транспортные затраты управленческого персонала | C61: 18584.5 | E61: =C61+D61 -> 18584.5 | F61: =E61/$E$87 -> 0.0078319344 | G61: 4883.36 | H61: 0 | I61: =G61+H61 -> 4883.36 | J61: =I61/$N$87 -> 0.023802644 | L61: 2711.61 | N61: =L61+M61 -> 2711.61 | O61: =N61/$N$87 -> 0.013217024 | P61: Бондарук 99 л - 2 711,61 грн | Q61: =2061 -> 2061 | S61: =Q61+R61 -> 2061 | T61: =S61/$S$87 -> 0.0027765132 | U61: Бондарук - 2 061 грн | V61: 2957.98 | X61: =V61+W61 -> 2957.98 | Y61: =X61/$X$87 -> 0.0030231068 | Z61: Бондарук 125,01=2 957,98 | AA61: =G61+L61+Q61+V61 -> 12613.95 | AB61: =H61+M61+R61+W61 -> 0 | AC61: =AA61+AB61*1.15 -> 12613.95 | AD61: =AC61/$AC$87 -> 0.0033006621 | AF61: =C61-AA61 -> 5970.55 | AG61: =D61-AB61 -> 0 | AH61: =AF61+AG61*1.15 -> 5970.55 | AI61: =AH61/$AH$87 -> -0.0045866464
B62: Аренда офиса с коммунальными платежами | E62: =C62+D62 -> 0 | F62: =E62/$E$87 -> 0 | G62: 0 | H62: 0 | I62: =G62+H62 -> 0 | J62: =I62/$N$87 -> 0 | N62: =L62+M62 -> 0 | O62: =N62/$N$87 -> 0 | S62: =Q62+R62 -> 0 | T62: =S62/$S$87 -> 0 | X62: =V62+W62 -> 0 | Y62: =X62/$X$87 -> 0 | AA62: =G62+L62+Q62+V62 -> 0 | AB62: =H62+M62+R62+W62 -> 0 | AC62: =AA62+AB62*1.15 -> 0 | AD62: =AC62/$AC$87 -> 0 | AF62: =C62-AA62 -> 0 | AG62: =D62-AB62 -> 0 | AH62: =AF62+AG62*1.15 -> 0 | AI62: =AH62/$AH$87 -> 0
B63: Затраты на коммандировки управленческого персонала | E63: =C63+D63 -> 0 | F63: =E63/$E$87 -> 0 | G63: 0 | H63: 0 | I63: =G63+H63 -> 0 | J63: =I63/$N$87 -> 0 | N63: =L63+M63 -> 0 | O63: =N63/$N$87 -> 0 | S63: =Q63+R63 -> 0 | T63: =S63/$S$87 -> 0 | X63: =V63+W63 -> 0 | Y63: =X63/$X$87 -> 0 | AA63: =G63+L63+Q63+V63 -> 0 | AB63: =H63+M63+R63+W63 -> 0 | AC63: =AA63+AB63*1.15 -> 0 | AD63: =AC63/$AC$87 -> 0 | AF63: =C63-AA63 -> 0 | AG63: =D63-AB63 -> 0 | AH63: =AF63+AG63*1.15 -> 0 | AI63: =AH63/$AH$87 -> 0
B64: Юридические услуги | E64: =C64+D64 -> 0 | F64: =E64/$E$87 -> 0 | G64: 0 | H64: 0 | I64: =G64+H64 -> 0 | J64: =I64/$N$87 -> 0 | N64: =L64+M64 -> 0 | O64: =N64/$N$87 -> 0 | S64: =Q64+R64 -> 0 | T64: =S64/$S$87 -> 0 | X64: =V64+W64 -> 0 | Y64: =X64/$X$87 -> 0 | AA64: =G64+L64+Q64+V64 -> 0 | AB64: =H64+M64+R64+W64 -> 0 | AC64: =AA64+AB64*1.15 -> 0 | AD64: =AC64/$AC$87 -> 0 | AF64: =C64-AA64 -> 0 | AG64: =D64-AB64 -> 0 | AH64: =AF64+AG64*1.15 -> 0 | AI64: =AH64/$AH$87 -> 0
B65: Услуги | E65: =C65+D65 -> 0 | F65: =E65/$E$87 -> 0 | G65: 0 | H65: 0 | I65: =G65+H65 -> 0 | J65: =I65/$N$87 -> 0 | N65: =L65+M65 -> 0 | O65: =N65/$N$87 -> 0 | S65: =Q65+R65 -> 0 | T65: =S65/$S$87 -> 0 | X65: =V65+W65 -> 0 | Y65: =X65/$X$87 -> 0 | AA65: =G65+L65+Q65+V65 -> 0 | AB65: =H65+M65+R65+W65 -> 0 | AC65: =AA65+AB65*1.15 -> 0 | AD65: =AC65/$AC$87 -> 0 | AF65: =C65-AA65 -> 0 | AG65: =D65-AB65 -> 0 | AH65: =AF65+AG65*1.15 -> 0 | AI65: =AH65/$AH$87 -> 0
B66: Услуги банков | D66: 2000 | E66: =C66+D66 -> 2000 | F66: =E66/$E$87 -> 0.00084284586 | G66: 0 | H66: 135.63 | I66: =G66+H66 -> 135.63 | J66: =I66/$N$87 -> 0.00066109249 | M66: 50.23 | N66: =L66+M66 -> 50.23 | O66: =N66/$N$87 -> 0.00024483282 | R66: 951.95 | S66: =Q66+R66 -> 951.95 | T66: =S66/$S$87 -> 0.0012824365 | W66: 305 | X66: =V66+W66 -> 305 | Y66: =X66/$X$87 -> 0.00031171529 | AA66: =G66+L66+Q66+V66 -> 0 | AB66: =H66+M66+R66+W66 -> 1442.81 | AC66: =AA66+AB66*1.15 -> 1659.2315 | AD66: =AC66/$AC$87 -> 0.00043416714 | AF66: =C66-AA66 -> 0 | AG66: =D66-AB66 -> 557.19 | AH66: =AF66+AG66*1.15 -> 640.7685 | AI66: =AH66/$AH$87 -> -0.00049224587
B67: Затраты на обучение персонала | E67: =C67+D67*1.15 -> 0 | F67: =E67/$E$87 -> 0 | I67: =G67+H67*1.15 -> 0 | J67: =I67/$E$87 -> 0 | N67: =L67+M67*1.15 -> 0 | O67: =N67/$E$87 -> 0 | S67: =Q67+R67*1.15 -> 0 | T67: =S67/$E$87 -> 0 | X67: =V67+W67*1.15 -> 0 | Y67: =X67/$E$87 -> 0 | AA67: =G67+L67+Q67+V67 -> 0 | AB67: =H67+M67+R67+W67 -> 0 | AC67: =AA67+AB67*1.15 -> 0 | AD67: =AC67/$AC$87 -> 0 | AF67: =C67-AA67 -> 0 | AG67: =D67-AB67 -> 0 | AH67: =AF67+AG67*1.15 -> 0 | AI67: =AH67/$E$87 -> 0
B68: Затраты по корпоративной культуре | E68: =C68+D68*1.15 -> 0 | F68: =E68/$E$87 -> 0 | I68: =G68+H68*1.15 -> 0 | J68: =I68/$E$87 -> 0 | N68: =L68+M68*1.15 -> 0 | O68: =N68/$E$87 -> 0 | S68: =Q68+R68*1.15 -> 0 | T68: =S68/$E$87 -> 0 | X68: =V68+W68*1.15 -> 0 | Y68: =X68/$E$87 -> 0 | AA68: =G68+L68+Q68+V68 -> 0 | AB68: =H68+M68+R68+W68 -> 0 | AC68: =AA68+AB68*1.15 -> 0 | AD68: =AC68/$AC$87 -> 0 | AF68: =C68-AA68 -> 0 | AG68: =D68-AB68 -> 0 | AH68: =AF68+AG68*1.15 -> 0 | AI68: =AH68/$E$87 -> 0
B69: Штраф | E69: =C69+D69*1.15 -> 0 | F69: =E69/$E$87 -> 0 | I69: =G69+H69*1.15 -> 0 | J69: =I69/$E$87 -> 0 | N69: =L69+M69*1.15 -> 0 | O69: =N69/$E$87 -> 0 | S69: =Q69+R69*1.15 -> 0 | T69: =S69/$E$87 -> 0 | X69: =V69+W69*1.15 -> 0 | Y69: =X69/$E$87 -> 0 | AA69: =G69+L69+Q69+V69 -> 0 | AB69: =H69+M69+R69+W69 -> 0 | AC69: =AA69+AB69*1.15 -> 0 | AD69: =AC69/$AC$87 -> 0 | AF69: =C69-AA69 -> 0 | AG69: =D69-AB69 -> 0 | AH69: =AF69+AG69*1.15 -> 0 | AI69: =AH69/$E$87 -> 0
F70: =E70/$E$87 -> 0 | J70: =I70/$E$87 -> 0 | O70: =N70/$E$87 -> 0 | T70: =S70/$E$87 -> 0 | Y70: =X70/$E$87 -> 0 | AA70: =G70+L70+Q70+V70 -> 0 | AB70: =H70+M70+R70+W70 -> 0 | AC70: =AA70+AB70*1.15 -> 0 | AD70: =AC70/$AC$87 -> 0 | AF70: =C70-AA70 -> 0 | AG70: =D70-AB70 -> 0 | AH70: =AF70+AG70*1.15 -> 0 | AI70: =AH70/$E$87 -> 0
B71: Налоги и сборы | C71: =C72 -> 0 | D71: =D72 -> 0 | E71: =E72 -> 0 | F71: =E71/$E$87 -> 0 | G71: =G72 -> 0 | H71: =H72 -> 0 | I71: =I72 -> 0 | J71: =I71/$E$87 -> 0 | L71: =L72 -> 0 | M71: =M72 -> 0 | N71: =N72 -> 0 | O71: =N71/$E$87 -> 0 | Q71: =Q72 -> 0 | R71: =R72 -> 0 | S71: =S72 -> 0 | T71: =S71/$E$87 -> 0 | V71: =V72 -> 0 | W71: =W72 -> 0 | X71: =X72 -> 0 | Y71: =X71/$E$87 -> 0 | AA71: =AA72 -> 0 | AB71: =AB72 -> 0 | AC71: =AC72 -> 0 | AF71: =C71-AA71 -> 0 | AG71: =D71-AB71 -> 0 | AH71: =AF71+AG71*1.15 -> 0 | AI71: =AH71/$E$87 -> 0
B72: НДС/ Прочие налоги | E72: =C72+D72 -> 0 | I72: =G72+H72 -> 0 | N72: =L72+M72 -> 0 | S72: =Q72+R72 -> 0 | X72: =V72+W72 -> 0 | AA72: =L72 -> 0 | AB72: =M72 -> 0 | AC72: =AA72+AB72 -> 0 | AF72: =C72-AA72 -> 0 | AG72: =D72-AB72 -> 0 | AH72: =AF72+AG72 -> 0
B73: Операционная прибыль, грн | C73: =C36-C39-C48-C52 -> 1653399.5 | D73: =D36-D39-D48-D52 -> -980031.28 | E73: =E36-E39-E48-E52 -> 673368.18 | G73: =G36-G39-G48-G52 -> -359488.67 | H73: =H36-H39-H48-H52 -> 673235.29 | I73: =I36-I39-I48-I52 -> 313746.62 | L73: =L36-L39-L48-L52 -> -116844.7 | M73: =M36-M39-M48-M52 -> -77479.23 | N73: =N36-N39-N48-N52 -> -194323.93 | Q73: =Q36-Q39-Q48-Q52 -> 518172.31 | R73: =R36-R39-R48-R52 -> -256506.95 | S73: =S36-S39-S48-S52 -> 261665.36 | V73: =V36-V39-V48-V52 -> 1120318.7 | W73: =W36-W39-W48-W52 -> -253869.22 | X73: =X36-X39-X48-X52 -> 866449.53 | AA73: =AA36-AA39-AA48-AA52 -> 1162157.7 | AB73: =AB36-AB39-AB48-AB52 -> 85379.89 | AC73: =AC36-AC39-AC48-AC52 -> 1078844.6 | AF73: =AF36-AF39-AF48-AF52 -> 491241.78 | AG73: =AG36-AG39-AG48-AG52 -> -1065411.2 | AH73: =AH36-AH39-AH48-AH52 -> -552481.07
B74: Операционная прибыль, % | C74: =C73/C5 -> 0.54275994 | D74: =D73/D5 -> #DIV/0! | E74: =E73/E5 -> 0.22104596 | G74: =G73/G5 -> -0.42714043 | H74: =H73/H5 -> 0.5563928 | I74: =I73/I5 -> 0.1529265 | L74: =L73/L5 -> #DIV/0! | M74: =M73/M5 -> #DIV/0! | N74: =N73/N5 -> #DIV/0! | Q74: =Q73/Q5 -> 0.51612675 | R74: =R73/R5 -> #DIV/0! | S74: =S73/S5 -> 0.26063239 | V74: =V73/V5 -> 0.61856429 | W74: =W73/W5 -> #DIV/0! | X74: =X73/X5 -> 0.47839486 | AA74: =AA73/AA5 -> 0.31781249 | AB74: =AB73/AB5 -> 0.070561893 | AC74: =AC73/AC5 -> 0.22167704 | AF74: =AF73/AF5 -> -0.80470914 | AG74: =AG73/AG5 -> 0.8805051 | AH74: =AH73/AH5 -> 0.30348452
B75: Финансовая деятельность | C75: =C76-C77 -> 0 | D75: =D76-D77 -> 0 | E75: =E76-E77 -> 0 | G75: =G76-G77 -> 0 | H75: =H76-H77 -> 0 | I75: =I76-I77 -> 0 | L75: =L76-L77 -> 0 | M75: =M76-M77 -> 0 | N75: =N76-N77 -> -10836.471 | Q75: =Q76-Q77 -> 0 | R75: =R76-R77 -> 0 | S75: =S76-S77 -> 0 | V75: =V76-V77 -> 0 | W75: =W76-W77 -> -29345 | X75: =X76-X77 -> -33746.75 | AA75: =AA76-AA77 -> 0 | AB75: =AB76-AB77 -> -29345 | AC75: =AC76-AC77 -> -33746.75 | AF75: =AF76-AF77 -> 0 | AG75: =AG76-AG77 -> 29345 | AH75: =AH76-AH77 -> 33746.75
B76: Финансовый доход | E76: =C76+D76*1.15 -> 0 | I76: =G76+H76*1.15 -> 0 | N76: =L76+M76*1.15 -> 0 | S76: =Q76+R76*1.15 -> 0 | X76: =V76+W76*1.15 -> 0
B77: Финансовые расходы | E77: =C77+D77*1.15 -> 0 | F77: =E77/$E$87 -> 0 | I77: =G77+H77*1.15 -> 0 | J77: =I77/$E$87 -> 0 | N77: =(M8+M39+M48+M52)/(1-'расчет 2020'!E4)*'расчет 2020'!E4 -> 10836.471 | O77: =N77/$E$87 -> 0.0045667372 | S77: =Q77+R77*1.15 -> 0 | T77: =S77/$E$87 -> 0 | W77: =7300+7300+14745 -> 29345 | X77: =V77+W77*1.15 -> 33746.75 | Y77: =X77/$X$87 -> 0.034489764 | AA77: =G77+L77+Q77+V77 -> 0 | AB77: =H77+M77+R77+W77 -> 29345 | AC77: =AA77+AB77*1.15 -> 33746.75 | AF77: =C77-AA77 -> 0 | AG77: =D77-AB77 -> -29345 | AH77: =AF77+AG77*1.15 -> -33746.75 | AI77: =AH77/$E$87 -> -0.014221654
B79: Прибыль после вычета финансовых затрат | C79: =(C73+C76)-C77 -> 1653399.5 | D79: =(D73+D76)-D77 -> -980031.28 | E79: =(E73+E76)-E77 -> 673368.18 | G79: =(G73+G76)-G77 -> -359488.67 | H79: =(H73+H76)-H77 -> 673235.29 | I79: =(I73+I76)-I77 -> 313746.62 | L79: =(L73+L76)-L77 -> -116844.7 | M79: =(M73+M76)-M77 -> -77479.23 | N79: =(N73+N76)-N77 -> -205160.4 | Q79: =(Q73+Q76)-Q77 -> 518172.31 | R79: =(R73+R76)-R77 -> -256506.95 | S79: =(S73+S76)-S77 -> 261665.36 | V79: =(V73+V76)-V77 -> 1120318.7 | W79: =(W73+W76)-W77 -> -283214.22 | X79: =(X73+X76)-X77 -> 832702.78 | AA79: =(AA73+AA76)-AA77 -> 1162157.7 | AB79: =(AB73+AB76)-AB77 -> 56034.89 | AC79: =(AC73+AC76)-AC77 -> 1045097.8 | AF79: =(AF73+AF76)-AF77 -> 491241.78 | AG79: =(AG73+AG76)-AG77 -> -1036066.2 | AH79: =(AH73+AH76)-AH77 -> -518734.32
B80: Затраты на налог на прибыль | E80: =C80+D80 -> 0 | F80: =E80/$E$87 -> 0 | I80: =G80+H80 -> 0 | J80: =I80/$E$87 -> 0 | N80: =L80+M80 -> 0 | O80: =N80/$E$87 -> 0 | S80: =Q80+R80 -> 0 | T80: =S80/$E$87 -> 0 | X80: =V80+W80 -> 0 | Y80: =X80/$E$87 -> 0 | AC80: =AA80+AB80 -> 0 | AH80: =AF80+AG80 -> 0 | AI80: =AH80/$E$87 -> 0
B81: Прибыль до вычета налогов | C81: =(C79+C7)-C34 -> 1653399.5 | D81: =(D79+D7)-D34 -> -980031.28 | E81: =(E79+E7)-E34 -> 673368.18 | G81: =(G79+G7)-G34 -> -359488.67 | H81: =(H79+H7)-H34 -> 673235.29 | I81: =(I79+I7)-I34 -> 313746.62 | L81: =(L79+L7)-L34 -> -116844.7 | M81: =(M79+M7)-M34 -> -77479.23 | N81: =(N79+N7)-N34 -> -205160.4 | Q81: =(Q79+Q7)-Q34 -> 518172.31 | R81: =(R79+R7)-R34 -> -256506.95 | S81: =(S79+S7)-S34 -> 261665.36 | V81: =(V79+V7)-V34 -> 1120318.7 | W81: =(W79+W7)-W34 -> -283214.22 | X81: =(X79+X7)-X34 -> 832702.78 | AA81: =(AA79+AA7)-AA34 -> 1162157.7 | AB81: =(AB79+AB7)-AB34 -> 56034.89 | AC81: =(AC79+AC7)-AC34 -> 1045097.8 | AF81: =(AF79+AF7)-AF34 -> 491241.78 | AG81: =(AG79+AG7)-AG34 -> -1036066.2 | AH81: =(AH79+AH7)-AH34 -> -518734.32
B82: Чистый доход | C82: =C81-C71-C80 -> 1653399.5 | D82: =D81-D71-D80 -> -980031.28 | E82: =E81-E71-E80 -> 673368.18 | G82: =G81-G71-G80 -> -359488.67 | H82: =H81-H71-H80 -> 673235.29 | I82: =I81-I71-I80 -> 313746.62 | L82: =L81-L71-L80 -> -116844.7 | M82: =M81-M71-M80 -> -77479.23 | N82: =N81-N71-N80 -> -205160.4 | Q82: =Q81-Q71-Q80 -> 518172.31 | R82: =R81-R71-R80 -> -256506.95 | S82: =S81-S71-S80 -> 261665.36 | V82: =V81-V71-V80 -> 1120318.7 | W82: =W81-W71-W80 -> -283214.22 | X82: =X81-X71-X80 -> 832702.78 | AA82: =AA81-AA71-AA80 -> 1162157.7 | AB82: =AB81-AB71-AB80 -> 56034.89 | AC82: =AC81-AC71-AC80 -> 1045097.8 | AF82: =AF81-AF71-AF80 -> 491241.78 | AG82: =AG81-AG71-AG80 -> -1036066.2 | AH82: =AH81-AH71-AH80 -> -518734.32
B83: Дивиденды | E83: =C83+D83 -> 0 | F83: =E83/$E$87 -> 0 | I83: =G83+H83 -> 0 | J83: =I83/$E$87 -> 0 | N83: =L83+M83 -> 0 | O83: =N83/$E$87 -> 0 | S83: =Q83+R83 -> 0 | T83: =S83/$E$87 -> 0 | X83: =V83+W83 -> 0 | Y83: =X83/$E$87 -> 0 | AA83: =L83 -> 0 | AB83: =M83 -> 0 | AC83: =AA83+AB83*1.15 -> 0 | AF83: =C83-AA83 -> 0 | AG83: =D83-AB83 -> 0 | AH83: =AF83+AG83*1.15 -> 0 | AI83: =AH83/$E$87 -> 0
B84: Прибыль в распоряжении компании (нераспределенная прибыль), грн | C84: =C82-C83 -> 1653399.5 | D84: =D82-D83 -> -980031.28 | E84: =E82-E83 -> 673368.18 | G84: =G82-G83 -> -359488.67 | H84: =H82-H83 -> 673235.29 | I84: =I82-I83 -> 313746.62 | L84: =L82-L83 -> -116844.7 | M84: =M82-M83 -> -77479.23 | N84: =N82-N83 -> -205160.4 | Q84: =Q82-Q83 -> 518172.31 | R84: =R82-R83 -> -256506.95 | S84: =S82-S83 -> 261665.36 | V84: =V82-V83 -> 1120318.7 | W84: =W82-W83 -> -283214.22 | X84: =X82-X83 -> 832702.78 | AA84: =AA82-AA83 -> 1162157.7 | AB84: =AB82-AB83 -> 56034.89 | AC84: =AC82-AC83 -> 1045097.8 | AF84: =AF82-AF83 -> 491241.78 | AG84: =AG82-AG83 -> -1036066.2 | AH84: =AH82-AH83 -> -518734.32
B85: Рентабельность продукции, % | C85: =C84/C5 -> 0.54275994 | D85: =D84/D5 -> #DIV/0! | E85: =E84/E5 -> 0.22104596 | G85: =G84/G5 -> -0.42714043 | H85: =H84/H5 -> 0.5563928 | I85: =I84/I5 -> 0.1529265 | L85: =L84/L5 -> #DIV/0! | M85: =M84/M5 -> #DIV/0! | N85: =N84/N5 -> #DIV/0! | Q85: =Q84/Q5 -> 0.51612675 | R85: =R84/R5 -> #DIV/0! | S85: =S84/S5 -> 0.26063239 | V85: =V84/V5 -> 0.61856429 | W85: =W84/W5 -> #DIV/0! | X85: =X84/X5 -> 0.45976219 | AA85: =AA84/AA5 -> 0.31781249 | AB85: =AB84/AB5 -> 0.046309826 | AC85: =AC84/AC5 -> 0.21474288 | AF85: =AF84/AF5 -> -0.80470914 | AG85: =AG84/AG5 -> 0.85625304 | AH85: =AH84/AH5 -> 0.28494702
B87: Итого затрат | E87: =E8+E34+E39+E48+E52+E71+E77+E80+E83 -> 2372913.1 | I87: =I8+I34+I39+I48+I52+I71+I77+I80+I83 -> 1737870.4 | N87: =N8+N34+N39+N48+N52+N71+N77+N80+N83 -> 205160.4 | S87: =S8+S34+S39+S48+S52+S71+S77+S80+S83 -> 742297.93 | X87: =X8+X34+X39+X48+X52+X71+X77+X80+X83 -> 978456.98 | AC87: =AC8+AC34+AC39+AC48+AC52+AC71+AC77+AC80+AC83 -> 3821642.3 | AH87: =AH8+AH34+AH39+AH48+AH52+AH71+AH77+AH80+AH83 -> -1301724.5

Sheet Печановка-2
A2: PL Печановка-2 | G2: Август 2023 | L2: Сентябрь 2023 | Q2: Накопительный PL объекта
A3: План итого
B4: Статья | C4: Сумма по Ф1, грн | D4: Сумма по Ф2, грн | E4: Сумма итого, грн | F4: % суммы затрат в общем объеме | G4: Сумма по Ф1, грн | H4: Сумма по Ф2, грн | I4: Сумма итого, грн | J4: % суммы затрат в общем объеме | K4: Комментарии | L4: Сумма по Ф1, грн | M4: Сумма по Ф2, грн | N4: Сумма итого, грн | O4: % суммы затрат в общем объеме | P4: Комментарии | Q4: Сумма по Ф1, грн | R4: Сумма по Ф2, грн | S4: Сумма итого, грн | T4: % суммы затрат в общем объеме | U4: Комментарии
B5: Операционный доход | C5: =C6 -> 0 | D5: =D6 -> 0 | E5: =E6 -> 0 | G5: =G6 -> 0 | H5: =H6 -> 0 | I5: =I6 -> 0 | L5: =SUM(L6:L7) -> 277178.11 | M5: =SUM(M6:M7) -> 0 | N5: =SUM(N6:N7) -> 277178.11 | Q5: =Q6+Q7 -> 277178.11 | R5: =R6+R7 -> 0 | S5: =S6+S7 -> 277178.11
B6: Выручка от продаж (товаров, работ, услуг) | E6: =C6+D6 -> 0 | I6: =G6+H6 -> 0 | K6: АГРОЛІДЕР СХІД ТОВ | L6: 277178.11 | N6: =L6+M6 -> 277178.11 | P6: АГРОЛІДЕР СХІД ТОВ | Q6: =G6+L6 -> 277178.11 | R6: =H6+M6 -> 0 | S6: =Q6+R6 -> 277178.11
B7: Доход от прочей операционной деятельности | E7: =C7+D7 -> 0 | I7: =G7+H7 -> 0 | N7: =L7+M7 -> 0 | Q7: =G7+L7 -> 0 | R7: =H7+M7 -> 0 | S7: =Q7+R7 -> 0
B8: Себестоимость проданой продукции (переменные производственные затраты) | C8: =SUM(C9:C33) -> 0 | D8: =SUM(D9:D33) -> 0 | E8: =SUM(E9:E33) -> 0 | F8: =E8/$E$89 -> #DIV/0! | G8: =SUM(G9:G33) -> 37527.2 | H8: =SUM(H9:H33) -> 0 | I8: =SUM(I9:I33) -> 37527.2 | J8: =I8/I$89 -> 0.9248939 | L8: =SUM(L9:L33) -> 0 | M8: =SUM(M9:M33) -> 74675 | N8: =SUM(N9:N33) -> 74675 | O8: =N8/N$89 -> 0.92133144 | Q8: =SUM(Q9:Q33) -> 37527.2 | R8: =SUM(R9:R33) -> 74675 | S8: =SUM(S9:S33) -> 112202.2 | T8: =S8/$S$89 -> 0.92251988
B9: ЗП производственного персонала | E9: =C9+D9 -> 0 | F9: =E9/$E$89 -> #DIV/0! | G9: 24761.8 | I9: =G9+H9*1 -> 24761.8 | J9: =I9/I$89 -> 0.61027835 | N9: =L9+M9*1 -> 0 | O9: =N9/N$89 -> 0 | Q9: =G9+L9 -> 24761.8 | R9: =H9+M9 -> 0 | S9: =Q9+R9*1 -> 24761.8 | T9: =S9/$S$89 -> 0.20359006
B10: Удержание с зарплаты производственного персонала | E10: =C10+D10 -> 0 | F10: =E10/$E$89 -> #DIV/0! | G10: 5998.2 | I10: =G10+H10*1 -> 5998.2 | J10: =I10/I$89 -> 0.1478314 | N10: =L10+M10*1 -> 0 | O10: =N10/N$89 -> 0 | Q10: =G10+L10 -> 5998.2 | R10: =H10+M10 -> 0 | S10: =Q10+R10*1 -> 5998.2 | T10: =S10/$S$89 -> 0.049316847
B11: Начисления на зарплату производственного персонала | E11: =C11+D11 -> 0 | F11: =E11/$E$89 -> #DIV/0! | G11: 6767.2 | I11: =G11+H11*1 -> 6767.2 | J11: =I11/I$89 -> 0.16678415 | N11: =L11+M11*1 -> 0 | O11: =N11/N$89 -> 0 | Q11: =G11+L11 -> 6767.2 | R11: =H11+M11 -> 0 | S11: =Q11+R11*1 -> 6767.2 | T11: =S11/$S$89 -> 0.05563952
B12: Зарплата ИТР | E12: =C12+D12 -> 0 | F12: =E12/$E$89 -> #DIV/0! | I12: =G12+H12*1 -> 0 | J12: =I12/I$89 -> 0 | N12: =L12+M12*1 -> 0 | O12: =N12/N$89 -> 0 | Q12: =G12+L12 -> 0 | R12: =H12+M12 -> 0 | S12: =Q12+R12*1 -> 0 | T12: =S12/$S$89 -> 0
B13: Удержание с зарплаты ИТР | E13: =C13+D13 -> 0 | F13: =E13/$E$89 -> #DIV/0! | I13: =G13+H13*1 -> 0 | J13: =I13/I$89 -> 0 | N13: =L13+M13*1 -> 0 | O13: =N13/N$89 -> 0 | Q13: =G13+L13 -> 0 | R13: =H13+M13 -> 0 | S13: =Q13+R13*1 -> 0 | T13: =S13/$S$89 -> 0
B14: Начисления на зарплату ИТР | E14: =C14+D14 -> 0 | F14: =E14/$E$89 -> #DIV/0! | I14: =G14+H14*1 -> 0 | J14: =I14/I$89 -> 0 | N14: =L14+M14*1 -> 0 | O14: =N14/N$89 -> 0 | Q14: =G14+L14 -> 0 | R14: =H14+M14 -> 0 | S14: =Q14+R14*1 -> 0 | T14: =S14/$S$89 -> 0
B15: ЗП подсобников | E15: =C15+D15 -> 0 | F15: =E15/$E$89 -> #DIV/0! | I15: =G15+H15*1 -> 0 | J15: =I15/I$89 -> 0 | N15: =L15+M15*1 -> 0 | O15: =N15/N$89 -> 0 | Q15: =G15+L15 -> 0 | R15: =H15+M15 -> 0 | S15: =Q15+R15*1 -> 0 | T15: =S15/$S$89 -> 0
B16: Оплата за выполненные работы | E16: =C16+D16 -> 0 | F16: =E16/$E$89 -> #DIV/0! | H16: =25395*0 -> 0 | I16: =G16+H16*1 -> 0 | J16: =I16/I$89 -> 0 | K16: Козеев - 25 395,0 - сентябрь | M16: 66133 | N16: =L16+M16*1 -> 66133 | O16: =N16/N$89 -> 0.81594124 | P16: Козеев | Q16: =G16+L16 -> 0 | R16: =H16+M16 -> 66133 | S16: =Q16+R16*1 -> 66133 | T16: =S16/$S$89 -> 0.54374163
B17: Премия производственного персонала | E17: =C17+D17 -> 0 | F17: =E17/$E$89 -> #DIV/0! | I17: =G17+H17*1 -> 0 | J17: =I17/I$89 -> 0 | N17: =L17+M17*1 -> 0 | O17: =N17/N$89 -> 0 | Q17: =G17+L17 -> 0 | R17: =H17+M17 -> 0 | S17: =Q17+R17*1 -> 0 | T17: =S17/$S$89 -> 0
B18: Услуги сторонних организаций | E18: =C18+D18 -> 0 | F18: =E18/$E$89 -> #DIV/0! | I18: =G18+H18*1 -> 0 | J18: =I18/I$89 -> 0 | N18: =L18+M18*1 -> 0 | O18: =N18/N$89 -> 0 | Q18: =G18+L18 -> 0 | R18: =H18+M18 -> 0 | S18: =Q18+R18*1 -> 0 | T18: =S18/$S$89 -> 0
B19: Аренда строительного оборудования | E19: =C19+D19 -> 0 | F19: =E19/$E$89 -> #DIV/0! | I19: =G19+H19*1 -> 0 | J19: =I19/I$89 -> 0 | N19: =L19+M19*1 -> 0 | O19: =N19/N$89 -> 0 | Q19: =G19+L19 -> 0 | R19: =H19+M19 -> 0 | S19: =Q19+R19*1 -> 0 | T19: =S19/$S$89 -> 0
B20: Аренда опалубки | E20: =C20+D20 -> 0 | F20: =E20/$E$89 -> #DIV/0! | I20: =G20+H20*1 -> 0 | J20: =I20/I$89 -> 0 | N20: =L20+M20*1 -> 0 | O20: =N20/N$89 -> 0 | Q20: =G20+L20 -> 0 | R20: =H20+M20 -> 0 | S20: =Q20+R20*1 -> 0 | T20: =S20/$S$89 -> 0
B21: Арена техники | E21: =C21+D21 -> 0 | F21: =E21/$E$89 -> #DIV/0! | I21: =G21+H21*1 -> 0 | J21: =I21/I$89 -> 0 | N21: =L21+M21*1 -> 0 | O21: =N21/N$89 -> 0 | Q21: =G21+L21 -> 0 | R21: =H21+M21 -> 0 | S21: =Q21+R21*1 -> 0 | T21: =S21/$S$89 -> 0
B22: Аренда сторонней техники | E22: =C22+D22 -> 0 | F22: =E22/$E$89 -> #DIV/0! | I22: =G22+H22*1 -> 0 | J22: =I22/I$89 -> 0 | N22: =L22+M22*1 -> 0 | O22: =N22/N$89 -> 0 | Q22: =G22+L22 -> 0 | R22: =H22+M22 -> 0 | S22: =Q22+R22*1 -> 0 | T22: =S22/$S$89 -> 0
B23: Аренда вагончика | E23: =C23+D23 -> 0 | F23: =E23/$E$89 -> #DIV/0! | I23: =G23+H23*1 -> 0 | J23: =I23/I$89 -> 0 | N23: =L23+M23*1 -> 0 | O23: =N23/N$89 -> 0 | Q23: =G23+L23 -> 0 | R23: =H23+M23 -> 0 | S23: =Q23+R23*1 -> 0 | T23: =S23/$S$89 -> 0
B24: Логистические затраты | E24: =C24+D24 -> 0 | F24: =E24/$E$89 -> #DIV/0! | I24: =G24+H24*1 -> 0 | J24: =I24/I$89 -> 0 | N24: =L24+M24*1 -> 0 | O24: =N24/N$89 -> 0 | Q24: =G24+L24 -> 0 | R24: =H24+M24 -> 0 | S24: =Q24+R24*1 -> 0 | T24: =S24/$S$89 -> 0
B25: МШП | E25: =C25+D25 -> 0 | F25: =E25/$E$89 -> #DIV/0! | I25: =G25+H25*1 -> 0 | J25: =I25/I$89 -> 0 | N25: =L25+M25*1 -> 0 | O25: =N25/N$89 -> 0 | Q25: =G25+L25 -> 0 | R25: =H25+M25 -> 0 | S25: =Q25+R25*1 -> 0 | T25: =S25/$S$89 -> 0
B26: Строительные материалы | E26: =C26+D26 -> 0 | F26: =E26/$E$89 -> #DIV/0! | I26: =G26+H26*1 -> 0 | J26: =I26/I$89 -> 0 | N26: =L26+M26*1 -> 0 | O26: =N26/N$89 -> 0 | Q26: =G26+L26 -> 0 | R26: =H26+M26 -> 0 | S26: =Q26+R26*1 -> 0 | T26: =S26/$S$89 -> 0
B27: Ремонты | E27: =C27+D27 -> 0 | F27: =E27/$E$89 -> #DIV/0! | I27: =G27+H27*1 -> 0 | J27: =I27/I$89 -> 0 | N27: =L27+M27*1 -> 0 | O27: =N27/N$89 -> 0 | Q27: =G27+L27 -> 0 | R27: =H27+M27 -> 0 | S27: =Q27+R27*1 -> 0 | T27: =S27/$S$89 -> 0
B28: Прочие производственные затраты | E28: =C28+D28 -> 0 | F28: =E28/$E$89 -> #DIV/0! | I28: =G28+H28*1 -> 0 | J28: =I28/I$89 -> 0 | N28: =L28+M28*1 -> 0 | O28: =N28/N$89 -> 0 | Q28: =G28+L28 -> 0 | R28: =H28+M28 -> 0 | S28: =Q28+R28*1 -> 0 | T28: =S28/$S$89 -> 0
B29: Командировочные производственного персонала | E29: =C29+D29 -> 0 | F29: =E29/$E$89 -> #DIV/0! | I29: =G29+H29*1 -> 0 | J29: =I29/I$89 -> 0 | M29: 742 | N29: =L29+M29*1 -> 742 | O29: =N29/N$89 -> 0.0091547094 | Q29: =G29+L29 -> 0 | R29: =H29+M29 -> 742 | S29: =Q29+R29*1 -> 742 | T29: =S29/$S$89 -> 0.0061006803
B30: Аренда квартиры с коммунальными платежами | E30: =C30+D30 -> 0 | F30: =E30/$E$89 -> #DIV/0! | I30: =G30+H30*1 -> 0 | J30: =I30/I$89 -> 0 | M30: 7800 | N30: =L30+M30*1 -> 7800 | O30: =N30/N$89 -> 0.09623549 | Q30: =G30+L30 -> 0 | R30: =H30+M30 -> 7800 | S30: =Q30+R30*1 -> 7800 | T30: =S30/$S$89 -> 0.064131141
B31: Транспортные затраты производственного персонала | E31: =C31+D31 -> 0 | F31: =E31/$E$89 -> #DIV/0! | I31: =G31+H31*1 -> 0 | J31: =I31/I$89 -> 0 | N31: =L31+M31*1 -> 0 | O31: =N31/N$89 -> 0 | Q31: =G31+L31 -> 0 | R31: =H31+M31 -> 0 | S31: =Q31+R31*1 -> 0 | T31: =S31/$S$89 -> 0
B32: Разрешительная документация | E32: =C32+D32 -> 0 | F32: =E32/$E$89 -> #DIV/0! | I32: =G32+H32*1 -> 0 | J32: =I32/I$89 -> 0 | N32: =L32+M32*1 -> 0 | O32: =N32/N$89 -> 0 | Q32: =G32+L32 -> 0 | R32: =H32+M32 -> 0 | S32: =Q32+R32*1 -> 0 | T32: =S32/$S$89 -> 0
B33: Представительские затраты | E33: =C33+D33 -> 0 | F33: =E33/$E$89 -> #DIV/0! | I33: =G33+H33*1 -> 0 | J33: =I33/I$89 -> 0 | N33: =L33+M33*1 -> 0 | O33: =N33/N$89 -> 0 | Q33: =G33+L33 -> 0 | R33: =H33+M33 -> 0 | S33: =Q33+R33*1 -> 0 | T33: =S33/$S$89 -> 0
B35: Дополнительные расходы | C35: =C36 -> 0 | D35: =D36 -> 0 | E35: =E36 -> 0 | F35: =E35/$E$89 -> #DIV/0! | I35: =I36 -> 0 | J35: =I35/I$89 -> 0 | N35: =N36 -> 0 | O35: =N35/N$89 -> 0 | Q35: =Q36 -> 0 | R35: =R36 -> 0 | S35: =S36 -> 0 | T35: =T36 -> 0
B36: Расход от ивест. Деятельности (ОС) | E36: =C36+D36 -> 0 | F36: =E36/$E$89 -> #DIV/0! | I36: =G36+H36*1 -> 0 | J36: =I36/I$89 -> 0 | N36: =L36+M36*1 -> 0 | O36: =N36/N$89 -> 0 | Q36: =G36+L36 -> 0 | R36: =H36+M36 -> 0 | S36: =Q36+R36*1 -> 0 | T36: =S36/$S$89 -> 0
O37: =N37/$AN$89 -> #DIV/0!
B38: Маржинальный доход, грн | C38: =(C5)-(C8) -> 0 | D38: =(D5)-(D8) -> 0 | E38: =(E5)-(E8) -> 0 | G38: =(G5)-(G8) -> -37527.2 | H38: =(H5)-(H8) -> 0 | I38: =(I5)-(I8) -> -37527.2 | L38: =(L5)-(L8) -> 277178.11 | M38: =(M5)-(M8) -> -74675 | N38: =(N5)-(N8) -> 202503.11 | Q38: =(Q5)-(Q8) -> 239650.91 | R38: =(R5)-(R8) -> -74675 | S38: =(S5)-(S8) -> 164975.91
B39: Маржинальный доход, % | C39: =C38/(C5) -> #DIV/0! | D39: =D38/(D5) -> #DIV/0! | E39: =E38/(E5) -> #DIV/0! | G39: =G38/(G5) -> #DIV/0! | H39: =H38/(H5) -> #DIV/0! | I39: =I38/(I5) -> #DIV/0! | L39: =L38/(L5) -> 1 | M39: =M38/(M5) -> #DIV/0! | N39: =N38/(N5) -> 0.73058839 | Q39: =Q38/(Q5) -> 0.8646098 | R39: =R38/(R5) -> #DIV/0! | S39: =S38/(S5) -> 0.59519819
B41: Общепроизводственные затраты | C41: =SUM(C42:C48) -> 0 | D41: =SUM(D42:D48) -> 0 | E41: =SUM(E42:E48) -> 0 | F41: =E41/$E$89 -> #DIV/0! | G41: =SUM(G42:G48) -> 0 | H41: =SUM(H42:H48) -> 0 | I41: =SUM(I42:I48) -> 0 | J41: =I41/I$89 -> 0 | L41: =SUM(L42:L48) -> 462.58 | M41: =SUM(M42:M48) -> 0 | N41: =SUM(N42:N48) -> 462.58 | O41: =N41/N$89 -> 0.0057072581 | Q41: =SUM(Q42:Q48) -> 462.58 | R41: =SUM(R42:R48) -> 0 | S41: =SUM(S42:S48) -> 462.58 | T41: =S41/$S$89 -> 0.0038033055
B42: Благоустройство офиса | E42: =C42+D42 -> 0 | F42: =E42/$E$89 -> #DIV/0! | I42: =G42+H42*1 -> 0 | J42: =I42/I$89 -> 0 | N42: =L42+M42*1 -> 0 | O42: =N42/N$89 -> 0 | Q42: =G42+L42 -> 0 | R42: =H42+M42 -> 0 | S42: =Q42+R42*1 -> 0 | T42: =S42/$S$89 -> 0
B43: Хозтовары и материалы | E43: =C43+D43 -> 0 | F43: =E43/$E$89 -> #DIV/0! | I43: =G43+H43*1 -> 0 | J43: =I43/I$89 -> 0 | N43: =L43+M43*1 -> 0 | O43: =N43/N$89 -> 0 | Q43: =G43+L43 -> 0 | R43: =H43+M43 -> 0 | S43: =Q43+R43*1 -> 0 | T43: =S43/$S$89 -> 0
B44: ИТ расходы | E44: =C44+D44 -> 0 | F44: =E44/$E$89 -> #DIV/0! | I44: =G44+H44*1 -> 0 | J44: =I44/I$89 -> 0 | N44: =L44+M44*1 -> 0 | O44: =N44/N$89 -> 0 | Q44: =G44+L44 -> 0 | R44: =H44+M44 -> 0 | S44: =Q44+R44*1 -> 0 | T44: =S44/$S$89 -> 0
B45: Питьевая вода | E45: =C45+D45 -> 0 | F45: =E45/$E$89 -> #DIV/0! | I45: =G45+H45*1 -> 0 | J45: =I45/I$89 -> 0 | N45: =L45+M45*1 -> 0 | O45: =N45/N$89 -> 0 | Q45: =G45+L45 -> 0 | R45: =H45+M45 -> 0 | S45: =Q45+R45*1 -> 0 | T45: =S45/$S$89 -> 0
B46: Охрана офиса и пожарная сигнализация | E46: =C46+D46 -> 0 | F46: =E46/$E$89 -> #DIV/0! | I46: =G46+H46*1 -> 0 | J46: =I46/I$89 -> 0 | N46: =L46+M46*1 -> 0 | O46: =N46/N$89 -> 0 | Q46: =G46+L46 -> 0 | R46: =H46+M46 -> 0 | S46: =Q46+R46*1 -> 0 | T46: =S46/$S$89 -> 0
B47: Курьерские и почтовые | E47: =C47+D47 -> 0 | F47: =E47/$E$89 -> #DIV/0! | I47: =G47+H47*1 -> 0 | J47: =I47/I$89 -> 0 | L47: 462.58 | N47: =L47+M47*1 -> 462.58 | O47: =N47/N$89 -> 0.0057072581 | Q47: =G47+L47 -> 462.58 | R47: =H47+M47 -> 0 | S47: =Q47+R47*1 -> 462.58 | T47: =S47/$S$89 -> 0.0038033055
B48: Канцтовары | E48: =C48+D48 -> 0 | F48: =E48/$E$89 -> #DIV/0! | I48: =G48+H48*1 -> 0 | J48: =I48/I$89 -> 0 | N48: =L48+M48*1 -> 0 | O48: =N48/N$89 -> 0 | Q48: =G48+L48 -> 0 | R48: =H48+M48 -> 0 | S48: =Q48+R48*1 -> 0 | T48: =S48/$S$89 -> 0
T49: =S49/$S$89 -> 0
B50: Маркетинговые затраты | C50: =SUM(C51:C52) -> 0 | D50: =SUM(D51:D52) -> 0 | E50: =SUM(E51:E52) -> 0 | F50: =E50/$E$89 -> #DIV/0! | G50: =G52+G51 -> 0 | H50: =H52+H51 -> 0 | I50: =SUM(I51:I52) -> 0 | J50: =I50/I$89 -> 0 | L50: =L52+L51 -> 0 | M50: =M52+M51 -> 0 | N50: =SUM(N51:N52) -> 0 | O50: =N50/N$89 -> 0 | Q50: =Q52+Q51 -> 0 | R50: =R52+R51 -> 0 | S50: =SUM(S51:S52) -> 0
B51: Реклама | E51: =C51+D51 -> 0 | F51: =E51/$E$89 -> #DIV/0! | I51: =G51+H51*1 -> 0 | J51: =I51/I$89 -> 0 | N51: =L51+M51*1 -> 0 | O51: =N51/N$89 -> 0 | Q51: =G51+L51 -> 0 | R51: =H51+M51 -> 0 | S51: =Q51+R51*1 -> 0 | T51: =S51/$S$89 -> 0
B52: Прочие маркетинговые затраты | E52: =C52+D52 -> 0 | F52: =E52/$E$89 -> #DIV/0! | I52: =G52+H52*1 -> 0 | J52: =I52/I$89 -> 0 | N52: =L52+M52*1 -> 0 | O52: =N52/N$89 -> 0 | Q52: =G52+L52 -> 0 | R52: =H52+M52 -> 0 | S52: =Q52+R52*1 -> 0 | T52: =S52/$S$89 -> 0
B54: Административные затраты | C54: =SUM(C55:C71) -> 0 | D54: =SUM(D55:D71) -> 0 | E54: =SUM(E55:E71) -> 0 | F54: =E54/$E$89 -> #DIV/0! | G54: =SUM(G55:G72) -> 0 | H54: =SUM(H55:H72) -> 0 | I54: =SUM(I55:I72) -> 0 | J54: =I54/I$89 -> 0 | L54: =SUM(L55:L72) -> 0 | M54: =SUM(M55:M72) -> 0 | N54: =SUM(N55:N72) -> 0 | O54: =N54/N$89 -> 0 | Q54: =SUM(Q55:Q72) -> 0 | R54: =SUM(R55:R72) -> 0 | S54: =SUM(S55:S72) -> 0 | T54: =S54/$S$89 -> 0
