Workbook

Sheet СВОД
B2: Доходы - акты выполненных работ
B3: № АВР | C3: Примечания | D3: Сумма | E3: Сумма, грн
E4: Апрель (закроются в мае) | H4: Май
E5: Сумма | F5: ф1 | G5: ф2 | H5: Сумма | I5: ф1 | J5: ф2
B6: ='АВР травень'!E7 -> 12 | C6: ='АВР травень'!M7 -> Розробка котловану ВУХО. Зворотня засипка 10-19 | D6: ='АВР травень'!I7 -> 1266503 | E6: =SUM(F6:G6) -> 1266503 | F6: =D6 -> 1266503 | H6: =SUM(I6:J6) -> 0
C7: Зворотня засипка 10-19 съёмка №2 | D7: 531791 | E7: =SUM(F7:G7) -> 531791 | F7: =D7 -> 531791 | H7: =SUM(I7:J7) -> 0
B8: ='АВР травень'!E8 -> 26 | C8: ='АВР травень'!M8 -> стіни підвалу | D8: ='АВР травень'!I8 -> 3760428 | E8: =SUM(F8:G8) -> 3760428 | F8: =D8 -> 3760428 | H8: =SUM(I8:J8) -> 0
B9: ='АВР травень'!E9 -> 27 | C9: ='АВР травень'!M9 -> гідроізоляція ст.фундаментів | D9: ='АВР травень'!I9 -> 105069.23 | E9: =SUM(F9:G9) -> 105069.23 | F9: =D9 -> 105069.23 | H9: =SUM(I9:J9) -> 0
B10: ='АВР травень'!E10 -> 28 | C10: бетонирование стен 3я захватка | D10: ='АВР травень'!I10 -> 3718814.2 | E10: =SUM(F10:G10) -> 0 | H10: =SUM(I10:J10) -> 3718814.2 | I10: =D10 -> 3718814.2
B11: ='АВР травень'!E11 -> 3 | C11: ='АВР травень'!B11 -> Гідроізоляція котловану | D11: ='АВР травень'!I11 -> 715575.3 | E11: =SUM(F11:G11) -> 357787.65 | F11: =I11 -> 357787.65 | H11: =SUM(I11:J11) -> 357787.65 | I11: =D11/2 -> 357787.65
B12: ='АВР травень'!E12 -> 7 | C12: ='АВР травень'!M12 -> водозниження | D12: ='АВР травень'!I12 -> 472322.34 | E12: =SUM(F12:G12) -> 472322.34 | F12: =D12 -> 472322.34 | H12: =SUM(I12:J12) -> 0
B13: ='АВР травень'!E13 -> 1 | C13: ='АВР травень'!M13 -> каналізація в плиті | D13: ='АВР травень'!I13 -> 98309.75 | E13: =SUM(F13:G13) -> 98309.75 | F13: =D13 -> 98309.75 | H13: =SUM(I13:J13) -> 0
B14: ='АВР травень'!E14 -> 1 | C14: ='АВР травень'!M14 -> зворотня засипка піском | D14: ='АВР травень'!I14 -> 836792.11 | E14: =SUM(F14:G14) -> 836792.11 | F14: =D14 -> 836792.11 | H14: =SUM(I14:J14) -> 0
B15: ='АВР травень'!E15 -> 1 | C15: ='АВР травень'!M15 -> водозниження (вухо) | D15: ='АВР травень'!I15 -> 233757.78 | E15: =SUM(F15:G15) -> 233757.78 | F15: =D15 -> 233757.78 | H15: =SUM(I15:J15) -> 0
B16: ='АВР травень'!E16 -> 1 | C16: ='АВР травень'!M16 -> бентонвтовий шнур | D16: ='АВР травень'!I16 -> 36249.65 | E16: =SUM(F16:G16) -> 36249.65 | F16: =D16 -> 36249.65 | H16: =SUM(I16:J16) -> 0
B17: ='АВР травень'!E17 -> 1 | C17: ='АВР травень'!M17 -> гідрошпонка | D17: ='АВР травень'!I17 -> 98455.63 | E17: =SUM(F17:G17) -> 98455.63 | F17: =D17 -> 98455.63 | H17: =SUM(I17:J17) -> 0
B18: ИТОГО | D18: =SUM(D6:D17) -> 11874068 | E18: =SUM(E6:E17) -> 7797466.2 | F18: =SUM(F6:F17) -> 7797466.2 | G18: =SUM(G6:G17) -> 0 | H18: =SUM(H6:H17) -> 4076601.9 | I18: =SUM(I6:I17) -> 4076601.9 | J18: =SUM(J6:J17) -> 0 | K18: =D18-F18-G18-I18-J18 -> 4.6566129e-10
B20: Затраты
B21: № | C21: Примечания | D21: Сумма | E21: Сумма, грн
E22: Апрель (закроются в мае) | H22: Май
E23: Сумма | F23: ф1 | G23: ф2 | H23: Сумма | I23: ф1 | J23: ф2
B24: 1 | C24: Услуги сторонних организаций | D24: =E24+H24 -> 445855.26 | E24: =SUM(F24:G24) -> 445855.26 | F24: =115137.1+330718.16 -> 445855.26 | H24: =SUM(I24:J24) -> 0
B25: 2 | C25: Транспортные затраты | D25: =E25+H25 -> 57100 | E25: =SUM(F25:G25) -> 0 | H25: =SUM(I25:J25) -> 57100 | I25: =2000+6500+7100+7100+5500+3600+1800+9500+5500+8500 -> 57100 | K25: * доставка опалубки и прочие транспортные
B26: 3 | C26: Строительные материалы | D26: =E26+H26 -> 4934662.6 | E26: =SUM(F26:G26) -> 2826724.9 | F26: =('АВР травень'!K8+'АВР травень'!K9+'АВР травень'!K12+'АВР травень'!K13+'АВР травень'!K14+'АВР травень'!K15+'АВР травень'!K16+'АВР травень'!K17)*0.92+'АВР травень'!K11/2*0.92 -> 2826724.9 | H26: =SUM(I26:J26) -> 2107937.7 | I26: =('АВР травень'!K10+'АВР травень'!K11/2)*0.92 -> 2107937.7
B27: 4 | C27: Строит. мат-лы (потеряны) | D27: =E27+H27 -> 135000 | E27: =SUM(F27:G27) -> 135000 | F27: 135000 | H27: =SUM(I27:J27) -> 0 | K27: *щебень
B28: 5 | C28: Оплата за выполненные работы | D28: =E28+H28 -> 471558.63 | E28: =SUM(F28:G28) -> 118495 | G28: ='АВР травень'!N9+'АВР травень'!N11/2+'АВР травень'!N13+'АВР травень'!N16+'АВР травень'!N17 -> 118495 | H28: =SUM(I28:J28) -> 353063.63 | J28: ='АВР травень'!N10+'АВР травень'!N11/2 -> 353063.63
B29: 6 | C29: Аренда техники | D29: =E29+H29 -> 1054306 | E29: =SUM(F29:G29) -> 0 | H29: =SUM(I29:J29) -> 1054306 | I29: 1054306
B30: 7 | C30: Аренда сторонней техники | D30: =E30+H30 -> 267700 | E30: =SUM(F30:G30) -> 0 | H30: =SUM(I30:J30) -> 267700 | I30: =177600+4500+67600+18000 -> 267700
B31: 8 | C31: Аренда опалубки | D31: =E31+H31 -> 733000 | E31: =SUM(F31:G31) -> 0 | H31: =SUM(I31:J31) -> 733000 | I31: =22600*25+5600*30 -> 733000
B32: 9 | C32: ЗП ИТР | D32: =E32+H32 -> 234320 | E32: =SUM(F32:G32) -> 0 | H32: =SUM(I32:J32) -> 234320 | I32: 83020 | J32: 151300 | K32: * с начислениями и удержаниями
B33: 10 | C33: ЗП РМ | D33: =E33+H33 -> 63480 | E33: =SUM(F33:G33) -> 0 | H33: =SUM(I33:J33) -> 63480 | I33: 19580 | J33: 43900 | K33: * с начислениями и удержаниями
B34: 11 | C34: Аренда квартиры+коммун | D34: =E34+H34 -> 86900 | E34: =SUM(F34:G34) -> 0 | H34: =SUM(I34:J34) -> 86900 | J34: 86900
B35: 12 | C35: ЗП подсобников | D35: =E35+H35 -> 234000 | E35: =SUM(F35:G35) -> 0 | H35: =SUM(I35:J35) -> 234000 | J35: 234000
B36: 13 | C36: Суточные | D36: =E36+H36 -> 20150 | E36: =SUM(F36:G36) -> 0 | H36: =SUM(I36:J36) -> 20150 | I36: 20150
B37: 14 | C37: ГСМ | D37: =E37+H37 -> 39000 | E37: =SUM(F37:G37) -> 0 | H37: =SUM(I37:J37) -> 39000 | I37: =15000+24000 -> 39000 | K37: * бензоинструмент + ГСМ РМ и ИТР
B38: 6 | C38: Комиссия Фин. (13%) | D38: =E38+H38 -> 174292.7 | E38: =SUM(F38:G38) -> 20910.882 | G38: =SUM(G24:G37)/(1-15%)*15% -> 20910.882 | H38: =SUM(I38:J38) -> 153381.82 | J38: =SUM(J24:J37)/(1-15%)*15% -> 153381.82
B39: ИТОГО | D39: =SUM(D24:D38) -> 8951325.1 | E39: =SUM(E24:E38) -> 3546986.1 | F39: =SUM(F24:F38) -> 3407580.2 | G39: =SUM(G24:G38) -> 139405.88 | H39: =SUM(H24:H38) -> 5404339.1 | I39: =SUM(I24:I38) -> 4381793.6 | J39: =SUM(J24:J38) -> 1022545.4 | K39: =D39-F39-G39-I39-J39 -> 0
B41: МАРЖА (План) | D41: =D18-D39 -> 2922742.9 | E41: =E18-E39 -> 4250480.1 | F41: =F18-F39 -> 4389886 | G41: =G18-G39 -> -139405.88 | H41: =H18-H39 -> -1327737.2 | I41: =I18-I39 -> -305191.77 | J41: =J18-J39 -> -1022545.4 | K41: =D41-F41-G41-I41-J41 -> 1.6298145e-09
B43: PL Апрель 24 | E43: -3292448.9
B45: МАРЖА итог | E45: =E41+E43 -> 958031.15

Sheet АВР травень
A2: Реєстр актів виконаних робіт по об'єкту "Нове будівництво виробничого комплексу центру передових технологій в с.Крушинка, Фастівського району, Київської області"
B4: Найменування договірної ціни | C4: Договірна ціна | E4: №, період, статус 2023 р. | H4: ТОВ "ІНДАСТРІАЛБУД"
C6: № ДЦ | D6: Сумма ДЦ | E6: № акта | F6: сума, грн з ПДВ | G6: статус | I6: всього | J6: робота | K6: мат-ли | N6: РАБОТЫ
B7: Земляні роботи | C7: №1 | D7: 20014627 | E7: 12 | F7: 1266503 | G7: готується документація | H7: 12 | I7: =F7 -> 1266503 | J7: =I7-K7 -> 1266503 | K7: 0 | M7: Розробка котловану ВУХО. Зворотня засипка 10-19
B8: Конструкції залізобетонні | C8: №1 | D8: 1.6290261e+08 | E8: 26 | F8: 3760428 | G8: тн замовника | H8: 26 | I8: =F8 -> 3760428 | J8: =I8-K8 -> 1775879.8 | K8: 1984548.2 | L8: 45413 | M8: стіни підвалу
E9: 27 | F9: 105069.23 | G9: тн замовника | H9: 27 | I9: =F9 -> 105069.23 | J9: =I9-K9 -> 48094.12 | K9: 56975.11 | L9: 17травня | M9: гідроізоляція ст.фундаментів | N9: 9000
E10: 28 | F10: 3718814.2 | G10: готується документація | H10: 28 | I10: =F10 -> 3718814.2 | J10: =I10-K10 -> 1677769.6 | K10: 2041044.6 | N10: 276568.63
B11: Гідроізоляція котловану | C11: № F-20231127-1 | D11: 11216410 | E11: 3 | F11: 715575.3 | G11: готується документація | H11: 3 | I11: =F11 -> 715575.3 | J11: =I11-K11 -> 215191.3 | K11: 500384 | N11: 152990 | O11: бц
B12: Водозниження | C12: №2 | D12: 1479619.4 | E12: 7 | F12: 472322.34 | G12: оригінал на підпис у замовника | H12: 7 | I12: =F12 -> 472322.34 | J12: =I12-K12 -> 449708.22 | K12: 22614.12 | L12: 45412 | M12: водозниження
A13: 4 | B13: Каналізація (в плиті) | C13: №3 | D13: 98309.75 | E13: 1 | F13: =D13 -> 98309.75 | G13: тн замовника | H13: 1 | I13: =F13 -> 98309.75 | J13: =I13-K13 -> 42182.08 | K13: 56127.67 | L13: 45432 | M13: каналізація в плиті | N13: 18000
A14: 8 | B14: Зворотня засипка піском | C14: №7 | D14: 1907190.8 | E14: 1 | F14: 836792.11 | G14: тн замовника | H14: 1 | I14: =F14 -> 836792.11 | J14: =I14-K14 -> 227573.6 | K14: 609218.51 | L14: 17 травня | M14: зворотня засипка піском
A15: 9 | B15: Водозниження (ВУХО) | C15: №8 | D15: 554589.34 | E15: 1 | F15: 233757.78 | G15: оригінал на підпис у замовника | H15: 1 | I15: 233757.78 | J15: =I15-K15 -> 225075.77 | K15: 8682.01 | L15: 45412 | M15: водозниження (вухо)
A16: 10 | B16: Армування підбетонки; Двері; Бентонітовий шнур | C16: №9 | D16: 205250.65 | E16: 1 | F16: 36249.65 | G16: кошторисник замовника | H16: 1 | I16: =F16 -> 36249.65 | J16: =I16-K16 -> 21207.086 | K16: 15042.564 | L16: 17 травня | M16: бентонвтовий шнур | N16: 10000
A17: 14 | B17: Гідрошпонка | C17: ДУ№2 | D17: 164975.04 | E17: 1 | F17: 98455.63 | G17: кошторисник замовника | H17: 1 | I17: =F17 -> 98455.63 | J17: =I17-K17 -> 29328.718 | K17: 69126.912 | M17: гідрошпонка | N17: 5000
B18: ВСЬОГО: | D18: =SUM(D8:D17) -> 1.7852896e+08 | F18: =SUM(F7:F17) -> 11342277 | I18: =SUM(I7:I17) -> 11342277 | J18: =SUM(J7:J17) -> 5978513.3 | K18: =SUM(K7:K17) -> 5363763.7 | N18: =SUM(N7:N17) -> 471558.63
K19: =K18*0.92-СВОД!D26 -> 0 | N19: =N18-СВОД!D28 -> 0

Sheet Субподряд
A1: Дата | B1: Номер | C1: Вид операції | D1: Сума | E1: Валюта | F1: Склад | G1: Контрагент | H1: Дата вх. | I1: Номер вх. | J1: Договір | K1: Документ розрахунків | L1: Організація | M1: Відповідальний | N1: Коментар
A2: 30.11.2023 19:00:00 | B2: ІБ00-001841 | C2: Покупка, комісія | D2: 225572.6 | E2: грн | F2: Крушинка | G2: ДНІПРО АКВАБУД ІНВЕСТ | H2: 30.11.2023 | I2: Акт 1 | J2: Договір №12/09 від 12.09.2023 Крушинка | K2: Рахунок на оплату постачальника ІБ00-000432 от 15.09.2023 18:08:03 | L2: ТОВ "ІНДАСТРІАЛБУД" | M2: Хлань Елена
A3: 30.11.2023 19:00:00 | B3: ІБ00-001842 | C3: Покупка, комісія | D3: 152858.76 | E3: грн | F3: Крушинка | G3: ДНІПРО АКВАБУД ІНВЕСТ | H3: 30.11.2023 | I3: Акт 2 | J3: Договір №12/09 від 12.09.2023 Крушинка | K3: Рахунок на оплату постачальника ІБ00-000432 от 15.09.2023 18:08:03 | L3: ТОВ "ІНДАСТРІАЛБУД" | M3: Хлань Елена | N3: АКТ 2
A4: 30.11.2023 19:00:00 | B4: ІБ00-001843 | C4: Покупка, комісія | D4: 167820.77 | E4: грн | F4: Крушинка | G4: ДНІПРО АКВАБУД ІНВЕСТ | H4: 30.11.2023 | I4: Акт 3 | J4: Договір №12/09 від 12.09.2023 Крушинка | K4: Рахунок на оплату постачальника ІБ00-000432 от 15.09.2023 18:08:03 | L4: ТОВ "ІНДАСТРІАЛБУД" | M4: Хлань Елена
A5: 25.12.2023 10:36:50 | B5: ІБ00-002154 | C5: Покупка, комісія | D5: 367828.66 | E5: грн | F5: Крушинка | G5: ДНІПРО АКВАБУД ІНВЕСТ | H5: 25.12.2023 | I5: Акт 4 | J5: Договір №12/09 від 12.09.2023 Крушинка | K5: Рахунок на оплату постачальника ІБ00-000432 от 15.09.2023 18:08:03 | L5: ТОВ "ІНДАСТРІАЛБУД" | M5: Хлань Елена
A6: 26.01.2024 17:45:29 | B6: ІБ00-000281 | C6: Покупка, комісія | D6: 348055.43 | E6: грн | F6: Крушинка | G6: ДНІПРО АКВАБУД ІНВЕСТ | H6: 26.01.2024 | I6: Акт 5 | J6: Дог№12/09 від 12.09.23 ДУ1_661 044,29_Крушинка | K6: Рахунок на оплату постачальника ІБ00-000314 от 26.01.2024 17:45:34 | L6: ТОВ "ІНДАСТРІАЛБУД" | M6: Шостак Жанета
A7: 28.02.2024 17:11:38 | B7: ІБ00-000725 | C7: Покупка, комісія | D7: 331224.06 | E7: грн | F7: Крушинка | G7: ДНІПРО АКВАБУД ІНВЕСТ | H7: 28.02.2024 | I7: Акт 6 | J7: Дог№12/09 від 12.09.23 ДУ1_661 044,29_Крушинка | K7: Рахунок на оплату постачальника ІБ00-000314 от 26.01.2024 17:45:34 | L7: ТОВ "ІНДАСТРІАЛБУД" | M7: Хлань Елена
A8: 29.03.2024 22:00:02 | B8: ІБ00-001324 | C8: Покупка, комісія | D8: 293561.58 | E8: грн | F8: Крушинка | G8: ДНІПРО АКВАБУД ІНВЕСТ | H8: 29.03.2024 | I8: Акт 7 | J8: Дог№12/09 від 12.09.23 ДУ1_661 044,29_Крушинка | K8: Рахунок на оплату постачальника ІБ00-000314 от 26.01.2024 17:45:34 | L8: ТОВ "ІНДАСТРІАЛБУД" | M8: Хлань Елена
