Workbook
Name Excel_BuiltIn_Print_Area_4: "#REF!"
Name Excel_BuiltIn_Print_Area_4_1: "#REF!"
Name Excel_BuiltIn_Print_Area_7: "#REF!"
Name Excel_BuiltIn_Print_Area_7_1: "#REF!"
Name Механизаторі: МЕХАНИЗАТОРЫ!#REF!
Name Механизаторы: МЕХАНИЗАТОРЫ!#REF!
Name Объекты: [1]Объекты!$B$2:$B$12
Name Объекты: [2]Объекты!$B$2:$B$12

Sheet Июнь 2024 
A1: Наименование | B1: Отчетный период | C1: Остаток на начало | D1: Топливо заправленное | E1: Остаток на конец | F1: Расход топлива за период | G1: Моточасы на начало | H1: Моточасы на конец | I1: Разница | J1: Перегон на доругой объект, л | K1: Перегон на доругой объект, км | L1: Часы работы на обьекте | M1: Норма на 1 мото час | N1: Факт витрат на 1 мото/год, км витрат (л/год) | O1: PL план , грн | P1: PL факт , грн | Q1: Diff, грн
A2: Телескоп 1 | B2: 45444 | C2: ='[3]Май 2024 '!E2 -> 80 | D2: =SUMIF($A$30:$A$99,A2,$B$30:$B$99) -> 0 | E2: 80 | F2: =C2+D2-E2 -> 0 | G2: ='[3]Май 2024 '!H2 -> 14075 | H2: 14075 | I2: =H2-G2 -> 0 | J2: 0 | L2: 0 | M2: =VLOOKUP(A2,[3]Тарас!$C$4:$P$23,14,0) -> 3.4 | O2: =194.94*I2 -> 0 | P2: =F2*$K$25 -> 0 | Q2: =O2-P2 -> 0
A3: Телескоп 2 | B3: 45444 | C3: ='[3]Май 2024 '!E3 -> 110 | D3: =SUMIF($A$30:$A$99,A3,$B$30:$B$99) -> 500 | E3: 120 | F3: =C3+D3-E3 -> 490 | G3: ='[3]Май 2024 '!H3 -> 10563 | H3: 10647 | I3: =H3-G3 -> 84 | J3: 0 | L3: 191 | M3: =VLOOKUP(A3,[3]Тарас!$C$4:$P$23,14,0) -> 3.4 | N3: =F3/I3 -> 5.8333333 | O3: =194.94*I3 -> 16374.96 | P3: =F3*$K$25 -> 26100.364 | Q3: =O3-P3 -> -9725.4036
A4: Телескоп JCB 533-105 (№3) | B4: 45444 | C4: ='[3]Май 2024 '!E4 -> 0 | D4: =SUMIF($A$30:$A$99,A4,$B$30:$B$99) -> 0 | F4: =C4+D4-E4 -> 0 | G4: ='[3]Май 2024 '!H4 -> #N/A | J4: 0 | M4: =VLOOKUP(A4,[3]Тарас!$C$4:$P$23,14,0) -> #N/A | N4: =F4/I4 -> #DIV/0! | O4: =194.94*I4 -> 0 | P4: =F4*$K$25 -> 0 | Q4: =O4-P4 -> 0
A5: Телескоп JCB 535-140 (№4) | B5: 45444 | C5: ='[3]Май 2024 '!E5 -> 60 | D5: =SUMIF($A$30:$A$99,A5,$B$30:$B$99) -> 600 | E5: 110 | F5: =C5+D5-E5 -> 550 | G5: ='[3]Май 2024 '!H5 -> 9096 | H5: 9280 | I5: =H5-G5 -> 184 | J5: 0 | L5: 210 | M5: =VLOOKUP(A5,[3]Тарас!$C$4:$P$23,14,0) -> 3.4 | N5: =F5/I5 -> 2.9891304 | O5: =194.94*I5 -> 35868.96 | P5: =F5*$K$25 -> 29296.326 | Q5: =O5-P5 -> 6572.6335
A6: Телескоп JCB 540-170 №5 | B6: 45444 | C6: ='[3]Май 2024 '!E6 -> 110 | D6: =SUMIF($A$30:$A$99,A6,$B$30:$B$99) -> 0 | E6: 60 | F6: =C6+D6-E6 -> 50 | G6: ='[3]Май 2024 '!H6 -> 0 | H6: 0 | I6: =L6*0.53 -> 2.65 | J6: 0 | L6: 5 | M6: =VLOOKUP(A6,[3]Тарас!$C$4:$P$23,14,0) -> 3.4 | N6: =F6/I6 -> 18.867925 | O6: =194.94*I6 -> 516.591 | P6: =F6*$K$25 -> 2663.3024 | Q6: =O6-P6 -> -2146.7114
A7: Виброкаток | B7: 45444 | C7: ='[3]Май 2024 '!E7 -> 90 | D7: =SUMIF($A$30:$A$99,A7,$B$30:$B$99) -> 100 | E7: 85 | F7: =C7+D7-E7 -> 105 | G7: ='[3]Май 2024 '!H7 -> 4934 | H7: 4948 | I7: =H7-G7 -> 14 | J7: 0 | L7: 66 | M7: =VLOOKUP(A7,[3]Тарас!$C$4:$P$23,14,0) -> 5 | N7: =F7/I7 -> 7.5 | O7: =285*I7 -> 3990 | P7: =F7*$K$25 -> 5592.9351 | Q7: =O7-P7 -> -1602.9351
A8: Ротор Пегасус | B8: 45444 | C8: ='[3]Май 2024 '!E8 -> 0 | D8: =SUMIF($A$30:$A$99,A8,$B$30:$B$99) -> 0 | F8: =C8+D8-E8 -> 0 | G8: ='[3]Май 2024 '!H8 -> 0 | I8: =H8-G8 -> 0 | J8: 0 | M8: =VLOOKUP(A8,[3]Тарас!$C$4:$P$23,14,0) -> #N/A | N8: =F8/I8 -> #DIV/0! | P8: =F8*$K$25 -> 0 | Q8: =O8-P8 -> 0
A9: Экскаватор JCB | B9: 45444 | C9: ='[3]Май 2024 '!E9 -> 90 | D9: =SUMIF($A$30:$A$99,A9,$B$30:$B$99) -> 695.86 | E9: 70 | F9: =C9+D9-E9 -> 715.86 | G9: ='[3]Май 2024 '!H9 -> 17188 | H9: 17307 | I9: =H9-G9 -> 119 | J9: 0 | L9: 152 | M9: =VLOOKUP(A9,[3]Тарас!$C$4:$P$23,14,0) -> 4.1 | N9: =F9/I9 -> 6.0156303 | O9: =235.41*I9 -> 28013.79 | P9: =F9*$K$25 -> 38131.033 | Q9: =O9-P9 -> -10117.243
A10: Экскаватор JCB 3CX 2008 | B10: 45444 | C10: ='[3]Май 2024 '!E10 -> 20 | D10: =SUMIF($A$30:$A$99,A10,$B$30:$B$99) -> 200 | E10: 20 | F10: =C10+D10-E10 -> 200 | G10: ='[3]Май 2024 '!H10 -> 3915 | H10: 39553 | I10: =H10-G10 -> 35638 | J10: 0 | L10: 113 | M10: =VLOOKUP(A10,[3]Тарас!$C$4:$P$23,14,0) -> 4.1 | N10: =F10/I10 -> 0.0056119872 | O10: =235.41*I10 -> 8389541.6 | P10: =F10*$K$25 -> 10653.21 | Q10: =O10-P10 -> 8378888.4
A11: Экскаватор JCB 2013 | B11: 45444 | C11: ='[3]Май 2024 '!E11 -> 10 | D11: =SUMIF($A$30:$A$99,A11,$B$30:$B$99) -> 800 | E11: 10 | F11: =C11+D11-E11 -> 800 | G11: ='[3]Май 2024 '!H11 -> 11698 | H11: 11904 | I11: =H11-G11 -> 206 | J11: 0 | L11: 193 | M11: =VLOOKUP(A11,[3]Тарас!$C$4:$P$23,14,0) -> 4.1 | N11: =F11/I11 -> 3.8834951 | O11: =235.41*I11 -> 48494.46 | P11: =F11*$K$25 -> 42612.839 | Q11: =O11-P11 -> 5881.6215
A12: Экскаватор JCB 220 | B12: 45444 | C12: ='[3]Май 2024 '!E12 -> 169 | D12: =SUMIF($A$30:$A$99,A12,$B$30:$B$99) -> 100 | E12: 80 | F12: =C12+D12-E12 -> 189 | G12: ='[3]Май 2024 '!H12 -> 7064 | H12: 7096 | I12: =H12-G12 -> 32 | J12: 0 | L12: 10 | M12: =VLOOKUP(A12,[3]Тарас!$C$4:$P$23,14,0) -> 10.5 | N12: =F12/I12 -> 5.90625 | O12: =595.65*I12 -> 19060.8 | P12: =F12*$K$25 -> 10067.283 | Q12: =O12-P12 -> 8993.5169
A13: МАЗ 264 | B13: 45444 | C13: ='[3]Май 2024 '!E13 -> 150 | D13: =SUMIF($A$30:$A$99,A13,$B$30:$B$99) -> 537.12 | E13: 40 | F13: =C13+D13-E13 -> 647.12 | G13: ='[3]Май 2024 '!H13 -> 30838 | H13: 31643 | I13: =H13-G13 -> 805 | J13: 0 | K13: 260 | L13: 194 | M13: =VLOOKUP(A13,[3]Тарас!$C$4:$P$23,14,0) -> 0.9 | N13: =F13/I13 -> 0.80387578 | O13: =(51.3*(I13-K13))+(K13*14.25) -> 31663.5 | P13: =F13*$K$25 -> 34469.525 | Q13: =O13-P13 -> -2806.0251
A14: МАЗ 265 | B14: 45444 | C14: ='[3]Май 2024 '!E14 -> 120 | D14: =SUMIF($A$30:$A$99,A14,$B$30:$B$99) -> 459.42 | E14: 140 | F14: =C14+D14-E14 -> 439.42 | G14: ='[3]Май 2024 '!H14 -> 34272 | H14: 34719 | I14: =H14-G14 -> 447 | J14: 0 | K14: 320 | L14: 81 | M14: =VLOOKUP(A14,[3]Тарас!$C$4:$P$23,14,0) -> 0.9 | N14: =F14/I14 -> 0.98304251 | O14: =(51.3*(I14-K14))+(K14*14.25) -> 11075.1 | P14: =F14*$K$25 -> 23406.167 | Q14: =O14-P14 -> -12331.067
A15: Самосвал Камаз | B15: 45444 | C15: ='[3]Май 2024 '!E15 -> 229 | D15: =SUMIF($A$30:$A$99,A15,$B$30:$B$99) -> 129.65 | E15: 130 | F15: =C15+D15-E15 -> 228.65 | G15: ='[3]Май 2024 '!H15 -> 559189 | H15: 559553 | I15: =H15-G15 -> 364 | J15: 0 | L15: 76 | M15: =VLOOKUP(A15,[3]Тарас!$C$4:$P$23,14,0) -> 0.9 | N15: =F15/I15 -> 0.62815934 | O15: =(51.3*(I15-K15))+(K15*19.85) -> 18673.2 | P15: =F15*$K$25 -> 12179.282 | Q15: =O15-P15 -> 6493.9181
A16: Самосвал МАЗ | B16: 45444 | C16: ='[3]Май 2024 '!E16 -> 143 | D16: =SUMIF($A$30:$A$99,A16,$B$30:$B$99) -> 179.71 | E16: 240 | F16: =C16+D16-E16 -> 82.71 | G16: ='[3]Май 2024 '!H16 -> 64107 | H16: 64160 | I16: =H16-G16 -> 53 | J16: 0 | L16: 22 | M16: =VLOOKUP(A16,[3]Тарас!$C$4:$P$23,14,0) -> 0.9 | N16: =F16/I16 -> 1.560566 | O16: =(51.3*(I16-K16)) -> 2718.9 | P16: =F16*$K$25 -> 4405.6348 | Q16: =O16-P16 -> -1686.7348
A17: РДК 250 | B17: 45444 | C17: ='[3]Май 2024 '!E17 -> 0 | D17: =SUMIF($A$30:$A$99,A17,$B$30:$B$99) -> 0 | F17: =C17+D17-E17 -> 0 | G17: ='[3]Май 2024 '!H17 -> #N/A | I17: =H17-G17 -> #N/A | J17: 0 | M17: =VLOOKUP(A17,[3]Тарас!$C$4:$P$23,14,0) -> #N/A | N17: =F17/I17 -> #N/A | P17: =F17*$K$25 -> 0 | Q17: =O17-P17 -> 0
A18: Автокран XCMG 55 | B18: 45444 | C18: ='[3]Май 2024 '!E18 -> 130 | D18: =SUMIF($A$30:$A$99,A18,$B$30:$B$99) -> 400 | E18: 130 | F18: =C18+D18-E18 -> 400 | G18: ='[3]Май 2024 '!H18 -> 0 | H18: 0 | I18: =L18*0.7 -> 49.7 | J18: 0 | L18: 71 | M18: 5.1 | N18: =F18/I18 -> 8.0482897 | P18: =F18*$K$25 -> 21306.419 | Q18: =O18-P18 -> -21306.419
A19: Автокран XCMG | B19: 45444 | C19: ='[3]Май 2024 '!E19 -> 20 | D19: =SUMIF($A$30:$A$99,A19,$B$30:$B$99) -> 320 | E19: 100 | F19: =C19+D19-E19 -> 240 | G19: ='[3]Май 2024 '!H19 -> 5749 | H19: 5827 | I19: =H19-G19 -> 78 | J19: 0 | L19: 215 | M19: =VLOOKUP(A19,[3]Тарас!$C$4:$P$23,14,0) -> 3.2 | N19: =F19/I19 -> 3.0769231 | O19: =182.4*I19 -> 14227.2 | P19: =F19*$K$25 -> 12783.852 | Q19: =O19-P19 -> 1443.3484
A20: Автокран Клинцы | B20: 45444 | C20: ='[3]Май 2024 '!E20 -> 0 | D20: =SUMIF($A$30:$A$99,A20,$B$30:$B$99) -> 0 | F20: =C20+D20-E20 -> 0 | G20: ='[3]Май 2024 '!H20 -> 0 | I20: 0 | J20: 0 | N20: =VLOOKUP(A20,[3]Тарас!$C$4:$N$23,12,0) -> #N/A | O20: =194.94*I20 -> 0 | P20: =F20*$K$25 -> 0 | Q20: =O20-P20 -> 0
A21: Подъемник Haulotte №1 | B21: 45383 | C21: ='[3]Апрель 2024'!E21 -> 0 | D21: =SUMIF($A$30:$A$99,A21,$B$30:$B$99) -> 0 | F21: =C21+D21-E21 -> 0 | I21: 0 | J21: 0 | N21: =VLOOKUP(A21,[3]Тарас!$C$4:$N$23,12,0) -> #N/A | O21: =194.94*I21 -> 0 | P21: =F21*$K$25 -> 0 | Q21: =O21-P21 -> 0
C22: =SUM(C2:C21) -> 1531 | D22: =SUM(D2:D21) -> 5021.76 | E22: =SUM(E2:E21) -> 1415
C23: =C22='[3]Май 2024 '!E22 -> TRUE | D23: =D22-B100 -> 0
J25: Стоимость 1 л | K25: =SUM(C30:C99)/B100 -> 53.266048
A28: Заправки АЗС
A29: Наименование | B29: Количество | C29: Сумма | D29: АЗС
A30: Автокран XCMG | B30: 160 | C30: 8638.4 | D30: Амик
A31: Автокран XCMG | B31: 160 | C31: 8638.4 | D31: Амик
A32: Самосвал Камаз | B32: 129.65 | C32: 6999.8 | D32: Амик
A33: Экскаватор JCB 2013 | B33: 100 | C33: 5399 | D33: Амик
A34: Экскаватор JCB 2013 | B34: 100 | C34: 5399 | D34: Амик
A35: Экскаватор JCB 2013 | B35: 100 | C35: 5199 | D35: Амик
A36: Экскаватор JCB 2013 | B36: 100 | C36: 5399 | D36: Амик
A37: Экскаватор JCB 2013 | B37: 100 | C37: 5399 | D37: Амик
A38: Экскаватор JCB 2013 | B38: 100 | C38: 5199 | D38: Амик
A39: Экскаватор JCB 2013 | B39: 100 | C39: 5399 | D39: Амик
A40: Экскаватор JCB 2013 | B40: 100 | C40: 5299 | D40: Амик
A41: Телескоп JCB 535-140 (№4) | B41: 100 | C41: 5399 | D41: Амик
... A50: МАЗ 264 | B50: 37.12 | C50: 1929.87 | D50: Амик
A51: МАЗ 264 | B51: 100 | C51: 5299 | D51: Амик | E51: =SUM(C30:C51) -> 122388.47
A52: МАЗ 264 | B52: 100 | C52: =B52*50 -> 5000 | D52: Авиас
A53: МАЗ 265 | B53: 100 | C53: =B53*50 -> 5000 | D53: Авиас
A54: Экскаватор JCB | B54: 100 | C54: =B54*50 -> 5000 | D54: Авиас
A55: Экскаватор JCB | B55: 100 | C55: =B55*50 -> 5000 | D55: Авиас
A56: Экскаватор JCB | B56: 100 | C56: =B56*50 -> 5000 | D56: Авиас | E56: =SUM(C52:C56) -> 25000
A57: Экскаватор JCB 220 | B57: 20 | C57: 979.8 | D57: ВОГ
A58: Экскаватор JCB 220 | B58: 80 | C58: 3919.2 | D58: ВОГ | E58: =SUM(C57:C58) -> 4899
A59: Автокран XCMG 55 | B59: 400 | C59: 22036 | D59: КЛО
A60: МАЗ 265 | B60: 359.42 | C60: 19800.44 | D60: КЛО
A61: Самосвал МАЗ | B61: 179.71 | C61: 9900.22 | D61: КЛО
A62: Виброкаток | B62: 100 | C62: 5509 | D62: КЛО
A63: Экскаватор JCB 3CX 2008 | B63: 200 | C63: 11018 | D63: КЛО
A64: Телескоп 2 | B64: 500 | C64: 27545 | D64: КЛО | E64: =SUM(C59:C64) -> 95808.66
A65: Экскаватор JCB | B65: 100 | C65: 4899 | D65: ОККО
A66: Экскаватор JCB | B66: 100 | C66: 4899 | D66: ОККО
A67: Экскаватор JCB | B67: 195.86 | C67: 9595.18 | D67: ОККО | E67: =SUM(C65:C67) -> 19393.18
D82: КЛО
D83: КЛО
D84: КЛО | F84: =-337162.41-C80 -> -337162.41
D85: ОККО
D86: ОККО
D87: ОККО
D88: ОККО
D89: ОККО
D90: ОККО
D91: ОККО
D92: ОККО
D93: ОККО
D94: ОККО
D95: ОККО
D96: ОККО
... D98: ОККО
D99: ОККО | E99: =SUM(C85:C99) -> 0
B100: =SUM(B30:B99) -> 5021.76 | C100: =SUM(C30:C99) -> 267489.31

Sheet Топливо Июль 2024.
A1: Наименование | B1: Отчетный период | C1: Остаток на начало | D1: Топливо заправленное | E1: Остаток на конец | F1: Расход топлива за период, л | G1: Моточасы на начало | H1: Моточасы на конец | I1: Отработано техникой моточасов | J1: Перегон на доругой объект, л | K1: Перегон на доругой объект, км | L1: Часы работы на обьекте | M1: Норма расхода топлива литр/1 мото час согласно сс | N1: Факт витрат на 1 мото/год, км витрат (л/год) | O1: PL план , грн | P1: PL факт , грн | Q1: Diff, грн | R1: Примечание по строке
A2: Телескоп 1 | B2: 45474 | C2: 80 | D2: =SUMIF($A$30:$A$112,A2,$B$30:$B$112) -> 0 | F2: =C2+D2-E2 -> 80 | G2: ='[4]Июнь 2024 '!H2 -> 14075 | I2: =H2-G2 -> -14075 | J2: 0 | L2: 0 | M2: =VLOOKUP(A2,[4]Тарас!$C$4:$P$23,14,0) -> 3.4 | O2: =194.94*I2 -> -2743780.5 | P2: =F2*$K$25 -> 4116.5561 | Q2: =O2-P2 -> -2747897.1
A3: Телескоп 2 | B3: 45474 | C3: 120 | D3: =SUMIF($A$30:$A$112,A3,$B$30:$B$112) -> 100 | E3: 40 | F3: =C3+D3-E3 -> 180 | G3: 10647 | H3: 10718 | I3: =H3-G3 -> 71 | J3: 0 | L3: 82 | M3: 3.4 | N3: =F3/I3 -> 2.5352113 | O3: =194.94*I3 -> 13840.74 | P3: =F3*$K$25 -> 9262.2512 | Q3: =O3-P3 -> 4578.4888
A4: Телескоп JCB 533-105 (№3) | B4: 45474 | C4: 0 | D4: =SUMIF($A$30:$A$112,A4,$B$30:$B$112) -> 0 | F4: =C4+D4-E4 -> 0 | G4: 0 | J4: 0 | M4: #N/A | N4: =F4/I4 -> #DIV/0! | O4: =194.94*I4 -> 0 | P4: =F4*$K$25 -> 0 | Q4: =O4-P4 -> 0
A5: Телескоп JCB 535-140 (№4) | B5: 45474 | C5: 110 | D5: =SUMIF($A$30:$A$112,A5,$B$30:$B$112) -> 860 | E5: 115 | F5: =C5+D5-E5 -> 855 | G5: 9280 | H5: 9455 | I5: =H5-G5 -> 175 | J5: 0 | L5: 242 | M5: 3.4 | N5: =F5/I5 -> 4.8857143 | O5: =194.94*I5 -> 34114.5 | P5: =F5*$K$25 -> 43995.693 | Q5: =O5-P5 -> -9881.1932
A6: Телескоп JCB 540-170 №5 | B6: 45474 | C6: 60 | D6: =SUMIF($A$30:$A$112,A6,$B$30:$B$112) -> 0 | E6: 50 | F6: =C6+D6-E6 -> 10 | G6: 0 | I6: =L6*0.53 -> 1.59 | J6: 0 | L6: 3 | M6: 3.4 | N6: =F6/I6 -> 6.2893082 | O6: =194.94*I6 -> 309.9546 | P6: =F6*$K$25 -> 514.56951 | Q6: =O6-P6 -> -204.61491 | R6: не работает мотосчетчик
A7: Виброкаток | B7: 45474 | C7: 85 | D7: =SUMIF($A$30:$A$112,A7,$B$30:$B$112) -> 83 | E7: 150 | F7: =C7+D7-E7 -> 18 | G7: 4948 | H7: 4958 | I7: =H7-G7 -> 10 | J7: 0 | L7: 9 | M7: 5 | N7: =F7/I7 -> 1.8 | O7: =285*I7 -> 2850 | P7: =F7*$K$25 -> 926.22512 | Q7: =O7-P7 -> 1923.7749
A8: Ротор Пегасус | B8: 45474 | C8: 0 | D8: =SUMIF($A$30:$A$112,A8,$B$30:$B$112) -> 0 | F8: =C8+D8-E8 -> 0 | G8: 0 | I8: =H8-G8 -> 0 | J8: 0 | M8: #N/A | N8: =F8/I8 -> #DIV/0! | P8: =F8*$K$25 -> 0 | Q8: =O8-P8 -> 0
A9: Экскаватор JCB | B9: 45474 | C9: 70 | D9: =SUMIF($A$30:$A$112,A9,$B$30:$B$112) -> 800 | E9: 70 | F9: =C9+D9-E9 -> 800 | G9: 17307 | H9: 17434 | I9: =H9-G9 -> 127 | J9: 0 | L9: 198 | M9: 4.1 | N9: =F9/I9 -> 6.2992126 | O9: =235.41*I9 -> 29897.07 | P9: =F9*$K$25 -> 41165.561 | Q9: =O9-P9 -> -11268.491
A10: Экскаватор JCB 3CX 2008 | B10: 45474 | C10: 20 | D10: =SUMIF($A$30:$A$112,A10,$B$30:$B$112) -> 799.94 | E10: 30 | F10: =C10+D10-E10 -> 789.94 | G10: 39553 | H10: 39728 | I10: =H10-G10 -> 175 | J10: 0 | L10: 233 | M10: 4.1 | N10: =F10/I10 -> 4.5139429 | O10: =235.41*I10 -> 41196.75 | P10: =F10*$K$25 -> 40647.904 | Q10: =O10-P10 -> 548.84607
A11: Экскаватор JCB 2013 | B11: 45474 | C11: 10 | D11: =SUMIF($A$30:$A$112,A11,$B$30:$B$112) -> 850 | E11: 15 | F11: =C11+D11-E11 -> 845 | G11: 11904 | H11: 12082 | I11: =H11-G11 -> 178 | J11: 0 | L11: 237 | M11: 4.1 | N11: =F11/I11 -> 4.747191 | O11: =235.41*I11 -> 41902.98 | P11: =F11*$K$25 -> 43481.124 | Q11: =O11-P11 -> -1578.1437
A12: Экскаватор JCB 220 | B12: 45474 | C12: 80 | D12: =SUMIF($A$30:$A$112,A12,$B$30:$B$112) -> 0 | F12: =C12+D12-E12 -> 80 | G12: 7096 | I12: =H12-G12 -> -7096 | J12: 0 | M12: 10.5 | N12: =F12/I12 -> -0.011273957 | O12: =595.65*I12 -> -4226732.4 | P12: =F12*$K$25 -> 4116.5561 | Q12: =O12-P12 -> -4230849
A13: МАЗ 264 | B13: 45474 | C13: 40 | D13: =SUMIF($A$30:$A$112,A13,$B$30:$B$112) -> 400 | E13: 130 | F13: =C13+D13-E13 -> 310 | G13: 31643 | H13: 31832 | I13: =H13-G13 -> 189 | J13: 0 | L13: 175 | M13: 0.9 | N13: =F13/I13 -> 1.6402116 | O13: =(51.3*(I13-K13))+(K13*14.25) -> 9695.7 | P13: =F13*$K$25 -> 15951.655 | Q13: =O13-P13 -> -6255.9548 | R13: слив 15.2 л
A14: МАЗ 265 | B14: 45474 | C14: 140 | D14: =SUMIF($A$30:$A$112,A14,$B$30:$B$112) -> 500 | E14: 150 | F14: =C14+D14-E14 -> 490 | G14: 34719 | H14: 35350 | I14: =H14-G14 -> 631 | J14: 0 | L14: 135 | M14: 0.9 | N14: =F14/I14 -> 0.77654517 | O14: =(51.3*(I14-K14))+(K14*14.25) -> 32370.3 | P14: =F14*$K$25 -> 25213.906 | Q14: =O14-P14 -> 7156.394 | R14: слив 10,47 л
A15: Самосвал Камаз | B15: 45474 | C15: 130 | D15: =SUMIF($A$30:$A$112,A15,$B$30:$B$112) -> 200 | E15: 137 | F15: =C15+D15-E15 -> 193 | G15: 559353 | H15: 559550 | I15: =H15-G15 -> 197 | J15: 0 | L15: 128 | M15: 0.9 | N15: =F15/I15 -> 0.97969543 | O15: =(51.3*(I15-K15))+(K15*19.85) -> 10106.1 | P15: =F15*$K$25 -> 9931.1916 | Q15: =O15-P15 -> 174.90844 | R15: слив 509 л
A16: Самосвал МАЗ | B16: 45474 | C16: 240 | D16: =SUMIF($A$30:$A$112,A16,$B$30:$B$112) -> 59.54 | E16: 160 | F16: =C16+D16-E16 -> 139.54 | G16: 64160 | H16: 64239 | I16: =H16-G16 -> 79 | J16: 0 | L16: 16 | M16: 0.9 | N16: =F16/I16 -> 1.7663291 | O16: =(51.3*(I16-K16))+(K16*19.85) -> 4052.7 | P16: =F16*$K$25 -> 7180.303 | Q16: =O16-P16 -> -3127.603 | R16: слив 16,5 л
A17: РДК 250 | B17: 45474 | C17: 0 | D17: =SUMIF($A$30:$A$112,A17,$B$30:$B$112) -> 0 | F17: =C17+D17-E17 -> 0 | G17: 0 | I17: =H17-G17 -> 0 | J17: 0 | M17: #N/A | N17: =F17/I17 -> #DIV/0! | P17: =F17*$K$25 -> 0 | Q17: =O17-P17 -> 0
A18: Автокран XCMG 55 | B18: 45474 | C18: 130 | D18: =SUMIF($A$30:$A$112,A18,$B$30:$B$112) -> 380 | E18: 190 | F18: =C18+D18-E18 -> 320 | G18: 0 | I18: =L18*0.7 -> 70 | J18: 0 | L18: 100 | M18: 5.1 | N18: =F18/I18 -> 4.5714286 | O18: =290.07*I18 -> 20304.9 | P18: =F18*$K$25 -> 16466.224 | Q18: =O18-P18 -> 3838.6757 | R18: не работает мотосчетчик, слив 127 л
A19: Автокран XCMG | B19: 45474 | C19: 100 | D19: =SUMIF($A$30:$A$112,A19,$B$30:$B$112) -> 570 | E19: 180 | F19: =C19+D19-E19 -> 490 | G19: 5827 | H19: 5973 | I19: =H19-G19 -> 146 | J19: 0 | L19: 274 | M19: 3.2 | N19: =F19/I19 -> 3.3561644 | O19: =182.4*I19 -> 26630.4 | P19: =F19*$K$25 -> 25213.906 | Q19: =O19-P19 -> 1416.494 | R19: слив 3435 л
A20: Автокран Клинцы | B20: 45474 | C20: 230 | D20: =SUMIF($A$30:$A$112,A20,$B$30:$B$112) -> 300 | E20: 230 | F20: =C20+D20-E20 -> 300 | G20: ='[4]Июнь 2024 '!H20 -> 0 | I20: =L20*0.7 -> 16.1 | J20: 0 | K20: 360 | L20: 23 | M20: 2.9 | N20: =F20/I20 -> 18.63354 | O20: =I20*165.3+28.5*K20 -> 12921.33 | P20: =F20*$K$25 -> 15437.085 | Q20: =O20-P20 -> -2515.7553 | R20: не работает мотосчетчик слив 400 л
A21: Подъемник Haulotte №1 | B21: 45474 | C21: ='[4]Июнь 2024 '!E21 -> 0 | D21: =SUMIF($A$30:$A$112,A21,$B$30:$B$112) -> 0 | F21: =C21+D21-E21 -> 0 | G21: ='[4]Июнь 2024 '!H21 -> 0 | I21: 0 | J21: 0 | N21: =VLOOKUP(A21,[4]Тарас!$C$4:$N$23,12,0) -> #N/A | O21: =194.94*I21 -> 0 | P21: =F21*$K$25 -> 0 | Q21: =O21-P21 -> 0
C22: =SUM(C2:C21) -> 1645 | D22: =SUM(D2:D21) -> 5902.48 | E22: =SUM(E2:E21) -> 1647
D23: =D22-B113 -> 0
J25: Стоимость 1 л | K25: =SUM(C30:C112)/B113 -> 51.456951
A28: Заправки АЗС
A29: Наименование | B29: Количество | C29: Сумма | D29: АЗС
A30: Экскаватор JCB | B30: 100 | C30: =B30*47.63 -> 4763 | D30: Авиас
A31: Экскаватор JCB | B31: 100 | C31: =B31*47.63 -> 4763 | D31: Авиас
A32: Экскаватор JCB | B32: 100 | C32: =B32*47.63 -> 4763 | D32: Авиас
A33: Экскаватор JCB | B33: 100 | C33: =B33*47.63 -> 4763 | D33: Авиас
A34: Экскаватор JCB | B34: 100 | C34: =B34*47.63 -> 4763 | D34: Авиас
A35: Экскаватор JCB | B35: 100 | C35: =B35*47.63 -> 4763 | D35: Авиас
A36: Экскаватор JCB | B36: 100 | C36: =B36*47.63 -> 4763 | D36: Авиас
A37: Экскаватор JCB | B37: 100 | C37: =B37*47.63 -> 4763 | D37: Авиас
A38: МАЗ 265 | B38: 100 | C38: =B38*47.63 -> 4763 | D38: Авиас
A39: МАЗ 265 | B39: 100 | C39: =B39*47.63 -> 4763 | D39: Авиас
A40: МАЗ 265 | B40: 100 | C40: =B40*47.63 -> 4763 | D40: Авиас
A41: МАЗ 265 | B41: 100 | C41: =B41*47.63 -> 4763 | D41: Авиас
... A47: МАЗ 264 | B47: 100 | C47: =B47*47.63 -> 4763 | D47: Авиас
E48: =SUM(C30:C48) -> 85734
A49: Автокран XCMG | B49: 50 | C49: 2649.5 | D49: Амик
A50: Автокран XCMG | B50: 40 | C50: 2119.6 | D50: Амик
A51: Автокран XCMG | B51: 160 | C51: 8478.4 | D51: Амик
A52: Автокран XCMG | B52: 160 | C52: 8478.4 | D52: Амик
A53: Автокран XCMG | B53: 160 | C53: 8558.4 | D53: Амик
A54: Самосвал Камаз | B54: 100 | C54: 5299 | D54: Амик
A55: Самосвал Камаз | B55: 100 | C55: 5349 | D55: Амик
A56: Автокран XCMG 55 | B56: 100 | C56: 5099 | D56: Амик
A57: Автокран XCMG 55 | B57: 100 | C57: 5099 | D57: Амик
A58: Автокран XCMG 55 | B58: 150 | C58: 8023.5 | D58: Амик
A59: Автокран XCMG 55 | B59: 30 | C59: 1604.7 | D59: Амик
A60: Экскаватор JCB 2013 | B60: 100 | C60: 5299 | D60: Амик
... A80: Телескоп JCB 535-140 (№4) | B80: 100 | C80: 5399 | D80: Амик
E81: =SUM(C49:C81) -> 150761.4
A82: Самосвал МАЗ | B82: 59.54 | C82: 3280.06 | D82: КЛО
A83: Экскаватор JCB 3CX 2008 | B83: 799.94 | C83: 44068.695 | D83: КЛО
A84: Виброкаток | B84: 83 | C84: 4572.47 | D84: КЛО
A85: Телескоп 2 | B85: 100 | C85: 5509 | D85: КЛО | E85: =SUM(C82:C85) -> 57430.225
A86: Автокран Клинцы | B86: 100 | C86: 4899 | D86: ВОГ
A87: Автокран Клинцы | B87: 100 | C87: 4899 | D87: ВОГ
E88: =SUM(C86:C88) -> 9798
D95: КЛО
D96: КЛО
D97: КЛО | F97: =-337162.41-C93 -> -337162.41
D98: ОККО
D99: ОККО
D100: ОККО
D101: ОККО
D102: ОККО
D103: ОККО
D104: ОККО
D105: ОККО
D106: ОККО
D107: ОККО
D108: ОККО
D109: ОККО
... D111: ОККО
D112: ОККО | E112: =SUM(C98:C112) -> 0
B113: =SUM(B30:B112) -> 5902.48 | C113: =SUM(C30:C112) -> 303723.62

Sheet Топливо Август 2024
A1: Наименование | B1: Отчетный период | C1: Остаток на начало | D1: Топливо заправленное | E1: Остаток на конец | F1: Расход топлива за период, л | G1: Моточасы на начало | H1: Моточасы на конец | I1: Отработано техникой моточасов | J1: Перегон на доругой объект, л | K1: Перегон на доругой объект, км | L1: Часы работы на обьекте | M1: Норма расхода топлива литр/1 мото час согласно сс | N1: Факт витрат на 1 мото/год, км витрат (л/год) | O1: PL план , грн | P1: PL факт , грн | Q1: Diff, грн | R1: Примечание по строке
A2: Телескоп 1 | B2: 45474 | C2: 80 | D2: =SUMIF($A$29:$A$128,A2,$B$29:$B$128) -> 0 | F2: =C2+D2-E2 -> 80 | G2: ='[4]Июнь 2024 '!H2 -> 14075 | I2: =H2-G2 -> -14075 | J2: 0 | L2: 0 | M2: =VLOOKUP(A2,[4]Тарас!$C$4:$P$23,14,0) -> 3.4 | O2: =194.94*I2 -> -2743780.5 | P2: =F2*$K$24 -> 4081.149 | Q2: =O2-P2 -> -2747861.6
A3: Телескоп 2 | B3: 45474
A4: Телескоп JCB 533-105 (№3) | B4: 45474 | C4: 0 | D4: =SUMIF($A$29:$A$128,A4,$B$29:$B$128) -> 0 | F4: =C4+D4-E4 -> 0 | G4: 0 | J4: 0 | M4: #N/A | N4: =F4/I4 -> #DIV/0! | O4: =194.94*I4 -> 0 | P4: =F4*$K$24 -> 0 | Q4: =O4-P4 -> 0
A5: Телескоп JCB 535-140 (№4) | B5: 45474 | C5: 115 | D5: =SUMIF($A$29:$A$128,A5,$B$29:$B$128) -> 926.25 | E5: 70 | F5: =C5+D5-E5 -> 971.25 | G5: 9455 | H5: 9655 | I5: =H5-G5 -> 200 | J5: 0 | L5: 254 | M5: 3.4 | N5: =F5/I5 -> 4.85625 | O5: =194.94*I5 -> 38988 | P5: =F5*$K$24 -> 49547.699 | Q5: =O5-P5 -> -10559.699
A6: Телескоп JCB 540-170 №5 | B6: 45474 | C6: 50 | D6: =SUMIF($A$29:$A$128,A6,$B$29:$B$128) -> 210 | E6: 120 | F6: =C6+D6-E6 -> 140 | I6: =L6*0.53 -> 36.57 | J6: 0 | L6: 69 | M6: 3.4 | N6: =F6/I6 -> 3.8282745 | O6: =194.94*I6 -> 7128.9558 | P6: =F6*$K$24 -> 7142.0107 | Q6: =O6-P6 -> -13.05492 | R6: не работает мотосчетчик
A7: Виброкаток | B7: 45474 | C7: 150 | D7: =SUMIF($A$29:$A$128,A7,$B$29:$B$128) -> 0 | E7: 125 | F7: =C7+D7-E7 -> 25 | G7: 4958 | H7: 4970 | I7: =H7-G7 -> 12 | J7: 0 | L7: 20 | M7: 5 | N7: =F7/I7 -> 2.0833333 | O7: =285*I7 -> 3420 | P7: =F7*$K$24 -> 1275.3591 | Q7: =O7-P7 -> 2144.6409
A8: Ротор Пегасус | B8: 45474 | D8: =SUMIF($A$29:$A$128,A8,$B$29:$B$128) -> 0 | F8: =C8+D8-E8 -> 0 | I8: =H8-G8 -> 0 | J8: 0 | M8: #N/A | N8: =F8/I8 -> #DIV/0! | P8: =F8*$K$24 -> 0 | Q8: =O8-P8 -> 0
A9: Экскаватор JCB | B9: 45474 | C9: 70 | D9: =SUMIF($A$29:$A$128,A9,$B$29:$B$128) -> 789.18 | E9: 55 | F9: =C9+D9-E9 -> 804.18 | G9: 17434 | H9: 17608 | I9: =H9-G9 -> 174 | J9: 0 | L9: 198 | M9: 4.1 | N9: =F9/I9 -> 4.6217241 | O9: =235.41*I9 -> 40961.34 | P9: =F9*$K$24 -> 41024.73 | Q9: =O9-P9 -> -63.389865
A10: Экскаватор JCB 3CX 2008 | B10: 45474 | C10: 30 | D10: =SUMIF($A$29:$A$128,A10,$B$29:$B$128) -> 874 | E10: 0 | F10: =C10+D10-E10 -> 904 | G10: 39728 | I10: =L10*0.55 -> 116.6 | J10: 0 | L10: 212 | M10: 4.1 | N10: =F10/I10 -> 7.7530017 | O10: =235.41*I10 -> 27448.806 | P10: =F10*$K$24 -> 46116.984 | Q10: =O10-P10 -> -18668.178 | R10: не работает счетчик на топливо и на моточасы, поламался в августе
A11: Экскаватор JCB 2013 | B11: 45474 | C11: 15 | D11: =SUMIF($A$29:$A$128,A11,$B$29:$B$128) -> 849.99 | E11: 10 | F11: =C11+D11-E11 -> 854.99 | G11: 12082 | H11: 12270 | I11: =H11-G11 -> 188 | J11: 0 | L11: 251 | M11: 4.1 | N11: =F11/I11 -> 4.5478191 | O11: =235.41*I11 -> 44257.08 | P11: =F11*$K$24 -> 43616.77 | Q11: =O11-P11 -> 640.31039
A12: Экскаватор JCB 220 | B12: 45474 | C12: 80 | D12: =SUMIF($A$29:$A$128,A12,$B$29:$B$128) -> 1811.92 | E12: 394 | F12: =C12+D12-E12 -> 1497.92 | G12: 7096 | H12: 7255 | I12: =H12-G12 -> 159 | J12: 0 | L12: 240 | M12: 10.5 | N12: =F12/I12 -> 9.4208805 | O12: =595.65*I12 -> 94708.35 | P12: =F12*$K$24 -> 76415.434 | Q12: =O12-P12 -> 18292.916 | R12: слив 85 л
A13: МАЗ 264 | B13: 45474 | C13: 130 | D13: =SUMIF($A$29:$A$128,A13,$B$29:$B$128) -> 472.27 | E13: 150 | F13: =C13+D13-E13 -> 452.27 | G13: 31832 | H13: 32189 | I13: =H13-G13 -> 357 | J13: 0 | L13: 143 | M13: 0.9 | N13: =F13/I13 -> 1.2668627 | O13: =(51.3*(I13-K13))+(K13*14.25) -> 18314.1 | P13: =F13*$K$24 -> 23072.266 | Q13: =O13-P13 -> -4758.1656 | R13: слив 51 л
A14: МАЗ 265 | B14: 45474 | C14: 150 | D14: =SUMIF($A$29:$A$128,A14,$B$29:$B$128) -> 524.92 | E14: 150 | F14: =C14+D14-E14 -> 524.92 | G14: 35350 | H14: 35800 | I14: =H14-G14 -> 450 | J14: 0 | L14: 180 | M14: 0.9 | N14: =F14/I14 -> 1.1664889 | O14: =(51.3*(I14-K14))+(K14*14.25) -> 23085 | P14: =F14*$K$24 -> 26778.459 | Q14: =O14-P14 -> -3693.4591
A15: Самосвал Камаз | B15: 45474 | C15: 137 | D15: =SUMIF($A$29:$A$128,A15,$B$29:$B$128) -> 500 | E15: 170 | F15: =C15+D15-E15 -> 467 | G15: 559550 | H15: 559867 | I15: =H15-G15 -> 317 | J15: 0 | L15: 124 | M15: 0.9 | N15: =F15/I15 -> 1.4731861 | O15: =(51.3*(I15-K15))+(K15*19.85) -> 16262.1 | P15: =F15*$K$24 -> 23823.707 | Q15: =O15-P15 -> -7561.6072 | R15: слив 1277 л
A16: Самосвал МАЗ | B16: 45474 | C16: 160 | D16: =SUMIF($A$29:$A$128,A16,$B$29:$B$128) -> 626.98 | E16: 161 | F16: =C16+D16-E16 -> 625.98 | G16: 64239 | H16: 65010 | I16: =H16-G16 -> 771 | J16: 0 | K16: 220 | L16: 108 | M16: 0.9 | N16: =F16/I16 -> 0.81190661 | O16: =(51.3*(I16-K16))+(K16*19.85) -> 32633.3 | P16: =F16*$K$24 -> 31933.971 | Q16: =O16-P16 -> 699.3295 | R16: слив 32,57
A17: РДК 250 | B17: 45474 | D17: =SUMIF($A$29:$A$128,A17,$B$29:$B$128) -> 0 | F17: =C17+D17-E17 -> 0 | I17: =H17-G17 -> 0 | J17: 0 | M17: #N/A | N17: =F17/I17 -> #DIV/0! | P17: =F17*$K$24 -> 0 | Q17: =O17-P17 -> 0
A18: Автокран XCMG 55 | B18: 45474 | C18: 190 | D18: =SUMIF($A$29:$A$128,A18,$B$29:$B$128) -> 559.99 | E18: 170 | F18: =C18+D18-E18 -> 579.99 | I18: =L18*0.7 -> 105 | J18: 0 | L18: 150 | M18: 5.1 | N18: =F18/I18 -> 5.5237143 | O18: =290.07*I18 -> 30457.35 | P18: =F18*$K$24 -> 29587.82 | Q18: =O18-P18 -> 869.53002 | R18: не работает мотосчетчик, слив 114 л
A19: Автокран XCMG | B19: 45474 | C19: 180 | D19: =SUMIF($A$29:$A$128,A19,$B$29:$B$128) -> 424.84 | E19: 230 | F19: =C19+D19-E19 -> 374.84 | G19: 5973 | H19: 6073 | I19: =H19-G19 -> 100 | J19: 0 | L19: 280 | M19: 3.2 | N19: =F19/I19 -> 3.7484 | O19: =182.4*I19 -> 18240 | P19: =F19*$K$24 -> 19122.224 | Q19: =O19-P19 -> -882.22356 | R19: слив 188 л
A20: Автокран Клинцы | B20: 45474 | C20: 230 | D20: =SUMIF($A$29:$A$128,A20,$B$29:$B$128) -> 401.42 | E20: 230 | F20: =C20+D20-E20 -> 401.42 | I20: =L20*0.7 -> 140.7 | J20: 0 | L20: 201 | M20: 2.9 | N20: =F20/I20 -> 2.8530206 | O20: =I20*165.3+28.5*K20 -> 23257.71 | P20: =F20*$K$24 -> 20478.185 | Q20: =O20-P20 -> 2779.5247 | R20: не работает мотосчетчик, слив 99 л
C21: =SUM(C5:C20) -> 1687 | D21: =SUM(D2:D20) -> 8971.76 | E21: =SUM(E2:E20) -> 2035
D22: =D21-B129 -> 0
J24: Стоимость 1 л | K24: =SUM(C29:C128)/B129 -> 51.014362
A27: Заправки АЗС
A28: Наименование | B28: Количество | C28: Сумма | D28: АЗС
A29: Экскаватор JCB | B29: 92.08 | C29: =B29*50.5 -> 4650.04 | D29: Авиас
A30: Экскаватор JCB | B30: 45.87 | C30: =B30*50.5 -> 2316.435 | D30: Авиас
A31: Экскаватор JCB | B31: 100 | C31: =B31*50.5 -> 5050 | D31: Авиас
A32: Экскаватор JCB | B32: 100 | C32: =B32*50.5 -> 5050 | D32: Авиас
A33: Экскаватор JCB | B33: 96.46 | C33: =B33*50.5 -> 4871.23 | D33: Авиас
A34: Экскаватор JCB | B34: 54.77 | C34: =B34*50.5 -> 2765.885 | D34: Авиас
A35: Экскаватор JCB | B35: 100 | C35: =B35*50.5 -> 5050 | D35: Авиас
A36: Экскаватор JCB | B36: 100 | C36: =B36*50.5 -> 5050 | D36: Авиас
A37: Экскаватор JCB | B37: 100 | C37: =B37*50.5 -> 5050 | D37: Авиас
A38: Автокран Клинцы | B38: 50 | C38: =B38*50.5 -> 2525 | D38: Авиас
A39: Автокран Клинцы | B39: 138.42 | C39: =B39*50.5 -> 6990.21 | D39: Авиас
A40: Автокран Клинцы | B40: 13 | C40: =B40*50.5 -> 656.5 | D40: Авиас
... A47: МАЗ 264 | B47: 100 | C47: =B47*50.5 -> 5050 | D47: Авиас
E48: =SUM(C29:C48) -> 83974.935
A49: Автокран XCMG | B49: 100 | C49: 5349 | D49: Амик
A50: Автокран XCMG | B50: 150 | C50: 8023.5 | D50: Амик
A51: Автокран XCMG | B51: 150 | C51: 8023.5 | D51: Амик
A52: Автокран XCMG | B52: 24.84 | C52: 1328.69 | D52: Амик
A53: Самосвал Камаз | B53: 100 | C53: 5349 | D53: Амик
A54: Самосвал Камаз | B54: 100 | C54: 5349 | D54: Амик
A55: Самосвал Камаз | B55: 100 | C55: 5349 | D55: Амик
A56: Самосвал Камаз | B56: 100 | C56: 5149 | D56: Амик
A57: Самосвал Камаз | B57: 100 | C57: 5149 | D57: Амик
A58: Автокран XCMG 55 | B58: 160 | C58: 8558.4 | D58: Амик
A59: Автокран XCMG 55 | B59: 150 | C59: 8023.5 | D59: Амик
A60: Автокран XCMG 55 | B60: 50 | C60: 2674.5 | D60: Амик
... A89: Самосвал МАЗ | B89: 70.98 | C89: 3654.76 | D89: Амик
D90: Амик
D91: Амик
E92: =SUM(C49:C92) -> 203041.69
D93: КЛО
D94: КЛО
D95: КЛО
D96: КЛО | E96: =SUM(C93:C96) -> 0
A97: МАЗ 265 | B97: 200 | C97: 9798 | D97: ВОГ
A98: Телескоп JCB 540-170 №5 | B98: 210 | C98: 10287.9 | D98: ВОГ
E99: =SUM(C97:C99) -> 20085.9
A100: Самосвал МАЗ | B100: 56 | C100: 3085.04 | D100: КЛО | E100: =SUM(C100:C100) -> 3085.04
A101: Экскаватор JCB 220 | B101: 200 | C101: 9798 | D101: ОККО
A102: Экскаватор JCB 220 | B102: 200 | C102: 9798 | D102: ОККО
A103: Экскаватор JCB 220 | B103: 160 | C103: 7838.4 | D103: ОККО
A104: Экскаватор JCB 220 | B104: 160 | C104: 7838.4 | D104: ОККО
A105: Экскаватор JCB 220 | B105: 160 | C105: 7838.4 | D105: ОККО
A106: Экскаватор JCB 220 | B106: 200 | C106: 9798 | D106: ОККО
A107: Экскаватор JCB 220 | B107: 160 | C107: 7838.4 | D107: ОККО
A108: Экскаватор JCB 220 | B108: 160 | C108: 7838.4 | D108: ОККО
A109: Экскаватор JCB 220 | B109: 160 | C109: 7838.4 | D109: ОККО
A110: Экскаватор JCB 220 | B110: 111.92 | C110: 5482.96 | D110: ОККО
A111: Экскаватор JCB 220 | B111: 140 | C111: 6858.6 | D111: ОККО
A112: Экскаватор JCB 3CX 2008 | B112: 40 | C112: 1959.6 | D112: ОККО
... A126: МАЗ 265 | B126: 100 | C126: 4899 | D126: ОККО
D127: ОККО
D128: ОККО | E128: =SUM(C101:C128) -> 147501.05
B129: =SUM(B29:B128) -> 8971.76 | C129: =SUM(C29:C128) -> 457688.62

Sheet Топливо Сентябрь 2024
A1: Наименование | B1: Отчетный период | C1: Остаток на начало | D1: Топливо заправленное | E1: Остаток на конец | F1: Расход топлива за период, л | G1: Моточасы на начало | H1: Моточасы на конец | I1: Отработано техникой моточасов | J1: Перегон на доругой объект, л | K1: Перегон на доругой объект, км | L1: Часы работы на обьекте | M1: Норма расхода топлива литр/1 мото час согласно сс | N1: Факт витрат на 1 мото/год, км витрат (л/год) | O1: PL план , грн | P1: PL факт , грн | Q1: Diff, грн | R1: Примечание по строке
A2: Телескоп 1 | B2: 45474 | C2: 80 | D2: =SUMIF($A$30:$A$149,A2,$B$30:$B$149) -> 0 | F2: =C2+D2-E2 -> 80 | G2: ='[4]Июнь 2024 '!H2 -> 14075 | I2: =H2-G2 -> -14075 | J2: 0 | L2: 0 | M2: =VLOOKUP(A2,[4]Тарас!$C$4:$P$23,14,0) -> 3.4 | O2: =194.94*I2 -> -2743780.5 | P2: =F2*$K$25 -> 4049.5087 | Q2: =O2-P2 -> -2747830
A3: Телескоп 2 | B3: 45536 | C3: 40 | D3: =SUMIF($A$30:$A$149,A3,$B$30:$B$149) -> 400 | E3: 30 | F3: =C3+D3-E3 -> 410 | G3: 10718 | I3: =L3*0.53 -> 60.42 | L3: 114 | M3: 3.4 | N3: =F3/I3 -> 6.7858325 | O3: =194.94*I3 -> 11778.275 | P3: =F3*$K$25 -> 20753.732 | Q3: =O3-P3 -> -8975.457 | R3: мотосчетчик дал сбой, на табло ошибка
A4: Телескоп JCB 533-105 (№3) | B4: 45536 | D4: =SUMIF($A$30:$A$149,A4,$B$30:$B$149) -> 0 | F4: =C4+D4-E4 -> 0 | J4: 0 | M4: #N/A | N4: =F4/I4 -> #DIV/0! | O4: =194.94*I4 -> 0 | P4: =F4*$K$25 -> 0 | Q4: =O4-P4 -> 0
A5: Телескоп JCB 535-140 (№4) | B5: 45536 | C5: 70 | D5: =SUMIF($A$30:$A$149,A5,$B$30:$B$149) -> 775.34 | E5: 10 | F5: =C5+D5-E5 -> 835.34 | G5: 9655 | H5: 9842 | I5: =H5-G5 -> 187 | J5: 0 | L5: 186 | M5: 3.4 | N5: =F5/I5 -> 4.4670588 | O5: =194.94*I5 -> 36453.78 | P5: =F5*$K$25 -> 42283.957 | Q5: =O5-P5 -> -5830.177
A6: Телескоп JCB 540-170 №5 | B6: 45536 | C6: 120 | D6: =SUMIF($A$30:$A$149,A6,$B$30:$B$149) -> 319.49 | E6: 20 | F6: =C6+D6-E6 -> 419.49 | I6: =L6*0.53 -> 33.92 | J6: 0 | L6: 64 | M6: 3.4 | N6: =F6/I6 -> 12.36704 | O6: =194.94*I6 -> 6612.3648 | P6: =F6*$K$25 -> 21234.105 | Q6: =O6-P6 -> -14621.74 | R6: не работает мотосчетчик
A7: Виброкаток | B7: 45536 | C7: 125 | D7: =SUMIF($A$30:$A$149,A7,$B$30:$B$149) -> 0 | E7: 65 | F7: =C7+D7-E7 -> 60 | G7: 4970 | H7: 4981 | I7: =H7-G7 -> 11 | J7: 0 | L7: 10 | M7: 5 | N7: =F7/I7 -> 5.4545455 | O7: =285*I7 -> 3135 | P7: =F7*$K$25 -> 3037.1315 | Q7: =O7-P7 -> 97.868512
A8: Ротор Пегасус | B8: 45536 | D8: =SUMIF($A$30:$A$149,A8,$B$30:$B$149) -> 0 | F8: =C8+D8-E8 -> 0 | I8: =H8-G8 -> 0 | J8: 0 | M8: #N/A | N8: =F8/I8 -> #DIV/0! | P8: =F8*$K$25 -> 0 | Q8: =O8-P8 -> 0
A9: Экскаватор JCB | B9: 45536 | C9: 55 | D9: =SUMIF($A$30:$A$149,A9,$B$30:$B$149) -> 974.88 | E9: 10 | F9: =C9+D9-E9 -> 1019.88 | G9: 17608 | H9: 17802 | I9: =H9-G9 -> 194 | J9: 0 | L9: 242 | M9: 4.1 | N9: =F9/I9 -> 5.2571134 | O9: =235.41*I9 -> 45669.54 | P9: =F9*$K$25 -> 51625.161 | Q9: =O9-P9 -> -5955.621
A10: Экскаватор JCB 3CX 2008 | B10: 45536 | C10: 0 | D10: =SUMIF($A$30:$A$149,A10,$B$30:$B$149) -> 1111.37 | E10: 20 | F10: =C10+D10-E10 -> 1091.37 | I10: =L10*0.55 -> 114.4 | J10: 0 | L10: 208 | M10: 4.1 | N10: =F10/I10 -> 9.5399476 | O10: =235.41*I10 -> 26930.904 | P10: =F10*$K$25 -> 55243.903 | Q10: =O10-P10 -> -28312.999
A11: Экскаватор JCB 2013 | B11: 45536 | C11: 10 | D11: =SUMIF($A$30:$A$149,A11,$B$30:$B$149) -> 400 | E11: 20 | F11: =C11+D11-E11 -> 390 | G11: 12270 | I11: =H11-G11 -> -12270 | J11: 0 | L11: 91 | M11: 4.1 | R11: на ремонте, не можем получить данные счетчика
A12: Экскаватор JCB 220 | B12: 45536 | C12: 394 | D12: =SUMIF($A$30:$A$149,A12,$B$30:$B$149) -> 1831.05 | E12: 301 | F12: =C12+D12-E12 -> 1924.05 | G12: 7255 | H12: 7387 | I12: =H12-G12 -> 132 | J12: 0 | L12: 230 | M12: 10.5 | N12: =F12/I12 -> 14.576136 | O12: =595.65*I12 -> 78625.8 | P12: =F12*$K$25 -> 97393.214 | Q12: =O12-P12 -> -18767.414 | R12: gps показывает слив топлива 396 л
A13: МАЗ 264 | B13: 45536 | C13: 150 | D13: =SUMIF($A$30:$A$149,A13,$B$30:$B$149) -> 580.43 | E13: 150 | F13: =C13+D13-E13 -> 580.43 | G13: 32189 | H13: 32692 | I13: =H13-G13 -> 503 | J13: 0 | L13: 222 | M13: 0.9 | N13: =F13/I13 -> 1.1539364 | O13: =(51.3*(I13-K13))+(K13*14.25) -> 25803.9 | P13: =F13*$K$25 -> 29380.704 | Q13: =O13-P13 -> -3576.8038
A14: МАЗ 265 | B14: 45536 | C14: 150 | D14: =SUMIF($A$30:$A$149,A14,$B$30:$B$149) -> 547.46 | E14: 160 | F14: =C14+D14-E14 -> 537.46 | G14: 35800 | H14: 37210 | I14: =H14-G14 -> 1410 | J14: 0 | K14: 450 | L14: 189 | M14: 0.9 | N14: =F14/I14 -> 0.3811773 | O14: =(51.3*(I14-K14))+(K14*14.25) -> 55660.5 | P14: =F14*$K$25 -> 27205.611 | Q14: =O14-P14 -> 28454.889
A15: Самосвал Камаз | B15: 45536 | C15: 170 | D15: =SUMIF($A$30:$A$149,A15,$B$30:$B$149) -> 254.47 | E15: 204 | F15: =C15+D15-E15 -> 220.47 | G15: 559867 | H15: 560504 | I15: =H15-G15 -> 637 | J15: 0 | K15: 413 | L15: 4 | M15: 0.9 | N15: =F15/I15 -> 0.34610675 | O15: =(51.3*(I15-K15))+(K15*19.85) -> 19689.25 | P15: =F15*$K$25 -> 11159.94 | Q15: =O15-P15 -> 8529.3103
A16: Самосвал МАЗ | B16: 45536 | C16: 161 | D16: =SUMIF($A$30:$A$149,A16,$B$30:$B$149) -> 1498.88 | E16: 181 | F16: =C16+D16-E16 -> 1478.88 | G16: 65010 | H16: 68211 | I16: =H16-G16 -> 3201 | J16: 0 | K16: 250 | L16: 89 | M16: 0.9 | N16: =F16/I16 -> 0.46200562 | O16: =(51.3*(I16-K16))+(K16*19.85) -> 156348.8 | P16: =F16*$K$25 -> 74859.217 | Q16: =O16-P16 -> 81489.583 | R16: gps показывает слив топлива 11 л
A17: Самосвал МАЗ №2 | B17: 45536 | C17: 0 | D17: =SUMIF($A$30:$A$149,A17,$B$30:$B$149) -> 940.02 | E17: 160 | F17: =C17+D17-E17 -> 780.02 | G17: 63140 | H17: 64118 | I17: =H17-G17 -> 978 | J17: 0 | K17: 480 | L17: 76 | M17: 0.9 | N17: =F17/I17 -> 0.79756646 | O17: =(51.3*(I17-K17))+(K17*19.85) -> 35075.4 | P17: =F17*$K$25 -> 39483.722 | Q17: =O17-P17 -> -4408.3217 | R17: gps показывает слив топлива 27 л
A18: РДК 250 | B18: 45536 | D18: =SUMIF($A$30:$A$149,A18,$B$30:$B$149) -> 0 | F18: =C18+D18-E18 -> 0 | I18: =H18-G18 -> 0 | J18: 0 | M18: #N/A | N18: =F18/I18 -> #DIV/0! | P18: =F18*$K$25 -> 0 | Q18: =O18-P18 -> 0
A19: Автокран XCMG 55 | B19: 45536 | C19: 170 | D19: =SUMIF($A$30:$A$149,A19,$B$30:$B$149) -> 299.95 | E19: 40 | F19: =C19+D19-E19 -> 429.95 | I19: =L19*0.7 -> 35 | J19: 0 | L19: 50 | M19: 5.1 | N19: =F19/I19 -> 12.284286 | O19: =290.07*I19 -> 10152.45 | P19: =F19*$K$25 -> 21763.578 | Q19: =O19-P19 -> -11611.128 | R19: не работает мотосчетчик
A20: Автокран XCMG | B20: 45536 | C20: 230 | D20: =SUMIF($A$30:$A$149,A20,$B$30:$B$149) -> 250 | E20: 60 | F20: =C20+D20-E20 -> 420 | G20: 6073 | H20: 6142 | I20: =H20-G20 -> 69 | J20: 0 | L20: 195 | M20: 3.2 | N20: =F20/I20 -> 6.0869565 | O20: =182.4*I20 -> 12585.6 | P20: =F20*$K$25 -> 21259.92 | Q20: =O20-P20 -> -8674.3204 | R20: gps показывает слив топлива 242 л
A21: Автокран Клинцы | B21: 45536 | C21: 230 | D21: =SUMIF($A$30:$A$149,A21,$B$30:$B$149) -> 229.83 | E21: 152 | F21: =C21+D21-E21 -> 307.83 | I21: =L21*0.7 -> 110.6 | J21: 0 | L21: 158 | M21: 2.9 | N21: =F21/I21 -> 2.7832731 | O21: =I21*165.3+28.5*K21 -> 18282.18 | P21: =F21*$K$25 -> 15582.003 | Q21: =O21-P21 -> 2700.1769 | R21: не работает мотосчетчик , gps показывает слив топлива 784 л
C22: =SUM(C5:C21) -> 2035 | D22: =SUM(D2:D21) -> 10413.17 | E22: =SUM(E2:E21) -> 1583
D23: =D22-B150 -> 0
J25: Стоимость 1 л | K25: =SUM(C30:C149)/B150 -> 50.618858
A28: Заправки АЗС
A29: Наименование | B29: Количество | C29: Сумма | D29: АЗС
A30: Экскаватор JCB | B30: 78.63 | C30: =B30*50.5 -> 3970.815 | D30: Авиас
A31: Экскаватор JCB | B31: 100 | C31: =B31*50.5 -> 5050 | D31: Авиас
A32: Экскаватор JCB | B32: 100 | C32: =B32*50.5 -> 5050 | D32: Авиас
A33: Экскаватор JCB | B33: 100 | C33: =B33*50.5 -> 5050 | D33: Авиас
A34: Экскаватор JCB | B34: 97.24 | C34: =B34*50.5 -> 4910.62 | D34: Авиас
A35: Экскаватор JCB | B35: 35.71 | C35: =B35*50.5 -> 1803.355 | D35: Авиас
A36: Экскаватор JCB | B36: 100 | C36: =B36*50.5 -> 5050 | D36: Авиас
A37: Экскаватор JCB | B37: 100 | C37: =B37*50.5 -> 5050 | D37: Авиас
A38: Автокран Клинцы | B38: 100 | C38: =B38*50.5 -> 5050 | D38: Авиас
A39: Автокран Клинцы | B39: 123.63 | C39: =B39*50.5 -> 6243.315 | D39: Авиас
A40: Автокран Клинцы | B40: 6.2 | C40: =B40*50.5 -> 313.1 | D40: Авиас
A41: МАЗ 264 | B41: 100 | C41: =B41*50.5 -> 5050 | D41: Авиас
... A64: Самосвал МАЗ | B64: 158 | C64: =B64*50.5 -> 7979 | D64: Авиас
C65: =B65*50.5 -> 0 | D65: Авиас
C66: =B66*50.5 -> 0 | D66: Авиас
C67: =B67*50.5 -> 0 | D67: Авиас
C68: =B68*50.5 -> 0 | D68: Авиас
D69: Авиас
E72: =SUM(C30:C72) -> 168680.61
A73: Автокран XCMG | B73: 100 | C73: 5349 | D73: Амик
A74: Автокран XCMG | B74: 100 | C74: 5349 | D74: Амик
A75: Автокран XCMG | B75: 50 | C75: 2674.5 | D75: Амик
A76: Самосвал Камаз | B76: 140 | C76: 7488.6 | D76: Амик
A77: Автокран XCMG 55 | B77: 60.49 | C77: 3235.61 | D77: Амик
A78: Автокран XCMG 55 | B78: 17.65 | C78: 944.1 | D78: Амик
A79: Автокран XCMG 55 | B79: 21.81 | C79: 1166.62 | D79: Амик
A80: Автокран XCMG 55 | B80: 100 | C80: 5349 | D80: Амик
A81: Автокран XCMG 55 | B81: 100 | C81: 5349 | D81: Амик
A82: Экскаватор JCB 2013 | B82: 100 | C82: 5349 | D82: Амик
A83: Экскаватор JCB 2013 | B83: 100 | C83: 5349 | D83: Амик
A84: Экскаватор JCB 2013 | B84: 100 | C84: 5349 | D84: Амик
... A96: Экскаватор JCB 220 | B96: 60.9 | C96: 3257.54 | D96: Амик
D97: Амик
D98: Амик
D99: Амик
D100: Амик
D101: Амик
D102: Амик
E103: =SUM(C73:C103) -> 108380.91
D104: КЛО
D105: КЛО
D106: КЛО
D107: КЛО | E107: =SUM(C104:C107) -> 0
A108: МАЗ 265 | B108: 165.3 | C108: 8098.05 | D108: ВОГ
A109: Телескоп 2 | B109: =100+100 -> 200 | C109: =4899+5599 -> 10498 | D109: ВОГ
A110: Телескоп 2 | B110: 200 | C110: 9798 | D110: ВОГ
A111: Самосвал МАЗ №2 | B111: 100 | C111: 4899 | D111: ВОГ
A112: Самосвал МАЗ №2 | B112: 120 | C112: 5878.8 | D112: ВОГ
A113: Самосвал МАЗ №2 | B113: 182.46 | C113: 8938.71 | D113: ВОГ
A114: Самосвал МАЗ №2 | B114: 160.74 | C114: 7874.65 | D114: ВОГ
A115: Самосвал МАЗ №2 | B115: =176.82+200 -> 376.82 | C115: =8662.41+11198 -> 19860.41 | D115: ВОГ
A116: Экскаватор JCB 3CX 2008 | B116: =258.66+100 -> 358.66 | C116: =12671.75+5599 -> 18270.75 | D116: ВОГ
A117: Экскаватор JCB 3CX 2008 | B117: 132.71 | C117: 6501.46 | D117: ВОГ
D118: ВОГ
E120: =SUM(C108:C120) -> 100617.83
A121: Самосвал МАЗ | D121: КЛО | E121: =SUM(C121:C121) -> 0
A122: Экскаватор JCB 220 | B122: 160 | C122: 7838.4 | D122: ОККО
A123: Экскаватор JCB 220 | B123: 160 | C123: 7838.4 | D123: ОККО
A124: Экскаватор JCB 220 | B124: 240.07 | C124: 11761.03 | D124: ОККО
A125: Экскаватор JCB 220 | B125: 240 | C125: 11757.6 | D125: ОККО
A126: Экскаватор JCB 220 | B126: 160 | C126: 7838.4 | D126: ОККО
A127: Экскаватор JCB 220 | B127: -138.3 | C127: -6775.32 | D127: ОККО
A128: Экскаватор JCB 220 | B128: 138.3 | C128: 6775.32 | D128: ОККО
A129: Экскаватор JCB 220 | B129: 310.09 | C129: 15191.31 | D129: ОККО
A130: Экскаватор JCB 220 | B130: 243.18 | C130: 11913.39 | D130: ОККО
A131: Экскаватор JCB 220 | B131: 156.81 | C131: 7682.12 | D131: ОККО
A132: Экскаватор JCB | B132: 263.3 | C132: 12899.07 | D132: ОККО
A133: Экскаватор JCB 3CX 2008 | B133: 100 | C133: 4899 | D133: ОККО
... A144: Самосвал Камаз | B144: 114.47 | C144: 5607.89 | D144: ОККО
D145: ОККО
D146: ОККО
D147: ОККО
D148: ОККО
D149: ОККО | E149: =SUM(C122:C149) -> 149423.43
...

Sheet Топливо Июль 2024
A1: Наименование | B1: Отчетный период | C1: Остаток на начало | D1: Топливо заправленное | E1: Остаток на конец | F1: Расход топлива за период, л | G1: Моточасы на начало | H1: Моточасы на конец | I1: Отработано техникой моточасов | J1: Перегон на доругой объект, л | K1: Перегон на доругой объект, км | L1: Часы работы на обьекте | M1: Норма расхода топлива литр/1 мото час согласно сс | N1: Факт витрат на 1 мото/год, км витрат (л/год) | O1: PL план , грн | P1: PL факт , грн | Q1: Diff, грн | R1: Примечание по строке
A2: Телескоп 1 | B2: 45474 | C2: 80 | D2: =SUMIF($A$30:$A$112,A2,$B$30:$B$112) -> 0 | F2: =C2+D2-E2 -> 80 | G2: ='[4]Июнь 2024 '!H2 -> 14075 | I2: =H2-G2 -> -14075 | J2: 0 | L2: 0 | M2: =VLOOKUP(A2,[4]Тарас!$C$4:$P$23,14,0) -> 3.4 | O2: =194.94*I2 -> -2743780.5 | P2: =F2*$K$25 -> 4116.5561 | Q2: =O2-P2 -> -2747897.1
A3: Телескоп 2 | B3: 45474 | C3: 120 | D3: =SUMIF($A$30:$A$112,A3,$B$30:$B$112) -> 100 | E3: 40 | F3: =C3+D3-E3 -> 180 | G3: 10647 | H3: 10718 | I3: =H3-G3 -> 71 | J3: 0 | L3: 82 | M3: 3.4 | N3: =F3/I3 -> 2.5352113 | O3: =194.94*I3 -> 13840.74 | P3: =F3*$K$25 -> 9262.2512 | Q3: =O3-P3 -> 4578.4888
A4: Телескоп JCB 533-105 (№3) | B4: 45474 | C4: 0 | D4: =SUMIF($A$30:$A$112,A4,$B$30:$B$112) -> 0 | F4: =C4+D4-E4 -> 0 | G4: 0 | J4: 0 | M4: #N/A | N4: =F4/I4 -> #DIV/0! | O4: =194.94*I4 -> 0 | P4: =F4*$K$25 -> 0 | Q4: =O4-P4 -> 0
A5: Телескоп JCB 535-140 (№4) | B5: 45474 | C5: 110 | D5: =SUMIF($A$30:$A$112,A5,$B$30:$B$112) -> 860 | E5: 115 | F5: =C5+D5-E5 -> 855 | G5: 9280 | H5: 9455 | I5: =H5-G5 -> 175 | J5: 0 | L5: 242 | M5: 3.4 | N5: =F5/I5 -> 4.8857143 | O5: =194.94*I5 -> 34114.5 | P5: =F5*$K$25 -> 43995.693 | Q5: =O5-P5 -> -9881.1932
A6: Телескоп JCB 540-170 №5 | B6: 45474 | C6: 60 | D6: =SUMIF($A$30:$A$112,A6,$B$30:$B$112) -> 0 | E6: 50 | F6: =C6+D6-E6 -> 10 | G6: 0 | I6: =L6*0.53 -> 1.59 | J6: 0 | L6: 3 | M6: 3.4 | N6: =F6/I6 -> 6.2893082 | O6: =194.94*I6 -> 309.9546 | P6: =F6*$K$25 -> 514.56951 | Q6: =O6-P6 -> -204.61491 | R6: не работает мотосчетчик
A7: Виброкаток | B7: 45474 | C7: 85 | D7: =SUMIF($A$30:$A$112,A7,$B$30:$B$112) -> 83 | E7: 150 | F7: =C7+D7-E7 -> 18 | G7: 4948 | H7: 4958 | I7: =H7-G7 -> 10 | J7: 0 | L7: 9 | M7: 5 | N7: =F7/I7 -> 1.8 | O7: =285*I7 -> 2850 | P7: =F7*$K$25 -> 926.22512 | Q7: =O7-P7 -> 1923.7749
A8: Ротор Пегасус | B8: 45474 | C8: 0 | D8: =SUMIF($A$30:$A$112,A8,$B$30:$B$112) -> 0 | F8: =C8+D8-E8 -> 0 | G8: 0 | I8: =H8-G8 -> 0 | J8: 0 | M8: #N/A | N8: =F8/I8 -> #DIV/0! | P8: =F8*$K$25 -> 0 | Q8: =O8-P8 -> 0
A9: Экскаватор JCB | B9: 45474 | C9: 70 | D9: =SUMIF($A$30:$A$112,A9,$B$30:$B$112) -> 800 | E9: 70 | F9: =C9+D9-E9 -> 800 | G9: 17307 | H9: 17434 | I9: =H9-G9 -> 127 | J9: 0 | L9: 198 | M9: 4.1 | N9: =F9/I9 -> 6.2992126 | O9: =235.41*I9 -> 29897.07 | P9: =F9*$K$25 -> 41165.561 | Q9: =O9-P9 -> -11268.491
A10: Экскаватор JCB 3CX 2008 | B10: 45474 | C10: 20 | D10: =SUMIF($A$30:$A$112,A10,$B$30:$B$112) -> 799.94 | E10: 30 | F10: =C10+D10-E10 -> 789.94 | G10: 39553 | H10: 39728 | I10: =H10-G10 -> 175 | J10: 0 | L10: 233 | M10: 4.1 | N10: =F10/I10 -> 4.5139429 | O10: =235.41*I10 -> 41196.75 | P10: =F10*$K$25 -> 40647.904 | Q10: =O10-P10 -> 548.84607
A11: Экскаватор JCB 2013 | B11: 45474 | C11: 10 | D11: =SUMIF($A$30:$A$112,A11,$B$30:$B$112) -> 850 | E11: 15 | F11: =C11+D11-E11 -> 845 | G11: 11904 | H11: 12082 | I11: =H11-G11 -> 178 | J11: 0 | L11: 237 | M11: 4.1 | N11: =F11/I11 -> 4.747191 | O11: =235.41*I11 -> 41902.98 | P11: =F11*$K$25 -> 43481.124 | Q11: =O11-P11 -> -1578.1437
A12: Экскаватор JCB 220 | B12: 45474 | C12: 80 | D12: =SUMIF($A$30:$A$112,A12,$B$30:$B$112) -> 0 | F12: =C12+D12-E12 -> 80 | G12: 7096 | I12: =H12-G12 -> -7096 | J12: 0 | M12: 10.5 | N12: =F12/I12 -> -0.011273957 | O12: =595.65*I12 -> -4226732.4 | P12: =F12*$K$25 -> 4116.5561 | Q12: =O12-P12 -> -4230849
A13: МАЗ 264 | B13: 45474 | C13: 40 | D13: =SUMIF($A$30:$A$112,A13,$B$30:$B$112) -> 400 | E13: 130 | F13: =C13+D13-E13 -> 310 | G13: 31643 | H13: 31832 | I13: =H13-G13 -> 189 | J13: 0 | L13: 175 | M13: 0.9 | N13: =F13/I13 -> 1.6402116 | O13: =(51.3*(I13-K13))+(K13*14.25) -> 9695.7 | P13: =F13*$K$25 -> 15951.655 | Q13: =O13-P13 -> -6255.9548 | R13: слив 15.2 л
A14: МАЗ 265 | B14: 45474 | C14: 140 | D14: =SUMIF($A$30:$A$112,A14,$B$30:$B$112) -> 500 | E14: 150 | F14: =C14+D14-E14 -> 490 | G14: 34719 | H14: 35350 | I14: =H14-G14 -> 631 | J14: 0 | L14: 135 | M14: 0.9 | N14: =F14/I14 -> 0.77654517 | O14: =(51.3*(I14-K14))+(K14*14.25) -> 32370.3 | P14: =F14*$K$25 -> 25213.906 | Q14: =O14-P14 -> 7156.394 | R14: слив 10,47 л
A15: Самосвал Камаз | B15: 45474 | C15: 130 | D15: =SUMIF($A$30:$A$112,A15,$B$30:$B$112) -> 200 | E15: 137 | F15: =C15+D15-E15 -> 193 | G15: 559353 | H15: 559550 | I15: =H15-G15 -> 197 | J15: 0 | L15: 128 | M15: 0.9 | N15: =F15/I15 -> 0.97969543 | O15: =(51.3*(I15-K15))+(K15*19.85) -> 10106.1 | P15: =F15*$K$25 -> 9931.1916 | Q15: =O15-P15 -> 174.90844 | R15: слив 509 л
A16: Самосвал МАЗ | B16: 45474 | C16: 240 | D16: =SUMIF($A$30:$A$112,A16,$B$30:$B$112) -> 59.54 | E16: 160 | F16: =C16+D16-E16 -> 139.54 | G16: 64160 | H16: 64239 | I16: =H16-G16 -> 79 | J16: 0 | L16: 16 | M16: 0.9 | N16: =F16/I16 -> 1.7663291 | O16: =(51.3*(I16-K16))+(K16*19.85) -> 4052.7 | P16: =F16*$K$25 -> 7180.303 | Q16: =O16-P16 -> -3127.603 | R16: слив 16,5 л
A17: РДК 250 | B17: 45474 | C17: 0 | D17: =SUMIF($A$30:$A$112,A17,$B$30:$B$112) -> 0 | F17: =C17+D17-E17 -> 0 | G17: 0 | I17: =H17-G17 -> 0 | J17: 0 | M17: #N/A | N17: =F17/I17 -> #DIV/0! | P17: =F17*$K$25 -> 0 | Q17: =O17-P17 -> 0
A18: Автокран XCMG 55 | B18: 45474 | C18: 130 | D18: =SUMIF($A$30:$A$112,A18,$B$30:$B$112) -> 380 | E18: 190 | F18: =C18+D18-E18 -> 320 | G18: 0 | I18: =L18*0.7 -> 70 | J18: 0 | L18: 100 | M18: 5.1 | N18: =F18/I18 -> 4.5714286 | O18: =290.07*I18 -> 20304.9 | P18: =F18*$K$25 -> 16466.224 | Q18: =O18-P18 -> 3838.6757 | R18: не работает мотосчетчик, слив 127 л
A19: Автокран XCMG | B19: 45474 | C19: 100 | D19: =SUMIF($A$30:$A$112,A19,$B$30:$B$112) -> 570 | E19: 180 | F19: =C19+D19-E19 -> 490 | G19: 5827 | H19: 5973 | I19: =H19-G19 -> 146 | J19: 0 | L19: 274 | M19: 3.2 | N19: =F19/I19 -> 3.3561644 | O19: =182.4*I19 -> 26630.4 | P19: =F19*$K$25 -> 25213.906 | Q19: =O19-P19 -> 1416.494 | R19: слив 3435 л
A20: Автокран Клинцы | B20: 45474 | C20: 230 | D20: =SUMIF($A$30:$A$112,A20,$B$30:$B$112) -> 300 | E20: 230 | F20: =C20+D20-E20 -> 300 | G20: ='[4]Июнь 2024 '!H20 -> 0 | I20: =L20*0.7 -> 16.1 | J20: 0 | K20: 360 | L20: 23 | M20: 2.9 | N20: =F20/I20 -> 18.63354 | O20: =I20*165.3+28.5*K20 -> 12921.33 | P20: =F20*$K$25 -> 15437.085 | Q20: =O20-P20 -> -2515.7553 | R20: не работает мотосчетчик слив 400 л
A21: Подъемник Haulotte №1 | B21: 45474 | C21: ='[4]Июнь 2024 '!E21 -> 0 | D21: =SUMIF($A$30:$A$112,A21,$B$30:$B$112) -> 0 | F21: =C21+D21-E21 -> 0 | G21: ='[4]Июнь 2024 '!H21 -> 0 | I21: 0 | J21: 0 | N21: =VLOOKUP(A21,[4]Тарас!$C$4:$N$23,12,0) -> #N/A | O21: =194.94*I21 -> 0 | P21: =F21*$K$25 -> 0 | Q21: =O21-P21 -> 0
C22: =SUM(C2:C21) -> 1645 | D22: =SUM(D2:D21) -> 5902.48 | E22: =SUM(E2:E21) -> 1647
D23: =D22-B113 -> 0
J25: Стоимость 1 л | K25: =SUM(C30:C112)/B113 -> 51.456951
A28: Заправки АЗС
A29: Наименование | B29: Количество | C29: Сумма | D29: АЗС
A30: Экскаватор JCB | B30: 100 | C30: =B30*47.63 -> 4763 | D30: Авиас
A31: Экскаватор JCB | B31: 100 | C31: =B31*47.63 -> 4763 | D31: Авиас
A32: Экскаватор JCB | B32: 100 | C32: =B32*47.63 -> 4763 | D32: Авиас
A33: Экскаватор JCB | B33: 100 | C33: =B33*47.63 -> 4763 | D33: Авиас
A34: Экскаватор JCB | B34: 100 | C34: =B34*47.63 -> 4763 | D34: Авиас
A35: Экскаватор JCB | B35: 100 | C35: =B35*47.63 -> 4763 | D35: Авиас
A36: Экскаватор JCB | B36: 100 | C36: =B36*47.63 -> 4763 | D36: Авиас
A37: Экскаватор JCB | B37: 100 | C37: =B37*47.63 -> 4763 | D37: Авиас
A38: МАЗ 265 | B38: 100 | C38: =B38*47.63 -> 4763 | D38: Авиас
A39: МАЗ 265 | B39: 100 | C39: =B39*47.63 -> 4763 | D39: Авиас
A40: МАЗ 265 | B40: 100 | C40: =B40*47.63 -> 4763 | D40: Авиас
A41: МАЗ 265 | B41: 100 | C41: =B41*47.63 -> 4763 | D41: Авиас
... A47: МАЗ 264 | B47: 100 | C47: =B47*47.63 -> 4763 | D47: Авиас
E48: =SUM(C30:C48) -> 85734
A49: Автокран XCMG | B49: 50 | C49: 2649.5 | D49: Амик
A50: Автокран XCMG | B50: 40 | C50: 2119.6 | D50: Амик
A51: Автокран XCMG | B51: 160 | C51: 8478.4 | D51: Амик
A52: Автокран XCMG | B52: 160 | C52: 8478.4 | D52: Амик
A53: Автокран XCMG | B53: 160 | C53: 8558.4 | D53: Амик
A54: Самосвал Камаз | B54: 100 | C54: 5299 | D54: Амик
A55: Самосвал Камаз | B55: 100 | C55: 5349 | D55: Амик
A56: Автокран XCMG 55 | B56: 100 | C56: 5099 | D56: Амик
A57: Автокран XCMG 55 | B57: 100 | C57: 5099 | D57: Амик
A58: Автокран XCMG 55 | B58: 150 | C58: 8023.5 | D58: Амик
A59: Автокран XCMG 55 | B59: 30 | C59: 1604.7 | D59: Амик
A60: Экскаватор JCB 2013 | B60: 100 | C60: 5299 | D60: Амик
... A80: Телескоп JCB 535-140 (№4) | B80: 100 | C80: 5399 | D80: Амик
E81: =SUM(C49:C81) -> 150761.4
A82: Самосвал МАЗ | B82: 59.54 | C82: 3280.06 | D82: КЛО
A83: Экскаватор JCB 3CX 2008 | B83: 799.94 | C83: 44068.695 | D83: КЛО
A84: Виброкаток | B84: 83 | C84: 4572.47 | D84: КЛО
A85: Телескоп 2 | B85: 100 | C85: 5509 | D85: КЛО | E85: =SUM(C82:C85) -> 57430.225
A86: Автокран Клинцы | B86: 100 | C86: 4899 | D86: ВОГ
A87: Автокран Клинцы | B87: 100 | C87: 4899 | D87: ВОГ
E88: =SUM(C86:C88) -> 9798
D95: КЛО
D96: КЛО
D97: КЛО | F97: =-337162.41-C93 -> -337162.41
D98: ОККО
D99: ОККО
D100: ОККО
D101: ОККО
D102: ОККО
D103: ОККО
D104: ОККО
D105: ОККО
D106: ОККО
D107: ОККО
D108: ОККО
D109: ОККО
... D111: ОККО
D112: ОККО | E112: =SUM(C98:C112) -> 0
B113: =SUM(B30:B112) -> 5902.48 | C113: =SUM(C30:C112) -> 303723.62

Sheet Топливо Октябрь  2024  (2)
A1: Наименование | B1: Отчетный период | C1: Остаток на начало | D1: Топливо заправленное | E1: Остаток на конец | F1: Расход топлива за период, л | G1: Моточасы на начало | H1: Моточасы на конец | I1: Отработано техникой моточасов | J1: Перегон на доругой объект, л | K1: Перегон на доругой объект, км | L1: Часы работы на обьекте | M1: Норма расхода топлива литр/1 мото час согласно сс | N1: Факт витрат на 1 мото/год, км витрат (л/год) | O1: Отклонения л/мотогод | P1: Отклонения, грн/мес | Q1: Водитель | R1: Примечание по строке | S1: Начислено зп, грн | T1: Разница начисление от недостачи топлива, грн
A2: Телескоп 1 | B2: 45474 | C2: 80 | D2: =SUMIF($A$30:$A$188,A2,$B$30:$B$188) -> 0 | F2: =C2+D2-E2 -> 80 | G2: ='[4]Июнь 2024 '!H2 -> 14075 | I2: =H2-G2 -> -14075 | J2: 0 | L2: 0 | M2: =VLOOKUP(A2,[4]Тарас!$C$4:$P$23,14,0) -> 3.4 | O2: =194.94*I2 -> -2743780.5 | P2: =F2*$K$25 -> 3915.4135 | Q2: =O2-P2 -> -2747695.9
A3: Телескоп 2 | B3: 45566 | C3: 30 | D3: =SUMIF($A$30:$A$188,A3,$B$30:$B$188) -> 1057.02 | E3: 60 | F3: =C3+D3-E3 -> 1027.02 | H3: 10943 | I3: =L3*0.53 -> 94.34 | L3: 178 | M3: 3.4 | N3: =F3/I3 -> 10.886368 | O3: =N3-M3 -> 7.4863685 | P3: =O3*I3*$K$25 -> 34566.445 | Q3: Косик Ю.А. | S3: 2900
A4: Телескоп JCB 533-105 (№3) | B4: 45536 | D4: =SUMIF($A$30:$A$188,A4,$B$30:$B$188) -> 0 | F4: =C4+D4-E4 -> 0 | J4: 0 | M4: #N/A | N4: =F4/I4 -> #DIV/0! | O4: =N4-M4 -> #DIV/0! | P4: =O4*I4*K26 -> #DIV/0!
A5: Телескоп JCB 535-140 (№4) | B5: 45566 | C5: 10 | D5: =SUMIF($A$30:$A$188,A5,$B$30:$B$188) -> 890 | E5: 60 | F5: =C5+D5-E5 -> 840 | G5: 9842 | H5: 10004 | I5: =H5-G5 -> 162 | J5: 0 | L5: 253 | M5: 3.4 | N5: =F5/I5 -> 5.1851852 | O5: =N5-M5 -> 1.7851852 | P5: =O5*I5*$K$25 -> 14154.22 | Q5: Мазуренко Е.В. | S5: 57000 | T5: =S5-P5 -> 42845.78
A6: Телескоп JCB 540-170 №5 | B6: 45566 | C6: 20 | D6: =SUMIF($A$30:$A$188,A6,$B$30:$B$188) -> 828 | E6: 70 | F6: =C6+D6-E6 -> 778 | I6: =L6*0.53 -> 108.65 | J6: 0 | L6: 205 | M6: 3.4 | N6: =F6/I6 -> 7.1606075 | O6: =N6-M6 -> 3.7606075 | P6: =O6*I6*$K$25 -> 19997.485 | Q6: Косик Ю.А. | S6: 33300
A7: Виброкаток | B7: 45566 | C7: 65 | D7: =SUMIF($A$30:$A$188,A7,$B$30:$B$188) -> 60 | E7: 85 | F7: =C7+D7-E7 -> 40 | G7: 4981 | H7: 4992 | I7: =H7-G7 -> 11 | J7: 0 | L7: 3 | M7: 5 | N7: =F7/I7 -> 3.6363636 | O7: =N7-M7 -> -1.3636364 | P7: =O7*I7*K29 -> 0
A8: Ротор Пегасус | B8: 45566 | D8: =SUMIF($A$30:$A$188,A8,$B$30:$B$188) -> 0 | F8: =C8+D8-E8 -> 0 | I8: =H8-G8 -> 0 | J8: 0 | M8: #N/A | N8: =F8/I8 -> #DIV/0! | O8: =N8-M8 -> #DIV/0! | P8: =O8*I8*K30 -> #DIV/0!
A9: Экскаватор JCB | B9: 45566 | C9: 10 | D9: =SUMIF($A$30:$A$188,A9,$B$30:$B$188) -> 840.05 | E9: 50 | F9: =C9+D9-E9 -> 800.05 | G9: 17802 | H9: 18010 | I9: =H9-G9 -> 208 | J9: 0 | L9: 216 | M9: 4.1 | N9: =F9/I9 -> 3.8463942 | O9: =N9-M9 -> -0.25360577 | P9: =O9*I9*K31 -> 0
A10: Экскаватор JCB 3CX 2008 | B10: 45566 | C10: 20 | D10: =SUMIF($A$30:$A$188,A10,$B$30:$B$188) -> 830 | E10: 80 | F10: =C10+D10-E10 -> 770 | I10: =L10*0.55 -> 97.35 | J10: 0 | L10: 177 | M10: 4.1 | N10: =F10/I10 -> 7.9096045 | O10: =N10-M10 -> 3.8096045 | P10: =O10*I10*$K$25 -> 18151.123 | Q10: Ковальчук В.В. | S10: 36400 | T10: =S10-P10 -> 18248.877
A11: Экскаватор JCB 2013 | B11: 45566 | C11: 20 | D11: =SUMIF($A$30:$A$188,A11,$B$30:$B$188) -> 0 | E11: 20 | F11: =C11+D11-E11 -> 0 | I11: =H11-G11 -> 0 | J11: 0 | M11: 4.1 | O11: =N11-M11 -> -4.1 | P11: =O11*I11*K33 -> 0
A12: Экскаватор JCB 220 | B12: 45566 | C12: 301 | D12: =SUMIF($A$30:$A$188,A12,$B$30:$B$188) -> 2127.9 | E12: 129 | F12: =C12+D12-E12 -> 2299.9 | G12: 7387 | H12: 7583 | I12: =H12-G12 -> 196 | J12: 0 | L12: 230 | M12: 10.5 | N12: =F12/I12 -> 11.734184 | O12: =N12-M12 -> 1.2341837 | P12: =O12*I12*K34 -> 0 | R12: gps показывает слив топлива 539 л
A13: МАЗ 264 | B13: 45566 | C13: 150 | D13: =SUMIF($A$30:$A$188,A13,$B$30:$B$188) -> 788.69 | E13: 40 | F13: =C13+D13-E13 -> 898.69 | G13: 32692 | H13: 33450 | I13: =H13-G13 -> 758 | J13: 0 | L13: 214 | M13: 0.9 | N13: =F13/I13 -> 1.1856069 | O13: =N13-M13 -> 0.28560686 | P13: =O13*I13*$K$25 -> 10595.598 | Q13: Черненко А.С/Самойленко | S13: 35300 | T13: =S13-P13 -> 24704.402
A14: МАЗ 265 | B14: 45566 | C14: 160 | D14: =SUMIF($A$30:$A$188,A14,$B$30:$B$188) -> 876.11 | E14: 150 | F14: =C14+D14-E14 -> 886.11 | G14: 37210 | H14: 38463 | I14: =H14-G14 -> 1253 | J14: 0 | K14: 730 | L14: 197 | M14: 0.9 | N14: =F14/I14 -> 0.70719074 | O14: =(51.3*(I14-K14))+(K14*14.25) -> 37232.4 | P14: =F14*$K$25 -> 43368.588 | Q14: =O14-P14 -> -6136.1883
A15: Самосвал Камаз | B15: 45566 | C15: 204 | D15: =SUMIF($A$30:$A$188,A15,$B$30:$B$188) -> 0 | E15: 204 | F15: =C15+D15-E15 -> 0 | G15: 560504 | I15: =H15-G15 -> -560504 | J15: 0 | M15: 0.9 | N15: =F15/I15 -> 0 | O15: =(51.3*(I15-K15))+(K15*19.85) -> -28753855 | P15: =F15*$K$25 -> 0 | Q15: =O15-P15 -> -28753855
A16: Самосвал МАЗ | B16: 45566 | C16: 181 | D16: =SUMIF($A$30:$A$188,A16,$B$30:$B$188) -> 1545.02 | E16: 130 | F16: =C16+D16-E16 -> 1596.02 | G16: 68211 | H16: 70039 | I16: =H16-G16 -> 1828 | J16: 0 | L16: 228 | M16: 0.9 | N16: =F16/I16 -> 0.87309628 | O16: =(51.3*(I16-K16))+(K16*19.85) -> 93776.4 | P16: =F16*$K$25 -> 78113.478 | Q16: =O16-P16 -> 15662.922 | R16: gps показывает слив топлива 169 л
A17: Самосвал МАЗ №2 | B17: 45566 | C17: 160 | D17: =SUMIF($A$30:$A$188,A17,$B$30:$B$188) -> 2237.81 | E17: 150 | F17: =C17+D17-E17 -> 2247.81 | G17: 64118 | H17: 67426 | I17: =H17-G17 -> 3308 | J17: 0 | K17: 730 | L17: 243 | M17: 0.9 | N17: =F17/I17 -> 0.67950726 | O17: =(51.3*(I17-K17))+(K17*19.85) -> 146741.9 | P17: =F17*$K$25 -> 110013.82 | Q17: =O17-P17 -> 36728.079 | R17: gps показывает слив топлива 206 л
A18: РДК 250 | B18: 45566 | D18: =SUMIF($A$30:$A$188,A18,$B$30:$B$188) -> 0 | F18: =C18+D18-E18 -> 0 | I18: =H18-G18 -> 0 | J18: 0 | M18: #N/A | N18: =F18/I18 -> #DIV/0! | P18: =F18*$K$25 -> 0 | Q18: =O18-P18 -> 0
A19: Автокран XCMG 55 | B19: 45566 | C19: 40 | D19: =SUMIF($A$30:$A$188,A19,$B$30:$B$188) -> 260 | E19: 70 | F19: =C19+D19-E19 -> 230 | I19: =L19*0.7 -> 32.2 | J19: 0 | L19: 46 | M19: 5.1 | N19: =F19/I19 -> 7.1428571 | O19: =290.07*I19 -> 9340.254 | P19: =F19*$K$25 -> 11256.814 | Q19: =O19-P19 -> -1916.5598
A20: Автокран XCMG | B20: 45566 | C20: 60 | D20: =SUMIF($A$30:$A$188,A20,$B$30:$B$188) -> 280 | E20: 224 | F20: =C20+D20-E20 -> 116 | G20: 6142 | H20: 6213 | I20: =H20-G20 -> 71 | J20: 0 | L20: 239 | M20: 3.2 | N20: =F20/I20 -> 1.6338028 | O20: =182.4*I20 -> 12950.4 | P20: =F20*$K$25 -> 5677.3496 | Q20: =O20-P20 -> 7273.0504 | R20: gps показывает слив топлива 37,82 л
A21: Автокран Клинцы | B21: 45566 | C21: 152 | D21: =SUMIF($A$30:$A$188,A21,$B$30:$B$188) -> 493.92 | E21: 40 | F21: =C21+D21-E21 -> 605.92 | I21: =L21*0.7 -> 155.4 | J21: 0 | L21: 222 | M21: 2.9 | N21: =F21/I21 -> 3.8990991 | O21: =I21*165.3+28.5*K21 -> 25687.62 | P21: =F21*$K$25 -> 29655.342 | Q21: =O21-P21 -> -3967.7219 | R21: gps показывает слив топлива 168 л
C22: =SUM(C3:C21) -> 1583 | D22: =SUM(D2:D21) -> 13114.52 | E22: =SUM(E2:E21) -> 1562
D23: =D22-B189 -> 0
J25: Стоимость 1 л | K25: =SUM(C30:C188)/B189 -> 48.942669
A28: Заправки АЗС
A29: Наименование | B29: Количество | C29: Сумма | D29: АЗС
A30: Экскаватор JCB | B30: 46.11 | C30: =B30*48.625 -> 2242.0988 | D30: Авиас
A31: Экскаватор JCB | B31: 53.89 | C31: =B31*48.625 -> 2620.4012 | D31: Авиас
A32: Экскаватор JCB | B32: 114.64 | C32: =B32*48.625 -> 5574.37 | D32: Авиас
A33: Экскаватор JCB | B33: 85.36 | C33: =B33*48.625 -> 4150.63 | D33: Авиас
A34: Экскаватор JCB | B34: 100 | C34: =B34*48.625 -> 4862.5 | D34: Авиас
A35: Экскаватор JCB | B35: 100 | C35: =B35*48.625 -> 4862.5 | D35: Авиас
A36: Экскаватор JCB | B36: 100 | C36: =B36*48.625 -> 4862.5 | D36: Авиас
A37: Экскаватор JCB | B37: 40.05 | C37: =B37*48.625 -> 1947.4312 | D37: Авиас
A38: Экскаватор JCB | B38: 100 | C38: =B38*48.625 -> 4862.5 | D38: Авиас
A39: Экскаватор JCB | B39: 100 | C39: =B39*48.625 -> 4862.5 | D39: Авиас
A40: МАЗ 265 | B40: 100 | C40: =B40*48.625 -> 4862.5 | D40: Авиас
A41: МАЗ 265 | B41: 140.01 | C41: =B41*48.625 -> 6807.9862 | D41: Авиас
... A110: Экскаватор JCB 220 | B110: 150 | C110: =B110*48.625 -> 7293.75 | D110: Авиас
A111: Виброкаток | B111: 60 | C111: =B111*48.625 -> 2917.5 | D111: Авиас | E111: =SUM(C30:C111) -> 467974.78
A112: Автокран XCMG | B112: 120 | C112: 6418.8 | D112: Амик
A113: Автокран XCMG | B113: 160 | C113: 8558.4 | D113: Амик
A114: Автокран XCMG 55 | B114: 160 | C114: 8238.4 | D114: Амик
A115: Автокран XCMG 55 | B115: 100 | C115: 5349 | D115: Амик
A116: Телескоп JCB 535-140 (№4) | B116: 100 | C116: 5349 | D116: Амик
A117: Телескоп JCB 535-140 (№4) | B117: 100 | C117: 5349 | D117: Амик
A118: Телескоп JCB 535-140 (№4) | B118: 100 | C118: 5349 | D118: Амик
A119: Телескоп JCB 535-140 (№4) | B119: 20 | C119: 1069.8 | D119: Амик
A120: Телескоп JCB 535-140 (№4) | B120: 70 | C120: 3744.3 | D120: Амик
A121: Телескоп JCB 535-140 (№4) | B121: 100 | C121: 5349 | D121: Амик
A122: Телескоп JCB 535-140 (№4) | B122: 100 | C122: 5349 | D122: Амик
A123: Телескоп JCB 535-140 (№4) | B123: 100 | C123: 5149 | D123: Амик
A124: Телескоп JCB 535-140 (№4) | B124: 100 | C124: 5349 | D124: Амик
A125: Телескоп JCB 535-140 (№4) | B125: 100 | C125: 5499 | D125: Амик | E125: премиум
D126: Амик
E142: =SUM(C112:C142) -> 76120.7
D143: КЛО
D144: КЛО
D145: КЛО
D146: КЛО | E146: =SUM(C143:C146) -> 0
A147: МАЗ 265 | B147: 145.53 | C147: 7129.51 | D147: ВОГ
A148: МАЗ 265 | B148: 107.23 | C148: 5253.2 | D148: ВОГ
A149: Самосвал МАЗ №2 | B149: 223.69 | C149: 10958.57 | D149: ВОГ
A150: Самосвал МАЗ №2 | B150: 176.95 | C150: 8668.78 | D150: ВОГ
A151: Самосвал МАЗ №2 | B151: 176.96 | C151: 8669.27 | D151: ВОГ
A152: Телескоп 2 | B152: 180 | C152: 7977.6 | D152: ВОГ кубышка
A153: Экскаватор JCB 3CX 2008 | B153: 210 | C153: 9307.2 | D153: ВОГ кубышка
A154: МАЗ 265 | B154: 60 | C154: 2659.2 | D154: ВОГ кубышка
A155: Самосвал МАЗ №2 | B155: 150 | C155: 6648 | D155: ВОГ кубышка
E159: =SUM(C147:C159) -> 67271.33
E160: =SUM(C160:C160) -> 0
A161: Экскаватор JCB 3CX 2008 | B161: 120 | C161: 5878.8 | D161: Окко
A162: Экскаватор JCB 3CX 2008 | B162: 100 | C162: 4899 | D162: Окко
A163: Экскаватор JCB 3CX 2008 | B163: 100 | C163: 4899 | D163: Окко
A164: Экскаватор JCB 3CX 2008 | B164: 100 | C164: 4799 | D164: Окко
A165: Экскаватор JCB 3CX 2008 | B165: 100 | C165: 4799 | D165: Окко
A166: Экскаватор JCB 3CX 2008 | B166: 100 | C166: 4799 | D166: Окко
A167: МАЗ 265 | B167: 10 | C167: 419
E188: =SUM(C161:C188) -> 30492.8
B189: =SUM(B30:B188) -> 13114.52 | C189: =SUM(C30:C188) -> 641859.61

Sheet Топливо Октябрь  2024 
A1: Наименование | B1: Отчетный период | C1: Остаток на начало | D1: Топливо заправленное | E1: Остаток на конец | F1: Расход топлива за период, л | G1: Моточасы на начало | H1: Моточасы на конец | I1: Отработано техникой моточасов | J1: Перегон на доругой объект, л | K1: Перегон на доругой объект, км | L1: Часы работы на обьекте | M1: Норма расхода топлива литр/1 мото час согласно сс | N1: Факт витрат на 1 мото/год, км витрат (л/год) | O1: PL план , грн | P1: PL факт , грн | Q1: Diff, грн | R1: Примечание по строке
A2: Телескоп 1 | B2: 45474 | C2: 80 | D2: =SUMIF($A$30:$A$188,A2,$B$30:$B$188) -> 0 | F2: =C2+D2-E2 -> 80 | G2: ='[4]Июнь 2024 '!H2 -> 14075 | I2: =H2-G2 -> -14075 | J2: 0 | L2: 0 | M2: =VLOOKUP(A2,[4]Тарас!$C$4:$P$23,14,0) -> 3.4 | O2: =194.94*I2 -> -2743780.5 | P2: =F2*$K$25 -> 3915.4135 | Q2: =O2-P2 -> -2747695.9
A3: Телескоп 2 | B3: 45566 | C3: 30 | D3: =SUMIF($A$30:$A$188,A3,$B$30:$B$188) -> 1057.02 | E3: 60 | F3: =C3+D3-E3 -> 1027.02 | H3: 10943 | I3: =L3*0.53 -> 94.34 | L3: 178 | M3: 3.4 | N3: =F3/I3 -> 10.886368 | O3: =194.94*I3 -> 18390.64 | P3: =F3*$K$25 -> 50265.1 | Q3: =O3-P3 -> -31874.46
A4: Телескоп JCB 533-105 (№3) | B4: 45536 | D4: =SUMIF($A$30:$A$188,A4,$B$30:$B$188) -> 0 | F4: =C4+D4-E4 -> 0 | J4: 0 | M4: #N/A | N4: =F4/I4 -> #DIV/0! | O4: =194.94*I4 -> 0 | P4: =F4*$K$25 -> 0 | Q4: =O4-P4 -> 0
A5: Телескоп JCB 535-140 (№4) | B5: 45566 | C5: 10 | D5: =SUMIF($A$30:$A$188,A5,$B$30:$B$188) -> 890 | E5: 60 | F5: =C5+D5-E5 -> 840 | G5: 9842 | H5: 10004 | I5: =H5-G5 -> 162 | J5: 0 | L5: 253 | M5: 3.4 | N5: =F5/I5 -> 5.1851852 | O5: =194.94*I5 -> 31580.28 | P5: =F5*$K$25 -> 41111.842 | Q5: =O5-P5 -> -9531.5619
A6: Телескоп JCB 540-170 №5 | B6: 45566 | C6: 20 | D6: =SUMIF($A$30:$A$188,A6,$B$30:$B$188) -> 828 | E6: 70 | F6: =C6+D6-E6 -> 778 | I6: =L6*0.53 -> 108.65 | J6: 0 | L6: 205 | M6: 3.4 | N6: =F6/I6 -> 7.1606075 | O6: =194.94*I6 -> 21180.231 | P6: =F6*$K$25 -> 38077.396 | Q6: =O6-P6 -> -16897.165
A7: Виброкаток | B7: 45566 | C7: 65 | D7: =SUMIF($A$30:$A$188,A7,$B$30:$B$188) -> 60 | E7: 85 | F7: =C7+D7-E7 -> 40 | G7: 4981 | H7: 4992 | I7: =H7-G7 -> 11 | J7: 0 | L7: 3 | M7: 5 | N7: =F7/I7 -> 3.6363636 | O7: =285*I7 -> 3135 | P7: =F7*$K$25 -> 1957.7068 | Q7: =O7-P7 -> 1177.2932
A8: Ротор Пегасус | B8: 45566 | D8: =SUMIF($A$30:$A$188,A8,$B$30:$B$188) -> 0 | F8: =C8+D8-E8 -> 0 | I8: =H8-G8 -> 0 | J8: 0 | M8: #N/A | N8: =F8/I8 -> #DIV/0! | P8: =F8*$K$25 -> 0 | Q8: =O8-P8 -> 0
A9: Экскаватор JCB | B9: 45566 | C9: 10 | D9: =SUMIF($A$30:$A$188,A9,$B$30:$B$188) -> 840.05 | E9: 50 | F9: =C9+D9-E9 -> 800.05 | G9: 17802 | H9: 18010 | I9: =H9-G9 -> 208 | J9: 0 | L9: 216 | M9: 4.1 | N9: =F9/I9 -> 3.8463942 | O9: =235.41*I9 -> 48965.28 | P9: =F9*$K$25 -> 39156.582 | Q9: =O9-P9 -> 9808.6978
A10: Экскаватор JCB 3CX 2008 | B10: 45566 | C10: 20 | D10: =SUMIF($A$30:$A$188,A10,$B$30:$B$188) -> 830 | E10: 80 | F10: =C10+D10-E10 -> 770 | I10: =L10*0.55 -> 97.35 | J10: 0 | L10: 177 | M10: 4.1 | N10: =F10/I10 -> 7.9096045 | O10: =235.41*I10 -> 22917.164 | P10: =F10*$K$25 -> 37685.855 | Q10: =O10-P10 -> -14768.692
A11: Экскаватор JCB 2013 | B11: 45566 | C11: 20 | D11: =SUMIF($A$30:$A$188,A11,$B$30:$B$188) -> 0 | E11: 20 | F11: =C11+D11-E11 -> 0 | I11: =H11-G11 -> 0 | J11: 0 | M11: 4.1 | O11: =235.41*I11 -> 0 | P11: =F11*$K$25 -> 0 | Q11: =O11-P11 -> 0
A12: Экскаватор JCB 220 | B12: 45566 | C12: 301 | D12: =SUMIF($A$30:$A$188,A12,$B$30:$B$188) -> 2127.9 | E12: 129 | F12: =C12+D12-E12 -> 2299.9 | G12: 7387 | H12: 7583 | I12: =H12-G12 -> 196 | J12: 0 | L12: 230 | M12: 10.5 | N12: =F12/I12 -> 11.734184 | O12: =595.65*I12 -> 116747.4 | P12: =F12*$K$25 -> 112563.24 | Q12: =O12-P12 -> 4184.1558 | R12: gps показывает слив топлива 539 л
A13: МАЗ 264 | B13: 45566 | C13: 150 | D13: =SUMIF($A$30:$A$188,A13,$B$30:$B$188) -> 788.69 | E13: 40 | F13: =C13+D13-E13 -> 898.69 | G13: 32692 | H13: 33450 | I13: =H13-G13 -> 758 | J13: 0 | L13: 214 | M13: 0.9 | N13: =F13/I13 -> 1.1856069 | O13: =(51.3*(I13-K13))+(K13*14.25) -> 38885.4 | P13: =F13*$K$25 -> 43984.287 | Q13: =O13-P13 -> -5098.8871
A14: МАЗ 265 | B14: 45566 | C14: 160 | D14: =SUMIF($A$30:$A$188,A14,$B$30:$B$188) -> 876.11 | E14: 150 | F14: =C14+D14-E14 -> 886.11 | G14: 37210 | H14: 38463 | I14: =H14-G14 -> 1253 | J14: 0 | K14: 730 | L14: 197 | M14: 0.9 | N14: =F14/I14 -> 0.70719074 | O14: =(51.3*(I14-K14))+(K14*14.25) -> 37232.4 | P14: =F14*$K$25 -> 43368.588 | Q14: =O14-P14 -> -6136.1883
A15: Самосвал Камаз | B15: 45566 | C15: 204 | D15: =SUMIF($A$30:$A$188,A15,$B$30:$B$188) -> 0 | E15: 204 | F15: =C15+D15-E15 -> 0 | G15: 560504 | I15: =H15-G15 -> -560504 | J15: 0 | M15: 0.9 | N15: =F15/I15 -> 0 | O15: =(51.3*(I15-K15))+(K15*19.85) -> -28753855 | P15: =F15*$K$25 -> 0 | Q15: =O15-P15 -> -28753855
A16: Самосвал МАЗ | B16: 45566 | C16: 181 | D16: =SUMIF($A$30:$A$188,A16,$B$30:$B$188) -> 1545.02 | E16: 130 | F16: =C16+D16-E16 -> 1596.02 | G16: 68211 | H16: 70039 | I16: =H16-G16 -> 1828 | J16: 0 | L16: 228 | M16: 0.9 | N16: =F16/I16 -> 0.87309628 | O16: =(51.3*(I16-K16))+(K16*19.85) -> 93776.4 | P16: =F16*$K$25 -> 78113.478 | Q16: =O16-P16 -> 15662.922 | R16: gps показывает слив топлива 169 л
A17: Самосвал МАЗ №2 | B17: 45566 | C17: 160 | D17: =SUMIF($A$30:$A$188,A17,$B$30:$B$188) -> 2237.81 | E17: 150 | F17: =C17+D17-E17 -> 2247.81 | G17: 64118 | H17: 67426 | I17: =H17-G17 -> 3308 | J17: 0 | K17: 730 | L17: 243 | M17: 0.9 | N17: =F17/I17 -> 0.67950726 | O17: =(51.3*(I17-K17))+(K17*19.85) -> 146741.9 | P17: =F17*$K$25 -> 110013.82 | Q17: =O17-P17 -> 36728.079 | R17: gps показывает слив топлива 206 л
A18: РДК 250 | B18: 45566 | D18: =SUMIF($A$30:$A$188,A18,$B$30:$B$188) -> 0 | F18: =C18+D18-E18 -> 0 | I18: =H18-G18 -> 0 | J18: 0 | M18: #N/A | N18: =F18/I18 -> #DIV/0! | P18: =F18*$K$25 -> 0 | Q18: =O18-P18 -> 0
A19: Автокран XCMG 55 | B19: 45566 | C19: 40 | D19: =SUMIF($A$30:$A$188,A19,$B$30:$B$188) -> 260 | E19: 70 | F19: =C19+D19-E19 -> 230 | I19: =L19*0.7 -> 32.2 | J19: 0 | L19: 46 | M19: 5.1 | N19: =F19/I19 -> 7.1428571 | O19: =290.07*I19 -> 9340.254 | P19: =F19*$K$25 -> 11256.814 | Q19: =O19-P19 -> -1916.5598
A20: Автокран XCMG | B20: 45566 | C20: 60 | D20: =SUMIF($A$30:$A$188,A20,$B$30:$B$188) -> 280 | E20: 224 | F20: =C20+D20-E20 -> 116 | G20: 6142 | H20: 6213 | I20: =H20-G20 -> 71 | J20: 0 | L20: 239 | M20: 3.2 | N20: =F20/I20 -> 1.6338028 | O20: =182.4*I20 -> 12950.4 | P20: =F20*$K$25 -> 5677.3496 | Q20: =O20-P20 -> 7273.0504 | R20: gps показывает слив топлива 37,82 л
A21: Автокран Клинцы | B21: 45566 | C21: 152 | D21: =SUMIF($A$30:$A$188,A21,$B$30:$B$188) -> 493.92 | E21: 40 | F21: =C21+D21-E21 -> 605.92 | I21: =L21*0.7 -> 155.4 | J21: 0 | L21: 222 | M21: 2.9 | N21: =F21/I21 -> 3.8990991 | O21: =I21*165.3+28.5*K21 -> 25687.62 | P21: =F21*$K$25 -> 29655.342 | Q21: =O21-P21 -> -3967.7219 | R21: gps показывает слив топлива 168 л
C22: =SUM(C3:C21) -> 1583 | D22: =SUM(D2:D21) -> 13114.52 | E22: =SUM(E2:E21) -> 1562
D23: =D22-B189 -> 0
J25: Стоимость 1 л | K25: =SUM(C30:C188)/B189 -> 48.942669
A28: Заправки АЗС
A29: Наименование | B29: Количество | C29: Сумма | D29: АЗС
A30: Экскаватор JCB | B30: 46.11 | C30: =B30*48.625 -> 2242.0988 | D30: Авиас
A31: Экскаватор JCB | B31: 53.89 | C31: =B31*48.625 -> 2620.4012 | D31: Авиас
A32: Экскаватор JCB | B32: 114.64 | C32: =B32*48.625 -> 5574.37 | D32: Авиас
A33: Экскаватор JCB | B33: 85.36 | C33: =B33*48.625 -> 4150.63 | D33: Авиас
A34: Экскаватор JCB | B34: 100 | C34: =B34*48.625 -> 4862.5 | D34: Авиас
A35: Экскаватор JCB | B35: 100 | C35: =B35*48.625 -> 4862.5 | D35: Авиас
A36: Экскаватор JCB | B36: 100 | C36: =B36*48.625 -> 4862.5 | D36: Авиас
A37: Экскаватор JCB | B37: 40.05 | C37: =B37*48.625 -> 1947.4312 | D37: Авиас
A38: Экскаватор JCB | B38: 100 | C38: =B38*48.625 -> 4862.5 | D38: Авиас
A39: Экскаватор JCB | B39: 100 | C39: =B39*48.625 -> 4862.5 | D39: Авиас
A40: МАЗ 265 | B40: 100 | C40: =B40*48.625 -> 4862.5 | D40: Авиас
A41: МАЗ 265 | B41: 140.01 | C41: =B41*48.625 -> 6807.9862 | D41: Авиас
... A110: Экскаватор JCB 220 | B110: 150 | C110: =B110*48.625 -> 7293.75 | D110: Авиас
A111: Виброкаток | B111: 60 | C111: =B111*48.625 -> 2917.5 | D111: Авиас | E111: =SUM(C30:C111) -> 467974.78
A112: Автокран XCMG | B112: 120 | C112: 6418.8 | D112: Амик
A113: Автокран XCMG | B113: 160 | C113: 8558.4 | D113: Амик
A114: Автокран XCMG 55 | B114: 160 | C114: 8238.4 | D114: Амик
A115: Автокран XCMG 55 | B115: 100 | C115: 5349 | D115: Амик
A116: Телескоп JCB 535-140 (№4) | B116: 100 | C116: 5349 | D116: Амик
A117: Телескоп JCB 535-140 (№4) | B117: 100 | C117: 5349 | D117: Амик
A118: Телескоп JCB 535-140 (№4) | B118: 100 | C118: 5349 | D118: Амик
A119: Телескоп JCB 535-140 (№4) | B119: 20 | C119: 1069.8 | D119: Амик
A120: Телескоп JCB 535-140 (№4) | B120: 70 | C120: 3744.3 | D120: Амик
A121: Телескоп JCB 535-140 (№4) | B121: 100 | C121: 5349 | D121: Амик
A122: Телескоп JCB 535-140 (№4) | B122: 100 | C122: 5349 | D122: Амик
A123: Телескоп JCB 535-140 (№4) | B123: 100 | C123: 5149 | D123: Амик
A124: Телескоп JCB 535-140 (№4) | B124: 100 | C124: 5349 | D124: Амик
A125: Телескоп JCB 535-140 (№4) | B125: 100 | C125: 5499 | D125: Амик | E125: премиум
D126: Амик
E142: =SUM(C112:C142) -> 76120.7
D143: КЛО
D144: КЛО
D145: КЛО
D146: КЛО | E146: =SUM(C143:C146) -> 0
A147: МАЗ 265 | B147: 145.53 | C147: 7129.51 | D147: ВОГ
A148: МАЗ 265 | B148: 107.23 | C148: 5253.2 | D148: ВОГ
A149: Самосвал МАЗ №2 | B149: 223.69 | C149: 10958.57 | D149: ВОГ
A150: Самосвал МАЗ №2 | B150: 176.95 | C150: 8668.78 | D150: ВОГ
A151: Самосвал МАЗ №2 | B151: 176.96 | C151: 8669.27 | D151: ВОГ
A152: Телескоп 2 | B152: 180 | C152: 7977.6 | D152: ВОГ кубышка
A153: Экскаватор JCB 3CX 2008 | B153: 210 | C153: 9307.2 | D153: ВОГ кубышка
A154: МАЗ 265 | B154: 60 | C154: 2659.2 | D154: ВОГ кубышка
A155: Самосвал МАЗ №2 | B155: 150 | C155: 6648 | D155: ВОГ кубышка
E159: =SUM(C147:C159) -> 67271.33
E160: =SUM(C160:C160) -> 0
A161: Экскаватор JCB 3CX 2008 | B161: 120 | C161: 5878.8 | D161: Окко
A162: Экскаватор JCB 3CX 2008 | B162: 100 | C162: 4899 | D162: Окко
A163: Экскаватор JCB 3CX 2008 | B163: 100 | C163: 4899 | D163: Окко
A164: Экскаватор JCB 3CX 2008 | B164: 100 | C164: 4799 | D164: Окко
A165: Экскаватор JCB 3CX 2008 | B165: 100 | C165: 4799 | D165: Окко
A166: Экскаватор JCB 3CX 2008 | B166: 100 | C166: 4799 | D166: Окко
A167: МАЗ 265 | B167: 10 | C167: 419
E188: =SUM(C161:C188) -> 30492.8
B189: =SUM(B30:B188) -> 13114.52 | C189: =SUM(C30:C188) -> 641859.61

Sheet Топливо Ноябрь  2024 
A1: Наименование | B1: Отчетный период | C1: Остаток на начало | D1: Топливо заправленное | E1: Остаток на конец | F1: Расход топлива за период, л | G1: Моточасы на начало | H1: Моточасы на конец | I1: Отработано техникой моточасов | J1: Перегон на доругой объект, л | K1: Перегон на доругой объект, км | L1: Часы работы на обьекте | M1: Норма расхода топлива литр/1 мото час согласно сс | N1: Факт витрат на 1 мото/год, км витрат (л/год) | O1: Отклонения л/мотогод | P1: Отклонения, грн/мес | Q1: Примечание по строке
A2: Телескоп 1 | B2: 45474 | D2: =SUMIF($A$28:$A$203,A2,$B$28:$B$203) -> 0 | F2: =C2+D2-E2 -> 0 | I2: =H2-G2 -> 0 | J2: 0 | M2: =VLOOKUP(A2,[4]Тарас!$C$4:$P$23,14,0) -> 3.4 | P2: =194.94*I2 -> 0
A3: Телескоп 2 | B3: 45597 | C3: 60 | D3: =SUMIF($A$28:$A$203,A3,$B$28:$B$203) -> 1158.9321 | E3: 80 | F3: =C3+D3-E3 -> 1138.9321 | G3: =10943 -> 10943 | H3: 11154 | I3: =H3-G3 -> 211 | L3: 218 | M3: 4.73 | N3: =F3/I3 -> 5.3977827 | O3: =N3-M3 -> 0.66778269 | P3: =(I3*O3*$K$23) -> 6758.677
A4: Телескоп JCB 535-140 (№4) | B4: 45597 | C4: 60 | D4: =SUMIF($A$28:$A$203,A4,$B$28:$B$203) -> 710 | E4: 30 | F4: =C4+D4-E4 -> 740 | G4: 10004 | H4: 10160 | I4: =H4-G4 -> 156 | J4: 0 | L4: 198 | M4: 4.73 | N4: =F4/I4 -> 4.7435897
A5: Телескоп JCB 540-170 №5 | B5: 45597 | C5: 70 | D5: =SUMIF($A$28:$A$203,A5,$B$28:$B$203) -> 779.92 | E5: 65 | F5: =C5+D5-E5 -> 784.92 | H5: 7961 | I5: =L5*0.65 -> 87.75 | J5: 0 | L5: 135 | M5: 4.73 | N5: =F5/I5 -> 8.9449573 | O5: =N5-M5 -> 4.2149573 | P5: =(I5*O5*$K$23) -> 17741.257 | Q5: моточасы расчетные, данные мотосчетчика на 30.11
A6: Виброкаток | B6: 45597 | C6: 85 | D6: =SUMIF($A$28:$A$203,A6,$B$28:$B$203) -> 352.30256 | E6: 40 | F6: =C6+D6-E6 -> 397.30256 | G6: 4992 | H6: 5089 | I6: =H6-G6 -> 97 | J6: 0 | L6: 194 | M6: 5 | N6: =F6/I6 -> 4.0959027
A7: Ротор Пегасус | B7: 45597 | D7: =SUMIF($A$28:$A$203,A7,$B$28:$B$203) -> 180 | E7: 50 | F7: =C7+D7-E7 -> 130 | H7: 10529 | I7: =L7*0.78 -> 28.08 | J7: 0 | L7: 36 | M7: 3.8 | N7: =F7/I7 -> 4.6296296 | O7: =N7-M7 -> 0.82962963 | P7: =(I7*O7*$K$23) -> 1117.4432 | Q7: моточасы расчетные, данные мотосчетчика на 30.11
A8: Экскаватор JCB | B8: 45597 | C8: 50 | D8: =SUMIF($A$28:$A$203,A8,$B$28:$B$203) -> 804.93082 | E8: 10 | F8: =C8+D8-E8 -> 844.93082 | G8: 18010 | H8: 18186 | I8: =H8-G8 -> 176 | J8: 0 | L8: 219 | M8: 4.35 | N8: =F8/I8 -> 4.8007433 | O8: =N8-M8 -> 0.45074331 | P8: =(I8*O8*$K$23) -> 3805.275
A9: Экскаватор JCB 3CX 2008 | B9: 45597 | C9: 80 | D9: =SUMIF($A$28:$A$203,A9,$B$28:$B$203) -> 600 | E9: 65 | F9: =C9+D9-E9 -> 615 | G9: 4 | H9: 108 | I9: =H9-G9 -> 104 | J9: 0 | L9: 149 | M9: 4.35 | N9: =F9/I9 -> 5.9134615 | O9: =N9-M9 -> 1.5634615 | P9: =(I9*O9*$K$23) -> 7799.4616
A10: Экскаватор JCB 2013 | B10: 45597 | C10: 20 | D10: =SUMIF($A$28:$A$203,A10,$B$28:$B$203) -> 528.98776 | E10: 25 | F10: =C10+D10-E10 -> 523.98776 | G10: 12270 | H10: 12463 | I10: =H10-G10 -> 193 | J10: 0 | L10: 126 | M10: 4.35 | N10: =F10/I10 -> 2.7149625
A11: Экскаватор JCB 220 | B11: 45597 | C11: 129 | D11: =SUMIF($A$28:$A$203,A11,$B$28:$B$203) -> 2495.997 | E11: 504 | F11: =C11+D11-E11 -> 2120.997 | G11: 7583 | H11: 7748 | I11: =H11-G11 -> 165 | J11: 0 | L11: 225 | M11: 10.5 | N11: =F11/I11 -> 12.854527 | O11: =N11-M11 -> 2.3545271 | P11: =(I11*O11*$K$23) -> 18635.099 | Q11: gps показывает слив топлива 132 л
A12: МАЗ 264 | B12: 45597 | C12: 40 | D12: =SUMIF($A$28:$A$203,A12,$B$28:$B$203) -> 887.34776 | E12: 150 | F12: =C12+D12-E12 -> 777.34776 | G12: 33450 | H12: 33919 | I12: =H12-G12 -> 469 | J12: 0 | L12: 223 | M12: 0.9 | N12: =F12/I12 -> 1.6574579 | O12: =N12-M12 -> 0.75745792 | P12: =(I12*O12*$K$23) -> 17040.229
A13: МАЗ 265 | B13: 45597 | C13: 150 | D13: =SUMIF($A$28:$A$203,A13,$B$28:$B$203) -> 783.54133 | E13: 90 | F13: =C13+D13-E13 -> 843.54133 | G13: 38463 | H13: 38912 | I13: =H13-G13 -> 449 | J13: 0 | L13: 234 | M13: 0.9 | N13: =F13/I13 -> 1.8787112 | O13: =N13-M13 -> 0.97871121 | P13: =(I13*O13*$K$23) -> 21078.757
A14: Самосвал Камаз | B14: 45597 | C14: 204 | D14: =SUMIF($A$28:$A$203,A14,$B$28:$B$203) -> 304.14 | E14: 280 | F14: =C14+D14-E14 -> 228.14 | G14: 560504 | H14: 560741 | I14: =H14-G14 -> 237 | J14: 0 | K14: 185 | L14: 6 | M14: 0.9 | N14: =F14/I14 -> 0.96261603 | Q14: gps показывает слив топлива 132 л
A15: Самосвал МАЗ | B15: 45597 | C15: 130 | D15: =SUMIF($A$28:$A$203,A15,$B$28:$B$203) -> 789.9792 | E15: 150 | F15: =C15+D15-E15 -> 769.9792 | G15: 70039 | H15: 70234 | I15: =H15-G15 -> 195 | J15: 0 | L15: 222 | M15: 0.9 | N15: =F15/I15 -> 3.9486113 | O15: =N15-M15 -> 3.0486113 | P15: =(I15*O15*$K$23) -> 28515.484 | Q15: gps показывает слив топлива 155 л
A16: Самосвал МАЗ №2 | B16: 45597 | C16: 150 | D16: =SUMIF($A$28:$A$203,A16,$B$28:$B$203) -> 789.74145 | E16: 60 | F16: =C16+D16-E16 -> 879.74145 | G16: 67426 | H16: 67635 | I16: =H16-G16 -> 209 | J16: 0 | L16: 221 | M16: 0.9 | N16: =F16/I16 -> 4.2092892 | O16: =N16-M16 -> 3.3092892 | P16: =(I16*O16*$K$23) -> 33176.082 | Q16: gps показывает слив топлива 90 л
A17: Автокран XCMG 55 | B17: 45597 | C17: 70 | D17: =SUMIF($A$28:$A$203,A17,$B$28:$B$203) -> 80 | E17: 40 | F17: =C17+D17-E17 -> 110 | I17: =L17*0.7 -> 11.9 | J17: 0 | L17: 17 | M17: 5.1 | N17: =F17/I17 -> 9.2436975 | O17: =N17-M17 -> 4.1436975 | P17: =(I17*O17*$K$23) -> 2365.2611 | Q17: не работает мотосчетчик
A18: Автокран XCMG | B18: 45597 | C18: 224 | D18: =SUMIF($A$28:$A$203,A18,$B$28:$B$203) -> 150 | E18: 40 | F18: =C18+D18-E18 -> 334 | G18: 6213 | H18: 6257 | I18: =H18-G18 -> 44 | J18: 0 | L18: 174 | M18: 4.07 | N18: =F18/I18 -> 7.5909091 | O18: =N18-M18 -> 3.5209091 | P18: =(I18*O18*$K$23) -> 7431.0738 | Q18: gps показывает слив топлива 68 л
A19: Автокран Клинцы | B19: 45597 | C19: 40 | D19: =SUMIF($A$28:$A$203,A19,$B$28:$B$203) -> 342.88 | E19: 190 | F19: =C19+D19-E19 -> 192.88 | I19: =L19*0.7 -> 118.3 | J19: 0 | L19: 169 | M19: 2.9 | N19: =F19/I19 -> 1.6304311
C20: =SUM(C3:C19) -> 1562 | D20: =SUM(D2:D19) -> 11738.7 | E20: =SUM(E2:E19) -> 1869 | P20: =SUM(P3:P19) -> 165464.1
D21: =D20-B204 -> 0
J23: Стоимость 1 л | K23: =SUM(C28:C203)/B204 -> 47.967169
A26: Заправки АЗС
A27: Наименование | B27: Количество | C27: Сумма | D27: АЗС
A28: Экскаватор JCB 2013 | B28: 88.987764 | C28: =B28*47.32 -> 4210.901 | D28: Авиас | E28: с кубышки
A29: Телескоп 2 | B29: 38.932147 | C29: =B29*47.32 -> 1842.2692 | D29: Авиас | E29: с кубышки
A30: Самосвал МАЗ №2 | B30: 171.30145 | C30: =B30*47.32 -> 8105.9844 | D30: Авиас | E30: с кубышки
A31: Самосвал МАЗ | B31: 151.2792 | C31: =B31*47.32 -> 7158.5317 | D31: Авиас | E31: с кубышки
A32: МАЗ 264 | B32: 88.987764 | C32: =B32*47.32 -> 4210.901 | D32: Авиас | E32: с кубышки
A33: Виброкаток | B33: 72.302558 | C33: =B33*47.32 -> 3421.3571 | D33: Авиас | E33: с кубышки
A34: МАЗ 265 | B34: 81.201335 | C34: =B34*47.32 -> 3842.4472 | D34: Авиас | E34: с кубышки
A35: Экскаватор JCB | B35: 66.740823 | C35: =B35*47.32 -> 3158.1758 | D35: Авиас | E35: с кубышки
A36: Экскаватор JCB 220 | B36: 111.23471 | C36: =B36*47.32 -> 5263.6263 | D36: Авиас | E36: с кубышки
A37: Экскаватор JCB 220 | B37: 129.03226 | C37: =B37*47.32 -> 6105.8065 | D37: Авиас | E37: с кубышки
A38: Телескоп JCB 535-140 (№4) | B38: 100 | C38: =B38*47.32 -> 4732 | D38: Авиас
A39: Телескоп JCB 535-140 (№4) | B39: 100 | C39: =B39*47.32 -> 4732 | D39: Авиас
A40: Экскаватор JCB 2013 | B40: 100 | C40: =B40*47.32 -> 4732 | D40: Авиас
A41: Экскаватор JCB 2013 | B41: 40 | C41: =B41*47.32 -> 1892.8 | D41: Авиас
A42: Экскаватор JCB 2013 | B42: 100 | C42: =B42*47.32 -> 4732 | D42: Авиас
A43: Экскаватор JCB 2013 | B43: 100 | C43: =B43*47.32 -> 4732 | D43: Авиас
A44: Экскаватор JCB 2013 | B44: 100 | C44: =B44*47.32 -> 4732 | D44: Авиас
A45: Экскаватор JCB | B45: 100 | C45: =B45*47.32 -> 4732 | D45: Авиас
A46: Экскаватор JCB | B46: 100 | C46: =B46*47.32 -> 4732 | D46: Авиас
A47: Экскаватор JCB | B47: 100 | C47: =B47*47.32 -> 4732 | D47: Авиас
A48: Экскаватор JCB | B48: 98.19 | C48: =B48*47.32 -> 4646.3508 | D48: Авиас
A49: Экскаватор JCB | B49: 40 | C49: =B49*47.32 -> 1892.8 | D49: Авиас
... A110: Экскаватор JCB 220 | B110: 91.01 | C110: =B110*47.32 -> 4306.5932 | D110: Авиас
A111: Экскаватор JCB 220 | B111: =198.06-B112 -> 12.41 | C111: =B111*47.32 -> 587.2412 | D111: Авиас
A112: Экскаватор JCB 220 | B112: 185.65 | C112: =B112*48.63 -> 9028.1595 | D112: Авиас
A113: Экскаватор JCB 220 | B113: 100.77 | C113: =B113*48.63 -> 4900.4451 | D113: Авиас
A114: Экскаватор JCB 220 | B114: 180 | C114: =B114*48.63 -> 8753.4 | D114: Авиас
A115: Экскаватор JCB 220 | B115: 187.14 | C115: =B115*48.63 -> 9100.6182 | D115: Авиас
A116: Экскаватор JCB 220 | B116: 35.21 | C116: =B116*48.63 -> 1712.2623 | D116: Авиас
A117: Экскаватор JCB 220 | B117: 178.12 | C117: =B117*48.63 -> 8661.9756 | D117: Авиас
A118: Экскаватор JCB 220 | B118: 186.94 | C118: =B118*48.63 -> 9090.8922 | D118: Авиас
A119: Экскаватор JCB 220 | B119: 80.73 | C119: =B119*48.63 -> 3925.8999 | D119: Авиас
A120: Виброкаток | B120: 100 | C120: =B120*48.63 -> 4863 | D120: Авиас
A121: Виброкаток | B121: 160 | C121: =B121*48.63 -> 7780.8 | D121: Авиас
A122: Виброкаток | B122: 20 | C122: =B122*48.63 -> 972.6 | D122: Авиас
C123: =B123*47.32 -> 0 | D123: Авиас
C124: =B124*47.32 -> 0 | D124: Авиас
C125: =B125*47.32 -> 0 | D125: Авиас
C126: =B126*48.625 -> 0 | D126: Авиас | E126: =SUM(C28:C126) -> 471010.05
A127: Автокран XCMG | B127: 150 | C127: 8023.5 | D127: Амик
A128: Автокран XCMG 55 | B128: 80 | C128: 4279.2 | D128: Амик
A129: Телескоп JCB 535-140 (№4) | B129: 130 | C129: 6953.7 | D129: Амик
A130: Телескоп JCB 535-140 (№4) | B130: 150 | C130: 8023.5 | D130: Амик
A131: Телескоп JCB 535-140 (№4) | B131: 120 | C131: 6418.8 | D131: Амик
A132: Телескоп JCB 535-140 (№4) | B132: 10 | C132: 534.9 | D132: Амик
A133: Телескоп JCB 535-140 (№4) | B133: 100 | C133: 5349 | D133: Амик
D134: Амик
D135: Амик
D136: Амик
D137: Амик
D138: Амик
D139: Амик
D140: Амик
D141: Амик
E157: =SUM(C127:C157) -> 39582.6
D158: КЛО
D159: КЛО
D160: КЛО
D161: КЛО | E161: =SUM(C158:C161) -> 0
A162: Самосвал Камаз | B162: 153.58 | C162: 7370.3 | D162: ВОГ
A163: Ротор Пегасус | B163: 100 | C163: 4799 | D163: ВОГ
A164: Ротор Пегасус | B164: 40 | C164: 1919.6 | D164: ВОГ
A165: Ротор Пегасус | B165: 40 | C165: 1919.6 | D165: ВОГ
D166: ВОГ
E174: =SUM(C162:C174) -> 16008.5
E175: =SUM(C175:C175) -> 0
A176: Экскаватор JCB 3CX 2008 | B176: 100 | C176: 4799 | D176: Окко
A177: Экскаватор JCB 3CX 2008 | B177: 100 | C177: 4799 | D177: Окко
A178: Экскаватор JCB 3CX 2008 | B178: 100 | C178: 4799 | D178: Окко
A179: Экскаватор JCB 3CX 2008 | B179: 100 | C179: 4799 | D179: Окко
A180: Экскаватор JCB 3CX 2008 | B180: 100 | C180: 4799 | D180: Окко
A181: Экскаватор JCB 3CX 2008 | B181: 100 | C181: 4799 | D181: Окко
A182: Самосвал Камаз | B182: 150.56 | C182: 7677.05
E203: =SUM(C176:C203) -> 36471.05
B204: =SUM(B28:B203) -> 11738.7 | C204: =SUM(C28:C203) -> 563072.2

Sheet Топливо Декабрь 2024 
A1: Наименование | B1: Отчетный период | C1: Остаток на начало | D1: Топливо заправленное | E1: Остаток на конец | F1: Расход топлива за период, л | G1: Моточасы на начало | H1: Моточасы на конец | I1: Отработано техникой моточасов | J1: Перегон на доругой объект, л | K1: Перегон на доругой объект, км | L1: Часы работы на обьекте | M1: Норма расхода топлива литр/1 мото час согласно сс | N1: Факт витрат на 1 мото/год, км витрат (л/год) | O1: Отклонения л/мотогод | P1: Отклонения, грн/мес | Q1: Примечание по строке
A2: Телескоп 1 | B2: 45474 | D2: =SUMIF($A$30:$A$191,A2,$B$30:$B$191) -> 0 | F2: =C2+D2-E2 -> 0 | I2: =H2-G2 -> 0 | J2: 0 | M2: =VLOOKUP(A2,[4]Тарас!$C$4:$P$23,14,0) -> 3.4 | P2: =194.94*I2 -> 0
A3: Телескоп 2 | B3: 45627 | C3: ='Топливо Ноябрь 2024 '!E3 -> 80 | D3: =SUMIF($A$30:$A$191,A3,$B$30:$B$191) -> 760 | E3: 30 | F3: =C3+D3-E3 -> 810 | G3: ='Топливо Ноябрь 2024 '!H3 -> 11154 | I3: =L3*0.65 -> 115.7 | L3: 178 | M3: 4.73 | N3: =F3/I3 -> 7.0008643 | Q3: не работает мотосчетчик
A4: Телескоп JCB 535-140 (№4) | B4: 45627 | C4: ='Топливо Ноябрь 2024 '!E4 -> 30 | D4: =SUMIF($A$30:$A$191,A4,$B$30:$B$191) -> 540 | E4: 50 | F4: =C4+D4-E4 -> 520 | G4: ='Топливо Ноябрь 2024 '!H4 -> 10160 | H4: 10288 | I4: =H4-G4 -> 128 | J4: 0 | L4: 131 | M4: 4.73 | N4: =F4/I4 -> 4.0625
A5: Телескоп JCB 540-170 №5 | B5: 45627 | C5: ='Топливо Ноябрь 2024 '!E5 -> 65 | D5: =SUMIF($A$30:$A$191,A5,$B$30:$B$191) -> 552 | E5: 70 | F5: =C5+D5-E5 -> 547 | G5: ='Топливо Ноябрь 2024 '!H5 -> 7961 | H5: 8064 | I5: =H5-G5 -> 103 | J5: 0 | L5: 123 | M5: 4.73 | N5: =F5/I5 -> 5.3106796 | O5: =N5-M5 -> 0.58067961 | P5: =(I5*O5*$K$25) -> 2945.7479
A6: Виброкаток | B6: 45627 | C6: ='Топливо Ноябрь 2024 '!E6 -> 40 | D6: =SUMIF($A$30:$A$191,A6,$B$30:$B$191) -> 380 | E6: 65 | F6: =C6+D6-E6 -> 355 | G6: ='Топливо Ноябрь 2024 '!H6 -> 5089 | H6: 5152 | I6: =H6-G6 -> 63 | J6: 0 | L6: 148 | M6: 5 | N6: =F6/I6 -> 5.6349206 | O6: =N6-M6 -> 0.63492063 | P6: =(I6*O6*$K$25) -> 1970.0705
A7: Ротор Пегасус | B7: 45627 | C7: ='Топливо Ноябрь 2024 '!E7 -> 50 | D7: =SUMIF($A$30:$A$191,A7,$B$30:$B$191) -> 39.59 | E7: 20 | F7: =C7+D7-E7 -> 69.59 | G7: ='Топливо Ноябрь 2024 '!H7 -> 10529 | H7: 10566 | I7: =H7-G7 -> 37 | J7: 0 | L7: 10 | M7: 3.8 | N7: =F7/I7 -> 1.8808108
A8: Экскаватор JCB | B8: 45627 | C8: ='Топливо Ноябрь 2024 '!E8 -> 10 | D8: =SUMIF($A$30:$A$191,A8,$B$30:$B$191) -> 840 | E8: 15 | F8: =C8+D8-E8 -> 835 | G8: ='Топливо Ноябрь 2024 '!H8 -> 18186 | H8: 18366 | I8: =H8-G8 -> 180 | J8: 0 | L8: 184 | M8: 4.35 | N8: =F8/I8 -> 4.6388889 | O8: =N8-M8 -> 0.28888889 | P8: =(I8*O8*$K$25) -> 2561.0917
A9: Экскаватор JCB 3CX 2008 | B9: 45627 | C9: ='Топливо Ноябрь 2024 '!E9 -> 65 | D9: =SUMIF($A$30:$A$191,A9,$B$30:$B$191) -> 400 | E9: 30 | F9: =C9+D9-E9 -> 435 | G9: ='Топливо Ноябрь 2024 '!H9 -> 108 | H9: 191 | I9: =H9-G9 -> 83 | J9: 0 | L9: 113 | M9: 4.35 | N9: =F9/I9 -> 5.2409639 | O9: =N9-M9 -> 0.89096386 | P9: =(I9*O9*$K$25) -> 3642.1679
A10: Экскаватор JCB 2013 | B10: 45627 | C10: ='Топливо Ноябрь 2024 '!E10 -> 25 | D10: =SUMIF($A$30:$A$191,A10,$B$30:$B$191) -> 820 | E10: 100 | F10: =C10+D10-E10 -> 745 | G10: ='Топливо Ноябрь 2024 '!H10 -> 12463 | H10: 12628 | I10: =H10-G10 -> 165 | J10: 0 | L10: 178 | M10: 4.35 | N10: =F10/I10 -> 4.5151515 | O10: =N10-M10 -> 0.16515152 | P10: =(I10*O10*$K$25) -> 1342.1105
A11: Экскаватор JCB 220 | B11: 45627 | C11: ='Топливо Ноябрь 2024 '!E11 -> 504 | D11: =SUMIF($A$30:$A$191,A11,$B$30:$B$191) -> 0 | E11: 460 | F11: =C11+D11-E11 -> 44 | G11: ='Топливо Ноябрь 2024 '!H11 -> 7748 | H11: 7753 | I11: =H11-G11 -> 5 | J11: 0 | L11: 4 | M11: 10.5 | N11: =F11/I11 -> 8.8
A12: МАЗ 264 | B12: 45627 | C12: ='Топливо Ноябрь 2024 '!E12 -> 150 | D12: =SUMIF($A$30:$A$191,A12,$B$30:$B$191) -> 300 | E12: 150 | F12: =C12+D12-E12 -> 300 | G12: ='Топливо Ноябрь 2024 '!H12 -> 33919 | H12: 34232 | I12: =H12-G12 -> 313 | J12: 0 | L12: 163 | M12: 0.9 | N12: =F12/I12 -> 0.95846645 | O12: =N12-M12 -> 0.058466454 | P12: =(I12*O12*$K$25) -> 901.30726
A13: МАЗ 265 | B13: 45627 | C13: ='Топливо Ноябрь 2024 '!E13 -> 90 | D13: =SUMIF($A$30:$A$191,A13,$B$30:$B$191) -> 620.08 | E13: 180 | F13: =C13+D13-E13 -> 530.08 | G13: ='Топливо Ноябрь 2024 '!H13 -> 38912 | H13: 39170 | I13: =H13-G13 -> 258 | J13: 0 | L13: 177 | M13: 0.9 | N13: =F13/I13 -> 2.0545736 | O13: =N13-M13 -> 1.1545736 | P13: =(I13*O13*$K$25) -> 14671.115
A14: Самосвал Камаз | B14: 45627 | C14: ='Топливо Ноябрь 2024 '!E14 -> 280 | D14: =SUMIF($A$30:$A$191,A14,$B$30:$B$191) -> 0 | E14: 280 | F14: =C14+D14-E14 -> 0 | G14: ='Топливо Ноябрь 2024 '!H14 -> 560741 | H14: 560741 | I14: =H14-G14 -> 0 | J14: 0 | L14: 0 | M14: 0.9
A15: Самосвал МАЗ | B15: 45627 | C15: ='Топливо Ноябрь 2024 '!E15 -> 150 | D15: =SUMIF($A$30:$A$191,A15,$B$30:$B$191) -> 2548.12 | E15: 150 | F15: =C15+D15-E15 -> 2548.12 | G15: ='Топливо Ноябрь 2024 '!H15 -> 70234 | H15: 74896 | I15: =H15-G15 -> 4662 | J15: 0 | L15: 192 | M15: 0.9 | N15: =F15/I15 -> 0.54657229
A16: Самосвал МАЗ №2 | B16: 45627 | C16: ='Топливо Ноябрь 2024 '!E16 -> 60 | D16: =SUMIF($A$30:$A$191,A16,$B$30:$B$191) -> 2172.55 | E16: 150 | F16: =C16+D16-E16 -> 2082.55 | G16: ='Топливо Ноябрь 2024 '!H16 -> 67635 | H16: 71598 | I16: =H16-G16 -> 3963 | J16: 0 | L16: 168 | M16: 0.9 | N16: =F16/I16 -> 0.52549836
A17: Автокран XCMG 55 | B17: 45627 | C17: ='Топливо Ноябрь 2024 '!E17 -> 40 | D17: =SUMIF($A$30:$A$191,A17,$B$30:$B$191) -> 1160 | E17: 110 | F17: =C17+D17-E17 -> 1090 | G17: ='Топливо Ноябрь 2024 '!H17 -> 0 | I17: =L17*0.7 -> 111.3 | J17: 0 | L17: 159 | M17: 5.1 | N17: =F17/I17 -> 9.7933513 | Q17: не работает мотосчетчик
A18: Автокран XCMG | B18: 45627 | C18: ='Топливо Ноябрь 2024 '!E18 -> 40 | D18: =SUMIF($A$30:$A$191,A18,$B$30:$B$191) -> 544.2 | E18: 100 | F18: =C18+D18-E18 -> 484.2 | G18: ='Топливо Ноябрь 2024 '!H18 -> 6257 | H18: 6326 | I18: =H18-G18 -> 69 | J18: 0 | K18: 242 | L18: 178 | M18: 4.07 | N18: =(F18-(0.4*K18))/I18 -> 5.6144928 | O18: =N18-M18 -> 1.5444928 | P18: =(I18*O18*$K$25) -> 5248.7604 | Q18: в т.ч перегон 242км по норме 0,4л/км
A19: Автокран Клинцы | B19: 45627 | C19: ='Топливо Ноябрь 2024 '!E19 -> 190 | D19: =SUMIF($A$30:$A$191,A19,$B$30:$B$191) -> 180 | E19: 40 | F19: =C19+D19-E19 -> 330 | G19: ='Топливо Ноябрь 2024 '!H19 -> 0 | H19: 32 | I19: =H19-G19 -> 32 | J19: 0 | L19: 71 | M19: 2.9 | N19: =F19/I19 -> 10.3125 | O19: =N19-M19 -> 7.4125 | P19: =(I19*O19*$K$25) -> 11682.518
A20: MAN №5 KA5697НВ | B20: 45627 | F20: 2960 | I20: 8661 | M20: 0.32 | N20: =F20/I20 -> 0.34176192 | O20: =N20-M20 -> 0.021761921 | P20: =0.02*I20*48.18 -> 8345.7396 | Q20: данные использ топлива согласно GPS
A21: MAN №3 white KA7837HO | B21: 45627 | F21: 1556 | I21: 4319 | M21: 0.32 | N21: =F21/I21 -> 0.36026858 | O21: =N21-M21 -> 0.040268581 | P21: =0.04*I21*48.18 -> 8323.5768 | Q21: данные использ топлива согласно GPS
C22: =SUM(C3:C19) -> 1869 | D22: =SUM(D2:D19) -> 11856.54 | E22: =SUM(E2:E19) -> 2000 | P22: =SUM(P3:P19) -> 44964.889
D23: =D22-B192 -> 0
J25: Стоимость 1 л | K25: =SUM(C30:C191)/B192 -> 49.251763
A28: Заправки АЗС
A29: Наименование | B29: Количество | C29: Сумма | D29: АЗС
A30: Автокран XCMG 55 | B30: 100 | C30: =B30*$E$30 -> 4883.1429 | D30: Авиас | E30: 48.831429
A31: Автокран XCMG 55 | B31: 100 | C31: =B31*$E$30 -> 4883.1429 | D31: Авиас
A32: Автокран XCMG 55 | B32: 100 | C32: =B32*$E$30 -> 4883.1429 | D32: Авиас
A33: Автокран XCMG 55 | B33: 100 | C33: =B33*$E$30 -> 4883.1429 | D33: Авиас
A34: Автокран XCMG 55 | B34: 100 | C34: =B34*$E$30 -> 4883.1429 | D34: Авиас
A35: Автокран XCMG 55 | B35: 100.02 | C35: =B35*$E$30 -> 4884.1195 | D35: Авиас
A36: Автокран XCMG 55 | B36: 99.98 | C36: =B36*$E$30 -> 4882.1662 | D36: Авиас
A37: Автокран XCMG 55 | B37: 100 | C37: =B37*$E$30 -> 4883.1429 | D37: Авиас
A38: Автокран XCMG 55 | B38: 100 | C38: =B38*$E$30 -> 4883.1429 | D38: Авиас
A39: Автокран XCMG 55 | B39: 100 | C39: =B39*$E$30 -> 4883.1429 | D39: Авиас
A40: Телескоп JCB 535-140 (№4) | B40: 100 | C40: =B40*$E$30 -> 4883.1429 | D40: Авиас
A41: Телескоп JCB 535-140 (№4) | B41: 100 | C41: =B41*$E$30 -> 4883.1429 | D41: Авиас
A42: Телескоп JCB 535-140 (№4) | B42: 100 | C42: =B42*$E$30 -> 4883.1429 | D42: Авиас
... A119: Виброкаток | B119: 100 | C119: =B119*$E$30 -> 4883.1429 | D119: Авиас
C120: =B120*$E$30 -> 0 | E120: =SUM(C30:C120) -> 496749.92
A121: Телескоп 2 | B121: 100 | C121: 5299 | D121: БВС ритейл
A122: Экскаватор JCB | B122: 100 | C122: 5299 | D122: БВС ритейл
A123: Экскаватор JCB 2013 | B123: 100 | C123: 5299 | D123: БВС ритейл
A124: Автокран Клинцы | B124: 140 | C124: 7418.6 | D124: БВС ритейл
A125: МАЗ 265 | B125: 100 | C125: 5299 | D125: БВС ритейл
A126: Автокран XCMG 55 | B126: 160 | C126: 8478.4 | D126: БВС ритейл
D128: Амик
D129: Амик
D130: Амик
D131: Амик
D132: Амик
D133: Амик
D134: Амик
E151: =SUM(C121:C151) -> 37093
A152: Экскаватор JCB 3CX 2008 | B152: 400 | C152: 19296 | D152: ОККО
A153: Ротор Пегасус | B153: 39.59 | C153: 1899.92 | D153: ВОГ
E155: =SUM(C152:C155) -> 21195.92
A156: Автокран XCMG | B156: 160 | C156: 8558.4 | D156: Амик
A157: Автокран XCMG | B157: 160 | C157: 8638.4 | D157: Амик
A158: Автокран XCMG | B158: 31.85 | C158: 1719.58 | D158: Амик
A159: Автокран XCMG | B159: 150 | C159: 7798.5 | D159: Амик
A160: Автокран XCMG | B160: 42.35 | C160: 2201.78 | D160: Амик
E162: =SUM(C156:C162) -> 28916.66
E163: =SUM(C163:C163) -> 0
E191: =SUM(C164:C191) -> 0
B192: =SUM(B30:B191) -> 11856.54 | C192: =SUM(C30:C191) -> 583955.5

Sheet Топливо Январь 2025
A1: Наименование | B1: Отчетный период | C1: Остаток на начало | D1: Топливо заправленное | E1: Остаток на конец | F1: Расход топлива за период, л | G1: Моточасы на начало | H1: Моточасы на конец | I1: Отработано техникой моточасов | J1: Перегон на доругой объект, л | K1: Перегон на доругой объект, км | L1: Часы работы на обьекте | M1: Норма расхода топлива литр/1 мото час согласно сс | N1: Факт витрат на 1 мото/год, км витрат (л/год) | O1: Отклонения л/мотогод | P1: Отклонения от нормы,% | Q1: Отклонения, грн/мес | R1: Примечание по строке
A2: Телескоп 1 | B2: 45474 | D2: =SUMIF($A$31:$A$112,A2,$B$31:$B$112) -> 0 | F2: =C2+D2-E2 -> 0 | I2: =H2-G2 -> 0 | J2: 0 | M2: =VLOOKUP(A2,[4]Тарас!$C$4:$P$23,14,0) -> 3.4 | Q2: =194.94*I2 -> 0
A3: Телескоп 2 | B3: 45658 | C3: ='Топливо Декабрь 2024 '!E3 -> 30 | D3: =SUMIF($A$31:$A$112,A3,$B$31:$B$112) -> 700 | E3: 120 | F3: =C3+D3-E3 -> 610 | G3: ='Топливо Декабрь 2024 '!H3 -> 0 | I3: =L3*0.65 -> 135.2 | L3: 208 | M3: 4.73 | N3: =F3/I3 -> 4.5118343 | R3: не работает мотосчетчик
A4: Телескоп JCB 535-140 (№4) | B4: 45658 | C4: ='Топливо Декабрь 2024 '!E4 -> 50 | D4: =SUMIF($A$31:$A$112,A4,$B$31:$B$112) -> 784.92 | E4: 65 | F4: =C4+D4-E4 -> 769.92 | G4: ='Топливо Декабрь 2024 '!H4 -> 10288 | H4: 10445 | I4: =H4-G4 -> 157 | J4: 0 | L4: 164 | M4: 4.73 | N4: =F4/I4 -> 4.903949 | O4: =N4-M4 -> 0.17394904 | P4: =O4/M4 -> 0.036775697 | Q4: =(I4*O4*$K$26) -> 1472.3897
A5: Телескоп JCB 540-170 №5 | B5: 45658 | C5: ='Топливо Декабрь 2024 '!E5 -> 70 | D5: =SUMIF($A$31:$A$112,A5,$B$31:$B$112) -> 700 | E5: 115 | F5: =C5+D5-E5 -> 655 | G5: ='Топливо Декабрь 2024 '!H5 -> 8064 | H5: 8202 | I5: =H5-G5 -> 138 | J5: 0 | L5: 144 | M5: 4.73 | N5: =F5/I5 -> 4.7463768 | O5: =N5-M5 -> 0.016376812 | P5: =O5/M5 -> 0.003462328 | Q5: =(I5*O5*$K$26) -> 121.84551
A6: Виброкаток | B6: 45658 | C6: ='Топливо Декабрь 2024 '!E6 -> 65 | D6: =SUMIF($A$31:$A$112,A6,$B$31:$B$112) -> 300 | E6: 100 | F6: =C6+D6-E6 -> 265 | G6: ='Топливо Декабрь 2024 '!H6 -> 5152 | H6: 5207 | I6: =H6-G6 -> 55 | J6: 0 | L6: 154 | M6: 5 | N6: =F6/I6 -> 4.8181818
A7: Ротор Пегасус | B7: 45658 | C7: ='Топливо Декабрь 2024 '!E7 -> 20 | D7: =SUMIF($A$31:$A$112,A7,$B$31:$B$112) -> 60 | E7: =C7+D7 -> 80 | F7: =C7+D7-E7 -> 0 | G7: ='Топливо Декабрь 2024 '!H7 -> 10566 | H7: 10566 | I7: =H7-G7 -> 0 | J7: 0 | M7: 3.8 | R7: не работал
A8: Экскаватор JCB | B8: 45658 | C8: ='Топливо Декабрь 2024 '!E8 -> 15 | D8: =SUMIF($A$31:$A$112,A8,$B$31:$B$112) -> 900 | E8: 20 | F8: =C8+D8-E8 -> 895 | G8: ='Топливо Декабрь 2024 '!H8 -> 18366 | H8: 18565 | I8: =H8-G8 -> 199 | J8: 0 | L8: 182 | M8: 4.35 | N8: =F8/I8 -> 4.4974874 | O8: =N8-M8 -> 0.14748744 | P8: =O8/M8 -> 0.033905158 | Q8: =(I8*O8*$K$26) -> 1582.3741
A9: Экскаватор JCB 3CX 2008 | B9: 45658 | C9: ='Топливо Декабрь 2024 '!E9 -> 30 | D9: =SUMIF($A$31:$A$112,A9,$B$31:$B$112) -> 0 | E9: 30 | F9: =C9+D9-E9 -> 0 | G9: ='Топливо Декабрь 2024 '!H9 -> 191 | H9: 191 | I9: =H9-G9 -> 0 | J9: 0 | M9: 4.35 | R9: не работал
A10: Экскаватор JCB 2013 | B10: 45658 | C10: ='Топливо Декабрь 2024 '!E10 -> 100 | D10: =SUMIF($A$31:$A$112,A10,$B$31:$B$112) -> 700 | E10: 20 | F10: =C10+D10-E10 -> 780 | G10: ='Топливо Декабрь 2024 '!H10 -> 12628 | H10: 12787 | I10: =H10-G10 -> 159 | J10: 0 | L10: 157 | M10: 4.35 | N10: =F10/I10 -> 4.9056604 | O10: =N10-M10 -> 0.55566038 | P10: =O10/M10 -> 0.12773802 | Q10: =(I10*O10*$K$26) -> 4763.2966
A11: Экскаватор JCB 220 | B11: 45658 | C11: ='Топливо Декабрь 2024 '!E11 -> 460 | D11: =SUMIF($A$31:$A$112,A11,$B$31:$B$112) -> 200 | E11: 450 | F11: =C11+D11-E11 -> 210 | G11: ='Топливо Декабрь 2024 '!H11 -> 7753 | H11: 7769 | I11: =H11-G11 -> 16 | J11: 0 | L11: 16 | M11: 10.5 | N11: =F11/I11 -> 13.125 | O11: =N11-M11 -> 2.625 | P11: =O11/M11 -> 0.25 | Q11: =(I11*O11*$K$26) -> 2264.3855 | R11: gps фиксирует слив 174 л
A12: МАЗ 264 | B12: 45658 | C12: ='Топливо Декабрь 2024 '!E12 -> 150 | D12: =SUMIF($A$31:$A$112,A12,$B$31:$B$112) -> 468 | E12: 220 | F12: =C12+D12-E12 -> 398 | G12: ='Топливо Декабрь 2024 '!H12 -> 34232 | H12: 34624 | I12: =H12-G12 -> 392 | J12: 0 | L12: 156 | M12: 0.9 | N12: =F12/I12 -> 1.0153061 | O12: =N12-M12 -> 0.11530612 | P12: =O12/M12 -> 0.12811791 | Q12: =(I12*O12*$K$26) -> 2436.9101
A13: МАЗ 265 | B13: 45658 | C13: ='Топливо Декабрь 2024 '!E13 -> 180 | D13: =SUMIF($A$31:$A$112,A13,$B$31:$B$112) -> 300 | E13: 150 | F13: =C13+D13-E13 -> 330 | G13: ='Топливо Декабрь 2024 '!H13 -> 39170 | H13: 39481 | I13: =H13-G13 -> 311 | J13: 0 | L13: 130 | M13: 0.9 | N13: =F13/I13 -> 1.0610932 | O13: =N13-M13 -> 0.16109325 | P13: =O13/M13 -> 0.1789925 | Q13: =(I13*O13*$K$26) -> 2701.0884
A14: Самосвал Камаз | B14: 45658 | C14: ='Топливо Декабрь 2024 '!E14 -> 280 | D14: =SUMIF($A$31:$A$112,A14,$B$31:$B$112) -> 0 | E14: 280 | F14: =C14+D14-E14 -> 0 | G14: ='Топливо Декабрь 2024 '!H14 -> 560741 | H14: 560741 | I14: =H14-G14 -> 0 | J14: 0 | L14: 6 | M14: 0.9
A15: Самосвал МАЗ | B15: 45658 | C15: ='Топливо Декабрь 2024 '!E15 -> 150 | D15: =SUMIF($A$31:$A$112,A15,$B$31:$B$112) -> 623.42 | E15: 150 | F15: =C15+D15-E15 -> 623.42 | G15: ='Топливо Декабрь 2024 '!H15 -> 74896 | H15: 75883 | I15: =H15-G15 -> 987 | J15: 0 | L15: 115 | M15: 0.9 | N15: =F15/I15 -> 0.63163121 | R15: gps фиксирует слив 11,52 л
A16: Самосвал МАЗ №2 | B16: 45658 | C16: ='Топливо Декабрь 2024 '!E16 -> 150 | D16: =SUMIF($A$31:$A$112,A16,$B$31:$B$112) -> 185 | E16: 185 | F16: =C16+D16-E16 -> 150 | G16: ='Топливо Декабрь 2024 '!H16 -> 71598 | H16: 71770 | I16: =H16-G16 -> 172 | J16: 0 | L16: 26 | M16: 0.9 | N16: =F16/I16 -> 0.87209302
A17: Автокран XCMG 55 | B17: 45658 | C17: ='Топливо Декабрь 2024 '!E17 -> 110 | D17: =SUMIF($A$31:$A$112,A17,$B$31:$B$112) -> 0 | E17: 110 | F17: =C17+D17-E17 -> 0 | G17: ='Топливо Декабрь 2024 '!H17 -> 0 | H17: 0 | I17: =L17*0.7 -> 0 | J17: 0 | M17: 5.1 | R17: не работал
A18: Автокран XCMG | B18: 45658 | C18: ='Топливо Декабрь 2024 '!E18 -> 100 | D18: =SUMIF($A$31:$A$112,A18,$B$31:$B$112) -> 400 | E18: 180 | F18: =C18+D18-E18 -> 320 | G18: ='Топливо Декабрь 2024 '!H18 -> 6326 | H18: 6426 | I18: =H18-G18 -> 100 | J18: 0 | L18: 180 | M18: 4.07 | N18: =(F18-(0.4*K18))/I18 -> 3.2
A19: Автокран Клинцы | B19: 45658 | C19: ='Топливо Декабрь 2024 '!E19 -> 40 | D19: =SUMIF($A$31:$A$112,A19,$B$31:$B$112) -> 400 | E19: 140 | F19: =C19+D19-E19 -> 300 | G19: ='Топливо Декабрь 2024 '!H19 -> 32 | H19: 98 | I19: =H19-G19 -> 66 | J19: 0 | L19: 151 | M19: 2.9 | N19: =F19/I19 -> 4.5454545 | O19: =N19-M19 -> 1.6454545 | P19: =O19/M19 -> 0.56739812 | Q19: =(I19*O19*$K$26) -> 5855.0539 | R19: gps фиксирует слив
A20: MAN №5 KA5697НВ | B20: 45658 | C20: ='Топливо Декабрь 2024 '!E20 -> 0 | F20: 1354 | I20: 3974 | M20: 0.32 | N20: =F20/I20 -> 0.34071465 | O20: =N20-M20 -> 0.020714645 | P20: =O20/M20 -> 0.064733266 | Q20: =O20*I20*50.41 -> 4149.7512 | R20: данные использ топлива согласно GPS
A21: MAN №4 KA5697НВ | B21: 45658 | F21: 656 | I21: 1811 | M21: 0.32 | N21: =F21/I21 -> 0.36223081 | O21: =N21-M21 -> 0.042230812 | P21: =O21/M21 -> 0.13197129 | Q21: =O21*I21*50.41 -> 3855.3568 | R21: данные использ топлива согласно GPS, gps фиксирует слив 30 л
A22: MAN №3 white KA7837HO | B22: 45658 | C22: ='Топливо Декабрь 2024 '!E21 -> 0 | F22: 403 | I22: 1106 | M22: 0.32 | N22: =F22/I22 -> 0.36437613 | O22: =N22-M22 -> 0.04437613 | P22: =O22/M22 -> 0.13867541 | Q22: =O22*I22*50.41 -> 2474.1228 | R22: данные использ топлива согласно GPS
C23: =SUM(C3:C19) -> 2000 | D23: =SUM(D2:D19) -> 6721.34 | E23: =SUM(E2:E19) -> 2415 | Q23: =SUM(Q3:Q19) -> 21197.344
D24: =D23-B113 -> 0
J26: Стоимость 1 л | K26: =SUM(C31:C112)/B113 -> 53.91394
A29: Заправки АЗС
A30: Наименование | B30: Количество | C30: Сумма | D30: АЗС
A31: Автокран XCMG | B31: 100 | C31: 4883 | D31: Авиас
A32: Телескоп JCB 535-140 (№4) | B32: 184.92 | C32: 9029.6436 | D32: Авиас
A33: Экскаватор JCB | B33: 200 | C33: 9766 | D33: Авиас
A34: Экскаватор JCB 2013 | B34: 200 | C34: 9766 | D34: Авиас
A35: Автокран Клинцы | B35: 200 | C35: 9766 | D35: Авиас
A36: МАЗ 264 | B36: 168 | C36: 8710.94 | D36: Авиас
A37: Телескоп 2 | B37: 200 | C37: 10578 | D37: Авиас
A38: Телескоп JCB 540-170 №5 | B38: 200 | C38: 10578 | D38: Авиас
A39: Самосвал МАЗ | B39: 175 | C39: 9255.75 | D39: Авиас
A40: Виброкаток | B40: 100 | C40: 5289 | D40: Авиас
E41: =SUM(C31:C41) -> 87622.334
A42: Телескоп 2 | B42: 500 | C42: 27295 | D42: БВС ритейл
A43: Телескоп JCB 540-170 №5 | B43: 500 | C43: 27495 | D43: БВС ритейл
A44: Экскаватор JCB | B44: 700 | C44: 38493 | D44: БВС ритейл
A45: Экскаватор JCB 2013 | B45: 500 | C45: 27595 | D45: БВС ритейл
A46: Автокран Клинцы | B46: 200 | C46: 10698 | D46: БВС ритейл
A47: МАЗ 265 | B47: 300 | C47: 16597 | D47: БВС ритейл
A48: МАЗ 264 | B48: 300 | C48: 16497 | D48: БВС ритейл
A49: Телескоп JCB 535-140 (№4) | B49: 600 | C49: 33194 | D49: БВС ритейл
A50: Виброкаток | B50: 200 | C50: 10998 | D50: БВС ритейл
A51: Самосвал МАЗ №2 | B51: 185 | C51: 9988.15 | D51: БВС ритейл
A52: Самосвал МАЗ | B52: 448.42 | C52: 25107.04 | D52: БВС ритейл
A53: Автокран XCMG | B53: 300 | C53: 16597 | D53: БВС ритейл
A54: Экскаватор JCB 220 | B54: 200 | C54: 11198 | D54: БВС ритейл
D55: БВС ритейл
E72: =SUM(C42:C72) -> 271752.19
A74: Ротор Пегасус | B74: 60 | C74: 2999.4 | D74: ВОГ
E76: =SUM(C73:C76) -> 2999.4
D77: Амик
D78: Амик
D79: Амик
D80: Амик
D81: Амик
E83: =SUM(C77:C83) -> 0
E84: =SUM(C84:C84) -> 0
E112: =SUM(C85:C112) -> 0
B113: =SUM(B31:B112) -> 6721.34 | C113: =SUM(C31:C112) -> 362373.92

Sheet Топливо Февраль 2025
A1: Наименование | B1: Отчетный период | C1: Остаток на начало | D1: Топливо заправленное | E1: Остаток на конец | F1: Расход топлива за период, л | G1: Моточасы на начало | H1: Моточасы на конец | I1: Отработано техникой моточасов | J1: Перегон на доругой объект, л | K1: Перегон на доругой объект, км | L1: Часы работы на обьекте | M1: Норма расхода топлива литр/1 мото час согласно сс | N1: Факт витрат на 1 мото/год, км витрат (л/год) | O1: Отклонения л/мотогод | P1: Отклонения от нормы,% | Q1: Отклонения, грн/мес | R1: Примечание по строке
A2: Телескоп 1 | B2: 45474 | D2: =SUMIF($A$31:$A$150,A2,$B$31:$B$150) -> 0 | F2: =C2+D2-E2 -> 0 | I2: =H2-G2 -> 0 | J2: 0 | M2: =VLOOKUP(A2,[4]Тарас!$C$4:$P$23,14,0) -> 3.4 | Q2: =194.94*I2 -> 0
A3: Телескоп 2 | B3: 45689 | C3: ='Топливо Январь 2025'!E3 -> 120 | D3: =SUMIF($A$31:$A$150,A3,$B$31:$B$150) -> 495.69 | E3: 100 | F3: =C3+D3-E3 -> 515.69 | G3: ='Топливо Январь 2025'!H3 -> 0 | I3: =L3*0.65 -> 102.05 | L3: 157 | M3: 4.73 | N3: =F3/I3 -> 5.0533072 | O3: =N3-M3 -> 0.3233072 | P3: =O3/M3 -> 0.068352474 | Q3: =(I3*O3*$K$26) -> 1846.0673 | R3: не работает мотосчетчик
A4: Телескоп JCB 535-140 (№4) | B4: 45689 | C4: ='Топливо Январь 2025'!E4 -> 65 | D4: =SUMIF($A$31:$A$150,A4,$B$31:$B$150) -> 300 | E4: 130 | F4: =C4+D4-E4 -> 235 | G4: ='Топливо Январь 2025'!H4 -> 10445 | H4: 10496 | I4: =H4-G4 -> 51 | J4: 0 | L4: 50 | M4: 4.73 | N4: =F4/I4 -> 4.6078431
A5: Телескоп JCB 540-170 №5 | B5: 45689 | C5: ='Топливо Январь 2025'!E5 -> 115 | D5: =SUMIF($A$31:$A$150,A5,$B$31:$B$150) -> 600 | E5: 30 | F5: =C5+D5-E5 -> 685 | G5: ='Топливо Январь 2025'!H5 -> 8202 | H5: 8359 | I5: =H5-G5 -> 157 | J5: 0 | L5: 180 | M5: 4.73 | N5: =F5/I5 -> 4.3630573
A6: Виброкаток | B6: 45689 | C6: ='Топливо Январь 2025'!E6 -> 100 | D6: =SUMIF($A$31:$A$150,A6,$B$31:$B$150) -> 400 | E6: 120 | F6: =C6+D6-E6 -> 380 | G6: ='Топливо Январь 2025'!H6 -> 5207 | H6: 5258 | I6: =H6-G6 -> 51 | J6: 0 | L6: 96 | M6: 5 | N6: =F6/I6 -> 7.4509804 | O6: =N6-M6 -> 2.4509804 | P6: =O6/M6 -> 0.49019608 | Q6: =(I6*O6*$K$26) -> 6994.0566
A7: Ротор Пегасус | B7: 45689 | C7: ='Топливо Январь 2025'!E7 -> 80 | D7: =SUMIF($A$31:$A$150,A7,$B$31:$B$150) -> 80 | E7: 25 | F7: =C7+D7-E7 -> 135 | G7: ='Топливо Январь 2025'!H7 -> 10566 | H7: 10616 | I7: =H7-G7 -> 50 | J7: 0 | L7: 0 | M7: 3.8 | N7: =F7/I7 -> 2.7 | R7: не работал
A8: Экскаватор JCB | B8: 45689 | C8: ='Топливо Январь 2025'!E8 -> 20 | D8: =SUMIF($A$31:$A$150,A8,$B$31:$B$150) -> 1010 | E8: 50 | F8: =C8+D8-E8 -> 980 | G8: ='Топливо Январь 2025'!H8 -> 18565 | H8: 18772 | I8: =H8-G8 -> 207 | J8: 0 | L8: 190 | M8: 4.35 | N8: =F8/I8 -> 4.7342995 | O8: =N8-M8 -> 0.38429952 | P8: =O8/M8 -> 0.088344717 | Q8: =(I8*O8*$K$26) -> 4451.0176
A9: Экскаватор JCB 3CX 2008 | B9: 45689 | C9: ='Топливо Январь 2025'!E9 -> 30 | D9: =SUMIF($A$31:$A$150,A9,$B$31:$B$150) -> 0 | E9: 30 | F9: =C9+D9-E9 -> 0 | G9: ='Топливо Январь 2025'!H9 -> 191 | H9: 191 | I9: =H9-G9 -> 0 | J9: 0 | M9: 4.35 | R9: не работал
A10: Экскаватор JCB 2013 | B10: 45689 | C10: ='Топливо Январь 2025'!E10 -> 20 | D10: =SUMIF($A$31:$A$150,A10,$B$31:$B$150) -> 977 | E10: 30 | F10: =C10+D10-E10 -> 967 | G10: ='Топливо Январь 2025'!H10 -> 12787 | H10: 12971 | I10: =H10-G10 -> 184 | J10: 0 | L10: 194 | M10: 4.35 | N10: =F10/I10 -> 5.2554348 | O10: =N10-M10 -> 0.90543478 | P10: =O10/M10 -> 0.20814593 | Q10: =(I10*O10*$K$26) -> 9321.6786
A11: Экскаватор JCB 220 | B11: 45689 | C11: ='Топливо Январь 2025'!E11 -> 450 | D11: =SUMIF($A$31:$A$150,A11,$B$31:$B$150) -> 1200 | E11: 515 | F11: =C11+D11-E11 -> 1135 | G11: ='Топливо Январь 2025'!H11 -> 7769 | H11: 7888 | I11: =H11-G11 -> 119 | J11: 0 | L11: 157 | M11: 10.5 | N11: =F11/I11 -> 9.5378151
A12: МАЗ 264 | B12: 45689 | C12: ='Топливо Январь 2025'!E12 -> 220 | D12: =SUMIF($A$31:$A$150,A12,$B$31:$B$150) -> 600 | E12: 160 | F12: =C12+D12-E12 -> 660 | G12: ='Топливо Январь 2025'!H12 -> 34624 | H12: 35617 | I12: =H12-G12 -> 993 | J12: 0 | L12: 151 | M12: 0.9 | N12: =F12/I12 -> 0.66465257
A13: МАЗ 265 | B13: 45689 | C13: ='Топливо Январь 2025'!E13 -> 150 | D13: =SUMIF($A$31:$A$150,A13,$B$31:$B$150) -> 200 | E13: 150 | F13: =C13+D13-E13 -> 200 | G13: ='Топливо Январь 2025'!H13 -> 39481 | H13: 39794 | I13: =H13-G13 -> 313 | J13: 0 | L13: 59 | M13: 0.9 | N13: =F13/I13 -> 0.63897764
A14: Самосвал Камаз | B14: 45689 | C14: ='Топливо Январь 2025'!E14 -> 280 | D14: =SUMIF($A$31:$A$150,A14,$B$31:$B$150) -> 0 | E14: 280 | F14: =C14+D14-E14 -> 0 | G14: ='Топливо Январь 2025'!H14 -> 560741 | H14: 560741 | I14: =H14-G14 -> 0 | J14: 0 | M14: 0.9 | R14: не работал
A15: Самосвал МАЗ | B15: 45689 | C15: ='Топливо Январь 2025'!E15 -> 150 | D15: =SUMIF($A$31:$A$150,A15,$B$31:$B$150) -> 665.01 | E15: 40 | F15: =C15+D15-E15 -> 775.01 | G15: ='Топливо Январь 2025'!H15 -> 75883 | H15: 76832 | I15: =H15-G15 -> 949 | J15: 0 | L15: 136 | M15: 0.9 | N15: =F15/I15 -> 0.81665964
A16: Самосвал МАЗ №2 | B16: 45689 | C16: ='Топливо Январь 2025'!E16 -> 185 | D16: =SUMIF($A$31:$A$150,A16,$B$31:$B$150) -> 995 | E16: 150 | F16: =C16+D16-E16 -> 1030 | G16: ='Топливо Январь 2025'!H16 -> 71770 | H16: 73578 | I16: =H16-G16 -> 1808 | J16: 0 | L16: 173 | M16: 0.9 | N16: =F16/I16 -> 0.56969027
A17: Автокран XCMG 55 | B17: 45689 | C17: ='Топливо Январь 2025'!E17 -> 110 | D17: =SUMIF($A$31:$A$150,A17,$B$31:$B$150) -> 400 | E17: 170 | F17: =C17+D17-E17 -> 340 | G17: ='Топливо Январь 2025'!H17 -> 0 | I17: =L17*0.7 -> 24.5 | J17: 0 | L17: 35 | M17: 5.1 | N17: =F17/I17 -> 13.877551 | O17: =N17-M17 -> 8.777551 | P17: =O17/M17 -> 1.7210884 | Q17: =(I17*O17*$K$26) -> 12032.575 | R17: не работает мотосчетчик
A18: Автокран XCMG | B18: 45689 | C18: ='Топливо Январь 2025'!E18 -> 180 | D18: =SUMIF($A$31:$A$150,A18,$B$31:$B$150) -> 400 | E18: 120 | F18: =C18+D18-E18 -> 460 | G18: ='Топливо Январь 2025'!H18 -> 6426 | H18: 6526 | I18: =H18-G18 -> 100 | J18: 0 | L18: 198 | M18: 4.07 | N18: =F18/I18 -> 4.6 | O18: =N18-M18 -> 0.53 | P18: =O18/M18 -> 0.13022113 | Q18: =(I18*O18*$K$26) -> 2965.48
A19: Автокран Клинцы | B19: 45689 | C19: ='Топливо Январь 2025'!E19 -> 140 | D19: =SUMIF($A$31:$A$150,A19,$B$31:$B$150) -> 200 | E19: 60 | F19: =C19+D19-E19 -> 280 | G19: ='Топливо Январь 2025'!H19 -> 98 | H19: 139 | I19: =H19-G19 -> 41 | J19: 0 | L19: 123 | M19: 2.9 | N19: =F19/I19 -> 6.8292683 | O19: =N19-M19 -> 3.9292683 | P19: =O19/M19 -> 1.3549201 | Q19: =(I19*O19*$K$26) -> 9013.9402
A20: MAN №5 KA5697НВ | B20: 45689 | C20: ='Топливо Декабрь 2024 '!E20 -> 0 | F20: 1212 | I20: 3171 | M20: 0.32 | N20: =F20/I20 -> 0.38221381 | O20: =N20-M20 -> 0.062213813 | P20: =O20/M20 -> 0.19441816 | Q20: =O20*I20*50.41 -> 9944.8848 | R20: данные использ топлива согласно GPS
A21: MAN №4 KA5697НВ | B21: 45689 | F21: 876 | I21: 2263 | M21: 0.32 | N21: =F21/I21 -> 0.38709677 | O21: =N21-M21 -> 0.067096774 | P21: =O21/M21 -> 0.20967742 | Q21: =O21*I21*51.99 -> 7894.1616 | R21: данные использ топлива согласно GPS
A22: MAN №3 white KA7837HO | B22: 45689 | C22: ='Топливо Декабрь 2024 '!E21 -> 0 | M22: 0.32 | N22: =F22/I22 -> #DIV/0! | O22: =N22-M22 -> #DIV/0! | P22: =O22/M22 -> #DIV/0! | Q22: =O22*I22*50.41 -> #DIV/0! | R22: данные использ топлива согласно GPS
C23: =SUM(C3:C19) -> 2415 | D23: =SUM(D2:D19) -> 8522.7 | E23: =SUM(E2:E19) -> 2160 | Q23: =SUM(Q3:Q19) -> 46624.815
D24: =D23-B151 -> 0
J26: Стоимость 1 л | K26: =SUM(C31:C150)/B151 -> 55.952453
A29: Заправки АЗС
A30: Наименование | B30: Количество | C30: Сумма | D30: АЗС
A31: Телескоп 2 | B31: 100 | C31: 5599 | D31: БВС ритейл
A32: Телескоп 2 | B32: 44 | C32: 2463.56 | D32: БВС ритейл
A33: Телескоп 2 | B33: 71.69 | C33: 4013.92 | D33: БВС ритейл
A34: Телескоп 2 | B34: 80 | C34: 4479.2 | D34: БВС ритейл
A35: Телескоп 2 | B35: 100 | C35: 5599 | D35: БВС ритейл
A36: Телескоп 2 | B36: 100 | C36: 5599 | D36: БВС ритейл
A37: Телескоп JCB 540-170 №5 | B37: 100 | C37: 5599 | D37: БВС ритейл
A38: Телескоп JCB 540-170 №5 | B38: 100 | C38: 5599 | D38: БВС ритейл
A39: Телескоп JCB 540-170 №5 | B39: 100 | C39: 5599 | D39: БВС ритейл
A40: Телескоп JCB 540-170 №5 | B40: 100 | C40: 5599 | D40: БВС ритейл
A41: Телескоп JCB 540-170 №5 | B41: 100 | C41: 5599 | D41: БВС ритейл
A42: Телескоп JCB 540-170 №5 | B42: 100 | C42: 5599 | D42: БВС ритейл
... A104: Экскаватор JCB 220 | B104: 200 | C104: 11198 | D104: БВС ритейл
D105: БВС ритейл
D106: БВС ритейл
D107: БВС ритейл
D108: БВС ритейл
D109: БВС ритейл
E110: =SUM(C31:C110) -> 472706.77
A111: Ротор Пегасус | B111: 40 | C111: 2079.6
A112: Ротор Пегасус | B112: 40 | C112: 2079.6 | D112: ВОГ
E114: =SUM(C111:C114) -> 4159.2
D115: Амик
D116: Амик
D117: Амик
D118: Амик
D119: Амик
E121: =SUM(C115:C121) -> 0
E122: =SUM(C122:C122) -> 0
E150: =SUM(C123:C150) -> 0
B151: =SUM(B31:B150) -> 8522.7 | C151: =SUM(C31:C150) -> 476865.97

Sheet Топливо Март 2025
A1: Наименование | B1: Отчетный период | C1: Остаток на начало | D1: Топливо заправленное | E1: Остаток на конец | F1: Расход топлива за период, л | G1: Моточасы на начало | H1: Моточасы на конец | I1: Отработано техникой моточасов | J1: Перегон на доругой объект, л | K1: Перегон на доругой объект, км | L1: Часы работы на обьекте | M1: Норма расхода топлива литр/1 мото час согласно сс | N1: Факт витрат на 1 мото/год, км витрат (л/год) | O1: Отклонения л/мотогод | P1: Отклонения от нормы,% | Q1: Отклонения, грн/мес | R1: Примечание по строке
A2: Телескоп 1 | B2: 45474 | D2: =SUMIF($A$31:$A$163,A2,$B$31:$B$163) -> 0 | F2: =C2+D2-E2 -> 0 | I2: =H2-G2 -> 0 | J2: 0 | M2: =VLOOKUP(A2,[4]Тарас!$C$4:$P$23,14,0) -> 3.4 | Q2: =194.94*I2 -> 0
A3: Телескоп 2 | B3: 45717 | C3: ='Топливо Февраль 2025'!E3 -> 100 | D3: =SUMIF($A$31:$A$163,A3,$B$31:$B$163) -> 600 | E3: 55 | F3: =C3+D3-E3 -> 645 | G3: ='Топливо Февраль 2025'!H3 -> 0 | H3: 0 | I3: =L3*0.65 -> 140.4 | L3: 216 | M3: 4.73 | N3: =F3/I3 -> 4.5940171 | R3: не работает мотосчетчик
A4: Телескоп JCB 535-140 (№4) | B4: 45717 | C4: ='Топливо Февраль 2025'!E4 -> 130 | D4: =SUMIF($A$31:$A$163,A4,$B$31:$B$163) -> 580 | E4: 70 | F4: =C4+D4-E4 -> 640 | G4: ='Топливо Февраль 2025'!H4 -> 10496 | H4: 10662 | I4: =H4-G4 -> 166 | J4: 0 | L4: 198 | M4: 4.73 | N4: =F4/I4 -> 3.8554217
A5: Телескоп JCB 540-170 №5 | B5: 45717 | C5: ='Топливо Февраль 2025'!E5 -> 30 | D5: =SUMIF($A$31:$A$163,A5,$B$31:$B$163) -> 740 | E5: 65 | F5: =C5+D5-E5 -> 705 | G5: ='Топливо Февраль 2025'!H5 -> 8359 | H5: 8506 | I5: =H5-G5 -> 147 | J5: 0 | L5: 182 | M5: 4.73 | N5: =F5/I5 -> 4.7959184 | O5: =N5-M5 -> 0.065918367 | P5: =O5/M5 -> 0.01393623 | Q5: =(I5*O5*$K$26) -> 538.98522
A6: Виброкаток | B6: 45717 | C6: ='Топливо Февраль 2025'!E6 -> 120 | D6: =SUMIF($A$31:$A$163,A6,$B$31:$B$163) -> 260 | E6: 150 | F6: =C6+D6-E6 -> 230 | G6: ='Топливо Февраль 2025'!H6 -> 5258 | H6: 5301 | I6: =H6-G6 -> 43 | J6: 0 | L6: 162 | M6: 5 | N6: =F6/I6 -> 5.3488372 | O6: =N6-M6 -> 0.34883721 | P6: =O6/M6 -> 0.069767442 | Q6: =(I6*O6*$K$26) -> 834.34244
A7: Ротор Пегасус | B7: 45717 | C7: ='Топливо Февраль 2025'!E7 -> 25 | D7: =SUMIF($A$31:$A$163,A7,$B$31:$B$163) -> 229.09 | E7: 25 | F7: =C7+D7-E7 -> 229.09 | G7: ='Топливо Февраль 2025'!H7 -> 10616 | H7: 10707 | I7: =H7-G7 -> 91 | J7: 0 | L7: 128 | M7: 3.8 | N7: =F7/I7 -> 2.5174725
A8: Экскаватор JCB | B8: 45717 | C8: ='Топливо Февраль 2025'!E8 -> 50 | D8: =SUMIF($A$31:$A$163,A8,$B$31:$B$163) -> 988 | E8: 30 | F8: =C8+D8-E8 -> 1008 | G8: ='Топливо Февраль 2025'!H8 -> 18772 | H8: 18992 | I8: =H8-G8 -> 220 | J8: 0 | L8: 220 | M8: 4.35 | N8: =F8/I8 -> 4.5818182 | O8: =N8-M8 -> 0.23181818 | P8: =O8/M8 -> 0.053291536 | Q8: =(I8*O8*$K$26) -> 2836.7643
A9: Экскаватор JCB 3CX 2008 | B9: 45717 | C9: ='Топливо Февраль 2025'!E9 -> 30 | D9: =SUMIF($A$31:$A$163,A9,$B$31:$B$163) -> 0 | E9: =C9 -> 30 | F9: =C9+D9-E9 -> 0 | G9: ='Топливо Февраль 2025'!H9 -> 191 | H9: =G9 -> 191 | I9: =H9-G9 -> 0 | J9: 0 | L9: 0 | M9: 4.35 | R9: не работал
A10: Экскаватор JCB 2013 | B10: 45717 | C10: ='Топливо Февраль 2025'!E10 -> 30 | D10: =SUMIF($A$31:$A$163,A10,$B$31:$B$163) -> 940 | E10: 15 | F10: =C10+D10-E10 -> 955 | G10: ='Топливо Февраль 2025'!H10 -> 12971 | H10: 13153 | I10: =H10-G10 -> 182 | J10: 0 | L10: 217 | M10: 4.35 | N10: =F10/I10 -> 5.2472527 | O10: =N10-M10 -> 0.89725275 | P10: =O10/M10 -> 0.206265 | Q10: =(I10*O10*$K$26) -> 9083.2081
A11: Экскаватор JCB 220 | B11: 45717 | C11: ='Топливо Февраль 2025'!E11 -> 515 | D11: =SUMIF($A$31:$A$163,A11,$B$31:$B$163) -> 900 | E11: 276 | F11: =C11+D11-E11 -> 1139 | G11: ='Топливо Февраль 2025'!H11 -> 7888 | H11: 8004 | I11: =H11-G11 -> 116 | J11: 0 | L11: 132 | M11: 10.5 | N11: =F11/I11 -> 9.8189655
A12: МАЗ 264 | B12: 45717 | C12: ='Топливо Февраль 2025'!E12 -> 160 | D12: =SUMIF($A$31:$A$163,A12,$B$31:$B$163) -> 700 | E12: 130 | F12: =C12+D12-E12 -> 730 | G12: ='Топливо Февраль 2025'!H12 -> 35617 | H12: 36907 | I12: =H12-G12 -> 1290 | J12: 0 | L12: 169 | M12: 0.9 | N12: =F12/I12 -> 0.56589147
A13: МАЗ 265 | B13: 45717 | C13: ='Топливо Февраль 2025'!E13 -> 150 | D13: =SUMIF($A$31:$A$163,A13,$B$31:$B$163) -> 500 | E13: 115 | F13: =C13+D13-E13 -> 535 | G13: ='Топливо Февраль 2025'!H13 -> 39794 | H13: 40633 | I13: =H13-G13 -> 839 | J13: 0 | L13: 114 | M13: 0.9 | N13: =F13/I13 -> 0.63766389
A14: Самосвал Камаз | B14: 45717 | C14: ='Топливо Февраль 2025'!E14 -> 280 | D14: =SUMIF($A$31:$A$163,A14,$B$31:$B$163) -> 0 | E14: =C14 -> 280 | F14: =C14+D14-E14 -> 0 | G14: ='Топливо Февраль 2025'!H14 -> 560741 | H14: =G14 -> 560741 | I14: =H14-G14 -> 0 | J14: 0 | L14: 0 | M14: 0.9 | R14: не работал
A15: Самосвал МАЗ | B15: 45717 | C15: ='Топливо Февраль 2025'!E15 -> 40 | D15: =SUMIF($A$31:$A$163,A15,$B$31:$B$163) -> 610 | E15: 130 | F15: =C15+D15-E15 -> 520 | G15: ='Топливо Февраль 2025'!H15 -> 76832 | H15: 77664 | I15: =H15-G15 -> 832 | J15: 0 | L15: 87 | M15: 0.9 | N15: =F15/I15 -> 0.625
A16: Самосвал МАЗ №2 | B16: 45717 | C16: ='Топливо Февраль 2025'!E16 -> 150 | D16: =SUMIF($A$31:$A$163,A16,$B$31:$B$163) -> 700 | E16: 80 | F16: =C16+D16-E16 -> 770 | G16: ='Топливо Февраль 2025'!H16 -> 73578 | H16: 74670 | I16: =H16-G16 -> 1092 | J16: 0 | L16: 125 | M16: 0.9 | N16: =F16/I16 -> 0.70512821
A17: Автокран XCMG 55 | B17: 45717 | C17: ='Топливо Февраль 2025'!E17 -> 170 | D17: =SUMIF($A$31:$A$163,A17,$B$31:$B$163) -> 560 | E17: 210 | F17: =C17+D17-E17 -> 520 | G17: ='Топливо Февраль 2025'!H17 -> 0 | H17: 560 | I17: =H17-G17 -> 560 | J17: 0 | L17: 71 | M17: 5.1 | N17: =F17/I17 -> 0.92857143
A18: Автокран XCMG | B18: 45717 | C18: ='Топливо Февраль 2025'!E18 -> 120 | D18: =SUMIF($A$31:$A$163,A18,$B$31:$B$163) -> 280 | E18: 35 | F18: =C18+D18-E18 -> 365 | G18: ='Топливо Февраль 2025'!H18 -> 6526 | H18: 6630 | I18: =H18-G18 -> 104 | J18: 0 | L18: 141 | M18: 4.07 | N18: =F18/I18 -> 3.5096154
A19: Автокран Клинцы | B19: 45717 | C19: ='Топливо Февраль 2025'!E19 -> 60 | D19: =SUMIF($A$31:$A$163,A19,$B$31:$B$163) -> 200 | E19: 50 | F19: =C19+D19-E19 -> 210 | G19: ='Топливо Февраль 2025'!H19 -> 139 | H19: 179 | I19: =H19-G19 -> 40 | J19: 0 | L19: 71 | M19: 2.9 | N19: =F19/I19 -> 5.25 | O19: =N19-M19 -> 2.35 | P19: =O19/M19 -> 0.81034483 | Q19: =(I19*O19*$K$26) -> 5228.546 | S19: комментарий февраля (не было ремонта???- Не корректно работает турбина
A20: MAN №5 KA5697НВ | B20: 45717 | C20: 115 | D20: 1406.38 | E20: 344 | F20: =C20+D20-E20 -> 1177.38 | I20: 3176 | M20: 0.32 | N20: =F20/I20 -> 0.37071159 | O20: =N20-M20 -> 0.050711587 | P20: =O20/M20 -> 0.15847371 | Q20: =O20*I20*51.53 -> 8299.4218 | R20: данные посчитаны с обороток, GPS показывает расход на 600 больше, написан запрос на Транс Групп
A21: MAN №4 KA5697НВ | B21: 45717 | C21: 214 | D21: 1283 | E21: 441 | F21: =C21+D21-E21 -> 1056 | I21: 3085 | M21: 0.32 | N21: =F21/I21 -> 0.34230146 | O21: =N21-M21 -> 0.022301459 | P21: =O21/M21 -> 0.069692058 | Q21: =O21*I21*51.53 -> 3545.264 | R21: данные посчитаны с обороток, GPS показывает расход на 400 больше, написан запрос на Транс Групп
A22: MAN №3 white KA7837HO | B22: 45717 | C22: ='Топливо Февраль 2025'!E22 -> 0 | M22: 0.32 | N22: =F22/I22 -> #DIV/0! | O22: =N22-M22 -> #DIV/0! | P22: =O22/M22 -> #DIV/0! | Q22: =O22*I22*50.41 -> #DIV/0! | R22: данные использ топлива согласно GPS
C23: =SUM(C3:C19) -> 2160 | D23: =SUM(D2:D19) -> 8787.09 | E23: =SUM(E2:E19) -> 1746 | Q23: =SUM(Q3:Q19) -> 18521.846
D24: =D23-B164 -> 0
J26: Стоимость 1 л | K26: =SUM(C31:C163)/B164 -> 55.62283
A29: Заправки АЗС
A30: Наименование | B30: Количество | C30: Сумма | D30: АЗС
A31: Телескоп 2 | B31: 600 | C31: 33394 | D31: БВС
A32: Телескоп JCB 540-170 №5 | B32: 740 | C32: 41252.6 | D32: БВС
A33: Экскаватор JCB | B33: 988 | C33: 54948.12 | D33: БВС
A34: Экскаватор JCB 2013 | B34: 940 | C34: 52330.6 | D34: БВС
A35: Автокран Клинцы | B35: 200 | C35: 11098 | D35: БВС
A36: МАЗ 265 | B36: 500 | C36: 27895 | D36: БВС
A37: МАЗ 264 | B37: 700 | C37: 39093 | D37: БВС
A38: Телескоп JCB 535-140 (№4) | B38: 580 | C38: 32214.2 | D38: БВС
A39: Автокран XCMG 55 | B39: 560 | C39: 30994.4 | D39: БВС
A40: Виброкаток | B40: 260 | C40: 14357.4 | D40: БВС
A41: Самосвал МАЗ №2 | B41: 700 | C41: 39193 | D41: БВС
A42: Самосвал МАЗ | B42: 610 | C42: 34153.9 | D42: БВС
... A44: Экскаватор JCB 220 | B44: 900 | C44: 50391 | D44: БВС
E123: =SUM(C31:C123) -> 476852.42
A124: Ротор Пегасус | B124: 149.09 | C124: 7751.19 | D124: ВОГ
A125: Ротор Пегасус | B125: 80 | C125: 4159.2 | D125: Укрнафта
E127: =SUM(C124:C127) -> 11910.39
D128: Амик
D129: Амик
D130: Амик
D131: Амик
D132: Амик
E134: =SUM(C128:C134) -> 0
E135: =SUM(C135:C135) -> 0
E163: =SUM(C136:C163) -> 0
B164: =SUM(B31:B163) -> 8787.09 | C164: =SUM(C31:C163) -> 488762.81

Sheet Паливо Грудень  2025
A1: Наименование | B1: Отчетный период | C1: Остаток на начало | D1: Топливо заправленное | E1: Остаток на конец | F1: Расход топлива за период, л | G1: Моточасы на начало | H1: Моточасы на конец | I1: Отработано техникой моточасов | J1: Перегон на доругой объект, л | K1: Перегон на доругой объект, км | L1: Часы работы на обьекте | M1: Норма расхода топлива литр/1 мото час согласно сс | N1: Факт витрат на 1 мото/год, км витрат (л/год) | O1: Отклонения л/мотогод | P1: Отклонения от нормы,% | Q1: Отклонения, грн/мес | R1: Примечание по строке
A2: Телескоп 3 | B2: Декабрь | C2: 0 | D2: 345 | E2: 0 | F2: 345 | G2: 78855 | H2: 79731 | I2: =(H2-G2)*0.65 -> 569.4 | L2: =I2 -> 569.4 | M2: 4.73 | N2: =F2/I2 -> 0.60590095 | O2: =N2-M2 -> -4.1240991
A3: Телескоп 2 | B3: Декабрь | C3: 90 | D3: =SUMIF(A31:A62,A3,B31:B60) -> 600 | E3: =SUMIF('Оренда техники'!$C$1:$C$30,A3,'Оренда техники'!$F$1:$F$30) -> 90 | F3: =C3+D3-E3 -> 600 | G3: 0 | H3: =SUMIF('Оренда техники'!$C$1:$C$30,A3,'Оренда техники'!$E$1:$E$30) -> 0 | I3: =L3*0.65 -> 127.4 | L3: =SUMIF(' то за Грудень 2025'!$B$4:$B$42,A3,' то за Грудень 2025'!$D$4:$D$42) -> 196 | M3: 4.73 | N3: =F3/I3 -> 4.7095761 | O3: =N3-M3 -> -0.020423862
A4: Телескоп JCB 535-140 (№4) | B4: Декабрь | C4: 30 | D4: =SUMIF($A$31:$A$95,A4,$B$31:$B$95) -> 700 | E4: =SUMIF('Оренда техники'!$C$1:$C$30,A4,'Оренда техники'!$F$1:$F$30) -> 70 | F4: =C4+D4-E4 -> 660 | G4: 11433 | H4: =SUMIF('Оренда техники'!$C$1:$C$30,A4,'Оренда техники'!$E$1:$E$30) -> 11678 | I4: =H4-G4 -> 245 | J4: 0 | L4: =SUMIF(' то за Грудень 2025'!$B$4:$B$42,A4,' то за Грудень 2025'!$D$4:$D$42) -> 193 | M4: 4.73 | N4: =F4/I4 -> 2.6938776 | O4: =N4-M4 -> -2.0361224
A5: Телескоп JCB 540-170 №5 | B5: Декабрь | C5: 60 | D5: =SUMIF($A$31:$A$95,A5,$B$31:$B$95) -> 900 | E5: =SUMIF('Оренда техники'!$C$1:$C$30,A5,'Оренда техники'!$F$1:$F$30) -> 70 | F5: =C5+D5-E5 -> 890 | G5: 9357 | H5: =SUMIF('Оренда техники'!$C$1:$C$30,A5,'Оренда техники'!$E$1:$E$30) -> 9672 | I5: =H5-G5 -> 315 | J5: 0 | L5: =SUMIF(' то за Грудень 2025'!$B$4:$B$42,A5,' то за Грудень 2025'!$D$4:$D$42) -> 191 | M5: 4.73 | N5: =F5/I5 -> 2.8253968 | O5: =N5-M5 -> -1.9046032
A6: Виброкаток | B6: 45962 | C6: 130 | D6: =SUMIF($A$31:$A$95,A6,$B$31:$B$95) -> 100 | E6: =SUMIF('Оренда техники'!$C$1:$C$30,A6,'Оренда техники'!$F$1:$F$30) -> 85 | F6: =C6+D6-E6 -> 145 | G6: 5468 | H6: =SUMIF('Оренда техники'!$C$1:$C$30,A6,'Оренда техники'!$E$1:$E$30) -> 5552 | I6: =H6-G6 -> 84 | J6: 0 | L6: =SUMIF(' то за Грудень 2025'!$B$4:$B$42,A6,' то за Грудень 2025'!$D$4:$D$42) -> 82 | M6: 5 | N6: =F6/I6 -> 1.7261905 | O6: =N6-M6 -> -3.2738095
A7: Ротор Пегасус | B7: 45962 | C7: 150 | D7: 0 | E7: 150 | F7: =C7+D7-E7 -> 0 | G7: 11111 | H7: 11111 | I7: =H7-G7 -> 0 | J7: 0 | L7: =SUMIF(' то за Грудень 2025'!$B$4:$B$42,A7,' то за Грудень 2025'!$D$4:$D$42) -> 0 | M7: 3.8 | N7: =IFERROR(F7/I7,0) -> 0 | O7: =N7-M7 -> -3.8
A8: Экскаватор JCB 2007 | B8: 45962 | C8: 0 | D8: =SUMIF($A$31:$A$95,A8,$B$31:$B$95) -> 800 | E8: =SUMIF('Оренда техники'!$C$1:$C$30,A8,'Оренда техники'!$F$1:$F$30) -> 20 | F8: =C8+D8-E8 -> 780 | G8: 19953 | H8: =SUMIF('Оренда техники'!$C$1:$C$30,A8,'Оренда техники'!$E$1:$E$30) -> 20316 | I8: =H8-G8 -> 363 | J8: 0 | L8: =SUMIF(' то за Грудень 2025'!$B$4:$B$42,A8,' то за Грудень 2025'!$D$4:$D$42) -> 191 | M8: 4.35 | N8: =F8/I8 -> 2.1487603 | O8: =N8-M8 -> -2.2012397
A9: Экскаватор JCB 3CX 2008 | B9: 45962 | C9: 80 | D9: =SUMIF($A$31:$A$95,A9,$B$31:$B$95) -> 561.99 | E9: =SUMIF('Оренда техники'!$C$1:$C$30,A9,'Оренда техники'!$F$1:$F$30) -> 50 | F9: =C9+D9-E9 -> 591.99 | G9: 652 | H9: =SUMIF('Оренда техники'!$C$1:$C$30,A9,'Оренда техники'!$E$1:$E$30) -> 874 | I9: =H9-G9 -> 222 | J9: 0 | L9: =SUMIF(' то за Грудень 2025'!$B$4:$B$42,A9,' то за Грудень 2025'!$D$4:$D$42) -> 63 | M9: 4.35 | N9: =F9/I9 -> 2.6666216 | O9: =N9-M9 -> -1.6833784
A10: Экскаватор JCB 2013 | B10: 45962 | C10: 100 | D10: =SUMIF($A$31:$A$95,A10,$B$31:$B$95) -> 650 | E10: =SUMIF('Оренда техники'!$C$1:$C$30,A10,'Оренда техники'!$F$1:$F$30) -> 150 | F10: =C10+D10-E10 -> 600 | G10: 0 | H10: =SUMIF('Оренда техники'!$C$1:$C$30,A10,'Оренда техники'!$E$1:$E$30) -> 13312 | I10: =L10*0.7 -> 39.2 | J10: 0 | L10: =SUMIF(' то за Грудень 2025'!$B$4:$B$42,A10,' то за Грудень 2025'!$D$4:$D$42) -> 56 | M10: 4.35 | N10: =F10/I10 -> 15.306122 | O10: =N10-M10 -> 10.956122 | P10: =O10/M10 -> 2.5186488 | Q10: =(I10*O10*$K$26) -> 25886.851 | R10: нет данных по моточасам на начало
A11: Экскаватор JCB 220 | B11: 45962 | C11: 247 | D11: =SUMIF($A$31:$A$95,A11,$B$31:$B$95) -> 300 | E11: =SUMIF('Оренда техники'!$C$1:$C$30,A11,'Оренда техники'!$F$1:$F$30) -> 173 | F11: =C11+D11-E11 -> 374 | G11: 8865 | H11: =SUMIF('Оренда техники'!$C$1:$C$30,A11,'Оренда техники'!$E$1:$E$30) -> 9077 | I11: =H11-G11 -> 212 | J11: 0 | L11: =SUMIF(' то за Грудень 2025'!$B$4:$B$42,A11,' то за Грудень 2025'!$D$4:$D$42) -> 60 | M11: 10.5 | N11: =F11/I11 -> 1.7641509 | O11: =N11-M11 -> -8.7358491 | R11: gps фиксирует слив - 203 л
A12: МАЗ 264 | B12: 45962 | C12: 150 | D12: =SUMIF($A$31:$A$95,A12,$B$31:$B$95) -> 440 | E12: =SUMIF('Оренда техники'!$C$1:$C$30,A12,'Оренда техники'!$F$1:$F$30) -> 140 | F12: =C12+D12-E12 -> 450 | G12: 40752 | H12: =SUMIF('Оренда техники'!$C$1:$C$30,A12,'Оренда техники'!$E$1:$E$30) -> 41707 | I12: =H12-G12 -> 955 | J12: 0 | L12: =SUMIF(' то за Грудень 2025'!$B$4:$B$42,A12,' то за Грудень 2025'!$D$4:$D$42) -> 183 | M12: 0.9 | N12: =F12/I12 -> 0.47120419 | O12: =N12-M12 -> -0.42879581
A13: МАЗ 265 | B13: 45962 | C13: 180 | D13: =SUMIF($A$31:$A$95,A13,$B$31:$B$95) -> 600 | E13: =SUMIF('Оренда техники'!$C$1:$C$30,A13,'Оренда техники'!$F$1:$F$30) -> 90 | F13: =C13+D13-E13 -> 690 | G13: 46054 | H13: =SUMIF('Оренда техники'!$C$1:$C$30,A13,'Оренда техники'!$E$1:$E$30) -> 47406 | I13: =H13-G13 -> 1352 | J13: 0 | L13: =SUMIF(' то за Грудень 2025'!$B$4:$B$42,A13,' то за Грудень 2025'!$D$4:$D$42) -> 99 | M13: 0.9 | N13: =F13/I13 -> 0.51035503 | O13: =N13-M13 -> -0.38964497
A14: Самосвал Камаз | B14: 45962 | C14: 170 | D14: =SUMIF($A$31:$A$95,A14,$B$31:$B$95) -> 700 | E14: =SUMIF('Оренда техники'!$C$1:$C$30,A14,'Оренда техники'!$F$1:$F$30) -> 146 | F14: =C14+D14-E14 -> 724 | G14: 0 | H14: =SUMIF('Оренда техники'!$C$1:$C$30,A14,'Оренда техники'!$E$1:$E$30) -> 0 | I14: =L14*2.37 -> 298.62 | J14: 0 | L14: =SUMIF(' то за Грудень 2025'!$B$4:$B$42,A14,' то за Грудень 2025'!$D$4:$D$42) -> 126 | M14: 0.9 | N14: =F14/I14 -> 2.424486 | O14: =N14-M14 -> 1.524486 | P14: =O14/M14 -> 1.6938733 | Q14: =(I14*O14*$K$26) -> 27439.652 | R14: нет данных по моточасам
A15: Самосвал МАЗ | B15: 45962 | C15: 140 | D15: =SUMIF($A$31:$A$95,A15,$B$31:$B$95) -> 750 | E15: =SUMIF('Оренда техники'!$C$1:$C$30,A15,'Оренда техники'!$F$1:$F$30) -> 120 | F15: =C15+D15-E15 -> 770 | G15: 90171 | H15: =SUMIF('Оренда техники'!$C$1:$C$30,A15,'Оренда техники'!$E$1:$E$30) -> 91004 | I15: =H15-G15 -> 833 | J15: 0 | L15: =SUMIF(' то за Грудень 2025'!$B$4:$B$42,A15,' то за Грудень 2025'!$D$4:$D$42) -> 159 | M15: 0.9 | N15: =IFERROR(F15/I15,0) -> 0.92436975 | O15: =N15-M15 -> 0.024369748 | P15: =O15/M15 -> 0.027077498 | Q15: =(I15*O15*$K$26) -> 1223.5799 | R15: gps фиксирует слив - 10 л
A16: Самосвал МАЗ №2 | B16: 45962 | C16: 150 | D16: =SUMIF($A$31:$A$95,A16,$B$31:$B$95) -> 600 | E16: =SUMIF('Оренда техники'!$C$1:$C$30,A16,'Оренда техники'!$F$1:$F$30) -> 70 | F16: =C16+D16-E16 -> 680 | G16: 89040 | H16: =SUMIF('Оренда техники'!$C$1:$C$30,A16,'Оренда техники'!$E$1:$E$30) -> 89907 | I16: =H16-G16 -> 867 | J16: 0 | L16: =SUMIF(' то за Грудень 2025'!$B$4:$B$42,A16,' то за Грудень 2025'!$D$4:$D$42) -> 168 | M16: 0.9 | N16: =F16/I16 -> 0.78431373 | O16: =N16-M16 -> -0.11568627 | R16: gps фиксирует слив - 57 л
A17: Автокран XCMG QAY55 | B17: 45962 | C17: 243 | D17: =SUMIF($A$31:$A$95,A17,$B$31:$B$95) -> 200 | E17: =SUMIF('Оренда техники'!$C$1:$C$30,A17,'Оренда техники'!$F$1:$F$30) -> 165 | F17: =C17+D17-E17 -> 278 | G17: 0 | H17: =SUMIF('Оренда техники'!$C$1:$C$30,A17,'Оренда техники'!$E$1:$E$30) -> 0 | I17: =L17*0.7 -> 21 | J17: 0 | L17: =SUMIF(' то за Грудень 2025'!$B$4:$B$42,A17,' то за Грудень 2025'!$D$4:$D$42) -> 30 | M17: 5.1 | N17: =IFERROR(F17/I17,0) -> 13.238095 | O17: =N17-M17 -> 8.1380952 | P17: =O17/M17 -> 1.5957049 | Q17: =(I17*O17*$K$26) -> 10300.975 | R17: gps фиксирует слив - 267 л ,
A18: Автокран XCMG | B18: 45962 | C18: 0 | D18: =SUMIF($A$31:$A$95,A18,$B$31:$B$95) -> 560 | E18: =SUMIF('Оренда техники'!$C$1:$C$30,A18,'Оренда техники'!$F$1:$F$30) -> 210 | F18: =C18+D18-E18 -> 350 | G18: 7367 | H18: =SUMIF('Оренда техники'!$C$1:$C$30,A18,'Оренда техники'!$E$1:$E$30) -> 7589 | I18: =H18-G18 -> 222 | J18: 0 | L18: =SUMIF(' то за Грудень 2025'!$B$4:$B$42,A18,' то за Грудень 2025'!$D$4:$D$42) -> 198 | M18: 4.07 | N18: =F18/I18 -> 1.5765766 | O18: =N18-M18 -> -2.4934234 | R18: gps фиксирует слив - 596 л
A19: Автокран Клинцы | B19: 45962 | C19: 0 | D19: =SUMIF($A$31:$A$95,A19,$B$31:$B$95) -> 166.53 | E19: =SUMIF('Оренда техники'!$C$1:$C$30,A19,'Оренда техники'!$F$1:$F$30) -> 80 | F19: =C19+D19-E19 -> 86.53 | G19: 202 | H19: =SUMIF('Оренда техники'!$C$1:$C$30,A19,'Оренда техники'!$E$1:$E$30) -> 392 | I19: =H19-G19 -> 190 | J19: 0 | L19: =SUMIF(' то за Грудень 2025'!$B$4:$B$42,A19,' то за Грудень 2025'!$D$4:$D$42) -> 48 | M19: 2.9 | N19: =F19/I19 -> 0.45542105 | O19: =N19-M19 -> -2.4445789 | R19: gps фиксирует слив - 27,21 л
A20: MAN №5 KA5697НВ | B20: 45901 | C20: 0 | E20: =SUMIF('Оренда техники'!C17:C32,A20,'Оренда техники'!F17:F32) -> 0 | G20: 202 | H20: =SUMIF('Оренда техники'!$C$1:$C$30,A20,'Оренда техники'!$E$1:$E$30) -> 0 | M20: 0.32 | N20: =F20/I20 -> #DIV/0! | O20: =N20-M20 -> #DIV/0! | P20: =O20/M20 -> #DIV/0! | Q20: =O20*I20*51.53 -> #DIV/0! | R20: данные посчитаны с обороток, GPS показывает расход на 600 больше, написан запрос на Транс Групп
A21: MAN №4 KA5697НВ | B21: 45901 | C21: 0 | E21: =SUMIF('Оренда техники'!C17:C33,A21,'Оренда техники'!F18:F33) -> 0 | G21: 0 | H21: =SUMIF('Оренда техники'!$C$1:$C$30,A21,'Оренда техники'!$E$1:$E$30) -> 0 | M21: 0.32 | N21: =F21/I21 -> #DIV/0! | O21: =N21-M21 -> #DIV/0! | P21: =O21/M21 -> #DIV/0! | Q21: =O21*I21*51.53 -> #DIV/0! | R21: данные посчитаны с обороток, GPS показывает расход на 400 больше, написан запрос на Транс Групп
A22: MAN №3 white KA7837HO | B22: 45901 | C22: 0 | E22: =SUMIF('Оренда техники'!C18:C34,A22,'Оренда техники'!F19:F34) -> 0 | G22: 0 | H22: =SUMIF('Оренда техники'!$C$1:$C$30,A22,'Оренда техники'!$E$1:$E$30) -> 0 | M22: 0.32
C23: =SUM(C3:C19) -> 1920 | D23: =SUM(D2:D19) -> 8973.52 | E23: =SUM(E2:E19) -> 1879 | G23: =SUM(G2:G19) -> 419280 | H23: =SUM(H2:H19) -> 439328 | L23: =SUM(L2:L19) -> 2612.4 | Q23: =SUM(Q3:Q19) -> 64851.059
D24: =D23-B96 -> -455 | E24: =E23-SUM('Оренда техники'!F2:F20) -> 110 | H24: =H23-SUM('Оренда техники'!E2:E20) -> 75864 | P24: 203
J26: Стоимость 1 л | K26: =SUM(C31:C95)/B96 -> 60.27487
A29: Заправки АЗС
A30: Наименование | B30: Количество | C30: Сумма | D30: АЗС
A31: Телескоп JCB 540-170 №5 | B31: 900 | C31: 53991 | D31: БВС
A32: Экскаватор JCB 2007 | B32: 800 | C32: 47992 | D32: БВС
A33: Экскаватор JCB 2013 | B33: 650 | C33: 38993.5 | D33: БВС
A34: Автокран Клинцы | B34: 166.53 | C34: 9990.13 | D34: БВС
A35: МАЗ 265 | B35: 600 | C35: 35994 | D35: БВС
A36: МАЗ 264 | B36: 440 | C36: 26395.6 | D36: БВС
A37: Телескоп JCB 535-140 (№4) | B37: 700 | C37: 41993 | D37: БВС
A38: Автокран XCMG QAY55 | B38: 200 | C38: 11998 | D38: БВС
A39: Виброкаток | B39: 100 | C39: 5999 | D39: БВС
A40: Самосвал МАЗ №2 | B40: 600 | C40: 35994 | D40: БВС
A41: Автокран XCMG | B41: 560 | C41: 33594.4 | D41: БВС
A42: Экскаватор JCB 220 | B42: 300 | C42: 17997 | D42: БВС
... A47: Экскаватор JCB 3CX 2008 | B47: 500 | C47: 29995 | D47: БВС
E53: =SUM(C31:C54) -> 561898.13
A55: Ротор Пегасус | B55: 0 | C55: 0 | D55: Укрнафта
A56: Досавка топлива
A57: Телескоп 3 (цех) | B57: 0
E58: =SUM(C55:C59) -> 0
E59: ДТ
A60: Экскаватор JCB 3CX 2008 | B60: 61.99 | C60: 6404.69 | D60: Окко
E65: =SUM(C60:C66) -> 6404.69
E66: =SUM(C67:C67) -> 0
E94: =SUM(C68:C95) -> 0
B96: =SUM(B31:B95) -> 9428.52 | C96: =SUM(C31:C95) -> 568302.82

Sheet  то за Грудень 2025
A3: Механизатор | B3: Наименование | C3: Объект | D3: Факт часов. | E3: ТО | F3: Заправка | G3: Примечание по строке
A4: Болох В. | B4: Автокран XCMG | C4: Глобино | D4: 198 | E4: 3 | F4: 4
A5: Борисенко О. | B5: Автокран клинцы | C5: Глобино | D5: 48 | E5: 0 | F5: 0
A6: Філянович Ю. | B6: Автокран XCMG QAY55 | C6: Глобино | D6: 30 | E6: 0 | F6: 0
A7: Хоменко Віталій | B7: Телескоп 1 | C7: Тищенки | D7: 27 | E7: 20 | F7: 3
A8: Рубцов С. | B8: Телескоп 1 | C8: Тищенки | D8: 62 | E8: 0 | F8: 0
A9: Окольничий В. | B9: Телескоп 1 | C9: Тищенки | D9: 16 | F9: 0
A10: Василиу Р. | B10: Телескоп 2 | C10: Глобино | D10: 196 | E10: 1 | F10: 7
A11: Грунковський В. | B11: Телескоп JCB 535-140 (№4) | C11: Глобино | D11: 41 | F11: 2
A12: Ляшко С. | B12: Телескоп JCB 535-140 (№4) | C12: Глобино | D12: 37 | E12: 4 | F12: 0
A13: Окольничий В. | B13: Телескоп JCB 535-140 (№4) | C13: Глобино | D13: 106 | E13: 0 | F13: 2
A14: Окольничий В. | B14: Телескоп JCB 540-170 №5 | C14: Глобино | D14: 23 | F14: 2
A15: Зубко О. | B15: Телескоп JCB 540-170 №5 | C15: Глобино | D15: 151 | E15: 1 | F15: 7
A16: Василиу Р. | B16: Телескоп JCB 535-140 (№4) | C16: Глобино | D16: 9 | E16: 0 | F16: 1
A17: Василиу Р. | B17: Телескоп JCB 540-170 №5 | C17: Глобино | D17: 17 | E17: 0 | F17: 0
A18: Карбунар Я. | B18: Экскаватор JCB 2007 | C18: Глобино | D18: 191 | E18: 10 | F18: 7
A19: Пахалков | B19: Экскаватор JCB 3CX 2008 | C19: Путрівка | D19: 63 | E19: 0 | F19: 4
A20: Шумко А. | B20: Экскаватор JCB 2013 | C20: Тищенки | D20: 56 | E20: 21 | F20: 4
A21: Ляшко С. | B21: Экскаватор JCB 220 | C21: Глобино | D21: 60 | E21: 42 | F21: 1
A22: Пахалков Ю. | B22: Виброкаток | C22: Тищенки | D22: 44 | E22: 0 | F22: 2
A23: Божков В. | B23: Виброкаток | C23: Тищенки | D23: 2
A24: Бубцов С | B24: Виброкаток | C24: Тищенки | D24: 24 | E24: 0 | F24: 0
A25: Сокур С. | B25: Виброкаток | C25: Глобино | D25: 12 | E25: 20 | F25: 0
A26: Черненко А. | B26: МАЗ 264 | C26: Глобино | D26: 183 | E26: 3 | F26: 6
A27: Комаров Д. | B27: МАЗ 265 | C27: Тищенки | D27: 80 | E27: 24 | F27: 8
A28: Божков В. | B28: МАЗ 265 | C28: Тищенки | D28: 19 | E28: 4 | F28: 0
A29: Хоришман А. | B29: Кран РДК №2 | C29: Глобино | D29: 104 | E29: 4 | F29: 0
A30: Гончаренко В.П. | B30: Самосвал МАЗ №2 | C30: Глобино | D30: 168 | E30: 13 | F30: 3
A31: Бутко І. | B31: Самосвал МАЗ | C31: Глобино | D31: 159 | E31: 8 | F31: 6
A32: Божков В. | B32: Самосвал Камаз | C32: Тищенки | D32: 115 | E32: 9 | F32: 14
A33: Божков В. | B33: Самосвал Камаз | C33: Глобино | D33: 11 | E33: 4 | F33: 0
A34: Омельченко С. | B34: Кран РДК №1 | C34: Путрівка | D34: 92 | E34: 36 | F34: 0
D35: =SUM(D4:D34) -> 2344 | E35: =SUM(E4:E34) -> 227 | F35: =SUM(F4:F34) -> 83

Sheet Оренда техники
A1: N | B1: Вид учета | C1: Подразделение | D1: Направление дохода | E1: Моточасы | F1: Топливо остаток | G1: Заправлено | H1: В дороге | I1: Отработано на объекте | J1: Отработано на объекте на другого подрядчика | K1: Отработано на объекте ремонт | L1: Простой | M1: Сторонний заказчик | N1: Контрагент заказчик | O1: Объект | P1: Направление расхода | Q1: Цена | R1: Сумма | S1: ФИО | T1: Примечание
A2: 1 | B2: Работа | C2: Телескоп 1 | D2: Спецтехника | E2: 14978 | F2: 40 | G2: 800 | H2: 0 | I2: 105 | J2: 0 | K2: 23 | L2: 0 | M2: Ні | O2: Главный офис | P2: Строительство | Q2: 494.88 | R2: 51962.4 | S2: Рубцов С. | U2: Телескоп 1
A3: 2 | B3: Работа | C3: Телескоп 2 | D3: Спецтехника | E3: 0 | F3: 90 | G3: 600 | H3: 0 | I3: 196 | J3: 0 | K3: 8 | L3: 0 | M3: Ні | O3: Главный офис | P3: Строительство | Q3: 494.88 | R3: 96996.48 | S3: Васіліу Р. | U3: Телескоп 2
A4: 3 | B4: Работа | C4: Телескоп JCB 535-140 (№4) | D4: Спецтехника | E4: 11678 | F4: 70 | G4: 700 | H4: 0 | I4: 193 | J4: 0 | K4: 9 | L4: 0 | M4: Ні | O4: Главный офис | P4: Строительство | Q4: 494.88 | R4: 95511.84 | S4: Зубко О. | U4: Телескоп JCB 535-140 (№4)
A5: 4 | B5: Работа | C5: Телескоп JCB 540-170 №5 | D5: Спецтехника | E5: 9672 | F5: 70 | G5: 900 | H5: 0 | I5: 191 | J5: 0 | K5: 10 | L5: 0 | M5: Ні | O5: Главный офис | P5: Строительство | Q5: 494.88 | R5: 94522.08 | S5: Окольничий В. | U5: Телескоп JCB 540-170 №5
A6: 5 | B6: Работа | C6: Экскаватор JCB 2007 | D6: Спецтехника | E6: 20316 | F6: 20 | G6: 800 | H6: 0 | I6: 191 | J6: 0 | K6: 17 | L6: 0 | M6: Ні | O6: Главный офис | P6: Строительство | Q6: 524.19 | R6: 100120.29 | S6: Карбунар Я. | U6: Экскаватор JCB
A7: 6 | B7: Работа | C7: Экскаватор JCB 3CX 2008 | D7: Спецтехника | E7: 874 | F7: 50 | G7: 0 | H7: 0 | I7: 63 | J7: 0 | K7: 4 | L7: 0 | M7: Ні | O7: Главный офис | P7: Строительство | Q7: 524.19 | R7: 33023.97 | S7: Пахалков С. | U7: Экскаватор JCB 3CX 2008
A8: 7 | B8: Работа | C8: Экскаватор JCB 2013 | D8: Спецтехника | E8: 13312 | F8: 150 | G8: 650 | H8: 0 | I8: 56 | J8: 0 | K8: 25 | L8: 0 | M8: Ні | O8: Главный офис | P8: Строительство | Q8: 524.19 | R8: 29354.64 | S8: Шумко А. | U8: Экскаватор JCB 2013
A9: 8 | B9: Работа | C9: Экскаватор JCB 220 | D9: Спецтехника | E9: 9077 | F9: 173 | G9: 300 | H9: 0 | I9: 60 | J9: 0 | K9: 43 | L9: 0 | M9: Ні | O9: Главный офис | P9: Строительство | Q9: 1023.33 | R9: 61399.8 | S9: Ляшко С. | U9: Экскаватор JCB 220
A10: 9 | B10: Работа | C10: Автокран XCMG | D10: Спецтехника | E10: 7589 | F10: 210 | G10: 560 | H10: 0 | I10: 198 | J10: 0 | K10: 7 | L10: 0 | M10: Ні | O10: Главный офис | P10: Строительство | Q10: 601.95 | R10: 119186.1 | S10: Болох В. | U10: Ротор Пегасус
A11: 10 | B11: Работа | C11: Автокран XCMG QAY55 | D11: Спецтехника | E11: 0 | F11: 165 | G11: 200 | H11: 0 | I11: 30 | J11: 0 | K11: 0 | L11: 0 | M11: Ні | O11: Главный офис | P11: Строительство | Q11: 969.93 | R11: 29097.9 | S11: Філянович Ю. | U11: Автокран XCMG
A12: 11 | B12: Работа | C12: Автокран Клинцы | D12: Спецтехника | E12: 392 | F12: 80 | G12: 167 | H12: 0 | I12: 48 | J12: 0 | K12: 0 | L12: 0 | M12: Ні | O12: Главный офис | P12: Строительство | Q12: 529.22 | R12: 25402.56 | S12: Борисенко О. | U12: Автокран Клинцы
A13: 12 | B13: Работа | C13: МАЗ 264 | D13: Спецтехника | E13: 41707 | F13: 140 | G13: 440 | H13: 0 | I13: 183 | J13: 0 | K13: 9 | L13: 0 | M13: Ні | O13: Главный офис | P13: Строительство | Q13: 386.37 | R13: 70705.71 | S13: Черненко А. | U13: МАЗ 264
A14: 13 | B14: Работа | C14: МАЗ 265 | D14: Спецтехника | E14: 47406 | F14: 90 | G14: 600 | H14: 0 | I14: 99 | J14: 0 | K14: 36 | L14: 0 | M14: Ні | O14: Главный офис | P14: Строительство | Q14: 386.37 | R14: 38250.63 | S14: Комаров Д. | U14: МАЗ 265
A15: 14 | B15: Работа | C15: Самосвал Камаз | D15: Спецтехника | E15: 0 | F15: 146 | G15: 700 | H15: 0 | I15: 123 | J15: 0 | K15: 27 | L15: 0 | M15: Ні | O15: Главный офис | P15: Строительство | Q15: 461.84 | R15: 56806.32 | S15: Божков В.
A16: 15 | B16: Работа | C16: Самосвал МАЗ | D16: Строительство | E16: 91004 | F16: 120 | G16: 750 | H16: 0 | I16: 159 | J16: 0 | K16: 14 | L16: 0 | M16: Ні | O16: Главный офис | P16: Строительство | Q16: 514.61 | R16: 81822.99 | S16: Бутко І. | U16: Самосвал МАЗ
A17: 16 | B17: Работа | C17: Самосвал МАЗ №2 | D17: Спецтехника | E17: 89907 | F17: 70 | G17: 600 | H17: 0 | I17: 168 | J17: 0 | K17: 16 | L17: 0 | M17: Ні | O17: Главный офис | P17: Строительство | Q17: 514.61 | R17: 86454.48 | S17: Гончаренко В. | U17: Самосвал МАЗ №2
A18: 17 | B18: Работа | C18: Виброкаток | D18: Спецтехника | E18: 5552 | F18: 85 | G18: 100 | H18: 0 | I18: 82 | J18: 0 | K18: 22 | L18: 0 | M18: Ні | O18: Главный офис | P18: Строительство | Q18: 606.82 | R18: 49759.24 | S18: Рубцов С. | U18: Виброкаток
A19: 18 | B19: Работа | C19: РДК 250 | D19: Спецтехника | E19: 0 | F19: 0 | G19: 0 | H19: 0 | I19: 92 | J19: 0 | K19: 36 | L19: 0 | M19: Ні | O19: Главный офис | P19: Строительство | Q19: 308.41 | R19: 28373.72
C20: РДК 250-3№2 | D20: Спецтехника | E20: 0 | F20: 0 | G20: 0 | H20: 0 | I20: 104 | J20: 0 | K20: 4 | L20: 0 | M20: Ні | O20: Главный офис | P20: Строительство | Q20: 308.41 | R20: 32074.64 | S20: Хоришман А.

Sheet МЕХАНИЗАТОРЫ
A1: № п/п | B1: ФИО | C1: Ед. спецтехник | D1: Місце дислокації | H1: I и II недели | L1: ІІІ- IV недели | P1: Итого за Июнь: | T1: Оплата за відпрацьовані години | U1: Оплата ТО і АЗС | V1: Разом | W1: Разом | X1: Рахунок у Казні
H3: План по Бюджету колво часов | I3: Факт по Бюджету колво часов | J3: ТО | K3: Заправка | L3: План по Бюджету колво часов | M3: Факт по Бюджету колво часов | N3: ТО | O3: Заправка | P3: План по Бюджету колво часов | Q3: Факт по Бюджету колво часов | R3: ТО | S3: Заправка
A4: 1 | B4: Болох В. | C4: Автокран XCMG | D4: Глобино | H4: 192 | I4: 98 | J4: 1 | K4: 2 | M4: 106 | N4: 0 | O4: 1 | Q4: 186 | R4: 0 | S4: 2 | T4: 55080 | U4: 400 | V4: 55480 | W4: =U4+V4 -> 55880 | X4: 5111
A5: 2 | B5: Борисенко О. | C5: Автокран XCMG | D5: Глобино | H5: 192 | I5: 104 | K5: 1 | M5: 93 | N5: 3 | O5: 0 | Q5: 16 | R5: 0 | S5: 0 | T5: 53190 | U5: 400 | V5: 53590 | W5: =U5+V5 -> 53990 | X5: 5110
A6: 3 | B6: Борисенко О. | C6: Автокран клинцы | D6: Глобино | H6: 160 | I6: 22 | J6: 0 | K6: 0 | M6: 28 | Q6: 190 | R6: 8 | S6: 0 | T6: 50000 | U6: 0 | V6: 50000 | W6: =U6+V6 -> 50000 | X6: 5112
A7: 4 | B7: Зубко О. | C7: Автокран клинцы | D7: Глобино | H7: 192 | I7: 56 | J7: 5 | M7: 102 | N7: 5 | Q7: 15 | R7: 0 | S7: 0 | T7: 31600 | U7: 1000 | V7: 32600 | W7: 50000 | X7: 5113
A8: 5 | B8: Філянович Ю. | C8: Автокран XCMG QAY55 | D8: Глобино | H8: 192 | I8: 103 | J8: 0 | K8: 2 | M8: 116 | N8: 6 | O8: 3 | Q8: 0 | R8: 0 | S8: 0 | T8: 50370 | U8: 1100 | V8: 51470 | W8: =U8+V8 -> 52570 | X8: 5114
A9: 6 | B9: Котик М. | C9: РДК 250-3№2 | D9: Глобино | H9: 192 | M9: 96 | N9: 3 | O9: 4 | Q9: 138 | R9: 37 | S9: 0 | T9: 22080 | U9: 700 | V9: 22780 | W9: =U9+V9 -> 23480 | X9: 5115
A10: 7 | B10: Сокур С. | C10: Телескоп 1 | D10: Тищенки | H10: 192 | I10: 92 | J10: 1 | K10: 3 | Q10: 47 | R10: 0 | S10: 0 | T10: 21160 | U10: 400 | V10: 21560 | W10: =U10+V10 -> 21960 | X10: 5116
A11: 8 | B11: Ошманін Я. | C11: Телескоп 1 | D11: Тищенки | H11: 192 | I11: 97 | J11: 2 | K11: 4 | M11: 110 | N11: 6 | O11: 4 | Q11: 64 | R11: 4 | S11: 2 | T11: 47610 | U11: 1600 | V11: 49210 | W11: =U11+V11 -> 50810 | X11: 5117
A12: 9 | B12: Скоц. С. | C12: Телескоп 1 | D12: Тищенки | H12: 192 | I12: 80 | J12: 0 | K12: 2 | M12: 75 | N12: 13 | O12: 3 | Q12: 18 | R12: 0 | S12: 1 | T12: 35650 | U12: 1800 | V12: 37450 | W12: =U12+V12 -> 39250 | X12: 5118
A13: 10 | B13: Василиу Р. | C13: Телескоп 2 | D13: Глобино | H13: 192 | I13: 6 | Q13: 205 | R13: 13 | S13: 5 | T13: 1380 | U13: 0 | V13: 1380 | W13: =U13+V13 -> 1380 | X13: 5119
A14: 11 | B14: Грунковський В | C14: Телескоп JCB 535-140 №4 | D14: Глобино | H14: 80 | I14: 85 | J14: 5 | K14: 2 | M14: 68 | N14: 1 | O14: 2 | Q14: 162 | R14: 1 | S14: 6 | T14: 35190 | U14: 1000 | V14: 36190 | W14: =U14+V14 -> 37190 | X14: 5120
A15: 12 | B15: Зубко О. | C15: Телескоп JCB 540-170 (№4) | D15: Глобино | H15: 40 | I15: 6 | Q15: 9 | R15: 0 | S15: 0 | T15: 1320 | U15: 0 | V15: 1320 | W15: =U15+V15 -> 1320 | X15: 5121
A16: 13 | B16: Зубко О. | C16: Телескоп JCB 540-170 (№5) | D16: Глобино | I16: 17 | J16: 1 | M16: 45 | N16: 0 | Q16: 183 | R16: 10 | S16: 4 | T16: 13640 | U16: 100 | V16: 13740 | W16: =U16+V16 -> 13840 | X16: 5122
A17: 14 | B17: Карбунар Я. | C17: Экскаватор JCB 2007 | D17: Глобино | H17: 192 | I17: 76 | J17: 7 | K17: 4 | M17: 28 | N17: 0 | O17: 1 | Q17: 197 | R17: 24 | S17: 8 | T17: 20800 | U17: 1200 | V17: 22000 | W17: =U17+V17 -> 23200 | X17: 5124
A18: 15 | B18: Воскресенський С. | C18: Экскаватор JCB 3CX 2008 | D18: Подгорцы | H18: 80 | M18: 106 | N18: 0 | O18: 2 | Q18: 126 | R18: 0 | S18: 5 | T18: 21200 | U18: 200 | V18: 21400 | W18: =U18+V18 -> 21600 | X18: 5125
A19: 16 | B19: Ляшко С. | C19: Экскаватор JCB 2013 | D19: Тищенки | I19: 49 | J19: 2 | K19: 1 | Q19: 19 | R19: 0 | S19: 0 | T19: 9800 | U19: 300 | V19: 10100 | W19: =U19+V19 -> 10400 | X19: 5126
A20: 17 | B20: Скоц. С. | C20: Экскаватор JCB 2013 | D20: Тищенки | H20: 80 | I20: 71 | J20: 0 | M20: 104 | Q20: 107 | R20: 5 | S20: 4 | T20: 35000 | U20: 0 | V20: 35000 | W20: =U20+V20 -> 35000 | X20: 5127
A21: 18 | B21: Ляшко С. | C21: Экскаватор JCB 220 | D21: Тищенки | I21: 17 | M21: 25 | O21: 1 | Q21: 197 | R21: 7 | S21: 6 | T21: 8400 | U21: 100 | V21: 8500 | W21: =U21+V21 -> 8600 | X21: 5128
A22: 19 | B22: Сокур С. | C22: Виброкаток | D22: Глобино | H22: 80 | I22: 92 | M22: 98 | Q22: 5 | R22: 0 | S22: 0 | T22: 38000 | U22: 0 | V22: 38000 | W22: =U22+V22 -> 38000 | X22: 5129
A23: 20 | B23: Гончаренко О. | C23: Виброкаток | D23: Глобино | I23: 17 | M23: 24 | Q23: 0 | R23: 0 | S23: 0 | T23: 8200 | U23: 0 | V23: 8200 | W23: =U23+V23 -> 8200 | X23: 5130 | Y23: кар'єр Кременчук
A24: 21 | B24: Черненко А. | C24: МАЗ 264 | D24: Глобино | H24: 160 | Q24: 172 | R24: 2 | S24: 3 | U24: 0 | V24: 0 | W24: =U24+V24 -> 0 | X24: 5131 | Y24: кар'єр Кременчук
A25: 22 | B25: Окольничий В. | C25: МАЗ 264 | D25: Глобино | H25: 192 | I25: 130 | K25: 2 | M25: 75 | O25: 1 | Q25: 16 | R25: 1 | S25: 0 | T25: 47150 | U25: 300 | V25: 47450 | W25: =U25+V25 -> 47750 | X25: 5132 | Y25: кар'єр Кременчук
A26: 23 | B26: Черненко А. | C26: МАЗ 265 | D26: Глобино | Q26: 33 | R26: 0 | S26: 0
A27: 24 | B27: Комаров Д. | C27: МАЗ 265 | D27: Тищенки | Q27: 165 | R27: 23 | S27: 4 | T27: 0 | U27: 0 | V27: 0 | X27: 5133 | Y27: 13.14.15.05- стажування 5400 для ЗП з фонду спецтехніка. Об'єкт ці дні не оплачує
A28: 25 | B28: Окольничий В. | C28: Самосвал МАЗ | D28: Глобино | Q28: 90 | R28: 0 | S28: 0 | T28: 0 | U28: 0 | V28: 0 | W28: =U28+V28 -> 0 | X28: 5134 | Y28: Оплата на загальних підставах
A29: 26 | B29: Сокур С. | C29: Самосвал МАЗ | D29: Тищенки | H29: 2792 | I29: 1218 | J29: 24 | K29: 23 | L29: 0 | M29: 1299 | N29: 37 | O29: 22 | P29: 0 | Q29: 15 | R29: 0 | S29: 0 | T29: 606820 | U29: 10600 | V29: 617420 | W29: =U29+V29 -> 628020
A30: 27 | B30: Сокур С. | C30: Самосвал МАЗ №2 | D30: Тищенки | Q30: 0 | R30: 0 | S30: 0 | U30: =E30*Q30 -> 0 | V30: =(R30+S30)*G30 -> 0 | W30: =U30+V30 -> 0
A31: 28 | B31: Сокур С. | C31: Самосвал МАЗ №2 | D31: Тищенки | Q31: 0 | R31: 0 | S31: 0 | U31: =E31*Q31 -> 0 | V31: =(R31+S31)*G31 -> 0 | W31: =U31+V31 -> 0
A32: 29 | B32: Сокур С. | C32: Самосвал МАЗ №2 | D32: Тищенки | H32: =SUM(H4:H31) -> 5584 | I32: =SUM(I4:I31) -> 2436 | J32: =SUM(J4:J31) -> 48 | K32: =SUM(K4:K31) -> 46 | L32: =SUM(L4:L31) -> 0 | M32: =SUM(M4:M31) -> 2598 | N32: =SUM(N4:N31) -> 74 | O32: =SUM(O4:O31) -> 44 | P32: =SUM(P4:P31) -> 0 | Q32: 62 | R32: 0 | S32: 2 | U32: =SUM(U3:U31) -> 21200 | V32: =SUM(V3:V31) -> 1234840 | W32: =SUM(W3:W31) -> 1272440
A33: 30 | C33: Haulotte | D33: Глобино | Q33: 0 | R33: 0 | S33: 0
A34: 31 | B34: Ошманін Я. | C34: Пегас Ротор | D34: Тищенки | Q34: 56 | R34: 0 | S34: 3
A35: 32 | B35: Ошманін Я. | C35: Пегас Ротор | D35: МХП Єрки | Q35: 11 | R35: 0 | S35: 0
