Workbook

Sheet Взаиморасчеты
A1: Отработанно за ноябрь 2022 | B1: =Ноябрь!H24 -> 0
A2: Оплаты с р/с Индастриалбуда
A3: Статья ДДС | B3: Сумма | C3: Комментарий
A4: топливо | B4: 30823.45 | C4: переходящий остаток
A5: топливо | B5: 29176.55 | C5: переходящий остаток
A6: топливо | B6: 293020 | C6: оплаты за месяц
A7: Разрешительная документация | B7: 960 | C7: Навчання Борисенко
A8: Страхование | B8: 3744 | C8: Телескоп 4, JCB 3CX 2008
A9: ЗП с налогами | B9: 130516.49 | C9: Выплаченная ЗП, удержания из ЗП и налоги на ЗП
B10: =SUM(B4:B9) -> 488240.49
A11: Полученная предоплата | B11: 599456 | C11: 60% предоплаты от бюджета на ноябрь
A12: К выплате с Индастриалбуда | B12: =B1-B10-B11 -> -1087696.5 | C12: Итог по ноябрю по взаиморасчетам
A14: Предоплата на декабрь | B14: 649978.86 | C14: 60% предоплаты от бюджета на декабрь
A16: К выплате с Индастриалбуда | B16: =B12+B14 -> -437717.63

Sheet Ноябрь
A1: Техника | B1: Объект | C1: Стоимость за 1 час, грн | D1: План | F1: предоплата 60% | G1: Факт | I1: Распределение предоплаты по факту отработанного на объектах | J1: Сумма к взаиморасчетам, грн | K1: Оплаты с Индастриалбуд | P1: Поступление на Индастриал от сторонних заказчиков, грн | Q1: Сумма к взаиморасчетам с учетом движения ДС на р/с Индастриалбуд, грн | S1: Распределение предоплаты по факту отработанного на объектах
D2: кол-во часов | E2: сумма, грн | G2: Кол-во Часов | H2: Сума | K2: ЗП механизаторов с налогами, грн. | L2: Разрешительная документация, грн. | M2: Страховка, грн | N2: Топливо, грн | O2: вместе оплаченно, грн
A3: Телескоп 1 | B3: Староконстантинов | C3: =467.63 -> 467.63 | D3: =18*8 -> 144 | E3: =C3*D3 -> 67338.72 | F3: =E3*0.6 -> 40403.232 | G3: 155 | H3: =C3*G3 -> 72482.65 | I3: =ROUND($F$9/$H$9*H3,2) -> 152671.27 | J3: =H3-I3 -> -80188.62 | K3: -8187.98 | N3: -44609.48 | O3: =SUM(K3:N3) -> -52797.46 | Q3: =J3+O3+P3 -> -132986.08 | S3: =ROUND($F$9/$H$9*R3,2) -> 0
A4: Экскаватор JCB 220 | B4: Староконстантинов | C4: 995.97 | D4: =15*8 -> 120 | E4: =C4*D4 -> 119516.4 | F4: =E4*0.6 -> 71709.84 | G4: 22 | H4: =C4*G4 -> 21911.34 | I4: =ROUND($F$9/$H$9*H4,2) -> 46152.18 | J4: =H4-I4 -> -24240.84 | K4: -12053.6 | N4: -70565.54 | O4: =SUM(K4:N4) -> -82619.14 | P4: =12000+12000+12000+12000+9000+12000 -> 69000 | Q4: =J4+O4+P4 -> -37859.98 | S4: =ROUND($F$9/$H$9*R4,2) -> 0
A5: Виброкаток | B5: Староконстантинов | C5: 544.05 | D5: =5*8 -> 40 | E5: =C5*D5 -> 21762 | F5: =E5*0.6 -> 13057.2 | H5: =C5*G5 -> 0 | I5: =ROUND($F$9/$H$9*H5,2) -> 0 | J5: =H5-I5 -> 0 | K5: -860.11 | O5: =SUM(K5:N5) -> -860.11 | P5: 8800 | Q5: =J5+O5+P5 -> 7939.89 | S5: =ROUND($F$9/$H$9*R5,2) -> 0
A6: МАЗ 264 | B6: Староконстантинов | C6: 355.37 | D6: =15*8 -> 120 | E6: =C6*D6 -> 42644.4 | F6: =E6*0.6 -> 25586.64 | H6: =C6*G6 -> 0 | I6: =ROUND($F$9/$H$9*H6,2) -> 0 | J6: =H6-I6 -> 0 | K6: -6224 | N6: -969 | O6: =SUM(K6:N6) -> -7193 | Q6: =J6+O6+P6 -> -7193 | S6: =ROUND($F$9/$H$9*R6,2) -> 0
A7: РДК 250 | B7: Староконстантинов | C7: 304.15 | D7: =21*8 -> 168 | E7: =C7*D7 -> 51097.2 | F7: =E7*0.6 -> 30658.32 | H7: =C7*G7 -> 0 | I7: =ROUND($F$9/$H$9*H7,2) -> 0 | J7: =H7-I7 -> 0 | O7: =SUM(K7:N7) -> 0 | Q7: =J7+O7+P7 -> 0 | S7: =ROUND($F$9/$H$9*R7,2) -> 0
A8: КАМАЗ | B8: Староконстантинов | C8: 430.84 | D8: =15*8 -> 120 | E8: =C8*D8 -> 51700.8 | F8: =E8*0.6 -> 31020.48 | G8: 15 | H8: =C8*G8 -> 6462.6 | I8: =ROUND($F$9/$H$9*H8,2) -> 13612.27 | J8: =H8-I8 -> -7149.67 | K8: -6224 | O8: =SUM(K8:N8) -> -6224 | Q8: =J8+O8+P8 -> -13373.67 | S8: =ROUND($F$9/$H$9*R8,2) -> 0
A9: Вместе по объекту Староконстантинов | E9: =SUM(E3:E8) -> 354059.52 | F9: =SUM(F3:F8) -> 212435.71 | H9: =SUM(H3:H8) -> 100856.59 | I9: =SUM(I3:I8) -> 212435.72 | J9: =SUM(J3:J8) -> -111579.13 | O9: =SUM(O3:O8) -> -149693.71 | P9: =SUM(P3:P8) -> 77800 | Q9: =SUM(Q3:Q8) -> -183472.84 | S9: =Q9 -> -183472.84
A10: Телескоп 2 | B10: Приднепровский МЕТАЛЛ | C10: 467.63 | D10: =15*8 -> 120 | E10: =C10*D10 -> 56115.6 | F10: =E10*0.6 -> 33669.36 | G10: 149 | H10: =C10*G10 -> 69676.87 | I10: =ROUND($F$12/$H$12*H10,2) -> 41203.42 | J10: =H10-F10 -> 36007.51 | K10: -7578 | N10: -13042.04 | O10: =SUM(K10:N10) -> -20620.04 | Q10: =J10+O10+P10 -> 15387.47 | S10: =ROUND($R$12/$H$12*H10,2) -> 10604.39
A11: Экскаватор JCB 2013 | B11: Приднепровский МЕТАЛЛ | C11: 496.93 | D11: =14*8 -> 112 | E11: =C11*D11 -> 55656.16 | F11: =E11*0.6 -> 33393.696 | G11: 88 | H11: =C11*G11 -> 43729.84 | I11: =ROUND($F$12/$H$12*H11,2) -> 25859.64 | J11: =H11-F11 -> 10336.144 | K11: -4475.6 | N11: -5888.21 | O11: =SUM(K11:N11) -> -10363.81 | P11: 1900 | Q11: =J11+O11+P11 -> 1872.334 | S11: =ROUND($R$12/$H$12*H11,2) -> 6655.41
A12: Вместе по объекту Приднепровский МЕТАЛЛ | E12: =E10 -> 56115.6 | F12: =SUM(F10:F11) -> 67063.056 | H12: =SUM(H10:H11) -> 113406.71 | I12: =SUM(I10:I11) -> 67063.06 | J12: =SUM(J10:J11) -> 46343.654 | O12: =SUM(O10:O11) -> -30983.85 | P12: =SUM(P10:P11) -> 1900 | Q12: =SUM(Q10:Q11) -> 17259.804 | R12: =J12+O12+P12 -> 17259.804 | S12: =SUM(S10:S11) -> 17259.8
A13: Телескоп 5 | B13: Ретал | C13: 467.63 | D13: =22*8 -> 176 | E13: =C13*D13 -> 82302.88 | F13: =E13*0.6 -> 49381.728 | G13: 280 | H13: =C13*G13 -> 130936.4 | I13: =ROUND($F$17/$H$17*H13,2) -> 62309.95 | J13: =H13-F13 -> 81554.672 | K13: -12053.6 | N13: -33558.39 | O13: =SUM(K13:N13) -> -45611.99 | Q13: =J13+O13+P13 -> 35942.682 | S13: =ROUND($Q$17/$H$17*H13,2) -> 29699.9
A14: Экскаватор JCB 2008 | B14: Ретал | C14: 496.93 | D14: =22*8 -> 176 | E14: =C14*D14 -> 87459.68 | F14: =E14*0.6 -> 52475.808 | G14: 153 | H14: =C14*G14 -> 76030.29 | I14: =ROUND($F$17/$H$17*H14,2) -> 36181.25 | J14: =H14-F14 -> 23554.482 | K14: -11480.73 | M14: -1872 | N14: -10562.68 | O14: =SUM(K14:N14) -> -23915.41 | Q14: =J14+O14+P14 -> -360.928 | S14: =ROUND($Q$17/$H$17*H14,2) -> 17245.72
A15: Haulotte | B15: Ретал | C15: 802.86 | D15: 22 | E15: =C15*D15 -> 17662.92 | F15: =E15*0.6 -> 10597.752 | G15: 26 | H15: =C15*G15 -> 20874.36 | I15: =ROUND($F$17/$H$17*H15,2) -> 9933.68 | J15: =H15-F15 -> 10276.608 | O15: =SUM(K15:N15) -> 0 | Q15: =J15+O15+P15 -> 10276.608 | S15: =ROUND($Q$17/$H$17*H15,2) -> 4734.87
A16: Клинцы | B16: Ретал | C16: 490.46 | D16: =20*8 -> 160 | E16: =C16*D16 -> 78473.6 | F16: =E16*0.6 -> 47084.16 | G16: 219 | H16: =C16*G16 -> 107410.74 | I16: =ROUND($F$17/$H$17*H16,2) -> 51114.57 | J16: =H16-F16 -> 60326.58 | K16: -12448 | L16: -960 | N16: -16732.81 | O16: =SUM(K16:N16) -> -30140.81 | Q16: =J16+O16+P16 -> 30185.77 | S16: =ROUND($Q$17/$H$17*H16,2) -> 24363.65
A17: Вместе по объекту Ретал | E17: =SUM(E13:E16) -> 265899.08 | F17: =SUM(F13:F16) -> 159539.45 | H17: =SUM(H13:H16) -> 335251.79 | I17: =SUM(I13:I16) -> 159539.45 | J17: =SUM(J13:J16) -> 175712.34 | O17: =SUM(O13:O16) -> -99668.21 | P17: =SUM(P13:P16) -> 0 | Q17: =SUM(Q13:Q16) -> 76044.132 | R17: =J17+O17+P17 -> 76044.132 | S17: =SUM(S13:S16) -> 76044.14
A18: Ротор Пегасус | B18: Биогаз | C18: 592.98 | D18: =24*8 -> 192 | E18: =C18*D18 -> 113852.16 | F18: =E18*0.6 -> 68311.296 | G18: 138 | H18: =C18*G18 -> 81831.24 | I18: =ROUND($F$22/$H$22*H18,2) -> 44997.06 | J18: =H18-F18 -> 13519.944 | K18: -7902.27 | N18: -27620 | O18: =SUM(K18:N18) -> -35522.27 | Q18: =J18+O18+P18 -> -22002.326 | S18: =ROUND($Q$22/$H$22*H18,2) -> 7849.63
A19: Виброкаток | B19: Биогаз | C19: 544.05 | D19: =10*8 -> 80 | E19: =C19*D19 -> 43524 | F19: =E19*0.6 -> 26114.4 | H19: =C19*G19 -> 0 | I19: =ROUND($F$22/$H$22*H19,2) -> 0 | J19: =H19-F19 -> -26114.4 | O19: =SUM(K19:N19) -> 0 | Q19: =J19+O19+P19 -> -26114.4 | S19: =ROUND($Q$22/$H$22*H19,2) -> 0
A20: Экскаватор JCB | B20: Биогаз | C20: 496.93 | D20: =22*8 -> 176 | E20: =C20*D20 -> 87459.68 | F20: =E20*0.6 -> 52475.808 | G20: 283 | H20: =C20*G20 -> 140631.19 | I20: =ROUND($F$22/$H$22*H20,2) -> 77329.76 | J20: =H20-F20 -> 88155.382 | K20: -12053.6 | N20: -30563.86 | O20: =SUM(K20:N20) -> -42617.46 | Q20: =J20+O20+P20 -> 45537.922 | S20: =ROUND($Q$22/$H$22*H20,2) -> 13489.99
A21: Автокран XCMG | B21: Биогаз | C21: 563.19 | D21: =5*8 -> 40 | E21: =C21*D21 -> 22527.6 | F21: =E21*0.6 -> 13516.56 | G21: 123 | H21: =C21*G21 -> 69272.37 | I21: =ROUND($F$22/$H$22*H21,2) -> 38091.24 | J21: =H21-F21 -> 55755.81 | K21: -11590 | N21: -13602.47 | O21: =SUM(K21:N21) -> -25192.47 | Q21: =J21+O21+P21 -> 30563.34 | S21: =ROUND($Q$22/$H$22*H21,2) -> 6644.92
A22: Вресте по объекту Биогаз | E22: =SUM(E18:E21) -> 267363.44 | F22: =SUM(F18:F21) -> 160418.06 | H22: =H18+H20+H21 -> 291734.8 | I22: =SUM(I18:I21) -> 160418.06 | J22: =SUM(J18:J21) -> 131316.74 | O22: =O18+O20+O21 -> -103332.2 | P22: =P18+P20+P21 -> 0 | Q22: =SUM(Q18:Q21) -> 27984.536 | R22: =J22+O22+P22 -> 27984.536 | S22: =SUM(S18:S21) -> 27984.54
A23: Телекоп №4 | B23: ЦО Спецтехника | I23: =ROUND($F$26/$H$26*H23,2) -> 0 | M23: -1872 | O23: =SUM(K23:N23) -> -1872 | Q23: =J23+O23+P23 -> -1872 | S23: =Q23 -> -1872
A24: Главный офис | B24: ЦО Спецтехника | I24: =ROUND($F$26/$H$26*H24,2) -> 0 | N24: -87035.89 | O24: =SUM(K24:N24) -> -87035.89 | Q24: =J24+O24+P24 -> -87035.89 | S24: =Q24 -> -87035.89
E26: =E22+E17+E12+E9 -> 943437.64 | F26: =ROUND(F9+F12+F17+F22,0) -> 599456 | H26: =H9+H12+H17+H22 -> 841249.89 | I26: =I9+I12+I17+I22 -> 599456.29 | J26: =J9+J12+J17+J22 -> 241793.6 | O26: =O9+O12+O17+O22+O23+O24 -> -472585.86 | P26: =P9+P12+P17+P22 -> 79700 | Q26: =Q9+Q12+Q17+Q22+Q23+Q24 -> -151092.26 | S26: =S9+S12+S17+S22+S23+S24 -> -151092.25
J27: =H26-I26 -> 241793.6 | Q27: =H26-I26+O26+P26 -> -151092.26

Sheet Староконстантинов
A1: Техника | B1: Объект | C1: Стоимость за 1 час, грн | D1: План | F1: предоплата 60% | G1: Факт | I1: Сумма к взаиморасчетам, грн | J1: Оплаты с Индастриалбуд | O1: Поступление на Индастриал от сторонних заказчиков, грн | P1: Сумма к взаиморасчетам с учетом движения ДС на р/с Индастриалбуд, грн
D2: кол-во часов | E2: сумма, грн | G2: Кол-во Часов | H2: Сума | J2: ЗП механизаторов с налогами, грн. | K2: Разрешительная документация, грн. | L2: Страховка, грн | M2: Топливо, грн | N2: вместе оплаченно, грн
A3: Телескоп 1 | B3: Староконстантинов | C3: =467.63 -> 467.63 | D3: =18*8 -> 144 | E3: =C3*D3 -> 67338.72 | F3: =E3*0.6 -> 40403.232 | G3: 155 | H3: =C3*G3 -> 72482.65 | I3: =H3-F3 -> 32079.418 | J3: 8187.98 | M3: 44609.48 | N3: =SUM(J3:M3) -> 52797.46 | P3: =I3-N3+O3 -> -20718.042
A4: Экскаватор JCB 220 | B4: Староконстантинов | C4: 995.97 | D4: =15*8 -> 120 | E4: =C4*D4 -> 119516.4 | F4: =E4*0.6 -> 71709.84 | G4: 22 | H4: =C4*G4 -> 21911.34 | I4: =H4-F4 -> -49798.5 | J4: 12053.6 | M4: 70565.54 | N4: =SUM(J4:M4) -> 82619.14 | O4: =12000+12000+12000+12000+9000+12000 -> 69000 | P4: =I4-N4+O4 -> -63417.64
A5: Виброкаток | B5: Староконстантинов | C5: 544.05 | D5: =5*8 -> 40 | E5: =C5*D5 -> 21762 | F5: =E5*0.6 -> 13057.2 | H5: =C5*G5 -> 0 | I5: =H5-F5 -> -13057.2 | J5: 860.11 | N5: =SUM(J5:M5) -> 860.11 | O5: 8800 | P5: =I5-N5+O5 -> -5117.31
A6: МАЗ 264 | B6: Староконстантинов | C6: 355.37 | D6: =15*8 -> 120 | E6: =C6*D6 -> 42644.4 | F6: =E6*0.6 -> 25586.64 | H6: =C6*G6 -> 0 | I6: =H6-F6 -> -25586.64 | J6: 6224 | M6: 969 | N6: =SUM(J6:M6) -> 7193 | P6: =I6-N6+O6 -> -32779.64
A7: РДК 250 | B7: Староконстантинов | C7: 304.15 | D7: =21*8 -> 168 | E7: =C7*D7 -> 51097.2 | F7: =E7*0.6 -> 30658.32 | H7: =C7*G7 -> 0 | I7: =H7-F7 -> -30658.32 | N7: =SUM(J7:M7) -> 0 | P7: =I7-N7+O7 -> -30658.32
A8: КАМАЗ | B8: Староконстантинов | C8: 430.84 | D8: =15*8 -> 120 | E8: =C8*D8 -> 51700.8 | F8: =E8*0.6 -> 31020.48 | G8: 15 | H8: =C8*G8 -> 6462.6 | I8: =H8-F8 -> -24557.88 | J8: 6224 | N8: =SUM(J8:M8) -> 6224 | P8: =I8-N8+O8 -> -30781.88
A9: Вместе по объекту Староконстантинов | E9: =SUM(E3:E8) -> 354059.52 | F9: =SUM(F3:F8) -> 212435.71 | H9: =SUM(H3:H8) -> 100856.59 | I9: =SUM(I3:I8) -> -111579.12 | N9: =SUM(N3:N8) -> 149693.71 | O9: =SUM(O3:O8) -> 77800 | P9: =SUM(P3:P8) -> -183472.83

Sheet Приднепровский МЕТАЛЛ
A1: Техника | B1: Объект | C1: Стоимость за 1 час, грн | D1: План | F1: предоплата 60% | G1: Факт | I1: Сумма к взаиморасчетам, грн | J1: Оплаты с Индастриалбуд | O1: Поступление на Индастриал от сторонних заказчиков, грн | P1: Сумма к взаиморасчетам с учетом движения ДС на р/с Индастриалбуд, грн
D2: кол-во часов | E2: сумма, грн | G2: Кол-во Часов | H2: Сума | J2: ЗП механизаторов с налогами, грн. | K2: Разрешительная документация, грн. | L2: Страховка, грн | M2: Топливо, грн | N2: вместе оплаченно, грн
A3: Телескоп 2 | B3: Приднепровский МЕТАЛЛ | C3: 467.63 | D3: =15*8 -> 120 | E3: =C3*D3 -> 56115.6 | F3: =E3*0.6 -> 33669.36 | G3: 149 | H3: =C3*G3 -> 69676.87 | I3: =H3-F3 -> 36007.51 | J3: 7578 | M3: 13042.04 | N3: =SUM(J3:M3) -> 20620.04 | P3: =I3-N3+O3 -> 15387.47
A4: Экскаватор JCB 2013 | B4: Приднепровский МЕТАЛЛ | C4: 496.93 | D4: =14*8 -> 112 | E4: =C4*D4 -> 55656.16 | F4: =E4*0.6 -> 33393.696 | G4: 88 | H4: =C4*G4 -> 43729.84 | I4: =H4-F4 -> 10336.144 | J4: 4475.6 | M4: 5888.21 | N4: =SUM(J4:M4) -> 10363.81 | O4: 1900 | P4: =I4-N4+O4 -> 1872.334
A5: Вместе по объекту Приднепровский МЕТАЛЛ | E5: =E3 -> 56115.6 | F5: =SUM(F3:F4) -> 67063.056 | H5: =SUM(H3:H4) -> 113406.71 | I5: =SUM(I3:I4) -> 46343.654 | N5: =SUM(N3:N4) -> 30983.85 | O5: =SUM(O3:O4) -> 1900 | P5: =SUM(P3:P4) -> 17259.804

Sheet Ретал
A1: Техника | B1: Объект | C1: Стоимость за 1 час, грн | D1: План | F1: предоплата 60% | G1: Факт | I1: Сумма к взаиморасчетам, грн | J1: Оплаты с Индастриалбуд | O1: Поступление на Индастриал от сторонних заказчиков, грн | P1: Сумма к взаиморасчетам с учетом движения ДС на р/с Индастриалбуд, грн
D2: кол-во часов | E2: сумма, грн | G2: Кол-во Часов | H2: Сума | J2: ЗП механизаторов с налогами, грн. | K2: Разрешительная документация, грн. | L2: Страховка, грн | M2: Топливо, грн | N2: вместе оплаченно, грн
A3: Телескоп 5 | B3: Ретал | C3: 467.63 | D3: =22*8 -> 176 | E3: =C3*D3 -> 82302.88 | F3: =E3*0.6 -> 49381.728 | G3: 280 | H3: =C3*G3 -> 130936.4 | I3: =H3-F3 -> 81554.672 | J3: 12053.6 | M3: 33558.39 | N3: =SUM(J3:M3) -> 45611.99 | P3: =I3-N3+O3 -> 35942.682
A4: Экскаватор JCB 2008 | B4: Ретал | C4: 496.93 | D4: =22*8 -> 176 | E4: =C4*D4 -> 87459.68 | F4: =E4*0.6 -> 52475.808 | G4: 153 | H4: =C4*G4 -> 76030.29 | I4: =H4-F4 -> 23554.482 | J4: 11480.73 | L4: 1872 | M4: 10562.68 | N4: =SUM(J4:M4) -> 23915.41 | P4: =I4-N4+O4 -> -360.928
A5: Haulotte | B5: Ретал | C5: 802.86 | D5: 22 | E5: =C5*D5 -> 17662.92 | F5: =E5*0.6 -> 10597.752 | G5: 26 | H5: =C5*G5 -> 20874.36 | I5: =H5-F5 -> 10276.608 | N5: =SUM(J5:M5) -> 0 | P5: =I5-N5+O5 -> 10276.608
A6: Клинцы | B6: Ретал | C6: 490.46 | D6: =20*8 -> 160 | E6: =C6*D6 -> 78473.6 | F6: =E6*0.6 -> 47084.16 | G6: 219 | H6: =C6*G6 -> 107410.74 | I6: =H6-F6 -> 60326.58 | J6: 12448 | K6: 960 | M6: 16732.81 | N6: =SUM(J6:M6) -> 30140.81 | P6: =I6-N6+O6 -> 30185.77
A7: Вместе по объекту Ретал | E7: =SUM(E3:E6) -> 265899.08 | F7: =SUM(F3:F6) -> 159539.45 | H7: =SUM(H3:H6) -> 335251.79 | I7: =SUM(I3:I6) -> 175712.34 | N7: =SUM(N3:N6) -> 99668.21 | O7: =SUM(O3:O6) -> 0 | P7: =P3+P6+P5 -> 76405.06

Sheet Биогаз
A1: Техника | B1: Объект | C1: Стоимость за 1 час, грн | D1: План | F1: предоплата 60% | G1: Факт | I1: Сумма к взаиморасчетам, грн | J1: Оплаты с Индастриалбуд | O1: Поступление на Индастриал от сторонних заказчиков, грн | P1: Сумма к взаиморасчетам с учетом движения ДС на р/с Индастриалбуд, грн
D2: кол-во часов | E2: сумма, грн | G2: Кол-во Часов | H2: Сума | J2: ЗП механизаторов с налогами, грн. | K2: Разрешительная документация, грн. | L2: Страховка, грн | M2: Топливо, грн | N2: вместе оплаченно, грн
A3: Ротор Пегасус | B3: Биогаз | C3: 592.98 | D3: =24*8 -> 192 | E3: =C3*D3 -> 113852.16 | F3: =E3*0.6 -> 68311.296 | G3: 138 | H3: =C3*G3 -> 81831.24 | I3: =H3-F3 -> 13519.944 | J3: 7902.27 | M3: 27620 | N3: =SUM(J3:M3) -> 35522.27 | P3: =I3-N3+O3 -> -22002.326
A4: Виброкаток | B4: Биогаз | C4: 544.05 | D4: =10*8 -> 80 | E4: =C4*D4 -> 43524 | F4: =E4*0.6 -> 26114.4 | H4: =C4*G4 -> 0 | I4: =H4-F4 -> -26114.4 | N4: =SUM(J4:M4) -> 0 | P4: =I4-N4+O4 -> -26114.4
A5: Экскаватор JCB | B5: Биогаз | C5: 496.93 | D5: =22*8 -> 176 | E5: =C5*D5 -> 87459.68 | F5: =E5*0.6 -> 52475.808 | G5: 283 | H5: =C5*G5 -> 140631.19 | I5: =H5-F5 -> 88155.382 | J5: 12053.6 | M5: 30563.86 | N5: =SUM(J5:M5) -> 42617.46 | P5: =I5-N5+O5 -> 45537.922
A6: Автокран XCMG | B6: Биогаз | C6: 563.19 | D6: =5*8 -> 40 | E6: =C6*D6 -> 22527.6 | F6: =E6*0.6 -> 13516.56 | G6: 123 | H6: =C6*G6 -> 69272.37 | I6: =H6-F6 -> 55755.81 | J6: 11590 | M6: 13602.47 | N6: =SUM(J6:M6) -> 25192.47 | P6: =I6-N6+O6 -> 30563.34
A7: Вресте по объекту Биогаз | E7: =SUM(E3:E6) -> 267363.44 | F7: =SUM(F3:F6) -> 160418.06 | H7: =H3+H5+H6 -> 291734.8 | I7: =SUM(I3:I6) -> 131316.74 | N7: =N3+N5+N6 -> 103332.2 | O7: =O3+O5+O6 -> 0 | P7: =SUM(P3:P6) -> 27984.536

Sheet ЦО
A1: Техника | B1: Объект | C1: Стоимость за 1 час, грн | D1: План | F1: предоплата 60% | G1: Факт | I1: Сумма к взаиморасчетам, грн | J1: Оплаты с Индастриалбуд | O1: Поступление на Индастриал от сторонних заказчиков, грн | P1: Сумма к взаиморасчетам с учетом движения ДС на р/с Индастриалбуд, грн
D2: кол-во часов | E2: сумма, грн | G2: Кол-во Часов | H2: Сума | J2: ЗП механизаторов с налогами, грн. | K2: Разрешительная документация, грн. | L2: Страховка, грн | M2: Топливо, грн | N2: вместе оплаченно, грн
A3: Телекоп №4 | B3: ЦО Спецтехника | L3: 1872 | N3: =SUM(J3:M3) -> 1872 | P3: =I3-N3+O3 -> -1872
A4: Главный офис | B4: ЦО Спецтехника | M4: 87035.89 | N4: =SUM(J4:M4) -> 87035.89 | P4: =I4-N4+O4 -> -87035.89

Sheet Бюджет Декабрь
A1: Техника | B1: Объект | C1: Кол-во смен | D1: Предоплаты на 01/12/22 | E1: План сумма за месяц, грн | F1: Плановая предоплата 60%, грн | G1: Предоплаты на декабрь | H1: Распределение по CF, грн
A2: Телескоп 1 | B2: Староконстантинов | C2: 22 смены | D2: -20718.042 | E2: 93526 | F2: =E2*0.6 -> 56115.6 | G2: =D2+F2 -> 35397.558 | H2: =$G$10/($G$2+$G$5+$G$9)*G2 -> 1536.4611
A3: Виброкаток | B3: Староконстантинов | D3: -5117.31 | G3: =D3+F3 -> -5117.31
A4: РДК 250 | B4: Староконстантинов | D4: -30658.32 | G4: =D4+F4 -> -30658.32
A5: Телескоп 4 | B5: Староконстантинов | C5: 10 смен | E5: 37410.4 | F5: =E5*0.6 -> 22446.24 | G5: =D5+F5 -> 22446.24 | H5: =$G$10/($G$2+$G$5+$G$9)*G5 -> 974.29811
A6: Экскаватор JCB 220 | B6: Староконстантинов | C6: 5 смен | D6: -63417.64 | E6: 39838.8 | F6: =E6*0.6 -> 23903.28 | G6: =D6+F6 -> -39514.36
A7: МАЗ 264 | B7: Староконстантинов | C7: 5 смен | D7: -32779.64 | E7: =14215-0.2 -> 14214.8 | F7: =E7*0.6 -> 8528.88 | G7: =D7+F7 -> -24250.76
A8: Самосвал Камаз | B8: Староконстантинов | C8: 5 смен | D8: -30781.88 | E8: 17233.6 | F8: =E8*0.6 -> 10340.16 | G8: =D8+F8 -> -20441.72
A9: Автокран XCMG | B9: Староконстантинов | C9: 25 смен | E9: 112638 | F9: =E9*0.6 -> 67582.8 | G9: =D9+F9 -> 67582.8 | H9: =$G$10/($G$2+$G$5+$G$9)*G9 -> 2933.4888
A10: Вместе по объекту Староконстантинов | D10: =SUM(D2:D9) -> -183472.83 | E10: =SUM(E2:E9) -> 314861.6 | F10: =SUM(F2:F9) -> 188916.96 | G10: =SUM(G2:G9)+0.12 -> 5444.248 | H10: =SUM(H2:H9) -> 5444.248
A11: Телескоп 2 | B11: Приднепровский МЕТАЛЛ | C11: 20 смен | D11: 15387.47 | E11: 74820.8 | F11: =E11*0.6 -> 44892.48 | G11: =D11+F11 -> 60279.95 | H11: =G11 -> 60279.95
A12: Экскаватор JCB 2013 | B12: Приднепровский МЕТАЛЛ | D12: 1872.334 | G12: =D12+F12 -> 1872.334 | H12: =G12 -> 1872.334
A13: Вместе по объекту Приднепровский МЕТАЛЛ | D13: =SUM(D11:D12) -> 17259.804 | E13: =SUM(E11:E12) -> 74820.8 | F13: =SUM(F11:F12) -> 44892.48 | G13: =SUM(G11:G12) -> 62152.284 | H13: =H11 -> 60279.95
A14: Экскаватор JCB 2013 | B14: МЭЗ СЕТИ | C14: 25 смен | E14: 99386 | F14: =E14*0.6 -> 59631.6 | G14: =F14 -> 59631.6 | H14: =G14 -> 59631.6
A15: МАЗ 265 | B15: МЭЗ СЕТИ | C15: 15 смен | E15: 42644.4 | F15: =E15*0.6 -> 25586.64 | G15: =F15 -> 25586.64 | H15: =G15 -> 25586.64
A16: Вместе по объекту МЭЗ СЕТИ | E16: =SUM(E14:E15) -> 142030.4 | F16: =SUM(F14:F15) -> 85218.24 | G16: =SUM(G14:G15) -> 85218.24 | H16: =SUM(H14:H15) -> 85218.24
A17: Телескоп 5 | B17: Ретал | C17: 25 смен | D17: 35942.682 | E17: 93526 | F17: =E17*0.6 -> 56115.6 | G17: =D17+F17 -> 92058.282 | H17: =G17 -> 92058.282
A18: Экскаватор JCB 2008 | B18: Ретал | C18: 25 смен | D18: -360.928 | E18: 99386 | F18: =E18*0.6 -> 59631.6 | G18: =D18+F18 -> 59270.672 | H18: =G18 -> 59270.672
A19: Haulotte | B19: Ретал | C19: 25 часов | D19: 10276.608 | E19: 20071.5 | F19: =E19*0.6 -> 12042.9 | G19: =D19+F19 -> 22319.508 | H19: =G19 -> 22319.508
A20: Клинцы | B20: Ретал | C20: 25 смен | D20: 30185.77 | E20: 98092 | F20: =E20*0.6 -> 58855.2 | G20: =D20+F20 -> 89040.97 | H20: =G20 -> 89040.97
A21: Вместе по объекту Ретал | D21: =SUM(D17:D20) -> 76044.132 | E21: =SUM(E17:E20) -> 311075.5 | F21: =SUM(F17:F20) -> 186645.3 | G21: =SUM(G17:G20) -> 262689.43 | H21: =SUM(H17:H20) -> 262689.43
A22: Ротор Пегасус | B22: Биогаз | C22: 25 смен | D22: -22002.326 | E22: 118596 | F22: =E22*0.6 -> 71157.6 | G22: =D22+F22 -> 49155.274 | H22: =$G$26/($G$22+$G$23+$G$25)*G22 -> 42685.364
A23: Экскаватор JCB | B23: Биогаз | C23: 25 смен | D23: 45537.922 | E23: 99386 | F23: =E23*0.6 -> 59631.6 | G23: =D23+F23 -> 105169.52 | H23: =$G$26/($G$22+$G$23+$G$25)*G23 -> 91326.911
A24: Виброкаток | B24: Биогаз | D24: -26114.4 | G24: =D24+F24 -> -26114.4
A25: Автокран XCMG | B25: Биогаз | C25: 5 смен | D25: 30563.34 | E25: 22527.6 | F25: =E25*0.6 -> 13516.56 | G25: =D25+F25 -> 44079.9 | H25: =$G$26/($G$22+$G$23+$G$25)*G25 -> 38278.02
A26: Вресте по объекту Биогаз | D26: =SUM(D22:D25) -> 27984.536 | E26: =SUM(E22:E25) -> 240509.6 | F26: =SUM(F22:F25) -> 144305.76 | G26: =SUM(G22:G25) -> 172290.3 | H26: =SUM(H22:H25) -> 172290.3
E28: =E10+E13+E16+E21+E26 -> 1083297.9 | F28: =F10+F13+F16+F21+F26 -> 649978.74 | H28: =H26+H21+H16+H13+H10 -> 585922.17
E29: =E28-'Декабрь факт'!E31 -> 0

Sheet Декабрь факт
A1: Техника | B1: Объект | C1: Стоимость за 1 час, грн | D1: План | F1: предоплата 60% | H1: Распределение предоплаты по факту отработанного на объектах | I1: Факт | K1: Сумма к взаиморасчетам, грн | L1: Оплаты с Индастриалбуд | Q1: Поступление на Индастриал от сторонних заказчиков, грн | R1: Сумма к взаиморасчетам с учетом движения ДС на р/с Индастриалбуд, грн
D2: кол-во часов | E2: сумма, грн | I2: Кол-во Часов | J2: Сума | L2: ЗП механизаторов с налогами, грн. | M2: Разрешительная документация, грн. | N2: Страховка, грн | O2: Топливо, грн | P2: вместе оплаченно, грн
A3: Телескоп 1 | B3: Староконстантинов | C3: =467.63 -> 467.63 | D3: =22*9 -> 198 | E3: =C3*D3+935.26 -> 93526 | H3: =$G$10/$J$10*J3 -> 1646.2393 | I3: =111+107+37 -> 255 | J3: =I3*C3 -> 119245.65 | L3: 11590 | O3: =15338.51-110000/365153.35*15338.51 -> 10717.887 | P3: =SUM(L3:O3) -> 22307.887 | Q3: =6000+4400 -> 10400
A4: Телескоп 4 | B4: Староконстантинов | C4: 467.63 | D4: =10*8 -> 80 | E4: =C4*D4 -> 37410.4 | H4: =$G$10/$J$10*J4 -> 942.55269 | I4: =33+73+40 -> 146 | J4: =I4*C4 -> 68273.98 | L4: 12053.6 | N4: 1872 | O4: =14273.45-110000/365153.35*14273.45 -> 9973.6688 | P4: =SUM(L4:O4) -> 23899.269
A5: Экскаватор JCB 220 | B5: Староконстантинов | C5: 995.97 | D5: =5*8 -> 40 | E5: =C5*D5 -> 39838.8 | H5: =$G$10/$J$10*J5 -> 1182.4836 | I5: =67+19 -> 86 | J5: =I5*C5 -> 85653.42 | L5: 9530.21 | O5: =5775-110000/365153.35*5775 -> 4035.3199 | P5: =SUM(L5:O5) -> 13565.53
A6: Автокран XCMG | B6: Староконстантинов | C6: 563.19 | D6: =25*8 -> 200 | E6: =C6*D6 -> 112638 | H6: =$G$10/$J$10*J6 -> 1352.8654 | I6: 174 | J6: =I6*C6 -> 97995.06 | L6: =11590/(I6+I23)*I6 -> 9934.2857 | O6: =(68415.84+8597.98)/(I6+I23)*I6-110000/365153.35*(68415.84+8597.98)/(I6+I23)*I6 -> 46126.22 | P6: =SUM(L6:O6) -> 56060.505
A7: МАЗ 264 | B7: Староконстантинов | C7: 355.37 | D7: =5*8 -> 40 | E7: =C7*D7 -> 14214.8 | H7: =$G$10/$J$10*J7 -> 260.02018 | I7: =36+17 -> 53 | J7: =I7*C7 -> 18834.61 | L7: 7087.64 | O7: =9980.32-110000/365153.35*9980.32 -> 6973.8155 | P7: =SUM(L7:O7) -> 14061.455
A8: Самосвал Камаз | B8: Староконстантинов | C8: 430.84 | D8: =5*8 -> 40 | E8: =C8*D8 -> 17233.6 | H8: =$G$10/$J$10*J8 -> 0 | J8: =I8*C8 -> 0 | P8: =SUM(L8:O8) -> 0
A9: Виброкаток | B9: Староконстантинов | C9: 544.05 | E9: =C9*D9 -> 0 | H9: =$G$10/$J$10*J9 -> 60.08682 | I9: 8 | J9: =I9*C9 -> 4352.4 | L9: =879.72/(I9+I20)*I9 -> 190.20973 | O9: =10971.23/(I9+I20)*I9-110000/365153.35*10971.23/(I9+I20)*I9 -> 1657.5612 | P9: =SUM(L9:O9) -> 1847.7709 | Q9: 26400
A10: Вместе по объекту Староконстантинов | E10: =SUM(E3:E9) -> 314861.6 | F10: ='Бюджет Декабрь'!F10 -> 188916.96 | G10: ='Бюджет Декабрь'!H10 -> 5444.248 | H10: =SUM(H3:H9) -> 5444.248 | J10: =SUM(J3:J9) -> 394355.12 | K10: =J10-F10 -> 205438.16 | P10: =SUM(P3:P9) -> 131742.42 | Q10: =SUM(Q3:Q9) -> 36800 | R10: =K10-P10+Q10 -> 110495.74 | S10: =J10-F10-P10+Q10 -> 110495.74
A11: Телескоп 2 | B11: Приднепровский МЕТАЛЛ | C11: 467.63 | D11: =20*8 -> 160 | E11: =C11*D11 -> 74820.8 | H11: =$G$13/$J$13*J11 -> 3955.4823 | I11: 5 | J11: =C11*I11 -> 2338.15 | L11: =6026.8/(I11+I27)*I11 -> 456.57576 | O11: =11183.64/(I11+I27)*I11-110000/365153.35*11183.64/(I11+I27)*I11 -> 592.01844 | P11: =SUM(L11:O11) -> 1048.5942
A12: Экскаватор JCB 2013 | B12: Приднепровский МЕТАЛЛ | C12: 496.93 | E12: =C12*D12 -> 0 | H12: =$G$13/$J$13*J12 -> 56324.468 | I12: 67 | J12: =C12*I12 -> 33294.31 | L12: =(2173.6+1926.6+7953.4)/(I12+I25)*I12 -> 3827.4464 | O12: =(24736.16+6668.32)/(I12+I25)*I12-110000/365153.35*(24736.16+6668.32)/(I12+I25)*I12 -> 6968.0288 | P12: =SUM(L12:O12) -> 10795.475
A13: Вместе по объекту Приднепровский МЕТАЛЛ | E13: =SUM(E11:E12) -> 74820.8 | F13: ='Бюджет Декабрь'!F13 -> 44892.48 | G13: ='Бюджет Декабрь'!H13 -> 60279.95 | H13: =SUM(H11:H12) -> 60279.95 | J13: =SUM(J11:J12) -> 35632.46 | K13: =J13-F13 -> -9260.02 | P13: =SUM(P11:P12) -> 11844.069 | Q13: =SUM(Q11:Q12) -> 0 | R13: =K13-P13+Q13 -> -21104.089 | S13: =J13-F13-P13 -> -21104.089
A14: Телескоп 5 | B14: Ретал | C14: 467.63 | D14: =25*8 -> 200 | E14: =C14*D14 -> 93526 | H14: =$G$18/$J$18*J14 -> 92637.667 | I14: 232 | J14: =C14*I14 -> 108490.16 | L14: 12053.6 | O14: =28600.01-110000/365153.35*28600.01 -> 19984.449 | P14: =SUM(L14:O14) -> 32038.049 | V14: ='Бюджет Декабрь'!F17 -> 56115.6 | W14: =J14 -> 108490.16 | X14: =W14-V14 -> 52374.56 | Y14: =P14 -> 32038.049 | Z14: =X14-Y14 -> 20336.511
A15: Экскаватор JCB 2008 | B15: Ретал | C15: 496.93 | D15: =25*8 -> 200 | E15: =C15*D15 -> 99386 | H15: =$G$18/$J$18*J15 -> 83166.523 | I15: 196 | J15: =C15*I15 -> 97398.28 | L15: 17917.08 | O15: =(16439.54+16101.36)-110000/365153.35*(16439.54+16101.36) -> 22738.172 | P15: =SUM(L15:O15) -> 40655.252 | V15: ='Бюджет Декабрь'!F18 -> 59631.6 | W15: =J15 -> 97398.28 | X15: =W15-V15 -> 37766.68 | Y15: =P15 -> 40655.252 | Z15: =X15-Y15 -> -2888.5719
A16: Haulotte | B16: Ретал | C16: 802.86 | D16: 25 | E16: =C16*D16 -> 20071.5 | H16: =$G$18/$J$18*J16 -> 12339.842 | I16: 18 | J16: =C16*I16 -> 14451.48 | M16: 13060.28 | P16: =SUM(L16:O16) -> 13060.28 | V16: ='Бюджет Декабрь'!F19 -> 12042.9 | W16: =J16 -> 14451.48 | X16: =W16-V16 -> 2408.58 | Y16: =P16 -> 13060.28 | Z16: =X16-Y16 -> -10651.7
A17: Клинцы | B17: Ретал | C17: 490.46 | D17: =25*8 -> 200 | E17: =C17*D17 -> 98092 | H17: =$G$18/$J$18*J17 -> 74545.401 | I17: 178 | J17: =C17*I17 -> 87301.88 | L17: 11590 | O17: =19097.36-110000/365153.35*19097.36 -> 13344.408 | P17: =SUM(L17:O17) -> 24934.408 | V17: ='Бюджет Декабрь'!F20 -> 58855.2 | W17: =J17 -> 87301.88 | X17: =W17-V17 -> 28446.68 | Y17: =P17 -> 24934.408 | Z17: =X17-Y17 -> 3512.2717
A18: Вместе по объекту Ретал | E18: =SUM(E14:E17) -> 311075.5 | F18: ='Бюджет Декабрь'!F21 -> 186645.3 | G18: ='Бюджет Декабрь'!H21 -> 262689.43 | H18: =SUM(H14:H17) -> 262689.43 | J18: =SUM(J14:J17) -> 307641.8 | K18: =J18-F18 -> 120996.5 | P18: =SUM(P14:P17) -> 110687.99 | Q18: =SUM(Q14:Q17) -> 0 | R18: =K18-P18+Q18 -> 10308.511 | S18: =J18-F18-P18 -> 10308.511 | V18: =SUM(V14:V17) -> 186645.3 | W18: =SUM(W14:W17) -> 307641.8 | X18: =SUM(X14:X17) -> 120996.5 | Y18: =SUM(Y14:Y17) -> 110687.99 | Z18: =SUM(Z14:Z17) -> 10308.511
A19: Ротор Пегасус | B19: Биогаз | C19: 592.98 | D19: =25*8 -> 200 | E19: =C19*D19 -> 118596 | H19: =$G$24/$J$24*J19 -> 67151.197 | I19: 225 | J19: =C19*I19 -> 133420.5 | L19: 11590 | O19: =39760.03-110000/365153.35*39760.03 -> 27782.587 | P19: =SUM(L19:O19) -> 39372.587
A20: Виброкаток | B20: Биогаз | C20: 544.05 | E20: =C20*D20 -> 0 | H20: =$G$24/$J$24*J20 -> 7940.8686 | I20: 29 | J20: =C20*I20 -> 15777.45 | L20: =879.72/(I20+I9)*I20 -> 689.51027 | O20: =10971.23/(I20+I9)*I20-110000/365153.35*10971.23/(I20+I9)*I20 -> 6008.6593 | P20: =SUM(L20:O20) -> 6698.1696
A21: Самосвал Камаз | B21: Биогаз | C21: 430.84 | E21: =C21*D21 -> 0 | H21: =$G$24/$J$24*J21 -> 16696.98 | I21: 77 | J21: =C21*I21 -> 33174.68 | L21: 8955.91 | O21: =(17084.48+6420)-110000/365153.35*(17084.48+6420) -> 16423.913 | P21: =SUM(L21:O21) -> 25379.823
A22: Экскаватор JCB | B22: Биогаз | C22: 496.93 | D22: =25*8 -> 200 | E22: =C22*D22 -> 99386 | H22: =$G$24/$J$24*J22 -> 72281.017 | I22: 289 | J22: =C22*I22 -> 143612.77 | L22: =12053.6 -> 12053.6 | O22: =45710.12-110000/365153.35*45710.12 -> 31940.253 | P22: =SUM(L22:O22) -> 43993.853
A23: Автокран XCMG | B23: Биогаз | C23: 563.19 | D23: =5*8 -> 40 | E23: =C23*D23 -> 22527.6 | H23: =$G$24/$J$24*J23 -> 8220.233 | I23: 29 | J23: =C23*I23 -> 16332.51 | L23: =11590/(I6+I23)*I23 -> 1655.7143 | O23: =(68415.84+8597.98)/(I6+I23)*I23-110000/365153.35*(68415.84+8597.98)/(I6+I23)*I23 -> 7687.7033 | P23: =SUM(L23:O23) -> 9343.4175
A24: Вресте по объекту Биогаз | E24: =SUM(E19:E23) -> 240509.6 | F24: ='Бюджет Декабрь'!F26 -> 144305.76 | G24: ='Бюджет Декабрь'!H26 -> 172290.3 | H24: =SUM(H19:H23) -> 172290.3 | J24: =SUM(J19:J23) -> 342317.91 | K24: =J24-F24 -> 198012.15 | P24: =SUM(P19:P23) -> 124787.85 | Q24: =SUM(Q19:Q23) -> 0 | R24: =K24-P24+Q24 -> 73224.3 | S24: =J24-F24-P24 -> 73224.3
A25: Экскаватор JCB 2013 | B25: МЕЗ Сети | C25: 496.93 | D25: =25*8 -> 200 | E25: =C25*D25 -> 99386 | H25: =$G$28/$J$28*J25 -> 60929.615 | I25: 144 | J25: =C25*I25 -> 71557.92 | L25: =12053.6/(I12+I25)*I25 -> 8226.1536 | O25: =45710.12/(I12+I25)*I25-110000/365153.35*45710.12/(I12+I25)*I25 -> 21798.087 | P25: =SUM(L25:O25) -> 30024.241
A26: МАЗ 264 | B26: МЕЗ Сети | C26: 355.37 | D26: =15*8 -> 120 | E26: =C26*D26 -> 42644.4 | H26: =$G$28/$J$28*J26 -> 0 | J26: =C26*I26 -> 0 | P26: =SUM(L26:O26) -> 0
A27: Телескоп 2 | B27: МЕЗ Сети | C27: 467.63 | E27: =C27*D27 -> 0 | H27: =$G$28/$J$28*J27 -> 24288.625 | I27: 61 | J27: =C27*I27 -> 28525.43 | L27: =11590/(I6+I23+I27)*I27 -> 2677.9924 | O27: =(68415.84+8597.98)/(I6+I23+I27)*I27-110000/365153.35*(68415.84+8597.98)/(I6+I23+I27)*I27 -> 12434.278 | P27: =SUM(L27:O27) -> 15112.27
A28: Вресте по объекту МЕЗ СЕТИ | E28: =SUM(E25:E27) -> 142030.4 | F28: ='Бюджет Декабрь'!F16 -> 85218.24 | G28: ='Бюджет Декабрь'!H16 -> 85218.24 | H28: =SUM(H25:H27) -> 85218.24 | J28: =SUM(J25:J27) -> 100083.35 | K28: =J28-F28 -> 14865.11 | P28: =SUM(P25:P27) -> 45136.511 | Q28: =SUM(Q25:Q27) -> 0 | R28: =K28-P28+Q28 -> -30271.401 | S28: =J28-F28-P28 -> -30271.401
A29: Главный офис | B29: ЦО Спецтехника | O29: =87035.89+334746.5-(O27+O25+O23+O22+O21+O20+O19+O17+O15+O14+O12+O11+O9+O7+O6+O5+O4+O3)-110000 -> 44595.362 | P29: =SUM(L29:O29) -> 44595.362
E31: =E24+E18+E13+E10+E28 -> 1083297.9 | F31: =F10+F13+F18+F24+F28 -> 649978.74 | G31: =G10+G13+G18+G24+G28 -> 585922.17 | H31: =H10+H13+H18+H24+H28 -> 585922.17 | J31: =J10+J13+J18+J24+J28 -> 1180030.6 | K31: =K10+K13+K18+K24+K28 -> 530051.9 | P31: =P10+P13+P18+P24+P28 -> 424198.84 | Q31: =Q10+Q13+Q18+Q24+Q28 -> 36800 | R31: =R10+R13+R18+R24+R28 -> 142653.06 | S31: =S28+S24+S18+S13+S10 -> 142653.06
H32: =F10+Ноябрь!S9+'Декабрь факт'!F13+Ноябрь!S12+'Декабрь факт'!F18+Ноябрь!S17+'Декабрь факт'!F24+Ноябрь!S22+'Декабрь факт'!F28+Ноябрь!S23 -> 585922.38 | S32: =J31-F31-P31+Q31 -> 142653.06
R33: =J31-F31-P31+Q31 -> 142653.06

Sheet Лист1
C1: ВСЕГО
B2: Телескоп 1 | C2: =SUM(E2:H2) -> 15338.51 | E2: 4392 | F2: 5456.51 | G2: 1098 | H2: 4392
B3: Телескоп 4 | C3: =SUM(E3:I3) -> 14273.45 | E3: 2195.45 | F3: 4392 | H3: 4392 | I3: 3294
B4: Экскаватор JCB 220 | C4: =SUM(E4:Z4) -> 5775 | E4: 5775
B5: Автокран XCMG | C5: =SUM(E5:Z5) -> 77013.82 | E5: 2196 | F5: 549 | G5: 2745 | I5: 1098 | J5: 4392 | K5: 4392 | L5: 1479.56 | M5: 5490 | N5: 5465.84 | O5: 5132.6 | P5: 583.59 | Q5: 5459.26 | R5: 4937.16 | S5: 5280.83 | T5: 4117.5 | U5: 2581.4 | V5: 1536.1 | W5: 2196 | X5: 4392 | Y5: 4392 | Z5: 8597.98
B6: МАЗ 264 | C6: =SUM(E6:Z6) -> 9980.32 | E6: 4760 | F6: 5220.32
B7: Виброкаток | C7: =SUM(E7:Z7) -> 10971.23 | E7: 3164.99 | F7: 952.52 | G7: 1098 | H7: 3761.2 | I7: 622.02 | J7: 1372.5
B8: Вместе по объекту Староконстантинов
B9: Телескоп 2 | C9: =SUM(E9:Z9) -> 11183.64 | E9: 11183.64
B10: Экскаватор JCB 2013 | C10: =SUM(E10:Z10) -> 31404.48 | E10: 6073.27 | F10: 4240 | G10: 5942.89 | H10: 4240 | I10: 4240 | J10: 6668.32
B11: Вместе по объекту Приднепровский МЕТАЛЛ
B12: Телескоп 5 | C12: =SUM(E12:Z12) -> 28600.01 | E12: 28600.01
B13: Экскаватор JCB 2008 | C13: =SUM(E13:Z13) -> 32540.9 | E13: 5839.54 | F13: 4240 | G13: 6360 | H13: 16101.36
B14: Haulotte | C14: =SUM(E14:Z14) -> 0
B15: Клинцы | C15: =SUM(E15:Z15) -> 19097.36 | E15: 19097.36
B16: Вместе по объекту Ретал
B17: Ротор Пегасус | C17: =SUM(E17:Z17) -> 39760.03 | E17: 39760.03
B18: Виброкаток | C18: =SUM(E18:Z18) -> 0
B19: Камаз | C19: =SUM(E19:Z19) -> 23504.48 | E19: 8542.24 | F19: 8542.24 | G19: 6420
B20: Экскаватор JCB | C20: =SUM(E20:Z20) -> 45710.12 | E20: 45710.12
B21: Автокран XCMG | C21: =SUM(E21:Z21) -> 0
B22: Вресте по объекту Биогаз
B23: Экскаватор JCB | C23: =SUM(E23:Z23) -> 0
B24: Автокран XCMG | C24: =SUM(E24:Z24) -> 0
B25: Вресте по объекту МЕЗ СЕТИ
B26: Главный офис

Sheet Бюджет Январь 23
A1: Техника | B1: Объект | C1: Кол-во смен | D1: сумма за месяц, грн | E1: предоплата 60%, грн | F1: Сумма к взаиморасчетам по декабрю, грн | G1: Итого, сумма предоплаты за январь, грн. | H1: ЯНВАРЬ ФАКТ | I1: предоплата декабрь | J1: Факт декабрь | K1: факт-пред | L1: Оплаты с индастриал | M1: ЛЕВАК | N1: Сумма к взаиморасчетам | O1: предоплата январь | P1: Итого предоплат за январь | Q1: 0.8 | R1: Цифра для распределения в казне
A2: Телескоп 1 | B2: Староконстантинов | C2: 15 смен | D2: 56115.6 | E2: =D2*0.6 -> 33669.36 | H2: 71079.76 | I2: =VLOOKUP(A2,'Бюджет Декабрь'!$A$2:$F$9,6,0) -> 56115.6 | J2: =VLOOKUP(A2,'Декабрь факт'!$A$3:$J$9,8,0) -> 1646.2393 | K2: =J2-I2 -> -54469.361 | L2: =VLOOKUP(A2,'Декабрь факт'!$A$3:$P$9,14,0) -> 0 | M2: =6000+4400 -> 10400 | N2: =K2-L2+M2 -> -44069.361 | O2: =E2 -> 33669.36 | P2: =N2+O2 -> -10400.001 | Q2: =P2*0.8 -> -8320.0006 | R2: =$Q$10/($Q$2+$Q$3+$Q$4+$Q$5+$Q$6+$Q$7)*Q2 -> -6596.7291
A3: Телескоп 4 | B3: Староконстантинов | C3: 15 смен | D3: 56115.6 | E3: =D3*0.6 -> 33669.36 | H3: 75288.43 | I3: =VLOOKUP(A3,'Бюджет Декабрь'!$A$2:$F$9,6,0) -> 22446.24 | J3: =VLOOKUP(A3,'Декабрь факт'!$A$3:$J$9,8,0) -> 942.55269 | K3: =J3-I3 -> -21503.687 | L3: =VLOOKUP(A3,'Декабрь факт'!$A$3:$P$9,14,0) -> 1872 | N3: =K3-L3+M3 -> -23375.687 | O3: =E3 -> 33669.36 | P3: =N3+O3 -> 10293.673 | Q3: =P3*0.8 -> 8234.9382 | R3: =$Q$10/($Q$2+$Q$3+$Q$4+$Q$5+$Q$6+$Q$7)*Q3 -> 6529.2851
A4: Экскаватор JCB 220 | B4: Староконстантинов | C4: 15 смен | D4: 119516.4 | E4: =D4*0.6 -> 71709.84 | H4: 0 | I4: =VLOOKUP(A4,'Бюджет Декабрь'!$A$2:$F$9,6,0) -> 23903.28 | J4: =VLOOKUP(A4,'Декабрь факт'!$A$3:$J$9,8,0) -> 1182.4836 | K4: =J4-I4 -> -22720.796 | L4: =VLOOKUP(A4,'Декабрь факт'!$A$3:$P$9,14,0) -> 0 | N4: =K4-L4+M4 -> -22720.796 | O4: =E4 -> 71709.84 | P4: =N4+O4 -> 48989.044 | Q4: =P4*0.8 -> 39191.235 | R4: =$Q$10/($Q$2+$Q$3+$Q$4+$Q$5+$Q$6+$Q$7)*Q4 -> 31073.791 | S4: =R4-51771.17 -> -20697.379
A5: МАЗ 264 | B5: Староконстантинов | C5: 5 смен | D5: 14214.8 | E5: =D5*0.6 -> 8528.88 | H5: 0 | I5: =VLOOKUP(A5,'Бюджет Декабрь'!$A$2:$F$9,6,0) -> 8528.88 | J5: =VLOOKUP(A5,'Декабрь факт'!$A$3:$J$9,8,0) -> 260.02018 | K5: =J5-I5 -> -8268.8598 | L5: =VLOOKUP(A5,'Декабрь факт'!$A$3:$P$9,14,0) -> 0 | N5: =K5-L5+M5 -> -8268.8598 | O5: =E5 -> 8528.88 | P5: =N5+O5 -> 260.02018 | Q5: =P5*0.8 -> 208.01614 | R5: =$Q$10/($Q$2+$Q$3+$Q$4+$Q$5+$Q$6+$Q$7)*Q5 -> 164.93101
A6: Автокран XCMG | B6: Староконстантинов | C6: 15 смен | D6: 67582.8 | E6: =D6*0.6 -> 40549.68 | H6: 86731.26 | I6: =VLOOKUP(A6,'Бюджет Декабрь'!$A$2:$F$9,6,0) -> 67582.8 | J6: =VLOOKUP(A6,'Декабрь факт'!$A$3:$J$9,8,0) -> 1352.8654 | K6: =J6-I6 -> -66229.935 | L6: =VLOOKUP(A6,'Декабрь факт'!$A$3:$P$9,14,0) -> 0 | N6: =K6-L6+M6 -> -66229.935 | O6: =E6 -> 40549.68 | P6: =N6+O6 -> -25680.255 | Q6: =P6*0.8 -> -20544.204 | R6: =$Q$10/($Q$2+$Q$3+$Q$4+$Q$5+$Q$6+$Q$7)*Q6 -> -16289.007
A7: Виброкаток | B7: Староконстантинов | J7: =VLOOKUP(A7,'Декабрь факт'!$A$3:$J$9,8,0) -> 60.08682 | K7: =J7-I7 -> 60.08682 | L7: =VLOOKUP(A7,'Декабрь факт'!$A$3:$P$9,14,0) -> 0 | M7: 26400 | N7: =K7-L7+M7 -> 26460.087 | O7: =E7 -> 0 | P7: =N7+O7 -> 26460.087 | Q7: =P7*0.8 -> 21168.069 | R7: =$Q$10/($Q$2+$Q$3+$Q$4+$Q$5+$Q$6+$Q$7)*Q7 -> 16783.655
A8: Самосвал Камаз | B8: Староконстантинов | I8: =VLOOKUP(A8,'Бюджет Декабрь'!$A$2:$F$9,6,0) -> 10340.16 | K8: =J8-I8 -> -10340.16 | N8: =K8-L8+M8 -> -10340.16 | P8: =N8+O8 -> -10340.16 | Q8: =P8*0.8 -> -8272.128
A9: Клинцы | B9: Староконстантинов | H9: 16675.64
A10: Вместе по объекту Староконстантинов | D10: =SUM(D2:D6) -> 313545.2 | E10: =SUM(E2:E6) -> 188127.12 | F10: ='Декабрь факт'!R10 -> 110495.74 | G10: =E10+F10 -> 298622.86 | H10: =SUM(H2:H9) -> 249775.09 | I10: =SUM(I2:I9) -> 188916.96 | J10: =SUM(J2:J9) -> 5444.248 | K10: =SUM(K2:K9) -> -183472.71 | L10: =SUM(L2:L9) -> 1872 | N10: =SUM(N2:N9) -> -148544.71 | O10: =SUM(O2:O9) -> 188127.12 | P10: =SUM(P2:P9) -> 39582.408 | Q10: =SUM(Q2:Q9) -> 31665.926 | R10: =SUM(R2:R9) -> 31665.926
A12: Вместе по объекту Приднепровский МЕТАЛЛ | D12: =D11 -> 0 | E12: =E11 -> 0 | F12: ='Декабрь факт'!R13 -> -21104.089 | G12: =E12+F12 -> -21104.089
A13: Экскаватор JCB 2013 | B13: МЭЗ СЕТИ | C13: 20 смен | D13: 79508.8 | E13: =D13*0.6 -> 47705.28 | H13: 110815.39 | I13: =VLOOKUP(A13,'Бюджет Декабрь'!$A$14:$F$15,6,0) -> 59631.6 | J13: =VLOOKUP(A13,'Декабрь факт'!$A$25:$J$27,8,0) -> 60929.615 | K13: =J13-I13 -> 1298.0152 | L13: =VLOOKUP(A13,'Декабрь факт'!$A$25:$P$27,14,0) -> 0 | N13: =K13-L13 -> 1298.0152 | O13: =E13 -> 47705.28 | P13: =N13+O13 -> 49003.295 | Q13: =P13*0.8 -> 39202.636 | R13: =$S$16/($Q$13+$Q$15)*Q13 -> 20673.993
A14: МАЗ 265 | H14: 28784.97 | I14: =VLOOKUP(A14,'Бюджет Декабрь'!$A$14:$F$15,6,0) -> 25586.64 | K14: =J14-I14 -> -25586.64 | N14: =K14-L14 -> -25586.64 | O14: =E14 -> 0 | P14: =N14+O14 -> -25586.64 | Q14: =P14*0.8 -> -20469.312
A15: Телескоп 2 | B15: МЭЗ СЕТИ | C15: 20 смен | D15: 74820.8 | E15: =D15*0.6 -> 44892.48 | H15: 43021.96 | J15: =VLOOKUP(A15,'Декабрь факт'!$A$25:$J$27,8,0) -> 24288.625 | K15: =J15-I15 -> 24288.625 | L15: =VLOOKUP(A15,'Декабрь факт'!$A$25:$P$27,14,0) -> 0 | N15: =K15-L15 -> 24288.625 | O15: =E15 -> 44892.48 | P15: =N15+O15 -> 69181.105 | Q15: =P15*0.8 -> 55344.884 | R15: =$S$16/($Q$13+$Q$15)*Q15 -> 29186.807
A16: Вместе по объекту МЭЗ СЕТИ | D16: =SUM(D13:D15) -> 154329.6 | E16: =SUM(E13:E15) -> 92597.76 | F16: ='Декабрь факт'!R28 -> -30271.401 | G16: =E16+F16 -> 62326.359 | H16: =SUM(H13:H15) -> 182622.32 | I16: =SUM(I13:I15) -> 85218.24 | J16: =SUM(J13:J15) -> 85218.24 | K16: =SUM(K13:K15) -> 0 | L16: =SUM(L13:L15) -> 0 | N16: =SUM(N13:N15) -> 0 | O16: =SUM(O13:O15) -> 92597.76 | P16: =SUM(P13:P15) -> 92597.76 | Q16: =SUM(Q13:Q15) -> 74078.208 | R16: =SUM(R13:R15) -> 49860.8 | S16: 49860.8
A17: Телескоп 5 | B17: Ретал | C17: 20 смен | D17: 74820.8 | E17: =D17*0.6 -> 44892.48 | H17: 77626.58 | I17: ='Бюджет Декабрь'!F17 -> 56115.6 | J17: ='Декабрь факт'!J14 -> 108490.16 | K17: =J17-I17 -> 52374.56 | L17: ='Декабрь факт'!P14 -> 32038.049 | N17: =K17-L17 -> 20336.511 | O17: =E17 -> 44892.48 | P17: =N17+O17 -> 65228.991 | Q17: =P17*0.8 -> 52183.193 | R17: =$Q$21/($Q$17+$Q$18+$Q$20)*Q17 -> 51808.157
A18: Экскаватор JCB 2008 | B18: Ретал | C18: 12 смен | D18: 47705.28 | E18: =D18*0.6 -> 28623.168 | H18: 73545.64 | I18: ='Бюджет Декабрь'!F18 -> 59631.6 | J18: ='Декабрь факт'!J15 -> 97398.28 | K18: =J18-I18 -> 37766.68 | L18: ='Декабрь факт'!P15 -> 40655.252 | N18: =K18-L18 -> -2888.5719 | O18: =E18 -> 28623.168 | P18: =N18+O18 -> 25734.596 | Q18: =P18*0.8 -> 20587.677 | R18: =$Q$21/($Q$17+$Q$18+$Q$20)*Q18 -> 20439.715
A19: Haulotte | B19: Ретал | C19: 20 смен | D19: 16057.2 | E19: =D19*0.6 -> 9634.32 | H19: 16057.2 | I19: ='Бюджет Декабрь'!F19 -> 12042.9 | J19: ='Декабрь факт'!J16 -> 14451.48 | K19: =J19-I19 -> 2408.58 | L19: ='Декабрь факт'!P16 -> 13060.28 | N19: =K19-L19 -> -10651.7 | O19: =E19 -> 9634.32 | P19: =N19+O19 -> -1017.38 | Q19: =P19*0.8 -> -813.904
A20: Клинцы | B20: Ретал | C20: 20 смен | D20: 78473.6 | E20: =D20*0.6 -> 47084.16 | H20: 48555.54 | I20: ='Бюджет Декабрь'!F20 -> 58855.2 | J20: ='Декабрь факт'!J17 -> 87301.88 | K20: =J20-I20 -> 28446.68 | L20: ='Декабрь факт'!P17 -> 24934.408 | N20: =K20-L20 -> 3512.2717 | O20: =E20 -> 47084.16 | P20: =N20+O20 -> 50596.432 | Q20: =P20*0.8 -> 40477.145 | R20: =$Q$21/($Q$17+$Q$18+$Q$20)*Q20 -> 40186.24
A21: Вместе по объекту Ретал | D21: =SUM(D17:D20) -> 217056.88 | E21: =SUM(E17:E20) -> 130234.13 | F21: ='Декабрь факт'!R18 -> 10308.511 | G21: =E21+F21 -> 140542.64 | H21: =SUM(H17:H20) -> 215784.96 | I21: =SUM(I17:I20) -> 186645.3 | J21: =SUM(J17:J20) -> 307641.8 | K21: =SUM(K17:K20) -> 120996.5 | L21: =SUM(L17:L20) -> 110687.99 | N21: =SUM(N17:N20) -> 10308.511 | O21: =SUM(O17:O20) -> 130234.13 | P21: =SUM(P17:P20) -> 140542.64 | Q21: =G21*0.8 -> 112434.11 | R21: =SUM(R17:R20) -> 112434.11
A22: Ротор Пегасус | B22: Биогаз | C22: 20 смен | D22: 94876.8 | E22: =D22*0.6 -> 56926.08 | H22: 49217.34 | I22: =VLOOKUP(A22,'Бюджет Декабрь'!$A$22:$F$25,6,0) -> 71157.6 | J22: =VLOOKUP(A22,'Декабрь факт'!$A$19:$J$23,8,0) -> 67151.197 | K22: =J22-I22 -> -4006.4029 | L22: =VLOOKUP(A22,'Декабрь факт'!$A$19:$P$23,14,0) -> 0 | N22: =K22-L22 -> -4006.4029 | O22: =E22 -> 56926.08 | P22: =N22+O22 -> 52919.677 | Q22: =P22*0.8+4017.43204722502 -> 46353.174 | R22: =$Q$27/($Q$22+$Q$23+$Q$24+$Q$25)*Q22 -> 46353.174
A23: Экскаватор JCB | B23: Биогаз | C23: 25 смен | D23: 79508.8 | E23: =D23*0.6 -> 47705.28 | H23: 134668.03 | I23: =VLOOKUP(A23,'Бюджет Декабрь'!$A$22:$F$25,6,0) -> 59631.6 | J23: =VLOOKUP(A23,'Декабрь факт'!$A$19:$J$23,8,0) -> 72281.017 | K23: =J23-I23 -> 12649.417 | L23: =VLOOKUP(A23,'Декабрь факт'!$A$19:$P$23,14,0) -> 0 | N23: =K23-L23 -> 12649.417 | O23: =E23 -> 47705.28 | P23: =N23+O23 -> 60354.697 | Q23: =P23*0.8+4413.86837200027 -> 52697.626 | R23: =$Q$27/($Q$22+$Q$23+$Q$24+$Q$25)*Q23 -> 52697.626
A24: Самосвал Камаз | B24: Биогаз | C24: 20 смен | D24: 68934.4 | E24: =D24*0.6 -> 41360.64 | H24: 40068.12 | J24: =VLOOKUP(A24,'Декабрь факт'!$A$19:$J$23,8,0) -> 16696.98 | K24: =J24-I24 -> 16696.98 | L24: =VLOOKUP(A24,'Декабрь факт'!$A$19:$P$23,14,0) -> 0 | N24: =K24-L24 -> 16696.98 | O24: =E24 -> 41360.64 | P24: =N24+O24 -> 58057.62 | Q24: =P24*0.8+2474.1643023936 -> 48920.261 | R24: =$Q$27/($Q$22+$Q$23+$Q$24+$Q$25)*Q24 -> 48920.261
A25: Виброкаток | H25: 13057.2 | J25: =VLOOKUP(A25,'Декабрь факт'!$A$19:$J$23,8,0) -> 7940.8686 | K25: =J25-I25 -> 7940.8686 | L25: =VLOOKUP(A25,'Декабрь факт'!$A$19:$P$23,14,0) -> 0 | N25: =K25-L25 -> 7940.8686 | O25: 0 | P25: =N25+O25 -> 7940.8686 | Q25: =P25*0.8+456.991239517727 -> 6809.6861 | R25: =$Q$27/($Q$22+$Q$23+$Q$24+$Q$25)*Q25 -> 6809.6861
A26: Автокран XCMG | H26: 0 | I26: =VLOOKUP(A26,'Бюджет Декабрь'!$A$22:$F$25,6,0) -> 13516.56 | J26: =VLOOKUP(A26,'Декабрь факт'!$A$19:$J$23,8,0) -> 8220.233 | K26: =J26-I26 -> -5296.327 | L26: =VLOOKUP(A26,'Декабрь факт'!$A$19:$P$23,14,0) -> 0 | N26: =K26-L26 -> -5296.327 | O26: 0 | P26: =N26+O26 -> -5296.327
A27: Вресте по объекту Биогаз | D27: =SUM(D22:D24) -> 243320 | E27: =SUM(E22:E24) -> 145992 | F27: ='Декабрь факт'!R24 -> 73224.3 | G27: =E27+F27 -> 219216.3 | H27: =SUM(H22:H26) -> 237010.69 | I27: =SUM(I22:I26) -> 144305.76 | J27: =SUM(J22:J26) -> 172290.3 | K27: =SUM(K22:K26) -> 27984.536 | L27: =SUM(L22:L26) -> 0 | N27: =SUM(N22:N26) -> 27984.536 | O27: =SUM(O22:O26) -> 145992 | P27: =SUM(P22:P26) -> 173976.54 | Q27: =SUM(Q22:Q26) -> 154780.75 | R27: =SUM(R22:R26) -> 154780.75
R28: переплата
D29: =D10+D12+D16+D21+D27 -> 928251.68 | E29: =E10+E12+E16+E21+E27 -> 556951.01 | F29: =F10+F12+F16+F21+F27 -> 142653.06 | G29: =G10+G12+G16+G21+G27 -> 699604.07 | P29: 239946.84

Sheet Январь23 факт
A1: Техника | B1: Объект | C1: Стоимость за 1 час, грн | D1: План | F1: предоплата 60% | H1: Распределение предоплаты по факту отработанного на объектах | I1: Факт | K1: Сумма к взаиморасчетам, грн | L1: Оплаты с Индастриалбуд | Q1: Поступление на Индастриал от сторонних заказчиков, грн | R1: Сумма к взаиморасчетам с учетом движения ДС на р/с Индастриалбуд, грн
D2: кол-во часов | E2: сумма, грн | I2: Кол-во Часов | J2: Сума | L2: ЗП механизаторов с налогами, грн. | M2: Разрешительная документация, грн. | N2: Страховка, грн | O2: Топливо, грн | P2: вместе оплаченно, грн
A3: Телескоп 1 | B3: Староконстантинов | C3: =467.63 -> 467.63 | D3: =15*8 -> 120 | E3: =C3*D3 -> 56115.6 | H3: =$G$11/$J$11*J3 -> 84980.618 | I3: 152 | J3: =I3*C3 -> 71079.76 | L3: 11420.04 | O3: =26326.67-71.54 -> 26255.13 | P3: =SUM(L3:O3) -> 37675.17
A4: Телескоп 4 | B4: Староконстантинов | C4: 467.63 | D4: =15*8 -> 120 | E4: =C4*D4 -> 56115.6 | H4: =$G$11/$J$11*J4 -> 90012.365 | I4: 161 | J4: =I4*C4 -> 75288.43 | L4: 11919.12 | O4: =19904.01-71.54 -> 19832.47 | P4: =SUM(L4:O4) -> 31751.59
A5: Экскаватор JCB 220 | B5: Староконстантинов | C5: 995.97 | D5: =15*8 -> 120 | E5: =C5*D5 -> 119516.4 | H5: =$G$11/$J$11*J5 -> 0 | J5: =I5*C5 -> 0 | P5: =SUM(L5:O5) -> 0 | Q5: =76560+64380 -> 140940
A6: Автокран XCMG | B6: Староконстантинов | C6: 563.19 | D6: =15*8 -> 120 | E6: =C6*D6 -> 67582.8 | H6: =$G$11/$J$11*J6 -> 103693.04 | I6: 154 | J6: =I6*C6 -> 86731.26 | L6: 11350.94 | O6: =19082.01-71.54 -> 19010.47 | P6: =SUM(L6:O6) -> 30361.41
A7: МАЗ 264 | B7: Староконстантинов | C7: 355.37 | D7: =5*8 -> 40 | E7: =C7*D7 -> 14214.8 | H7: =$G$11/$J$11*J7 -> 0 | J7: =I7*C7 -> 0 | P7: =SUM(L7:O7) -> 0
A8: Клинцы | B8: Староконстантинов | C8: 490.46 | E8: =C8*D8 -> 0 | H8: =$G$11/$J$11*J8 -> 19936.845 | I8: =24+10 -> 34 | J8: =I8*C8 -> 16675.64 | L8: =11590/(I8+I19)*I8 -> 2962.8571 | N8: =3074/(I8+I19)*I8 -> 785.83459 | O8: =21101.72/(I8+I19)*I8-71.54 -> 5322.8847 | P8: =SUM(L8:O8) -> 9071.5764
A9: КАМАЗ | B9: Староконстантинов | C9: 430.84 | E9: =C9*D9 -> 0 | H9: =$G$11/$J$11*J9 -> 0 | J9: =I9*C9 -> 0 | P9: =SUM(L9:O9) -> 0
A10: Виброкаток | B10: Староконстантинов | C10: 544.05 | E10: =C10*D10 -> 0 | H10: =$G$11/$J$11*J10 -> 0 | J10: =I10*C10 -> 0 | P10: =SUM(L10:O10) -> 0
A11: Вместе по объекту Староконстантинов | E11: =SUM(E3:E10) -> 313545.2 | F11: ='Бюджет Январь 23'!E10 -> 188127.12 | G11: =F11+'Декабрь факт'!S10 -> 298622.86 | H11: =SUM(H3:H9) -> 298622.86 | J11: =SUM(J3:J10) -> 249775.09 | K11: =IF(F11<0,F11+J11,J11-F11) -> 61647.97 | P11: =SUM(P3:P10) -> 108859.75 | Q11: =SUM(Q3:Q10) -> 140940 | R11: =K11-P11+Q11 -> 93728.224
A12: Телескоп 2 | B12: Приднепровский МЕТАЛЛ | C12: 467.63 | E12: =C12*D12 -> 0 | J12: =C12*I12 -> 0 | P12: =SUM(L12:O12) -> 0
A13: МАЗ 265 | B13: Приднепровский МЕТАЛЛ | C13: 355.37 | E13: =C13*D13 -> 0 | I13: 4 | J13: =C13*I13 -> 1421.48 | L13: =6655.82/(I13+I28)*I13 -> 313.21506 | O13: =12480/(I13+I28)*I13-71.54 -> 515.75412 | P13: =SUM(L13:O13) -> 828.96918
A14: Экскаватор JCB 2013 | B14: Приднепровский МЕТАЛЛ | C14: 496.93 | E14: =C14*D14 -> 0 | J14: =C14*I14 -> 0 | P14: =SUM(L14:O14) -> 0
A15: Вместе по объекту Приднепровский МЕТАЛЛ | E15: =SUM(E12:E14) -> 0 | F15: ='Бюджет Январь 23'!G12 -> -21104.089 | G15: =E15+'Декабрь факт'!R13 -> -21104.089 | H15: =SUM(H12:H13) -> 0 | J15: =SUM(J12:J14) -> 1421.48 | K15: =IF(F15<0,F15+J15,J15-F15) -> -19682.609 | P15: =SUM(P12:P14) -> 828.96918 | Q15: =SUM(Q12:Q14) -> 0 | R15: =K15-P15+Q15 -> -20511.579
A16: Телескоп 5 | B16: Ретал | C16: 467.63 | D16: =20*8 -> 160 | E16: =C16*D16 -> 74820.8 | H16: =$G$20/$J$20*J16 -> 50558.873 | I16: 166 | J16: =C16*I16 -> 77626.58 | L16: 12053.6 | O16: =20950.78-71.54 -> 20879.24 | P16: =SUM(L16:O16) -> 32932.84
A17: Экскаватор JCB 2008 | B17: Ретал | C17: 496.93 | D17: =12*8 -> 96 | E17: =C17*D17 -> 47705.28 | H17: =$G$20/$J$20*J17 -> 47900.921 | I17: 148 | J17: =C17*I17 -> 73545.64 | L17: 12053.6 | O17: =31883.08-71.54 -> 31811.54 | P17: =SUM(L17:O17) -> 43865.14
A18: Haulotte | B18: Ретал | C18: 802.86 | D18: =20 -> 20 | E18: =C18*D18 -> 16057.2 | H18: =$G$20/$J$20*J18 -> 10458.195 | I18: 20 | J18: =C18*I18 -> 16057.2 | P18: =SUM(L18:O18) -> 0
A19: Клинцы | B19: Ретал | C19: 490.46 | D19: =20*8 -> 160 | E19: =C19*D19 -> 78473.6 | H19: =$G$20/$J$20*J19 -> 31624.65 | I19: 99 | J19: =C19*I19 -> 48555.54 | L19: =11590/(I8+I19)*I19 -> 8627.1429 | N19: =3074/(I19+I8)*I19 -> 2288.1654 | O19: =21101.72/(I19+I8)*I19-71.54 -> 15635.755 | P19: =SUM(L19:O19) -> 26551.064
A20: Вместе по объекту Ретал | E20: =SUM(E16:E19) -> 217056.88 | F20: ='Бюджет Январь 23'!E21 -> 130234.13 | G20: =F20+'Декабрь факт'!S18 -> 140542.64 | H20: =SUM(H16:H19) -> 140542.64 | J20: =SUM(J16:J19) -> 215784.96 | K20: =IF(F20<0,F20+J20,J20-F20) -> 85550.832 | P20: =SUM(P16:P19) -> 103349.04 | Q20: =SUM(Q16:Q19) -> 0 | R20: =K20-P20+Q20 -> -17798.212
A21: Ротор Пегасус | B21: Биогаз | C21: 592.98 | D21: =20*8 -> 160 | E21: =C21*D21 -> 94876.8 | H21: =$G$26/$J$26*J21 -> 45522.179 | I21: 83 | J21: =C21*I21 -> 49217.34 | L21: 11590 | O21: =23830-71.54 -> 23758.46 | P21: =SUM(L21:O21) -> 35348.46
A22: Виброкаток | B22: Биогаз | C22: 544.05 | E22: =C22*D22 -> 0 | H22: =$G$26/$J$26*J22 -> 12076.886 | I22: 24 | J22: =C22*I22 -> 13057.2 | L22: 1328.23 | P22: =SUM(L22:O22) -> 1328.23
A23: КАМАЗ | B23: Биогаз | C23: 430.84 | D23: =20*8 -> 160 | E23: =C23*D23 -> 68934.4 | H23: =$G$26/$J$26*J23 -> 37059.869 | I23: 93 | J23: =C23*I23 -> 40068.12 | L23: 7100.86 | O23: =27127.94-71.54 -> 27056.4 | P23: =SUM(L23:O23) -> 34157.26
A24: Экскаватор JCB 2007 | B24: Биогаз | C24: 496.93 | D24: =25*8 -> 200 | E24: =C24*D24-19877.2 -> 79508.8 | H24: =$G$26/$J$26*J24 -> 124557.37 | I24: 271 | J24: =C24*I24 -> 134668.03 | L24: 12053.6 | O24: =30910.53-71.54 -> 30838.99 | P24: =SUM(L24:O24) -> 42892.59
A25: Автокран XCMG | B25: Биогаз | C25: 563.19 | E25: =C25*D25 -> 0 | H25: =$G$26/$J$26*J25 -> 0 | J25: =C25*I25 -> 0 | P25: =SUM(L25:O25) -> 0
A26: Вресте по объекту Биогаз | E26: =SUM(E21:E25) -> 243320 | F26: ='Бюджет Январь 23'!E27 -> 145992 | G26: =F26+'Декабрь факт'!S24 -> 219216.3 | H26: =SUM(H21:H25) -> 219216.3 | J26: =SUM(J21:J25) -> 237010.69 | K26: =IF(F26<0,F26+J26,J26-F26) -> 91018.69 | P26: =SUM(P21:P25) -> 113726.54 | Q26: =SUM(Q21:Q25) -> 0 | R26: =K26-P26+Q26 -> -22707.85
A27: Экскаватор JCB 2013 | B27: МЕЗ Сети | C27: 496.93 | D27: =20*8 -> 160 | E27: =C27*D27 -> 79508.8 | H27: =$G$30/$J$30*J27 -> 37819.692 | I27: 223 | J27: =C27*I27 -> 110815.39 | L27: 12053.6 | O27: =35721.08-71.54 -> 35649.54 | P27: =SUM(L27:O27) -> 47703.14
A28: МАЗ 265 | B28: МЕЗ Сети | C28: 355.37 | E28: =C28*D28 -> 0 | H28: =$G$30/$J$30*J28 -> 9823.8944 | I28: 81 | J28: =C28*I28 -> 28784.97 | L28: =6655.82/(I13+I28)*I28 -> 6342.6049 | O28: =12480/(I13+I28)*I28-71.54 -> 11821.166 | P28: =SUM(L28:O28) -> 18163.771
A29: Телескоп 2 | B29: МЕЗ Сети | C29: 467.63 | D29: =20*8 -> 160 | E29: =C29*D29 -> 74820.8 | H29: =$G$30/$J$30*J29 -> 14682.773 | I29: 92 | J29: =C29*I29 -> 43021.96 | L29: 11741.31 | O29: =14708.71-71.54 -> 14637.17 | P29: =SUM(L29:O29) -> 26378.48
A30: Вресте по объекту МЕЗ СЕТИ | E30: =SUM(E27:E29) -> 154329.6 | F30: ='Бюджет Январь 23'!E16 -> 92597.76 | G30: =F30+'Декабрь факт'!R28 -> 62326.359 | H30: =SUM(H27:H29) -> 62326.359 | J30: =SUM(J27:J29) -> 182622.32 | K30: =IF(F30<0,F30+J30,J30-F30) -> 90024.56 | P30: =SUM(P27:P29) -> 92245.391 | Q30: =SUM(Q27:Q29) -> 0 | R30: =K30-P30+Q30 -> -2220.8308
A31: Главный офис | B31: ЦО Спецтехника | J31: 50000 | P31: =SUM(L31:O31) -> 0
E33: =E26+E20+E15+E11+E30 -> 928251.68 | F33: =F11+F15+F20+F26+F30 -> 535846.92 | G33: =G30+G26+G20+G15+G11 -> 699604.07 | H33: =H11+G15+H20+H26+H30 -> 699604.07 | J33: =J11+J15+J20+J26+J30 -> 886614.54 | K33: =K11+K15+K20+K26+K30 -> 308559.44 | L33: =SUM(L3:L31) -> 132910.72 | O33: =SUM(O3:O31) -> 283024.97 | P33: =P11+P15+P20+P26+P30 -> 419009.69 | Q33: =Q11+Q15+Q20+Q26+Q30 -> 140940 | R33: =R11+R15+R20+R26+R30 -> 30489.753
E34: =E33-'Бюджет Январь 23'!D29 -> 0 | H34: =F33+'Декабрь факт'!S31-G15 -> 699604.07 | J34: =886614.54-J33 -> 0
R35: =J33-F33-P33+Q33 -> 72697.931
A37: Работа в аренде у других предприятий
A38: Экскаватор JCB 220 | B38: Староконстантинов | C38: 995.97 | D38: =15*8 -> 120 | E38: =C38*D38 -> 119516.4 | I38: 84 | J38: =I38*C38 -> 83661.48 | L38: 12053.6 | O38: =36974.5-71.54 -> 36902.96 | P38: =SUM(L38:O38) -> 48956.56 | Q38: =76560+64380 -> 140940 | T38: =Q38-P38 -> 91983.44

Sheet Бюджет Февраль 23
A1: Техника | B1: Объект | C1: Кол-во смен | D1: Ст-сть за 1 час, грн | E1: сумма за месяц, грн | F1: предоплата 60%, грн | G1: Сумма к взаиморасчетам по Январю, грн | H1: Незарегестрированный НДС | I1: Итого, сумма предоплаты за Февраль 2023, грн. | J1: п/оплата январь | K1: Факт январь | L1: факт-пред | M1: Оплаты с индастриал | N1: ЛЕВАК | O1: Сумма к взаиморасчетам | P1: пр/оплата февраль | Q1: Итого предоплат за февраль | R1: 0.8 | S1: Цифра для распределения в казне
A2: Телескоп 1 | B2: Староконстантинов | C2: 25 | D2: 467.63 | E2: =C2*8*D2 -> 93526 | F2: =E2*0.6 -> 56115.6 | J2: =VLOOKUP(A2,'Бюджет Январь 23'!$A:$G,5,FALSE) -> 33669.36 | K2: =VLOOKUP(A2,'Январь23 факт'!$A:$J,8,FALSE) -> 84980.618 | L2: =K2-J2 -> 51311.258 | M2: =VLOOKUP(A2,'Январь23 факт'!$A:$R,14,FALSE) -> 0 | O2: =L2-M2+N2 -> 51311.258 | P2: =F2 -> 56115.6
A3: Телескоп 4 | B3: Староконстантинов | C3: 25 | D3: 467.63 | E3: =C3*8*D3 -> 93526 | F3: =E3*0.6 -> 56115.6 | J3: =VLOOKUP(A3,'Бюджет Январь 23'!$A:$G,5,FALSE) -> 33669.36 | K3: =VLOOKUP(A3,'Январь23 факт'!$A:$J,8,FALSE) -> 90012.365 | L3: =K3-J3 -> 56343.005 | M3: =VLOOKUP(A3,'Январь23 факт'!$A:$R,14,FALSE) -> 0 | O3: =L3-M3+N3 -> 56343.005 | P3: =F3 -> 56115.6
A4: Экскаватор JCB 220 | B4: Староконстантинов | C4: 10 | D4: 995.97 | E4: =C4*8*D4 -> 79677.6 | F4: =E4*0.6 -> 47806.56 | J4: =VLOOKUP(A4,'Бюджет Январь 23'!$A:$G,5,FALSE) -> 71709.84 | K4: =VLOOKUP(A4,'Январь23 факт'!$A:$J,8,FALSE) -> 0 | L4: =K4-J4 -> -71709.84 | M4: =VLOOKUP(A4,'Январь23 факт'!$A:$R,14,FALSE) -> 0 | O4: =L4-M4+N4 -> -71709.84 | P4: =F4 -> 47806.56
A5: МАЗ 264 | B5: Староконстантинов | C5: 10 | D5: 355.37 | E5: =C5*8*D5 -> 28429.6 | F5: =E5*0.6 -> 17057.76 | J5: =VLOOKUP(A5,'Бюджет Январь 23'!$A:$G,5,FALSE) -> 8528.88 | K5: =VLOOKUP(A5,'Январь23 факт'!$A:$J,8,FALSE) -> 0 | L5: =K5-J5 -> -8528.88 | M5: =VLOOKUP(A5,'Январь23 факт'!$A:$R,14,FALSE) -> 0 | O5: =L5-M5+N5 -> -8528.88 | P5: =F5 -> 17057.76
A6: Клинцы | B6: Староконстантинов | C6: 25 | D6: 490.46 | E6: =C6*8*D6 -> 98092 | F6: =E6*0.6 -> 58855.2 | J6: =VLOOKUP(A6,'Бюджет Январь 23'!$A:$G,5,FALSE) -> 0 | K6: =VLOOKUP(A6,'Январь23 факт'!$A:$J,8,FALSE) -> 19936.845 | L6: =K6-J6 -> 19936.845 | M6: =VLOOKUP(A6,'Январь23 факт'!$A:$R,14,FALSE) -> 785.83459 | O6: =L6-M6+N6 -> 19151.011 | P6: =F6 -> 58855.2
A7: Автокран XCMG | B7: Староконстантинов | C7: 25 | D7: 563.19 | E7: =C7*8*D7 -> 112638 | F7: =E7*0.6 -> 67582.8 | J7: =VLOOKUP(A7,'Бюджет Январь 23'!$A:$G,5,FALSE) -> 40549.68 | K7: =VLOOKUP(A7,'Январь23 факт'!$A:$J,8,FALSE) -> 103693.04 | L7: =K7-J7 -> 63143.355 | M7: =VLOOKUP(A7,'Январь23 факт'!$A:$R,14,FALSE) -> 0 | O7: =L7-M7+N7 -> 63143.355 | P7: =F7 -> 67582.8
A8: Вместе по объекту Староконстантинов | E8: =SUM(E2:E7) -> 505889.2 | F8: =SUM(F2:F7) -> 303533.52 | G8: ='Январь23 факт'!R11 -> 93728.224 | H8: -31187.85 | I8: =F8+G8+H8 -> 366073.89 | J8: =SUM(J2:J7) -> 188127.12 | K8: =SUM(K2:K7) -> 298622.86 | L8: =K8-J8 -> 110495.74 | M8: =SUM(M2:M7) -> 785.83459 | N8: =SUM(N2:N7) -> 0 | O8: =L8-M8+N8 -> 109709.91 | P8: =SUM(P2:P7) -> 303533.52 | Q8: =SUM(Q2:Q7) -> 0 | R8: =SUM(R2:R7) -> 0 | S8: =SUM(S2:S7) -> 0
E9: =C9*8*D9 -> 0 | F9: =E9*0.6 -> 0 | L9: =K9-J9 -> 0 | O9: =L9-M9+N9 -> 0 | P9: =F9 -> 0
A10: Вместе по объекту Приднепровский МЕТАЛЛ | E10: =E9 -> 0 | F10: =F9 -> 0 | G10: ='Январь23 факт'!R15 -> -20511.579 | I10: =F10+G10+H10 -> -20511.579 | L10: =K10-J10 -> 0 | O10: =L10-M10+N10 -> 0 | P10: =F10 -> 0
A11: Экскаватор JCB 2013 | B11: МЭЗ СЕТИ | C11: 24 | D11: 496.93 | E11: =C11*8*D11 -> 95410.56 | F11: =E11*0.6 -> 57246.336 | J11: =VLOOKUP(A11,'Бюджет Январь 23'!$A:$G,5,FALSE) -> 47705.28 | K11: =VLOOKUP(A11,'Январь23 факт'!$A:$J,8,FALSE) -> 0 | L11: =K11-J11 -> -47705.28 | M11: =VLOOKUP(A11,'Январь23 факт'!$A:$R,14,FALSE) -> 0 | O11: =L11-M11+N11 -> -47705.28 | P11: =F11 -> 57246.336
A12: Телескоп 2 | B12: МЭЗ СЕТИ | C12: 24 | D12: 467.63 | E12: =C12*8*D12 -> 89784.96 | F12: =E12*0.6 -> 53870.976 | J12: =VLOOKUP(A12,'Бюджет Январь 23'!$A:$G,5,FALSE) -> 44892.48 | K12: =VLOOKUP(A12,'Январь23 факт'!$A:$J,8,FALSE) -> 0 | L12: =K12-J12 -> -44892.48 | M12: =VLOOKUP(A12,'Январь23 факт'!$A:$R,14,FALSE) -> 0 | O12: =L12-M12+N12 -> -44892.48 | P12: =F12 -> 53870.976
A13: МАЗ 265 | B13: МЭЗ СЕТИ | C13: 24 | D13: 355.37 | E13: =C13*8*D13 -> 68231.04 | F13: =E13*0.6 -> 40938.624 | J13: =VLOOKUP(A13,'Бюджет Январь 23'!$A:$G,5,FALSE) -> 0 | K13: =VLOOKUP(A13,'Январь23 факт'!$A:$J,8,FALSE) -> 0 | L13: =K13-J13 -> 0 | M13: =VLOOKUP(A13,'Январь23 факт'!$A:$R,14,FALSE) -> 0 | O13: =L13-M13+N13 -> 0 | P13: =F13 -> 40938.624
A14: Вместе по объекту МЭЗ СЕТИ | E14: =SUM(E11:E13) -> 253426.56 | F14: =SUM(F11:F13) -> 152055.94 | G14: ='Январь23 факт'!R30 -> -2220.8308 | I14: =F14+G14+H14 -> 149835.11 | J14: =SUM(J11:J13) -> 92597.76 | K14: =SUM(K11:K13) -> 0 | L14: =K14-J14 -> -92597.76 | M14: =SUM(M11:M13) -> 0 | N14: =SUM(N11:N13) -> 0 | O14: =L14-M14+N14 -> -92597.76 | P14: =SUM(P11:P13) -> 152055.94 | Q14: =SUM(Q11:Q13) -> 0 | R14: =SUM(R11:R13) -> 0 | S14: =SUM(S11:S13) -> 0
A15: Телескоп 5 | B15: Ретал | C15: 25 | D15: 467.63 | E15: =C15*8*D15 -> 93526 | F15: =E15*0.6 -> 56115.6 | J15: =VLOOKUP(A15,'Бюджет Январь 23'!$A:$G,5,FALSE) -> 44892.48 | K15: =VLOOKUP(A15,'Январь23 факт'!$A:$J,8,FALSE) -> 50558.873 | L15: =K15-J15 -> 5666.3932 | M15: =VLOOKUP(A15,'Январь23 факт'!$A:$R,14,FALSE) -> 0 | O15: =L15-M15+N15 -> 5666.3932 | P15: =F15 -> 56115.6
A16: Экскаватор JCB 2008 | B16: Ретал | C16: 25 | D16: 496.93 | E16: =C16*8*D16 -> 99386 | F16: =E16*0.6 -> 59631.6 | J16: =VLOOKUP(A16,'Бюджет Январь 23'!$A:$G,5,FALSE) -> 28623.168 | K16: =VLOOKUP(A16,'Январь23 факт'!$A:$J,8,FALSE) -> 47900.921 | L16: =K16-J16 -> 19277.753 | M16: =VLOOKUP(A16,'Январь23 факт'!$A:$R,14,FALSE) -> 0 | O16: =L16-M16+N16 -> 19277.753 | P16: =F16 -> 59631.6
A17: Haulotte | B17: Ретал | C17: 20 | D17: 802.86 | E17: =C17*D17 -> 16057.2 | F17: =E17*0.6 -> 9634.32 | J17: =VLOOKUP(A17,'Бюджет Январь 23'!$A:$G,5,FALSE) -> 9634.32 | K17: =VLOOKUP(A17,'Январь23 факт'!$A:$J,8,FALSE) -> 10458.195 | L17: =K17-J17 -> 823.87535 | M17: =VLOOKUP(A17,'Январь23 факт'!$A:$R,14,FALSE) -> 0 | O17: =L17-M17+N17 -> 823.87535 | P17: =F17 -> 9634.32
A18: Клинцы | B18: Ретал | E18: =C18*8*D18 -> 0 | F18: =E18*0.6 -> 0 | J18: 47084.16 | K18: =VLOOKUP(A18,'Январь23 факт'!$A:$J,8,FALSE) -> 19936.845 | L18: =K18-J18 -> -27147.315 | M18: 26551.064 | O18: =L18-M18+N18 -> -53698.378 | P18: =F18 -> 0
A19: Вместе по объекту Ретал | E19: =SUM(E15:E18) -> 208969.2 | F19: =SUM(F15:F18) -> 125381.52 | G19: ='Январь23 факт'!R20 -> -17798.212 | H19: -18739.02 | I19: =F19+G19+H19 -> 88844.288 | J19: =SUM(J15:J18) -> 130234.13 | K19: =SUM(K15:K18) -> 128854.84 | L19: =K19-J19 -> -1379.2929 | M19: =SUM(M15:M18) -> 26551.064 | N19: =SUM(N15:N18) -> 0 | O19: =L19-M19+N19 -> -27930.357 | P19: =SUM(P15:P18) -> 125381.52 | Q19: =SUM(Q15:Q18) -> 0 | R19: =SUM(R15:R18) -> 0 | S19: =SUM(S15:S18) -> 0
A20: Ротор Пегасус | B20: Биогаз | C20: 14 | D20: 592.98 | E20: =C20*8*D20 -> 66413.76 | F20: =E20*0.6 -> 39848.256 | J20: =VLOOKUP(A20,'Бюджет Январь 23'!$A:$G,5,FALSE) -> 56926.08 | K20: =VLOOKUP(A20,'Январь23 факт'!$A:$J,8,FALSE) -> 45522.179 | L20: =K20-J20 -> -11403.901 | M20: =VLOOKUP(A20,'Январь23 факт'!$A:$R,14,FALSE) -> 0 | O20: =L20-M20+N20 -> -11403.901 | P20: =F20 -> 39848.256
A21: Экскаватор JCB 2007 | B21: Биогаз | C21: 14 | D21: 496.93 | E21: =C21*8*D21 -> 55656.16 | F21: =E21*0.6 -> 33393.696 | J21: 47705.28 | K21: =VLOOKUP(A21,'Январь23 факт'!$A:$J,8,FALSE) -> 124557.37 | L21: =K21-J21 -> 76852.086 | M21: =VLOOKUP(A21,'Январь23 факт'!$A:$R,14,FALSE) -> 0 | O21: =L21-M21+N21 -> 76852.086 | P21: =F21 -> 33393.696
A22: Самосвал Камаз | B22: Биогаз | C22: 14 | D22: 430.84 | E22: =C22*8*D22 -> 48254.08 | F22: =E22*0.6 -> 28952.448 | J22: 41360.64 | K22: =VLOOKUP(A22,'Январь23 факт'!$A:$J,8,FALSE) -> #N/A | L22: =K22-J22 -> #N/A | M22: =VLOOKUP(A22,'Январь23 факт'!$A:$R,14,FALSE) -> #N/A | O22: =L22-M22+N22 -> #N/A | P22: =F22 -> 28952.448
A23: Вресте по объекту Биогаз | E23: =SUM(E20:E22) -> 170324 | F23: =SUM(F20:F22) -> 102194.4 | G23: ='Январь23 факт'!R26 -> -22707.85 | H23: -31992.91 | I23: =F23+G23+H23 -> 47493.64 | J23: =SUM(J20:J22) -> 145992 | K23: =SUM(K20:K22) -> #N/A | L23: =SUM(L20:L22) -> #N/A | M23: =SUM(M20:M22) -> #N/A | N23: =SUM(N20:N22) -> 0 | O23: =SUM(O20:O22) -> #N/A | P23: =SUM(P20:P22) -> 102194.4 | Q23: =SUM(Q20:Q22) -> 0 | ... S23: =SUM(S20:S22) -> 0
C25: =SUM(A2:C22) -> 304 | E25: =E8+E10+E14+E19+E23 -> 1138609 | F25: =F8+F10+F14+F19+F23 -> 683165.38 | G25: =G8+G10+G14+G19+G23 -> 30489.753 | H25: =H8+H10+H14+H19+H23 -> -81919.78 | I25: =I8+I10+I14+I19+I23 -> 631735.35
H27: -8333.33 | I27: Управление спецтехникой

Sheet Февраль23 факт 
A1: Техника | B1: Объект | C1: Стоимость за 1 час, грн | D1: План | F1: предоплата 60% | G1: Факт | I1: Сумма к взаиморасчетам, грн | J1: Оплаты с Индастриалбуд | O1: Поступление на Индастриал от сторонних заказчиков, грн | P1: Сумма к взаиморасчетам с учетом движения ДС на р/с Индастриалбуд, грн
D2: кол-во часов | E2: сумма, грн | G2: Кол-во Часов | H2: Сума | J2: ЗП механизаторов с налогами, грн. | K2: Разрешительная документация, грн. | L2: Страховка, грн | M2: Топливо, грн | N2: вместе оплаченно, грн
A3: Телескоп 1 | B3: Староконстантинов | C3: 467.63 | D3: =25*8 -> 200 | E3: =C3*D3 -> 93526 | F3: =E3*0.6 -> 56115.6 | G3: 163 | H3: =G3*C3 -> 76223.69 | J3: 17802.6 | M3: 21695.63 | N3: =SUM(J3:M3) -> 39498.23
A4: Телескоп 4 | B4: Староконстантинов | C4: 467.63 | D4: =25*8 -> 200 | E4: =C4*D4 -> 93526 | F4: =E4*0.6 -> 56115.6 | G4: 151 | H4: =G4*C4 -> 70612.13 | J4: 18069.79 | M4: 15648 | N4: =SUM(J4:M4) -> 33717.79
A5: Экскаватор JCB 220 | B5: Староконстантинов | C5: 995.97 | D5: =10*8 -> 80 | E5: =C5*D5 -> 79677.6 | F5: =E5*0.6 -> 47806.56 | G5: 51 | H5: =G5*C5 -> 50794.47 | J5: =12053.6/($G$5+$G$26)*G5 -> 7781.438 | M5: =17630/($G$5+$G$26)*G5 -> 11381.392 | N5: =SUM(J5:M5) -> 19162.83
A6: МАЗ 264 | B6: Староконстантинов | C6: 355.37 | D6: =10*8 -> 80 | E6: =C6*D6 -> 28429.6 | F6: =E6*0.6 -> 17057.76 | G6: 22 | H6: =G6*C6 -> 7818.14 | N6: =SUM(J6:M6) -> 0
A7: Клинцы | B7: Староконстантинов | C7: 430.84 | D7: =25*8 -> 200 | E7: =C7*D7 -> 86168 | F7: =E7*0.6 -> 51700.8 | G7: 179 | H7: =G7*C7 -> 77120.36 | J7: 20360.54 | M7: 26559.13 | N7: =SUM(J7:M7) -> 46919.67
A8: Автокран XCMG 25 | B8: Староконстантинов | C8: 563.19 | D8: =25*8 -> 200 | E8: =C8*D8 -> 112638 | F8: =E8*0.6 -> 67582.8 | G8: 189 | H8: =G8*C8 -> 106442.91 | J8: 11590 | M8: 22085.61 | N8: =SUM(J8:M8) -> 33675.61
A9: Вместе по объекту Староконстантинов | E9: =SUM(E3:E8) -> 493965.2 | F9: ='Бюджет Февраль 23'!F8 -> 303533.52 | H9: =SUM(H3:H8) -> 389011.7 | I9: =IF(F9<0,F9+H9,H9-F9) -> 85478.18 | N9: =SUM(N3:N8) -> 172974.13 | O9: =SUM(O3:O8) -> 0 | P9: =I9-N9+O9 -> -87495.95
A10: Экскаватор JCB 2013 | B10: МЕЗ Сети | C10: 496.93 | D10: =24*8 -> 192 | E10: =C10*D10 -> 95410.56 | F10: =E10*0.6 -> 57246.336 | G10: 167 | H10: =C10*G10 -> 82987.31 | J10: 12053.6 | M10: 17754.4 | N10: =SUM(J10:M10) -> 29808
A11: Телескоп 2 | B11: МЕЗ Сети | C11: 467.63 | D11: =24*8 -> 192 | E11: =C11*D11 -> 89784.96 | F11: =E11*0.6 -> 53870.976 | G11: 162 | H11: =C11*G11 -> 75756.06 | J11: 3942.5 | M11: 19971.93 | N11: =SUM(J11:M11) -> 23914.43
A12: МАЗ 265 | B12: МЕЗ Сети | C12: 355.37 | D12: =24*8 -> 192 | E12: =C12*D12 -> 68231.04 | F12: =E12*0.6 -> 40938.624 | G12: 92 | H12: =C12*G12 -> 32694.04 | J12: 11590 | M12: 9900 | N12: =SUM(J12:M12) -> 21490
A13: Вресте по объекту МЕЗ СЕТИ | E13: =SUM(E10:E12) -> 253426.56 | F13: ='Бюджет Февраль 23'!F14 -> 152055.94 | H13: =SUM(H10:H12) -> 191437.41 | I13: =IF(F13<0,F13+H13,H13-F13) -> 39381.474 | N13: =SUM(N10:N12) -> 75212.43 | O13: =SUM(O10:O12) -> 0 | P13: =I13-N13+O13 -> -35830.956
A14: Телескоп 5 | B14: Ретал | C14: 467.63 | D14: =25*8 -> 200 | E14: =C14*D14 -> 93526 | F14: =E14*0.6 -> 56115.6 | G14: 209 | H14: =C14*G14 -> 97734.67 | J14: 12053.6 | M14: 33024.97 | N14: =SUM(J14:M14) -> 45078.57
A15: Экскаватор JCB 2008 | B15: Ретал | C15: 496.93 | D15: =25*8 -> 200 | E15: =C15*D15 -> 99386 | F15: =E15*0.6 -> 59631.6 | G15: 115 | H15: =C15*G15 -> 57146.95 | J15: 12053.6 | M15: 20305.55 | N15: =SUM(J15:M15) -> 32359.15
A16: Haulotte | B16: Ретал | C16: 802.86 | D16: 20 | E16: =C16*D16 -> 16057.2 | F16: =E16*0.6 -> 9634.32 | G16: 20 | H16: =C16*G16 -> 16057.2 | N16: =SUM(J16:M16) -> 0
A17: Вместе по объекту Ретал | E17: =SUM(E14:E16) -> 208969.2 | F17: ='Бюджет Февраль 23'!F19 -> 125381.52 | H17: =SUM(H14:H16) -> 170938.82 | I17: =IF(F17<0,F17+H17,H17-F17) -> 45557.3 | N17: =SUM(N14:N16) -> 77437.72 | O17: =SUM(O14:O16) -> 0 | P17: =I17-N17+O17 -> -31880.42
A18: Ротор Пегасус | B18: Биогаз | C18: 592.98 | D18: =14*8 -> 112 | E18: =C18*D18 -> 66413.76 | F18: =E18*0.6 -> 39848.256 | G18: 193 | H18: =C18*G18 -> 114445.14 | J18: 11590 | M18: 35300 | N18: =SUM(J18:M18) -> 46890
A19: Экскаватор JCB 2007 | B19: Биогаз | C19: 496.93 | D19: =14*8 -> 112 | E19: =C19*D19 -> 55656.16 | F19: =E19*0.6 -> 33393.696 | G19: 240 | H19: =C19*G19 -> 119263.2 | J19: 12053.6 | M19: 48043.15 | N19: =SUM(J19:M19) -> 60096.75
A20: Самосвал Камаз | B20: Биогаз | C20: 430.84 | D20: =14*8 -> 112 | E20: =C20*D20 -> 48254.08 | F20: =E20*0.6 -> 28952.448 | G20: 35 | H20: =C20*G20 -> 15079.4 | J20: 11590 | M20: 9327.35 | N20: =SUM(J20:M20) -> 20917.35
A21: Вресте по объекту Биогаз | E21: =SUM(E18:E20) -> 170324 | F21: ='Бюджет Февраль 23'!F23 -> 102194.4 | H21: =SUM(H18:H20) -> 248787.74 | I21: =IF(F21<0,F21+H21,H21-F21) -> 146593.34 | N21: =SUM(N18:N20) -> 127904.1 | O21: =SUM(O18:O20) -> 0 | P21: =I21-N21+O21 -> 18689.24
A22: Главный офис | B22: ЦО Спецтехника | H22: 50000 | N22: =SUM(J22:M22) -> 0
A24: Работа в аренде у других предприятий
A25: РДК 250 | B25: АКІМ ТОВ | C25: 450 | G25: 19 | H25: 25000 | J25: =5573.81 -> 5573.81 | N25: =SUM(J25:M25) -> 5573.81 | O25: 25000 | R25: 19426.19
A26: Экскаватор JCB 220 | B26: ТОВ Металургбуд | C26: 1450 | G26: 28 | H26: 64380 | J26: =12053.6/($G$5+$G$26)*G26 -> 4272.162 | M26: =17630/($G$5+$G$26)*G26 -> 6248.6076 | N26: =SUM(J26:M26) -> 10520.77 | O26: 64380 | R26: 53859.23

Sheet Бюджет Март 23
A1: Техника | B1: Объект | C1: Кол-во смен | D1: Ст-сть за 1 час, грн | E1: сумма за месяц, грн | F1: предоплата 60%, грн | G1: Сумма к взаиморасчетам по Январю, грн | H1: Незарегестрированный НДС | I1: Итого, сумма предоплаты за Февраль 2023, грн.
A2: Телескоп 1 | B2: Староконстантинов | C2: 27 | D2: 467.63 | E2: =C2*8*D2 -> 101008.08 | F2: =E2*0.6 -> 60604.848
A3: Телескоп 4 | B3: Староконстантинов | C3: 27 | D3: 467.63 | E3: =C3*8*D3 -> 101008.08 | F3: =E3*0.6 -> 60604.848
A4: Экскаватор JCB 220 | B4: Староконстантинов | C4: 0 | D4: 995.97 | E4: =C4*8*D4 -> 0 | F4: =E4*0.6 -> 0
A5: МАЗ 264 | B5: Староконстантинов | C5: 15 | D5: 355.37 | E5: =C5*8*D5 -> 42644.4 | F5: =E5*0.6 -> 25586.64
A6: Клинцы | B6: Староконстантинов | C6: 27 | D6: 430.84 | E6: =C6*8*D6 -> 93061.44 | F6: =E6*0.6 -> 55836.864
A7: Автокран XCMG | B7: Староконстантинов | C7: 27 | D7: 563.19 | E7: =C7*8*D7 -> 121649.04 | F7: =E7*0.6 -> 72989.424
A8: Вместе по объекту Староконстантинов | E8: =SUM(E2:E7) -> 459371.04 | F8: =SUM(F2:F7) -> 275622.62 | G8: ='Февраль23 факт '!P9 -> -87495.95 | H8: =-7504.46-'Бюджет Февраль 23'!H8 -> 23683.39 | I8: =F8+G8+H8 -> 211810.06
A9: Экскаватор JCB 2013 | B9: МЭЗ СЕТИ | C9: 20 | D9: 496.93 | E9: =C9*8*D9 -> 79508.8 | F9: =E9*0.6 -> 47705.28
A10: Телескоп 2 | B10: МЭЗ СЕТИ | C10: 5 | D10: 467.63 | E10: =C10*8*D10 -> 18705.2 | F10: =E10*0.6 -> 11223.12
A11: МАЗ 265 | B11: МЭЗ СЕТИ | C11: 10 | D11: 355.37 | E11: =C11*8*D11 -> 28429.6 | F11: =E11*0.6 -> 17057.76
A12: Вместе по объекту МЭЗ СЕТИ | E12: =SUM(E9:E11) -> 126643.6 | F12: =SUM(F9:F11) -> 75986.16 | G12: ='Февраль23 факт '!P13 -> -35830.956 | H12: -6003.55 | I12: =F12+G12+H12 -> 34151.654
A13: Телескоп 5 | B13: Ретал | C13: 24 | D13: 467.63 | E13: =C13*8*D13 -> 89784.96 | F13: =E13*0.6 -> 53870.976
A14: Экскаватор JCB 2008 | B14: Ретал | C14: 24 | D14: 496.93 | E14: =C14*8*D14 -> 95410.56 | F14: =E14*0.6 -> 57246.336
A15: Haulotte | B15: Ретал | C15: 20 | D15: 802.86 | E15: =C15*D15 -> 16057.2 | F15: =E15*0.6 -> 9634.32
A16: Вместе по объекту Ретал | E16: =SUM(E13:E15) -> 201252.72 | F16: =SUM(F13:F15) -> 120751.63 | G16: ='Февраль23 факт '!P17 -> -31880.42 | H16: =-2961.48-'Бюджет Февраль 23'!H19 -> 15777.54 | I16: =F16+G16+H16 -> 104648.75
A17: Ротор Пегасус | B17: Биогаз | C17: 0 | D17: 592.98 | E17: =C17*8*D17 -> 0 | F17: =E17*0.6 -> 0
A18: Экскаватор JCB 2007 | B18: Биогаз | C18: 0 | D18: 496.93 | E18: =C18*8*D18 -> 0 | F18: =E18*0.6 -> 0
A19: Самосвал Камаз | B19: Биогаз | C19: 0 | D19: 430.84 | E19: =C19*8*D19 -> 0 | F19: =E19*0.6 -> 0
A20: Вресте по объекту Биогаз | E20: =SUM(E17:E19) -> 0 | F20: =SUM(F17:F19) -> 0 | G20: ='Февраль23 факт '!P21 -> 18689.24 | H20: =-1583.12-'Бюджет Февраль 23'!H23-4543.14 -> 25866.65 | I20: =F20+G20+H20 -> 44555.89
C22: =SUM(A2:C19) -> 226 | E22: =E8+E12+E16+E20 -> 787267.36 | F22: =F8+F12+F16+F20 -> 472360.42 | G22: =G8+G12+G16+G20 -> -136518.09 | H22: =H8+H12+H16+H20 -> 59324.03 | I22: =I8+I12+I16+I20 -> 395166.36

Sheet Март прогноз 28_03
G1: Факт | I1: Сумма к взаиморасчетам, грн | J1: Оплаты с Индастриалбуд | O1: Поступление на Индастриал от сторонних заказчиков, грн | P1: Сумма к взаиморасчетам с учетом движения ДС на р/с Индастриалбуд, грн
A2: Техника | B2: Объект | C2: Ст-сть за 1 час, грн | D2: Кол-во смен | E2: сумма за месяц, грн | F2: предоплата 60%, грн | G2: Кол-во Часов | H2: Сума | J2: ЗП механизаторов с налогами, грн. | K2: Разрешительная документация, грн. | L2: Страховка, грн | M2: Топливо, грн | N2: вместе оплаченно, грн
A3: Телескоп 1 | B3: Староконстантинов | C3: 467.63 | D3: 27 | E3: =C3*D3*8 -> 101008.08 | F3: =E3*0.6 -> 60604.848 | G3: 224 | H3: =C3*G3 -> 104749.12 | J3: 23180 | M3: =13939.2+6756 -> 20695.2 | N3: =SUM(J3:M3) -> 43875.2 | Q3: =P9/($G$3+$G$4+$G$7+$G$8)*G3 -> 15191.451
A4: Телескоп 4 | B4: Староконстантинов | C4: 467.63 | D4: 27 | E4: =C4*D4*8 -> 101008.08 | F4: =E4*0.6 -> 60604.848 | G4: 213 | H4: =C4*G4 -> 99605.19 | J4: 23180 | M4: =9400+6424 -> 15824 | N4: =SUM(J4:M4) -> 39004 | Q4: =P9/($G$3+$G$4+$G$7+$G$8)*G4 -> 14445.443
A5: Экскаватор JCB 220 | B5: Староконстантинов | C5: 995.97 | D5: 0 | E5: =C5*D5*8 -> 0 | F5: =E5*0.6 -> 0 | H5: =C5*G5 -> 0 | M5: 0 | N5: =SUM(J5:M5) -> 0 | Q5: =P9/($G$3+$G$4+$G$7+$G$8)*G5 -> 0
A6: МАЗ 264 | B6: Староконстантинов | C6: 355.37 | D6: 15 | E6: =C6*D6*8 -> 42644.4 | F6: =E6*0.6 -> 25586.64 | H6: =C6*G6 -> 0 | M6: 0 | N6: =SUM(J6:M6) -> 0 | Q6: =P9/($G$3+$G$4+$G$7+$G$8)*G6 -> 0
A7: Клинцы | B7: Староконстантинов | C7: 430.84 | D7: 27 | E7: =C7*D7*8 -> 93061.44 | F7: =E7*0.6 -> 55836.864 | G7: 220 | H7: =C7*G7 -> 94784.8 | J7: 11590 | M7: 6690 | N7: =SUM(J7:M7) -> 18280 | Q7: =P9/($G$3+$G$4+$G$7+$G$8)*G7 -> 14920.175
A8: Автокран XCMG | B8: Староконстантинов | C8: 563.19 | D8: 27 | E8: =C8*D8*8 -> 121649.04 | F8: =E8*0.6 -> 72989.424 | G8: 214 | H8: =C8*G8 -> 120522.66 | J8: 11590 | M8: =20944.14+6400 -> 27344.14 | N8: =SUM(J8:M8) -> 38934.14 | Q8: =P9/($G$3+$G$4+$G$7+$G$8)*G8 -> 14513.262
A9: Вместе по объекту Староконстантинов | E9: =SUM(E3:E8) -> 459371.04 | F9: =SUM(F3:F8) -> 275622.62 | H9: =SUM(H3:H8) -> 419661.77 | I9: =H9-F9 -> 144039.15 | N9: =SUM(N3:N8) -> 140093.34 | O9: =SUM(O3:O8) -> 0 | P9: =I9-N9+O9+F9*0.2 -> 59070.331
A10: Экскаватор JCB 2013 | B10: МЭЗ СЕТИ | C10: 496.93 | D10: 20 | E10: =C10*D10*8 -> 79508.8 | F10: =E10*0.6 -> 47705.28 | G10: 196 | H10: =C10*G10 -> 97398.28 | J10: 11590 | M10: 5170 | N10: =SUM(J10:M10) -> 16760 | Q10: =$P$13/($G$10+$G$11+$G$12)*G10 -> 33622.76
A11: Телескоп 2 | B11: МЭЗ СЕТИ | C11: 467.63 | D11: 5 | E11: =C11*D11*8 -> 18705.2 | F11: =E11*0.6 -> 11223.12 | G11: 95 | H11: =C11*G11 -> 44424.85 | J11: 11590 | M11: =4499+1379.7 -> 5878.7 | N11: =SUM(J11:M11) -> 17468.7 | Q11: =$P$13/($G$10+$G$11+$G$12)*G11 -> 16296.746
A12: МАЗ 265 | B12: МЭЗ СЕТИ | C12: 355.37 | D12: 10 | E12: =C12*D12*8 -> 28429.6 | F12: =E12*0.6 -> 17057.76 | G12: 95 | H12: =C12*G12 -> 33760.15 | J12: 11590 | M12: 2759.4 | N12: =SUM(J12:M12) -> 14349.4 | Q12: =$P$13/($G$10+$G$11+$G$12)*G12 -> 16296.746
A13: Вместе по объекту МЭЗ СЕТИ | E13: =SUM(E10:E12) -> 126643.6 | F13: =SUM(F10:F12) -> 75986.16 | H13: =SUM(H10:H12) -> 175583.28 | I13: =H13-F13 -> 99597.12 | N13: =SUM(N10:N12) -> 48578.1 | O13: =SUM(O10:O12) -> 0 | P13: =I13-N13+O13+F13*0.2 -> 66216.252
A14: Телескоп 5 | B14: Ретал | C14: 467.63 | D14: 24 | E14: =C14*D14*8 -> 89784.96 | F14: =E14*0.6 -> 53870.976 | G14: 188 | H14: =C14*G14 -> 87914.44 | J14: 23180 | M14: 33024.97 | N14: =SUM(J14:M14) -> 56204.97 | Q14: =$P$20/($G$14+$G$15+$G$16+$G$17+$G$18+$G$19)*G14 -> -25455.865
A15: Экскаватор JCB | B15: Ретал | C15: 496.93 | E15: =C15*D15 -> 0 | F15: =E15*0.6 -> 0 | G15: 32 | H15: =C15*G15 -> 15901.76 | J15: 11590 | M15: 4700 | N15: =SUM(J15:M15) -> 16290 | Q15: =$P$20/($G$14+$G$15+$G$16+$G$17+$G$18+$G$19)*G15 -> -4332.9131
A16: Экскаватор JCB 2008 | B16: Ретал | C16: 496.93 | D16: 24 | E16: =C16*D16*8 -> 95410.56 | F16: =E16*0.6 -> 57246.336 | G16: 25 | H16: =C16*G16 -> 12423.25 | J16: 11590 | M16: 30717 | N16: =SUM(J16:M16) -> 42307 | Q16: =$P$20/($G$14+$G$15+$G$16+$G$17+$G$18+$G$19)*G16 -> -3385.0884
A17: Самосвал Камаз | B17: Ретал | C17: 430.84 | E17: =C17*D17 -> 0 | F17: =E17*0.6 -> 0 | G17: 155 | H17: =C17*G17 -> 66780.2 | J17: 11693.15 | M17: 28456.74 | N17: =SUM(J17:M17) -> 40149.89 | Q17: =$P$20/($G$14+$G$15+$G$16+$G$17+$G$18+$G$19)*G17 -> -20987.548
A18: Виброкаток | B18: Ретал | C18: 544.05 | E18: =C18*D18 -> 0 | F18: =E18*0.6 -> 0 | G18: 20 | H18: =C18*G18 -> 10881 | Q18: =$P$20/($G$14+$G$15+$G$16+$G$17+$G$18+$G$19)*G18 -> -2708.0707
A19: Haulotte | B19: Ретал | C19: 802.86 | D19: 20 | E19: =C19*D19 -> 16057.2 | F19: =E19*0.6 -> 9634.32 | G19: 24 | H19: =C19*G19 -> 19268.64 | N19: =SUM(J19:M19) -> 0 | Q19: =$P$20/($G$14+$G$15+$G$16+$G$17+$G$18+$G$19)*G19 -> -3249.6848
A20: Вместе по объекту Ретал | E20: =SUM(E14:E19) -> 201252.72 | F20: =SUM(F14:F19) -> 120751.63 | H20: =SUM(H14:H19) -> 213169.29 | I20: =H20-F20 -> 92417.658 | N20: =SUM(N14:N19) -> 154951.86 | O20: =SUM(O14:O19) -> 0 | P20: =I20-N20+O20+F20*0.02 -> -60119.169
A21: Ротор Пегасус | B21: Биогаз | C21: 592.98 | D21: 0 | E21: =C21*D21 -> 0 | F21: =E21*0.6 -> 0 | G21: 30 | H21: =C21*G21 -> 17789.4 | J21: 11590 | M21: 9996.43 | N21: =SUM(J21:M21) -> 21586.43 | Q21: =$P$24/($G$21+$G$22+$G$23)*G21 -> 2118.6848
A22: Экскаватор JCB | B22: Биогаз | C22: 496.93 | D22: 0 | E22: =C22*D22 -> 0 | F22: =E22*0.6 -> 0 | G22: 95 | H22: =C22*G22 -> 47208.35 | J22: 11590 | M22: 24392.44 | N22: =SUM(J22:M22) -> 35982.44 | Q22: =$P$24/($G$21+$G$22+$G$23)*G22 -> 6709.1685
A23: Самосвал Камаз | B23: Биогаз | C23: 430.84 | D23: 0 | E23: =C23*D23 -> 0 | F23: =E23*0.6 -> 0 | G23: 13 | H23: =C23*G23 -> 5600.92 | J23: 896.85 | M23: 2387 | N23: =SUM(J23:M23) -> 3283.85 | Q23: =$P$24/($G$21+$G$22+$G$23)*G23 -> 918.09674
A24: Вресте по объекту Биогаз | E24: =SUM(E21:E23) -> 0 | F24: =SUM(F21:F23) -> 0 | H24: =SUM(H21:H23) -> 70598.67 | I24: =H24-F24 -> 70598.67 | N24: =SUM(N21:N23) -> 60852.72 | O24: =SUM(O21:O23) -> 0 | P24: =I24-N24+O24 -> 9745.95
H25: 50000 | N25: =SUM(J25:M25) -> 0
D26: =SUM(C3:D23) -> 9586.55 | E26: =E9+E13+E20+E24 -> 787267.36 | F26: =F9+F13+F20+F24 -> 472360.42
G28: 19 | H28: 25000 | J28: =5573.81 -> 5573.81 | N28: =SUM(J28:M28) -> 5573.81 | O28: 25000
G29: 28 | H29: 64380 | J29: =12053.6/(#REF!+#REF!)*G29 -> #REF! | M29: =17630/(#REF!+#REF!)*G29 -> #REF! | N29: =SUM(J29:M29) -> #REF! | O29: 64380

Sheet Свод Спецтехника
J1: Ноябрь | S1: Декабрь | AC1: 44927 | AM1: 44958 | AW1: 44986 | BG1: 45017 | BQ1: 45047 | CA1: 45078 | CK1: 45108 | CU1: 45139 | DF1: 45170 | DT1: 45200 | EH1: 45231 | EW1: 45261 | FL1: 45292 | GA1: 45323 | GQ1: 45352 | HG1: 45383 | HW1: 45413 | IM1: 45444 | JC1: 45474 | JS1: 45505 | KI1: 45536 | KY1: 45566 | LO1: 45597 | ME1: 45627 | MU1: 45658 | NK1: 45689 | OA1: 45717 | OQ1: 45748 | PG1: 45778
A2: Техника | B2: Имя техники в отчете | C2: ="Позиция по объектам на "&TEXT(Позиция!D2,"ДД.ММ.ГГ") -> Позиция по объектам на 28.11.23 | D2: GPS | E2: Объект | F2: Ст-сть за 1 час, грн до 30.09.23 | G2: Ст-сть за 1 час, грн с 01.10.23 | H2: Ст-сть за 1 час, грн с 01.07.24 | I2: Ст-сть за 1 час, грн с 01.11.24 | J2: Фактически отработано | L2: Фактически оплачено | M2: Затраты Индастриала, грн | Q2: Поступление на Индастриал от сторонних заказчиков, грн | R2: Результат ноября, грн | S2: Фактически отработано | U2: Фактически оплачено | V2: Затраты Индастриала, грн | Z2: Поступление на Индастриал от сторонних заказчиков, грн | AA2: Результат декабря, грн | AB2: Результат накопительно, грн | AC2: Фактически отработано | AE2: Фактически оплачено | AF2: Затраты Индастриала, грн | AJ2: Поступление на Индастриал от сторонних заказчиков, грн | AK2: Результат январь, грн | AL2: Результат накопительно, грн | AM2: Фактически отработано | AO2: Фактически оплачено | AP2: Затраты Индастриала, грн | AT2: Поступление на Индастриал от сторонних заказчиков, грн | AU2: Результат февраль, грн | AV2: Результат накопительно, грн | AW2: Фактически отработано | AY2: Фактически оплачено | AZ2: Затраты Индастриала, грн | BD2: Поступление на Индастриал от сторонних заказчиков, грн | BE2: Результат март, грн | BF2: Результат накопительно, грн | BG2: Фактически отработано | BI2: Фактически оплачено | BJ2: Затраты Индастриала, грн | BN2: Поступление на Индастриал от сторонних заказчиков, грн | BO2: Результат апрель, грн | BP2: Результат накопительно, грн | BQ2: Фактически отработано | BS2: Фактически оплачено | BT2: Затраты Индастриала, грн | BX2: Поступление на Индастриал от сторонних заказчиков, грн | BY2: Результат май, грн | BZ2: Результат накопительно, грн | CA2: Фактически отработано | CC2: Фактически оплачено | CD2: Затраты Индастриала, грн | CH2: Поступление на Индастриал от сторонних заказчиков, грн | CI2: Результат июнь, грн | CJ2: Результат накопительно, грн | CK2: Фактически отработано | CM2: Фактически оплачено | CN2: Затраты Индастриала, грн | CR2: Поступление на Индастриал от сторонних заказчиков, грн | CS2: Результат июль, грн | CT2: Результат накопительно, грн | CU2: Фактически отработано | CW2: Фактически оплачено | CX2: Затраты Индастриала, грн | DB2: Поступление на Индастриал от сторонних заказчиков, грн | DC2: Результат августа, грн | DD2: Корректировка по единицам техники, грн | DE2: Результат накопительно, грн | DF2: Фактически отработано | DH2: Фактически оплачено | DI2: Затраты Индастриала, грн | DP2: Поступление на Индастриал от сторонних заказчиков, грн | DQ2: Результат Сентябрь 2023, грн | DR2: Корректировка по единицам техники, грн | DS2: Результат накопительно, грн | DT2: Фактически отработано | DV2: Фактически оплачено | DW2: Затраты Индастриала, грн | ED2: Поступление на Индастриал от сторонних заказчиков, грн | EE2: Результат Октябрь 2023, грн | EF2: Корректировка по единицам техники, грн | EG2: Результат накопительно, грн | EH2: Фактически отработано | EJ2: Фактически оплачено | EK2: Затраты Индастриала, грн | ES2: Поступление на Индастриал от сторонних заказчиков, грн | ET2: Результат Ноябрь 2023, грн | EU2: Корректировка по единицам техники, грн | EV2: Результат накопительно, грн | EW2: Фактически отработано | EY2: Фактически оплачено | EZ2: Затраты Индастриала, грн | FH2: Поступление на Индастриал от сторонних заказчиков, грн | FI2: Результат Декабрь 2023, грн | FJ2: Корректировка по единицам техники, грн | FK2: Результат накопительно, грн | FL2: Фактически отработано | FN2: Фактически оплачено | FO2: Затраты Индастриала, грн | FW2: Поступление на Индастриал от сторонних заказчиков, грн | FX2: Результат Январь 2024, грн | FY2: Корректировка по единицам техники, грн | FZ2: Результат накопительно, грн | GA2: Фактически отработано | GC2: Фактически оплачено | GD2: Затраты Индастриала, грн | GM2: Поступление на Индастриал от сторонних заказчиков, грн | GN2: Результат Февраль 2024, грн | GO2: Корректировка по единицам техники, грн | GP2: Результат накопительно, грн | GQ2: Фактически отработано | GS2: Фактически оплачено | GT2: Затраты Индастриала, грн | HC2: Поступление на Индастриал от сторонних заказчиков, грн | HD2: Результат Март 2024, грн | HE2: Корректировка по единицам техники, грн | HF2: Результат накопительно, грн | HG2: Фактически отработано | HI2: Фактически оплачено | HJ2: Затраты Индастриала, грн | HS2: Поступление на Индастриал от сторонних заказчиков, грн | HT2: Результат Апрель 2024, грн | HU2: Корректировка по единицам техники, грн | HV2: Результат накопительно, грн | HW2: Фактически отработано | HY2: Фактически оплачено | HZ2: Затраты Индастриала, грн | II2: Поступление на Индастриал от сторонних заказчиков, грн | IJ2: Результат Май 2024, грн | IK2: Корректировка по единицам техники, грн | IL2: Результат накопительно, грн | IM2: Фактически отработано | IO2: Фактически оплачено | IP2: Затраты Индастриала, грн | IY2: Поступление на Индастриал от сторонних заказчиков, грн | IZ2: Результат Июнь 2024, грн | JA2: Корректировка по единицам техники, грн | JB2: Результат накопительно, грн | JC2: Фактически отработано | JE2: Фактически оплачено | JF2: Затраты Индастриала, грн | JO2: Поступление на Индастриал от сторонних заказчиков, грн | JP2: Результат Июль 2024, грн | JQ2: Корректировка по единицам техники, грн | JR2: Результат накопительно, грн | JS2: Фактически отработано | JU2: Фактически оплачено | JV2: Затраты Индастриала, грн | KE2: Поступление на Индастриал от сторонних заказчиков, грн | KF2: Результат Август 2024, грн | KG2: Корректировка по единицам техники, грн | KH2: Результат накопительно, грн | KI2: Фактически отработано | KK2: Фактически оплачено | KL2: Затраты Индастриала, грн | KU2: Поступление на Индастриал от сторонних заказчиков, грн | KV2: Результат Сентябрь 2024, грн | KW2: Корректировка по единицам техники, грн | KX2: Результат накопительно, грн | KY2: Фактически отработано | LA2: Фактически оплачено | LB2: Затраты Индастриала, грн | LK2: Поступление на Индастриал от сторонних заказчиков, грн | LL2: Результат Октябрь 2024, грн | LM2: Корректировка по единицам техники, грн | LN2: Результат накопительно, грн | LO2: Фактически отработано | LQ2: Фактически оплачено | LR2: Затраты Индастриала, грн | MA2: Поступление на Индастриал от сторонних заказчиков, грн | MB2: Результат Ноябрь 2024, грн | MC2: Корректировка по единицам техники, грн | MD2: Результат накопительно, грн | ME2: Фактически отработано | MG2: Фактически оплачено | MH2: Затраты Индастриала, грн | MQ2: Поступление на Индастриал от сторонних заказчиков, грн | MR2: Результат Декабрь 2024, грн | MS2: Корректировка по единицам техники, грн | MT2: Результат накопительно, грн | MU2: Фактически отработано | MW2: Фактически оплачено | MX2: Затраты Индастриала, грн | NG2: Поступление на Индастриал от сторонних заказчиков, грн | NH2: Результат Январь 2024, грн | NI2: Корректировка по единицам техники, грн | NJ2: Результат накопительно, грн | NK2: Фактически отработано | NM2: Фактически оплачено | NN2: Затраты Индастриала, грн | NW2: Поступление на Индастриал от сторонних заказчиков, грн | NX2: Результат Февраль 2025, грн | NY2: Корректировка по единицам техники, грн | NZ2: Результат накопительно, грн | OA2: Фактически отработано | OC2: Фактически оплачено | OD2: Затраты Индастриала, грн | OM2: Поступление на Индастриал от сторонних заказчиков, грн | ON2: Результат Март 2025, грн | OO2: Корректировка по единицам техники, грн | OP2: Результат накопительно, грн | OQ2: Фактически отработано | OS2: Фактически оплачено | OT2: Затраты Индастриала, грн | PC2: Поступление на Индастриал от сторонних заказчиков, грн | PD2: Результат Апрель 2025, грн | PE2: Корректировка по единицам техники, грн | PF2: Результат накопительно, грн | PG2: План на май 2025 | PI2: Сумма предоплаты за май 2025 | PJ2: Результат накопительно, грн | PL2: Счет на Май 2025 предоплату [100 %]
J3: Часов | K3: грн. | L3: грн | M3: ЗП | N3: Топливо | O3: Прочие | P3: Всего | S3: Часов | T3: грн. | U3: грн | V3: ЗП | W3: Топливо | X3: Прочие | Y3: Всего | AC3: Часов | AD3: грн. | AE3: грн | AF3: ЗП | AG3: Топливо | AH3: Прочие | AI3: Всего | AM3: Часов | AN3: грн. | AO3: грн | AP3: ЗП | AQ3: Топливо | AR3: Прочие | AS3: Всего | AW3: Часов | AX3: грн. | AY3: грн | AZ3: ЗП | BA3: Топливо | BB3: Прочие | BC3: Всего | BG3: Часов | BH3: грн. | BI3: грн | BJ3: ЗП | BK3: Топливо | BL3: Прочие | BM3: Всего | BQ3: Часов | BR3: грн. | BS3: грн | BT3: ЗП | BU3: Топливо | BV3: Прочие | BW3: Всего | CA3: Часов | CB3: грн. | CC3: грн | CD3: ЗП | CE3: Топливо | CF3: Прочие | CG3: Всего | CK3: Часов | CL3: грн. | CM3: грн | CN3: ЗП | CO3: Топливо | CP3: Прочие | CQ3: Всего | CU3: Часов | CV3: грн. | CW3: грн | CX3: ЗП | CY3: Топливо | CZ3: Прочие | DA3: Всего | DF3: Часов | DG3: грн. | DH3: грн | DI3: ЗП | DJ3: ВОГ | DK3: ОККО | DL3: КАРТМАРКЕТ | DM3: Топливо | DN3: Прочие | DO3: Всего | DT3: Часов | DU3: грн. | DV3: грн | DW3: ЗП | DX3: ВОГ | DY3: ОККО | DZ3: КАРТМАРКЕТ | EA3: Топливо | EB3: Прочие | EC3: Всего | EH3: Часов | EI3: грн. | EJ3: грн | EK3: ЗП | EL3: ВОГ | EM3: КЛО (Глобал Сейд) | EN3: ОККО | EO3: КАРТМАРКЕТ | EP3: Топливо | EQ3: Прочие | ER3: Всего | EW3: Часов | EX3: грн. | EY3: грн | EZ3: ЗП | FA3: ВОГ | FB3: КЛО (Глобал Сейд) | FC3: ОККО | FD3: КАРТМАРКЕТ | FE3: Топливо | FF3: Прочие | FG3: Всего | FL3: Часов | FM3: грн. | FN3: грн | FO3: ЗП | FP3: ВОГ | FQ3: КЛО (Глобал Сейд) | FR3: ОККО | FS3: КАРТМАРКЕТ | FT3: Топливо | FU3: Прочие | FV3: Всего | GA3: Часов | GB3: грн. | GC3: грн | GD3: ЗП | GE3: ВОГ | GF3: КЛО (Глобал Сейд) | GG3: АМИК | GH3: ОККО | GI3: КАРТМАРКЕТ | GJ3: Топливо | GK3: Прочие | GL3: Всего | GQ3: Часов | GR3: грн. | GS3: грн | GT3: ЗП | GU3: ВОГ | GV3: КЛО (Глобал Сейд) | GW3: АМИК | GX3: ОККО | GY3: КАРТМАРКЕТ | GZ3: Топливо | HA3: Прочие | HB3: Всего | HG3: Часов | HH3: грн. | HI3: грн | HJ3: ЗП | HK3: ВОГ | HL3: КЛО (Глобал Сейд) | HM3: АМИК | HN3: ОККО | HO3: КАРТМАРКЕТ | HP3: Топливо | HQ3: Прочие | HR3: Всего | HW3: Часов | HX3: грн. | HY3: грн | HZ3: ЗП | IA3: ВОГ | IB3: КЛО (Глобал Сейд) | IC3: АМИК | ID3: ОККО | IE3: КАРТМАРКЕТ | IF3: Топливо | IG3: Прочие | IH3: Всего | IM3: Часов | IN3: грн. | IO3: грн | IP3: ЗП | IQ3: ВОГ | IR3: КЛО (Глобал Сейд) | IS3: АМИК | IT3: ОККО | IU3: Авиас (ТОВ "ТЕНЕГІЯ") | IV3: Топливо | IW3: Прочие | IX3: Всего | JC3: Часов | JD3: грн. | JE3: грн | JF3: ЗП | JG3: ВОГ | JH3: КЛО (Глобал Сейд) | JI3: АМИК | JJ3: ОККО | JK3: Авиас (ТОВ "ТЕНЕГІЯ") | JL3: Топливо | JM3: Прочие | JN3: Всего | JS3: Часов | JT3: грн. | JU3: грн | JV3: ЗП | JW3: ВОГ | JX3: КЛО (Глобал Сейд) | JY3: АМИК | JZ3: ОККО | KA3: Авиас (ТОВ "ТЕНЕГІЯ") | KB3: Топливо | KC3: Прочие | KD3: Всего | KI3: Часов | KJ3: грн. | KK3: грн | KL3: ЗП | KM3: ВОГ | KN3: КЛО (Глобал Сейд) | KO3: АМИК | KP3: ОККО | KQ3: Авиас (ТОВ "ТЕНЕГІЯ") | KR3: Топливо | KS3: Прочие | KT3: Всего | KY3: Часов | KZ3: грн. | LA3: грн | LB3: ЗП | LC3: ВОГ | LD3: КЛО (Глобал Сейд) | LE3: АМИК | LF3: ОККО | LG3: Авиас (ТОВ "ТЕНЕГІЯ") | LH3: Топливо | LI3: Прочие | LJ3: Всего | LO3: Часов | LP3: грн. | LQ3: грн | LR3: ЗП | LS3: ВОГ | LT3: КЛО (Глобал Сейд) | LU3: АМИК | LV3: ОККО | LW3: Авиас (ТОВ "ТЕНЕГІЯ") | LX3: Топливо | LY3: Прочие | LZ3: Всего | ME3: Часов | MF3: грн. | MG3: грн | MH3: ЗП | MI3: ВОГ | MJ3: БВС | MK3: АМИК | ML3: ОККО | MM3: Авиас (ТОВ "ТЕНЕГІЯ") | MN3: Топливо | MO3: Прочие | MP3: Всего | MU3: Часов | MV3: грн. | MW3: грн | MX3: ЗП | MY3: ВОГ | MZ3: БВС | NA3: АМИК | NB3: ОККО | NC3: Авиас (ТОВ "ТЕНЕГІЯ") | ND3: Топливо | NE3: Прочие | NF3: Всего | NK3: Часов | NL3: грн. | NM3: грн | NN3: ЗП | NO3: ВОГ | NP3: БВС | NQ3: АМИК | NR3: ОККО | NS3: Авиас (ТОВ "ТЕНЕГІЯ") | NT3: Топливо | NU3: Прочие | NV3: Всего | OA3: Часов | OB3: грн. | OC3: грн | OD3: ЗП | OE3: ВОГ | OF3: БВС | OG3: АМИК | OH3: ОККО | OI3: Авиас (ТОВ "ТЕНЕГІЯ") | OJ3: Топливо | OK3: Прочие | OL3: Всего | OQ3: Часов | OR3: грн. | OS3: грн | OT3: ЗП | OU3: ВОГ | OV3: БВС | OW3: АМИК | OX3: ОККО | OY3: Авиас (ТОВ "ТЕНЕГІЯ") | OZ3: Топливо | PA3: Прочие | PB3: Всего | PG3: Часов | PH3: грн.
A4: Телескоп 1 | B4: Телескоп №1 | C4: =INDEX(Позиция!$D$3:$D$22,MATCH(A4,Позиция!$C$3:$C$22,0)) -> Староконстантинов | D4: =INDEX(Позиция!$E$3:$E$22,MATCH(A4,Позиция!$C$3:$C$22,0)) -> 1 | E4: Староконстантинов | F4: 467.63 | G4: 494.88 | H4: 579.13 | J4: 155 | K4: =F4*J4 -> 72482.65 | L4: 51649.53 | M4: -8187.98 | N4: -44609.48 | P4: =SUM(M4:O4) -> -52797.46 | R4: =K4-L4+P4+Q4 -> -31964.34 | S4: 255 | T4: =F4*S4 -> 119245.65 | U4: =$U$16/$T$16*T4 -> 1646.2399 | V4: -11173.72 | W4: -10332.94 | Y4: =SUM(V4:X4) -> -21506.66 | AA4: =T4-U4+Y4+Z4 -> 96092.75 | AB4: =R4+AA4 -> 64128.41 | AC4: 152 | AD4: =F4*AC4 -> 71079.76 | AE4: =$AE$16/$AD$16*AD4 -> 67984.494 | AF4: -11420.04 | AG4: -26255.13 | AI4: =SUM(AF4:AH4) -> -37675.17 | AK4: =AD4-AE4+AI4+AJ4 -> -34579.904 | AL4: =AB4+AK4 -> 29548.506 | AM4: 163 | AN4: =F4*AM4 -> 76223.69 | AO4: =$AO$16/$AN$16*AN4 -> 34348.234 | AP4: =-12053.6 -> -12053.6 | AQ4: -21695.63 | AS4: =SUM(AP4:AR4) -> -33749.23 | AU4: =AN4-AO4+AS4+AT4 -> 8126.2261 | AV4: =AL4+AU4 -> 37674.732 | AW4: 221 | AX4: =F4*AW4 -> 103346.23 | AY4: =$AY$16/$AX$16*AX4 -> 76945.601 | AZ4: =-11590-5985 -> -17575 | BA4: =-(13939.2+9439) -> -23378.2 | BC4: =SUM(AZ4:BB4) -> -40953.2 | BE4: =AX4-AY4+BC4+BD4 -> -14552.571 | BF4: =AV4+BE4 -> 23122.161 | BG4: =апрель!E3+апрель!E4 -> 96 | BH4: =F4*BG4 -> 44892.48 | BI4: =$BI$16/($BG$4+$BG$5+$BG$13+$BG$15)*BG4 -> 53583.066 | BJ4: =-апрель!N3-апрель!O3-апрель!P3-апрель!N4-апрель!O4-апрель!P4 -> -23054.13 | BK4: -16216.4 | BM4: =SUM(BJ4:BL4) -> -39270.53 | BO4: =BH4-BI4+BM4+BN4 -> -47961.116 | BP4: =BF4+BO4 -> -24838.955 | BQ4: 194 | BR4: =F4*BQ4 -> 90720.22 | BS4: 0 | BT4: =-май!C23 -> -16979.19 | BU4: =май!H9 -> -8200 | BW4: =SUM(BT4:BV4) -> -25179.19 | BY4: =BR4-BS4+BW4+BX4 -> 65541.03 | BZ4: =BP4+BY4 -> 40702.075 | CA4: 33 | CB4: =$F4*CA4 -> 15431.79 | CC4: =$CC$16/SUM($CA$4:$CA$15)*CA4 -> 18857.25 | CD4: -17568.34 | CE4: -5354.78 | CG4: =SUM(CD4:CF4) -> -22923.12 | CI4: =CB4-CC4+CG4+CH4 -> -26348.58 | CJ4: =BZ4+CI4 -> 14353.495 | CL4: =$F4*CK4 -> 0 | CM4: =$CM$16/SUM($CK$4:$CK$15)*CK4 -> 0 | CP4: -4140 | CQ4: =SUM(CN4:CP4) -> -4140 | CS4: =CL4-CM4+CQ4+CR4 -> -4140 | CT4: =CJ4+CS4 -> 10213.495 | CV4: =$F4*CU4 -> 0 | CW4: =$CW$16/SUM($CU$4:$CU$15)*CU4 -> 0 | DA4: =SUM(CX4:CZ4) -> 0 | DC4: =CV4-CW4+DA4+DB4 -> 0 | DE4: =ROUND(CT4+DC4+DD4,2) -> 10213.5 | DG4: =$F4*DF4 -> 0 | DO4: =DI4+DM4+DN4 -> 0 | DQ4: =DG4-DH4+DO4+DP4 -> 0 | DS4: =ROUND(DE4+DQ4+DR4,2) -> 10213.5 | DU4: =$G4*DT4 -> 0 | DV4: =IFERROR(ROUND(DT4/DT16*DV16,2),0) -> 0 | EA4: =SUM(DX4:DZ4) -> 0 | EC4: =DW4+EA4+EB4 -> 0 | EE4: =DU4-DV4+EC4+ED4 -> 0 | EF4: -10213.5 | EG4: =ROUND(DS4+EE4+EF4,2) -> 0 | EI4: =$G4*EH4 -> 0 | EJ4: =IFERROR(ROUND(EH4/EH16*EJ16,2),0) -> 0 | EP4: =SUM(EL4:EO4) -> 0 | ER4: =EK4+EP4+EQ4 -> 0 | ET4: =EI4-EJ4+ER4+ES4 -> 0 | EV4: =ROUND(EG4+ET4+EU4,2) -> 0 | EX4: =$G4*EW4 -> 0 | EY4: =IFERROR(ROUND(EW4/EW16*EY16,2),0) -> 0 | FE4: =SUM(FA4:FD4) -> 0 | FG4: =EZ4+FE4+FF4 -> 0 | FI4: =EX4-EY4+FG4+FH4 -> 0 | FK4: =ROUND(EV4+FI4+FJ4,2) -> 0 | FM4: =$G4*FL4 -> 0 | FN4: =IFERROR(ROUND(FL4/FL16*FN16,2),0) -> 0 | FT4: =SUM(FP4:FS4) -> 0 | FV4: =FO4+FT4+FU4 -> 0 | FX4: =FM4-FN4+FV4+FW4 -> 0 | FZ4: =ROUND(FK4+FX4+FY4,2) -> 0 | GB4: =$G4*GA4 -> 0 | GC4: =IFERROR(ROUND(GA4/GA16*GC16,2),0) -> 0 | GJ4: =SUM(GE4:GI4) -> 0 | GL4: =GD4+GJ4+GK4 -> 0 | GN4: =GB4-GC4+GL4+GM4 -> 0 | GP4: =ROUND(FZ4+GN4+GO4,2) -> 0 | GR4: =$G4*GQ4 -> 0 | GS4: =IFERROR(ROUND(GQ4/GQ16*GS16,2),0) -> 0 | GZ4: =SUM(GU4:GY4) -> 0 | HB4: =GT4+GZ4+HA4 -> 0 | HD4: =GR4-GS4+HB4+HC4 -> 0 | HF4: =ROUND(GP4+HD4+HE4,2) -> 0 | HH4: =$G4*HG4 -> 0 | HI4: =IFERROR(ROUND(HG4/$HG$16*$HI$16,2),0) -> 0 | HP4: =SUM(HK4:HO4) -> 0 | HR4: =HJ4+HP4+HQ4 -> 0 | HT4: =HH4-HI4+HR4+HS4 -> 0 | HV4: =ROUND(HF4+HT4+HU4,2) -> 0 | HX4: =$G4*HW4 -> 0 | HY4: =IFERROR(ROUND(HW4/$HG$16*$HI$16,2),0) -> 0 | IF4: =SUM(IA4:IE4) -> 0 | IH4: =HZ4+IF4+IG4 -> 0 | IJ4: =HX4-HY4+IH4+II4 -> 0 | IL4: =ROUND(HV4+IJ4+IK4,2) -> 0 | IN4: =$G4*IM4 -> 0 | IO4: =IFERROR(ROUND(IM4/$HG$16*$HI$16,2),0) -> 0 | IV4: =SUM(IQ4:IU4) -> 0 | IX4: =IP4+IV4+IW4 -> 0 | IZ4: =IN4-IO4+IX4+IY4 -> 0 | JB4: =ROUND(IL4+IZ4+JA4,2) -> 0 | JD4: =$G4*JC4 -> 0 | JE4: =IFERROR(ROUND(JC4/$HG$16*$HI$16,2),0) -> 0 | JL4: =SUM(JG4:JK4) -> 0 | JN4: =JF4+JL4+JM4 -> 0 | JP4: =JD4-JE4+JN4+JO4 -> 0 | JR4: =ROUND(JB4+JP4+JQ4,2) -> 0 | JT4: =$G4*JS4 -> 0 | JU4: =IFERROR(ROUND(JS4/$HG$16*$HI$16,2),0) -> 0 | KB4: =SUM(JW4:KA4) -> 0 | KD4: =JV4+KB4+KC4 -> 0 | KF4: =JT4-JU4+KD4+KE4 -> 0 | KH4: =ROUND(JR4+KF4+KG4,2) -> 0 | KJ4: =$G4*KI4 -> 0 | KK4: =IFERROR(ROUND(KI4/$HG$16*$HI$16,2),0) -> 0 | KR4: =SUM(KM4:KQ4) -> 0 | KT4: =KL4+KR4+KS4 -> 0 | KV4: =KJ4-KK4+KT4+KU4 -> 0 | KX4: =ROUND(KH4+KV4+KW4,2) -> 0 | KZ4: =$G4*KY4 -> 0 | LA4: =IFERROR(ROUND(KY4/$HG$16*$HI$16,2),0) -> 0 | LH4: =SUM(LC4:LG4) -> 0 | LJ4: =LB4+LH4+LI4 -> 0 | LL4: =KZ4-LA4+LJ4+LK4 -> 0 | LN4: =ROUND(KX4+LL4+LM4,2) -> 0 | LP4: =$G4*LO4 -> 0 | LQ4: =IFERROR(ROUND(LO4/$HG$16*$HI$16,2),0) -> 0 | LX4: =SUM(LS4:LW4) -> 0 | LZ4: =LR4+LX4+LY4 -> 0 | MB4: =LP4-LQ4+LZ4+MA4 -> 0 | MD4: =ROUND(LN4+MB4+MC4,2) -> 0 | MF4: =$G4*ME4 -> 0 | MG4: =IFERROR(ROUND(ME4/$HG$16*$HI$16,2),0) -> 0 | MN4: =SUM(MI4:MM4) -> 0 | MP4: =MH4+MN4+MO4 -> 0 | MR4: =MF4-MG4+MP4+MQ4 -> 0 | MT4: =ROUND(MD4+MR4+MS4,2) -> 0 | MV4: =$G4*MU4 -> 0 | MW4: =IFERROR(ROUND(MU4/$HG$16*$HI$16,2),0) -> 0 | ND4: =SUM(MY4:NC4) -> 0 | NF4: =MX4+ND4+NE4 -> 0 | NH4: =MV4-MW4+NF4+NG4 -> 0 | NJ4: =ROUND(MT4+NH4+NI4,2) -> 0 | NL4: =$G4*NK4 -> 0 | NM4: =IFERROR(ROUND(NK4/$HG$16*$HI$16,2),0) -> 0 | NT4: =SUM(NO4:NS4) -> 0 | NV4: =NN4+NT4+NU4 -> 0 | NX4: =NL4-NM4+NV4+NW4 -> 0 | NZ4: =ROUND(NJ4+NX4+NY4,2) -> 0 | OB4: =$G4*OA4 -> 0 | OC4: =IFERROR(ROUND(OA4/$HG$16*$HI$16,2),0) -> 0 | OJ4: =SUM(OE4:OI4) -> 0 | OL4: =OD4+OJ4+OK4 -> 0 | ON4: =OB4-OC4+OL4+OM4 -> 0 | OP4: =ROUND(NZ4+ON4+OO4,2) -> 0 | OR4: =$G4*OQ4 -> 0 | OS4: =IFERROR(ROUND(OQ4/$HG$16*$HI$16,2),0) -> 0 | OZ4: =SUM(OU4:OY4) -> 0 | PB4: =OT4+OZ4+PA4 -> 0 | PD4: =OR4-OS4+PB4+PC4 -> 0 | PF4: =ROUND(OP4+PD4+PE4,2) -> 0 | PH4: =$H4*PG4 -> 0 | PI4: =PH4*0.6 -> 0 | PJ4: =JB4+PI4 -> 0
A5: Телескоп 4 | B5: Телескоп №4 | C5: =INDEX(Позиция!$D$3:$D$22,MATCH(A5,Позиция!$C$3:$C$22,0)) -> Староконстантинов | D5: =INDEX(Позиция!$E$3:$E$22,MATCH(A5,Позиция!$C$3:$C$22,0)) -> 0 | E5: Староконстантинов | F5: 467.63 | G5: 494.88 | H5: 579.13 | K5: =F5*J5 -> 0 | P5: =SUM(M5:O5) -> 0 | S5: 146 | T5: =F5*S5 -> 68273.98 | U5: =$U$16/$T$16*T5 -> 942.55304 | V5: -12053.6 | W5: -9973.67 | X5: -1872 | Y5: =SUM(V5:X5) -> -23899.27 | AA5: =T5-U5+Y5+Z5 -> 43432.157 | AB5: =R5+AA5 -> 43432.157 | AC5: 161 | AD5: =F5*AC5 -> 75288.43 | AE5: =$AE$16/$AD$16*AD5 -> 72009.892 | AF5: -11919.12 | AG5: -19832.47 | AI5: =SUM(AF5:AH5) -> -31751.59 | AK5: =AD5-AE5+AI5+AJ5 -> -28473.052 | AL5: =AB5+AK5 -> 14959.105 | AM5: 151 | AN5: =F5*AM5 -> 70612.13 | AO5: =$AO$16/$AN$16*AN5 -> 31819.53 | AP5: -10309.71 | AQ5: -15648 | AS5: =SUM(AP5:AR5) -> -25957.71 | AU5: =AN5-AO5+AS5+AT5 -> 12834.89 | AV5: =AL5+AU5 -> 27793.996 | AW5: 218 | AX5: =F5*AW5 -> 101943.34 | AY5: =$AY$16/$AX$16*AX5 -> 75901.091 | AZ5: =-5435.6-3590-5039.12 -> -14064.72 | BA5: =-(13160+11260.59) -> -24420.59 | BC5: =SUM(AZ5:BB5) -> -38485.31 | BE5: =AX5-AY5+BC5+BD5 -> -12443.061 | BF5: =AV5+BE5 -> 15350.935 | BG5: =апрель!E13 -> 143 | BH5: =F5*BG5 -> 66871.09 | BI5: =$BI$16/($BG$4+$BG$5+$BG$13+$BG$15)*BG5 -> 79816.442 | BJ5: =-апрель!N13-апрель!O13-апрель!P13 -> -11590 | BK5: -13447 | BM5: =SUM(BJ5:BL5) -> -25037 | BO5: =BH5-BI5+BM5+BN5 -> -37982.352 | BP5: =BF5+BO5 -> -22631.417 | BQ5: 207 | BR5: =F5*BQ5 -> 96799.41 | BS5: 0 | BT5: =-май!C31 -> -25071.38 | BU5: =май!H11 -> -24046.05 | BW5: =SUM(BT5:BV5) -> -49117.43 | BY5: =BR5-BS5+BW5+BX5 -> 47681.98 | BZ5: =BP5+BY5 -> 25050.563 | CA5: 193 | CB5: =$F5*CA5 -> 90252.59 | CC5: =$CC$16/SUM($CA$4:$CA$15)*CA5 -> 110286.34 | CD5: -11688.34 | CE5: -14770.22 | CG5: =SUM(CD5:CF5) -> -26458.56 | CI5: =CB5-CC5+CG5+CH5 -> -46492.311 | CJ5: =BZ5+CI5 -> -21441.748 | CK5: 204 | CL5: =$F5*CK5 -> 95396.52 | CM5: =$CM$16/SUM($CK$4:$CK$15)*CK5 -> 109125.63 | CN5: -12053.6 | CO5: -20037.85 | CQ5: =SUM(CN5:CP5) -> -32091.45 | CS5: =CL5-CM5+CQ5+CR5 -> -45820.563 | CT5: =CJ5+CS5 -> -67262.311 | CU5: 228 | CV5: =$F5*CU5 -> 106619.64 | CW5: =$CW$16/SUM($CU$4:$CU$15)*CU5 -> 23560.533 | CX5: -12053.6 | CY5: -21600.69 | DA5: =SUM(CX5:CZ5) -> -33654.29 | DC5: =CV5-CW5+DA5+DB5 -> 49404.817 | DD5: 6422.23 | DE5: =ROUND(CT5+DC5+DD5,2) -> -11435.26 | DF5: 80 | DG5: =$F5*DF5 -> 37410.4 | DH5: =ROUND(DF5/$DF$16*$DH$16,2) -> 13582.68 | DI5: -12053.6 | DL5: -18296.06 | DM5: =SUM(DJ5:DL5) -> -18296.06 | DO5: =DI5+DM5+DN5 -> -30349.66 | DQ5: =DG5-DH5+DO5+DP5 -> -6521.94 | DS5: =ROUND(DE5+DQ5+DR5,2) -> -17957.2 | DT5: 198 | DU5: =$G5*DT5 -> 97986.24 | DV5: =IFERROR(ROUND(DT5/DT16*DV16,2),0) -> 71582.38 | DW5: -12053.6 | DX5: -7283.72 | DZ5: -19992 | EA5: =SUM(DX5:DZ5) -> -27275.72 | EC5: =DW5+EA5+EB5 -> -39329.32 | EE5: =DU5-DV5+EC5+ED5 -> -12925.46 | EF5: 71803.81 | EG5: =ROUND(DS5+EE5+EF5,2) -> 40921.15 | EH5: 151 | EI5: =$G5*EH5 -> 74726.88 | EJ5: =IFERROR(ROUND(EH5/EH16*EJ16,2),0) -> 61242 | EK5: -12053.6 | EO5: -14800 | EP5: =SUM(EL5:EO5) -> -14800 | ER5: =EK5+EP5+EQ5 -> -26853.6 | ET5: =EI5-EJ5+ER5+ES5 -> -13368.72 | EV5: =ROUND(EG5+ET5+EU5,2) -> 27552.43 | EW5: 223 | EX5: =$G5*EW5 -> 110358.24 | EY5: =IFERROR(ROUND(EW5/EW16*EY16,2),0) -> 78028.63 | EZ5: -12053.6 | FA5: -5998.8 | FD5: =-24623.29 -> -24623.29 | FE5: =SUM(FA5:FD5) -> -30622.09 | FG5: =EZ5+FE5+FF5 -> -42675.69 | FI5: =EX5-EY5+FG5+FH5 -> -10346.08 | FK5: =ROUND(EV5+FI5+FJ5,2) -> 17206.35 | FL5: 155 | FM5: =$G5*FL5 -> 76706.4 | FN5: =IFERROR(ROUND(FL5/FL16*FN16,2),0) -> 98549.63 | FO5: -12053.6 | FS5: -24089.6 | FT5: =SUM(FP5:FS5) -> -24089.6 | FV5: =FO5+FT5+FU5 -> -36143.2 | FX5: =FM5-FN5+FV5+FW5 -> -57986.43 | FZ5: =ROUND(FK5+FX5+FY5,2) -> -40780.08 | GA5: 168 | GB5: =$G5*GA5 -> 83139.84 | GC5: 5091.36 | GD5: -12053.6 | GE5: -10917.8 | GI5: -14297 | GJ5: =SUM(GE5:GI5) -> -25214.8 | GL5: =GD5+GJ5+GK5 -> -37268.4 | GN5: =GB5-GC5+GL5+GM5 -> 40780.08 | GP5: =ROUND(FZ5+GN5+GO5,2) -> 0 | GR5: =$G5*GQ5 -> 0 | GS5: =IFERROR(ROUND(GQ5/GQ16*GS16,2),0) -> 0 | GZ5: =SUM(GU5:GY5) -> 0 | HB5: =GT5+GZ5+HA5 -> 0 | HD5: =GR5-GS5+HB5+HC5 -> 0 | HF5: =ROUND(GP5+HD5+HE5,2) -> 0 | HH5: =$G5*HG5 -> 0 | HI5: =IFERROR(ROUND(HG5/$HG$16*$HI$16,2),0) -> 0 | HP5: =SUM(HK5:HO5) -> 0 | HR5: =HJ5+HP5+HQ5 -> 0 | HT5: =HH5-HI5+HR5+HS5 -> 0 | HV5: =ROUND(HF5+HT5+HU5,2) -> 0 | HX5: =$G5*HW5 -> 0 | HY5: =IFERROR(ROUND(HW5/$HG$16*$HI$16,2),0) -> 0 | IF5: =SUM(IA5:IE5) -> 0 | IH5: =HZ5+IF5+IG5 -> 0 | IJ5: =HX5-HY5+IH5+II5 -> 0 | IL5: =ROUND(HV5+IJ5+IK5,2) -> 0 | IN5: =$G5*IM5 -> 0 | IO5: =IFERROR(ROUND(IM5/$HG$16*$HI$16,2),0) -> 0 | IV5: =SUM(IQ5:IU5) -> 0 | IX5: =IP5+IV5+IW5 -> 0 | IZ5: =IN5-IO5+IX5+IY5 -> 0 | JB5: =ROUND(IL5+IZ5+JA5,2) -> 0 | JD5: =$G5*JC5 -> 0 | JE5: =IFERROR(ROUND(JC5/$HG$16*$HI$16,2),0) -> 0 | JL5: =SUM(JG5:JK5) -> 0 | JN5: =JF5+JL5+JM5 -> 0 | JP5: =JD5-JE5+JN5+JO5 -> 0 | JR5: =ROUND(JB5+JP5+JQ5,2) -> 0 | JT5: =$G5*JS5 -> 0 | JU5: =IFERROR(ROUND(JS5/$HG$16*$HI$16,2),0) -> 0 | KB5: =SUM(JW5:KA5) -> 0 | KD5: =JV5+KB5+KC5 -> 0 | KF5: =JT5-JU5+KD5+KE5 -> 0 | KH5: =ROUND(JR5+KF5+KG5,2) -> 0 | KJ5: =$G5*KI5 -> 0 | KK5: =IFERROR(ROUND(KI5/$HG$16*$HI$16,2),0) -> 0 | KR5: =SUM(KM5:KQ5) -> 0 | KT5: =KL5+KR5+KS5 -> 0 | KV5: =KJ5-KK5+KT5+KU5 -> 0 | KX5: =ROUND(KH5+KV5+KW5,2) -> 0 | KZ5: =$G5*KY5 -> 0 | LA5: =IFERROR(ROUND(KY5/$HG$16*$HI$16,2),0) -> 0 | LH5: =SUM(LC5:LG5) -> 0 | LJ5: =LB5+LH5+LI5 -> 0 | LL5: =KZ5-LA5+LJ5+LK5 -> 0 | LN5: =ROUND(KX5+LL5+LM5,2) -> 0 | LP5: =$G5*LO5 -> 0 | LQ5: =IFERROR(ROUND(LO5/$HG$16*$HI$16,2),0) -> 0 | LX5: =SUM(LS5:LW5) -> 0 | LZ5: =LR5+LX5+LY5 -> 0 | MB5: =LP5-LQ5+LZ5+MA5 -> 0 | MD5: =ROUND(LN5+MB5+MC5,2) -> 0 | MF5: =$G5*ME5 -> 0 | MG5: =IFERROR(ROUND(ME5/$HG$16*$HI$16,2),0) -> 0 | MN5: =SUM(MI5:MM5) -> 0 | MP5: =MH5+MN5+MO5 -> 0 | MR5: =MF5-MG5+MP5+MQ5 -> 0 | MT5: =ROUND(MD5+MR5+MS5,2) -> 0 | MV5: =$G5*MU5 -> 0 | MW5: =IFERROR(ROUND(MU5/$HG$16*$HI$16,2),0) -> 0 | ND5: =SUM(MY5:NC5) -> 0 | NF5: =MX5+ND5+NE5 -> 0 | NH5: =MV5-MW5+NF5+NG5 -> 0 | NJ5: =ROUND(MT5+NH5+NI5,2) -> 0 | NL5: =$G5*NK5 -> 0 | NM5: =IFERROR(ROUND(NK5/$HG$16*$HI$16,2),0) -> 0 | NT5: =SUM(NO5:NS5) -> 0 | NV5: =NN5+NT5+NU5 -> 0 | NX5: =NL5-NM5+NV5+NW5 -> 0 | NZ5: =ROUND(NJ5+NX5+NY5,2) -> 0 | OB5: =$G5*OA5 -> 0 | OC5: =IFERROR(ROUND(OA5/$HG$16*$HI$16,2),0) -> 0 | OJ5: =SUM(OE5:OI5) -> 0 | OL5: =OD5+OJ5+OK5 -> 0 | ON5: =OB5-OC5+OL5+OM5 -> 0 | OP5: =ROUND(NZ5+ON5+OO5,2) -> 0 | OR5: =$G5*OQ5 -> 0 | OS5: =IFERROR(ROUND(OQ5/$HG$16*$HI$16,2),0) -> 0 | OZ5: =SUM(OU5:OY5) -> 0 | PB5: =OT5+OZ5+PA5 -> 0 | PD5: =OR5-OS5+PB5+PC5 -> 0 | PF5: =ROUND(OP5+PD5+PE5,2) -> 0 | PH5: =$H5*PG5 -> 0 | PI5: =PH5*0.6 -> 0 | PJ5: =JB5+PI5 -> 0
A6: Экскаватор JCB 2007 | B6: Экскаватор JCB 2007 | C6: =INDEX(Позиция!$D$3:$D$22,MATCH(A6,Позиция!$C$3:$C$22,0)) -> Ладыжин-3 | D6: =INDEX(Позиция!$E$3:$E$22,MATCH(A6,Позиция!$C$3:$C$22,0)) -> 1 | E6: Староконстантинов | F6: 496.93 | G6: 524.19 | H6: 608.43 | P6: =SUM(M6:O6) -> 0 | R6: =K6-L6+P6+Q6 -> 0 | T6: =F6*S6 -> 0 | U6: =$U$33/$T$33*T6 -> 0 | Y6: =SUM(V6:X6) -> 0 | AA6: =T6-U6+Y6+Z6 -> 0 | AB6: =R6+AA6 -> 0 | AD6: =AC6*F6 -> 0 | AE6: =$AE$33/$AD$33*AD6 -> 0 | AI6: =SUM(AF6:AH6) -> 0 | AK6: =AD6-AE6+AI6+AJ6 -> 0 | AL6: =AB6+AK6 -> 0 | AN6: =F6*AM6 -> 0 | AO6: =$AO$33/$AN$33*AN6 -> 0 | AS6: =SUM(AP6:AR6) -> 0 | AU6: =AN6-AO6+AS6+AT6 -> 0 | AV6: =AL6+AU6 -> 0 | AX6: =F6*AW6 -> 0 | AY6: =$AY$33/$AX$33*AX6 -> 0 | BC6: =SUM(AZ6:BB6) -> 0 | BE6: =AX6-AY6+BC6+BD6 -> 0 | BF6: =AV6+BE6 -> 0 | BH6: =F6*BG6 -> 0 | BI6: =$BI$33/($BG$26+$BG$27+$BG$29+$BG$30+$BG$31)*BG6 -> 0 | BM6: =SUM(BJ6:BL6) -> 0 | BO6: =BH6-BI6+BM6+BN6 -> 0 | BP6: =BF6+BO6 -> 0 | BR6: =F6*BQ6 -> 0 | BS6: =$BS$33/SUM(BQ4:BQ11)*BQ6 -> 0 | BW6: =SUM(BT6:BV6) -> 0 | BY6: =BR6-BS6+BW6+BX6 -> 0 | BZ6: =BP6+BY6 -> 0 | CB6: =$F6*CA6 -> 0 | CC6: =CC12/SUM(CA4:CA11)*CA6 -> 0 | CG6: =SUM(CD6:CF6) -> 0 | CI6: =CB6-CC6+CG6+CH6 -> 0 | CJ6: =BZ6+CI6 -> 0 | CK6: 38 | CL6: =$F6*CK6 -> 18883.34 | CM6: =$CM$16/SUM($CK$4:$CK$15)*CK6 -> 20327.324 | CO6: -8578 | CQ6: =SUM(CN6:CP6) -> -8578 | CS6: =CL6-CM6+CQ6+CR6 -> -10021.984 | CT6: =CJ6+CS6 -> -10021.984 | CU6: 202 | CV6: =$F6*CU6 -> 100379.86 | CW6: =$CW$16/SUM($CU$4:$CU$15)*CU6 -> 20873.806 | CX6: -13337.38 | CY6: -45964.17 | DA6: =SUM(CX6:CZ6) -> -59301.55 | DC6: =CV6-CW6+DA6+DB6 -> 20204.504 | DE6: =ROUND(CT6+DC6+DD6,2) -> 10182.52 | DF6: 168 | DG6: =$F6*DF6 -> 83484.24 | DH6: =ROUND(DF6/$DF$16*$DH$16,2) -> 28523.64 | DI6: -12053.6 | DJ6: -9639.45 | DL6: -18766.78 | DM6: =SUM(DJ6:DL6) -> -28406.23 | DO6: =DI6+DM6+DN6 -> -40459.83 | DQ6: =DG6-DH6+DO6+DP6 -> 14500.77 | DS6: =ROUND(DE6+DQ6+DR6,2) -> 24683.29 | DU6: =$G6*DT6 -> 0 | DV6: =IFERROR(ROUND(DT6/DT16*DV16,2),0) -> 0 | EA6: =SUM(DX6:DZ6) -> 0 | EC6: =DW6+EA6+EB6 -> 0 | EE6: =DU6-DV6+EC6+ED6 -> 0 | EF6: -24683.29 | EG6: =ROUND(DS6+EE6+EF6,2) -> 0 | EI6: =$G6*EH6 -> 0 | EJ6: =IFERROR(ROUND(EH6/EH16*EJ16,2),0) -> 0 | EP6: =SUM(EL6:EO6) -> 0 | ER6: =EK6+EP6+EQ6 -> 0 | ET6: =EI6-EJ6+ER6+ES6 -> 0 | EV6: =ROUND(EG6+ET6+EU6,2) -> 0 | EX6: =$G6*EW6 -> 0 | EY6: =IFERROR(ROUND(EW6/EW16*EY16,2),0) -> 0 | FE6: =SUM(FA6:FD6) -> 0 | FG6: =EZ6+FE6+FF6 -> 0 | FI6: =EX6-EY6+FG6+FH6 -> 0 | FK6: =ROUND(EV6+FI6+FJ6,2) -> 0 | FM6: =$G6*FL6 -> 0 | FN6: =IFERROR(ROUND(FL6/FL16*FN16,2),0) -> 0 | FT6: =SUM(FP6:FS6) -> 0 | FV6: =FO6+FT6+FU6 -> 0 | FX6: =FM6-FN6+FV6+FW6 -> 0 | FZ6: =ROUND(FK6+FX6+FY6,2) -> 0 | GB6: =$G6*GA6 -> 0 | GC6: =IFERROR(ROUND(GA6/GA16*GC16,2),0) -> 0 | GJ6: =SUM(GE6:GI6) -> 0 | GL6: =GD6+GJ6+GK6 -> 0 | GN6: =GB6-GC6+GL6+GM6 -> 0 | GP6: =ROUND(FZ6+GN6+GO6,2) -> 0 | GR6: =$G6*GQ6 -> 0 | GS6: =IFERROR(ROUND(GQ6/GQ16*GS16,2),0) -> 0 | GZ6: =SUM(GU6:GY6) -> 0 | HB6: =GT6+GZ6+HA6 -> 0 | HD6: =GR6-GS6+HB6+HC6 -> 0 | HF6: =ROUND(GP6+HD6+HE6,2) -> 0 | HH6: =$G6*HG6 -> 0 | HI6: =IFERROR(ROUND(HG6/$HG$16*$HI$16,2),0) -> 0 | HP6: =SUM(HK6:HO6) -> 0 | HR6: =HJ6+HP6+HQ6 -> 0 | HT6: =HH6-HI6+HR6+HS6 -> 0 | HV6: =ROUND(HF6+HT6+HU6,2) -> 0 | HX6: =$G6*HW6 -> 0 | HY6: =IFERROR(ROUND(HW6/$HG$16*$HI$16,2),0) -> 0 | IF6: =SUM(IA6:IE6) -> 0 | IH6: =HZ6+IF6+IG6 -> 0 | IJ6: =HX6-HY6+IH6+II6 -> 0 | IL6: =ROUND(HV6+IJ6+IK6,2) -> 0 | IN6: =$G6*IM6 -> 0 | IO6: =IFERROR(ROUND(IM6/$HG$16*$HI$16,2),0) -> 0 | IV6: =SUM(IQ6:IU6) -> 0 | IX6: =IP6+IV6+IW6 -> 0 | IZ6: =IN6-IO6+IX6+IY6 -> 0 | JB6: =ROUND(IL6+IZ6+JA6,2) -> 0 | JD6: =$G6*JC6 -> 0 | JE6: =IFERROR(ROUND(JC6/$HG$16*$HI$16,2),0) -> 0 | JL6: =SUM(JG6:JK6) -> 0 | JN6: =JF6+JL6+JM6 -> 0 | JP6: =JD6-JE6+JN6+JO6 -> 0 | JR6: =ROUND(JB6+JP6+JQ6,2) -> 0 | JT6: =$G6*JS6 -> 0 | JU6: =IFERROR(ROUND(JS6/$HG$16*$HI$16,2),0) -> 0 | KB6: =SUM(JW6:KA6) -> 0 | KD6: =JV6+KB6+KC6 -> 0 | KF6: =JT6-JU6+KD6+KE6 -> 0 | KH6: =ROUND(JR6+KF6+KG6,2) -> 0 | KJ6: =$G6*KI6 -> 0 | KK6: =IFERROR(ROUND(KI6/$HG$16*$HI$16,2),0) -> 0 | KR6: =SUM(KM6:KQ6) -> 0 | KT6: =KL6+KR6+KS6 -> 0 | KV6: =KJ6-KK6+KT6+KU6 -> 0 | KX6: =ROUND(KH6+KV6+KW6,2) -> 0 | KZ6: =$G6*KY6 -> 0 | LA6: =IFERROR(ROUND(KY6/$HG$16*$HI$16,2),0) -> 0 | LH6: =SUM(LC6:LG6) -> 0 | LJ6: =LB6+LH6+LI6 -> 0 | LL6: =KZ6-LA6+LJ6+LK6 -> 0 | LN6: =ROUND(KX6+LL6+LM6,2) -> 0 | LP6: =$G6*LO6 -> 0 | LQ6: =IFERROR(ROUND(LO6/$HG$16*$HI$16,2),0) -> 0 | LX6: =SUM(LS6:LW6) -> 0 | LZ6: =LR6+LX6+LY6 -> 0 | MB6: =LP6-LQ6+LZ6+MA6 -> 0 | MD6: =ROUND(LN6+MB6+MC6,2) -> 0 | MF6: =$G6*ME6 -> 0 | MG6: =IFERROR(ROUND(ME6/$HG$16*$HI$16,2),0) -> 0 | MN6: =SUM(MI6:MM6) -> 0 | MP6: =MH6+MN6+MO6 -> 0 | MR6: =MF6-MG6+MP6+MQ6 -> 0 | MT6: =ROUND(MD6+MR6+MS6,2) -> 0 | MV6: =$G6*MU6 -> 0 | MW6: =IFERROR(ROUND(MU6/$HG$16*$HI$16,2),0) -> 0 | ND6: =SUM(MY6:NC6) -> 0 | NF6: =MX6+ND6+NE6 -> 0 | NH6: =MV6-MW6+NF6+NG6 -> 0 | NJ6: =ROUND(MT6+NH6+NI6,2) -> 0 | NL6: =$G6*NK6 -> 0 | NM6: =IFERROR(ROUND(NK6/$HG$16*$HI$16,2),0) -> 0 | NT6: =SUM(NO6:NS6) -> 0 | NV6: =NN6+NT6+NU6 -> 0 | NX6: =NL6-NM6+NV6+NW6 -> 0 | NZ6: =ROUND(NJ6+NX6+NY6,2) -> 0 | OB6: =$G6*OA6 -> 0 | OC6: =IFERROR(ROUND(OA6/$HG$16*$HI$16,2),0) -> 0 | OJ6: =SUM(OE6:OI6) -> 0 | OL6: =OD6+OJ6+OK6 -> 0 | ON6: =OB6-OC6+OL6+OM6 -> 0 | OP6: =ROUND(NZ6+ON6+OO6,2) -> 0 | OR6: =$G6*OQ6 -> 0 | OS6: =IFERROR(ROUND(OQ6/$HG$16*$HI$16,2),0) -> 0 | OZ6: =SUM(OU6:OY6) -> 0 | PB6: =OT6+OZ6+PA6 -> 0 | PD6: =OR6-OS6+PB6+PC6 -> 0 | PF6: =ROUND(OP6+PD6+PE6,2) -> 0 | PH6: =$H6*PG6 -> 0 | PI6: =PH6*0.6 -> 0 | PJ6: =JB6+PI6 -> 0
A7: Экскаватор JCB 220 | B7: Экскаватор JCB 220 | C7: =INDEX(Позиция!$D$3:$D$22,MATCH(A7,Позиция!$C$3:$C$22,0)) -> Крушинка | D7: =INDEX(Позиция!$E$3:$E$22,MATCH(A7,Позиция!$C$3:$C$22,0)) -> 1 | E7: Староконстантинов | F7: 995.97 | G7: 1023.23 | H7: 1107.47 | J7: 22 | K7: =F7*J7 -> 21911.34 | L7: 15613.53 | M7: -3899.69 | N7: -22830 | P7: =SUM(M7:O7) -> -26729.69 | R7: =K7-L7+P7+Q7 -> -20431.88 | S7: 86 | T7: =F7*S7 -> 85653.42 | U7: =$U$16/$T$16*T7 -> 1182.484 | V7: -7258.94 | W7: -4035.32 | Y7: =SUM(V7:X7) -> -11294.26 | AA7: =T7-U7+Y7+Z7 -> 73176.676 | AB7: =R7+AA7 -> 52744.796 | AD7: =F7*AC7 -> 0 | AE7: =$AE$16/$AD$16*AD7 -> 0 | AI7: =SUM(AF7:AH7) -> 0 | AK7: =AD7-AE7+AI7+AJ7 -> 0 | AL7: =AB7+AK7 -> 52744.796 | AM7: 51 | AN7: =F7*AM7 -> 50794.47 | AO7: =$AO$16/$AN$16*AN7 -> 22889.214 | AP7: -6470.88 | AQ7: -4890 | AS7: =SUM(AP7:AR7) -> -11360.88 | AU7: =AN7-AO7+AS7+AT7 -> 16544.376 | AV7: =AL7+AU7 -> 69289.172 | AX7: =F7*AW7 -> 0 | AY7: =$AY$16/$AX$16*AX7 -> 0 | BA7: =-4700 -> -4700 | BC7: =SUM(AZ7:BB7) -> -4700 | BE7: =AX7-AY7+BC7+BD7 -> -4700 | BF7: =AV7+BE7 -> 64589.172 | BH7: =F7*BG7 -> 0 | BI7: =$BI$16/($BG$4+$BG$5+$BG$13+$BG$15)*BG7 -> 0 | BM7: =SUM(BJ7:BL7) -> 0 | BO7: =BH7-BI7+BM7+BN7 -> 0 | BP7: =BF7+BO7 -> 64589.172 | BR7: =F7*BQ7 -> 0 | BS7: 0 | BV7: =-36543.99-9136 -> -45679.99 | BW7: =SUM(BT7:BV7) -> -45679.99 | BY7: =BR7-BS7+BW7+BX7 -> -45679.99 | BZ7: =BP7+BY7 -> 18909.182 | CB7: =$F7*CA7 -> 0 | CC7: =$CC$16/SUM($CA$4:$CA$15)*CA7 -> 0 | CG7: =SUM(CD7:CF7) -> 0 | CI7: =CB7-CC7+CG7+CH7 -> 0 | CJ7: =BZ7+CI7 -> 18909.182 | CK7: 10 | CL7: =$F7*CK7 -> 9959.7 | CM7: =$CM$16/SUM($CK$4:$CK$15)*CK7 -> 5349.2957 | CN7: =-6649.24/(CK165+CK7)*CK7 -> -707.36596 | CO7: =-30097.69/(CK165+CK7)*CK7 -> -3201.8819 | CP7: =-7566.07/(CK165+CK7)*CK7 -> -804.90106 | CQ7: =SUM(CN7:CP7) -> -4714.1489 | CS7: =CL7-CM7+CQ7+CR7 -> -103.74466 | CT7: =CJ7+CS7 -> 18805.438 | CU7: 8 | CV7: =$F7*CU7 -> 7967.76 | CW7: =$CW$16/SUM($CU$4:$CU$15)*CU7 -> 826.68538 | CX7: =CU7/(CU7+CU54)*12053.6 -> 983.96735 | CY7: =-60189.17*CU7/(CU7+CU54) -> -4913.4016 | DA7: =SUM(CX7:CZ7) -> -3929.4343 | DC7: =CV7-CW7+DA7+DB7 -> 3211.6403 | DD7: =--14015.71 -> 14015.71 | DE7: =ROUND(CT7+DC7+DD7,2) -> 36032.79 | DG7: =$F7*DF7 -> 0 | DH7: =ROUND(DF7/$DF$16*$DH$16,2) -> 0 | DO7: =DI7+DM7+DN7 -> 0 | DQ7: =DG7-DH7+DO7+DP7 -> 0 | DS7: =ROUND(DE7+DQ7+DR7,2) -> 36032.79 | DU7: =$G7*DT7 -> 0 | DV7: =IFERROR(ROUND(DT7/DT16*DV16,2),0) -> 0 | EA7: =SUM(DX7:DZ7) -> 0 | EC7: =DW7+EA7+EB7 -> 0 | EE7: =DU7-DV7+EC7+ED7 -> 0 | EF7: -36032.79 | EG7: =ROUND(DS7+EE7+EF7,2) -> 0 | EI7: =$G7*EH7 -> 0 | EJ7: =IFERROR(ROUND(EH7/EH16*EJ16,2),0) -> 0 | EP7: =SUM(EL7:EO7) -> 0 | ER7: =EK7+EP7+EQ7 -> 0 | ET7: =EI7-EJ7+ER7+ES7 -> 0 | EV7: =ROUND(EG7+ET7+EU7,2) -> 0 | EX7: =$G7*EW7 -> 0 | EY7: =IFERROR(ROUND(EW7/EW16*EY16,2),0) -> 0 | FE7: =SUM(FA7:FD7) -> 0 | FG7: =EZ7+FE7+FF7 -> 0 | FI7: =EX7-EY7+FG7+FH7 -> 0 | FK7: =ROUND(EV7+FI7+FJ7,2) -> 0 | FM7: =$G7*FL7 -> 0 | FN7: =IFERROR(ROUND(FL7/FL16*FN16,2),0) -> 0 | FT7: =SUM(FP7:FS7) -> 0 | FV7: =FO7+FT7+FU7 -> 0 | FX7: =FM7-FN7+FV7+FW7 -> 0 | FZ7: =ROUND(FK7+FX7+FY7,2) -> 0 | GB7: =$G7*GA7 -> 0 | GC7: =IFERROR(ROUND(GA7/GA16*GC16,2),0) -> 0 | GJ7: =SUM(GE7:GI7) -> 0 | GL7: =GD7+GJ7+GK7 -> 0 | GN7: =GB7-GC7+GL7+GM7 -> 0 | GP7: =ROUND(FZ7+GN7+GO7,2) -> 0 | GR7: =$G7*GQ7 -> 0 | GS7: =IFERROR(ROUND(GQ7/GQ16*GS16,2),0) -> 0 | GZ7: =SUM(GU7:GY7) -> 0 | HB7: =GT7+GZ7+HA7 -> 0 | HD7: =GR7-GS7+HB7+HC7 -> 0 | HF7: =ROUND(GP7+HD7+HE7,2) -> 0 | HH7: =$G7*HG7 -> 0 | HI7: =IFERROR(ROUND(HG7/$HG$16*$HI$16,2),0) -> 0 | HP7: =SUM(HK7:HO7) -> 0 | HR7: =HJ7+HP7+HQ7 -> 0 | HT7: =HH7-HI7+HR7+HS7 -> 0 | HV7: =ROUND(HF7+HT7+HU7,2) -> 0 | HX7: =$G7*HW7 -> 0 | HY7: =IFERROR(ROUND(HW7/$HG$16*$HI$16,2),0) -> 0 | IF7: =SUM(IA7:IE7) -> 0 | IH7: =HZ7+IF7+IG7 -> 0 | IJ7: =HX7-HY7+IH7+II7 -> 0 | IL7: =ROUND(HV7+IJ7+IK7,2) -> 0 | IN7: =$G7*IM7 -> 0 | IO7: =IFERROR(ROUND(IM7/$HG$16*$HI$16,2),0) -> 0 | IV7: =SUM(IQ7:IU7) -> 0 | IX7: =IP7+IV7+IW7 -> 0 | IZ7: =IN7-IO7+IX7+IY7 -> 0 | JB7: =ROUND(IL7+IZ7+JA7,2) -> 0 | JD7: =$G7*JC7 -> 0 | JE7: =IFERROR(ROUND(JC7/$HG$16*$HI$16,2),0) -> 0 | JL7: =SUM(JG7:JK7) -> 0 | JN7: =JF7+JL7+JM7 -> 0 | JP7: =JD7-JE7+JN7+JO7 -> 0 | JR7: =ROUND(JB7+JP7+JQ7,2) -> 0 | JT7: =$G7*JS7 -> 0 | JU7: =IFERROR(ROUND(JS7/$HG$16*$HI$16,2),0) -> 0 | KB7: =SUM(JW7:KA7) -> 0 | KD7: =JV7+KB7+KC7 -> 0 | KF7: =JT7-JU7+KD7+KE7 -> 0 | KH7: =ROUND(JR7+KF7+KG7,2) -> 0 | KJ7: =$G7*KI7 -> 0 | KK7: =IFERROR(ROUND(KI7/$HG$16*$HI$16,2),0) -> 0 | KR7: =SUM(KM7:KQ7) -> 0 | KT7: =KL7+KR7+KS7 -> 0 | KV7: =KJ7-KK7+KT7+KU7 -> 0 | KX7: =ROUND(KH7+KV7+KW7,2) -> 0 | KZ7: =$G7*KY7 -> 0 | LA7: =IFERROR(ROUND(KY7/$HG$16*$HI$16,2),0) -> 0 | LH7: =SUM(LC7:LG7) -> 0 | LJ7: =LB7+LH7+LI7 -> 0 | LL7: =KZ7-LA7+LJ7+LK7 -> 0 | LN7: =ROUND(KX7+LL7+LM7,2) -> 0 | LP7: =$G7*LO7 -> 0 | LQ7: =IFERROR(ROUND(LO7/$HG$16*$HI$16,2),0) -> 0 | LX7: =SUM(LS7:LW7) -> 0 | LZ7: =LR7+LX7+LY7 -> 0 | MB7: =LP7-LQ7+LZ7+MA7 -> 0 | MD7: =ROUND(LN7+MB7+MC7,2) -> 0 | MF7: =$G7*ME7 -> 0 | MG7: =IFERROR(ROUND(ME7/$HG$16*$HI$16,2),0) -> 0 | MN7: =SUM(MI7:MM7) -> 0 | MP7: =MH7+MN7+MO7 -> 0 | MR7: =MF7-MG7+MP7+MQ7 -> 0 | MT7: =ROUND(MD7+MR7+MS7,2) -> 0 | MV7: =$G7*MU7 -> 0 | MW7: =IFERROR(ROUND(MU7/$HG$16*$HI$16,2),0) -> 0 | ND7: =SUM(MY7:NC7) -> 0 | NF7: =MX7+ND7+NE7 -> 0 | NH7: =MV7-MW7+NF7+NG7 -> 0 | NJ7: =ROUND(MT7+NH7+NI7,2) -> 0 | NL7: =$G7*NK7 -> 0 | NM7: =IFERROR(ROUND(NK7/$HG$16*$HI$16,2),0) -> 0 | NT7: =SUM(NO7:NS7) -> 0 | NV7: =NN7+NT7+NU7 -> 0 | NX7: =NL7-NM7+NV7+NW7 -> 0 | NZ7: =ROUND(NJ7+NX7+NY7,2) -> 0 | OB7: =$G7*OA7 -> 0 | OC7: =IFERROR(ROUND(OA7/$HG$16*$HI$16,2),0) -> 0 | OJ7: =SUM(OE7:OI7) -> 0 | OL7: =OD7+OJ7+OK7 -> 0 | ON7: =OB7-OC7+OL7+OM7 -> 0 | OP7: =ROUND(NZ7+ON7+OO7,2) -> 0 | OR7: =$G7*OQ7 -> 0 | OS7: =IFERROR(ROUND(OQ7/$HG$16*$HI$16,2),0) -> 0 | OZ7: =SUM(OU7:OY7) -> 0 | PB7: =OT7+OZ7+PA7 -> 0 | PD7: =OR7-OS7+PB7+PC7 -> 0 | PF7: =ROUND(OP7+PD7+PE7,2) -> 0 | PH7: =$H7*PG7 -> 0 | PI7: =PH7*0.6 -> 0 | PJ7: =JB7+PI7 -> 0
A8: Виброкаток | B8: Виброкаток | C8: =INDEX(Позиция!$D$3:$D$22,MATCH(A8,Позиция!$C$3:$C$22,0)) -> Крушинка | D8: =INDEX(Позиция!$E$3:$E$22,MATCH(A8,Позиция!$C$3:$C$22,0)) -> 1 | E8: Староконстантинов | F8: 544.05 | G8: 606.82 | H8: 644.05 | K8: =F8*J8 -> 0 | P8: =SUM(M8:O8) -> 0 | R8: =K8-L8+P8+Q8 -> 0 | S8: 8 | T8: =F8*S8 -> 4352.4 | U8: =$U$16/$T$16*T8 -> 60.086842 | V8: -190.21 | W8: -1657.56 | Y8: =SUM(V8:X8) -> -1847.77 | AA8: =T8-U8+Y8+Z8 -> 2444.5432 | AB8: =R8+AA8 -> 2444.5432 | AD8: =F8*AC8 -> 0 | AE8: =$AE$16/$AD$16*AD8 -> 0 | AI8: =SUM(AF8:AH8) -> 0 | AK8: =AD8-AE8+AI8+AJ8 -> 0 | AL8: =AB8+AK8 -> 2444.5432 | AN8: =F8*AM8 -> 0 | AO8: =$AO$16/$AN$16*AN8 -> 0 | AS8: =SUM(AP8:AR8) -> 0 | AU8: =AN8-AO8+AS8+AT8 -> 0 | AV8: =AL8+AU8 -> 2444.5432 | AX8: =F8*AW8 -> 0 | AY8: =$AY$16/$AX$16*AX8 -> 0 | BC8: =SUM(AZ8:BB8) -> 0 | BE8: =AX8-AY8+BC8+BD8 -> 0 | BF8: =AV8+BE8 -> 2444.5432 | BH8: =F8*BG8 -> 0 | BI8: =$BI$16/($BG$4+$BG$5+$BG$13+$BG$15)*BG8 -> 0 | BM8: =SUM(BJ8:BL8) -> 0 | BO8: =BH8-BI8+BM8+BN8 -> 0 | BP8: =BF8+BO8 -> 2444.5432 | BR8: =F8*BQ8 -> 0 | BS8: 0 | BW8: =SUM(BT8:BV8) -> 0 | BY8: =BR8-BS8+BW8+BX8 -> 0 | BZ8: =BP8+BY8 -> 2444.5432 | CB8: =$F8*CA8 -> 0 | CC8: =$CC$16/SUM($CA$4:$CA$15)*CA8 -> 0 | CG8: =SUM(CD8:CF8) -> 0 | CI8: =CB8-CC8+CG8+CH8 -> 0 | CJ8: =BZ8+CI8 -> 2444.5432 | CK8: 6 | CL8: =$F8*CK8 -> 3264.3 | CM8: =$CM$16/SUM($CK$4:$CK$15)*CK8 -> 3209.5774 | CN8: -1069.84 | CQ8: =SUM(CN8:CP8) -> -1069.84 | CS8: =CL8-CM8+CQ8+CR8 -> -1015.1174 | CT8: =CJ8+CS8 -> 1429.4257 | CU8: 20 | CV8: =$F8*CU8 -> 10881 | CW8: =$CW$16/SUM($CU$4:$CU$15)*CU8 -> 2066.7134 | CX8: -1327.09 | CY8: -3736.8 | DA8: =SUM(CX8:CZ8) -> -5063.89 | DC8: =CV8-CW8+DA8+DB8 -> 3750.3966 | DE8: =ROUND(CT8+DC8+DD8,2) -> 5179.82 | DF8: 6 | DG8: =$F8*DF8 -> 3264.3 | DH8: =ROUND(DF8/$DF$16*$DH$16,2) -> 1018.7 | DL8: -2005.62 | DM8: =SUM(DJ8:DL8) -> -2005.62 | DO8: =DI8+DM8+DN8 -> -2005.62 | DQ8: =DG8-DH8+DO8+DP8 -> 239.98 | DS8: =ROUND(DE8+DQ8+DR8,2) -> 5419.8 | DU8: =$G8*DT8 -> 0 | DV8: =IFERROR(ROUND(DT8/DT16*DV16,2),0) -> 0 | EA8: =SUM(DX8:DZ8) -> 0 | EC8: =DW8+EA8+EB8 -> 0 | EE8: =DU8-DV8+EC8+ED8 -> 0 | EF8: -5419.8 | EG8: =ROUND(DS8+EE8+EF8,2) -> 0 | EI8: =$G8*EH8 -> 0 | EJ8: =IFERROR(ROUND(EH8/EH16*EJ16,2),0) -> 0 | EP8: =SUM(EL8:EO8) -> 0 | ER8: =EK8+EP8+EQ8 -> 0 | ET8: =EI8-EJ8+ER8+ES8 -> 0 | EV8: =ROUND(EG8+ET8+EU8,2) -> 0 | EX8: =$G8*EW8 -> 0 | EY8: =IFERROR(ROUND(EW8/EW16*EY16,2),0) -> 0 | FE8: =SUM(FA8:FD8) -> 0 | FG8: =EZ8+FE8+FF8 -> 0 | FI8: =EX8-EY8+FG8+FH8 -> 0 | FK8: =ROUND(EV8+FI8+FJ8,2) -> 0 | FM8: =$G8*FL8 -> 0 | FN8: =IFERROR(ROUND(FL8/FL16*FN16,2),0) -> 0 | FT8: =SUM(FP8:FS8) -> 0 | FV8: =FO8+FT8+FU8 -> 0 | FX8: =FM8-FN8+FV8+FW8 -> 0 | FZ8: =ROUND(FK8+FX8+FY8,2) -> 0 | GB8: =$G8*GA8 -> 0 | GC8: =IFERROR(ROUND(GA8/GA16*GC16,2),0) -> 0 | GJ8: =SUM(GE8:GI8) -> 0 | GL8: =GD8+GJ8+GK8 -> 0 | GN8: =GB8-GC8+GL8+GM8 -> 0 | GP8: =ROUND(FZ8+GN8+GO8,2) -> 0 | GR8: =$G8*GQ8 -> 0 | GS8: =IFERROR(ROUND(GQ8/GQ16*GS16,2),0) -> 0 | GZ8: =SUM(GU8:GY8) -> 0 | HB8: =GT8+GZ8+HA8 -> 0 | HD8: =GR8-GS8+HB8+HC8 -> 0 | HF8: =ROUND(GP8+HD8+HE8,2) -> 0 | HH8: =$G8*HG8 -> 0 | HI8: =IFERROR(ROUND(HG8/$HG$16*$HI$16,2),0) -> 0 | HP8: =SUM(HK8:HO8) -> 0 | HR8: =HJ8+HP8+HQ8 -> 0 | HT8: =HH8-HI8+HR8+HS8 -> 0 | HV8: =ROUND(HF8+HT8+HU8,2) -> 0 | HX8: =$G8*HW8 -> 0 | HY8: =IFERROR(ROUND(HW8/$HG$16*$HI$16,2),0) -> 0 | IF8: =SUM(IA8:IE8) -> 0 | IH8: =HZ8+IF8+IG8 -> 0 | IJ8: =HX8-HY8+IH8+II8 -> 0 | IL8: =ROUND(HV8+IJ8+IK8,2) -> 0 | IN8: =$G8*IM8 -> 0 | IO8: =IFERROR(ROUND(IM8/$HG$16*$HI$16,2),0) -> 0 | IV8: =SUM(IQ8:IU8) -> 0 | IX8: =IP8+IV8+IW8 -> 0 | IZ8: =IN8-IO8+IX8+IY8 -> 0 | JB8: =ROUND(IL8+IZ8+JA8,2) -> 0 | JD8: =$G8*JC8 -> 0 | JE8: =IFERROR(ROUND(JC8/$HG$16*$HI$16,2),0) -> 0 | JL8: =SUM(JG8:JK8) -> 0 | JN8: =JF8+JL8+JM8 -> 0 | JP8: =JD8-JE8+JN8+JO8 -> 0 | JR8: =ROUND(JB8+JP8+JQ8,2) -> 0 | JT8: =$G8*JS8 -> 0 | JU8: =IFERROR(ROUND(JS8/$HG$16*$HI$16,2),0) -> 0 | KB8: =SUM(JW8:KA8) -> 0 | KD8: =JV8+KB8+KC8 -> 0 | KF8: =JT8-JU8+KD8+KE8 -> 0 | KH8: =ROUND(JR8+KF8+KG8,2) -> 0 | KJ8: =$G8*KI8 -> 0 | KK8: =IFERROR(ROUND(KI8/$HG$16*$HI$16,2),0) -> 0 | KR8: =SUM(KM8:KQ8) -> 0 | KT8: =KL8+KR8+KS8 -> 0 | KV8: =KJ8-KK8+KT8+KU8 -> 0 | KX8: =ROUND(KH8+KV8+KW8,2) -> 0 | KZ8: =$G8*KY8 -> 0 | LA8: =IFERROR(ROUND(KY8/$HG$16*$HI$16,2),0) -> 0 | LH8: =SUM(LC8:LG8) -> 0 | LJ8: =LB8+LH8+LI8 -> 0 | LL8: =KZ8-LA8+LJ8+LK8 -> 0 | LN8: =ROUND(KX8+LL8+LM8,2) -> 0 | LP8: =$G8*LO8 -> 0 | LQ8: =IFERROR(ROUND(LO8/$HG$16*$HI$16,2),0) -> 0 | LX8: =SUM(LS8:LW8) -> 0 | LZ8: =LR8+LX8+LY8 -> 0 | MB8: =LP8-LQ8+LZ8+MA8 -> 0 | MD8: =ROUND(LN8+MB8+MC8,2) -> 0 | MF8: =$G8*ME8 -> 0 | MG8: =IFERROR(ROUND(ME8/$HG$16*$HI$16,2),0) -> 0 | MN8: =SUM(MI8:MM8) -> 0 | MP8: =MH8+MN8+MO8 -> 0 | MR8: =MF8-MG8+MP8+MQ8 -> 0 | MT8: =ROUND(MD8+MR8+MS8,2) -> 0 | MV8: =$G8*MU8 -> 0 | MW8: =IFERROR(ROUND(MU8/$HG$16*$HI$16,2),0) -> 0 | ND8: =SUM(MY8:NC8) -> 0 | NF8: =MX8+ND8+NE8 -> 0 | NH8: =MV8-MW8+NF8+NG8 -> 0 | NJ8: =ROUND(MT8+NH8+NI8,2) -> 0 | NL8: =$G8*NK8 -> 0 | NM8: =IFERROR(ROUND(NK8/$HG$16*$HI$16,2),0) -> 0 | NT8: =SUM(NO8:NS8) -> 0 | NV8: =NN8+NT8+NU8 -> 0 | NX8: =NL8-NM8+NV8+NW8 -> 0 | NZ8: =ROUND(NJ8+NX8+NY8,2) -> 0 | OB8: =$G8*OA8 -> 0 | OC8: =IFERROR(ROUND(OA8/$HG$16*$HI$16,2),0) -> 0 | OJ8: =SUM(OE8:OI8) -> 0 | OL8: =OD8+OJ8+OK8 -> 0 | ON8: =OB8-OC8+OL8+OM8 -> 0 | OP8: =ROUND(NZ8+ON8+OO8,2) -> 0 | OR8: =$G8*OQ8 -> 0 | OS8: =IFERROR(ROUND(OQ8/$HG$16*$HI$16,2),0) -> 0 | OZ8: =SUM(OU8:OY8) -> 0 | PB8: =OT8+OZ8+PA8 -> 0 | PD8: =OR8-OS8+PB8+PC8 -> 0 | PF8: =ROUND(OP8+PD8+PE8,2) -> 0 | PH8: =$H8*PG8 -> 0 | PI8: =PH8*0.6 -> 0 | PJ8: =JB8+PI8 -> 0
A9: Haulotte | B9: Подъемник Haulotte №1 | C9: =INDEX(Позиция!$D$3:$D$22,MATCH(A9,Позиция!$C$3:$C$22,0)) -> Белая Церковь | E9: Староконстантинов | F9: 802.86 | G9: 802.86 | H9: 802.86 | K9: =F9*J9 -> 0 | AD9: =F9*AC9 -> 0 | AE9: =$AE$16/$AD$16*AD9 -> 0 | AN9: =F9*AM9 -> 0 | AO9: =$AO$16/$AN$16*AN9 -> 0 | AX9: =F9*AW9 -> 0 | AY9: =$AY$16/$AX$16*AX9 -> 0 | BH9: =F9*BG9 -> 0 | BR9: =F9*BQ9 -> 0 | CB9: =$F9*CA9 -> 0 | DU9: =$G9*DT9 -> 0 | EH9: 0 | EI9: =$G9*EH9 -> 0 | EJ9: =IFERROR(ROUND(EH9/EH17*EJ17,2),0) -> 0 | EP9: =SUM(EL9:EO9) -> 0 | ER9: =EK9+EP9+EQ9 -> 0 | ET9: =EI9-EJ9+ER9+ES9 -> 0 | EV9: =ROUND(EG9+ET9+EU9,2) -> 0 | EX9: =$G9*EW9 -> 0 | EY9: =IFERROR(ROUND(EW9/EW16*EY16,2),0) -> 0 | FE9: =SUM(FA9:FD9) -> 0 | FG9: =EZ9+FE9+FF9 -> 0 | FI9: =EX9-EY9+FG9+FH9 -> 0 | FK9: =ROUND(EV9+FI9+FJ9,2) -> 0 | FM9: =$G9*FL9 -> 0 | FN9: =IFERROR(ROUND(FL9/FL16*FN16,2),0) -> 0 | FT9: =SUM(FP9:FS9) -> 0 | FV9: =FO9+FT9+FU9 -> 0 | FX9: =FM9-FN9+FV9+FW9 -> 0 | FZ9: =ROUND(FK9+FX9+FY9,2) -> 0 | GB9: =$G9*GA9 -> 0 | GC9: =IFERROR(ROUND(GA9/GA16*GC16,2),0) -> 0 | GJ9: =SUM(GE9:GI9) -> 0 | GK9: -9400 | GL9: =GD9+GJ9+GK9 -> -9400 | GN9: =GB9-GC9+GL9+GM9 -> -9400 | GP9: =ROUND(FZ9+GN9+GO9,2) -> -9400 | GQ9: 5 | GR9: =$G9*GQ9 -> 4014.3 | GS9: =IFERROR(ROUND(GQ9/GQ16*GS16,2),0) -> 1086.78 | GZ9: =SUM(GU9:GY9) -> 0 | HB9: =GT9+GZ9+HA9 -> 0 | HD9: =GR9-GS9+HB9+HC9 -> 2927.52 | HF9: =ROUND(GP9+HD9+HE9,2) -> -6472.48 | HH9: =$G9*HG9 -> 0 | HI9: =IFERROR(ROUND(HG9/$HG$16*$HI$16,2),0) -> 0 | HP9: =SUM(HK9:HO9) -> 0 | HR9: =HJ9+HP9+HQ9 -> 0 | HT9: =HH9-HI9+HR9+HS9 -> 0 | HV9: =ROUND(HF9+HT9+HU9,2) -> -6472.48 | HX9: =$G9*HW9 -> 0 | HY9: =IFERROR(ROUND(HW9/HW16*HY16,2),0) -> 0 | IF9: =SUM(IA9:IE9) -> 0 | IH9: =HZ9+IF9+IG9 -> 0 | IJ9: =HX9-HY9+IH9+II9 -> 0 | IL9: =ROUND(HV9+IJ9+IK9,2) -> -6472.48 | IN9: =$G9*IM9 -> 0 | IO9: =IFERROR(ROUND(IM9/IM16*IO16,2),0) -> 0 | IV9: =SUM(IQ9:IU9) -> 0 | IX9: =IP9+IV9+IW9 -> 0 | IZ9: =IN9-IO9+IX9+IY9 -> 0 | JA9: 6472.48 | JB9: =ROUND(IL9+IZ9+JA9,2) -> 0 | JD9: =$G9*JC9 -> 0 | JE9: =IFERROR(ROUND(JC9/JC16*JE16,2),0) -> 0 | JL9: =SUM(JG9:JK9) -> 0 | JN9: =JF9+JL9+JM9 -> 0 | JP9: =JD9-JE9+JN9+JO9 -> 0 | JR9: =ROUND(JB9+JP9+JQ9,2) -> 0 | JT9: =$G9*JS9 -> 0 | JU9: =IFERROR(ROUND(JS9/JS16*JU16,2),0) -> 0 | KB9: =SUM(JW9:KA9) -> 0 | KD9: =JV9+KB9+KC9 -> 0 | KF9: =JT9-JU9+KD9+KE9 -> 0 | KH9: =ROUND(JR9+KF9+KG9,2) -> 0 | KJ9: =$G9*KI9 -> 0 | KK9: =IFERROR(ROUND(KI9/KI16*KK16,2),0) -> 0 | KR9: =SUM(KM9:KQ9) -> 0 | KT9: =KL9+KR9+KS9 -> 0 | KV9: =KJ9-KK9+KT9+KU9 -> 0 | KX9: =ROUND(KH9+KV9+KW9,2) -> 0 | KZ9: =$G9*KY9 -> 0 | LA9: =IFERROR(ROUND(KY9/KY16*LA16,2),0) -> 0 | LH9: =SUM(LC9:LG9) -> 0 | LJ9: =LB9+LH9+LI9 -> 0 | LL9: =KZ9-LA9+LJ9+LK9 -> 0 | LN9: =ROUND(KX9+LL9+LM9,2) -> 0 | LP9: =$G9*LO9 -> 0 | LQ9: =IFERROR(ROUND(LO9/LO16*LQ16,2),0) -> 0 | LX9: =SUM(LS9:LW9) -> 0 | LZ9: =LR9+LX9+LY9 -> 0 | MB9: =LP9-LQ9+LZ9+MA9 -> 0 | MD9: =ROUND(LN9+MB9+MC9,2) -> 0 | MF9: =$G9*ME9 -> 0 | MG9: =IFERROR(ROUND(ME9/ME16*MG16,2),0) -> 0 | MN9: =SUM(MI9:MM9) -> 0 | MP9: =MH9+MN9+MO9 -> 0 | MR9: =MF9-MG9+MP9+MQ9 -> 0 | MT9: =ROUND(MD9+MR9+MS9,2) -> 0 | MV9: =$G9*MU9 -> 0 | MW9: =IFERROR(ROUND(MU9/MU16*MW16,2),0) -> 0 | ND9: =SUM(MY9:NC9) -> 0 | NF9: =MX9+ND9+NE9 -> 0 | NH9: =MV9-MW9+NF9+NG9 -> 0 | NJ9: =ROUND(MT9+NH9+NI9,2) -> 0 | NL9: =$G9*NK9 -> 0 | NM9: =IFERROR(ROUND(NK9/NK16*NM16,2),0) -> 0 | NT9: =SUM(NO9:NS9) -> 0 | NV9: =NN9+NT9+NU9 -> 0 | NX9: =NL9-NM9+NV9+NW9 -> 0 | NZ9: =ROUND(NJ9+NX9+NY9,2) -> 0 | OB9: =$G9*OA9 -> 0 | OC9: =IFERROR(ROUND(OA9/OA16*OC16,2),0) -> 0 | OJ9: =SUM(OE9:OI9) -> 0 | OL9: =OD9+OJ9+OK9 -> 0 | ON9: =OB9-OC9+OL9+OM9 -> 0 | OP9: =ROUND(NZ9+ON9+OO9,2) -> 0 | OR9: =$G9*OQ9 -> 0 | OS9: =IFERROR(ROUND(OQ9/OQ16*OS16,2),0) -> 0 | OZ9: =SUM(OU9:OY9) -> 0 | PB9: =OT9+OZ9+PA9 -> 0 | PD9: =OR9-OS9+PB9+PC9 -> 0 | PF9: =ROUND(OP9+PD9+PE9,2) -> 0 | PH9: =$H9*PG9 -> 0 | PI9: =PH9*0.6 -> 0 | PJ9: =JB9+PI9 -> 0
A10: МАЗ 264 | B10: МАЗ 264 | C10: =INDEX(Позиция!$D$3:$D$22,MATCH(A10,Позиция!$C$3:$C$22,0)) -> Крушинка | D10: =INDEX(Позиция!$E$3:$E$22,MATCH(A10,Позиция!$C$3:$C$22,0)) -> 1 | E10: Староконстантинов | F10: 355.37 | G10: 386.37 | H10: 455.37 | K10: =F10*J10 -> 0 | M10: -6224 | N10: -969 | P10: =SUM(M10:O10) -> -7193 | R10: =K10-L10+P10+Q10 -> -7193 | S10: 53 | T10: =F10*S10 -> 18834.61 | U10: =$U$16/$T$16*T10 -> 260.02027 | V10: -7087.64 | W10: -6973.82 | Y10: =SUM(V10:X10) -> -14061.46 | AA10: =T10-U10+Y10+Z10 -> 4513.1297 | AB10: =R10+AA10 -> -2679.8703 | AD10: =F10*AC10 -> 0 | AE10: =$AE$16/$AD$16*AD10 -> 0 | AI10: =SUM(AF10:AH10) -> 0 | AK10: =AD10-AE10+AI10+AJ10 -> 0 | AL10: =AB10+AK10 -> -2679.8703 | AM10: 22 | AN10: =F10*AM10 -> 7818.14 | AO10: =$AO$16/$AN$16*AN10 -> 3523.0425 | AS10: =SUM(AP10:AR10) -> 0 | AU10: =AN10-AO10+AS10+AT10 -> 4295.0975 | AV10: =AL10+AU10 -> 1615.2272 | AX10: =F10*AW10 -> 0 | AY10: =$AY$16/$AX$16*AX10 -> 0 | BC10: =SUM(AZ10:BB10) -> 0 | BE10: =AX10-AY10+BC10+BD10 -> 0 | BF10: =AV10+BE10 -> 1615.2272 | BH10: =F10*BG10 -> 0 | BI10: =$BI$16/($BG$4+$BG$5+$BG$13+$BG$15)*BG10 -> 0 | BM10: =SUM(BJ10:BL10) -> 0 | BO10: =BH10-BI10+BM10+BN10 -> 0 | BP10: =BF10+BO10 -> 1615.2272 | BR10: =F10*BQ10 -> 0 | BS10: 0 | BW10: =SUM(BT10:BV10) -> 0 | BY10: =BR10-BS10+BW10+BX10 -> 0 | BZ10: =BP10+BY10 -> 1615.2272 | CB10: =$F10*CA10 -> 0 | CC10: =$CC$16/SUM($CA$4:$CA$15)*CA10 -> 0 | CG10: =SUM(CD10:CF10) -> 0 | CI10: =CB10-CC10+CG10+CH10 -> 0 | CJ10: =BZ10+CI10 -> 1615.2272 | CK10: 56 | CL10: =$F10*CK10 -> 19900.72 | CM10: =$CM$16/SUM($CK$4:$CK$15)*CK10 -> 29956.056 | CO10: -6004.6 | CQ10: =SUM(CN10:CP10) -> -6004.6 | CS10: =CL10-CM10+CQ10+CR10 -> -16059.936 | CT10: =CJ10+CS10 -> -14444.709 | CU10: 122 | CV10: =$F10*CU10 -> 43355.14 | CW10: =$CW$16/SUM($CU$4:$CU$15)*CU10 -> 12606.952 | CY10: =-17131.68*CU10/(CU10+CU42) -> -12667.06 | DA10: =SUM(CX10:CZ10) -> -12667.06 | DC10: =CV10-CW10+DA10+DB10 -> 18081.128 | DE10: =ROUND(CT10+DC10+DD10,2) -> 3636.42 | DG10: =$F10*DF10 -> 0 | DH10: =ROUND(DF10/$DF$16*$DH$16,2) -> 0 | DO10: =DI10+DM10+DN10 -> 0 | DQ10: =DG10-DH10+DO10+DP10 -> 0 | DS10: =ROUND(DE10+DQ10+DR10,2) -> 3636.42 | DU10: =$G10*DT10 -> 0 | DV10: =IFERROR(ROUND(DT10/DT16*DV16,2),0) -> 0 | EA10: =SUM(DX10:DZ10) -> 0 | EC10: =DW10+EA10+EB10 -> 0 | EE10: =DU10-DV10+EC10+ED10 -> 0 | EF10: -3636.42 | EG10: =ROUND(DS10+EE10+EF10,2) -> 0 | EI10: =$G10*EH10 -> 0 | EJ10: =IFERROR(ROUND(EH10/EH16*EJ16,2),0) -> 0 | EP10: =SUM(EL10:EO10) -> 0 | ER10: =EK10+EP10+EQ10 -> 0 | ET10: =EI10-EJ10+ER10+ES10 -> 0 | EV10: =ROUND(EG10+ET10+EU10,2) -> 0 | EX10: =$G10*EW10 -> 0 | EY10: =IFERROR(ROUND(EW10/EW16*EY16,2),0) -> 0 | FE10: =SUM(FA10:FD10) -> 0 | FG10: =EZ10+FE10+FF10 -> 0 | FI10: =EX10-EY10+FG10+FH10 -> 0 | FK10: =ROUND(EV10+FI10+FJ10,2) -> 0 | FM10: =$G10*FL10 -> 0 | FN10: =IFERROR(ROUND(FL10/FL16*FN16,2),0) -> 0 | FT10: =SUM(FP10:FS10) -> 0 | FV10: =FO10+FT10+FU10 -> 0 | FX10: =FM10-FN10+FV10+FW10 -> 0 | FZ10: =ROUND(FK10+FX10+FY10,2) -> 0 | GB10: =$G10*GA10 -> 0 | GC10: =IFERROR(ROUND(GA10/GA16*GC16,2),0) -> 0 | GJ10: =SUM(GE10:GI10) -> 0 | GL10: =GD10+GJ10+GK10 -> 0 | GN10: =GB10-GC10+GL10+GM10 -> 0 | GP10: =ROUND(FZ10+GN10+GO10,2) -> 0 | GR10: =$G10*GQ10 -> 0 | GS10: =IFERROR(ROUND(GQ10/GQ16*GS16,2),0) -> 0 | GZ10: =SUM(GU10:GY10) -> 0 | HB10: =GT10+GZ10+HA10 -> 0 | HD10: =GR10-GS10+HB10+HC10 -> 0 | HF10: =ROUND(GP10+HD10+HE10,2) -> 0 | HH10: =$G10*HG10 -> 0 | HI10: =IFERROR(ROUND(HG10/$HG$16*$HI$16,2),0) -> 0 | HP10: =SUM(HK10:HO10) -> 0 | HR10: =HJ10+HP10+HQ10 -> 0 | HT10: =HH10-HI10+HR10+HS10 -> 0 | HV10: =ROUND(HF10+HT10+HU10,2) -> 0 | HX10: =$G10*HW10 -> 0 | HY10: =IFERROR(ROUND(HW10/$HG$16*$HI$16,2),0) -> 0 | IF10: =SUM(IA10:IE10) -> 0 | IH10: =HZ10+IF10+IG10 -> 0 | IJ10: =HX10-HY10+IH10+II10 -> 0 | IL10: =ROUND(HV10+IJ10+IK10,2) -> 0 | IN10: =$G10*IM10 -> 0 | IO10: =IFERROR(ROUND(IM10/$HG$16*$HI$16,2),0) -> 0 | IV10: =SUM(IQ10:IU10) -> 0 | IX10: =IP10+IV10+IW10 -> 0 | IZ10: =IN10-IO10+IX10+IY10 -> 0 | JB10: =ROUND(IL10+IZ10+JA10,2) -> 0 | JD10: =$G10*JC10 -> 0 | JE10: =IFERROR(ROUND(JC10/$HG$16*$HI$16,2),0) -> 0 | JL10: =SUM(JG10:JK10) -> 0 | JN10: =JF10+JL10+JM10 -> 0 | JP10: =JD10-JE10+JN10+JO10 -> 0 | JR10: =ROUND(JB10+JP10+JQ10,2) -> 0 | JT10: =$G10*JS10 -> 0 | JU10: =IFERROR(ROUND(JS10/$HG$16*$HI$16,2),0) -> 0 | KB10: =SUM(JW10:KA10) -> 0 | KD10: =JV10+KB10+KC10 -> 0 | KF10: =JT10-JU10+KD10+KE10 -> 0 | KH10: =ROUND(JR10+KF10+KG10,2) -> 0 | KJ10: =$G10*KI10 -> 0 | KK10: =IFERROR(ROUND(KI10/$HG$16*$HI$16,2),0) -> 0 | KR10: =SUM(KM10:KQ10) -> 0 | KT10: =KL10+KR10+KS10 -> 0 | KV10: =KJ10-KK10+KT10+KU10 -> 0 | KX10: =ROUND(KH10+KV10+KW10,2) -> 0 | KZ10: =$G10*KY10 -> 0 | LA10: =IFERROR(ROUND(KY10/$HG$16*$HI$16,2),0) -> 0 | LH10: =SUM(LC10:LG10) -> 0 | LJ10: =LB10+LH10+LI10 -> 0 | LL10: =KZ10-LA10+LJ10+LK10 -> 0 | LN10: =ROUND(KX10+LL10+LM10,2) -> 0 | LP10: =$G10*LO10 -> 0 | LQ10: =IFERROR(ROUND(LO10/$HG$16*$HI$16,2),0) -> 0 | LX10: =SUM(LS10:LW10) -> 0 | LZ10: =LR10+LX10+LY10 -> 0 | MB10: =LP10-LQ10+LZ10+MA10 -> 0 | MD10: =ROUND(LN10+MB10+MC10,2) -> 0 | MF10: =$G10*ME10 -> 0 | MG10: =IFERROR(ROUND(ME10/$HG$16*$HI$16,2),0) -> 0 | MN10: =SUM(MI10:MM10) -> 0 | MP10: =MH10+MN10+MO10 -> 0 | MR10: =MF10-MG10+MP10+MQ10 -> 0 | MT10: =ROUND(MD10+MR10+MS10,2) -> 0 | MV10: =$G10*MU10 -> 0 | MW10: =IFERROR(ROUND(MU10/$HG$16*$HI$16,2),0) -> 0 | ND10: =SUM(MY10:NC10) -> 0 | NF10: =MX10+ND10+NE10 -> 0 | NH10: =MV10-MW10+NF10+NG10 -> 0 | NJ10: =ROUND(MT10+NH10+NI10,2) -> 0 | NL10: =$G10*NK10 -> 0 | NM10: =IFERROR(ROUND(NK10/$HG$16*$HI$16,2),0) -> 0 | NT10: =SUM(NO10:NS10) -> 0 | NV10: =NN10+NT10+NU10 -> 0 | NX10: =NL10-NM10+NV10+NW10 -> 0 | NZ10: =ROUND(NJ10+NX10+NY10,2) -> 0 | OB10: =$G10*OA10 -> 0 | OC10: =IFERROR(ROUND(OA10/$HG$16*$HI$16,2),0) -> 0 | OJ10: =SUM(OE10:OI10) -> 0 | OL10: =OD10+OJ10+OK10 -> 0 | ON10: =OB10-OC10+OL10+OM10 -> 0 | OP10: =ROUND(NZ10+ON10+OO10,2) -> 0 | OR10: =$G10*OQ10 -> 0 | OS10: =IFERROR(ROUND(OQ10/$HG$16*$HI$16,2),0) -> 0 | OZ10: =SUM(OU10:OY10) -> 0 | PB10: =OT10+OZ10+PA10 -> 0 | PD10: =OR10-OS10+PB10+PC10 -> 0 | PF10: =ROUND(OP10+PD10+PE10,2) -> 0 | PH10: =$H10*PG10 -> 0 | PI10: =PH10*0.6 -> 0 | PJ10: =JB10+PI10 -> 0
A11: РДК 250 | B11: РДК 250 | C11: =INDEX(Позиция!$D$3:$D$22,MATCH(A11,Позиция!$C$3:$C$22,0)) -> Стороняя аренда | D11: =INDEX(Позиция!$E$3:$E$22,MATCH(A11,Позиция!$C$3:$C$22,0)) -> 0 | E11: Староконстантинов | F11: 304.15 | G11: 308.41 | H11: 392.65 | K11: =F11*J11 -> 0 | P11: =SUM(M11:O11) -> 0 | R11: =K11-L11+P11+Q11 -> 0 | T11: =F11*S11 -> 0 | U11: =$U$16/$T$16*T11 -> 0 | Y11: =SUM(V11:X11) -> 0 | AA11: =T11-U11+Y11+Z11 -> 0 | AB11: =R11+AA11 -> 0 | AD11: =F11*AC11 -> 0 | AE11: =$AE$16/$AD$16*AD11 -> 0 | AI11: =SUM(AF11:AH11) -> 0 | AK11: =AD11-AE11+AI11+AJ11 -> 0 | AL11: =AB11+AK11 -> 0 | AN11: =F11*AM11 -> 0 | AO11: =$AO$16/$AN$16*AN11 -> 0 | AS11: =SUM(AP11:AR11) -> 0 | AU11: =AN11-AO11+AS11+AT11 -> 0 | AV11: =AL11+AU11 -> 0 | AX11: =F11*AW11 -> 0 | AY11: =$AY$16/$AX$16*AX11 -> 0 | BC11: =SUM(AZ11:BB11) -> 0 | BE11: =AX11-AY11+BC11+BD11 -> 0 | BF11: =AV11+BE11 -> 0 | BH11: =F11*BG11 -> 0 | BI11: =$BI$16/($BG$4+$BG$5+$BG$13+$BG$15)*BG11 -> 0 | BM11: =SUM(BJ11:BL11) -> 0 | BO11: =BH11-BI11+BM11+BN11 -> 0 | BP11: =BF11+BO11 -> 0 | BR11: =F11*BQ11 -> 0 | BS11: 0 | BW11: =SUM(BT11:BV11) -> 0 | BY11: =BR11-BS11+BW11+BX11 -> 0 | BZ11: =BP11+BY11 -> 0 | CB11: =$F11*CA11 -> 0 | CC11: =$CC$16/SUM($CA$4:$CA$15)*CA11 -> 0 | CG11: =SUM(CD11:CF11) -> 0 | CI11: =CB11-CC11+CG11+CH11 -> 0 | CJ11: =BZ11+CI11 -> 0 | CL11: =$F11*CK11 -> 0 | CM11: =$CM$16/SUM($CK$4:$CK$15)*CK11 -> 0 | CQ11: =SUM(CN11:CP11) -> 0 | CS11: =CL11-CM11+CQ11+CR11 -> 0 | CT11: =CJ11+CS11 -> 0 | CV11: =$F11*CU11 -> 0 | CW11: =$CW$16/SUM($CU$4:$CU$15)*CU11 -> 0 | DA11: =SUM(CX11:CZ11) -> 0 | DC11: =CV11-CW11+DA11+DB11 -> 0 | DE11: =ROUND(CT11+DC11+DD11,2) -> 0 | DF11: 188 | DG11: =$F11*DF11 -> 57180.2 | DH11: =ROUND(DF11/$DF$16*$DH$16,2) -> 31919.31 | DO11: =DI11+DM11+DN11 -> 0 | DQ11: =DG11-DH11+DO11+DP11 -> 25260.89 | DS11: =ROUND(DE11+DQ11+DR11,2) -> 25260.89 | DU11: =$G11*DT11 -> 0 | DV11: =IFERROR(ROUND(DT11/DT16*DV16,2),0) -> 0 | EA11: =SUM(DX11:DZ11) -> 0 | EC11: =DW11+EA11+EB11 -> 0 | EE11: =DU11-DV11+EC11+ED11 -> 0 | EF11: -25260.89 | EG11: =ROUND(DS11+EE11+EF11,2) -> 0 | EI11: =$G11*EH11 -> 0 | EJ11: =IFERROR(ROUND(EH11/EH16*EJ16,2),0) -> 0 | EP11: =SUM(EL11:EO11) -> 0 | ER11: =EK11+EP11+EQ11 -> 0 | ET11: =EI11-EJ11+ER11+ES11 -> 0 | EV11: =ROUND(EG11+ET11+EU11,2) -> 0 | EX11: =$G11*EW11 -> 0 | EY11: =IFERROR(ROUND(EW11/EW16*EY16,2),0) -> 0 | FE11: =SUM(FA11:FD11) -> 0 | FG11: =EZ11+FE11+FF11 -> 0 | FI11: =EX11-EY11+FG11+FH11 -> 0 | FK11: =ROUND(EV11+FI11+FJ11,2) -> 0 | FM11: =$G11*FL11 -> 0 | FN11: =IFERROR(ROUND(FL11/FL16*FN16,2),0) -> 0 | FT11: =SUM(FP11:FS11) -> 0 | FV11: =FO11+FT11+FU11 -> 0 | FX11: =FM11-FN11+FV11+FW11 -> 0 | FZ11: =ROUND(FK11+FX11+FY11,2) -> 0 | GB11: =$G11*GA11 -> 0 | GC11: =IFERROR(ROUND(GA11/GA16*GC16,2),0) -> 0 | GJ11: =SUM(GE11:GI11) -> 0 | GL11: =GD11+GJ11+GK11 -> 0 | GN11: =GB11-GC11+GL11+GM11 -> 0 | GP11: =ROUND(FZ11+GN11+GO11,2) -> 0 | GR11: =$G11*GQ11 -> 0 | GS11: =IFERROR(ROUND(GQ11/GQ16*GS16,2),0) -> 0 | GZ11: =SUM(GU11:GY11) -> 0 | HB11: =GT11+GZ11+HA11 -> 0 | HD11: =GR11-GS11+HB11+HC11 -> 0 | HF11: =ROUND(GP11+HD11+HE11,2) -> 0 | HH11: =$G11*HG11 -> 0 | HI11: =IFERROR(ROUND(HG11/$HG$16*$HI$16,2),0) -> 0 | HP11: =SUM(HK11:HO11) -> 0 | HR11: =HJ11+HP11+HQ11 -> 0 | HT11: =HH11-HI11+HR11+HS11 -> 0 | HV11: =ROUND(HF11+HT11+HU11,2) -> 0 | HX11: =$G11*HW11 -> 0 | HY11: =IFERROR(ROUND(HW11/$HG$16*$HI$16,2),0) -> 0 | IF11: =SUM(IA11:IE11) -> 0 | IH11: =HZ11+IF11+IG11 -> 0 | IJ11: =HX11-HY11+IH11+II11 -> 0 | IL11: =ROUND(HV11+IJ11+IK11,2) -> 0 | IN11: =$G11*IM11 -> 0 | IO11: =IFERROR(ROUND(IM11/$HG$16*$HI$16,2),0) -> 0 | IV11: =SUM(IQ11:IU11) -> 0 | IX11: =IP11+IV11+IW11 -> 0 | IZ11: =IN11-IO11+IX11+IY11 -> 0 | JB11: =ROUND(IL11+IZ11+JA11,2) -> 0 | JD11: =$G11*JC11 -> 0 | JE11: =IFERROR(ROUND(JC11/$HG$16*$HI$16,2),0) -> 0 | JL11: =SUM(JG11:JK11) -> 0 | JN11: =JF11+JL11+JM11 -> 0 | JP11: =JD11-JE11+JN11+JO11 -> 0 | JR11: =ROUND(JB11+JP11+JQ11,2) -> 0 | JT11: =$G11*JS11 -> 0 | JU11: =IFERROR(ROUND(JS11/$HG$16*$HI$16,2),0) -> 0 | KB11: =SUM(JW11:KA11) -> 0 | KD11: =JV11+KB11+KC11 -> 0 | KF11: =JT11-JU11+KD11+KE11 -> 0 | KH11: =ROUND(JR11+KF11+KG11,2) -> 0 | KJ11: =$G11*KI11 -> 0 | KK11: =IFERROR(ROUND(KI11/$HG$16*$HI$16,2),0) -> 0 | KR11: =SUM(KM11:KQ11) -> 0 | KT11: =KL11+KR11+KS11 -> 0 | KV11: =KJ11-KK11+KT11+KU11 -> 0 | KX11: =ROUND(KH11+KV11+KW11,2) -> 0 | KZ11: =$G11*KY11 -> 0 | LA11: =IFERROR(ROUND(KY11/$HG$16*$HI$16,2),0) -> 0 | LH11: =SUM(LC11:LG11) -> 0 | LJ11: =LB11+LH11+LI11 -> 0 | LL11: =KZ11-LA11+LJ11+LK11 -> 0 | LN11: =ROUND(KX11+LL11+LM11,2) -> 0 | LP11: =$G11*LO11 -> 0 | LQ11: =IFERROR(ROUND(LO11/$HG$16*$HI$16,2),0) -> 0 | LX11: =SUM(LS11:LW11) -> 0 | LZ11: =LR11+LX11+LY11 -> 0 | MB11: =LP11-LQ11+LZ11+MA11 -> 0 | MD11: =ROUND(LN11+MB11+MC11,2) -> 0 | MF11: =$G11*ME11 -> 0 | MG11: =IFERROR(ROUND(ME11/$HG$16*$HI$16,2),0) -> 0 | MN11: =SUM(MI11:MM11) -> 0 | MP11: =MH11+MN11+MO11 -> 0 | MR11: =MF11-MG11+MP11+MQ11 -> 0 | MT11: =ROUND(MD11+MR11+MS11,2) -> 0 | MV11: =$G11*MU11 -> 0 | MW11: =IFERROR(ROUND(MU11/$HG$16*$HI$16,2),0) -> 0 | ND11: =SUM(MY11:NC11) -> 0 | NF11: =MX11+ND11+NE11 -> 0 | NH11: =MV11-MW11+NF11+NG11 -> 0 | NJ11: =ROUND(MT11+NH11+NI11,2) -> 0 | NL11: =$G11*NK11 -> 0 | NM11: =IFERROR(ROUND(NK11/$HG$16*$HI$16,2),0) -> 0 | NT11: =SUM(NO11:NS11) -> 0 | NV11: =NN11+NT11+NU11 -> 0 | NX11: =NL11-NM11+NV11+NW11 -> 0 | NZ11: =ROUND(NJ11+NX11+NY11,2) -> 0 | OB11: =$G11*OA11 -> 0 | OC11: =IFERROR(ROUND(OA11/$HG$16*$HI$16,2),0) -> 0 | OJ11: =SUM(OE11:OI11) -> 0 | OL11: =OD11+OJ11+OK11 -> 0 | ON11: =OB11-OC11+OL11+OM11 -> 0 | OP11: =ROUND(NZ11+ON11+OO11,2) -> 0 | OR11: =$G11*OQ11 -> 0 | OS11: =IFERROR(ROUND(OQ11/$HG$16*$HI$16,2),0) -> 0 | OZ11: =SUM(OU11:OY11) -> 0 | PB11: =OT11+OZ11+PA11 -> 0 | PD11: =OR11-OS11+PB11+PC11 -> 0 | PF11: =ROUND(OP11+PD11+PE11,2) -> 0 | PH11: =$H11*PG11 -> 0 | PI11: =PH11*0.6 -> 0 | PJ11: =JB11+PI11 -> 0
A12: КАМАЗ | B12: Самосвал камаз | C12: =INDEX(Позиция!$D$3:$D$22,MATCH(A12,Позиция!$C$3:$C$22,0)) -> Ладыжин-3 | D12: =INDEX(Позиция!$E$3:$E$22,MATCH(A12,Позиция!$C$3:$C$22,0)) -> 1 | E12: Староконстантинов | F12: 430.84 | G12: 461.84 | H12: 530.84 | J12: 15 | K12: =F12*J12 -> 6462.6 | L12: 4605.11 | M12: -6224 | P12: =SUM(M12:O12) -> -6224 | R12: =K12-L12+P12+Q12 -> -4366.51 | T12: =F12*S12 -> 0 | U12: =$U$16/$T$16*T12 -> 0 | Y12: =SUM(V12:X12) -> 0 | AA12: =T12-U12+Y12+Z12 -> 0 | AB12: =R12+AA12 -> -4366.51 | AD12: =F12*AC12 -> 0 | AE12: =$AE$16/$AD$16*AD12 -> 0 | AI12: =SUM(AF12:AH12) -> 0 | AK12: =AD12-AE12+AI12+AJ12 -> 0 | AL12: =AB12+AK12 -> -4366.51 | AN12: =F12*AM12 -> 0 | AO12: =$AO$16/$AN$16*AN12 -> 0 | AS12: =SUM(AP12:AR12) -> 0 | AU12: =AN12-AO12+AS12+AT12 -> 0 | AV12: =AL12+AU12 -> -4366.51 | AX12: =F12*AW12 -> 0 | AY12: =$AY$16/$AX$16*AX12 -> 0 | BC12: =SUM(AZ12:BB12) -> 0 | BE12: =AX12-AY12+BC12+BD12 -> 0 | BF12: =AV12+BE12 -> -4366.51 | BH12: =F12*BG12 -> 0 | BI12: =$BI$16/($BG$4+$BG$5+$BG$13+$BG$15)*BG12 -> 0 | BM12: =SUM(BJ12:BL12) -> 0 | BO12: =BH12-BI12+BM12+BN12 -> 0 | BP12: =BF12+BO12 -> -4366.51 | BR12: =F12*BQ12 -> 0 | BS12: 0 | BW12: =SUM(BT12:BV12) -> 0 | BY12: =BR12-BS12+BW12+BX12 -> 0 | BZ12: =BP12+BY12 -> -4366.51 | CB12: =$F12*CA12 -> 0 | CC12: =$CC$16/SUM($CA$4:$CA$15)*CA12 -> 0 | CG12: =SUM(CD12:CF12) -> 0 | CI12: =CB12-CC12+CG12+CH12 -> 0 | CJ12: =BZ12+CI12 -> -4366.51 | CK12: 55 | CL12: =$F12*CK12+11195.94 -> 34892.14 | CM12: =$CM$16/SUM($CK$4:$CK$15)*CK12 -> 29421.126 | CN12: =-10520.16/(CK12+CK29)*CK12 -> -9806.9288 | CO12: =(-9447.9-6555.85)/(CK12+CK29)*CK12 -> -14918.75 | CP12: =-7940/(CK12+CK29)*CK12 -> -7401.6949 | CQ12: =SUM(CN12:CP12) -> -32127.374 | CS12: =CL12-CM12+CQ12+CR12 -> -26656.36 | CT12: =CJ12+CS12 -> -31022.87 | CV12: =$F12*CU12 -> 0 | CW12: =$CW$16/SUM($CU$4:$CU$15)*CU12 -> 0 | CX12: -11590 | CY12: -7028.6 | DA12: =SUM(CX12:CZ12) -> -18618.6 | DC12: =CV12-CW12+DA12+DB12 -> -18618.6 | DD12: -10865.98 | DE12: =ROUND(CT12+DC12+DD12,2) -> -60507.45 | DF12: 100 | DG12: =$F12*DF12 -> 43084 | DH12: =ROUND(DF12/$DF$16*$DH$16,2) -> 16978.36 | DI12: -6070.95 | DJ12: -4560.12 | DM12: =SUM(DJ12:DL12) -> -4560.12 | DO12: =DI12+DM12+DN12 -> -10631.07 | DQ12: =DG12-DH12+DO12+DP12 -> 15474.57 | DS12: =ROUND(DE12+DQ12+DR12,2) -> -45032.88 | DU12: =$G12*DT12 -> 0 | DV12: =IFERROR(ROUND(DT12/DT16*DV16,2),0) -> 0 | EA12: =SUM(DX12:DZ12) -> 0 | EC12: =DW12+EA12+EB12 -> 0 | EE12: =DU12-DV12+EC12+ED12 -> 0 | EF12: =--45032.88 -> 45032.88 | EG12: =ROUND(DS12+EE12+EF12,2) -> 0 | EI12: =$G12*EH12 -> 0 | EJ12: =IFERROR(ROUND(EH12/EH16*EJ16,2),0) -> 0 | EP12: =SUM(EL12:EO12) -> 0 | ER12: =EK12+EP12+EQ12 -> 0 | ET12: =EI12-EJ12+ER12+ES12 -> 0 | EV12: =ROUND(EG12+ET12+EU12,2) -> 0 | EX12: =$G12*EW12 -> 0 | EY12: =IFERROR(ROUND(EW12/EW16*EY16,2),0) -> 0 | FE12: =SUM(FA12:FD12) -> 0 | FG12: =EZ12+FE12+FF12 -> 0 | FI12: =EX12-EY12+FG12+FH12 -> 0 | FK12: =ROUND(EV12+FI12+FJ12,2) -> 0 | FM12: =$G12*FL12 -> 0 | FN12: =IFERROR(ROUND(FL12/FL16*FN16,2),0) -> 0 | FT12: =SUM(FP12:FS12) -> 0 | FV12: =FO12+FT12+FU12 -> 0 | FX12: =FM12-FN12+FV12+FW12 -> 0 | FZ12: =ROUND(FK12+FX12+FY12,2) -> 0 | GB12: =$G12*GA12 -> 0 | GC12: =IFERROR(ROUND(GA12/GA16*GC16,2),0) -> 0 | GJ12: =SUM(GE12:GI12) -> 0 | GL12: =GD12+GJ12+GK12 -> 0 | GN12: =GB12-GC12+GL12+GM12 -> 0 | GP12: =ROUND(FZ12+GN12+GO12,2) -> 0 | GR12: =$G12*GQ12 -> 0 | GS12: =IFERROR(ROUND(GQ12/GQ16*GS16,2),0) -> 0 | GZ12: =SUM(GU12:GY12) -> 0 | HB12: =GT12+GZ12+HA12 -> 0 | HD12: =GR12-GS12+HB12+HC12 -> 0 | HF12: =ROUND(GP12+HD12+HE12,2) -> 0 | HH12: =$G12*HG12 -> 0 | HI12: =IFERROR(ROUND(HG12/$HG$16*$HI$16,2),0) -> 0 | HP12: =SUM(HK12:HO12) -> 0 | HR12: =HJ12+HP12+HQ12 -> 0 | HT12: =HH12-HI12+HR12+HS12 -> 0 | HV12: =ROUND(HF12+HT12+HU12,2) -> 0 | HX12: =$G12*HW12 -> 0 | HY12: =IFERROR(ROUND(HW12/$HG$16*$HI$16,2),0) -> 0 | IF12: =SUM(IA12:IE12) -> 0 | IH12: =HZ12+IF12+IG12 -> 0 | IJ12: =HX12-HY12+IH12+II12 -> 0 | IL12: =ROUND(HV12+IJ12+IK12,2) -> 0 | IN12: =$G12*IM12 -> 0 | IO12: =IFERROR(ROUND(IM12/$HG$16*$HI$16,2),0) -> 0 | IV12: =SUM(IQ12:IU12) -> 0 | IX12: =IP12+IV12+IW12 -> 0 | IZ12: =IN12-IO12+IX12+IY12 -> 0 | JB12: =ROUND(IL12+IZ12+JA12,2) -> 0 | JD12: =$G12*JC12 -> 0 | JE12: =IFERROR(ROUND(JC12/$HG$16*$HI$16,2),0) -> 0 | JL12: =SUM(JG12:JK12) -> 0 | JN12: =JF12+JL12+JM12 -> 0 | JP12: =JD12-JE12+JN12+JO12 -> 0 | JR12: =ROUND(JB12+JP12+JQ12,2) -> 0 | JT12: =$G12*JS12 -> 0 | JU12: =IFERROR(ROUND(JS12/$HG$16*$HI$16,2),0) -> 0 | KB12: =SUM(JW12:KA12) -> 0 | KD12: =JV12+KB12+KC12 -> 0 | KF12: =JT12-JU12+KD12+KE12 -> 0 | KH12: =ROUND(JR12+KF12+KG12,2) -> 0 | KJ12: =$G12*KI12 -> 0 | KK12: =IFERROR(ROUND(KI12/$HG$16*$HI$16,2),0) -> 0 | KR12: =SUM(KM12:KQ12) -> 0 | KT12: =KL12+KR12+KS12 -> 0 | KV12: =KJ12-KK12+KT12+KU12 -> 0 | KX12: =ROUND(KH12+KV12+KW12,2) -> 0 | KZ12: =$G12*KY12 -> 0 | LA12: =IFERROR(ROUND(KY12/$HG$16*$HI$16,2),0) -> 0 | LH12: =SUM(LC12:LG12) -> 0 | LJ12: =LB12+LH12+LI12 -> 0 | LL12: =KZ12-LA12+LJ12+LK12 -> 0 | LN12: =ROUND(KX12+LL12+LM12,2) -> 0 | LP12: =$G12*LO12 -> 0 | LQ12: =IFERROR(ROUND(LO12/$HG$16*$HI$16,2),0) -> 0 | LX12: =SUM(LS12:LW12) -> 0 | LZ12: =LR12+LX12+LY12 -> 0 | MB12: =LP12-LQ12+LZ12+MA12 -> 0 | MD12: =ROUND(LN12+MB12+MC12,2) -> 0 | MF12: =$G12*ME12 -> 0 | MG12: =IFERROR(ROUND(ME12/$HG$16*$HI$16,2),0) -> 0 | MN12: =SUM(MI12:MM12) -> 0 | MP12: =MH12+MN12+MO12 -> 0 | MR12: =MF12-MG12+MP12+MQ12 -> 0 | MT12: =ROUND(MD12+MR12+MS12,2) -> 0 | MV12: =$G12*MU12 -> 0 | MW12: =IFERROR(ROUND(MU12/$HG$16*$HI$16,2),0) -> 0 | ND12: =SUM(MY12:NC12) -> 0 | NF12: =MX12+ND12+NE12 -> 0 | NH12: =MV12-MW12+NF12+NG12 -> 0 | NJ12: =ROUND(MT12+NH12+NI12,2) -> 0 | NL12: =$G12*NK12 -> 0 | NM12: =IFERROR(ROUND(NK12/$HG$16*$HI$16,2),0) -> 0 | NT12: =SUM(NO12:NS12) -> 0 | NV12: =NN12+NT12+NU12 -> 0 | NX12: =NL12-NM12+NV12+NW12 -> 0 | NZ12: =ROUND(NJ12+NX12+NY12,2) -> 0 | OB12: =$G12*OA12 -> 0 | OC12: =IFERROR(ROUND(OA12/$HG$16*$HI$16,2),0) -> 0 | OJ12: =SUM(OE12:OI12) -> 0 | OL12: =OD12+OJ12+OK12 -> 0 | ON12: =OB12-OC12+OL12+OM12 -> 0 | OP12: =ROUND(NZ12+ON12+OO12,2) -> 0 | OR12: =$G12*OQ12 -> 0 | OS12: =IFERROR(ROUND(OQ12/$HG$16*$HI$16,2),0) -> 0 | OZ12: =SUM(OU12:OY12) -> 0 | PB12: =OT12+OZ12+PA12 -> 0 | PD12: =OR12-OS12+PB12+PC12 -> 0 | PF12: =ROUND(OP12+PD12+PE12,2) -> 0 | PH12: =$H12*PG12 -> 0 | PI12: =PH12*0.6 -> 0 | PJ12: =JB12+PI12 -> 0
A13: Клинцы | B13: Автокран клинцы | C13: =INDEX(Позиция!$D$3:$D$22,MATCH(A13,Позиция!$C$3:$C$22,0)) -> Крушинка | D13: =INDEX(Позиция!$E$3:$E$22,MATCH(A13,Позиция!$C$3:$C$22,0)) -> 1 | E13: Староконстантинов | F13: 490.46 | G13: 529.22 | H13: 649.39 | K13: =F13*J13 -> 0 | P13: =SUM(M13:O13) -> 0 | R13: =K13-L13+P13+Q13 -> 0 | T13: =F13*S13 -> 0 | U13: =$U$16/$T$16*T13 -> 0 | Y13: =SUM(V13:X13) -> 0 | AA13: =T13-U13+Y13+Z13 -> 0 | AB13: =R13+AA13 -> 0 | AC13: 34 | AD13: =F13*AC13 -> 16675.64 | AE13: =$AE$16/$AD$16*AD13 -> 15949.476 | AF13: -2962.86 | AG13: -5322.8847 | AH13: -785.83 | AI13: =SUM(AF13:AH13) -> -9071.5747 | AK13: =AD13-AE13+AI13+AJ13 -> -8345.411 | AL13: =AB13+AK13 -> -8345.411 | AM13: 179 | AN13: =F13*AM13 -> 87792.34 | AO13: =$AO$16/$AN$16*AN13 -> 39561.347 | AP13: -11590 | AQ13: -26559.13 | AS13: =SUM(AP13:AR13) -> -38149.13 | AU13: =AN13-AO13+AS13+AT13 -> 10081.863 | AV13: =AL13+AU13 -> 1736.4523 | AW13: 198 | AX13: =F13*AW13 -> 97111.08 | AY13: =$AY$16/$AX$16*AX13 -> 72303.271 | AZ13: -11590 | BA13: -6935.41 | BC13: =SUM(AZ13:BB13) -> -18525.41 | BE13: =AX13-AY13+BC13+BD13 -> 6282.3995 | BF13: =AV13+BE13 -> 8018.8518 | BG13: =апрель!E11 -> 117 | BH13: =F13*BG13 -> 57383.82 | BI13: =$BI$16/($BG$4+$BG$5+$BG$13+$BG$15)*BG13 -> 65304.362 | BJ13: =-апрель!N11-апрель!O11-апрель!P11 -> -11206.86 | BK13: =-8453.1/(BG13+BG168)*BG13 -> -8173.6587 | BM13: =SUM(BJ13:BL13) -> -19380.518 | BO13: =BH13-BI13+BM13+BN13 -> -27301.06 | BP13: =BF13+BO13 -> -19282.208 | BQ13: 23 | BR13: =F13*BQ13 -> 11280.58 | BS13: 0 | BT13: =-май!C7 -> -6017.48 | BU13: =май!H5 -> -7886.96 | BW13: =SUM(BT13:BV13) -> -13904.44 | BY13: =BR13-BS13+BW13+BX13 -> -2623.86 | BZ13: =BP13+BY13 -> -21906.068 | CA13: 130 | CB13: =$F13*CA13 -> 63759.8 | CC13: =$CC$16/SUM($CA$4:$CA$15)*CA13 -> 74286.136 | CD13: -11590 | CE13: 4049 | CG13: =SUM(CD13:CF13) -> -7541 | CI13: =CB13-CC13+CG13+CH13 -> -18067.336 | CJ13: =BZ13+CI13 -> -39973.404 | CK13: 145 | CL13: =$F13*CK13 -> 71116.7 | CM13: =$CM$16/SUM($CK$4:$CK$15)*CK13 -> 77564.788 | CN13: -11590 | CO13: -10610.19 | CP13: -6360 | CQ13: =SUM(CN13:CP13) -> -28560.19 | CS13: =CL13-CM13+CQ13+CR13 -> -35008.278 | CT13: =CJ13+CS13 -> -74981.682 | CV13: =$F13*CU13 -> 0 | CW13: =$CW$16/SUM($CU$4:$CU$15)*CU13 -> 0 | DA13: =SUM(CX13:CZ13) -> 0 | DC13: =CV13-CW13+DA13+DB13 -> 0 | DD13: =--86571.68 -> 86571.68 | DE13: =ROUND(CT13+DC13+DD13,2) -> 11590 | DG13: =$F13*DF13 -> 0 | DH13: =ROUND(DF13/$DF$16*$DH$16,2) -> 0 | DO13: =DI13+DM13+DN13 -> 0 | DQ13: =DG13-DH13+DO13+DP13 -> 0 | DS13: =ROUND(DE13+DQ13+DR13,2) -> 11590 | DU13: =$G13*DT13 -> 0 | DV13: =IFERROR(ROUND(DT13/DT16*DV16,2),0) -> 0 | EA13: =SUM(DX13:DZ13) -> 0 | EC13: =DW13+EA13+EB13 -> 0 | EE13: =DU13-DV13+EC13+ED13 -> 0 | EF13: -11590 | EG13: =ROUND(DS13+EE13+EF13,2) -> 0 | EI13: =$G13*EH13 -> 0 | EJ13: =IFERROR(ROUND(EH13/EH16*EJ16,2),0) -> 0 | EP13: =SUM(EL13:EO13) -> 0 | ER13: =EK13+EP13+EQ13 -> 0 | ET13: =EI13-EJ13+ER13+ES13 -> 0 | EV13: =ROUND(EG13+ET13+EU13,2) -> 0 | EX13: =$G13*EW13 -> 0 | EY13: =IFERROR(ROUND(EW13/EW16*EY16,2),0) -> 0 | FE13: =SUM(FA13:FD13) -> 0 | FG13: =EZ13+FE13+FF13 -> 0 | FI13: =EX13-EY13+FG13+FH13 -> 0 | FK13: =ROUND(EV13+FI13+FJ13,2) -> 0 | FM13: =$G13*FL13 -> 0 | FN13: =IFERROR(ROUND(FL13/FL16*FN16,2),0) -> 0 | FT13: =SUM(FP13:FS13) -> 0 | FV13: =FO13+FT13+FU13 -> 0 | FX13: =FM13-FN13+FV13+FW13 -> 0 | FZ13: =ROUND(FK13+FX13+FY13,2) -> 0 | GB13: =$G13*GA13 -> 0 | GC13: =IFERROR(ROUND(GA13/GA16*GC16,2),0) -> 0 | GJ13: =SUM(GE13:GI13) -> 0 | GL13: =GD13+GJ13+GK13 -> 0 | GN13: =GB13-GC13+GL13+GM13 -> 0 | GP13: =ROUND(FZ13+GN13+GO13,2) -> 0 | GR13: =$G13*GQ13 -> 0 | GS13: =IFERROR(ROUND(GQ13/GQ16*GS16,2),0) -> 0 | GZ13: =SUM(GU13:GY13) -> 0 | HB13: =GT13+GZ13+HA13 -> 0 | HD13: =GR13-GS13+HB13+HC13 -> 0 | HF13: =ROUND(GP13+HD13+HE13,2) -> 0 | HH13: =$G13*HG13 -> 0 | HI13: =IFERROR(ROUND(HG13/$HG$16*$HI$16,2),0) -> 0 | HP13: =SUM(HK13:HO13) -> 0 | HR13: =HJ13+HP13+HQ13 -> 0 | HT13: =HH13-HI13+HR13+HS13 -> 0 | HV13: =ROUND(HF13+HT13+HU13,2) -> 0 | HX13: =$G13*HW13 -> 0 | HY13: =IFERROR(ROUND(HW13/$HG$16*$HI$16,2),0) -> 0 | IF13: =SUM(IA13:IE13) -> 0 | IH13: =HZ13+IF13+IG13 -> 0 | IJ13: =HX13-HY13+IH13+II13 -> 0 | IL13: =ROUND(HV13+IJ13+IK13,2) -> 0 | IN13: =$G13*IM13 -> 0 | IO13: =IFERROR(ROUND(IM13/$HG$16*$HI$16,2),0) -> 0 | IV13: =SUM(IQ13:IU13) -> 0 | IX13: =IP13+IV13+IW13 -> 0 | IZ13: =IN13-IO13+IX13+IY13 -> 0 | JB13: =ROUND(IL13+IZ13+JA13,2) -> 0 | JD13: =$G13*JC13 -> 0 | JE13: =IFERROR(ROUND(JC13/$HG$16*$HI$16,2),0) -> 0 | JL13: =SUM(JG13:JK13) -> 0 | JN13: =JF13+JL13+JM13 -> 0 | JP13: =JD13-JE13+JN13+JO13 -> 0 | JR13: =ROUND(JB13+JP13+JQ13,2) -> 0 | JT13: =$G13*JS13 -> 0 | JU13: =IFERROR(ROUND(JS13/$HG$16*$HI$16,2),0) -> 0 | KB13: =SUM(JW13:KA13) -> 0 | KD13: =JV13+KB13+KC13 -> 0 | KF13: =JT13-JU13+KD13+KE13 -> 0 | KH13: =ROUND(JR13+KF13+KG13,2) -> 0 | KJ13: =$G13*KI13 -> 0 | KK13: =IFERROR(ROUND(KI13/$HG$16*$HI$16,2),0) -> 0 | KR13: =SUM(KM13:KQ13) -> 0 | KT13: =KL13+KR13+KS13 -> 0 | KV13: =KJ13-KK13+KT13+KU13 -> 0 | KX13: =ROUND(KH13+KV13+KW13,2) -> 0 | KZ13: =$G13*KY13 -> 0 | LA13: =IFERROR(ROUND(KY13/$HG$16*$HI$16,2),0) -> 0 | LH13: =SUM(LC13:LG13) -> 0 | LJ13: =LB13+LH13+LI13 -> 0 | LL13: =KZ13-LA13+LJ13+LK13 -> 0 | LN13: =ROUND(KX13+LL13+LM13,2) -> 0 | LP13: =$G13*LO13 -> 0 | LQ13: =IFERROR(ROUND(LO13/$HG$16*$HI$16,2),0) -> 0 | LX13: =SUM(LS13:LW13) -> 0 | LZ13: =LR13+LX13+LY13 -> 0 | MB13: =LP13-LQ13+LZ13+MA13 -> 0 | MD13: =ROUND(LN13+MB13+MC13,2) -> 0 | MF13: =$G13*ME13 -> 0 | MG13: =IFERROR(ROUND(ME13/$HG$16*$HI$16,2),0) -> 0 | MN13: =SUM(MI13:MM13) -> 0 | MP13: =MH13+MN13+MO13 -> 0 | MR13: =MF13-MG13+MP13+MQ13 -> 0 | MT13: =ROUND(MD13+MR13+MS13,2) -> 0 | MV13: =$G13*MU13 -> 0 | MW13: =IFERROR(ROUND(MU13/$HG$16*$HI$16,2),0) -> 0 | ND13: =SUM(MY13:NC13) -> 0 | NF13: =MX13+ND13+NE13 -> 0 | NH13: =MV13-MW13+NF13+NG13 -> 0 | NJ13: =ROUND(MT13+NH13+NI13,2) -> 0 | NL13: =$G13*NK13 -> 0 | NM13: =IFERROR(ROUND(NK13/$HG$16*$HI$16,2),0) -> 0 | NT13: =SUM(NO13:NS13) -> 0 | NV13: =NN13+NT13+NU13 -> 0 | NX13: =NL13-NM13+NV13+NW13 -> 0 | NZ13: =ROUND(NJ13+NX13+NY13,2) -> 0 | OB13: =$G13*OA13 -> 0 | OC13: =IFERROR(ROUND(OA13/$HG$16*$HI$16,2),0) -> 0 | OJ13: =SUM(OE13:OI13) -> 0 | OL13: =OD13+OJ13+OK13 -> 0 | ON13: =OB13-OC13+OL13+OM13 -> 0 | OP13: =ROUND(NZ13+ON13+OO13,2) -> 0 | OR13: =$G13*OQ13 -> 0 | OS13: =IFERROR(ROUND(OQ13/$HG$16*$HI$16,2),0) -> 0 | OZ13: =SUM(OU13:OY13) -> 0 | PB13: =OT13+OZ13+PA13 -> 0 | PD13: =OR13-OS13+PB13+PC13 -> 0 | PF13: =ROUND(OP13+PD13+PE13,2) -> 0 | PH13: =$H13*PG13 -> 0 | PI13: =PH13*0.6 -> 0 | PJ13: =JB13+PI13 -> 0
A14: Телескоп 5 | B14: Ротор Пегасус | C14: =INDEX(Позиция!$D$3:$D$22,MATCH(A14,Позиция!$C$3:$C$22,0)) -> Ретал | D14: =INDEX(Позиция!$E$3:$E$22,MATCH(A14,Позиция!$C$3:$C$22,0)) -> 0 | E14: Староконстантинов | F14: 592.98 | G14: 494.88 | H14: 579.13 | CV14: =$F14*CU14 -> 0 | CW14: =$CW$16/SUM($CU$4:$CU$15)*CU14 -> 0 | DA14: =SUM(CX14:CZ14) -> 0 | DC14: =CV14-CW14+DA14+DB14 -> 0 | DE14: =ROUND(CT14+DC14+DD14,2) -> 0 | DG14: =$F14*DF14 -> 0 | DH14: =ROUND(DF14/$DF$16*$DH$16,2) -> 0 | DO14: =DI14+DM14+DN14 -> 0 | DQ14: =DG14-DH14+DO14+DP14 -> 0 | DS14: =ROUND(DE14+DQ14+DR14,2) -> 0 | DU14: =$G14*DT14 -> 0 | DV14: =IFERROR(ROUND(DT14/DT16*DV16,2),0) -> 0 | EA14: =SUM(DX14:DZ14) -> 0 | EC14: =DW14+EA14+EB14 -> 0 | EE14: =DU14-DV14+EC14+ED14 -> 0 | EG14: =ROUND(DS14+EE14+EF14,2) -> 0 | EI14: =$G14*EH14 -> 0 | EJ14: =IFERROR(ROUND(EH14/EH16*EJ16,2),0) -> 0 | EP14: =SUM(EL14:EO14) -> 0 | ER14: =EK14+EP14+EQ14 -> 0 | ET14: =EI14-EJ14+ER14+ES14 -> 0 | EV14: =ROUND(EG14+ET14+EU14,2) -> 0 | EX14: =$G14*EW14 -> 0 | EY14: =IFERROR(ROUND(EW14/EW16*EY16,2),0) -> 0 | FE14: =SUM(FA14:FD14) -> 0 | FG14: =EZ14+FE14+FF14 -> 0 | FI14: =EX14-EY14+FG14+FH14 -> 0 | FK14: =ROUND(EV14+FI14+FJ14,2) -> 0 | FM14: =$G14*FL14 -> 0 | FN14: =IFERROR(ROUND(FL14/FL16*FN16,2),0) -> 0 | FT14: =SUM(FP14:FS14) -> 0 | FV14: =FO14+FT14+FU14 -> 0 | FX14: =FM14-FN14+FV14+FW14 -> 0 | FZ14: =ROUND(FK14+FX14+FY14,2) -> 0 | GA14: 149 | GB14: =$G14*GA14 -> 73737.12 | GC14: =GC16-GC5 -> 71158.18 | GD14: -10170.225 | GE14: -9598 | GI14: -17091.18 | GJ14: =SUM(GE14:GI14) -> -26689.18 | GL14: =GD14+GJ14+GK14 -> -36859.405 | GN14: =GB14-GC14+GL14+GM14 -> -34280.465 | GP14: =ROUND(FZ14+GN14+GO14,2) -> -34280.47 | GQ14: 150 | GR14: =$G14*GQ14 -> 74232 | GS14: =IFERROR(ROUND(GQ14/GQ16*GS16,2),0) -> 32603.34 | GT14: -12053.6 | GU14: -24295 | GZ14: =SUM(GU14:GY14) -> -24295 | HB14: =GT14+GZ14+HA14 -> -36348.6 | HD14: =GR14-GS14+HB14+HC14 -> 5280.06 | HF14: =ROUND(GP14+HD14+HE14,2) -> -29000.41 | HG14: 146 | HH14: =$G14*HG14 -> 72252.48 | HI14: =IFERROR(ROUND(HG14/$HG$16*$HI$16,2),0) -> 4877.62 | HJ14: -9589.6 | HK14: -20346 | HP14: =SUM(HK14:HO14) -> -20346 | HR14: =HJ14+HP14+HQ14 -> -29935.6 | HT14: =HH14-HI14+HR14+HS14 -> 37439.26 | HV14: =ROUND(HF14+HT14+HU14,2) -> 8438.85 | HW14: 195 | HX14: =$G14*HW14 -> 96501.6 | HY14: =IFERROR(ROUND(HW14/HW16*HY16,2),0) -> 34829.03 | HZ14: -12053.6 | IA14: -39592 | IF14: =SUM(IA14:IE14) -> -39592 | IH14: =HZ14+IF14+IG14 -> -51645.6 | IJ14: =HX14-HY14+IH14+II14 -> 10026.97 | IL14: =ROUND(HV14+IJ14+IK14,2) -> 18465.82 | IM14: 5 | IN14: =$G14*IM14 -> 2474.4 | IO14: =IFERROR(ROUND(IM14/IM16*IO16,2),0) -> 14345.52 | IP14: -871.18 | IV14: =SUM(IQ14:IU14) -> 0 | IX14: =IP14+IV14+IW14 -> -871.18 | IZ14: =IN14-IO14+IX14+IY14 -> -12742.3 | JA14: -6472.48 | JB14: =ROUND(IL14+IZ14+JA14,2) -> -748.96 | JC14: 2 | JD14: =$H14*JC14 -> 1158.26 | JE14: =IFERROR(ROUND(JC14/JC16*JE16,2),0) -> 0 | JL14: =SUM(JG14:JK14) -> 0 | JN14: =JF14+JL14+JM14 -> 0 | JP14: =JD14-JE14+JN14+JO14 -> 1158.26 | JR14: =ROUND(JB14+JP14+JQ14,2) -> 409.3 | JS14: 69 | JT14: =$H14*JS14 -> 39959.97 | JU14: =IFERROR(ROUND(JS14/JS16*JU16,2),0) -> 0 | JV14: -6707.55 | JW14: -10287.9 | KB14: =SUM(JW14:KA14) -> -10287.9 | KD14: =JV14+KB14+KC14 -> -16995.45 | KF14: =JT14-JU14+KD14+KE14 -> 22964.52 | KH14: =ROUND(JR14+KF14+KG14,2) -> 23373.82 | KI14: 36 | KJ14: =$H14*KI14 -> 20848.68 | KK14: =IFERROR(ROUND(KI14/KI16*KK16,2),0) -> 0 | KL14: -2749.42 | KR14: =SUM(KM14:KQ14) -> 0 | KT14: =KL14+KR14+KS14 -> -2749.42 | KV14: =KJ14-KK14+KT14+KU14 -> 18099.26 | KX14: =ROUND(KH14+KV14+KW14,2) -> 41473.08 | KZ14: =$H14*KY14 -> 0 | LA14: =LA16 -> 41473.08 | LH14: =SUM(LC14:LG14) -> 0 | LJ14: =LB14+LH14+LI14 -> 0 | LL14: =KZ14-LA14+LJ14+LK14 -> -41473.08 | LN14: =ROUND(KX14+LL14+LM14,2) -> 0 | LP14: =$H14*LO14 -> 0 | LQ14: =LQ16 -> 0 | LX14: =SUM(LS14:LW14) -> 0 | LZ14: =LR14+LX14+LY14 -> 0 | MB14: =LP14-LQ14+LZ14+MA14 -> 0 | MD14: =ROUND(LN14+MB14+MC14,2) -> 0 | MF14: =$H14*ME14 -> 0 | MG14: =MG16 -> 0 | MN14: =SUM(MI14:MM14) -> 0 | MP14: =MH14+MN14+MO14 -> 0 | MR14: =MF14-MG14+MP14+MQ14 -> 0 | MT14: =ROUND(MD14+MR14+MS14,2) -> 0 | MV14: =$H14*MU14 -> 0 | MW14: =MW16 -> 0 | ND14: =SUM(MY14:NC14) -> 0 | NF14: =MX14+ND14+NE14 -> 0 | NH14: =MV14-MW14+NF14+NG14 -> 0 | NJ14: =ROUND(MT14+NH14+NI14,2) -> 0 | NL14: =$H14*NK14 -> 0 | NM14: =NM16 -> 0 | NT14: =SUM(NO14:NS14) -> 0 | NV14: =NN14+NT14+NU14 -> 0 | NX14: =NL14-NM14+NV14+NW14 -> 0 | NZ14: =ROUND(NJ14+NX14+NY14,2) -> 0 | OB14: =$H14*OA14 -> 0 | OC14: =OC16 -> 0 | OJ14: =SUM(OE14:OI14) -> 0 | OL14: =OD14+OJ14+OK14 -> 0 | ON14: =OB14-OC14+OL14+OM14 -> 0 | OP14: =ROUND(NZ14+ON14+OO14,2) -> 0 | OR14: =$H14*OQ14 -> 0 | OS14: =OS16 -> 0 | OZ14: =SUM(OU14:OY14) -> 0 | PB14: =OT14+OZ14+PA14 -> 0 | PD14: =OR14-OS14+PB14+PC14 -> 0 | PF14: =ROUND(OP14+PD14+PE14,2) -> 0 | PH14: =$H14*PG14 -> 0 | PI14: =PH14*0.6 -> 0 | PJ14: =LN14+PI14 -> 0
A15: Автокран XCMG | B15: Автокран XCMG | C15: =INDEX(Позиция!$D$3:$D$22,MATCH(A15,Позиция!$C$3:$C$22,0)) -> Ладыжин-3 с 14.11.2023 | D15: =INDEX(Позиция!$E$3:$E$22,MATCH(A15,Позиция!$C$3:$C$22,0)) -> 1 | E15: Староконстантинов | F15: 563.19 | G15: 601.95 | H15: 722.13 | K15: =F15*J15 -> 0 | P15: =SUM(M15:O15) -> 0 | R15: =K15-L15+P15+Q15 -> 0 | S15: 174 | T15: =F15*S15 -> 97995.06 | U15: =$U$16/$T$16*T15 -> 1352.8659 | V15: -9934.29 | W15: -46126.22 | Y15: =SUM(V15:X15) -> -56060.51 | AA15: =T15-U15+Y15+Z15 -> 40581.684 | AB15: =R15+AA15 -> 40581.684 | AC15: 154 | AD15: =F15*AC15 -> 86731.26 | AE15: =$AE$16/$AD$16*AD15 -> 82954.428 | AF15: -11350.94 | AG15: -19010.47 | AI15: =SUM(AF15:AH15) -> -30361.41 | AK15: =AD15-AE15+AI15+AJ15 -> -26584.578 | AL15: =AB15+AK15 -> 13997.106 | AM15: 189 | AN15: =F15*AM15 -> 106442.91 | AO15: =$AO$16/$AN$16*AN15 -> 47965.744 | AP15: =-11590 -> -11590 | AQ15: -22085.61 | AS15: =SUM(AP15:AR15) -> -33675.61 | AU15: =AN15-AO15+AS15+AT15 -> 24801.556 | AV15: =AL15+AU15 -> 38798.663 | AW15: 218 | AX15: =F15*AW15 -> 122775.42 | AY15: =$AY$16/$AX$16*AX15 -> 91411.448 | AZ15: -11590 | BA15: =-(20944.14+5458.8) -> -26402.94 | BC15: =SUM(AZ15:BB15) -> -37992.94 | BE15: =AX15-AY15+BC15+BD15 -> -6628.9677 | BF15: =AV15+BE15 -> 32169.695 | BG15: =апрель!E10 -> 150 | BH15: =F15*BG15 -> 84478.5 | BI15: =$BI$16/($BG$4+$BG$5+$BG$13+$BG$15)*BG15 -> 83723.541 | BJ15: =-апрель!N10-апрель!O10-апрель!P10 -> -11590 | BK15: -5458.8 | BM15: =SUM(BJ15:BL15) -> -17048.8 | BO15: =BH15-BI15+BM15+BN15 -> -16293.841 | BP15: =BF15+BO15 -> 15875.854 | BQ15: 198 | BR15: =F15*BQ15 -> 111511.62 | BS15: 0 | BT15: =-май!C3 -> -10134.68 | BU15: =май!H4 -> -16412.06 | BW15: =SUM(BT15:BV15) -> -26546.74 | BY15: =BR15-BS15+BW15+BX15 -> 84964.88 | BZ15: =BP15+BY15 -> 100840.73 | CA15: 40 | CB15: =$F15*CA15 -> 22527.6 | CC15: =$CC$16/SUM($CA$4:$CA$15)*CA15 -> 22857.273 | CD15: =-12448/(40+182)*40 -> -2242.8829 | CE15: =-1115.54054054054-1009 -> -2124.5405 | CF15: =(-2500-4792)*0 -> 0 | CG15: =SUM(CD15:CF15) -> -4367.4234 | CI15: =CB15-CC15+CG15+CH15 -> -4697.0962 | CJ15: =BZ15+CI15 -> 96143.638 | CL15: =$F15*CK15 -> 0 | CM15: =$CM$16/SUM($CK$4:$CK$15)*CK15 -> 0 | CQ15: =SUM(CN15:CP15) -> 0 | CS15: =CL15-CM15+CQ15+CR15 -> 0 | CT15: =CJ15+CS15 -> 96143.638 | CV15: =$F15*CU15 -> 0 | CW15: =$CW$16/SUM($CU$4:$CU$15)*CU15 -> 0 | DA15: =SUM(CX15:CZ15) -> 0 | DC15: =CV15-CW15+DA15+DB15 -> 0 | DD15: -96143.64 | DE15: =ROUND(CT15+DC15+DD15,2) -> 0 | DG15: =$F15*DF15 -> 0 | DH15: =ROUND(DF15/$DF$16*$DH$16,2) -> 0 | DO15: =DI15+DM15+DN15 -> 0 | DQ15: =DG15-DH15+DO15+DP15 -> 0 | DS15: =ROUND(DE15+DQ15+DR15,2) -> 0 | DU15: =$G15*DT15 -> 0 | DV15: =IFERROR(ROUND(DT15/DT16*DV16,2),0) -> 0 | EA15: =SUM(DX15:DZ15) -> 0 | EC15: =DW15+EA15+EB15 -> 0 | EE15: =DU15-DV15+EC15+ED15 -> 0 | EG15: =ROUND(DS15+EE15+EF15,2) -> 0 | EI15: =$G15*EH15 -> 0 | EJ15: =IFERROR(ROUND(EH15/EH16*EJ16,2),0) -> 0 | EP15: =SUM(EL15:EO15) -> 0 | ER15: =EK15+EP15+EQ15 -> 0 | ET15: =EI15-EJ15+ER15+ES15 -> 0 | EV15: =ROUND(EG15+ET15+EU15,2) -> 0 | EX15: =$G15*EW15 -> 0 | EY15: =IFERROR(ROUND(EW15/EW16*EY16,2),0) -> 0 | FE15: =SUM(FA15:FD15) -> 0 | FG15: =EZ15+FE15+FF15 -> 0 | FI15: =EX15-EY15+FG15+FH15 -> 0 | FK15: =ROUND(EV15+FI15+FJ15,2) -> 0 | FM15: =$G15*FL15 -> 0 | FN15: =IFERROR(ROUND(FL15/FL16*FN16,2),0) -> 0 | FT15: =SUM(FP15:FS15) -> 0 | FV15: =FO15+FT15+FU15 -> 0 | FX15: =FM15-FN15+FV15+FW15 -> 0 | FZ15: =ROUND(FK15+FX15+FY15,2) -> 0 | GB15: =$G15*GA15 -> 0 | GC15: =IFERROR(ROUND(GA15/GA16*GC16,2),0) -> 0 | GJ15: =SUM(GE15:GI15) -> 0 | GL15: =GD15+GJ15+GK15 -> 0 | GN15: =GB15-GC15+GL15+GM15 -> 0 | GP15: =ROUND(FZ15+GN15+GO15,2) -> 0 | GR15: =$G15*GQ15 -> 0 | GS15: =IFERROR(ROUND(GQ15/GQ16*GS16,2),0) -> 0 | GZ15: =SUM(GU15:GY15) -> 0 | HB15: =GT15+GZ15+HA15 -> 0 | HD15: =GR15-GS15+HB15+HC15 -> 0 | HF15: =ROUND(GP15+HD15+HE15,2) -> 0 | HH15: =$G15*HG15 -> 0 | HI15: =IFERROR(ROUND(HG15/$HG$16*$HI$16,2),0) -> 0 | HP15: =SUM(HK15:HO15) -> 0 | HR15: =HJ15+HP15+HQ15 -> 0 | HT15: =HH15-HI15+HR15+HS15 -> 0 | HV15: =ROUND(HF15+HT15+HU15,2) -> 0 | HX15: =$G15*HW15 -> 0 | HY15: =IFERROR(ROUND(HW15/$HG$16*$HI$16,2),0) -> 0 | IF15: =SUM(IA15:IE15) -> 0 | IH15: =HZ15+IF15+IG15 -> 0 | IJ15: =HX15-HY15+IH15+II15 -> 0 | IL15: =ROUND(HV15+IJ15+IK15,2) -> 0 | IN15: =$G15*IM15 -> 0 | IO15: =IFERROR(ROUND(IM15/$HG$16*$HI$16,2),0) -> 0 | IV15: =SUM(IQ15:IU15) -> 0 | IX15: =IP15+IV15+IW15 -> 0 | IZ15: =IN15-IO15+IX15+IY15 -> 0 | JB15: =ROUND(IL15+IZ15+JA15,2) -> 0 | JD15: =$H15*JC15 -> 0 | JE15: =IFERROR(ROUND(JC15/$HG$16*$HI$16,2),0) -> 0 | JL15: =SUM(JG15:JK15) -> 0 | JN15: =JF15+JL15+JM15 -> 0 | JP15: =JD15-JE15+JN15+JO15 -> 0 | JR15: =ROUND(JB15+JP15+JQ15,2) -> 0 | JT15: =$H15*JS15 -> 0 | JU15: =IFERROR(ROUND(JS15/$HG$16*$HI$16,2),0) -> 0 | KB15: =SUM(JW15:KA15) -> 0 | KD15: =JV15+KB15+KC15 -> 0 | KF15: =JT15-JU15+KD15+KE15 -> 0 | KH15: =ROUND(JR15+KF15+KG15,2) -> 0 | KJ15: =$H15*KI15 -> 0 | KK15: =IFERROR(ROUND(KI15/$HG$16*$HI$16,2),0) -> 0 | KR15: =SUM(KM15:KQ15) -> 0 | KT15: =KL15+KR15+KS15 -> 0 | KV15: =KJ15-KK15+KT15+KU15 -> 0 | KX15: =ROUND(KH15+KV15+KW15,2) -> 0 | KZ15: =$H15*KY15 -> 0 | LA15: =IFERROR(ROUND(KY15/$HG$16*$HI$16,2),0) -> 0 | LH15: =SUM(LC15:LG15) -> 0 | LJ15: =LB15+LH15+LI15 -> 0 | LL15: =KZ15-LA15+LJ15+LK15 -> 0 | LN15: =ROUND(KX15+LL15+LM15,2) -> 0 | LP15: =$H15*LO15 -> 0 | LQ15: =IFERROR(ROUND(LO15/$HG$16*$HI$16,2),0) -> 0 | LX15: =SUM(LS15:LW15) -> 0 | LZ15: =LR15+LX15+LY15 -> 0 | MB15: =LP15-LQ15+LZ15+MA15 -> 0 | MD15: =ROUND(LN15+MB15+MC15,2) -> 0 | MF15: =$H15*ME15 -> 0 | MG15: =IFERROR(ROUND(ME15/$HG$16*$HI$16,2),0) -> 0 | MN15: =SUM(MI15:MM15) -> 0 | MP15: =MH15+MN15+MO15 -> 0 | MR15: =MF15-MG15+MP15+MQ15 -> 0 | MT15: =ROUND(MD15+MR15+MS15,2) -> 0 | MV15: =$H15*MU15 -> 0 | MW15: =IFERROR(ROUND(MU15/$HG$16*$HI$16,2),0) -> 0 | ND15: =SUM(MY15:NC15) -> 0 | NF15: =MX15+ND15+NE15 -> 0 | NH15: =MV15-MW15+NF15+NG15 -> 0 | NJ15: =ROUND(MT15+NH15+NI15,2) -> 0 | NL15: =$H15*NK15 -> 0 | NM15: =IFERROR(ROUND(NK15/$HG$16*$HI$16,2),0) -> 0 | NT15: =SUM(NO15:NS15) -> 0 | NV15: =NN15+NT15+NU15 -> 0 | NX15: =NL15-NM15+NV15+NW15 -> 0 | NZ15: =ROUND(NJ15+NX15+NY15,2) -> 0 | OB15: =$H15*OA15 -> 0 | OC15: =IFERROR(ROUND(OA15/$HG$16*$HI$16,2),0) -> 0 | OJ15: =SUM(OE15:OI15) -> 0 | OL15: =OD15+OJ15+OK15 -> 0 | ON15: =OB15-OC15+OL15+OM15 -> 0 | OP15: =ROUND(NZ15+ON15+OO15,2) -> 0 | OR15: =$H15*OQ15 -> 0 | OS15: =IFERROR(ROUND(OQ15/$HG$16*$HI$16,2),0) -> 0 | OZ15: =SUM(OU15:OY15) -> 0 | PB15: =OT15+OZ15+PA15 -> 0 | PD15: =OR15-OS15+PB15+PC15 -> 0 | PF15: =ROUND(OP15+PD15+PE15,2) -> 0 | PH15: =$H15*PG15 -> 0 | PI15: =PH15*0.6 -> 0 | PJ15: =KX15+PI15 -> 0
A16: Вместе по объекту Староконстантинов | K16: =SUM(K4:K15) -> 100856.59 | L16: =SUM(L4:L15) -> 71868.17 | P16: =SUM(P4:P15) -> -92944.15 | Q16: =SUM(Q4:Q15) -> 0 | R16: =SUM(R4:R15) -> -63955.73 | T16: =SUM(T4:T15) -> 394355.12 | U16: =5444.25 -> 5444.25 | Y16: =SUM(Y4:Y15) -> -128669.93 | Z16: =SUM(Z4:Z15) -> 0 | AA16: =SUM(AA4:AA15) -> 260240.94 | AB16: =SUM(AB4:AB15) -> 196285.21 | AD16: =SUM(AD4:AD15) -> 249775.09 | AE16: =187127.12+51771.17 -> 238898.29 | AI16: =SUM(AI4:AI15) -> -108859.74 | AJ16: =SUM(AJ4:AJ15) -> 0 | AK16: =SUM(AK4:AK15) -> -97982.945 | AL16: =SUM(AL4:AL15) -> 98302.265 | AN16: =SUM(AN4:AN15) -> 399683.68 | AO16: 180107.11 | AS16: =SUM(AS4:AS15) -> -142892.56 | AT16: =SUM(AT4:AT15) -> 0 | AU16: =SUM(AU4:AU15) -> 76684.01 | AV16: =SUM(AV4:AV15) -> 174986.28 | AX16: =SUM(AX4:AX15) -> 425176.07 | AY16: =169448.05+59724.57+45026.78+42362.01 -> 316561.41 | BC16: =SUM(BC4:BC15) -> -140656.86 | BD16: =SUM(BD4:BD15) -> 0 | BE16: =SUM(BE4:BE15) -> -32042.2 | BF16: =SUM(BF4:BF15) -> 142944.08 | BH16: =SUM(BH4:BH15) -> 253625.89 | BI16: =апрель!H24 -> 282427.41 | BM16: =SUM(BM4:BM15) -> -100736.85 | BN16: =SUM(BN4:BN15) -> 0 | BO16: =SUM(BO4:BO15) -> -129538.37 | BP16: =SUM(BP4:BP15) -> 13405.707 | BR16: =SUM(BR4:BR15) -> 310311.83 | BW16: =SUM(BW4:BW15) -> -160427.79 | BX16: =SUM(BX4:BX15) -> 0 | BY16: =SUM(BY4:BY15) -> 149884.04 | BZ16: =SUM(BZ4:BZ15) -> 163289.75 | CB16: =SUM(CB4:CB15) -> 191971.78 | CC16: 226287 | CG16: =SUM(CG4:CG15) -> -61290.103 | CH16: =SUM(CH4:CH15) -> 0 | CI16: =SUM(CI4:CI15) -> -95605.323 | CJ16: =SUM(CJ4:CJ15) -> 67684.424 | CL16: =SUM(CL4:CL15) -> 253413.42 | CM16: 274953.8 | CQ16: =SUM(CQ4:CQ15) -> -117285.6 | CR16: =SUM(CR4:CR15) -> 0 | CS16: =SUM(CS4:CS15) -> -138825.98 | CT16: =SUM(CT4:CT15) -> -71141.559 | CV16: =SUM(CV4:CV15) -> 269203.4 | CW16: 59934.69 | DA16: =SUM(DA4:DA15) -> -133234.82 | DB16: =SUM(DB4:DB15) -> 0 | DC16: =SUM(DC4:DC15) -> 76033.885 | DD16: =SUM(DD4:DD15) -> 0 | DE16: =SUM(DE4:DE15) -> 4892.34 | DF16: =SUM(DF4:DF15) -> 542 | DG16: =SUM(DG4:DG15) -> 224423.14 | DH16: 92022.69 | DO16: =SUM(DO4:DO15) -> -83446.18 | DP16: =SUM(DP4:DP15) -> 0 | DQ16: =SUM(DQ4:DQ15) -> 48954.27 | DR16: =SUM(DR4:DR15) -> 0 | DS16: =SUM(DS4:DS15) -> 53846.61 | DT16: =SUM(DT4:DT15) -> 198 | DU16: =SUM(DU4:DU15) -> 97986.24 | DV16: 71582.38 | EC16: =SUM(EC4:EC15) -> -39329.32 | ED16: =SUM(ED4:ED15) -> 0 | EE16: =SUM(EE4:EE15) -> -12925.46 | EF16: =SUM(EF4:EF15) -> 0 | EG16: =SUM(EG4:EG15) -> 40921.15 | EH16: =SUM(EH4:EH15) -> 151 | EI16: =SUM(EI4:EI15) -> 74726.88 | EJ16: 61242 | ER16: =SUM(ER4:ER15) -> -26853.6 | ES16: =SUM(ES4:ES15) -> 0 | ET16: =SUM(ET4:ET15) -> -13368.72 | EU16: =SUM(EU4:EU15) -> 0 | EV16: =SUM(EV4:EV15) -> 27552.43 | EW16: =SUM(EW4:EW15) -> 223 | EX16: =SUM(EX4:EX15) -> 110358.24 | EY16: 78028.63 | FG16: =SUM(FG4:FG15) -> -42675.69 | FH16: =SUM(FH4:FH15) -> 0 | FI16: =SUM(FI4:FI15) -> -10346.08 | FJ16: =SUM(FJ4:FJ15) -> 0 | FK16: =SUM(FK4:FK15) -> 17206.35 | FL16: =SUM(FL4:FL15) -> 155 | FM16: =SUM(FM4:FM15) -> 76706.4 | FN16: 98549.63 | FV16: =SUM(FV4:FV15) -> -36143.2 | FW16: =SUM(FW4:FW15) -> 0 | FX16: =SUM(FX4:FX15) -> -57986.43 | FY16: =SUM(FY4:FY15) -> 0 | FZ16: =SUM(FZ4:FZ15) -> -40780.08 | GA16: =SUM(GA4:GA15) -> 317 | GB16: =SUM(GB4:GB15) -> 156876.96 | GC16: 76249.54 | GL16: =SUM(GL4:GL15) -> -83527.805 | GM16: =SUM(GM4:GM15) -> 0 | GN16: =SUM(GN4:GN15) -> -2900.385 | GO16: =SUM(GO4:GO15) -> 0 | GP16: =SUM(GP4:GP15) -> -43680.47 | GQ16: =SUM(GQ4:GQ15) -> 155 | GR16: =SUM(GR4:GR15) -> 78246.3 | GS16: 33690.117 | HB16: =SUM(HB4:HB15) -> -36348.6 | HC16: =SUM(HC4:HC15) -> 0 | HD16: =SUM(HD4:HD15) -> 8207.58 | HE16: =SUM(HE4:HE15) -> 0 | HF16: =SUM(HF4:HF15) -> -35472.89 | HG16: =SUM(HG4:HG15) -> 146 | HH16: =SUM(HH4:HH15) -> 72252.48 | HI16: 4877.62 | HR16: =SUM(HR4:HR15) -> -29935.6 | HS16: =SUM(HS4:HS15) -> 0 | HT16: =SUM(HT4:HT15) -> 37439.26 | HU16: =SUM(HU4:HU15) -> 0 | HV16: =SUM(HV4:HV15) -> 1966.37 | HW16: =SUM(HW4:HW15) -> 195 | HX16: =SUM(HX4:HX15) -> 96501.6 | HY16: 34829.03 | IH16: =SUM(IH4:IH15) -> -51645.6 | II16: =SUM(II4:II15) -> 0 | IJ16: =SUM(IJ4:IJ15) -> 10026.97 | IK16: =SUM(IK4:IK15) -> 0 | IL16: =SUM(IL4:IL15) -> 11993.34 | IM16: =SUM(IM4:IM15) -> 5 | IN16: =SUM(IN4:IN15) -> 2474.4 | IO16: =11476.42+2869.1 -> 14345.52 | IX16: =SUM(IX4:IX15) -> -871.18 | IY16: =SUM(IY4:IY15) -> 0 | IZ16: =SUM(IZ4:IZ15) -> -12742.3 | JA16: =SUM(JA4:JA15) -> 0 | JB16: =SUM(JB4:JB15) -> -748.96 | JC16: =SUM(JC4:JC15) -> 2 | JD16: =SUM(JD4:JD15) -> 1158.26 | JN16: =SUM(JN4:JN15) -> 0 | JO16: =SUM(JO4:JO15) -> 0 | JP16: =SUM(JP4:JP15) -> 1158.26 | JQ16: =SUM(JQ4:JQ15) -> 0 | JR16: =SUM(JR4:JR15) -> 409.3 | JS16: =SUM(JS4:JS15) -> 69 | JT16: =SUM(JT4:JT15) -> 39959.97 | KD16: =SUM(KD4:KD15) -> -16995.45 | KE16: =SUM(KE4:KE15) -> 0 | KF16: =SUM(KF4:KF15) -> 22964.52 | KG16: =SUM(KG4:KG15) -> 0 | KH16: =SUM(KH4:KH15) -> 23373.82 | KI16: =SUM(KI4:KI15) -> 36 | KJ16: =SUM(KJ4:KJ15) -> 20848.68 | KT16: =SUM(KT4:KT15) -> -2749.42 | KU16: =SUM(KU4:KU15) -> 0 | KV16: =SUM(KV4:KV15) -> 18099.26 | KW16: =SUM(KW4:KW15) -> 0 | KX16: =SUM(KX4:KX15) -> 41473.08 | KY16: =SUM(KY4:KY15) -> 0 | KZ16: =SUM(KZ4:KZ15) -> 0 | LA16: =41473.08 -> 41473.08 | LJ16: =SUM(LJ4:LJ15) -> 0 | LK16: =SUM(LK4:LK15) -> 0 | LL16: =SUM(LL4:LL15) -> -41473.08 | LM16: =SUM(LM4:LM15) -> 0 | LN16: =SUM(LN4:LN15) -> 0 | LO16: =SUM(LO4:LO15) -> 0 | LP16: =SUM(LP4:LP15) -> 0 | LZ16: =SUM(LZ4:LZ15) -> 0 | MA16: =SUM(MA4:MA15) -> 0 | MB16: =SUM(MB4:MB15) -> 0 | MC16: =SUM(MC4:MC15) -> 0 | MD16: =SUM(MD4:MD15) -> 0 | ME16: =SUM(ME4:ME15) -> 0 | MF16: =SUM(MF4:MF15) -> 0 | MP16: =SUM(MP4:MP15) -> 0 | MQ16: =SUM(MQ4:MQ15) -> 0 | MR16: =SUM(MR4:MR15) -> 0 | MS16: =SUM(MS4:MS15) -> 0 | MT16: =SUM(MT4:MT15) -> 0 | MU16: =SUM(MU4:MU15) -> 0 | MV16: =SUM(MV4:MV15) -> 0 | NF16: =SUM(NF4:NF15) -> 0 | NG16: =SUM(NG4:NG15) -> 0 | NH16: =SUM(NH4:NH15) -> 0 | NI16: =SUM(NI4:NI15) -> 0 | NJ16: =SUM(NJ4:NJ15) -> 0 | NK16: =SUM(NK4:NK15) -> 0 | NL16: =SUM(NL4:NL15) -> 0 | NV16: =SUM(NV4:NV15) -> 0 | NW16: =SUM(NW4:NW15) -> 0 | NX16: =SUM(NX4:NX15) -> 0 | NY16: =SUM(NY4:NY15) -> 0 | NZ16: =SUM(NZ4:NZ15) -> 0 | OA16: =SUM(OA4:OA15) -> 0 | OB16: =SUM(OB4:OB15) -> 0 | OL16: =SUM(OL4:OL15) -> 0 | OM16: =SUM(OM4:OM15) -> 0 | ON16: =SUM(ON4:ON15) -> 0 | OO16: =SUM(OO4:OO15) -> 0 | OP16: =SUM(OP4:OP15) -> 0 | OQ16: =SUM(OQ4:OQ15) -> 0 | OR16: =SUM(OR4:OR15) -> 0 | PB16: =SUM(PB4:PB15) -> 0 | PC16: =SUM(PC4:PC15) -> 0 | PD16: =SUM(PD4:PD15) -> 0 | PE16: =SUM(PE4:PE15) -> 0 | PF16: =SUM(PF4:PF15) -> 0 | PG16: =SUM(PG4:PG15) -> 0 | PH16: =SUM(PH4:PH15) -> 0 | PI16: =SUM(PI4:PI15) -> 0 | PJ16: =SUM(PJ4:PJ15) -> 0 | PL16: =IF(PJ16<0,0,PJ16) -> 0
A17: Телескоп 2 | B17: Телескоп №2 | C17: =INDEX(Позиция!$D$3:$D$22,MATCH(A17,Позиция!$C$3:$C$22,0)) -> Турбина-2 | D17: =INDEX(Позиция!$E$3:$E$22,MATCH(A17,Позиция!$C$3:$C$22,0)) -> 1 | E17: Приднепровский МЕТАЛЛ | F17: 467.63 | G17: 494.88 | H17: 579.13 | I17: 879.38 | J17: 149 | K17: =F17*J17 -> 69676.87 | L17: 49650.19 | M17: -7578 | N17: -13042.04 | P17: =SUM(M17:O17) -> -20620.04 | R17: =K17-L17+P17+Q17 -> -593.36 | S17: 5 | T17: =F17*S17 -> 2338.15 | U17: =$U$21/$T$21*T17 -> 4078.3419 | V17: -456.58 | W17: -592.02 | Y17: =SUM(V17:X17) -> -1048.6 | AA17: =T17-U17+Y17+Z17 -> -2788.7919 | AB17: =R17+AA17 -> -3382.1519 | AD17: =AC17*F17 -> 0 | AE17: =$U$21/$T$21*AD17 -> 0 | AI17: =SUM(AF17:AH17) -> 0 | AK17: =AD17-AE17+AI17+AJ17 -> 0 | AL17: =AB17+AK17 -> -3382.1519 | AN17: =AM17*S17 -> 0 | AO17: =$U$21/$T$21*AN17 -> 0 | AS17: =SUM(AP17:AR17) -> 0 | AU17: =AN17-AO17+AS17+AT17 -> 0 | AV17: =AL17+AU17 -> -3382.1519 | AX17: =F17*AW17 -> 0 | AY17: =$AY$16/$AX$16*AX17 -> 0 | BC17: =SUM(AZ17:BB17) -> 0 | BE17: =AX17-AY17+BC17+BD17 -> 0 | BF17: =AV17+BE17 -> -3382.1519 | BH17: =S17*BG17 -> 0 | BI17: =$AY$16/$AX$16*BH17 -> 0 | BM17: =SUM(BJ17:BL17) -> 0 | BO17: =BH17-BI17+BM17+BN17 -> 0 | BP17: =BF17+BO17 -> -3382.1519 | BR17: =AC17*BQ17 -> 0 | BS17: =$AY$16/$AX$16*BR17 -> 0 | BW17: =SUM(BT17:BV17) -> 0 | BY17: =BR17-BS17+BW17+BX17 -> 0 | BZ17: =BP17+BY17 -> -3382.1519 | CA17: 177 | CB17: =$F17*CA17 -> 82770.51 | CC17: =$CC$21/SUM($CA$17:$CA$20)*CA17 -> 22517.862 | CD17: -9398.62 | CE17: =-4305.72-5011 -> -9316.72 | CG17: =SUM(CD17:CF17) -> -18715.34 | CI17: =CB17-CC17+CG17+CH17 -> 41537.308 | CJ17: =BZ17+CI17 -> 38155.156 | CK17: 200 | CL17: =$F17*CK17 -> 93526 | CM17: =$CM$21/SUM($CK$17:$CK$20)*CK17 -> 0 | CN17: =-11479.62 -> -11479.62 | CO17: -9632.81 | CQ17: =SUM(CN17:CP17) -> -21112.43 | CS17: =CL17-CM17+CQ17+CR17 -> 72413.57 | CT17: =CJ17+CS17 -> 110568.73 | CU17: 202 | CV17: =$F17*CU17 -> 94461.26 | CW17: =$CW$21/SUM($CU$17:$CU$20)*CU17 -> 152001.18 | CX17: -12053.6 | CY17: =-11498.7-4849 -> -16347.7 | DA17: =SUM(CX17:CZ17) -> -28401.3 | DC17: =CV17-CW17+DA17+DB17 -> -85941.215 | DD17: -900.21 | DE17: =ROUND(CT17+DC17+DD17,2) -> 23727.3 | DF17: 194 | DG17: =$F17*DF17 -> 90720.22 | DH17: =DF17/$DF$21*$DH$21 -> 84703.708 | DI17: -12053.6 | DJ17: -10742.8 | DK17: -5356.13 | DM17: =SUM(DJ17:DL17) -> -16098.93 | DO17: =DI17+DM17+DN17 -> -28152.53 | DQ17: =DG17-DH17+DO17+DP17 -> -22136.018 | DS17: =ROUND(DE17+DQ17+DR17,2) -> 1591.28 | DT17: 181 | DU17: =$G17*DT17 -> 89573.28 | DV17: =IFERROR(ROUND(DT17/DT21*DV21,2),0) -> 0 | DW17: -12053.6 | DX17: -11972.37 | DY17: -3725.26 | EA17: =SUM(DX17:DZ17) -> -15697.63 | EC17: =DW17+EA17+EB17 -> -27751.23 | EE17: =DU17-DV17+EC17+ED17 -> 61822.05 | EG17: =ROUND(DS17+EE17+EF17,2) -> 63413.33 | EH17: 105 | EI17: =$G17*EH17 -> 51962.4 | EJ17: =IFERROR(ROUND(EH17/EH21*EJ21,2),0) -> 116473.23 | EK17: -12053.6 | EN17: =-9624.39981441648 -> -9624.3998 | EP17: =SUM(EL17:EO17) -> -9624.3998 | ER17: =EK17+EP17+EQ17 -> -21678 | ET17: =EI17-EJ17+ER17+ES17 -> -86188.83 | EU17: 50000 | EV17: =ROUND(EG17+ET17+EU17,2) -> 27224.5 | EW17: 0 | EX17: =$G17*EW17 -> 0 | EY17: 27224.5 | FE17: =SUM(FA17:FD17) -> 0 | FG17: =EZ17+FE17+FF17 -> 0 | FI17: =EX17-EY17+FG17+FH17 -> -27224.5 | FK17: =ROUND(EV17+FI17+FJ17,2) -> 0 | FM17: =$G17*FL17 -> 0 | FT17: =SUM(FP17:FS17) -> 0 | FV17: =FO17+FT17+FU17 -> 0 | FX17: =FM17-FN17+FV17+FW17 -> 0 | FZ17: =ROUND(FK17+FX17+FY17,2) -> 0 | GB17: =$G17*GA17 -> 0 | GJ17: =SUM(GE17:GI17) -> 0 | GL17: =GD17+GJ17+GK17 -> 0 | GN17: =GB17-GC17+GL17+GM17 -> 0 | GP17: =ROUND(FZ17+GN17+GO17,2) -> 0 | GR17: =$G17*GQ17 -> 0 | GZ17: =SUM(GU17:GY17) -> 0 | HB17: =GT17+GZ17+HA17 -> 0 | HD17: =GR17-GS17+HB17+HC17 -> 0 | HF17: =ROUND(GP17+HD17+HE17,2) -> 0 | HH17: =$G17*HG17 -> 0 | HI17: =IFERROR(ROUND(HG17/HG20*HI20,2),0) -> 0 | HP17: =SUM(HK17:HO17) -> 0 | HR17: =HJ17+HP17+HQ17 -> 0 | HT17: =HH17-HI17+HR17+HS17 -> 0 | HV17: =ROUND(HF17+HT17+HU17,2) -> 0 | HX17: =$G17*HW17 -> 0 | HY17: =IFERROR(ROUND(HW17/HW20*HY20,2),0) -> 0 | IF17: =SUM(IA17:IE17) -> 0 | IH17: =HZ17+IF17+IG17 -> 0 | IJ17: =HX17-HY17+IH17+II17 -> 0 | IL17: =ROUND(HV17+IJ17+IK17,2) -> 0 | IN17: =$G17*IM17 -> 0 | IO17: =IFERROR(ROUND(IM17/IM20*IO20,2),0) -> 0 | IV17: =SUM(IQ17:IU17) -> 0 | IX17: =IP17+IV17+IW17 -> 0 | IZ17: =IN17-IO17+IX17+IY17 -> 0 | JB17: =ROUND(IL17+IZ17+JA17,2) -> 0 | JD17: =$G17*JC17 -> 0 | JE17: =IFERROR(ROUND(JC17/JC20*JE20,2),0) -> 0 | JL17: =SUM(JG17:JK17) -> 0 | JN17: =JF17+JL17+JM17 -> 0 | JP17: =JD17-JE17+JN17+JO17 -> 0 | JR17: =ROUND(JB17+JP17+JQ17,2) -> 0 | JT17: =$G17*JS17 -> 0 | JU17: =IFERROR(ROUND(JS17/JS20*JU20,2),0) -> 0 | KB17: =SUM(JW17:KA17) -> 0 | KD17: =JV17+KB17+KC17 -> 0 | KF17: =JT17-JU17+KD17+KE17 -> 0 | KH17: =ROUND(JR17+KF17+KG17,2) -> 0 | KJ17: =$G17*KI17 -> 0 | KK17: =IFERROR(ROUND(KI17/KI20*KK20,2),0) -> 0 | KR17: =SUM(KM17:KQ17) -> 0 | KT17: =KL17+KR17+KS17 -> 0 | KV17: =KJ17-KK17+KT17+KU17 -> 0 | KX17: =ROUND(KH17+KV17+KW17,2) -> 0 | KZ17: =$G17*KY17 -> 0 | LA17: =IFERROR(ROUND(KY17/KY20*LA20,2),0) -> 0 | LH17: =SUM(LC17:LG17) -> 0 | LJ17: =LB17+LH17+LI17 -> 0 | LL17: =KZ17-LA17+LJ17+LK17 -> 0 | LN17: =ROUND(KX17+LL17+LM17,2) -> 0 | LP17: =$G17*LO17 -> 0 | LQ17: =IFERROR(ROUND(LO17/LO20*LQ20,2),0) -> 0 | LX17: =SUM(LS17:LW17) -> 0 | LZ17: =LR17+LX17+LY17 -> 0 | MB17: =LP17-LQ17+LZ17+MA17 -> 0 | MD17: =ROUND(LN17+MB17+MC17,2) -> 0 | MF17: =$G17*ME17 -> 0 | MG17: =IFERROR(ROUND(ME17/ME20*MG20,2),0) -> 0 | MN17: =SUM(MI17:MM17) -> 0 | MP17: =MH17+MN17+MO17 -> 0 | MR17: =MF17-MG17+MP17+MQ17 -> 0 | MT17: =ROUND(MD17+MR17+MS17,2) -> 0 | MV17: =$G17*MU17 -> 0 | MW17: =IFERROR(ROUND(MU17/MU20*MW20,2),0) -> 0 | ND17: =SUM(MY17:NC17) -> 0 | NF17: =MX17+ND17+NE17 -> 0 | NH17: =MV17-MW17+NF17+NG17 -> 0 | NJ17: =ROUND(MT17+NH17+NI17,2) -> 0 | NL17: =$G17*NK17 -> 0 | NM17: =IFERROR(ROUND(NK17/NK20*NM20,2),0) -> 0 | NT17: =SUM(NO17:NS17) -> 0 | NV17: =NN17+NT17+NU17 -> 0 | NX17: =NL17-NM17+NV17+NW17 -> 0 | NZ17: =ROUND(NJ17+NX17+NY17,2) -> 0 | OB17: =$G17*OA17 -> 0 | OC17: =IFERROR(ROUND(OA17/OA20*OC20,2),0) -> 0 | OJ17: =SUM(OE17:OI17) -> 0 | OL17: =OD17+OJ17+OK17 -> 0 | ON17: =OB17-OC17+OL17+OM17 -> 0 | OP17: =ROUND(NZ17+ON17+OO17,2) -> 0 | OR17: =$G17*OQ17 -> 0 | OS17: =IFERROR(ROUND(OQ17/OQ20*OS20,2),0) -> 0 | OZ17: =SUM(OU17:OY17) -> 0 | PB17: =OT17+OZ17+PA17 -> 0 | PD17: =OR17-OS17+PB17+PC17 -> 0 | PF17: =ROUND(OP17+PD17+PE17,2) -> 0 | PH17: =$H17*PG17 -> 0 | PI17: =PH17*0.6 -> 0 | PJ17: =JB17+PI17 -> 0
A18: МАЗ 265 | B18: МАЗ 265 | C18: =INDEX(Позиция!$D$3:$D$22,MATCH(A18,Позиция!$C$3:$C$22,0)) -> Крушинка | D18: =INDEX(Позиция!$E$3:$E$22,MATCH(A18,Позиция!$C$3:$C$22,0)) -> 1 | E18: Приднепровский МЕТАЛЛ | F18: 355.37 | G18: 386.37 | H18: 455.37 | AA18: =T18-U18+Y18+Z18 -> 0 | AB18: =R18+AA18 -> 0 | AC18: 4 | AD18: =AC18*F18 -> 1421.48 | AF18: -313.21506 | AG18: -515.75412 | AI18: =SUM(AF18:AH18) -> -828.96918 | AK18: =AD18-AE18+AI18+AJ18 -> 592.51082 | AL18: =AB18+AK18 -> 592.51082 | AN18: =AM18*S18 -> 0 | AO18: =$U$21/$T$21*AN18 -> 0 | AS18: =SUM(AP18:AR18) -> 0 | AU18: =AN18-AO18+AS18+AT18 -> 0 | AV18: =AL18+AU18 -> 592.51082 | AX18: =F18*AW18 -> 0 | AY18: =$AY$16/$AX$16*AX18 -> 0 | BC18: =SUM(AZ18:BB18) -> 0 | BE18: =AX18-AY18+BC18+BD18 -> 0 | BF18: =AV18+BE18 -> 592.51082 | BH18: =S18*BG18 -> 0 | BI18: =$AY$16/$AX$16*BH18 -> 0 | BM18: =SUM(BJ18:BL18) -> 0 | BO18: =BH18-BI18+BM18+BN18 -> 0 | BP18: =BF18+BO18 -> 592.51082 | BR18: =AC18*BQ18 -> 0 | BS18: =$AY$16/$AX$16*BR18 -> 0 | BW18: =SUM(BT18:BV18) -> 0 | BY18: =BR18-BS18+BW18+BX18 -> 0 | BZ18: =BP18+BY18 -> 592.51082 | CB18: =$F18*CA18 -> 0 | CC18: =$CC$21/SUM($CA$17:$CA$20)*CA18 -> 0 | CG18: =SUM(CD18:CF18) -> 0 | CI18: =CB18-CC18+CG18+CH18 -> 0 | CJ18: =BZ18+CI18 -> 592.51082 | CL18: =$F18*CK18 -> 0 | CM18: =$CM$21/SUM($CK$17:$CK$20)*CK18 -> 0 | CQ18: =SUM(CN18:CP18) -> 0 | CS18: =CL18-CM18+CQ18+CR18 -> 0 | CT18: =CJ18+CS18 -> 592.51082 | CV18: =$F18*CU18 -> 0 | CW18: =$CW$21/SUM($CU$17:$CU$20)*CU18 -> 0 | DA18: =SUM(CX18:CZ18) -> 0 | DC18: =CV18-CW18+DA18+DB18 -> 0 | DD18: -592.51 | DE18: =ROUND(CT18+DC18+DD18,2) -> 0 | DG18: =$F18*DF18 -> 0 | DO18: =DI18+DM18+DN18 -> 0 | DQ18: =DG18-DH18+DO18+DP18 -> 0 | DS18: =ROUND(DE18+DQ18+DR18,2) -> 0 | DU18: =$G18*DT18 -> 0 | DV18: =IFERROR(ROUND(DT18/DT21*DV21,2),0) -> 0 | EA18: =SUM(DX18:DZ18) -> 0 | EC18: =DW18+EA18+EB18 -> 0 | EE18: =DU18-DV18+EC18+ED18 -> 0 | EG18: =ROUND(DS18+EE18+EF18,2) -> 0 | EI18: =$G18*EH18 -> 0 | EJ18: =IFERROR(ROUND(EH18/EH21*EJ21,2),0) -> 0 | EP18: =SUM(EL18:EO18) -> 0 | ER18: =EK18+EP18+EQ18 -> 0 | ET18: =EI18-EJ18+ER18+ES18 -> 0 | EV18: =ROUND(EG18+ET18+EU18,2) -> 0 | EX18: =$G18*EW18 -> 0 | EY18: =IFERROR(ROUND(EW18/EW21*EY21,2),0) -> 0 | FE18: =SUM(FA18:FD18) -> 0 | FG18: =EZ18+FE18+FF18 -> 0 | FI18: =EX18-EY18+FG18+FH18 -> 0 | FK18: =ROUND(EV18+FI18+FJ18,2) -> 0 | FM18: =$G18*FL18 -> 0 | FN18: =IFERROR(ROUND(FL18/FL21*FN21,2),0) -> 0 | FT18: =SUM(FP18:FS18) -> 0 | FV18: =FO18+FT18+FU18 -> 0 | FX18: =FM18-FN18+FV18+FW18 -> 0 | FZ18: =ROUND(FK18+FX18+FY18,2) -> 0 | GB18: =$G18*GA18 -> 0 | GC18: =IFERROR(ROUND(GA18/GA21*GC21,2),0) -> 0 | GJ18: =SUM(GE18:GI18) -> 0 | GL18: =GD18+GJ18+GK18 -> 0 | GN18: =GB18-GC18+GL18+GM18 -> 0 | GP18: =ROUND(FZ18+GN18+GO18,2) -> 0 | GR18: =$G18*GQ18 -> 0 | GS18: =IFERROR(ROUND(GQ18/GQ21*GS21,2),0) -> 0 | GZ18: =SUM(GU18:GY18) -> 0 | HB18: =GT18+GZ18+HA18 -> 0 | HD18: =GR18-GS18+HB18+HC18 -> 0 | HF18: =ROUND(GP18+HD18+HE18,2) -> 0 | HH18: =$G18*HG18 -> 0 | HI18: =IFERROR(ROUND(HG18/HG21*HI21,2),0) -> 0 | HP18: =SUM(HK18:HO18) -> 0 | HR18: =HJ18+HP18+HQ18 -> 0 | HT18: =HH18-HI18+HR18+HS18 -> 0 | HV18: =ROUND(HF18+HT18+HU18,2) -> 0 | HX18: =$G18*HW18 -> 0 | HY18: =IFERROR(ROUND(HW18/HW21*HY21,2),0) -> 0 | IF18: =SUM(IA18:IE18) -> 0 | IH18: =HZ18+IF18+IG18 -> 0 | IJ18: =HX18-HY18+IH18+II18 -> 0 | IL18: =ROUND(HV18+IJ18+IK18,2) -> 0 | IN18: =$G18*IM18 -> 0 | IO18: =IFERROR(ROUND(IM18/IM21*IO21,2),0) -> 0 | IV18: =SUM(IQ18:IU18) -> 0 | IX18: =IP18+IV18+IW18 -> 0 | IZ18: =IN18-IO18+IX18+IY18 -> 0 | JB18: =ROUND(IL18+IZ18+JA18,2) -> 0 | JD18: =$G18*JC18 -> 0 | JE18: =IFERROR(ROUND(JC18/JC21*JE21,2),0) -> 0 | JL18: =SUM(JG18:JK18) -> 0 | JN18: =JF18+JL18+JM18 -> 0 | JP18: =JD18-JE18+JN18+JO18 -> 0 | JR18: =ROUND(JB18+JP18+JQ18,2) -> 0 | JT18: =$G18*JS18 -> 0 | JU18: =IFERROR(ROUND(JS18/JS21*JU21,2),0) -> 0 | KB18: =SUM(JW18:KA18) -> 0 | KD18: =JV18+KB18+KC18 -> 0 | KF18: =JT18-JU18+KD18+KE18 -> 0 | KH18: =ROUND(JR18+KF18+KG18,2) -> 0 | KJ18: =$G18*KI18 -> 0 | KK18: =IFERROR(ROUND(KI18/KI21*KK21,2),0) -> 0 | KR18: =SUM(KM18:KQ18) -> 0 | KT18: =KL18+KR18+KS18 -> 0 | KV18: =KJ18-KK18+KT18+KU18 -> 0 | KX18: =ROUND(KH18+KV18+KW18,2) -> 0 | KZ18: =$G18*KY18 -> 0 | LA18: =IFERROR(ROUND(KY18/KY21*LA21,2),0) -> 0 | LH18: =SUM(LC18:LG18) -> 0 | LJ18: =LB18+LH18+LI18 -> 0 | LL18: =KZ18-LA18+LJ18+LK18 -> 0 | LN18: =ROUND(KX18+LL18+LM18,2) -> 0 | LP18: =$G18*LO18 -> 0 | LQ18: =IFERROR(ROUND(LO18/LO21*LQ21,2),0) -> 0 | LX18: =SUM(LS18:LW18) -> 0 | LZ18: =LR18+LX18+LY18 -> 0 | MB18: =LP18-LQ18+LZ18+MA18 -> 0 | MD18: =ROUND(LN18+MB18+MC18,2) -> 0 | MF18: =$G18*ME18 -> 0 | MG18: =IFERROR(ROUND(ME18/ME21*MG21,2),0) -> 0 | MN18: =SUM(MI18:MM18) -> 0 | MP18: =MH18+MN18+MO18 -> 0 | MR18: =MF18-MG18+MP18+MQ18 -> 0 | MT18: =ROUND(MD18+MR18+MS18,2) -> 0 | MV18: =$G18*MU18 -> 0 | MW18: =IFERROR(ROUND(MU18/MU21*MW21,2),0) -> 0 | ND18: =SUM(MY18:NC18) -> 0 | NF18: =MX18+ND18+NE18 -> 0 | NH18: =MV18-MW18+NF18+NG18 -> 0 | NJ18: =ROUND(MT18+NH18+NI18,2) -> 0 | NL18: =$G18*NK18 -> 0 | NM18: =IFERROR(ROUND(NK18/NK21*NM21,2),0) -> 0 | NT18: =SUM(NO18:NS18) -> 0 | NV18: =NN18+NT18+NU18 -> 0 | NX18: =NL18-NM18+NV18+NW18 -> 0 | NZ18: =ROUND(NJ18+NX18+NY18,2) -> 0 | OB18: =$G18*OA18 -> 0 | OC18: =IFERROR(ROUND(OA18/OA21*OC21,2),0) -> 0 | OJ18: =SUM(OE18:OI18) -> 0 | OL18: =OD18+OJ18+OK18 -> 0 | ON18: =OB18-OC18+OL18+OM18 -> 0 | OP18: =ROUND(NZ18+ON18+OO18,2) -> 0 | OR18: =$G18*OQ18 -> 0 | OS18: =IFERROR(ROUND(OQ18/OQ21*OS21,2),0) -> 0 | OZ18: =SUM(OU18:OY18) -> 0 | PB18: =OT18+OZ18+PA18 -> 0 | PD18: =OR18-OS18+PB18+PC18 -> 0 | PF18: =ROUND(OP18+PD18+PE18,2) -> 0 | PH18: =$H18*PG18 -> 0 | PI18: =PH18*0.6 -> 0 | PJ18: =JB18+PI18 -> 0
A19: Автокран XCMG | B19: Автокран XCMG | C19: =INDEX(Позиция!$D$3:$D$22,MATCH(A19,Позиция!$C$3:$C$22,0)) -> Ладыжин-3 с 14.11.2023 | D19: =INDEX(Позиция!$E$3:$E$22,MATCH(A19,Позиция!$C$3:$C$22,0)) -> 1 | E19: Приднепровский МЕТАЛЛ | F19: 563.19 | G19: 601.95 | H19: 722.13 | AA19: =T19-U19+Y19+Z19 -> 0 | AB19: =R19+AA19 -> 0 | AD19: =AC19*F19 -> 0 | AI19: =SUM(AF19:AH19) -> 0 | AK19: =AD19-AE19+AI19+AJ19 -> 0 | AL19: =AB19+AK19 -> 0 | AN19: =AM19*S19 -> 0 | AO19: =$U$21/$T$21*AN19 -> 0 | AS19: =SUM(AP19:AR19) -> 0 | AU19: =AN19-AO19+AS19+AT19 -> 0 | AV19: =AL19+AU19 -> 0 | AX19: =F19*AW19 -> 0 | AY19: =$AY$16/$AX$16*AX19 -> 0 | BC19: =SUM(AZ19:BB19) -> 0 | BE19: =AX19-AY19+BC19+BD19 -> 0 | BF19: =AV19+BE19 -> 0 | BH19: =S19*BG19 -> 0 | BI19: =$AY$16/$AX$16*BH19 -> 0 | BM19: =SUM(BJ19:BL19) -> 0 | BO19: =BH19-BI19+BM19+BN19 -> 0 | BP19: =BF19+BO19 -> 0 | BR19: =AC19*BQ19 -> 0 | BS19: =$AY$16/$AX$16*BR19 -> 0 | BW19: =SUM(BT19:BV19) -> 0 | BY19: =BR19-BS19+BW19+BX19 -> 0 | BZ19: =BP19+BY19 -> 0 | CA19: 182 | CB19: =$F19*CA19 -> 102500.58 | CC19: =$CC$21/SUM($CA$17:$CA$20)*CA19 -> 23153.96 | CD19: =-12448/(40+182)*182 -> -10205.117 | CE19: =-5075.70945945946-4590 -> -9665.7095 | CF19: =496*44.65 -> 22146.4 | CG19: =SUM(CD19:CF19) -> 2275.5734 | CI19: =CB19-CC19+CG19+CH19 -> 81622.194 | CJ19: =BZ19+CI19 -> 81622.194 | CK19: 134 | CL19: =$F19*CK19 -> 75467.46 | CM19: =$CM$21/SUM($CK$17:$CK$20)*CK19 -> 0 | CN19: -11590 | CO19: -8184.1 | CQ19: =SUM(CN19:CP19) -> -19774.1 | CS19: =CL19-CM19+CQ19+CR19 -> 55693.36 | CT19: =CJ19+CS19 -> 137315.55 | CU19: 136 | CV19: =$F19*CU19 -> 76593.84 | CW19: =$CW$21/SUM($CU$17:$CU$20)*CU19 -> 102337.42 | CX19: -18020.52 | CY19: -5998.8 | DA19: =SUM(CX19:CZ19) -> -24019.32 | DC19: =CV19-CW19+DA19+DB19 -> -49762.905 | DD19: -21000 | DE19: =ROUND(CT19+DC19+DD19,2) -> 66552.65 | DF19: 189 | DG19: =$F19*DF19 -> 106442.91 | DH19: =DF19/$DF$21*$DH$21 -> 82520.622 | DI19: -11590 | DK19: -8276.61 | DM19: =SUM(DJ19:DL19) -> -8276.61 | DO19: =DI19+DM19+DN19 -> -19866.61 | DQ19: =DG19-DH19+DO19+DP19 -> 4055.6776 | DS19: =ROUND(DE19+DQ19+DR19,2) -> 70608.33 | DT19: 139 | DU19: =$G19*DT19 -> 83671.05 | DV19: =IFERROR(ROUND(DT19/DT21*DV21,2),0) -> 0 | DW19: -11590 | EA19: =SUM(DX19:DZ19) -> 0 | EC19: =DW19+EA19+EB19 -> -11590 | EE19: =DU19-DV19+EC19+ED19 -> 72081.05 | EG19: =ROUND(DS19+EE19+EF19,2) -> 142689.38 | EH19: 0 | EI19: =$G19*EH19 -> 0 | EJ19: =IFERROR(ROUND(EH19/EH21*EJ21,2),0) -> 0 | EP19: =SUM(EL19:EO19) -> 0 | ER19: =EK19+EP19+EQ19 -> 0 | ET19: =EI19-EJ19+ER19+ES19 -> 0 | EU19: -50000 | EV19: =ROUND(EG19+ET19+EU19,2) -> 92689.38 | EW19: 0 | EX19: =$G19*EW19 -> 0 | EY19: =EY21-EY17 -> 68706.6 | FE19: =SUM(FA19:FD19) -> 0 | FG19: =EZ19+FE19+FF19 -> 0 | FI19: =EX19-EY19+FG19+FH19 -> -68706.6 | FK19: =ROUND(EV19+FI19+FJ19,2) -> 23982.78 | FM19: =$G19*FL19 -> 0 | FN19: =FN21-FN17 -> 0 | FT19: =SUM(FP19:FS19) -> 0 | FV19: =FO19+FT19+FU19 -> 0 | FX19: =FM19-FN19+FV19+FW19 -> 0 | FZ19: =ROUND(FK19+FX19+FY19,2) -> 23982.78 | GB19: =$G19*GA19 -> 0 | GC19: =GC21-GC17 -> 0 | GJ19: =SUM(GE19:GI19) -> 0 | GL19: =GD19+GJ19+GK19 -> 0 | GN19: =GB19-GC19+GL19+GM19 -> 0 | GP19: =ROUND(FZ19+GN19+GO19,2) -> 23982.78 | GR19: =$G19*GQ19 -> 0 | GS19: =GS21-GS17 -> 0 | GZ19: =SUM(GU19:GY19) -> 0 | HB19: =GT19+GZ19+HA19 -> 0 | HD19: =GR19-GS19+HB19+HC19 -> 0 | HF19: =ROUND(GP19+HD19+HE19,2) -> 23982.78 | HH19: =$G19*HG19 -> 0 | HI19: =HI21-HI17 -> 0 | HP19: =SUM(HK19:HO19) -> 0 | HR19: =HJ19+HP19+HQ19 -> 0 | HT19: =HH19-HI19+HR19+HS19 -> 0 | HV19: =ROUND(HF19+HT19+HU19,2) -> 23982.78 | HX19: =$G19*HW19 -> 0 | HY19: =IFERROR(ROUND(HW19/HW21*HY21,2),0) -> 0 | IF19: =SUM(IA19:IE19) -> 0 | IH19: =HZ19+IF19+IG19 -> 0 | IJ19: =HX19-HY19+IH19+II19 -> 0 | IL19: =ROUND(HV19+IJ19+IK19,2) -> 23982.78 | IN19: =$G19*IM19 -> 0 | IO19: 23982.78 | IV19: =SUM(IQ19:IU19) -> 0 | IX19: =IP19+IV19+IW19 -> 0 | IZ19: =IN19-IO19+IX19+IY19 -> -23982.78 | JB19: =ROUND(IL19+IZ19+JA19,2) -> 0 | JD19: =$G19*JC19 -> 0 | JL19: =SUM(JG19:JK19) -> 0 | JN19: =JF19+JL19+JM19 -> 0 | JP19: =JD19-JE19+JN19+JO19 -> 0 | JR19: =ROUND(JB19+JP19+JQ19,2) -> 0 | JT19: =$G19*JS19 -> 0 | KB19: =SUM(JW19:KA19) -> 0 | KD19: =JV19+KB19+KC19 -> 0 | KF19: =JT19-JU19+KD19+KE19 -> 0 | KH19: =ROUND(JR19+KF19+KG19,2) -> 0 | KJ19: =$G19*KI19 -> 0 | KR19: =SUM(KM19:KQ19) -> 0 | KT19: =KL19+KR19+KS19 -> 0 | KV19: =KJ19-KK19+KT19+KU19 -> 0 | KX19: =ROUND(KH19+KV19+KW19,2) -> 0 | KZ19: =$G19*KY19 -> 0 | LH19: =SUM(LC19:LG19) -> 0 | LJ19: =LB19+LH19+LI19 -> 0 | LL19: =KZ19-LA19+LJ19+LK19 -> 0 | LN19: =ROUND(KX19+LL19+LM19,2) -> 0 | LP19: =$G19*LO19 -> 0 | LX19: =SUM(LS19:LW19) -> 0 | LZ19: =LR19+LX19+LY19 -> 0 | MB19: =LP19-LQ19+LZ19+MA19 -> 0 | MD19: =ROUND(LN19+MB19+MC19,2) -> 0 | MF19: =$G19*ME19 -> 0 | MN19: =SUM(MI19:MM19) -> 0 | MP19: =MH19+MN19+MO19 -> 0 | MR19: =MF19-MG19+MP19+MQ19 -> 0 | MT19: =ROUND(MD19+MR19+MS19,2) -> 0 | MV19: =$G19*MU19 -> 0 | ND19: =SUM(MY19:NC19) -> 0 | NF19: =MX19+ND19+NE19 -> 0 | NH19: =MV19-MW19+NF19+NG19 -> 0 | NJ19: =ROUND(MT19+NH19+NI19,2) -> 0 | NL19: =$G19*NK19 -> 0 | NT19: =SUM(NO19:NS19) -> 0 | NV19: =NN19+NT19+NU19 -> 0 | NX19: =NL19-NM19+NV19+NW19 -> 0 | NZ19: =ROUND(NJ19+NX19+NY19,2) -> 0 | OB19: =$G19*OA19 -> 0 | OJ19: =SUM(OE19:OI19) -> 0 | OL19: =OD19+OJ19+OK19 -> 0 | ON19: =OB19-OC19+OL19+OM19 -> 0 | OP19: =ROUND(NZ19+ON19+OO19,2) -> 0 | OR19: =$G19*OQ19 -> 0 | OZ19: =SUM(OU19:OY19) -> 0 | PB19: =OT19+OZ19+PA19 -> 0 | PD19: =OR19-OS19+PB19+PC19 -> 0 | PF19: =ROUND(OP19+PD19+PE19,2) -> 0 | PH19: =$H19*PG19 -> 0 | PI19: =PH19*0.6 -> 0 | PJ19: =JB19+PI19 -> 0
A20: Экскаватор JCB 2013 | B20: Экскаватор JCB 2013 | C20: =INDEX(Позиция!$D$3:$D$22,MATCH(A20,Позиция!$C$3:$C$22,0)) -> Подгорцы | D20: =INDEX(Позиция!$E$3:$E$22,MATCH(A20,Позиция!$C$3:$C$22,0)) -> 1 | E20: Приднепровский МЕТАЛЛ | F20: 496.93 | G20: 524.19 | H20: 608.43 | I20: 823.73 | J20: 88 | K20: =F20*J20 -> 43729.84 | L20: 31160.91 | M20: -4376.14 | N20: -5757.36 | P20: =SUM(M20:O20) -> -10133.5 | R20: =K20-L20+P20+Q20 -> 2435.43 | S20: 67 | T20: =F20*S20 -> 33294.31 | U20: =$U$21/$T$21*T20 -> 58073.938 | V20: -3827.45 | W20: =-24736.16/($S$20+$S$22)*S20 -> -7854.61 | Y20: =SUM(V20:X20) -> -11682.06 | AA20: =T20-U20+Y20+Z20 -> -36461.688 | AB20: =R20+AA20 -> -34026.258 | AD20: =AC20*F20 -> 0 | AE20: =$U$21/$T$21*AD20 -> 0 | AI20: =SUM(AF20:AH20) -> 0 | AK20: =AD20-AE20+AI20+AJ20 -> 0 | AL20: =AB20+AK20 -> -34026.258 | AN20: =AM20*S20 -> 0 | AO20: =$U$21/$T$21*AN20 -> 0 | AS20: =SUM(AP20:AR20) -> 0 | AU20: =AN20-AO20+AS20+AT20 -> 0 | AV20: =AL20+AU20 -> -34026.258 | AX20: =F20*AW20 -> 0 | AY20: =$AY$16/$AX$16*AX20 -> 0 | BC20: =SUM(AZ20:BB20) -> 0 | BE20: =AX20-AY20+BC20+BD20 -> 0 | BF20: =AV20+BE20 -> -34026.258 | BH20: =S20*BG20 -> 0 | BI20: =$AY$16/$AX$16*BH20 -> 0 | BM20: =SUM(BJ20:BL20) -> 0 | BO20: =BH20-BI20+BM20+BN20 -> 0 | BP20: =BF20+BO20 -> -34026.258 | BR20: =AC20*BQ20 -> 0 | BS20: =$AY$16/$AX$16*BR20 -> 0 | BW20: =SUM(BT20:BV20) -> 0 | BY20: =BR20-BS20+BW20+BX20 -> 0 | BZ20: =BP20+BY20 -> -34026.258 | CA20: 50 | CB20: =$F20*CA20 -> 24846.5 | CC20: =$CC$21/SUM($CA$17:$CA$20)*CA20 -> 6360.978 | CD20: -2654.98 | CE20: -4297 | CG20: =SUM(CD20:CF20) -> -6951.98 | CI20: =CB20-CC20+CG20+CH20 -> 11533.542 | CJ20: =BZ20+CI20 -> -22492.716 | CL20: =$F20*CK20 -> 0 | CM20: =$CM$21/SUM($CK$17:$CK$20)*CK20 -> 0 | CQ20: =SUM(CN20:CP20) -> 0 | CS20: =CL20-CM20+CQ20+CR20 -> 0 | CT20: =CJ20+CS20 -> -22492.716 | CV20: =$F20*CU20 -> 0 | CW20: =$CW$21/SUM($CU$17:$CU$20)*CU20 -> 0 | DA20: =SUM(CX20:CZ20) -> 0 | DC20: =CV20-CW20+DA20+DB20 -> 0 | DD20: =--22492.72 -> 22492.72 | DE20: =ROUND(CT20+DC20+DD20,2) -> 0 | DG20: =$F20*DF20 -> 0 | DO20: =DI20+DM20+DN20 -> 0 | DQ20: =DG20-DH20+DO20+DP20 -> 0 | DS20: =ROUND(DE20+DQ20+DR20,2) -> 0 | DU20: =$G20*DT20 -> 0 | DV20: =IFERROR(ROUND(DT20/DT21*DV21,2),0) -> 0 | EA20: =SUM(DX20:DZ20) -> 0 | EC20: =DW20+EA20+EB20 -> 0 | EE20: =DU20-DV20+EC20+ED20 -> 0 | EG20: =ROUND(DS20+EE20+EF20,2) -> 0 | EI20: =$G20*EH20 -> 0 | EJ20: =IFERROR(ROUND(EH20/EH21*EJ21,2),0) -> 0 | EP20: =SUM(EL20:EO20) -> 0 | ER20: =EK20+EP20+EQ20 -> 0 | ET20: =EI20-EJ20+ER20+ES20 -> 0 | EV20: =ROUND(EG20+ET20+EU20,2) -> 0 | EX20: =$G20*EW20 -> 0 | EY20: =IFERROR(ROUND(EW20/EW21*EY21,2),0) -> 0 | FE20: =SUM(FA20:FD20) -> 0 | FG20: =EZ20+FE20+FF20 -> 0 | FI20: =EX20-EY20+FG20+FH20 -> 0 | FK20: =ROUND(EV20+FI20+FJ20,2) -> 0 | FM20: =$G20*FL20 -> 0 | FN20: =IFERROR(ROUND(FL20/FL21*FN21,2),0) -> 0 | FT20: =SUM(FP20:FS20) -> 0 | FV20: =FO20+FT20+FU20 -> 0 | FX20: =FM20-FN20+FV20+FW20 -> 0 | FZ20: =ROUND(FK20+FX20+FY20,2) -> 0 | GB20: =$G20*GA20 -> 0 | GC20: =IFERROR(ROUND(GA20/GA21*GC21,2),0) -> 0 | GJ20: =SUM(GE20:GI20) -> 0 | GL20: =GD20+GJ20+GK20 -> 0 | GN20: =GB20-GC20+GL20+GM20 -> 0 | GP20: =ROUND(FZ20+GN20+GO20,2) -> 0 | GR20: =$G20*GQ20 -> 0 | GS20: =IFERROR(ROUND(GQ20/GQ21*GS21,2),0) -> 0 | GZ20: =SUM(GU20:GY20) -> 0 | HB20: =GT20+GZ20+HA20 -> 0 | HD20: =GR20-GS20+HB20+HC20 -> 0 | HF20: =ROUND(GP20+HD20+HE20,2) -> 0 | HH20: =$G20*HG20 -> 0 | HI20: =HI22-HI18 -> 0 | HP20: =SUM(HK20:HO20) -> 0 | HR20: =HJ20+HP20+HQ20 -> 0 | HT20: =HH20-HI20+HR20+HS20 -> 0 | HV20: =ROUND(HF20+HT20+HU20,2) -> 0 | HX20: =$G20*HW20 -> 0 | HY20: =IFERROR(ROUND(HW20/HW21*HY21,2),0) -> 0 | IF20: =SUM(IA20:IE20) -> 0 | IH20: =HZ20+IF20+IG20 -> 0 | IJ20: =HX20-HY20+IH20+II20 -> 0 | IL20: =ROUND(HV20+IJ20+IK20,2) -> 0 | IN20: =$G20*IM20 -> 0 | IO20: =IFERROR(ROUND(IM20/IM21*IO21,2),0) -> 0 | IV20: =SUM(IQ20:IU20) -> 0 | IX20: =IP20+IV20+IW20 -> 0 | IZ20: =IN20-IO20+IX20+IY20 -> 0 | JB20: =ROUND(IL20+IZ20+JA20,2) -> 0 | JD20: =$G20*JC20 -> 0 | JE20: =IFERROR(ROUND(JC20/JC21*JE21,2),0) -> 0 | JL20: =SUM(JG20:JK20) -> 0 | JN20: =JF20+JL20+JM20 -> 0 | JP20: =JD20-JE20+JN20+JO20 -> 0 | JR20: =ROUND(JB20+JP20+JQ20,2) -> 0 | JT20: =$G20*JS20 -> 0 | JU20: =IFERROR(ROUND(JS20/JS21*JU21,2),0) -> 0 | KB20: =SUM(JW20:KA20) -> 0 | KD20: =JV20+KB20+KC20 -> 0 | KF20: =JT20-JU20+KD20+KE20 -> 0 | KH20: =ROUND(JR20+KF20+KG20,2) -> 0 | KJ20: =$G20*KI20 -> 0 | KK20: =IFERROR(ROUND(KI20/KI21*KK21,2),0) -> 0 | KR20: =SUM(KM20:KQ20) -> 0 | KT20: =KL20+KR20+KS20 -> 0 | KV20: =KJ20-KK20+KT20+KU20 -> 0 | KX20: =ROUND(KH20+KV20+KW20,2) -> 0 | KZ20: =$G20*KY20 -> 0 | LA20: =IFERROR(ROUND(KY20/KY21*LA21,2),0) -> 0 | LH20: =SUM(LC20:LG20) -> 0 | LJ20: =LB20+LH20+LI20 -> 0 | LL20: =KZ20-LA20+LJ20+LK20 -> 0 | LN20: =ROUND(KX20+LL20+LM20,2) -> 0 | LP20: =$G20*LO20 -> 0 | LQ20: =IFERROR(ROUND(LO20/LO21*LQ21,2),0) -> 0 | LX20: =SUM(LS20:LW20) -> 0 | LZ20: =LR20+LX20+LY20 -> 0 | MB20: =LP20-LQ20+LZ20+MA20 -> 0 | MD20: =ROUND(LN20+MB20+MC20,2) -> 0 | MF20: =$G20*ME20 -> 0 | MG20: =IFERROR(ROUND(ME20/ME21*MG21,2),0) -> 0 | MN20: =SUM(MI20:MM20) -> 0 | MP20: =MH20+MN20+MO20 -> 0 | MR20: =MF20-MG20+MP20+MQ20 -> 0 | MT20: =ROUND(MD20+MR20+MS20,2) -> 0 | MV20: =$G20*MU20 -> 0 | MW20: =IFERROR(ROUND(MU20/MU21*MW21,2),0) -> 0 | ND20: =SUM(MY20:NC20) -> 0 | NF20: =MX20+ND20+NE20 -> 0 | NH20: =MV20-MW20+NF20+NG20 -> 0 | NJ20: =ROUND(MT20+NH20+NI20,2) -> 0 | NL20: =$G20*NK20 -> 0 | NM20: =IFERROR(ROUND(NK20/NK21*NM21,2),0) -> 0 | NT20: =SUM(NO20:NS20) -> 0 | NV20: =NN20+NT20+NU20 -> 0 | NX20: =NL20-NM20+NV20+NW20 -> 0 | NZ20: =ROUND(NJ20+NX20+NY20,2) -> 0 | OB20: =$G20*OA20 -> 0 | OC20: =IFERROR(ROUND(OA20/OA21*OC21,2),0) -> 0 | OJ20: =SUM(OE20:OI20) -> 0 | OL20: =OD20+OJ20+OK20 -> 0 | ON20: =OB20-OC20+OL20+OM20 -> 0 | OP20: =ROUND(NZ20+ON20+OO20,2) -> 0 | OR20: =$G20*OQ20 -> 0 | OS20: =IFERROR(ROUND(OQ20/OQ21*OS21,2),0) -> 0 | OZ20: =SUM(OU20:OY20) -> 0 | PB20: =OT20+OZ20+PA20 -> 0 | PD20: =OR20-OS20+PB20+PC20 -> 0 | PF20: =ROUND(OP20+PD20+PE20,2) -> 0 | PH20: =$H20*PG20 -> 0 | PI20: =PH20*0.6 -> 0 | PJ20: =JB20+PI20 -> 0
A21: Вместе по объекту Приднепровский МЕТАЛЛ | K21: =SUM(K17:K20) -> 113406.71 | L21: =SUM(L17:L20) -> 80811.1 | P21: =SUM(P17:P20) -> -30753.54 | Q21: =SUM(Q17:Q20) -> 0 | R21: =SUM(R17:R20) -> 1842.07 | T21: =SUM(T17:T20) -> 35632.46 | U21: =62152.28 -> 62152.28 | Y21: =SUM(Y17:Y20) -> -12730.66 | Z21: =SUM(Z17:Z20) -> 0 | AA21: =SUM(AA17:AA20) -> -39250.48 | AB21: =SUM(AB17:AB20) -> -37408.41 | AD21: =SUM(AD17:AD20) -> 1421.48 | AI21: =SUM(AI17:AI20) -> -828.96918 | AJ21: =SUM(AJ17:AJ20) -> 0 | AK21: =SUM(AK17:AK20) -> 592.51082 | AL21: =SUM(AL17:AL20) -> -36815.899 | AN21: =SUM(AN17:AN20) -> 0 | AS21: =SUM(AS17:AS20) -> 0 | AT21: =SUM(AT17:AT20) -> 0 | AU21: =SUM(AU17:AU20) -> 0 | AV21: =SUM(AV17:AV20) -> -36815.899 | AX21: =SUM(AX17:AX20) -> 0 | BC21: =SUM(BC17:BC20) -> 0 | BD21: =SUM(BD17:BD20) -> 0 | BE21: =SUM(BE17:BE20) -> 0 | BF21: =SUM(BF17:BF20) -> -36815.899 | BH21: =SUM(BH17:BH20) -> 0 | BM21: =SUM(BM17:BM20) -> 0 | BN21: =SUM(BN17:BN20) -> 0 | BO21: =SUM(BO17:BO20) -> 0 | BP21: =SUM(BP17:BP20) -> -36815.899 | BR21: =SUM(BR17:BR20) -> 0 | BW21: =SUM(BW17:BW20) -> 0 | BX21: =SUM(BX17:BX20) -> 0 | BY21: =SUM(BY17:BY20) -> 0 | BZ21: =SUM(BZ17:BZ20) -> -36815.899 | CB21: =SUM(CB17:CB20) -> 210117.59 | CC21: 52032.8 | CG21: =SUM(CG17:CG20) -> -23391.747 | CH21: =SUM(CH17:CH20) -> 0 | CI21: =SUM(CI17:CI20) -> 134693.04 | CJ21: =SUM(CJ17:CJ20) -> 97877.144 | CL21: =SUM(CL17:CL20) -> 168993.46 | CQ21: =SUM(CQ17:CQ20) -> -40886.53 | CR21: =SUM(CR17:CR20) -> 0 | CS21: =SUM(CS17:CS20) -> 128106.93 | CT21: =SUM(CT17:CT20) -> 225984.07 | CV21: =SUM(CV17:CV20) -> 171055.1 | CW21: 254338.6 | DA21: =SUM(DA17:DA20) -> -52420.62 | DB21: =SUM(DB17:DB20) -> 0 | DC21: =SUM(DC17:DC20) -> -135704.12 | DD21: =SUM(DD17:DD20) -> 0 | DE21: =SUM(DE17:DE20) -> 90279.95 | DF21: =SUM(DF17:DF20) -> 383 | DG21: =SUM(DG17:DG20) -> 197163.13 | DH21: =130000+37224.33 -> 167224.33 | DO21: =SUM(DO17:DO20) -> -48019.14 | DP21: =SUM(DP17:DP20) -> 0 | DQ21: =SUM(DQ17:DQ20) -> -18080.34 | DR21: =SUM(DR17:DR20) -> 0 | DS21: =SUM(DS17:DS20) -> 72199.61 | DT21: =SUM(DT17:DT20) -> 320 | DU21: =SUM(DU17:DU20) -> 173244.33 | EC21: =SUM(EC17:EC20) -> -39341.23 | ED21: =SUM(ED17:ED20) -> 0 | EE21: =SUM(EE17:EE20) -> 133903.1 | EF21: =SUM(EF17:EF20) -> 0 | EG21: =SUM(EG17:EG20) -> 206102.71 | EH21: =SUM(EH17:EH20) -> 105 | EI21: =SUM(EI17:EI20) -> 51962.4 | EJ21: 116473.23 | ER21: =SUM(ER17:ER20) -> -21678 | ES21: =SUM(ES17:ES20) -> 0 | ET21: =SUM(ET17:ET20) -> -86188.83 | EU21: =SUM(EU17:EU20) -> 0 | EV21: =SUM(EV17:EV20) -> 119913.88 | EW21: =SUM(EW17:EW20) -> 0 | EX21: =SUM(EX17:EX20) -> 0 | EY21: 95931.1 | FG21: =SUM(FG17:FG20) -> 0 | FH21: =SUM(FH17:FH20) -> 0 | FI21: =SUM(FI17:FI20) -> -95931.1 | FJ21: =SUM(FJ17:FJ20) -> 0 | FK21: =SUM(FK17:FK20) -> 23982.78 | FL21: =SUM(FL17:FL20) -> 0 | FM21: =SUM(FM17:FM20) -> 0 | FV21: =SUM(FV17:FV20) -> 0 | FW21: =SUM(FW17:FW20) -> 0 | FX21: =SUM(FX17:FX20) -> 0 | FY21: =SUM(FY17:FY20) -> 0 | FZ21: =SUM(FZ17:FZ20) -> 23982.78 | GA21: =SUM(GA17:GA20) -> 0 | GB21: =SUM(GB17:GB20) -> 0 | GL21: =SUM(GL17:GL20) -> 0 | GM21: =SUM(GM17:GM20) -> 0 | GN21: =SUM(GN17:GN20) -> 0 | GO21: =SUM(GO17:GO20) -> 0 | GP21: =SUM(GP17:GP20) -> 23982.78 | GQ21: =SUM(GQ17:GQ20) -> 0 | GR21: =SUM(GR17:GR20) -> 0 | HB21: =SUM(HB17:HB20) -> 0 | HC21: =SUM(HC17:HC20) -> 0 | HD21: =SUM(HD17:HD20) -> 0 | HE21: =SUM(HE17:HE20) -> 0 | HF21: =SUM(HF17:HF20) -> 23982.78 | HG21: =SUM(HG17:HG20) -> 0 | HH21: =SUM(HH17:HH20) -> 0 | HR21: =SUM(HR17:HR20) -> 0 | HS21: =SUM(HS17:HS20) -> 0 | HT21: =SUM(HT17:HT20) -> 0 | HU21: =SUM(HU17:HU20) -> 0 | HV21: =SUM(HV17:HV20) -> 23982.78 | HW21: =SUM(HW17:HW20) -> 0 | HX21: =SUM(HX17:HX20) -> 0 | IH21: =SUM(IH17:IH20) -> 0 | II21: =SUM(II17:II20) -> 0 | IJ21: =SUM(IJ17:IJ20) -> 0 | IK21: =SUM(IK17:IK20) -> 0 | IL21: =SUM(IL17:IL20) -> 23982.78 | IM21: =SUM(IM17:IM20) -> 0 | IN21: =SUM(IN17:IN20) -> 0 | IO21: =IO19 -> 23982.78 | IX21: =SUM(IX17:IX20) -> 0 | IY21: =SUM(IY17:IY20) -> 0 | IZ21: =SUM(IZ17:IZ20) -> -23982.78 | JA21: =SUM(JA17:JA20) -> 0 | JB21: =SUM(JB17:JB20) -> 0 | JC21: =SUM(JC17:JC20) -> 0 | JD21: =SUM(JD17:JD20) -> 0 | JE21: =JE19 -> 0 | JN21: =SUM(JN17:JN20) -> 0 | JO21: =SUM(JO17:JO20) -> 0 | JP21: =SUM(JP17:JP20) -> 0 | JQ21: =SUM(JQ17:JQ20) -> 0 | JR21: =SUM(JR17:JR20) -> 0 | JS21: =SUM(JS17:JS20) -> 0 | JT21: =SUM(JT17:JT20) -> 0 | JU21: =JU19 -> 0 | KD21: =SUM(KD17:KD20) -> 0 | KE21: =SUM(KE17:KE20) -> 0 | KF21: =SUM(KF17:KF20) -> 0 | KG21: =SUM(KG17:KG20) -> 0 | KH21: =SUM(KH17:KH20) -> 0 | KI21: =SUM(KI17:KI20) -> 0 | KJ21: =SUM(KJ17:KJ20) -> 0 | KK21: =KK19 -> 0 | KT21: =SUM(KT17:KT20) -> 0 | KU21: =SUM(KU17:KU20) -> 0 | KV21: =SUM(KV17:KV20) -> 0 | KW21: =SUM(KW17:KW20) -> 0 | KX21: =SUM(KX17:KX20) -> 0 | KY21: =SUM(KY17:KY20) -> 0 | KZ21: =SUM(KZ17:KZ20) -> 0 | LA21: =LA19 -> 0 | LJ21: =SUM(LJ17:LJ20) -> 0 | LK21: =SUM(LK17:LK20) -> 0 | LL21: =SUM(LL17:LL20) -> 0 | LM21: =SUM(LM17:LM20) -> 0 | LN21: =SUM(LN17:LN20) -> 0 | LO21: =SUM(LO17:LO20) -> 0 | LP21: =SUM(LP17:LP20) -> 0 | LQ21: =LQ19 -> 0 | LZ21: =SUM(LZ17:LZ20) -> 0 | MA21: =SUM(MA17:MA20) -> 0 | MB21: =SUM(MB17:MB20) -> 0 | MC21: =SUM(MC17:MC20) -> 0 | MD21: =SUM(MD17:MD20) -> 0 | ME21: =SUM(ME17:ME20) -> 0 | MF21: =SUM(MF17:MF20) -> 0 | MG21: =MG19 -> 0 | MP21: =SUM(MP17:MP20) -> 0 | MQ21: =SUM(MQ17:MQ20) -> 0 | MR21: =SUM(MR17:MR20) -> 0 | MS21: =SUM(MS17:MS20) -> 0 | MT21: =SUM(MT17:MT20) -> 0 | MU21: =SUM(MU17:MU20) -> 0 | MV21: =SUM(MV17:MV20) -> 0 | MW21: =MW19 -> 0 | NF21: =SUM(NF17:NF20) -> 0 | NG21: =SUM(NG17:NG20) -> 0 | NH21: =SUM(NH17:NH20) -> 0 | NI21: =SUM(NI17:NI20) -> 0 | NJ21: =SUM(NJ17:NJ20) -> 0 | NK21: =SUM(NK17:NK20) -> 0 | NL21: =SUM(NL17:NL20) -> 0 | NM21: =NM19 -> 0 | NV21: =SUM(NV17:NV20) -> 0 | NW21: =SUM(NW17:NW20) -> 0 | NX21: =SUM(NX17:NX20) -> 0 | NY21: =SUM(NY17:NY20) -> 0 | NZ21: =SUM(NZ17:NZ20) -> 0 | OA21: =SUM(OA17:OA20) -> 0 | OB21: =SUM(OB17:OB20) -> 0 | OC21: =OC19 -> 0 | OL21: =SUM(OL17:OL20) -> 0 | OM21: =SUM(OM17:OM20) -> 0 | ON21: =SUM(ON17:ON20) -> 0 | OO21: =SUM(OO17:OO20) -> 0 | OP21: =SUM(OP17:OP20) -> 0 | OQ21: =SUM(OQ17:OQ20) -> 0 | OR21: =SUM(OR17:OR20) -> 0 | OS21: =OS19 -> 0 | PB21: =SUM(PB17:PB20) -> 0 | PC21: =SUM(PC17:PC20) -> 0 | PD21: =SUM(PD17:PD20) -> 0 | PE21: =SUM(PE17:PE20) -> 0 | PF21: =SUM(PF17:PF20) -> 0 | PG21: =SUM(PG17:PG20) -> 0 | PH21: =SUM(PH17:PH20) -> 0 | PI21: =SUM(PI17:PI20) -> 0 | PJ21: =SUM(PJ17:PJ20) -> 0 | PL21: =PJ21 -> 0
